{
  "type": "Feature",
  "properties": {
    "iso:country":"US",
    "sg:address":"7565 9th Ave SE",
    "sg:city":"Linton",
    "sg:classifiers":[
        {
            "category":"Farming",
            "subcategory":"Livestock Farm",
            "type":"Manufacturing & Wholesale Goods"
        }
    ],
    "sg:phone":"+1 701 782 4256",
    "sg:postcode":"58552",
    "sg:province":"ND",
    "sg:tags":[
        "ranch"
    ],
    "wof:name":"Mc Culley Ranch",
    "wof:placetype":"venue"
},
  "geometry": {"coordinates":[-100.231939,46.334463],"type":"Point"}
}