{
  "type": "Feature",
  "properties": {
    "iso:country":"US",
    "sg:address":"3321 4th Ave S",
    "sg:city":"Fargo",
    "sg:classifiers":[
        {
            "category":"Wholesale",
            "subcategory":"Medical Equipment & Supplies",
            "type":"Manufacturing & Wholesale Goods"
        }
    ],
    "sg:phone":"+1 701 235 7387",
    "sg:postcode":"58103",
    "sg:province":"ND",
    "sg:tags":[
        "dental"
    ],
    "wof:name":"Patterson Dental 220",
    "wof:placetype":"venue"
},
  "geometry": {"coordinates":[-96.831981,46.871314],"type":"Point"}
}