{
  "type": "Feature",
  "properties": {
    "iso:country":"US",
    "sg:address":"9001 56th Ave N",
    "sg:city":"Harwood",
    "sg:classifiers":[
        {
            "category":"Professional",
            "subcategory":"Business Services",
            "type":"Services"
        }
    ],
    "sg:phone":"+1 701 282 0899",
    "sg:postcode":"58042",
    "sg:province":"ND",
    "wof:name":"Lnd Enterprise Inc",
    "wof:placetype":"venue"
},
  "geometry": {"coordinates":[-96.940735,46.955377],"type":"Point"}
}