{
  "type": "Feature",
  "properties": {
    "iso:country":"US",
    "sg:address":"5970 22nd St SW",
    "sg:city":"Beulah",
    "sg:phone":"+1 701 873 5221",
    "sg:postcode":"58523",
    "sg:province":"ND",
    "sg:tags":[
        "farm",
        "wheat"
    ],
    "wof:name":"Jack Schutt",
    "wof:placetype":"venue"
},
  "geometry": {"coordinates":[-101.759687,47.09691],"type":"Point"}
}