{
  "type": "Feature",
  "properties": {
    "iso:country":"US",
    "sg:address":"906 1st Ave S",
    "sg:city":"Fargo",
    "sg:classifiers":[
        {
            "category":"Place Of Worship",
            "subcategory":"Church",
            "type":"Public Place"
        },
        {
            "category":"Place Of Worship",
            "type":"Public Place"
        }
    ],
    "sg:phone":"+1 701 232 2450",
    "sg:postcode":"58103",
    "sg:province":"ND",
    "sg:tags":[
        "churches-methodist"
    ],
    "wof:name":"Friendship Church",
    "wof:placetype":"venue"
},
  "geometry": {"coordinates":[-96.792737,46.873607],"type":"Point"}
}