{
  "type": "Feature",
  "properties": {
    "addr:full":"7415 28th Ave NW Glenburn ND 58740",
    "addr:housenumber":"7415",
    "addr:postcode":"glenburn;58740",
    "addr:street":"28Th Ave Nw",
    "iso:country":"US",
    "sg:address":"7415 28th Ave NW",
    "sg:city":"Glenburn",
    "sg:phone":"+1 701 362 7980",
    "sg:postcode":"58740",
    "sg:province":"ND",
    "sg:tags":[
        "farm",
        "wheat"
    ],
    "wof:name":"Dennis and Ronald Hensen",
    "wof:placetype":"venue"
},
  "geometry": {"coordinates":[-101.320842,48.489439],"type":"Point"}
}