{
  "type": "Feature",
  "properties": {
    "iso:country":"US",
    "sg:address":"2842 Dakota Park Cir",
    "sg:city":"Fargo",
    "sg:classifiers":[
        {
            "category":"Professional",
            "subcategory":"Management & Consulting",
            "type":"Services"
        }
    ],
    "sg:phone":"+1 701 271 8680",
    "sg:postcode":"58104",
    "sg:province":"ND",
    "sg:tags":[
        "business"
    ],
    "wof:name":"Alliance Information MGT",
    "wof:placetype":"venue"
},
  "geometry": {"coordinates":[-96.82678,46.828791],"type":"Point"}
}