{
  "type": "Feature",
  "properties": {
    "addr:full":"1311 12th Ave NE Jamestown ND 58401",
    "addr:housenumber":"1311",
    "addr:postcode":"58401",
    "addr:street":"12Th Ave Ne",
    "iso:country":"US",
    "sg:address":"1311 12th Ave NE",
    "sg:city":"Jamestown",
    "sg:classifiers":[
        {
            "category":"Social Services",
            "type":"Services"
        }
    ],
    "sg:phone":"+1 701 252 1821",
    "sg:postcode":"58401",
    "sg:province":"ND",
    "sg:tags":[
        "organization",
        "welfare"
    ],
    "wof:name":"Community Action Program",
    "wof:placetype":"venue"
},
  "geometry": {"coordinates":[-98.691976,46.921632],"type":"Point"}
}