{
  "type": "Feature",
  "properties": {
    "addr:full":"8009 146th Ave SE Milnor ND 58060",
    "addr:housenumber":"8009",
    "addr:postcode":"58060",
    "addr:street":"146Th Ave Se",
    "iso:country":"US",
    "sg:address":"8009 146th Ave SE",
    "sg:city":"Milnor",
    "sg:classifiers":[
        {
            "category":"Farming",
            "subcategory":"Farm",
            "type":"Manufacturing & Wholesale Goods"
        }
    ],
    "sg:phone":"+1 701 427 5577",
    "sg:postcode":"58060",
    "sg:province":"ND",
    "wof:name":"Spike Brothers",
    "wof:placetype":"venue"
},
  "geometry": {"coordinates":[-97.321849,46.252005],"type":"Point"}
}