{
  "type": "Feature",
  "properties": {
    "iso:country":"US",
    "sg:address":"4 4th Ave N",
    "sg:city":"Carrington",
    "sg:classifiers":[
        {
            "category":"Autos & Motor Vehicles",
            "subcategory":"Auto Supplies",
            "type":"Retail Goods"
        },
        {
            "category":"Wholesale",
            "subcategory":"Auto Parts",
            "type":"Manufacturing & Wholesale Goods"
        }
    ],
    "sg:phone":"+1 701 652 3139",
    "sg:postcode":"58421",
    "sg:province":"ND",
    "sg:tags":[
        "automobile"
    ],
    "wof:name":"H E Everson Company",
    "wof:placetype":"venue"
},
  "geometry": {"coordinates":[-99.11730799999999,47.450039],"type":"Point"}
}