{
  "type": "Feature",
  "properties": {
    "iso:country":"US",
    "sg:address":"615 16th Ave N",
    "sg:city":"Fargo",
    "sg:classifiers":[
        {
            "category":"Building & Trades",
            "subcategory":"Cleaning & Sanitation",
            "type":"Services"
        }
    ],
    "sg:phone":"+1 701 866 7486",
    "sg:postcode":"58102",
    "sg:province":"ND",
    "sg:tags":[
        "window"
    ],
    "wof:name":"Skyview Window Cleaning",
    "wof:placetype":"venue"
},
  "geometry": {"coordinates":[-96.788195,46.899507],"type":"Point"}
}