{
  "type": "Feature",
  "properties": {
    "addr:full":"906 9th Ave NE Jamestown ND 58401",
    "addr:housenumber":"906",
    "addr:postcode":"58401",
    "addr:street":"9Th Ave Ne",
    "iso:country":"US",
    "sg:address":"906 9th Ave NE",
    "sg:city":"Jamestown",
    "sg:classifiers":[
        {
            "category":"Social Services",
            "subcategory":"Adult Care",
            "type":"Services"
        }
    ],
    "sg:phone":"+1 701 252 0735",
    "sg:postcode":"58401",
    "sg:province":"ND",
    "sg:tags":[
        "home",
        "group"
    ],
    "wof:name":"Alpha Opportunities Inc",
    "wof:placetype":"venue"
},
  "geometry": {"coordinates":[-98.696579,46.918092],"type":"Point"}
}