{
  "type": "Feature",
  "properties": {
    "iso:country":"US",
    "sg:address":"5046 10th Ave SW",
    "sg:city":"Fargo",
    "sg:classifiers":[
        {
            "category":"Building & Trades",
            "subcategory":"Construction",
            "type":"Services"
        }
    ],
    "sg:phone":"+1 701 492 0172",
    "sg:postcode":"58103",
    "sg:province":"ND",
    "sg:tags":[
        "house"
    ],
    "wof:name":"Scott Huset Construction",
    "wof:placetype":"venue"
},
  "geometry": {"coordinates":[-96.870169,46.866094],"type":"Point"}
}