{
  "type": "Feature",
  "properties": {
    "addr:full":"609 W Main St Mandan ND 58554",
    "addr:housenumber":"609",
    "addr:postcode":"58554",
    "addr:street":"W Main St",
    "iso:country":"US",
    "sg:address":"609 W Main St",
    "sg:city":"Mandan",
    "sg:classifiers":[
        {
            "category":"Building & Trades",
            "subcategory":"Plumbing",
            "type":"Services"
        }
    ],
    "sg:phone":"+1 701 663 9607",
    "sg:postcode":"58554",
    "sg:province":"ND",
    "sg:tags":[
        "conditioning",
        "air",
        "system",
        "contractor"
    ],
    "wof:name":"Thermo Cool Products",
    "wof:placetype":"venue"
},
  "geometry": {"coordinates":[-100.898543,46.825173],"type":"Point"}
}