{
  "type": "Feature",
  "properties": {
    "iso:country":"US",
    "sg:address":"516 Main St",
    "sg:city":"Edgeley",
    "sg:classifiers":[
        {
            "category":"Manufacturing",
            "subcategory":"Printing",
            "type":"Manufacturing & Wholesale Goods"
        }
    ],
    "sg:phone":"+1 701 493 2261",
    "sg:postcode":"58433",
    "sg:province":"ND",
    "sg:tags":[
        "newspaper"
    ],
    "wof:name":"Edgeley Mail",
    "wof:placetype":"venue"
},
  "geometry": {"coordinates":[-98.71140699999999,46.36075],"type":"Point"}
}