{
  "type": "Feature",
  "properties": {
    "iso:country":"US",
    "sg:address":"1716 29th St W",
    "sg:city":"Williston",
    "sg:classifiers":[
        {
            "category":"Social Services",
            "subcategory":"Child Care",
            "type":"Services"
        }
    ],
    "sg:phone":"+1 701 572 9728",
    "sg:postcode":"58801",
    "sg:province":"ND",
    "sg:tags":[
        "day"
    ],
    "wof:name":"Beards Family Day Care",
    "wof:placetype":"venue"
},
  "geometry": {"coordinates":[-103.650031,48.171157],"type":"Point"}
}