{
  "type": "Feature",
  "properties": {
    "addr:full":"17450 Co Rd 6 Wahpeton ND 58075",
    "addr:housenumber":"17450",
    "addr:postcode":"58075",
    "addr:street":"Co Rd 6",
    "iso:country":"US",
    "sg:address":"17450 Co Rd 6",
    "sg:city":"Wahpeton",
    "sg:classifiers":[
        {
            "category":"Organizations",
            "subcategory":"Membership Organization",
            "type":"Services"
        }
    ],
    "sg:phone":"+1 701 553 8799",
    "sg:postcode":"58075",
    "sg:province":"ND",
    "wof:name":"Sons of Norway",
    "wof:placetype":"venue"
},
  "geometry": {"coordinates":[-96.763837,46.427459],"type":"Point"}
}