{
  "type": "Feature",
  "properties": {
    "iso:country":"US",
    "sg:address":"5810 19th St NE",
    "sg:city":"New Rockford",
    "sg:classifiers":[
        {
            "category":"Professional",
            "subcategory":"Secretarial Services",
            "type":"Services"
        }
    ],
    "sg:phone":"+1 701 947 2568",
    "sg:postcode":"58356",
    "sg:province":"ND",
    "sg:tags":[
        "reporting"
    ],
    "wof:name":"Rhein Valley Publishing",
    "wof:placetype":"venue"
},
  "geometry": {"coordinates":[-99.34025099999999,47.688503],"type":"Point"}
}