{
  "type": "Feature",
  "properties": {
    "iso:country":"US",
    "sg:address":"3585 94th St SE",
    "sg:city":"Ashley",
    "sg:classifiers":[
        {
            "category":"Farming",
            "subcategory":"Farm",
            "type":"Manufacturing & Wholesale Goods"
        }
    ],
    "sg:phone":"+1 701 684 6231",
    "sg:postcode":"58413",
    "sg:province":"ND",
    "sg:tags":[
        "crop",
        "general"
    ],
    "wof:name":"Gideon Heupel",
    "wof:placetype":"venue"
},
  "geometry": {"coordinates":[-99.629295,46.057067],"type":"Point"}
}