{
  "type": "Feature",
  "properties": {
    "iso:country":"US",
    "sg:address":"202 5th Ave N",
    "sg:city":"Wahpeton",
    "sg:classifiers":[
        {
            "category":"Organizations",
            "subcategory":"Religious Organization",
            "type":"Services"
        }
    ],
    "sg:phone":"+1 701 642 1635",
    "sg:postcode":"58075",
    "sg:province":"ND",
    "wof:name":"LDS Missionaries",
    "wof:placetype":"venue"
},
  "geometry": {"coordinates":[-96.603044,46.268128],"type":"Point"}
}