{
  "type": "Feature",
  "properties": {
    "iso:country":"US",
    "sg:address":"4371 153rd Ave SE",
    "sg:city":"Mapleton",
    "sg:classifiers":[
        {
            "category":"Farming",
            "subcategory":"Dairy Farm",
            "type":"Manufacturing & Wholesale Goods"
        }
    ],
    "sg:phone":"+1 701 347 5318",
    "sg:postcode":"58059",
    "sg:province":"ND",
    "wof:name":"Jeffrey Cummer",
    "wof:placetype":"venue"
},
  "geometry": {"coordinates":[-97.263285,46.778791],"type":"Point"}
}