{
  "type": "Feature",
  "properties": {
    "iso:country":"US",
    "sg:address":"10875 State Hwy 28",
    "sg:city":"Sherwood",
    "sg:classifiers":[
        {
            "category":"Restaurant",
            "type":"Food & Drink"
        }
    ],
    "sg:phone":"+1 701 459 2792",
    "sg:postcode":"58782",
    "sg:province":"ND",
    "wof:name":"New Northern Lights",
    "wof:placetype":"venue"
},
  "geometry": {"coordinates":[-101.627945,48.991402],"type":"Point"}
}