{
  "type": "Feature",
  "properties": {
    "iso:country":"US",
    "sg:address":"320 2nd St SE",
    "sg:city":"Lamoure",
    "sg:classifiers":[
        {
            "category":"Social Services",
            "subcategory":"Adult Care",
            "type":"Services"
        }
    ],
    "sg:phone":"+1 701 883 5999",
    "sg:postcode":"58458",
    "sg:province":"ND",
    "sg:tags":[
        "home",
        "residential"
    ],
    "wof:name":"Rosewood Country Inc",
    "wof:placetype":"venue"
},
  "geometry": {"coordinates":[-98.291713,46.355058],"type":"Point"}
}