{
  "type": "Feature",
  "properties": {
    "addr:full":"2910 E Broadway Ave Bismarck ND 58501",
    "addr:housenumber":"2910",
    "addr:postcode":"58501",
    "addr:street":"E Broadway Ave",
    "iso:country":"US",
    "sg:address":"2910 E Broadway Ave",
    "sg:city":"Bismarck",
    "sg:classifiers":[
        {
            "category":"Personal",
            "type":"Services"
        }
    ],
    "sg:phone":"+1 701 391 8634",
    "sg:postcode":"58501",
    "sg:province":"ND",
    "sg:tags":[
        "therapist",
        "massage"
    ],
    "wof:name":"Michael's Therapeutic Massage",
    "wof:placetype":"venue"
},
  "geometry": {"coordinates":[-100.748262,46.806152],"type":"Point"}
}