{
  "type": "Feature",
  "properties": {
    "addr:full":"6185 58th Ave NE Leeds ND 58346",
    "addr:housenumber":"6185",
    "addr:postcode":"58346",
    "addr:street":"58Th Ave Ne",
    "iso:country":"US",
    "sg:address":"6185 58th Ave NE",
    "sg:city":"Leeds",
    "sg:phone":"+1 701 466 2990",
    "sg:postcode":"58346",
    "sg:province":"ND",
    "sg:tags":[
        "farm",
        "wheat"
    ],
    "wof:name":"Brian Engstrom",
    "wof:placetype":"venue"
},
  "geometry": {"coordinates":[-99.373138,48.30234],"type":"Point"}
}