{
  "type": "Feature",
  "properties": {
    "iso:country":"US",
    "sg:address":"16005 33rd St SE",
    "sg:city":"Casselton",
    "sg:phone":"+1 701 347 4482",
    "sg:postcode":"58012",
    "sg:province":"ND",
    "sg:tags":[
        "farm",
        "wheat",
        "soybean"
    ],
    "wof:name":"Roden Farms",
    "wof:placetype":"venue"
},
  "geometry": {"coordinates":[-97.11597999999999,46.934593],"type":"Point"}
}