{
  "type": "Feature",
  "properties": {
    "addr:full":"272 Chestnut Dr Horace ND 58047",
    "addr:housenumber":"272",
    "addr:postcode":"58047",
    "addr:street":"Chestnut Dr",
    "iso:country":"US",
    "sg:address":"272 Chestnut Dr",
    "sg:city":"Horace",
    "sg:classifiers":[
        {
            "category":"Shopping",
            "subcategory":"Computers & Home Electronics",
            "type":"Retail Goods"
        }
    ],
    "sg:phone":"+1 701 277 0313",
    "sg:postcode":"58047",
    "sg:province":"ND",
    "wof:name":"Custom Cinema & Sound",
    "wof:placetype":"venue"
},
  "geometry": {"coordinates":[-96.90504199999999,46.76565],"type":"Point"}
}