{
  "type": "Feature",
  "properties": {
    "iso:country":"US",
    "sg:address":"206 1st St NE",
    "sg:city":"Tioga",
    "sg:classifiers":[
        {
            "category":"Education",
            "subcategory":"School",
            "type":"Public Place"
        }
    ],
    "sg:phone":"+1 701 965 6313",
    "sg:postcode":"58852",
    "sg:province":"ND",
    "wof:name":"Divide County District Office",
    "wof:placetype":"venue"
},
  "geometry": {"coordinates":[-102.935676,48.395611],"type":"Point"}
}