{
  "type": "Feature",
  "properties": {
    "iso:country":"US",
    "sg:address":"802 2nd Ave W",
    "sg:city":"Lisbon",
    "sg:phone":"+1 701 683 5721",
    "sg:postcode":"58054",
    "sg:province":"ND",
    "sg:tags":[
        "farm",
        "wheat"
    ],
    "wof:name":"Brad Nims",
    "wof:placetype":"venue"
},
  "geometry": {"coordinates":[-97.692555,46.444544],"type":"Point"}
}