{
  "type": "Feature",
  "properties": {
    "iso:country":"US",
    "sg:address":"14358 State Hwy 13",
    "sg:city":"Milnor",
    "sg:phone":"+1 701 427 9467",
    "sg:postcode":"58060",
    "sg:province":"ND",
    "sg:tags":[
        "farm",
        "grain",
        "cash"
    ],
    "wof:name":"Harry Gainor",
    "wof:placetype":"venue"
},
  "geometry": {"coordinates":[-97.393131,46.253326],"type":"Point"}
}