{
  "type": "Feature",
  "properties": {
    "iso:country":"US",
    "sg:address":"200 3rd Ave SW",
    "sg:city":"Mandan",
    "sg:classifiers":[
        {
            "category":"Building & Trades",
            "subcategory":"Construction",
            "type":"Services"
        }
    ],
    "sg:phone":"+1 701 667 5774",
    "sg:postcode":"58554",
    "sg:province":"ND",
    "sg:tags":[
        "hanging",
        "contractor"
    ],
    "wof:name":"Walls By Walby",
    "wof:placetype":"venue"
},
  "geometry": {"coordinates":[-100.893698,46.821343],"type":"Point"}
}