{
  "type": "Feature",
  "properties": {
    "iso:country":"US",
    "sg:address":"1515 4th St N",
    "sg:city":"Fargo",
    "sg:classifiers":[
        {
            "category":"Building & Trades",
            "subcategory":"Construction",
            "type":"Services"
        }
    ],
    "sg:phone":"+1 701 298 7692",
    "sg:postcode":"58102",
    "sg:province":"ND",
    "sg:tags":[
        "general",
        "contractor"
    ],
    "wof:name":"S & S Custom Contracting",
    "wof:placetype":"venue"
},
  "geometry": {"coordinates":[-96.784423,46.899134],"type":"Point"}
}