{
  "type": "Feature",
  "properties": {
    "addr:full":"1440 18th St S Fargo ND 58103",
    "addr:housenumber":"1440",
    "addr:postcode":"58103",
    "addr:street":"18Th St S",
    "iso:country":"US",
    "sg:address":"1440 18th St S",
    "sg:city":"Fargo",
    "sg:classifiers":[
        {
            "category":"Building & Trades",
            "subcategory":"Construction",
            "type":"Services"
        }
    ],
    "sg:phone":"+1 701 232 6378",
    "sg:postcode":"58103",
    "sg:province":"ND",
    "sg:tags":[
        "hanging",
        "contractor"
    ],
    "wof:name":"Stock Decorating Inc",
    "wof:placetype":"venue"
},
  "geometry": {"coordinates":[-96.81027400000001,46.858849],"type":"Point"}
}