{
  "type": "Feature",
  "properties": {
    "iso:country":"US",
    "sg:address":"318 Ave A W",
    "sg:city":"Napoleon",
    "sg:classifiers":[
        {
            "category":"Building & Trades",
            "subcategory":"Construction",
            "type":"Services"
        }
    ],
    "sg:phone":"+1 701 754 2710",
    "sg:postcode":"58561",
    "sg:province":"ND",
    "sg:tags":[
        "house"
    ],
    "wof:name":"Hh Home Builders",
    "wof:placetype":"venue"
},
  "geometry": {"coordinates":[-99.772665,46.501519],"type":"Point"}
}