{
  "type": "Feature",
  "properties": {
    "iso:country":"US",
    "sg:address":"67 2nd Ln SW",
    "sg:city":"Hazen",
    "sg:classifiers":[
        {
            "category":"Building & Trades",
            "subcategory":"Construction",
            "type":"Services"
        }
    ],
    "sg:phone":"+1 701 487 3633",
    "sg:postcode":"58545",
    "sg:province":"ND",
    "sg:tags":[
        "hanging",
        "contractor"
    ],
    "wof:name":"McKnight Painting & Decorating",
    "wof:placetype":"venue"
},
  "geometry": {"coordinates":[-101.459255,47.509229],"type":"Point"}
}