{
  "type": "Feature",
  "properties": {
    "addr:full":"801 Main St Bottineau ND 58318",
    "addr:housenumber":"801",
    "addr:postcode":"58318",
    "addr:street":"Main St",
    "iso:country":"US",
    "sg:address":"801 Main St",
    "sg:city":"Bottineau",
    "sg:classifiers":[
        {
            "category":"Organizations",
            "subcategory":"Religious Organization",
            "type":"Services"
        }
    ],
    "sg:phone":"+1 701 228 2800",
    "sg:postcode":"58318",
    "sg:province":"ND",
    "sg:tags":[
        "church"
    ],
    "wof:name":"United Parish",
    "wof:placetype":"venue"
},
  "geometry": {"coordinates":[-100.445927,48.824224],"type":"Point"}
}