{
  "type": "Feature",
  "properties": {
    "iso:country":"US",
    "sg:address":"15142 29th St SE",
    "sg:city":"Amenia",
    "sg:classifiers":[
        {
            "category":"Farming",
            "subcategory":"Farm",
            "type":"Manufacturing & Wholesale Goods"
        }
    ],
    "sg:phone":"+1 701 347 4094",
    "sg:postcode":"58004",
    "sg:province":"ND",
    "sg:tags":[
        "primarily",
        "crop",
        "general"
    ],
    "wof:name":"Roland Priewe",
    "wof:placetype":"venue"
},
  "geometry": {"coordinates":[-97.284651,46.992205],"type":"Point"}
}