{
  "type": "Feature",
  "properties": {
    "iso:country":"US",
    "sg:address":"8586 Co Hwy 2",
    "sg:city":"Devils Lake",
    "sg:phone":"+1 701 662 2205",
    "sg:postcode":"58301",
    "sg:province":"ND",
    "sg:tags":[
        "wheat",
        "beef",
        "farm",
        "cash",
        "grain",
        "cattle",
        "feedlot"
    ],
    "wof:name":"Leonard Birkeland",
    "wof:placetype":"venue"
},
  "geometry": {"coordinates":[-98.768624,48.107829],"type":"Point"}
}