{
  "type": "Feature",
  "properties": {
    "iso:country":"US",
    "sg:address":"310 Eagle Ave",
    "sg:city":"Reynolds",
    "sg:classifiers":[
        {
            "category":"Farming",
            "subcategory":"Farm",
            "type":"Manufacturing & Wholesale Goods"
        }
    ],
    "sg:phone":"+1 701 847 2790",
    "sg:postcode":"58275",
    "sg:province":"ND",
    "sg:tags":[
        "crop",
        "general"
    ],
    "wof:name":"Sondreal Farms Inc",
    "wof:placetype":"venue"
},
  "geometry": {"coordinates":[-96.89941899999999,47.672179],"type":"Point"}
}