{
  "type": "Feature",
  "properties": {
    "iso:country":"US",
    "sg:address":"10 Morrison St W",
    "sg:city":"West Fargo",
    "sg:classifiers":[
        {
            "category":"Wholesale",
            "subcategory":"Machinery & Supplies",
            "type":"Manufacturing & Wholesale Goods"
        }
    ],
    "sg:phone":"+1 701 281 8056",
    "sg:postcode":"58078",
    "sg:province":"ND",
    "sg:tags":[
        "equipment",
        "industrial"
    ],
    "wof:name":"Northern Plains Coins",
    "wof:placetype":"venue"
},
  "geometry": {"coordinates":[-96.90555000000001,46.876401],"type":"Point"}
}