{
  "type": "Feature",
  "properties": {
    "iso:country":"US",
    "sg:address":"206 N 1st St",
    "sg:city":"Bismarck",
    "sg:classifiers":[
        {
            "category":"Manufacturing",
            "subcategory":"Printing",
            "type":"Manufacturing & Wholesale Goods"
        }
    ],
    "sg:phone":"+1 701 222 2004",
    "sg:postcode":"58501",
    "sg:province":"ND",
    "sg:tags":[
        "commercial",
        "lithographic"
    ],
    "wof:name":"Printing Plus Inc",
    "wof:placetype":"venue"
},
  "geometry": {"coordinates":[-100.790763,46.807526],"type":"Point"}
}