{
  "type": "Feature",
  "properties": {
    "iso:country":"US",
    "sg:address":"2821 Marina Rd SE",
    "sg:city":"Mandan",
    "sg:classifiers":[
        {
            "category":"Real Estate",
            "subcategory":"Real Estate Operator",
            "type":"Services"
        }
    ],
    "sg:phone":"+1 701 663 2300",
    "sg:postcode":"58554",
    "sg:province":"ND",
    "sg:tags":[
        "apartment"
    ],
    "wof:name":"Riverplace Apartments",
    "wof:placetype":"venue"
},
  "geometry": {"coordinates":[-100.823161,46.800583],"type":"Point"}
}