{
  "type": "Feature",
  "properties": {
    "iso:country":"US",
    "sg:address":"515 6th St NE",
    "sg:city":"Belfield",
    "sg:classifiers":[
        {
            "category":"Organizations",
            "subcategory":"Professional Association",
            "type":"Services"
        }
    ],
    "sg:phone":"+1 701 575 8135",
    "sg:postcode":"58622",
    "sg:province":"ND",
    "sg:tags":[
        "chambers",
        "commerce"
    ],
    "wof:name":"Belfield Area Chamber-Commerce",
    "wof:placetype":"venue"
},
  "geometry": {"coordinates":[-103.191284,46.889549],"type":"Point"}
}