{
  "type": "Feature",
  "properties": {
    "addr:full":"250 7th St NW West Fargo ND 58078",
    "addr:housenumber":"250",
    "addr:postcode":"58078",
    "addr:street":"7Th St Nw",
    "iso:country":"US",
    "sg:address":"250 7th St NW",
    "sg:city":"West Fargo",
    "sg:classifiers":[
        {
            "category":"Wholesale",
            "subcategory":"Farm Supplies",
            "type":"Manufacturing & Wholesale Goods"
        }
    ],
    "sg:phone":"+1 701 282 1600",
    "sg:postcode":"58078",
    "sg:province":"ND",
    "sg:tags":[
        "fertilizer"
    ],
    "sg:website":"www.cargill.com",
    "wof:name":"Cargill Inc",
    "wof:placetype":"venue"
},
  "geometry": {"coordinates":[-96.910821,46.88057],"type":"Point"}
}