{
  "type": "Feature",
  "properties": {
    "iso:country":"US",
    "sg:address":"1010 5th Ave S",
    "sg:city":"Devils Lake",
    "sg:classifiers":[
        {
            "category":"Building & Trades",
            "subcategory":"Construction",
            "type":"Services"
        }
    ],
    "sg:phone":"+1 701 665 3322",
    "sg:postcode":"58301",
    "sg:province":"ND",
    "sg:tags":[
        "dry wall",
        "contractor"
    ],
    "wof:name":"Bear Drywall",
    "wof:placetype":"venue"
},
  "geometry": {"coordinates":[-98.858988,48.099841],"type":"Point"}
}