{
  "type": "Feature",
  "properties": {
    "iso:country":"US",
    "sg:address":"15166 State Hwy 17",
    "sg:city":"Grafton",
    "sg:classifiers":[
        {
            "category":"Autos & Motor Vehicles",
            "subcategory":"Automobile Sales",
            "type":"Retail Goods"
        }
    ],
    "sg:phone":"+1 701 352 2264",
    "sg:postcode":"58237",
    "sg:province":"ND",
    "sg:tags":[
        "aircraft"
    ],
    "wof:name":"Agro Aviation",
    "wof:placetype":"venue"
},
  "geometry": {"coordinates":[-97.37166499999999,48.412436],"type":"Point"}
}