{
  "type": "Feature",
  "properties": {
    "iso:country":"US",
    "sg:address":"805 State Hwy 59",
    "sg:city":"Pembina",
    "sg:classifiers":[
        {
            "category":"Museum",
            "type":"Entertainment"
        }
    ],
    "sg:phone":"+1 701 825 6840",
    "sg:postcode":"58271",
    "sg:province":"ND",
    "wof:name":"Camp Kimball Historic Site",
    "wof:placetype":"venue"
},
  "geometry": {"coordinates":[-97.253742,48.972963],"type":"Point"}
}