{
  "type": "Feature",
  "properties": {
    "addr:full":"449 W Main St Valley City ND 58072",
    "addr:housenumber":"449",
    "addr:postcode":"58072",
    "addr:street":"W Main St",
    "iso:country":"US",
    "sg:address":"449 W Main St",
    "sg:city":"Valley City",
    "sg:classifiers":[
        {
            "category":"Retail",
            "subcategory":"Portrait Studio",
            "type":"Services"
        }
    ],
    "sg:phone":"+1 701 845 2581",
    "sg:postcode":"58072",
    "sg:province":"ND",
    "sg:tags":[
        "photographer",
        "photo"
    ],
    "wof:name":"Matson's Studio",
    "wof:placetype":"venue"
},
  "geometry": {"coordinates":[-98.00811299999999,46.92316],"type":"Point"}
}