{
  "type": "Feature",
  "properties": {
    "addr:full":"823 S 11th St Grand Forks ND 58201",
    "addr:housenumber":"823",
    "addr:postcode":"58201",
    "addr:street":"S 11Th St",
    "iso:country":"US",
    "sg:address":"823 S 11th St",
    "sg:city":"Grand Forks",
    "sg:classifiers":[
        {
            "category":"Organizations",
            "subcategory":"Religious Organization",
            "type":"Services"
        }
    ],
    "sg:phone":"+1 701 775 8857",
    "sg:postcode":"58201",
    "sg:province":"ND",
    "sg:tags":[
        "clergy"
    ],
    "wof:name":"Michael Fennell",
    "wof:placetype":"venue"
},
  "geometry": {"coordinates":[-97.041827,47.913247],"type":"Point"}
}