{
  "type": "Feature",
  "properties": {
    "iso:country":"US",
    "sg:address":"9973 53rd St NE",
    "sg:city":"Crary",
    "sg:phone":"+1 701 398 3415",
    "sg:postcode":"58327",
    "sg:province":"ND",
    "sg:tags":[
        "farm",
        "soybean"
    ],
    "wof:name":"Robert Kangas",
    "wof:placetype":"venue"
},
  "geometry": {"coordinates":[-98.471369,48.180323],"type":"Point"}
}