{
  "type": "Feature",
  "properties": {
    "addr:full":"3874 49th Ave SE Medina ND 58467",
    "addr:housenumber":"3874",
    "addr:postcode":"58467",
    "addr:street":"49Th Ave Se",
    "iso:country":"US",
    "sg:address":"3874 49th Ave SE",
    "sg:city":"Medina",
    "sg:classifiers":[
        {
            "category":"Farming",
            "subcategory":"Farm & Veterinary Services",
            "type":"Manufacturing & Wholesale Goods"
        }
    ],
    "sg:phone":"+1 701 486 3456",
    "sg:postcode":"58467",
    "sg:province":"ND",
    "sg:tags":[
        "hay",
        "grinding"
    ],
    "wof:name":"Brian Kleven Custom Haygrind",
    "wof:placetype":"venue"
},
  "geometry": {"coordinates":[-99.426349,46.852569],"type":"Point"}
}