{
  "type": "Feature",
  "properties": {
    "addr:full":"200 3rd St N Fargo ND 58102",
    "addr:housenumber":"200",
    "addr:postcode":"58102",
    "addr:street":"3Rd St N",
    "iso:country":"US",
    "sg:address":"200 3rd St N",
    "sg:city":"Fargo",
    "sg:classifiers":[
        {
            "category":"Utilities",
            "subcategory":"Water",
            "type":"Services"
        }
    ],
    "sg:phone":"+1 701 241 1324",
    "sg:postcode":"58102",
    "sg:province":"ND",
    "sg:tags":[
        "company",
        "sewage"
    ],
    "wof:name":"Fargo City Water Billing",
    "wof:placetype":"venue"
},
  "geometry": {"coordinates":[-96.783193,46.877979],"type":"Point"}
}