{
  "type": "Feature",
  "properties": {
    "iso:country":"US",
    "sg:address":"2750 Gateway Dr",
    "sg:city":"Grand Forks",
    "sg:classifiers":[
        {
            "category":"Personal",
            "subcategory":"Tanning Parlor",
            "type":"Services"
        },
        {
            "category":"Personal",
            "type":"Services"
        }
    ],
    "sg:phone":"+1 701 787 0200",
    "sg:postcode":"58203",
    "sg:province":"ND",
    "sg:tags":[
        "salon"
    ],
    "wof:name":"Tropics Tanning Salon",
    "wof:placetype":"venue"
},
  "geometry": {"coordinates":[-97.070026,47.933113],"type":"Point"}
}