{
  "type": "Feature",
  "properties": {
    "addr:full":"18123 Co Rd 10 Wahpeton ND 58075",
    "addr:housenumber":"18123;10",
    "addr:postcode":"58075",
    "addr:street":"Co Rd",
    "iso:country":"US",
    "sg:address":"18123 Co Rd 10",
    "sg:city":"Wahpeton",
    "sg:classifiers":[
        {
            "category":"Freight",
            "type":"Transportation"
        },
        {
            "category":"Professional",
            "type":"Services"
        }
    ],
    "sg:phone":"+1 701 642 8552",
    "sg:postcode":"58075",
    "sg:province":"ND",
    "sg:tags":[
        "truck",
        "driver",
        "lease"
    ],
    "wof:name":"American Driver Service Inc",
    "wof:placetype":"venue"
},
  "geometry": {"coordinates":[-96.63155500000001,46.28249],"type":"Point"}
}