{
  "type": "Feature",
  "properties": {
    "addr:full":"138 6th Ave W Sherwood ND 58782",
    "addr:housenumber":"138",
    "addr:postcode":"58782",
    "addr:street":"6Th Ave W",
    "iso:country":"US",
    "sg:address":"138 6th Ave W",
    "sg:city":"Sherwood",
    "sg:classifiers":[
        {
            "category":"Farming",
            "subcategory":"Farm",
            "type":"Manufacturing & Wholesale Goods"
        }
    ],
    "sg:phone":"+1 701 459 2283",
    "sg:postcode":"58782",
    "sg:province":"ND",
    "sg:tags":[
        "crop",
        "general"
    ],
    "wof:name":"Ron Volk",
    "wof:placetype":"venue"
},
  "geometry": {"coordinates":[-101.63437399999999,48.96417],"type":"Point"}
}