{
  "type": "Feature",
  "properties": {
    "addr:full":"108 N 3rd St Grand Forks ND 58203",
    "addr:housenumber":"108",
    "addr:postcode":"58203",
    "addr:street":"N 3Rd St",
    "iso:country":"US",
    "sg:address":"108 N 3rd St",
    "sg:city":"Grand Forks",
    "sg:classifiers":[
        {
            "category":"Restaurant",
            "type":"Food & Drink"
        }
    ],
    "sg:phone":"+1 701 775 7789",
    "sg:postcode":"58203",
    "sg:province":"ND",
    "wof:name":"Third Street Cafe",
    "wof:placetype":"venue"
},
  "geometry": {"coordinates":[-97.03277199999999,47.9266],"type":"Point"}
}