{
  "type": "Feature",
  "properties": {
    "iso:country":"US",
    "sg:address":"1029 Arthur St",
    "sg:city":"Stanton",
    "sg:classifiers":[
        {
            "category":"Government",
            "subcategory":"Office",
            "type":"Public Place"
        }
    ],
    "sg:phone":"+1 701 745 3392",
    "sg:postcode":"58571",
    "sg:province":"ND",
    "wof:name":"Mercer County Veterans Svc",
    "wof:placetype":"venue"
},
  "geometry": {"coordinates":[-101.380022,47.324174],"type":"Point"}
}