{
  "type": "Feature",
  "properties": {
    "addr:full":"5880 Rockhaven Harbor Rd N Mandan ND 58554",
    "addr:housenumber":"5880",
    "addr:postcode":"58554",
    "addr:street":"Rockhaven Harbor Rd N",
    "iso:country":"US",
    "sg:address":"5880 Rockhaven Harbor Rd N",
    "sg:city":"Mandan",
    "sg:classifiers":[
        {
            "category":"Building & Trades",
            "subcategory":"Construction",
            "type":"Services"
        }
    ],
    "sg:phone":"+1 701 663 3029",
    "sg:postcode":"58554",
    "sg:province":"ND",
    "sg:tags":[
        "acoustical",
        "contractor"
    ],
    "wof:name":"Orr Acoustics",
    "wof:placetype":"venue"
},
  "geometry": {"coordinates":[-100.892067,46.87693],"type":"Point"}
}