{
  "type": "Feature",
  "properties": {
    "addr:full":"963 Main St Carrington ND 58421",
    "addr:housenumber":"963",
    "addr:postcode":"58421",
    "addr:street":"Main St",
    "iso:country":"US",
    "sg:address":"963 Main St",
    "sg:city":"Carrington",
    "sg:classifiers":[
        {
            "category":"Personal",
            "subcategory":"Beauty Salon",
            "type":"Services"
        }
    ],
    "sg:phone":"+1 701 652 1416",
    "sg:postcode":"58421",
    "sg:province":"ND",
    "sg:tags":[
        "shop"
    ],
    "wof:name":"All That Jazz",
    "wof:placetype":"venue"
},
  "geometry": {"coordinates":[-99.12567900000001,47.44962],"type":"Point"}
}