{
  "type": "Feature",
  "properties": {
    "addr:full":"120 4th St N Wahpeton ND 58075",
    "addr:housenumber":"120",
    "addr:postcode":"58075",
    "addr:street":"4Th St N",
    "iso:country":"US",
    "sg:address":"120 4th St N",
    "sg:city":"Wahpeton",
    "sg:classifiers":[
        {
            "category":"Government",
            "subcategory":"Office",
            "type":"Public Place"
        }
    ],
    "sg:phone":"+1 701 642 9800",
    "sg:postcode":"58075",
    "sg:province":"ND",
    "sg:tags":[
        "village"
    ],
    "wof:name":"Wahpeton AWOS",
    "wof:placetype":"venue"
},
  "geometry": {"coordinates":[-96.605412,46.264269],"type":"Point"}
}