{
  "type": "Feature",
  "properties": {
    "addr:full":"4610 Amber Valley Pkwy S Fargo ND 58104",
    "addr:housenumber":"4610",
    "addr:postcode":"58104",
    "addr:street":"Amber Valley Pkwy S",
    "iso:country":"US",
    "sg:address":"4610 Amber Valley Pkwy S",
    "sg:city":"Fargo",
    "sg:classifiers":[
        {
            "category":"Professional",
            "subcategory":"Lawyer & Legal Services",
            "type":"Services"
        }
    ],
    "sg:phone":"+1 701 492 8880",
    "sg:postcode":"58104",
    "sg:province":"ND",
    "sg:tags":[
        "attorney"
    ],
    "wof:name":"Ellison Law Office",
    "wof:placetype":"venue"
},
  "geometry": {"coordinates":[-96.863697,46.842026],"type":"Point"}
}