{
  "type": "Feature",
  "properties": {
    "iso:country":"US",
    "sg:address":"4243 19th Ave SW",
    "sg:city":"Fargo",
    "sg:classifiers":[
        {
            "category":"Social Services",
            "type":"Services"
        }
    ],
    "sg:phone":"+1 701 277 4831",
    "sg:postcode":"58103",
    "sg:province":"ND",
    "sg:tags":[
        "community"
    ],
    "sg:website":"www.fmymca.org",
    "wof:name":"YMCA",
    "wof:placetype":"venue"
},
  "geometry": {"coordinates":[-96.85221799999999,46.849881],"type":"Point"}
}