{
  "type": "Feature",
  "properties": {
    "iso:country":"US",
    "sg:address":"114 B St NE",
    "sg:city":"Sykeston",
    "sg:classifiers":[
        {
            "category":"Education",
            "subcategory":"School",
            "type":"Public Place"
        }
    ],
    "sg:phone":"+1 701 984 2377",
    "sg:postcode":"58486",
    "sg:province":"ND",
    "wof:name":"Sykeston High School",
    "wof:placetype":"venue"
},
  "geometry": {"coordinates":[-99.398145,47.466264],"type":"Point"}
}