{
  "type": "Feature",
  "properties": {
    "addr:full":"1681 3rd Ave W Dickinson ND 58601",
    "addr:housenumber":"1681",
    "addr:postcode":"58601",
    "addr:street":"3Rd Ave W",
    "iso:country":"US",
    "sg:address":"1681 3rd Ave W",
    "sg:city":"Dickinson",
    "sg:classifiers":[
        {
            "category":"Restaurant",
            "type":"Food & Drink"
        }
    ],
    "sg:menulink":"http://www.allmenus.com/nd/dickinson/233437-pretzel-maker/menu/",
    "sg:phone":"+1 701 483 3455",
    "sg:postcode":"58601",
    "sg:province":"ND",
    "sg:tags":[
        "new",
        "american"
    ],
    "wof:name":"Pretzel Maker",
    "wof:placetype":"venue"
},
  "geometry": {"coordinates":[-102.78976400000001,46.90106],"type":"Point"}
}