{
  "type": "Feature",
  "properties": {
    "iso:country":"US",
    "sg:address":"603 Main Ave",
    "sg:city":"Hebron",
    "sg:classifiers":[
        {
            "category":"Food & Beverages",
            "subcategory":"Groceries & Convenience Stores",
            "type":"Retail Goods"
        }
    ],
    "sg:phone":"+1 701 878 4456",
    "sg:postcode":"58638",
    "sg:province":"ND",
    "sg:tags":[
        "grocer"
    ],
    "wof:name":"Lapp's Jack & Jill",
    "wof:placetype":"venue"
},
  "geometry": {"coordinates":[-102.045225,46.900813],"type":"Point"}
}