{
  "type": "Feature",
  "properties": {
    "iso:country":"US",
    "sg:address":"428 Cedar Cir",
    "sg:city":"Harwood",
    "sg:classifiers":[
        {
            "category":"Personal",
            "subcategory":"Beauty Salon",
            "type":"Services"
        }
    ],
    "sg:phone":"+1 701 281 9264",
    "sg:postcode":"58042",
    "sg:province":"ND",
    "sg:tags":[
        "shop",
        "care",
        "day",
        "child"
    ],
    "wof:name":"Jo's Hair & Nail Design",
    "wof:placetype":"venue"
},
  "geometry": {"coordinates":[-96.890495,46.98377],"type":"Point"}
}