{
  "type": "Feature",
  "properties": {
    "addr:full":"234 W Broadway Ave Bismarck ND 58501",
    "addr:housenumber":"234",
    "addr:postcode":"58501",
    "addr:street":"W Broadway Ave",
    "iso:country":"US",
    "sg:address":"234 W Broadway Ave",
    "sg:city":"Bismarck",
    "sg:classifiers":[
        {
            "category":"Shopping",
            "subcategory":"Hobbies, Toys, & Games",
            "type":"Retail Goods"
        }
    ],
    "sg:phone":"+1 701 222 2680",
    "sg:postcode":"58501",
    "sg:province":"ND",
    "wof:name":"Ceramic Shoppe",
    "wof:placetype":"venue"
},
  "geometry": {"coordinates":[-100.79383900000001,46.806645],"type":"Point"}
}