{
  "type": "Feature",
  "properties": {
    "addr:full":"810 N Washington St Grand Forks ND 58203",
    "addr:housenumber":"810",
    "addr:postcode":"58203",
    "addr:street":"N Washington St",
    "iso:country":"US",
    "sg:address":"810 N Washington St",
    "sg:city":"Grand Forks",
    "sg:classifiers":[
        {
            "category":"Restaurant",
            "type":"Food & Drink"
        }
    ],
    "sg:menulink":"http://www.allmenus.com/nd/grand-forks/23576-italian-moon/menu/",
    "sg:phone":"+1 701 772 7277",
    "sg:postcode":"58203",
    "sg:province":"ND",
    "sg:tags":[
        "italian"
    ],
    "wof:name":"Italian Moon",
    "wof:placetype":"venue"
},
  "geometry": {"coordinates":[-97.04497499999999,47.927544],"type":"Point"}
}