{
  "type": "Feature",
  "properties": {
    "iso:country":"US",
    "sg:address":"8500 106th St SE",
    "sg:city":"Bismarck",
    "sg:classifiers":[
        {
            "category":"Professional",
            "subcategory":"Management & Consulting",
            "type":"Services"
        }
    ],
    "sg:phone":"+1 701 400 6875",
    "sg:postcode":"58504",
    "sg:province":"ND",
    "sg:tags":[
        "consultant",
        "health"
    ],
    "wof:name":"Finn  John",
    "wof:placetype":"venue"
},
  "geometry": {"coordinates":[-100.626991,46.712206],"type":"Point"}
}