{
  "type": "Feature",
  "properties": {
    "iso:country":"US",
    "sg:address":"322 Main St",
    "sg:city":"Williston",
    "sg:classifiers":[
        {
            "category":"Banks & Credit Unions",
            "subcategory":"Investment Brokerage",
            "type":"Services"
        }
    ],
    "sg:phone":"+1 701 774 3423",
    "sg:postcode":"58801",
    "sg:province":"ND",
    "sg:tags":[
        "land",
        "oil",
        "lease"
    ],
    "wof:name":"Dublin Co",
    "wof:placetype":"venue"
},
  "geometry": {"coordinates":[-103.62176700000001,48.146779],"type":"Point"}
}