{
  "type": "Feature",
  "properties": {
    "addr:full":"118 11th St W Bottineau ND 58318",
    "addr:housenumber":"118",
    "addr:postcode":"58318",
    "addr:street":"11Th St W Bottineau",
    "iso:country":"US",
    "sg:address":"118 11th St W",
    "sg:city":"Bottineau",
    "sg:classifiers":[
        {
            "category":"Food & Beverages",
            "subcategory":"Specialty",
            "type":"Retail Goods"
        }
    ],
    "sg:phone":"+1 701 228 6014",
    "sg:postcode":"58318",
    "sg:province":"ND",
    "sg:tags":[
        "water",
        "bulk",
        "company"
    ],
    "wof:name":"Take 5 Water Store",
    "wof:placetype":"venue"
},
  "geometry": {"coordinates":[-100.447333,48.820778],"type":"Point"}
}