{
  "type": "Feature",
  "properties": {
    "iso:country":"US",
    "sg:address":"615 4th St",
    "sg:city":"Edgeley",
    "sg:phone":"+1 701 493 2374",
    "sg:postcode":"58433",
    "sg:province":"ND",
    "sg:tags":[
        "fuel",
        "diesel"
    ],
    "wof:name":"Double J Oil Co",
    "wof:placetype":"venue"
},
  "geometry": {"coordinates":[-98.71435099999999,46.361282],"type":"Point"}
}