{
  "type": "Feature",
  "properties": {
    "addr:full":"146 1st Ave E Dickinson ND 58601",
    "addr:housenumber":"146",
    "addr:postcode":"58601",
    "addr:street":"1St Ave E",
    "iso:country":"US",
    "sg:address":"146 1st Ave E",
    "sg:city":"Dickinson",
    "sg:classifiers":[
        {
            "category":"Shopping",
            "subcategory":"Gifts & Souvenirs",
            "type":"Retail Goods"
        }
    ],
    "sg:phone":"+1 701 483 1000",
    "sg:postcode":"58601",
    "sg:province":"ND",
    "sg:tags":[
        "shop"
    ],
    "wof:name":"Sister's Gifts & Antiques",
    "wof:placetype":"venue"
},
  "geometry": {"coordinates":[-102.783794,46.880199],"type":"Point"}
}