{
  "type": "Feature",
  "properties": {
    "iso:country":"US",
    "sg:address":"325 Co Rd 34",
    "sg:city":"Arthur",
    "sg:classifiers":[
        {
            "category":"Retail",
            "subcategory":"Auto Repair",
            "type":"Services"
        }
    ],
    "sg:phone":"+1 701 967 8333",
    "sg:postcode":"58006",
    "sg:province":"ND",
    "sg:tags":[
        "repairing",
        "automobile"
    ],
    "wof:name":"Lako Drilling",
    "wof:placetype":"venue"
},
  "geometry": {"coordinates":[-97.212017,47.10794],"type":"Point"}
}