{
  "type": "Feature",
  "properties": {
    "addr:full":"587 Eielson St Grand Forks Afb ND 58240",
    "addr:housenumber":"587",
    "addr:postcode":"58240",
    "addr:street":"Eielson St",
    "iso:country":"US",
    "sg:address":"587 Eielson St",
    "sg:city":"Grand Forks Afb",
    "sg:classifiers":[
        {
            "category":"Government",
            "subcategory":"Office",
            "type":"Public Place"
        }
    ],
    "sg:phone":"+1 701 594 5016",
    "sg:postcode":"58240",
    "sg:province":"ND",
    "sg:tags":[
        "federal"
    ],
    "wof:name":"US Army Corps Of Engineers",
    "wof:placetype":"venue"
},
  "geometry": {"coordinates":[-97.45774299999999,47.636924],"type":"Point"}
}