{
  "type": "Feature",
  "properties": {
    "iso:country":"US",
    "sg:address":"15750 Hwy 46",
    "sg:city":"Kindred",
    "sg:classifiers":[
        {
            "category":"Farming",
            "subcategory":"Livestock Farm",
            "type":"Manufacturing & Wholesale Goods"
        }
    ],
    "sg:phone":"+1 701 428 3000",
    "sg:postcode":"58051",
    "sg:province":"ND",
    "sg:tags":[
        "specialty",
        "animal"
    ],
    "wof:name":"Sperry Apiaries",
    "wof:placetype":"venue"
},
  "geometry": {"coordinates":[-97.12157999999999,46.629595],"type":"Point"}
}