{
  "type": "Feature",
  "properties": {
    "iso:country":"US",
    "sg:address":"1929 N Washington St",
    "sg:city":"Bismarck",
    "sg:classifiers":[
        {
            "category":"Shopping",
            "type":"Retail Goods"
        }
    ],
    "sg:phone":"+1 701 323 8460",
    "sg:postcode":"58501",
    "sg:province":"ND",
    "sg:tags":[
        "hearing",
        "equipment",
        "supply",
        "impaired"
    ],
    "wof:name":"Hearing Centers/Med Ctr One",
    "wof:placetype":"venue"
},
  "geometry": {"coordinates":[-100.794,46.827171],"type":"Point"}
}