{
  "type": "Feature",
  "properties": {
    "iso:country":"US",
    "sg:address":"6664 59th Ave SE",
    "sg:city":"Fredonia",
    "sg:classifiers":[
        {
            "category":"Professional",
            "subcategory":"Business Services",
            "type":"Services"
        }
    ],
    "sg:phone":"+1 701 485 3456",
    "sg:postcode":"58440",
    "sg:province":"ND",
    "sg:tags":[
        "development",
        "wind",
        "power"
    ],
    "wof:name":"Dakota I",
    "wof:placetype":"venue"
},
  "geometry": {"coordinates":[-99.18405,46.447702],"type":"Point"}
}