{
  "type": "Feature",
  "properties": {
    "iso:country":"US",
    "sg:address":"109 7th St W",
    "sg:city":"Dickinson",
    "sg:classifiers":[
        {
            "category":"Health Services",
            "subcategory":"Doctor",
            "type":"Services"
        }
    ],
    "sg:phone":"+1 701 483 2973",
    "sg:postcode":"58601",
    "sg:province":"ND",
    "sg:tags":[
        "physician",
        "surgeon"
    ],
    "wof:name":"Dakota Bone & Joint",
    "wof:placetype":"venue"
},
  "geometry": {"coordinates":[-102.78606499999999,46.885835],"type":"Point"}
}