{
  "type": "Feature",
  "properties": {
    "iso:country":"US",
    "sg:address":"15325 95th St SE",
    "sg:city":"Lidgerwood",
    "sg:classifiers":[
        {
            "category":"Farming",
            "subcategory":"Livestock Farm",
            "type":"Manufacturing & Wholesale Goods"
        }
    ],
    "sg:phone":"+1 701 538 7795",
    "sg:postcode":"58053",
    "sg:province":"ND",
    "sg:tags":[
        "wheat",
        "soybean"
    ],
    "wof:name":"Mike Forster",
    "wof:placetype":"venue"
},
  "geometry": {"coordinates":[-97.19334499999999,46.035681],"type":"Point"}
}