{
  "type": "Feature",
  "properties": {
    "addr:full":"1329 3rd Ave N Fargo ND 58102",
    "addr:housenumber":"1329",
    "addr:postcode":"58102",
    "addr:street":"3Rd Ave N",
    "iso:country":"US",
    "sg:address":"1329 3rd Ave N",
    "sg:city":"Fargo",
    "sg:classifiers":[
        {
            "category":"Building & Trades",
            "subcategory":"Construction",
            "type":"Services"
        }
    ],
    "sg:phone":"+1 701 280 1812",
    "sg:postcode":"58102",
    "sg:province":"ND",
    "sg:tags":[
        "system",
        "specialty",
        "heating",
        "contractor",
        "air conditioning"
    ],
    "wof:name":"Chiller System, Inc.",
    "wof:placetype":"venue"
},
  "geometry": {"coordinates":[-96.79900000000001,46.879449],"type":"Point"}
}