{
  "type": "Feature",
  "properties": {
    "iso:country":"US",
    "sg:address":"105 Front St W",
    "sg:city":"Rutland",
    "sg:classifiers":[
        {
            "category":"Wholesale",
            "subcategory":"Farm Supplies",
            "type":"Manufacturing & Wholesale Goods"
        }
    ],
    "sg:phone":"+1 701 724 3357",
    "sg:postcode":"58067",
    "sg:province":"ND",
    "sg:tags":[
        "chemical",
        "agricultural"
    ],
    "wof:name":"Weber Ag Svc",
    "wof:placetype":"venue"
},
  "geometry": {"coordinates":[-97.509057,46.054263],"type":"Point"}
}