{
  "type": "Feature",
  "properties": {
    "addr:full":"1403 S Washington St Grand Forks ND 58201",
    "addr:housenumber":"1403",
    "addr:postcode":"58201",
    "addr:street":"S Washington St",
    "iso:country":"US",
    "sg:address":"1403 S Washington St",
    "sg:city":"Grand Forks",
    "sg:classifiers":[
        {
            "category":"Travel",
            "subcategory":"Hotels & Motels",
            "type":"Entertainment"
        }
    ],
    "sg:phone":"+1 701 772 3459",
    "sg:postcode":"58201",
    "sg:province":"ND",
    "sg:tags":[
        "operation"
    ],
    "wof:name":"Lucky Inn Motel",
    "wof:placetype":"venue"
},
  "geometry": {"coordinates":[-97.04497600000001,47.907204],"type":"Point"}
}