{
  "type": "Feature",
  "properties": {
    "iso:country":"US",
    "sg:address":"1515 Park Ave",
    "sg:city":"Bismarck",
    "sg:classifiers":[
        {
            "category":"Building & Trades",
            "subcategory":"Landscaping Services",
            "type":"Services"
        }
    ],
    "sg:phone":"+1 701 222 0251",
    "sg:postcode":"58504",
    "sg:province":"ND",
    "sg:tags":[
        "lawn",
        "maintenance",
        "grounds"
    ],
    "wof:name":"Chem Lawn",
    "wof:placetype":"venue"
},
  "geometry": {"coordinates":[-100.769657,46.790331],"type":"Point"}
}