{
  "type": "Feature",
  "properties": {
    "addr:full":"1509 Bison Dr Williston ND 58801",
    "addr:housenumber":"1509",
    "addr:postcode":"58801",
    "addr:street":"Bison Dr",
    "iso:country":"US",
    "sg:address":"1509 Bison Dr",
    "sg:city":"Williston",
    "sg:classifiers":[
        {
            "category":"Real Estate",
            "subcategory":"Real Estate Operator",
            "type":"Services"
        }
    ],
    "sg:phone":"+1 701 774 1153",
    "sg:postcode":"58801",
    "sg:province":"ND",
    "sg:tags":[
        "apartment"
    ],
    "wof:name":"Century Apartments",
    "wof:placetype":"venue"
},
  "geometry": {"coordinates":[-103.645983,48.161454],"type":"Point"}
}