{
  "type": "Feature",
  "properties": {
    "addr:full":"3320 15th St S Fargo ND 58104",
    "addr:housenumber":"3320",
    "addr:postcode":"58104",
    "addr:street":"15Th St S",
    "iso:country":"US",
    "sg:address":"3320 15th St S",
    "sg:city":"Fargo",
    "sg:classifiers":[
        {
            "category":"Manufacturing",
            "subcategory":"Building Materials",
            "type":"Manufacturing & Wholesale Goods"
        }
    ],
    "sg:phone":"+1 701 237 6948",
    "sg:postcode":"58104",
    "sg:province":"ND",
    "sg:tags":[
        "wooden",
        "mfg",
        "kitchen",
        "cabinet"
    ],
    "wof:name":"Denning Fabricating Inc",
    "wof:placetype":"venue"
},
  "geometry": {"coordinates":[-96.803308,46.829707],"type":"Point"}
}