{
  "type": "Feature",
  "properties": {
    "iso:country":"US",
    "sg:address":"17185 Co Rd 8",
    "sg:city":"Wahpeton",
    "sg:classifiers":[
        {
            "category":"Farming",
            "subcategory":"Farm",
            "type":"Manufacturing & Wholesale Goods"
        }
    ],
    "sg:phone":"+1 701 553 8833",
    "sg:postcode":"58075",
    "sg:province":"ND",
    "wof:name":"Gorder Shop",
    "wof:placetype":"venue"
},
  "geometry": {"coordinates":[-96.823252,46.384015],"type":"Point"}
}