{
  "type": "Feature",
  "properties": {
    "iso:country":"US",
    "sg:address":"401 6th Ave",
    "sg:city":"Rolette",
    "sg:classifiers":[
        {
            "category":"Wholesale",
            "subcategory":"Meat",
            "type":"Manufacturing & Wholesale Goods"
        }
    ],
    "sg:phone":"+1 701 246 3358",
    "sg:postcode":"58366",
    "sg:province":"ND",
    "sg:tags":[
        "plant",
        "packing"
    ],
    "wof:name":"Steven Grenier",
    "wof:placetype":"venue"
},
  "geometry": {"coordinates":[-99.84647699999999,48.665983],"type":"Point"}
}