{
  "type": "Feature",
  "properties": {
    "addr:full":"121 Main Ave Oakes ND 58474",
    "addr:housenumber":"121",
    "addr:postcode":"58474",
    "addr:street":"Main Ave",
    "iso:country":"US",
    "sg:address":"121 Main Ave",
    "sg:city":"Oakes",
    "sg:classifiers":[
        {
            "category":"Freight",
            "type":"Transportation"
        }
    ],
    "sg:phone":"+1 701 742 2183",
    "sg:postcode":"58474",
    "sg:province":"ND",
    "sg:tags":[
        "broker",
        "trucking"
    ],
    "wof:name":"James River Dispatch",
    "wof:placetype":"venue"
},
  "geometry": {"coordinates":[-98.098645,46.138957],"type":"Point"}
}