{
  "type": "Feature",
  "properties": {
    "addr:full":"1121 18th St N Fargo ND 58102",
    "addr:housenumber":"1121",
    "addr:postcode":"58102",
    "addr:street":"18Th St N",
    "iso:country":"US",
    "sg:address":"1121 18th St N",
    "sg:city":"Fargo",
    "sg:classifiers":[
        {
            "category":"Professional",
            "subcategory":"Management & Consulting",
            "type":"Services"
        }
    ],
    "sg:phone":"+1 701 280 0387",
    "sg:postcode":"58102",
    "sg:province":"ND",
    "sg:tags":[
        "farm"
    ],
    "wof:name":"Bradley W & Pamela R Loos",
    "wof:placetype":"venue"
},
  "geometry": {"coordinates":[-96.809195,46.888988],"type":"Point"}
}