{
  "type": "Feature",
  "properties": {
    "addr:full":"8692 78th Ave SE Ellendale ND 58436",
    "addr:housenumber":"8692",
    "addr:postcode":"58436",
    "addr:street":"78Th Ave Se",
    "iso:country":"US",
    "sg:address":"8692 78th Ave SE",
    "sg:city":"Ellendale",
    "sg:phone":"+1 701 396 7171",
    "sg:postcode":"58436",
    "sg:province":"ND",
    "sg:tags":[
        "farm",
        "wheat",
        "corn",
        "grain",
        "cash"
    ],
    "wof:name":"Bryan Brandenburge",
    "wof:placetype":"venue"
},
  "geometry": {"coordinates":[-98.755309,46.142423],"type":"Point"}
}