{
  "type": "Feature",
  "properties": {
    "addr:full":"30 N University Dr Fargo ND 58102",
    "addr:housenumber":"30",
    "addr:postcode":"58102",
    "addr:street":"N University Dr",
    "iso:country":"US",
    "sg:address":"30 N University Dr",
    "sg:city":"Fargo",
    "sg:classifiers":[
        {
            "category":"Retail",
            "subcategory":"Auto Repair",
            "type":"Services"
        }
    ],
    "sg:phone":"+1 701 280 0620",
    "sg:postcode":"58102",
    "sg:province":"ND",
    "sg:tags":[
        "automotive"
    ],
    "wof:name":"Border Cities Service Center",
    "wof:placetype":"venue"
},
  "geometry": {"coordinates":[-96.798316,46.877085],"type":"Point"}
}