{
  "type": "Feature",
  "properties": {
    "iso:country":"US",
    "sg:address":"220 E Rosser Ave Rm 372",
    "sg:city":"Bismarck",
    "sg:classifiers":[
        {
            "category":"Government",
            "subcategory":"Office",
            "type":"Public Place"
        }
    ],
    "sg:phone":"+1 701 530 2420",
    "sg:postcode":"58501",
    "sg:province":"ND",
    "sg:tags":[
        "government-united",
        "state"
    ],
    "sg:website":"http://www.public-counsel.org",
    "wof:name":"Us Attorney's Office",
    "wof:placetype":"venue"
},
  "geometry": {"coordinates":[-100.788791,46.808599],"type":"Point"}
}