{
  "type": "Feature",
  "properties": {
    "iso:country":"US",
    "sg:address":"2553 Kirsten Ln S",
    "sg:city":"Fargo",
    "sg:classifiers":[
        {
            "category":"Ice Cream",
            "type":"Food & Drink"
        }
    ],
    "sg:menulink":"http://www.allmenus.com/nd/fargo/209217-tcby/menu/",
    "sg:phone":"+1 701 298 0707",
    "sg:postcode":"58104",
    "sg:province":"ND",
    "sg:tags":[
        "smoothy",
        "juice",
        "american"
    ],
    "wof:name":"TCBY",
    "wof:placetype":"venue"
},
  "geometry": {"coordinates":[-96.821112,46.831421],"type":"Point"}
}