{
  "type": "Feature",
  "properties": {
    "iso:country":"US",
    "sg:address":"217 Main St",
    "sg:city":"Turtle Lake",
    "sg:classifiers":[
        {
            "category":"Restaurant",
            "type":"Food & Drink"
        }
    ],
    "sg:phone":"+1 701 448 2813",
    "sg:postcode":"58575",
    "sg:province":"ND",
    "sg:tags":[
        "shop",
        "coffee"
    ],
    "wof:name":"Ms Vikki's On Main",
    "wof:placetype":"venue"
},
  "geometry": {"coordinates":[-100.88995799999999,47.520738],"type":"Point"}
}