{
  "type": "Feature",
  "properties": {
    "iso:country":"US",
    "sg:address":"1035 E Interstate Ave",
    "sg:city":"Bismarck",
    "sg:classifiers":[
        {
            "category":"Insurance",
            "subcategory":"Insurance Agent",
            "type":"Services"
        }
    ],
    "sg:phone":"+1 701 223 6523",
    "sg:postcode":"58503",
    "sg:province":"ND",
    "wof:name":"Reuppel Scott Ins Agency Inc",
    "wof:placetype":"venue"
},
  "geometry": {"coordinates":[-100.775779,46.83272],"type":"Point"}
}