{
  "type": "Feature",
  "properties": {
    "addr:full":"8224 6th Ave SE Linton ND 58552",
    "addr:housenumber":"8224",
    "addr:postcode":"58552",
    "addr:street":"6Th Ave Se;Nd",
    "iso:country":"US",
    "sg:address":"8224 6th Ave SE",
    "sg:city":"Linton",
    "sg:classifiers":[
        {
            "category":"Wholesale",
            "subcategory":"Meat",
            "type":"Manufacturing & Wholesale Goods"
        }
    ],
    "sg:phone":"+1 701 254 4015",
    "sg:postcode":"58552",
    "sg:province":"ND",
    "wof:name":"Roaming Bison Ranch",
    "wof:placetype":"venue"
},
  "geometry": {"coordinates":[-100.251672,46.230088],"type":"Point"}
}