{
  "type": "Feature",
  "properties": {
    "addr:full":"1029 5th Ave NE Valley City ND 58072",
    "addr:housenumber":"1029",
    "addr:postcode":"58072",
    "addr:street":"5Th Ave Ne",
    "iso:country":"US",
    "sg:address":"1029 5th Ave NE",
    "sg:city":"Valley City",
    "sg:classifiers":[
        {
            "category":"Government",
            "subcategory":"Office",
            "type":"Public Place"
        }
    ],
    "sg:phone":"+1 701 845 4151",
    "sg:postcode":"58072",
    "sg:province":"ND",
    "sg:tags":[
        "city"
    ],
    "wof:name":"Valley City Hi Line Prk",
    "wof:placetype":"venue"
},
  "geometry": {"coordinates":[-97.99718,46.934209],"type":"Point"}
}