{
  "type": "Feature",
  "properties": {
    "iso:country":"US",
    "sg:address":"501 E Front St",
    "sg:city":"Larimore",
    "sg:classifiers":[
        {
            "category":"Health Services",
            "subcategory":"Nursing And Care Facility",
            "type":"Services"
        }
    ],
    "sg:phone":"+1 701 343 6244",
    "sg:postcode":"58251",
    "sg:province":"ND",
    "sg:tags":[
        "home",
        "convalescent"
    ],
    "wof:name":"Trutle River Good Samaritan",
    "wof:placetype":"venue"
},
  "geometry": {"coordinates":[-97.61759000000001,47.904746],"type":"Point"}
}