{
  "type": "Feature",
  "properties": {
    "iso:country":"US",
    "sg:address":"101 3rd Ave NE",
    "sg:city":"Lidgerwood",
    "sg:classifiers":[
        {
            "category":"Freight",
            "type":"Transportation"
        }
    ],
    "sg:phone":"+1 701 538 7739",
    "sg:postcode":"58053",
    "sg:province":"ND",
    "sg:tags":[
        "hauling",
        "trucking"
    ],
    "wof:name":"Krause Express",
    "wof:placetype":"venue"
},
  "geometry": {"coordinates":[-97.14749500000001,46.077945],"type":"Point"}
}