{
  "type": "Feature",
  "properties": {
    "iso:country":"US",
    "sg:address":"1717 6th St W",
    "sg:city":"Williston",
    "sg:classifiers":[
        {
            "category":"Building & Trades",
            "subcategory":"Construction",
            "type":"Services"
        }
    ],
    "sg:phone":"+1 701 572 8046",
    "sg:postcode":"58801",
    "sg:province":"ND",
    "sg:tags":[
        "house"
    ],
    "wof:name":"Soiseth Construction",
    "wof:placetype":"venue"
},
  "geometry": {"coordinates":[-103.646507,48.148523],"type":"Point"}
}