{
  "type": "Feature",
  "properties": {
    "addr:full":"1646 Main S Dickinson ND 58601",
    "addr:housenumber":"1646",
    "addr:postcode":"58601",
    "addr:street":"Main S",
    "iso:country":"US",
    "sg:address":"1646 Main S",
    "sg:city":"Dickinson",
    "sg:classifiers":[
        {
            "category":"Retail",
            "subcategory":"Auto Repair",
            "type":"Services"
        }
    ],
    "sg:phone":"+1 701 483 0050",
    "sg:postcode":"58601",
    "sg:province":"ND",
    "sg:tags":[
        "repairing",
        "automobile"
    ],
    "wof:name":"Gary's Auto Svc",
    "wof:placetype":"venue"
},
  "geometry": {"coordinates":[-102.78985299999999,46.851759],"type":"Point"}
}