{
  "type": "Feature",
  "properties": {
    "iso:country":"US",
    "sg:address":"301 2nd St E",
    "sg:city":"Mcclusky",
    "sg:classifiers":[
        {
            "category":"Organizations",
            "subcategory":"Religious Organization",
            "type":"Services"
        }
    ],
    "sg:phone":"+1 701 363 2420",
    "sg:postcode":"58463",
    "sg:province":"ND",
    "sg:tags":[
        "church"
    ],
    "wof:name":"Mc Clusky United Methodist Chr",
    "wof:placetype":"venue"
},
  "geometry": {"coordinates":[-100.441169,47.483927],"type":"Point"}
}