{
  "type": "Feature",
  "properties": {
    "addr:full":"401 4th Ave NE Berthold ND 58718",
    "addr:housenumber":"401",
    "addr:postcode":"58718",
    "addr:street":"4Th Ave Ne",
    "iso:country":"US",
    "sg:address":"401 4th Ave NE",
    "sg:city":"Berthold",
    "sg:classifiers":[
        {
            "category":"Education",
            "subcategory":"School",
            "type":"Public Place"
        }
    ],
    "sg:phone":"+1 701 453 3484",
    "sg:postcode":"58718",
    "sg:province":"ND",
    "wof:name":"Lewis & Clark School Dist 161",
    "wof:placetype":"venue"
},
  "geometry": {"coordinates":[-101.728751,48.316427],"type":"Point"}
}