{
  "type": "Feature",
  "properties": {
    "iso:country":"US",
    "sg:address":"2550 University Dr S",
    "sg:city":"Fargo",
    "sg:classifiers":[
        {
            "category":"Restaurant",
            "type":"Food & Drink"
        }
    ],
    "sg:menulink":"http://www.allmenus.com/nd/fargo/200663-long-john-silvers/menu/",
    "sg:phone":"+1 701 232 0606",
    "sg:postcode":"58103",
    "sg:province":"ND",
    "sg:tags":[
        "seafood",
        "american"
    ],
    "wof:name":"Long John Silver's",
    "wof:placetype":"venue"
},
  "geometry": {"coordinates":[-96.79812,46.840214],"type":"Point"}
}