{
  "type": "Feature",
  "properties": {
    "iso:country":"US",
    "sg:address":"15 9th St S",
    "sg:city":"Fargo",
    "sg:classifiers":[
        {
            "category":"Professional",
            "subcategory":"Lawyer & Legal Services",
            "type":"Services"
        }
    ],
    "sg:phone":"+1 701 235 7501",
    "sg:postcode":"58103",
    "sg:province":"ND",
    "sg:tags":[
        "attorney"
    ],
    "wof:name":"Johnson Ramstad & Mottinger",
    "wof:placetype":"venue"
},
  "geometry": {"coordinates":[-96.792742,46.873765],"type":"Point"}
}