{
  "type": "Feature",
  "properties": {
    "addr:full":"100 4th St S Fargo ND 58103",
    "addr:housenumber":"100",
    "addr:postcode":"58103",
    "addr:street":"4Th St S",
    "iso:country":"US",
    "sg:address":"100 4th St S",
    "sg:city":"Fargo",
    "sg:classifiers":[
        {
            "category":"Real Estate",
            "subcategory":"Real Estate Operator",
            "type":"Services"
        }
    ],
    "sg:phone":"+1 701 235 2992",
    "sg:postcode":"58103",
    "sg:province":"ND",
    "sg:tags":[
        "building",
        "nonresidential"
    ],
    "wof:name":"Professional Associates Ltd",
    "wof:placetype":"venue"
},
  "geometry": {"coordinates":[-96.785146,46.872949],"type":"Point"}
}