{
  "type": "Feature",
  "properties": {
    "iso:country":"US",
    "sg:address":"11936 Valley Rd",
    "sg:city":"Fort Ransom",
    "sg:classifiers":[
        {
            "category":"Building & Trades",
            "subcategory":"Construction",
            "type":"Services"
        }
    ],
    "sg:phone":"+1 701 973 2221",
    "sg:postcode":"58033",
    "sg:province":"ND",
    "sg:tags":[
        "nonresidential",
        "contractor"
    ],
    "wof:name":"Riverside Contracting",
    "wof:placetype":"venue"
},
  "geometry": {"coordinates":[-97.9226,46.522401],"type":"Point"}
}