{
  "type": "Feature",
  "properties": {
    "iso:country":"US",
    "sg:address":"202 Jackson Ave W",
    "sg:city":"Lisbon",
    "sg:classifiers":[
        {
            "category":"Retail",
            "subcategory":"Car Wash",
            "type":"Services"
        }
    ],
    "sg:phone":"+1 701 683 3018",
    "sg:postcode":"58054",
    "sg:province":"ND",
    "sg:tags":[
        "polishing",
        "washing"
    ],
    "wof:name":"Rain Forest Car Wash-Auto",
    "wof:placetype":"venue"
},
  "geometry": {"coordinates":[-97.685411,46.432932],"type":"Point"}
}