{
  "type": "Feature",
  "properties": {
    "iso:country":"US",
    "sg:address":"116 1st St SW",
    "sg:city":"Minot",
    "sg:classifiers":[
        {
            "category":"Health Services",
            "subcategory":"Doctor",
            "type":"Services"
        }
    ],
    "sg:phone":"+1 701 839 1299",
    "sg:postcode":"58701",
    "sg:province":"ND",
    "sg:tags":[
        "dentist"
    ],
    "wof:name":"Family Dental Clinic",
    "wof:placetype":"venue"
},
  "geometry": {"coordinates":[-101.29464400000001,48.23525],"type":"Point"}
}