{
  "type": "Feature",
  "properties": {
    "iso:country":"US",
    "sg:address":"244 9th St NW",
    "sg:city":"Valley City",
    "sg:classifiers":[
        {
            "category":"Wholesale",
            "subcategory":"Books, Periodicals, & Newspapers",
            "type":"Manufacturing & Wholesale Goods"
        }
    ],
    "sg:phone":"+1 701 845 0050",
    "sg:postcode":"58072",
    "sg:province":"ND",
    "sg:tags":[
        "distributor"
    ],
    "wof:name":"Forum Agency Valley City",
    "wof:placetype":"venue"
},
  "geometry": {"coordinates":[-98.00537300000001,46.931808],"type":"Point"}
}