{
  "type": "Feature",
  "properties": {
    "iso:country":"US",
    "sg:address":"1125 E Main Ave",
    "sg:city":"Bismarck",
    "sg:classifiers":[
        {
            "category":"Education",
            "subcategory":"Dance Studio",
            "type":"Public Place"
        }
    ],
    "sg:phone":"+1 701 530 0986",
    "sg:postcode":"58501",
    "sg:province":"ND",
    "sg:tags":[
        "instruction",
        "dancing"
    ],
    "sg:website":"www.npb.org",
    "wof:name":"Northern Plains Ballet",
    "wof:placetype":"venue"
},
  "geometry": {"coordinates":[-100.774289,46.805224],"type":"Point"}
}