{
  "type": "Feature",
  "properties": {
    "iso:country":"US",
    "sg:address":"915 S 48th St",
    "sg:city":"Grand Forks",
    "sg:classifiers":[
        {
            "category":"Shopping",
            "subcategory":"Computers & Home Electronics",
            "type":"Retail Goods"
        },
        {
            "category":"Professional",
            "subcategory":"Computer Services",
            "type":"Services"
        }
    ],
    "sg:phone":"+1 701 772 6408",
    "sg:postcode":"58201",
    "sg:province":"ND",
    "sg:tags":[
        "equipment",
        "consulting",
        "dealer",
        "related"
    ],
    "wof:name":"Millennium Systems Tech Inc",
    "wof:placetype":"venue"
},
  "geometry": {"coordinates":[-97.099131,47.912879],"type":"Point"}
}