{
  "type": "Feature",
  "properties": {
    "iso:country":"US",
    "sg:address":"1428 Cottonwood St",
    "sg:city":"Grand Forks",
    "sg:classifiers":[
        {
            "category":"Communications",
            "subcategory":"Film & Video Production",
            "type":"Services"
        }
    ],
    "sg:phone":"+1 701 746 6424",
    "sg:postcode":"58201",
    "sg:province":"ND",
    "sg:tags":[
        "duplication",
        "tape"
    ],
    "wof:name":"Midwest Duplication",
    "wof:placetype":"venue"
},
  "geometry": {"coordinates":[-97.033416,47.907925],"type":"Point"}
}