{
  "type": "Feature",
  "properties": {
    "iso:country":"US",
    "sg:address":"1949 N Broadway",
    "sg:city":"Minot",
    "sg:classifiers":[
        {
            "category":"Personal",
            "subcategory":"Barber",
            "type":"Services"
        }
    ],
    "sg:phone":"+1 701 839 3860",
    "sg:postcode":"58703",
    "sg:province":"ND",
    "sg:tags":[
        "shop"
    ],
    "wof:name":"Bernies Northhill Barber Shop",
    "wof:placetype":"venue"
},
  "geometry": {"coordinates":[-101.295879,48.255439],"type":"Point"}
}