{
  "type": "Feature",
  "properties": {
    "iso:country":"US",
    "sg:address":"716 2nd St W",
    "sg:city":"Williston",
    "sg:classifiers":[
        {
            "category":"Social Services",
            "type":"Services"
        }
    ],
    "sg:phone":"+1 701 572 6752",
    "sg:postcode":"58801",
    "sg:province":"ND",
    "sg:tags":[
        "senior",
        "citizen"
    ],
    "wof:name":"Senior Citizens Program",
    "wof:placetype":"venue"
},
  "geometry": {"coordinates":[-103.634657,48.145277],"type":"Point"}
}