{
  "type": "Feature",
  "properties": {
    "iso:country":"US",
    "sg:address":"9400 205th Ave SW",
    "sg:city":"Douglas",
    "sg:phone":"+1 701 722 3244",
    "sg:postcode":"58735",
    "sg:province":"ND",
    "sg:tags":[
        "farm",
        "grain",
        "cash"
    ],
    "wof:name":"Gary Sys",
    "wof:placetype":"venue"
},
  "geometry": {"coordinates":[-101.405643,48.023201],"type":"Point"}
}