{
  "type": "Feature",
  "properties": {
    "addr:full":"1059 E Interstate Ave Bismarck ND 58503",
    "addr:housenumber":"1059",
    "addr:postcode":"58503",
    "addr:street":"E Interstate Ave",
    "iso:country":"US",
    "sg:address":"1059 E Interstate Ave",
    "sg:city":"Bismarck",
    "sg:classifiers":[
        {
            "category":"Bars & Pubs",
            "type":"Food & Drink"
        }
    ],
    "sg:phone":"+1 701 258 5700",
    "sg:postcode":"58503",
    "sg:province":"ND",
    "wof:name":"O'Brian's Tavern",
    "wof:placetype":"venue"
},
  "geometry": {"coordinates":[-100.7764,46.83272],"type":"Point"}
}