{
  "type": "Feature",
  "properties": {
    "iso:country":"US",
    "sg:address":"201 15th St NE",
    "sg:city":"Mandan",
    "sg:classifiers":[
        {
            "category":"Shopping",
            "subcategory":"Tobacco",
            "type":"Retail Goods"
        }
    ],
    "sg:phone":"+1 701 663 1134",
    "sg:postcode":"58554",
    "sg:province":"ND",
    "wof:name":"Connoisseur Cigar Co",
    "wof:placetype":"venue"
},
  "geometry": {"coordinates":[-100.88953600000001,46.839351],"type":"Point"}
}