{
  "type": "Feature",
  "properties": {
    "iso:country":"US",
    "sg:address":"3561 Woodbury Park Dr",
    "sg:city":"Fargo",
    "sg:classifiers":[
        {
            "category":"Real Estate",
            "subcategory":"Real Estate Operator",
            "type":"Services"
        }
    ],
    "sg:phone":"+1 701 293 8533",
    "sg:postcode":"58103",
    "sg:province":"ND",
    "sg:tags":[
        "building",
        "nonresidential"
    ],
    "wof:name":"Sundhans Properties Inc",
    "wof:placetype":"venue"
},
  "geometry": {"coordinates":[-96.836799,46.841859],"type":"Point"}
}