{
  "type": "Feature",
  "properties": {
    "iso:country":"US",
    "sg:address":"6550 33rd St SE",
    "sg:city":"Cleveland",
    "sg:classifiers":[
        {
            "category":"Farming",
            "subcategory":"Farm",
            "type":"Manufacturing & Wholesale Goods"
        }
    ],
    "sg:phone":"+1 701 763 6455",
    "sg:postcode":"58424",
    "sg:province":"ND",
    "wof:name":"Myron Tarno Farm",
    "wof:placetype":"venue"
},
  "geometry": {"coordinates":[-99.08257399999999,46.935071],"type":"Point"}
}