{
  "type": "Feature",
  "properties": {
    "iso:country":"US",
    "sg:address":"5032 133 Dr NW",
    "sg:city":"Williston",
    "sg:classifiers":[
        {
            "category":"Education",
            "subcategory":"School",
            "type":"Public Place"
        }
    ],
    "sg:phone":"+1 701 572 3579",
    "sg:postcode":"58801",
    "sg:province":"ND",
    "wof:name":"Stoney Creek Elementary School",
    "wof:placetype":"venue"
},
  "geometry": {"coordinates":[-103.991321,47.998632],"type":"Point"}
}