{
  "type": "Feature",
  "properties": {
    "addr:full":"3008 16th St NE Manvel ND 58256",
    "addr:housenumber":"3008",
    "addr:postcode":"58256",
    "addr:street":"16Th St Ne",
    "iso:country":"US",
    "sg:address":"3008 16th St NE",
    "sg:city":"Manvel",
    "sg:classifiers":[
        {
            "category":"Professional",
            "subcategory":"Management & Consulting",
            "type":"Services"
        }
    ],
    "sg:phone":"+1 701 787 5660",
    "sg:postcode":"58256",
    "sg:province":"ND",
    "sg:tags":[
        "agricultural",
        "consultant"
    ],
    "wof:name":"Philom Bios LTD",
    "wof:placetype":"venue"
},
  "geometry": {"coordinates":[-97.169905,48.116183],"type":"Point"}
}