{
  "type": "Feature",
  "properties": {
    "addr:full":"2630 114th Ave SE Valley City ND 58072",
    "addr:housenumber":"2630",
    "addr:postcode":"58072",
    "addr:street":"114Th Ave Se",
    "iso:country":"US",
    "sg:address":"2630 114th Ave SE",
    "sg:city":"Valley City",
    "sg:classifiers":[
        {
            "category":"Government",
            "subcategory":"Office",
            "type":"Public Place"
        }
    ],
    "sg:phone":"+1 701 845 2970",
    "sg:postcode":"58072",
    "sg:province":"ND",
    "sg:tags":[
        "federal"
    ],
    "wof:name":"US Army Corps Of Engineers",
    "wof:placetype":"venue"
},
  "geometry": {"coordinates":[-98.086433,47.0331],"type":"Point"}
}