{
  "type": "Feature",
  "properties": {
    "addr:full":"1407 35th St S Fargo ND 58103",
    "addr:housenumber":"1407",
    "addr:postcode":"58103",
    "addr:street":"35Th St S",
    "iso:country":"US",
    "sg:address":"1407 35th St S",
    "sg:city":"Fargo",
    "sg:classifiers":[
        {
            "category":"Travel",
            "subcategory":"Hotels & Motels",
            "type":"Entertainment"
        }
    ],
    "sg:phone":"+1 701 280 9666",
    "sg:postcode":"58103",
    "sg:province":"ND",
    "wof:name":"Comfort Inn",
    "wof:placetype":"venue"
},
  "geometry": {"coordinates":[-96.83793,46.859731],"type":"Point"}
}