{
  "type": "Feature",
  "properties": {
    "addr:full":"16603 128th St NW Berthold ND 58718",
    "addr:housenumber":"16603",
    "addr:postcode":"58718",
    "addr:street":"128Th St Nw",
    "iso:country":"US",
    "sg:address":"16603 128th St NW",
    "sg:city":"Berthold",
    "sg:classifiers":[
        {
            "category":"Farming",
            "subcategory":"Farm",
            "type":"Manufacturing & Wholesale Goods"
        }
    ],
    "sg:phone":"+1 701 468 5649",
    "sg:postcode":"58718",
    "sg:province":"ND",
    "sg:tags":[
        "crop",
        "general"
    ],
    "wof:name":"Murray Bock",
    "wof:placetype":"venue"
},
  "geometry": {"coordinates":[-101.49520099999999,48.412381],"type":"Point"}
}