{
  "type": "Feature",
  "properties": {
    "addr:full":"300 N 7th St Bismarck ND 58501",
    "addr:housenumber":"300",
    "addr:postcode":"58501",
    "addr:street":"N 7Th St",
    "iso:country":"US",
    "sg:address":"300 N 7th St",
    "sg:city":"Bismarck",
    "sg:classifiers":[
        {
            "category":"Health Services",
            "subcategory":"Doctor",
            "type":"Services"
        }
    ],
    "sg:phone":"+1 701 323 6150",
    "sg:postcode":"58501",
    "sg:province":"ND",
    "sg:tags":[
        "medical"
    ],
    "wof:name":"Craig Lambrecht",
    "wof:placetype":"venue"
},
  "geometry": {"coordinates":[-100.781527,46.808527],"type":"Point"}
}