{
  "type": "Feature",
  "properties": {
    "iso:country":"US",
    "sg:address":"677 26th Ave E",
    "sg:city":"Dickinson",
    "sg:classifiers":[
        {
            "category":"Wholesale",
            "subcategory":"Machinery & Supplies",
            "type":"Manufacturing & Wholesale Goods"
        }
    ],
    "sg:phone":"+1 701 225 6888",
    "sg:postcode":"58601",
    "sg:province":"ND",
    "sg:tags":[
        "we",
        "industrial",
        "for",
        "gas",
        "hardware",
        "equipment",
        "welding"
    ],
    "wof:name":"A-1 Welding Products Inc",
    "wof:placetype":"venue"
},
  "geometry": {"coordinates":[-102.744996,46.883399],"type":"Point"}
}