{
  "type": "Feature",
  "properties": {
    "iso:country":"US",
    "sg:address":"309 Millionaire Ave",
    "sg:city":"Mott",
    "sg:classifiers":[
        {
            "category":"Government",
            "subcategory":"Office",
            "type":"Public Place"
        }
    ],
    "sg:phone":"+1 701 824 3215",
    "sg:postcode":"58646",
    "sg:province":"ND",
    "wof:name":"County Nurse",
    "wof:placetype":"venue"
},
  "geometry": {"coordinates":[-102.317368,46.374652],"type":"Point"}
}