{
  "type": "Feature",
  "properties": {
    "addr:full":"1201 N 1st St Bismarck ND 58501",
    "addr:housenumber":"1201",
    "addr:postcode":"58501",
    "addr:street":"N 1St St",
    "iso:country":"US",
    "sg:address":"1201 N 1st St",
    "sg:city":"Bismarck",
    "sg:classifiers":[
        {
            "category":"Shopping",
            "subcategory":"Musical Instruments",
            "type":"Retail Goods"
        }
    ],
    "sg:phone":"+1 701 222 3451",
    "sg:postcode":"58501",
    "sg:province":"ND",
    "wof:name":"More Drums Percussion Studio",
    "wof:placetype":"venue"
},
  "geometry": {"coordinates":[-100.79286500000001,46.821543],"type":"Point"}
}