{
  "type": "Feature",
  "properties": {
    "iso:country":"US",
    "sg:address":"36 Main St E",
    "sg:city":"Mayville",
    "sg:classifiers":[
        {
            "category":"Insurance",
            "subcategory":"Insurance Agent",
            "type":"Services"
        }
    ],
    "sg:phone":"+1 701 786 2511",
    "sg:postcode":"58257",
    "sg:province":"ND",
    "wof:name":"Nodak Mutual Insurance Company",
    "wof:placetype":"venue"
},
  "geometry": {"coordinates":[-97.325272,47.500471],"type":"Point"}
}