{
  "type": "Feature",
  "properties": {
    "iso:country":"US",
    "sg:address":"911 Lincoln Ave",
    "sg:city":"Harvey",
    "sg:classifiers":[
        {
            "category":"Shopping",
            "subcategory":"Computers & Home Electronics",
            "type":"Retail Goods"
        }
    ],
    "sg:phone":"+1 701 324 2126",
    "sg:postcode":"58341",
    "sg:province":"ND",
    "sg:tags":[
        "equipment",
        "electronic",
        "supply"
    ],
    "wof:name":"B J Electronics",
    "wof:placetype":"venue"
},
  "geometry": {"coordinates":[-99.9362,47.768734],"type":"Point"}
}