{
  "type": "Feature",
  "properties": {
    "iso:country":"US",
    "sg:address":"3110 4th Ave NW",
    "sg:city":"Minot",
    "sg:classifiers":[
        {
            "category":"Shopping",
            "subcategory":"Used Merchandise",
            "type":"Retail Goods"
        }
    ],
    "sg:phone":"+1 701 839 6874",
    "sg:postcode":"58703",
    "sg:province":"ND",
    "wof:name":"ABC Market Used Furn & Var Sp",
    "wof:placetype":"venue"
},
  "geometry": {"coordinates":[-101.342078,48.240175],"type":"Point"}
}