{
  "type": "Feature",
  "properties": {
    "iso:country":"US",
    "sg:address":"1628 US Hwy 52",
    "sg:city":"Fessenden",
    "sg:classifiers":[
        {
            "category":"Personal",
            "subcategory":"Beauty Salon",
            "type":"Services"
        }
    ],
    "sg:phone":"+1 701 547 3370",
    "sg:postcode":"58438",
    "sg:province":"ND",
    "sg:tags":[
        "shop"
    ],
    "wof:name":"Hair Shak",
    "wof:placetype":"venue"
},
  "geometry": {"coordinates":[-99.639876,47.648362],"type":"Point"}
}