{
  "type": "Feature",
  "properties": {
    "iso:country":"US",
    "sg:address":"1505 N Broadway",
    "sg:city":"Minot",
    "sg:classifiers":[
        {
            "category":"Recreation",
            "subcategory":"Arcade",
            "type":"Entertainment"
        }
    ],
    "sg:phone":"+1 701 837 1684",
    "sg:postcode":"58703",
    "sg:province":"ND",
    "sg:tags":[
        "casino"
    ],
    "wof:name":"Reflections Lounge",
    "wof:placetype":"venue"
},
  "geometry": {"coordinates":[-101.295739,48.248647],"type":"Point"}
}