{
  "type": "Feature",
  "properties": {
    "addr:full":"102 Main Ave E Rolla ND 58367",
    "addr:housenumber":"102",
    "addr:postcode":"58367",
    "addr:street":"Main Ave E",
    "iso:country":"US",
    "sg:address":"102 Main Ave E",
    "sg:city":"Rolla",
    "sg:classifiers":[
        {
            "category":"Home & Garden",
            "subcategory":"Hardware",
            "type":"Retail Goods"
        }
    ],
    "sg:phone":"+1 701 477 3629",
    "sg:postcode":"58367",
    "sg:province":"ND",
    "wof:name":"Jacobsen Hardware",
    "wof:placetype":"venue"
},
  "geometry": {"coordinates":[-99.61388599999999,48.859697],"type":"Point"}
}