{
  "type": "Feature",
  "properties": {
    "addr:full":"808 1st St NW Bowman ND 58623",
    "addr:housenumber":"808",
    "addr:postcode":"58623",
    "addr:street":"1St St Nw",
    "iso:country":"US",
    "sg:address":"808 1st St NW",
    "sg:city":"Bowman",
    "sg:classifiers":[
        {
            "category":"Government",
            "subcategory":"Office",
            "type":"Public Place"
        }
    ],
    "sg:phone":"+1 701 523 4671",
    "sg:postcode":"58623",
    "sg:province":"ND",
    "sg:tags":[
        "state"
    ],
    "wof:name":"North Dakota Game & Fish WRDN",
    "wof:placetype":"venue"
},
  "geometry": {"coordinates":[-103.407265,46.183295],"type":"Point"}
}