{
  "type": "Feature",
  "properties": {
    "addr:full":"828 1st Ave S New Rockford ND 58356",
    "addr:housenumber":"828",
    "addr:postcode":"58356",
    "addr:street":"1St Ave S",
    "iso:country":"US",
    "sg:address":"828 1st Ave S",
    "sg:city":"New Rockford",
    "sg:classifiers":[
        {
            "category":"Organizations",
            "subcategory":"Religious Organization",
            "type":"Services"
        }
    ],
    "sg:phone":"+1 701 947 5683",
    "sg:postcode":"58356",
    "sg:province":"ND",
    "sg:tags":[
        "church"
    ],
    "wof:name":"Evangelical Free Church",
    "wof:placetype":"venue"
},
  "geometry": {"coordinates":[-99.13826400000001,47.679181],"type":"Point"}
}