{
  "type": "Feature",
  "properties": {
    "addr:full":"509 Division Ave N Cavalier ND 58220",
    "addr:housenumber":"509",
    "addr:postcode":"58220",
    "addr:street":"Division Ave N",
    "iso:country":"US",
    "sg:address":"509 Division Ave N",
    "sg:city":"Cavalier",
    "sg:classifiers":[
        {
            "category":"Building & Trades",
            "subcategory":"Construction",
            "type":"Services"
        }
    ],
    "sg:phone":"+1 701 549 3515",
    "sg:postcode":"58220",
    "sg:province":"ND",
    "sg:tags":[
        "contractor",
        "co",
        "hanging"
    ],
    "wof:name":"Kalis Albert Pntg Drywall Cntr",
    "wof:placetype":"venue"
},
  "geometry": {"coordinates":[-97.622366,48.798851],"type":"Point"}
}