{
  "type": "Feature",
  "properties": {
    "iso:country":"US",
    "sg:address":"714 S Washington St",
    "sg:city":"Grand Forks",
    "sg:classifiers":[
        {
            "category":"Shopping",
            "subcategory":"Music",
            "type":"Retail Goods"
        }
    ],
    "sg:phone":"+1 701 775 5172",
    "sg:postcode":"58201",
    "sg:province":"ND",
    "sg:tags":[
        "compact",
        "record",
        "disc",
        "video",
        "tape",
        "rental"
    ],
    "wof:name":"Budget Music & Video",
    "wof:placetype":"venue"
},
  "geometry": {"coordinates":[-97.04507700000001,47.914469],"type":"Point"}
}