{
  "type": "Feature",
  "properties": {
    "addr:full":"4202 14th Ave N Fargo ND 58102",
    "addr:housenumber":"4202",
    "addr:postcode":"58102",
    "addr:street":"14Th Ave N",
    "iso:country":"US",
    "sg:address":"4202 14th Ave N",
    "sg:city":"Fargo",
    "sg:classifiers":[
        {
            "category":"Wholesale",
            "subcategory":"Durable Goods & Equipment",
            "type":"Manufacturing & Wholesale Goods"
        }
    ],
    "sg:phone":"+1 701 492 3010",
    "sg:postcode":"58102",
    "sg:province":"ND",
    "wof:name":"United Rentals",
    "wof:placetype":"venue"
},
  "geometry": {"coordinates":[-96.85404,46.894337],"type":"Point"}
}