{
  "type": "Feature",
  "properties": {
    "iso:country":"US",
    "sg:address":"203 Towner Ave",
    "sg:city":"Larimore",
    "sg:classifiers":[
        {
            "category":"Shopping",
            "subcategory":"Pharmacy",
            "type":"Retail Goods"
        }
    ],
    "sg:phone":"+1 701 343 2461",
    "sg:postcode":"58251",
    "sg:province":"ND",
    "wof:name":"Larimore Drug & Gift",
    "wof:placetype":"venue"
},
  "geometry": {"coordinates":[-97.62364700000001,47.905223],"type":"Point"}
}