{
  "type": "Feature",
  "properties": {
    "iso:country":"US",
    "sg:address":"18 1st St E",
    "sg:city":"New Leipzig",
    "sg:classifiers":[
        {
            "category":"Government",
            "subcategory":"Office",
            "type":"Public Place"
        }
    ],
    "sg:phone":"+1 701 584 2006",
    "sg:postcode":"58562",
    "sg:province":"ND",
    "sg:tags":[
        "city"
    ],
    "wof:name":"New Leipzig City Hall",
    "wof:placetype":"venue"
},
  "geometry": {"coordinates":[-101.948134,46.374714],"type":"Point"}
}