{
  "type": "Feature",
  "properties": {
    "iso:country":"US",
    "sg:address":"1726 S Washington St",
    "sg:city":"Grand Forks",
    "sg:classifiers":[
        {
            "category":"Personal",
            "type":"Services"
        }
    ],
    "sg:phone":"+1 701 740 4511",
    "sg:postcode":"58201",
    "sg:province":"ND",
    "sg:tags":[
        "therapist",
        "massage"
    ],
    "wof:name":"Healing Hands Therapeutic Mssg",
    "wof:placetype":"venue"
},
  "geometry": {"coordinates":[-97.045587,47.902116],"type":"Point"}
}