{
  "type": "Feature",
  "properties": {
    "iso:country":"US",
    "sg:address":"628 5th St NW",
    "sg:city":"Valley City",
    "sg:classifiers":[
        {
            "category":"Wholesale",
            "subcategory":"Construction Materials",
            "type":"Manufacturing & Wholesale Goods"
        }
    ],
    "sg:phone":"+1 701 845 4293",
    "sg:postcode":"58072",
    "sg:province":"ND",
    "wof:name":"Murray Brothers",
    "wof:placetype":"venue"
},
  "geometry": {"coordinates":[-98.010982,46.927912],"type":"Point"}
}