{
  "type": "Feature",
  "properties": {
    "iso:country":"US",
    "sg:address":"695 6th St S",
    "sg:city":"Carrington",
    "sg:classifiers":[
        {
            "category":"Food & Beverages",
            "subcategory":"Specialty",
            "type":"Retail Goods"
        },
        {
            "category":"Wholesale",
            "subcategory":"Beer",
            "type":"Manufacturing & Wholesale Goods"
        }
    ],
    "sg:phone":"+1 701 652 2141",
    "sg:postcode":"58421",
    "sg:province":"ND",
    "sg:tags":[
        "water",
        "bulk",
        "company"
    ],
    "wof:name":"Central Distributing Company",
    "wof:placetype":"venue"
},
  "geometry": {"coordinates":[-99.120524,47.443787],"type":"Point"}
}