{
  "type": "Feature",
  "properties": {
    "iso:country":"US",
    "sg:address":"9 9th St S",
    "sg:city":"Fargo",
    "sg:classifiers":[
        {
            "category":"Government",
            "subcategory":"Office",
            "type":"Public Place"
        }
    ],
    "sg:phone":"+1 701 239 7141",
    "sg:postcode":"58103",
    "sg:province":"ND",
    "sg:tags":[
        "state",
        "resource"
    ],
    "wof:name":"Southeast Human Svc Ctr",
    "wof:placetype":"venue"
},
  "geometry": {"coordinates":[-96.79274700000001,46.8737],"type":"Point"}
}