{
  "type": "Feature",
  "properties": {
    "iso:country":"US",
    "sg:address":"5331 20th St NW",
    "sg:city":"Garrison",
    "sg:classifiers":[
        {
            "category":"Building & Trades",
            "subcategory":"Landscaping Services",
            "type":"Services"
        }
    ],
    "sg:phone":"+1 701 743 4304",
    "sg:postcode":"58540",
    "sg:province":"ND",
    "sg:tags":[
        "lawn",
        "garden"
    ],
    "wof:name":"Awn Services",
    "wof:placetype":"venue"
},
  "geometry": {"coordinates":[-101.743101,47.70295],"type":"Point"}
}