{
  "type": "Feature",
  "properties": {
    "iso:country":"US",
    "sg:address":"40105 Co Hwy 10",
    "sg:city":"Driscoll",
    "sg:classifiers":[
        {
            "category":"Freight",
            "type":"Transportation"
        }
    ],
    "sg:phone":"+1 701 387 4497",
    "sg:postcode":"58532",
    "sg:province":"ND",
    "sg:tags":[
        "trucking"
    ],
    "wof:name":"Simpson R Trucking",
    "wof:placetype":"venue"
},
  "geometry": {"coordinates":[-100.14287400000001,46.850846],"type":"Point"}
}