{
  "type": "Feature",
  "properties": {
    "iso:country":"US",
    "sg:address":"323 Main Ave",
    "sg:city":"Oakes",
    "sg:classifiers":[
        {
            "category":"Home & Garden",
            "subcategory":"Garden Supply",
            "type":"Retail Goods"
        }
    ],
    "sg:phone":"+1 701 742 2105",
    "sg:postcode":"58474",
    "sg:province":"SD",
    "wof:name":"Oakes Outdoor Power Sales",
    "wof:placetype":"venue"
},
  "geometry": {"coordinates":[-98.09543499999999,46.138949],"type":"Point"}
}