{
  "type": "Feature",
  "properties": {
    "iso:country":"US",
    "sg:address":"1215 8th St S",
    "sg:city":"Fargo",
    "sg:classifiers":[
        {
            "category":"Wholesale",
            "subcategory":"Vending Machines",
            "type":"Manufacturing & Wholesale Goods"
        }
    ],
    "sg:phone":"+1 701 252 8765",
    "sg:postcode":"58103",
    "sg:province":"ND",
    "sg:tags":[
        "operator"
    ],
    "wof:name":"Weber Vending",
    "wof:placetype":"venue"
},
  "geometry": {"coordinates":[-96.79199800000001,46.86174],"type":"Point"}
}