{
  "type": "Feature",
  "properties": {
    "iso:country":"US",
    "sg:address":"1214 2nd St S",
    "sg:city":"Carrington",
    "sg:classifiers":[
        {
            "category":"Building & Trades",
            "subcategory":"Construction",
            "type":"Services"
        }
    ],
    "sg:phone":"+1 701 652 2713",
    "sg:postcode":"58421",
    "sg:province":"ND",
    "sg:tags":[
        "excavation",
        "contractor"
    ],
    "wof:name":"Voglewede Excavating",
    "wof:placetype":"venue"
},
  "geometry": {"coordinates":[-99.13056,47.447448],"type":"Point"}
}