{
  "type": "Feature",
  "properties": {
    "addr:full":"954 10th Ave NE Valley City ND 58072",
    "addr:housenumber":"954",
    "addr:postcode":"58072",
    "addr:street":"10Th Ave Ne",
    "iso:country":"US",
    "sg:address":"954 10th Ave NE",
    "sg:city":"Valley City",
    "sg:classifiers":[
        {
            "category":"Real Estate",
            "subcategory":"Real Estate Operator",
            "type":"Services"
        }
    ],
    "sg:phone":"+1 701 845 2082",
    "sg:postcode":"58072",
    "sg:province":"ND",
    "sg:tags":[
        "property",
        "lessor"
    ],
    "wof:name":"Jack Egan",
    "wof:placetype":"venue"
},
  "geometry": {"coordinates":[-97.98910100000001,46.931767],"type":"Point"}
}