{
  "type": "Feature",
  "properties": {
    "iso:country":"US",
    "sg:address":"3910 25th St S",
    "sg:city":"Fargo",
    "sg:classifiers":[
        {
            "category":"Organizations",
            "subcategory":"Religious Organization",
            "type":"Services"
        }
    ],
    "sg:phone":"+1 701 232 2450",
    "sg:postcode":"58104",
    "sg:province":"ND",
    "wof:name":"Friendship Church",
    "wof:placetype":"venue"
},
  "geometry": {"coordinates":[-96.81934099999999,46.820333],"type":"Point"}
}