{
  "type": "Feature",
  "properties": {
    "iso:country":"US",
    "sg:address":"206 4th St",
    "sg:city":"Langdon",
    "sg:classifiers":[
        {
            "category":"Building & Trades",
            "subcategory":"Plumbing",
            "type":"Services"
        }
    ],
    "sg:phone":"+1 701 256 2138",
    "sg:postcode":"58249",
    "sg:province":"ND",
    "sg:tags":[
        "plumbing",
        "heating",
        "contractor"
    ],
    "wof:name":"Langdon Plbg Htg & Appls In",
    "wof:placetype":"venue"
},
  "geometry": {"coordinates":[-98.36988100000001,48.756962],"type":"Point"}
}