{
  "type": "Feature",
  "properties": {
    "addr:full":"102 N University Dr Fargo ND 58102",
    "addr:housenumber":"102",
    "addr:postcode":"58102",
    "addr:street":"N University Dr",
    "iso:country":"US",
    "sg:address":"102 N University Dr",
    "sg:city":"Fargo",
    "sg:classifiers":[
        {
            "category":"Retail",
            "subcategory":"Auto Repair",
            "type":"Services"
        }
    ],
    "sg:phone":"+1 701 237 5550",
    "sg:postcode":"58102",
    "sg:province":"ND",
    "sg:tags":[
        "general"
    ],
    "wof:name":"Adrians Autocare Center",
    "wof:placetype":"venue"
},
  "geometry": {"coordinates":[-96.79830699999999,46.877831],"type":"Point"}
}