{
  "type": "Feature",
  "properties": {
    "addr:full":"1433 7th St S Fargo ND 58103",
    "addr:housenumber":"1433",
    "addr:postcode":"58103",
    "addr:street":"7Th St S",
    "iso:country":"US",
    "sg:address":"1433 7th St S",
    "sg:city":"Fargo",
    "sg:classifiers":[
        {
            "category":"Professional",
            "subcategory":"Business Services",
            "type":"Services"
        }
    ],
    "sg:phone":"+1 701 232 4938",
    "sg:postcode":"58103",
    "sg:province":"ND",
    "wof:name":"Petry Enterprises Inc",
    "wof:placetype":"venue"
},
  "geometry": {"coordinates":[-96.790543,46.858302],"type":"Point"}
}