{
  "type": "Feature",
  "properties": {
    "addr:full":"1330 23rd St S Fargo ND 58103",
    "addr:housenumber":"1330",
    "addr:postcode":"58103",
    "addr:street":"23Rd St S",
    "iso:country":"US",
    "sg:address":"1330 23rd St S",
    "sg:city":"Fargo",
    "sg:classifiers":[
        {
            "category":"Professional",
            "subcategory":"Management & Consulting",
            "type":"Services"
        }
    ],
    "sg:phone":"+1 701 297 7908",
    "sg:postcode":"58103",
    "sg:province":"ND",
    "wof:name":"Internatl Assoc Impct Develp",
    "wof:placetype":"venue"
},
  "geometry": {"coordinates":[-96.81698,46.860848],"type":"Point"}
}