{
  "type": "Feature",
  "properties": {
    "iso:country":"US",
    "sg:address":"106 E 6th St",
    "sg:city":"Grafton",
    "sg:classifiers":[
        {
            "category":"Building & Trades",
            "subcategory":"Plumbing",
            "type":"Services"
        }
    ],
    "sg:phone":"+1 701 352 9303",
    "sg:postcode":"58237",
    "sg:province":"ND",
    "sg:tags":[
        "plumbing",
        "contractor"
    ],
    "wof:name":"Northland Plumbing & Heating",
    "wof:placetype":"venue"
},
  "geometry": {"coordinates":[-97.40869000000001,48.418537],"type":"Point"}
}