{
  "type": "Feature",
  "properties": {
    "addr:full":"12 Central Ave NE Garrison ND 58540",
    "addr:housenumber":"12",
    "addr:postcode":"58540",
    "addr:street":"Central Ave Ne",
    "iso:country":"US",
    "sg:address":"12 Central Ave NE",
    "sg:city":"Garrison",
    "sg:classifiers":[
        {
            "category":"Retail",
            "subcategory":"Repair Shop",
            "type":"Services"
        }
    ],
    "sg:phone":"+1 701 463 2588",
    "sg:postcode":"58540",
    "sg:province":"ND",
    "sg:tags":[
        "upholsterer"
    ],
    "wof:name":"Brenda's Upholstery",
    "wof:placetype":"venue"
},
  "geometry": {"coordinates":[-101.41728000000001,47.651363],"type":"Point"}
}