{
  "type": "Feature",
  "properties": {
    "addr:full":"13542 65th St NE Pisek ND 58273",
    "addr:housenumber":"13542",
    "addr:postcode":"58273",
    "addr:street":"65Th St Ne",
    "iso:country":"US",
    "sg:address":"13542 65th St NE",
    "sg:city":"Pisek",
    "sg:classifiers":[
        {
            "category":"Farming",
            "subcategory":"Farm",
            "type":"Manufacturing & Wholesale Goods"
        }
    ],
    "sg:phone":"+1 701 284 6990",
    "sg:postcode":"58273",
    "sg:province":"ND",
    "sg:tags":[
        "crop",
        "general"
    ],
    "wof:name":"Harry Schildberger",
    "wof:placetype":"venue"
},
  "geometry": {"coordinates":[-97.699648,48.354254],"type":"Point"}
}