{
  "type": "Feature",
  "properties": {
    "addr:full":"42 1st Ave NE Mayville ND 58257",
    "addr:housenumber":"42",
    "addr:postcode":"58257",
    "addr:street":"1St Ave Ne",
    "iso:country":"US",
    "sg:address":"42 1st Ave NE",
    "sg:city":"Mayville",
    "sg:classifiers":[
        {
            "category":"Banks & Credit Unions",
            "subcategory":"Investment Brokerage",
            "type":"Services"
        }
    ],
    "sg:phone":"+1 701 788 9118",
    "sg:postcode":"58257",
    "sg:province":"ND",
    "sg:tags":[
        "commodity",
        "dealer",
        "contract"
    ],
    "wof:name":"OBrien Seed Inc",
    "wof:placetype":"venue"
},
  "geometry": {"coordinates":[-97.325228,47.501071],"type":"Point"}
}