{
  "type": "Feature",
  "properties": {
    "iso:country":"US",
    "sg:address":"101 S University Dr",
    "sg:city":"Fargo",
    "sg:classifiers":[
        {
            "category":"Health Services",
            "subcategory":"Nursing And Care Facility",
            "type":"Services"
        }
    ],
    "sg:phone":"+1 701 239 3424",
    "sg:postcode":"58103",
    "sg:province":"ND",
    "sg:tags":[
        "home",
        "retirement",
        "community"
    ],
    "wof:name":"Bethany Kinder House",
    "wof:placetype":"venue"
},
  "geometry": {"coordinates":[-96.79827400000001,46.873508],"type":"Point"}
}