{
  "type": "Feature",
  "properties": {
    "addr:full":"301 Main St S Minot ND 58701",
    "addr:housenumber":"301",
    "addr:postcode":"58701",
    "addr:street":"Main St S",
    "iso:country":"US",
    "sg:address":"301 Main St S",
    "sg:city":"Minot",
    "sg:classifiers":[
        {
            "category":"Organizations",
            "subcategory":"Religious Organization",
            "type":"Services"
        }
    ],
    "sg:phone":"+1 701 839 1037",
    "sg:postcode":"58701",
    "sg:province":"ND",
    "sg:tags":[
        "church"
    ],
    "wof:name":"All Saints Episcopal Church",
    "wof:placetype":"venue"
},
  "geometry": {"coordinates":[-101.29295500000001,48.234216],"type":"Point"}
}