{
  "type": "Feature",
  "properties": {
    "addr:full":"907 10th St NE Beulah ND 58523",
    "addr:housenumber":"907",
    "addr:postcode":"58523",
    "addr:street":"10Th St Ne",
    "iso:country":"US",
    "sg:address":"907 10th St NE",
    "sg:city":"Beulah",
    "sg:classifiers":[
        {
            "category":"Organizations",
            "subcategory":"Religious Organization",
            "type":"Services"
        }
    ],
    "sg:phone":"+1 701 873 5066",
    "sg:postcode":"58523",
    "sg:province":"ND",
    "sg:tags":[
        "church"
    ],
    "wof:name":"Churches & Parsonages Prsng",
    "wof:placetype":"venue"
},
  "geometry": {"coordinates":[-101.767605,47.273357],"type":"Point"}
}