{
  "type": "Feature",
  "properties": {
    "iso:country":"US",
    "sg:address":"211 1st Ave N",
    "sg:city":"Jamestown",
    "sg:classifiers":[
        {
            "category":"Personal",
            "subcategory":"Beauty Salon",
            "type":"Services"
        }
    ],
    "sg:phone":"+1 701 252 0077",
    "sg:postcode":"58401",
    "sg:province":"ND",
    "wof:name":"Mane Snippers",
    "wof:placetype":"venue"
},
  "geometry": {"coordinates":[-98.70859900000001,46.909948],"type":"Point"}
}