{
  "type": "Feature",
  "properties": {
    "iso:country":"US",
    "sg:address":"504 Franklin Ave",
    "sg:city":"Harvey",
    "sg:classifiers":[
        {
            "category":"Building & Trades",
            "subcategory":"Construction",
            "type":"Services"
        }
    ],
    "sg:phone":"+1 701 324 2608",
    "sg:postcode":"58341",
    "sg:province":"ND",
    "sg:tags":[
        "house"
    ],
    "wof:name":"Kellers Building & Remodeling",
    "wof:placetype":"venue"
},
  "geometry": {"coordinates":[-99.924851,47.770242],"type":"Point"}
}