{
  "type": "Feature",
  "properties": {
    "iso:country":"US",
    "sg:address":"33 Main St W",
    "sg:city":"Hazen",
    "sg:classifiers":[
        {
            "category":"Retail",
            "subcategory":"Portrait Studio",
            "type":"Services"
        }
    ],
    "sg:phone":"+1 701 748 5656",
    "sg:postcode":"58545",
    "sg:province":"ND",
    "sg:tags":[
        "photographer"
    ],
    "wof:name":"Natural Impressions Photo",
    "wof:placetype":"venue"
},
  "geometry": {"coordinates":[-101.624419,47.294345],"type":"Point"}
}