{
  "type": "Feature",
  "properties": {
    "iso:country":"US",
    "sg:address":"1600 2nd Ave SW",
    "sg:city":"Minot",
    "sg:classifiers":[
        {
            "category":"Food & Beverages",
            "subcategory":"Groceries & Convenience Stores",
            "type":"Retail Goods"
        }
    ],
    "sg:phone":"+1 701 839 7934",
    "sg:postcode":"58701",
    "sg:province":"ND",
    "sg:tags":[
        "grocer"
    ],
    "wof:name":"Miracle Mart",
    "wof:placetype":"venue"
},
  "geometry": {"coordinates":[-101.317757,48.234148],"type":"Point"}
}