{
  "type": "Feature",
  "properties": {
    "iso:country":"US",
    "sg:address":"604 Elm Ave",
    "sg:city":"Wyndmere",
    "sg:classifiers":[
        {
            "category":"Shopping",
            "subcategory":"Florist",
            "type":"Retail Goods"
        },
        {
            "category":"Professional",
            "subcategory":"Art Services",
            "type":"Services"
        }
    ],
    "sg:phone":"+1 701 439 2382",
    "sg:postcode":"58081",
    "sg:province":"ND",
    "sg:tags":[
        "photography",
        "commercial"
    ],
    "wof:name":"Virginia's Photos & Flowers",
    "wof:placetype":"venue"
},
  "geometry": {"coordinates":[-97.13501599999999,46.262794],"type":"Point"}
}