{
  "type": "Feature",
  "properties": {
    "iso:country":"US",
    "sg:address":"103 14th St W",
    "sg:city":"Dickinson",
    "sg:classifiers":[
        {
            "category":"Travel",
            "subcategory":"Hotels & Motels",
            "type":"Entertainment"
        }
    ],
    "sg:phone":"+1 701 456 8000",
    "sg:postcode":"58601",
    "sg:province":"ND",
    "wof:name":"Holiday Inn Express",
    "wof:placetype":"venue"
},
  "geometry": {"coordinates":[-102.80318699999999,46.897228],"type":"Point"}
}