{
  "type": "Feature",
  "properties": {
    "addr:full":"15382 68th St NE Grafton ND 58237",
    "addr:housenumber":"15382",
    "addr:postcode":"58237",
    "addr:street":"68Th St Ne",
    "iso:country":"US",
    "sg:address":"15382 68th St NE",
    "sg:city":"Grafton",
    "sg:classifiers":[
        {
            "category":"Farming",
            "subcategory":"Farm",
            "type":"Manufacturing & Wholesale Goods"
        }
    ],
    "sg:phone":"+1 701 352 1557",
    "sg:postcode":"58237",
    "sg:province":"ND",
    "sg:tags":[
        "crop",
        "general"
    ],
    "wof:name":"Kevin Olmstead",
    "wof:placetype":"venue"
},
  "geometry": {"coordinates":[-97.325141,48.397873],"type":"Point"}
}