{
  "type": "Feature",
  "properties": {
    "iso:country":"US",
    "sg:address":"1708 22nd Ave S",
    "sg:city":"Grand Forks",
    "sg:classifiers":[
        {
            "category":"Insurance",
            "subcategory":"Insurance Agent",
            "type":"Services"
        }
    ],
    "sg:phone":"+1 701 772 7103",
    "sg:postcode":"58201",
    "sg:province":"ND",
    "wof:name":"Life Agents Inc",
    "wof:placetype":"venue"
},
  "geometry": {"coordinates":[-97.055762,47.898612],"type":"Point"}
}