{
  "type": "Feature",
  "properties": {
    "addr:full":"10150 37th Ave NW Mohall ND 58761",
    "addr:housenumber":"10150",
    "addr:postcode":"58761",
    "addr:street":"37Th Ave Nw",
    "iso:country":"US",
    "sg:address":"10150 37th Ave NW",
    "sg:city":"Mohall",
    "sg:classifiers":[
        {
            "category":"Mining & Drilling",
            "type":"Manufacturing & Wholesale Goods"
        }
    ],
    "sg:phone":"+1 701 756 6852",
    "sg:postcode":"58761",
    "sg:province":"ND",
    "sg:tags":[
        "field",
        "oil"
    ],
    "wof:name":"MDM Inc-Power Tongs-Casing",
    "wof:placetype":"venue"
},
  "geometry": {"coordinates":[-101.51843599999999,48.893073],"type":"Point"}
}