{
  "type": "Feature",
  "properties": {
    "iso:country":"US",
    "sg:address":"322 2nd St NW",
    "sg:city":"Valley City",
    "sg:classifiers":[
        {
            "category":"Retail",
            "subcategory":"Auto Repair",
            "type":"Services"
        }
    ],
    "sg:phone":"+1 701 845 0999",
    "sg:postcode":"58072",
    "sg:province":"ND",
    "sg:tags":[
        "repairing",
        "automobile"
    ],
    "wof:name":"Wade's Service Ctr",
    "wof:placetype":"venue"
},
  "geometry": {"coordinates":[-98.00636,46.924243],"type":"Point"}
}