{
  "type": "Feature",
  "properties": {
    "iso:country":"US",
    "sg:address":"404 25th St S",
    "sg:city":"Fargo",
    "sg:classifiers":[
        {
            "category":"Autos & Motor Vehicles",
            "subcategory":"Automobile Sales",
            "type":"Retail Goods"
        },
        {
            "category":"Retail",
            "subcategory":"Auto Repair",
            "type":"Services"
        }
    ],
    "sg:phone":"+1 701 235 1937",
    "sg:postcode":"58103",
    "sg:province":"ND",
    "sg:tags":[
        "body",
        "car",
        "new",
        "windshield",
        "painting",
        "repairing"
    ],
    "sg:website":"http://www.qualityautobodyshop.com",
    "wof:name":"Quality Auto Body Shop",
    "wof:placetype":"venue"
},
  "geometry": {"coordinates":[-96.819478,46.871274],"type":"Point"}
}