{
  "type": "Feature",
  "properties": {
    "iso:country":"US",
    "sg:address":"701 Thompson St",
    "sg:city":"Bottineau",
    "sg:classifiers":[
        {
            "category":"Building & Trades",
            "subcategory":"Construction",
            "type":"Services"
        }
    ],
    "sg:phone":"+1 701 228 2681",
    "sg:postcode":"58318",
    "sg:province":"ND",
    "sg:tags":[
        "contractor"
    ],
    "wof:name":"Ron Beckman Masonry",
    "wof:placetype":"venue"
},
  "geometry": {"coordinates":[-100.444346,48.825239],"type":"Point"}
}