{
  "type": "Feature",
  "properties": {
    "iso:country":"US",
    "sg:address":"214 E Thayer Ave",
    "sg:city":"Bismarck",
    "sg:classifiers":[
        {
            "category":"Social Services",
            "subcategory":"Child Care",
            "type":"Services"
        }
    ],
    "sg:phone":"+1 701 258 7490",
    "sg:postcode":"58501",
    "sg:province":"ND",
    "wof:name":"Infant Toddler Child Care Ctr",
    "wof:placetype":"venue"
},
  "geometry": {"coordinates":[-100.787781,46.807636],"type":"Point"}
}