{
  "type": "Feature",
  "properties": {
    "iso:country":"US",
    "sg:address":"503 E Main St",
    "sg:city":"Mandan",
    "sg:classifiers":[
        {
            "category":"Health Services",
            "subcategory":"Chiropractor",
            "type":"Services"
        }
    ],
    "sg:phone":"+1 701 663 3380",
    "sg:postcode":"58554",
    "sg:province":"ND",
    "wof:name":"Schwartz Family Chiropractic",
    "wof:placetype":"venue"
},
  "geometry": {"coordinates":[-100.882187,46.827374],"type":"Point"}
}