{
  "type": "Feature",
  "properties": {
    "addr:full":"116 E Ave B Bismarck ND 58501",
    "addr:housenumber":"116",
    "addr:postcode":"58501",
    "addr:street":"E Ave B",
    "iso:country":"US",
    "sg:address":"116 E Ave B",
    "sg:city":"Bismarck",
    "sg:classifiers":[
        {
            "category":"Professional",
            "subcategory":"Accounting & Tax Preparation",
            "type":"Services"
        }
    ],
    "sg:phone":"+1 701 734 6657",
    "sg:postcode":"58501",
    "sg:province":"ND",
    "sg:tags":[
        "return"
    ],
    "wof:name":"McCullough Family Ltd Par",
    "wof:placetype":"venue"
},
  "geometry": {"coordinates":[-100.789259,46.810785],"type":"Point"}
}