{
  "type": "Feature",
  "properties": {
    "addr:full":"102 128th Ave NW Minot ND 58703",
    "addr:housenumber":"102",
    "addr:postcode":"58703",
    "addr:street":"128Th Ave Nw",
    "iso:country":"US",
    "sg:address":"102 128th Ave NW",
    "sg:city":"Minot",
    "sg:classifiers":[
        {
            "category":"Building & Trades",
            "subcategory":"Landscaping Services",
            "type":"Services"
        }
    ],
    "sg:phone":"+1 701 728 6949",
    "sg:postcode":"58703",
    "sg:province":"ND",
    "sg:tags":[
        "landscape",
        "contractor"
    ],
    "wof:name":"Novak's",
    "wof:placetype":"venue"
},
  "geometry": {"coordinates":[-101.29837000000001,48.371675],"type":"Point"}
}