{
  "type": "Feature",
  "properties": {
    "addr:full":"2534 17th Ave S Grand Forks ND 58201",
    "addr:housenumber":"2534",
    "addr:postcode":"58201",
    "addr:street":"17Th Ave S",
    "iso:country":"US",
    "sg:address":"2534 17th Ave S",
    "sg:city":"Grand Forks",
    "sg:classifiers":[
        {
            "category":"Health Services",
            "subcategory":"Doctor",
            "type":"Services"
        }
    ],
    "sg:phone":"+1 701 775 3696",
    "sg:postcode":"58201",
    "sg:province":"ND",
    "sg:tags":[
        "medical"
    ],
    "wof:name":"Gary D Haynie MD",
    "wof:placetype":"venue"
},
  "geometry": {"coordinates":[-97.063142,47.904025],"type":"Point"}
}