{
  "type": "Feature",
  "properties": {
    "addr:full":"530 32nd Ave S Grand Forks ND 58201",
    "addr:housenumber":"530",
    "addr:postcode":"58201",
    "addr:street":"32Nd Ave S",
    "iso:country":"US",
    "sg:address":"530 32nd Ave S",
    "sg:city":"Grand Forks",
    "sg:classifiers":[
        {
            "category":"Professional",
            "subcategory":"Management & Consulting",
            "type":"Services"
        }
    ],
    "sg:phone":"+1 701 775 9342",
    "sg:postcode":"58201",
    "sg:province":"ND",
    "sg:tags":[
        "technical",
        "assistance"
    ],
    "wof:name":"Tiegs Computer Services",
    "wof:placetype":"venue"
},
  "geometry": {"coordinates":[-97.035832,47.88948],"type":"Point"}
}