{
  "type": "Feature",
  "properties": {
    "iso:country":"US",
    "sg:address":"214 W Main St",
    "sg:city":"Ashley",
    "sg:classifiers":[
        {
            "category":"Professional",
            "subcategory":"Lawyer & Legal Services",
            "type":"Services"
        }
    ],
    "sg:phone":"+1 701 288 3618",
    "sg:postcode":"58413",
    "sg:province":"ND",
    "sg:tags":[
        "attorney"
    ],
    "wof:name":"Gross Law Office",
    "wof:placetype":"venue"
},
  "geometry": {"coordinates":[-99.375647,46.034553],"type":"Point"}
}