{
  "type": "Feature",
  "properties": {
    "iso:country":"US",
    "sg:address":"1 Main St",
    "sg:city":"Carrington",
    "sg:classifiers":[
        {
            "category":"Health Services",
            "subcategory":"Nursing And Care Facility",
            "type":"Services"
        }
    ],
    "sg:phone":"+1 701 652 3117",
    "sg:postcode":"58421",
    "sg:province":"ND",
    "sg:tags":[
        "home",
        "convalescent"
    ],
    "wof:name":"Golden Acres Manor",
    "wof:placetype":"venue"
},
  "geometry": {"coordinates":[-99.11204499999999,47.449552],"type":"Point"}
}