{
  "type": "Feature",
  "properties": {
    "iso:country":"US",
    "sg:address":"504 Main Ave",
    "sg:city":"Oakes",
    "sg:classifiers":[
        {
            "category":"Food & Beverages",
            "subcategory":"Bakery",
            "type":"Retail Goods"
        }
    ],
    "sg:phone":"+1 701 742 2490",
    "sg:postcode":"58474",
    "sg:province":"ND",
    "sg:tags":[
        "baker"
    ],
    "wof:name":"Kelsen's Bakery",
    "wof:placetype":"venue"
},
  "geometry": {"coordinates":[-98.093418,46.138795],"type":"Point"}
}