{
  "type": "Feature",
  "properties": {
    "addr:full":"105 4th Ave SW Rugby ND 58368",
    "addr:housenumber":"105",
    "addr:postcode":"58368",
    "addr:street":"4Th Ave Sw",
    "iso:country":"US",
    "sg:address":"105 4th Ave SW",
    "sg:city":"Rugby",
    "sg:classifiers":[
        {
            "category":"Wholesale",
            "subcategory":"Farm Supplies",
            "type":"Manufacturing & Wholesale Goods"
        }
    ],
    "sg:phone":"+1 701 776 5221",
    "sg:postcode":"58368",
    "sg:province":"ND",
    "wof:name":"C H S",
    "wof:placetype":"venue"
},
  "geometry": {"coordinates":[-100.000778,48.370804],"type":"Point"}
}