{
  "type": "Feature",
  "properties": {
    "iso:country":"US",
    "sg:address":"408 Main St",
    "sg:city":"Nome",
    "sg:classifiers":[
        {
            "category":"Government",
            "subcategory":"Post Office",
            "type":"Public Place"
        }
    ],
    "sg:phone":"+1 701 924 8264",
    "sg:postcode":"58062",
    "sg:province":"ND",
    "sg:tags":[
        "postal",
        "us"
    ],
    "wof:name":"US Post Office",
    "wof:placetype":"venue"
},
  "geometry": {"coordinates":[-97.810641,46.677764],"type":"Point"}
}