{
  "type": "Feature",
  "properties": {
    "addr:full":"18 Main St W Hazen ND 58545",
    "addr:housenumber":"18",
    "addr:postcode":"58545",
    "addr:street":"Main St W",
    "iso:country":"US",
    "sg:address":"18 Main St W",
    "sg:city":"Hazen",
    "sg:classifiers":[
        {
            "category":"Home & Garden",
            "subcategory":"Carpets & Floor Coverings",
            "type":"Retail Goods"
        }
    ],
    "sg:phone":"+1 701 748 2737",
    "sg:postcode":"58545",
    "sg:province":"ND",
    "sg:tags":[
        "dealer",
        "rug"
    ],
    "wof:name":"Speidel's",
    "wof:placetype":"venue"
},
  "geometry": {"coordinates":[-101.624588,47.294496],"type":"Point"}
}