{
  "type": "Feature",
  "properties": {
    "iso:country":"US",
    "sg:address":"1900 S Washington St",
    "sg:city":"Grand Forks",
    "sg:classifiers":[
        {
            "category":"Food & Beverages",
            "subcategory":"Groceries & Convenience Stores",
            "type":"Retail Goods"
        }
    ],
    "sg:phone":"+1 701 772 2299",
    "sg:postcode":"58201",
    "sg:province":"ND",
    "wof:name":"Groceries & Gifts",
    "wof:placetype":"venue"
},
  "geometry": {"coordinates":[-97.04553,47.900842],"type":"Point"}
}