{
  "type": "Feature",
  "properties": {
    "iso:country":"US",
    "sg:address":"10845 53rd Ave NW",
    "sg:city":"Sherwood",
    "sg:phone":"+1 701 459 2768",
    "sg:postcode":"58782",
    "sg:province":"ND",
    "sg:tags":[
        "farm",
        "wheat"
    ],
    "wof:name":"Northland Farms",
    "wof:placetype":"venue"
},
  "geometry": {"coordinates":[-101.868872,48.98195],"type":"Point"}
}