{
  "type": "Feature",
  "properties": {
    "iso:country":"US",
    "sg:address":"6435 17th Ave NE",
    "sg:city":"Bismarck",
    "sg:classifiers":[
        {
            "category":"Building & Trades",
            "subcategory":"Construction",
            "type":"Services"
        }
    ],
    "sg:phone":"+1 701 222 8909",
    "sg:postcode":"58501",
    "sg:province":"ND",
    "sg:tags":[
        "house"
    ],
    "wof:name":"Michael Baumgartner Cnstr",
    "wof:placetype":"venue"
},
  "geometry": {"coordinates":[-100.688969,46.823488],"type":"Point"}
}