{
  "type": "Feature",
  "properties": {
    "iso:country":"US",
    "sg:address":"1705 45th St S",
    "sg:city":"Fargo",
    "sg:classifiers":[
        {
            "category":"Restaurant",
            "type":"Food & Drink"
        }
    ],
    "sg:menulink":"http://www.allmenus.com/nd/fargo/87116-little-caesars-pizza/menu/",
    "sg:phone":"+1 701 492 4510",
    "sg:postcode":"58103",
    "sg:province":"ND",
    "sg:tags":[
        "american",
        "pizza"
    ],
    "wof:name":"Little Caesar's Pizza",
    "wof:placetype":"venue"
},
  "geometry": {"coordinates":[-96.862026,46.853747],"type":"Point"}
}