{
  "type": "Feature",
  "properties": {
    "addr:full":"407 Main St Edmore ND 58330",
    "addr:housenumber":"407",
    "addr:postcode":"58330",
    "addr:street":"Main St",
    "iso:country":"US",
    "sg:address":"407 Main St",
    "sg:city":"Edmore",
    "sg:classifiers":[
        {
            "category":"Personal",
            "subcategory":"Beauty Salon",
            "type":"Services"
        }
    ],
    "sg:phone":"+1 701 644 2250",
    "sg:postcode":"58330",
    "sg:province":"ND",
    "wof:name":"Linda's Beauty Shop",
    "wof:placetype":"venue"
},
  "geometry": {"coordinates":[-98.454358,48.411832],"type":"Point"}
}