{
  "type": "Feature",
  "properties": {
    "iso:country":"US",
    "sg:address":"2016 N 12th St",
    "sg:city":"Bismarck",
    "sg:classifiers":[
        {
            "category":"Home & Garden",
            "subcategory":"Building Materials",
            "type":"Retail Goods"
        }
    ],
    "sg:phone":"+1 701 222 3171",
    "sg:postcode":"58501",
    "sg:province":"ND",
    "sg:tags":[
        "paint",
        "coating",
        "supply"
    ],
    "wof:name":"Columbia Paint & Coatings",
    "wof:placetype":"venue"
},
  "geometry": {"coordinates":[-100.77346,46.829196],"type":"Point"}
}