{
  "type": "Feature",
  "properties": {
    "iso:country":"US",
    "sg:address":"1800 Commerce Dr",
    "sg:city":"Bismarck",
    "sg:classifiers":[
        {
            "category":"Organizations",
            "subcategory":"Labor Organization",
            "type":"Services"
        }
    ],
    "sg:phone":"+1 701 222 2514",
    "sg:postcode":"58501",
    "sg:province":"ND",
    "wof:name":"Systems Council U-13 IBEW",
    "wof:placetype":"venue"
},
  "geometry": {"coordinates":[-100.735021,46.826086],"type":"Point"}
}