{
  "type": "Feature",
  "properties": {
    "iso:country":"US",
    "sg:address":"35 State Ave N",
    "sg:city":"Dickinson",
    "sg:classifiers":[
        {
            "category":"Retail",
            "subcategory":"Repair Shop",
            "type":"Services"
        }
    ],
    "sg:phone":"+1 701 225 9547",
    "sg:postcode":"58601",
    "sg:province":"ND",
    "sg:tags":[
        "engaged",
        "welding"
    ],
    "wof:name":"D & B Welding",
    "wof:placetype":"venue"
},
  "geometry": {"coordinates":[-102.81096599999999,46.879837],"type":"Point"}
}