{
  "type": "Feature",
  "properties": {
    "iso:country":"US",
    "sg:address":"515 1st Ave N",
    "sg:city":"Fargo",
    "sg:classifiers":[
        {
            "category":"Travel",
            "subcategory":"Hotels & Motels",
            "type":"Entertainment"
        }
    ],
    "sg:phone":"+1 701 298 0099",
    "sg:postcode":"58102",
    "sg:province":"ND",
    "wof:name":"Donaldson Hotel",
    "wof:placetype":"venue"
},
  "geometry": {"coordinates":[-96.787539,46.877012],"type":"Point"}
}