{
  "type": "Feature",
  "properties": {
    "iso:country":"US",
    "sg:address":"2020 46th Ave SE",
    "sg:city":"Mandan",
    "sg:classifiers":[
        {
            "category":"Wholesale",
            "subcategory":"Auto Parts",
            "type":"Manufacturing & Wholesale Goods"
        }
    ],
    "sg:phone":"+1 701 250 9391",
    "sg:postcode":"58554",
    "sg:province":"ND",
    "wof:name":"Chip Pro",
    "wof:placetype":"venue"
},
  "geometry": {"coordinates":[-100.830056,46.806982],"type":"Point"}
}