{
  "type": "Feature",
  "properties": {
    "iso:country":"US",
    "sg:address":"601 Main Ave",
    "sg:city":"Oakes",
    "sg:classifiers":[
        {
            "category":"Banks & Credit Unions",
            "subcategory":"Investment Brokerage",
            "type":"Services"
        }
    ],
    "sg:phone":"+1 701 742 2440",
    "sg:postcode":"58474",
    "sg:province":"ND",
    "sg:tags":[
        "security"
    ],
    "wof:name":"Prime Vest Financial Services",
    "wof:placetype":"venue"
},
  "geometry": {"coordinates":[-98.091949,46.138861],"type":"Point"}
}