{
  "type": "Feature",
  "properties": {
    "iso:country":"US",
    "sg:address":"814 Main St W",
    "sg:city":"Mayville",
    "sg:classifiers":[
        {
            "category":"Organizations",
            "subcategory":"Religious Organization",
            "type":"Services"
        }
    ],
    "sg:phone":"+1 701 786 4181",
    "sg:postcode":"58257",
    "sg:province":"ND",
    "wof:name":"Riverside Evang Free Church",
    "wof:placetype":"venue"
},
  "geometry": {"coordinates":[-97.344784,47.498553],"type":"Point"}
}