{
  "type": "Feature",
  "properties": {
    "iso:country":"US",
    "sg:address":"122 2nd Ave W",
    "sg:city":"Dickinson",
    "sg:classifiers":[
        {
            "category":"Recreation",
            "type":"Entertainment"
        }
    ],
    "sg:phone":"+1 701 225 9412",
    "sg:postcode":"58601",
    "sg:province":"ND",
    "sg:tags":[
        "parks"
    ],
    "wof:name":"Dickinson Parks & Recreation",
    "wof:placetype":"venue"
},
  "geometry": {"coordinates":[-102.788248,46.880187],"type":"Point"}
}