{
  "type": "Feature",
  "properties": {
    "addr:full":"308 7th St N Wilton ND 58579",
    "addr:housenumber":"308",
    "addr:postcode":"58579",
    "addr:street":"7Th St N",
    "iso:country":"US",
    "sg:address":"308 7th St N",
    "sg:city":"Wilton",
    "sg:classifiers":[
        {
            "category":"Freight",
            "type":"Transportation"
        }
    ],
    "sg:phone":"+1 701 734 6455",
    "sg:postcode":"58579",
    "sg:province":"ND",
    "sg:tags":[
        "distance",
        "carrier",
        "long",
        "contract",
        "common"
    ],
    "wof:name":"Hedstrom Truck Line Denis",
    "wof:placetype":"venue"
},
  "geometry": {"coordinates":[-100.79198,47.161001],"type":"Point"}
}