{
  "type": "Feature",
  "properties": {
    "addr:full":"2611 Old Red Trl Mandan ND 58554",
    "addr:housenumber":"2611",
    "addr:postcode":"58554",
    "addr:street":"Old Red Trl",
    "iso:country":"US",
    "sg:address":"2611 Old Red Trl",
    "sg:city":"Mandan",
    "sg:classifiers":[
        {
            "category":"Travel",
            "subcategory":"Hotels & Motels",
            "type":"Entertainment"
        }
    ],
    "sg:phone":"+1 701 663 7401",
    "sg:postcode":"58554",
    "sg:province":"ND",
    "wof:name":"Best Western",
    "wof:placetype":"venue"
},
  "geometry": {"coordinates":[-100.922174,46.854932],"type":"Point"}
}