{
  "type": "Feature",
  "properties": {
    "addr:full":"101 2nd St SE Rugby ND 58368",
    "addr:housenumber":"101",
    "addr:postcode":"58368",
    "addr:street":"2Nd St Se",
    "iso:country":"US",
    "sg:address":"101 2nd St SE",
    "sg:city":"Rugby",
    "sg:classifiers":[
        {
            "category":"Restaurant",
            "type":"Food & Drink"
        }
    ],
    "sg:phone":"+1 701 776 6233",
    "sg:postcode":"58368",
    "sg:province":"ND",
    "sg:tags":[
        "parlor",
        "ice",
        "cream"
    ],
    "sg:website":"www.dairyqueen.com",
    "wof:name":"Dairy Queen",
    "wof:placetype":"venue"
},
  "geometry": {"coordinates":[-99.996106,48.368694],"type":"Point"}
}