{
  "type": "Feature",
  "properties": {
    "iso:country":"US",
    "sg:address":"1841 37th St NE",
    "sg:city":"Larimore",
    "sg:classifiers":[
        {
            "category":"Government",
            "subcategory":"Office",
            "type":"Public Place"
        }
    ],
    "sg:phone":"+1 701 343 2096",
    "sg:postcode":"58251",
    "sg:province":"ND",
    "wof:name":"Game Warden",
    "wof:placetype":"venue"
},
  "geometry": {"coordinates":[-97.623912,47.94072],"type":"Point"}
}