{
  "type": "Feature",
  "properties": {
    "iso:country":"US",
    "sg:address":"1958 Oregon Dr",
    "sg:city":"Bismarck",
    "sg:classifiers":[
        {
            "category":"Real Estate",
            "subcategory":"Real Estate Operator",
            "type":"Services"
        }
    ],
    "sg:phone":"+1 701 258 3694",
    "sg:postcode":"58503",
    "sg:province":"ND",
    "sg:tags":[
        "building",
        "nonresidential"
    ],
    "wof:name":"M&M Properties LLP",
    "wof:placetype":"venue"
},
  "geometry": {"coordinates":[-100.762491,46.841036],"type":"Point"}
}