{
  "type": "Feature",
  "properties": {
    "addr:full":"3217 Fiechtner Dr Fargo ND 58103",
    "addr:housenumber":"3217",
    "addr:postcode":"58103",
    "addr:street":"Fiechtner Dr",
    "iso:country":"US",
    "sg:address":"3217 Fiechtner Dr",
    "sg:city":"Fargo",
    "sg:classifiers":[
        {
            "category":"Social Services",
            "type":"Services"
        }
    ],
    "sg:phone":"+1 701 237 9040",
    "sg:postcode":"58103",
    "sg:province":"ND",
    "wof:name":"Life Career Options",
    "wof:placetype":"venue"
},
  "geometry": {"coordinates":[-96.831006,46.865252],"type":"Point"}
}