{
  "type": "Feature",
  "properties": {
    "addr:full":"12505 52nd St SE Nome ND 58062",
    "addr:housenumber":"12505",
    "addr:postcode":"58062",
    "addr:street":"52Nd St Se",
    "iso:country":"US",
    "sg:address":"12505 52nd St SE",
    "sg:city":"Nome",
    "sg:classifiers":[
        {
            "category":"Organizations",
            "subcategory":"Religious Organization",
            "type":"Services"
        }
    ],
    "sg:phone":"+1 701 924 8215",
    "sg:postcode":"58062",
    "sg:province":"ND",
    "sg:tags":[
        "church"
    ],
    "wof:name":"St Paul's Lutheran Church",
    "wof:placetype":"venue"
},
  "geometry": {"coordinates":[-97.828356,46.659093],"type":"Point"}
}