{
  "type": "Feature",
  "properties": {
    "iso:country":"US",
    "sg:address":"2935 133rd Ave SE",
    "sg:city":"Tower City",
    "sg:classifiers":[
        {
            "category":"Retail",
            "subcategory":"Repair Shop",
            "type":"Services"
        }
    ],
    "sg:phone":"+1 701 749 2675",
    "sg:postcode":"58071",
    "sg:province":"ND",
    "sg:tags":[
        "plumbing",
        "drain",
        "cleaning",
        "sewer"
    ],
    "wof:name":"Floyd's Pumping & Drain Svc",
    "wof:placetype":"venue"
},
  "geometry": {"coordinates":[-97.68484599999999,46.988199],"type":"Point"}
}