{
  "type": "Feature",
  "properties": {
    "iso:country":"US",
    "sg:address":"3395 55th Ave SE",
    "sg:city":"Medina",
    "sg:classifiers":[
        {
            "category":"Wholesale",
            "subcategory":"Machinery & Supplies",
            "type":"Manufacturing & Wholesale Goods"
        }
    ],
    "sg:phone":"+1 701 486 3510",
    "sg:postcode":"58467",
    "sg:province":"ND",
    "sg:tags":[
        "farm",
        "equipment"
    ],
    "wof:name":"Donald Hofmann-Vermeer Sales",
    "wof:placetype":"venue"
},
  "geometry": {"coordinates":[-99.299885,46.921598],"type":"Point"}
}