{
  "type": "Feature",
  "properties": {
    "addr:full":"4828 48th Ave SE Streeter ND 58483",
    "addr:housenumber":"4828",
    "addr:postcode":"58483",
    "addr:street":"48Th Ave Se",
    "iso:country":"US",
    "sg:address":"4828 48th Ave SE",
    "sg:city":"Streeter",
    "sg:classifiers":[
        {
            "category":"Education",
            "subcategory":"College",
            "type":"Public Place"
        }
    ],
    "sg:phone":"+1 701 424 3406",
    "sg:postcode":"58483",
    "sg:province":"ND",
    "sg:tags":[
        "academic",
        "school"
    ],
    "wof:name":"Livestock Unit",
    "wof:placetype":"venue"
},
  "geometry": {"coordinates":[-99.448516,46.714518],"type":"Point"}
}