{
  "type": "Feature",
  "properties": {
    "addr:full":"306 3rd St NE Hazen ND 58545",
    "addr:housenumber":"306",
    "addr:postcode":"58545",
    "addr:street":"3Rd St Ne",
    "iso:country":"US",
    "sg:address":"306 3rd St NE",
    "sg:city":"Hazen",
    "sg:classifiers":[
        {
            "category":"Professional",
            "type":"Services"
        }
    ],
    "sg:phone":"+1 701 748 2805",
    "sg:postcode":"58545",
    "sg:province":"ND",
    "sg:tags":[
        "establishment"
    ],
    "wof:name":"Mack & Mack",
    "wof:placetype":"venue"
},
  "geometry": {"coordinates":[-101.618658,47.295763],"type":"Point"}
}