{
  "type": "Feature",
  "properties": {
    "iso:country":"US",
    "sg:address":"208 E Oak Ave",
    "sg:city":"New Salem",
    "sg:classifiers":[
        {
            "category":"Organizations",
            "subcategory":"Religious Organization",
            "type":"Services"
        }
    ],
    "sg:phone":"+1 701 843 8597",
    "sg:postcode":"58563",
    "sg:province":"ND",
    "sg:tags":[
        "church"
    ],
    "wof:name":"Word Of Life Baptist Church",
    "wof:placetype":"venue"
},
  "geometry": {"coordinates":[-101.405603,46.846588],"type":"Point"}
}