{
  "type": "Feature",
  "properties": {
    "iso:country":"US",
    "sg:address":"123 3rd St N",
    "sg:city":"Wahpeton",
    "sg:classifiers":[
        {
            "category":"Real Estate",
            "subcategory":"Real Estate Services",
            "type":"Services"
        }
    ],
    "sg:phone":"+1 701 642 3781",
    "sg:postcode":"58075",
    "sg:province":"ND",
    "wof:name":"Richland County Abstract Co",
    "wof:placetype":"venue"
},
  "geometry": {"coordinates":[-96.60401,46.264883],"type":"Point"}
}