{
  "type": "Feature",
  "properties": {
    "iso:country":"US",
    "sg:address":"816 Cedar Ave",
    "sg:city":"Harvey",
    "sg:phone":"+1 701 324 4245",
    "sg:postcode":"58341",
    "sg:province":"ND",
    "sg:tags":[
        "farm",
        "wheat",
        "beef",
        "feedlot",
        "cattle"
    ],
    "wof:name":"Held Farms",
    "wof:placetype":"venue"
},
  "geometry": {"coordinates":[-99.939515,47.77124],"type":"Point"}
}