{
  "type": "Feature",
  "properties": {
    "addr:full":"218 2nd Ave SE Rugby ND 58368",
    "addr:housenumber":"218",
    "addr:postcode":"58368",
    "addr:street":"2Nd Ave Se",
    "iso:country":"US",
    "sg:address":"218 2nd Ave SE",
    "sg:city":"Rugby",
    "sg:classifiers":[
        {
            "category":"Wholesale",
            "subcategory":"Vending Machines",
            "type":"Manufacturing & Wholesale Goods"
        }
    ],
    "sg:phone":"+1 701 776 6858",
    "sg:postcode":"58368",
    "sg:province":"ND",
    "wof:name":"Your Turn Vending",
    "wof:placetype":"venue"
},
  "geometry": {"coordinates":[-99.994651,48.368505],"type":"Point"}
}