{
  "type": "Feature",
  "properties": {
    "iso:country":"US",
    "sg:address":"203 6th Ave SE",
    "sg:city":"Jamestown",
    "sg:classifiers":[
        {
            "category":"Social Services",
            "subcategory":"Child Care",
            "type":"Services"
        }
    ],
    "sg:phone":"+1 701 251 9005",
    "sg:postcode":"58401",
    "sg:province":"ND",
    "wof:name":"Li'l Britches Day Care",
    "wof:placetype":"venue"
},
  "geometry": {"coordinates":[-98.700728,46.907762],"type":"Point"}
}