{
  "type": "Feature",
  "properties": {
    "addr:full":"5545 80th Ave SE Montpelier ND 58472",
    "addr:housenumber":"5545",
    "addr:postcode":"58472",
    "addr:street":"80Th Ave Se",
    "iso:country":"US",
    "sg:address":"5545 80th Ave SE",
    "sg:city":"Montpelier",
    "sg:classifiers":[
        {
            "category":"Farming",
            "subcategory":"Farm",
            "type":"Manufacturing & Wholesale Goods"
        }
    ],
    "sg:phone":"+1 701 685 2403",
    "sg:postcode":"58472",
    "sg:province":"ND",
    "sg:tags":[
        "crop",
        "general"
    ],
    "wof:name":"Duane Wirrenga",
    "wof:placetype":"venue"
},
  "geometry": {"coordinates":[-98.746422,46.60995],"type":"Point"}
}