{
  "type": "Feature",
  "properties": {
    "addr:full":"2325 118th Ave SE Valley City ND 58072",
    "addr:housenumber":"2325",
    "addr:postcode":"58072",
    "addr:street":"118Th Ave Se",
    "iso:country":"US",
    "sg:address":"2325 118th Ave SE",
    "sg:city":"Valley City",
    "sg:classifiers":[
        {
            "category":"Real Estate",
            "subcategory":"Real Estate Operator",
            "type":"Services"
        }
    ],
    "sg:phone":"+1 701 845 2344",
    "sg:postcode":"58072",
    "sg:province":"ND",
    "sg:tags":[
        "farm",
        "property",
        "wheat",
        "lessor"
    ],
    "wof:name":"Dittmer Elva",
    "wof:placetype":"venue"
},
  "geometry": {"coordinates":[-98.00251,47.077036],"type":"Point"}
}