{
  "type": "Feature",
  "properties": {
    "iso:country":"US",
    "sg:address":"213 Central Ave N",
    "sg:city":"Valley City",
    "sg:classifiers":[
        {
            "category":"Professional",
            "subcategory":"Computer Services",
            "type":"Services"
        }
    ],
    "sg:phone":"+1 701 845 5180",
    "sg:postcode":"58072",
    "sg:province":"ND",
    "sg:tags":[
        "agency",
        "advertising",
        "related"
    ],
    "wof:name":"Scherrcom",
    "wof:placetype":"venue"
},
  "geometry": {"coordinates":[-98.003169,46.925136],"type":"Point"}
}