{
  "type": "Feature",
  "properties": {
    "iso:country":"US",
    "sg:address":"221 4th St N",
    "sg:city":"Oakes",
    "sg:classifiers":[
        {
            "category":"Retail",
            "subcategory":"Auto Repair",
            "type":"Services"
        }
    ],
    "sg:phone":"+1 701 742 2131",
    "sg:postcode":"58474",
    "sg:province":"ND",
    "sg:tags":[
        "repairing",
        "automobile"
    ],
    "wof:name":"Zack's Repair",
    "wof:placetype":"venue"
},
  "geometry": {"coordinates":[-98.094992,46.141675],"type":"Point"}
}