{
  "type": "Feature",
  "properties": {
    "iso:country":"US",
    "sg:address":"800 24th Ave SW",
    "sg:city":"Minot",
    "sg:classifiers":[
        {
            "category":"Organizations",
            "subcategory":"Religious Organization",
            "type":"Services"
        }
    ],
    "sg:phone":"+1 701 839 0915",
    "sg:postcode":"58701",
    "sg:province":"ND",
    "wof:name":"Dakota Missionary Evangelism",
    "wof:placetype":"venue"
},
  "geometry": {"coordinates":[-101.303507,48.207245],"type":"Point"}
}