{
  "type": "Feature",
  "properties": {
    "addr:full":"700 24th Ave S Grand Forks ND 58201",
    "addr:housenumber":"700",
    "addr:postcode":"58201",
    "addr:street":"24Th Ave S",
    "iso:country":"US",
    "sg:address":"700 24th Ave S",
    "sg:city":"Grand Forks",
    "sg:classifiers":[
        {
            "category":"Organizations",
            "subcategory":"Religious Organization",
            "type":"Services"
        }
    ],
    "sg:phone":"+1 701 775 0648",
    "sg:postcode":"58201",
    "sg:province":"ND",
    "wof:name":"Grace Baptist Church",
    "wof:placetype":"venue"
},
  "geometry": {"coordinates":[-97.037351,47.896738],"type":"Point"}
}