{
  "type": "Feature",
  "properties": {
    "addr:full":"1828 E Main Ave Bismarck ND 58501",
    "addr:housenumber":"1828",
    "addr:postcode":"58501",
    "addr:street":"E Main Ave",
    "iso:country":"US",
    "sg:address":"1828 E Main Ave",
    "sg:city":"Bismarck",
    "sg:classifiers":[
        {
            "category":"Autos & Motor Vehicles",
            "subcategory":"Automobile Sales",
            "type":"Retail Goods"
        }
    ],
    "sg:phone":"+1 701 250 9090",
    "sg:postcode":"58501",
    "sg:province":"ND",
    "sg:tags":[
        "car",
        "dealer"
    ],
    "wof:name":"Capitol City Motorworx",
    "wof:placetype":"venue"
},
  "geometry": {"coordinates":[-100.76467,46.805266],"type":"Point"}
}