{
  "type": "Feature",
  "properties": {
    "addr:full":"1723 Dyke Ave Grand Forks ND 58203",
    "addr:housenumber":"1723",
    "addr:postcode":"58203",
    "addr:street":"Dyke Ave",
    "iso:country":"US",
    "sg:address":"1723 Dyke Ave",
    "sg:city":"Grand Forks",
    "sg:classifiers":[
        {
            "category":"Building & Trades",
            "subcategory":"Plumbing",
            "type":"Services"
        }
    ],
    "sg:phone":"+1 701 746 4622",
    "sg:postcode":"58203",
    "sg:province":"ND",
    "sg:tags":[
        "plumbing",
        "contractor"
    ],
    "wof:name":"Water Boys Plumbing Svc Inc",
    "wof:placetype":"venue"
},
  "geometry": {"coordinates":[-97.05217500000001,47.919026],"type":"Point"}
}