{
  "type": "Feature",
  "properties": {
    "addr:full":"117 Ave C E Mcclusky ND 58463",
    "addr:housenumber":"117",
    "addr:postcode":"58463",
    "addr:street":"Ave C E Mcclusky",
    "iso:country":"US",
    "sg:address":"117 Ave C E",
    "sg:city":"Mcclusky",
    "sg:classifiers":[
        {
            "category":"Retail",
            "subcategory":"Funeral Services",
            "type":"Services"
        }
    ],
    "sg:phone":"+1 701 363 2250",
    "sg:postcode":"58463",
    "sg:province":"ND",
    "sg:tags":[
        "director"
    ],
    "wof:name":"Hertz Funeral Homes Inc",
    "wof:placetype":"venue"
},
  "geometry": {"coordinates":[-100.442706,47.483848],"type":"Point"}
}