{
  "type": "Feature",
  "properties": {
    "iso:country":"US",
    "sg:address":"806 27th St N",
    "sg:city":"Fargo",
    "sg:classifiers":[
        {
            "category":"Social Services",
            "subcategory":"Child Care",
            "type":"Services"
        }
    ],
    "sg:phone":"+1 701 232 6644",
    "sg:postcode":"58102",
    "sg:province":"ND",
    "sg:tags":[
        "day"
    ],
    "wof:name":"Learning Patch",
    "wof:placetype":"venue"
},
  "geometry": {"coordinates":[-96.822681,46.8868],"type":"Point"}
}