{
  "type": "Feature",
  "properties": {
    "iso:country":"US",
    "sg:address":"316 6th St S",
    "sg:city":"Devils Lake",
    "sg:classifiers":[
        {
            "category":"Government",
            "subcategory":"Office",
            "type":"Public Place"
        }
    ],
    "sg:phone":"+1 701 665 5100",
    "sg:postcode":"58301",
    "sg:province":"ND",
    "sg:tags":[
        "state",
        "program"
    ],
    "wof:name":"Transportation Dept",
    "wof:placetype":"venue"
},
  "geometry": {"coordinates":[-98.861886,48.103659],"type":"Point"}
}