{
  "type": "Feature",
  "properties": {
    "addr:full":"216 Main St Halliday ND 58636",
    "addr:housenumber":"216",
    "addr:postcode":"58636",
    "addr:street":"Main St",
    "iso:country":"US",
    "sg:address":"216 Main St",
    "sg:city":"Halliday",
    "sg:classifiers":[
        {
            "category":"Health Services",
            "subcategory":"Doctor",
            "type":"Services"
        }
    ],
    "sg:phone":"+1 701 938 4464",
    "sg:postcode":"58636",
    "sg:province":"ND",
    "sg:tags":[
        "clinic"
    ],
    "wof:name":"Halliday Medical Clinic",
    "wof:placetype":"venue"
},
  "geometry": {"coordinates":[-102.334402,47.354381],"type":"Point"}
}