{
  "type": "Feature",
  "properties": {
    "iso:country":"US",
    "sg:address":"3264 20th St S",
    "sg:city":"Fargo",
    "sg:classifiers":[
        {
            "category":"Utilities",
            "subcategory":"Mobile Phone",
            "type":"Services"
        }
    ],
    "sg:phone":"+1 701 232 5200",
    "sg:postcode":"58104",
    "sg:province":"ND",
    "sg:tags":[
        "communication",
        "radiotelephone"
    ],
    "wof:name":"Cellular One",
    "wof:placetype":"venue"
},
  "geometry": {"coordinates":[-96.81269,46.831132],"type":"Point"}
}