{
  "type": "Feature",
  "properties": {
    "iso:country":"US",
    "sg:address":"101 3rd St SW",
    "sg:city":"Watford City",
    "sg:classifiers":[
        {
            "category":"Manufacturing",
            "subcategory":"Building Materials",
            "type":"Manufacturing & Wholesale Goods"
        }
    ],
    "sg:phone":"+1 701 444 9663",
    "sg:postcode":"58854",
    "sg:province":"ND",
    "sg:tags":[
        "fixture",
        "furniture"
    ],
    "wof:name":"Woodchips Inc",
    "wof:placetype":"venue"
},
  "geometry": {"coordinates":[-103.286106,47.799966],"type":"Point"}
}