{
  "type": "Feature",
  "properties": {
    "iso:country":"US",
    "sg:address":"1002 2nd Ave SE",
    "sg:city":"Jamestown",
    "sg:classifiers":[
        {
            "category":"Retail",
            "subcategory":"Laundry & Dry Cleaning",
            "type":"Services"
        }
    ],
    "sg:phone":"+1 701 251 1373",
    "sg:postcode":"58401",
    "sg:province":"ND",
    "sg:tags":[
        "cleaners",
        "rug",
        "carpet"
    ],
    "wof:name":"Carpet Connection",
    "wof:placetype":"venue"
},
  "geometry": {"coordinates":[-98.706684,46.898995],"type":"Point"}
}