{
  "type": "Feature",
  "properties": {
    "addr:full":"116 6th St E Bottineau ND 58318",
    "addr:housenumber":"116",
    "addr:postcode":"58318",
    "addr:street":"6Th St;Bottineau",
    "iso:country":"US",
    "sg:address":"116 6th St E",
    "sg:city":"Bottineau",
    "sg:classifiers":[
        {
            "category":"Retail",
            "subcategory":"Portrait Studio",
            "type":"Services"
        }
    ],
    "sg:phone":"+1 701 228 2700",
    "sg:postcode":"58318",
    "sg:province":"ND",
    "sg:tags":[
        "photographer"
    ],
    "wof:name":"Kapture By Kaleena",
    "wof:placetype":"venue"
},
  "geometry": {"coordinates":[-100.444496,48.826233],"type":"Point"}
}