{
  "type": "Feature",
  "properties": {
    "iso:country":"US",
    "sg:address":"101 Broadway S",
    "sg:city":"Buffalo",
    "sg:classifiers":[
        {
            "category":"Building & Trades",
            "subcategory":"Construction",
            "type":"Services"
        }
    ],
    "sg:phone":"+1 701 793 1612",
    "sg:postcode":"58011",
    "sg:province":"ND",
    "sg:tags":[
        "repairing",
        "remodeling",
        "contractor"
    ],
    "wof:name":"A-F Construction Co",
    "wof:placetype":"venue"
},
  "geometry": {"coordinates":[-97.54992900000001,46.918572],"type":"Point"}
}