{
  "type": "Feature",
  "properties": {
    "addr:full":"4431 Memorial Hwy Mandan ND 58554",
    "addr:housenumber":"4431",
    "addr:postcode":"58554",
    "addr:street":"Memorial Hwy",
    "iso:country":"US",
    "sg:address":"4431 Memorial Hwy",
    "sg:city":"Mandan",
    "sg:classifiers":[
        {
            "category":"Banks & Credit Unions",
            "subcategory":"Investment Brokerage",
            "type":"Services"
        }
    ],
    "sg:phone":"+1 701 663 8401",
    "sg:postcode":"58554",
    "sg:province":"ND",
    "sg:tags":[
        "consultant",
        "planning",
        "financial"
    ],
    "wof:name":"Securian Financial Advisors",
    "wof:placetype":"venue"
},
  "geometry": {"coordinates":[-100.833039,46.809528],"type":"Point"}
}