{
  "type": "Feature",
  "properties": {
    "iso:country":"US",
    "sg:address":"301 Nova Dr",
    "sg:city":"Bismarck",
    "sg:classifiers":[
        {
            "category":"Professional",
            "subcategory":"Accounting & Tax Preparation",
            "type":"Services"
        }
    ],
    "sg:phone":"+1 701 224 0087",
    "sg:postcode":"58503",
    "sg:province":"ND",
    "wof:name":"The Appert Co",
    "wof:placetype":"venue"
},
  "geometry": {"coordinates":[-100.787436,46.835066],"type":"Point"}
}