{
  "type": "Feature",
  "properties": {
    "iso:country":"US",
    "sg:address":"1426 Cottonwood Ave SW",
    "sg:city":"Minot",
    "sg:classifiers":[
        {
            "category":"Real Estate",
            "subcategory":"Developer",
            "type":"Services"
        }
    ],
    "sg:phone":"+1 701 838 3014",
    "sg:postcode":"58701",
    "sg:province":"ND",
    "sg:tags":[
        "mobile",
        "home"
    ],
    "wof:name":"Western Village",
    "wof:placetype":"venue"
},
  "geometry": {"coordinates":[-101.31874000000001,48.220348],"type":"Point"}
}