{
  "type": "Feature",
  "properties": {
    "addr:full":"916 2nd Ave NW Jamestown ND 58401",
    "addr:housenumber":"916",
    "addr:postcode":"58401",
    "addr:street":"2Nd Ave Nw",
    "iso:country":"US",
    "sg:address":"916 2nd Ave NW",
    "sg:city":"Jamestown",
    "sg:classifiers":[
        {
            "category":"Farming",
            "subcategory":"Farm & Veterinary Services",
            "type":"Manufacturing & Wholesale Goods"
        }
    ],
    "sg:phone":"+1 701 252 5201",
    "sg:postcode":"58401",
    "sg:province":"ND",
    "sg:tags":[
        "spraying",
        "aircraft",
        "crop"
    ],
    "wof:name":"Jamestown Aviation Inc",
    "wof:placetype":"venue"
},
  "geometry": {"coordinates":[-98.71078,46.917031],"type":"Point"}
}