{
  "type": "Feature",
  "properties": {
    "iso:country":"US",
    "sg:address":"1525 Cook Dr",
    "sg:city":"Minot",
    "sg:classifiers":[
        {
            "category":"Professional",
            "subcategory":"Business Services",
            "type":"Services"
        }
    ],
    "sg:phone":"+1 701 839 5376",
    "sg:postcode":"58701",
    "sg:province":"ND",
    "wof:name":"Metz Fri LLP",
    "wof:placetype":"venue"
},
  "geometry": {"coordinates":[-101.31350500000001,48.221214],"type":"Point"}
}