{
  "type": "Feature",
  "properties": {
    "addr:full":"22 7th St SW Minot ND 58701",
    "addr:housenumber":"22",
    "addr:postcode":"58701",
    "addr:street":"7Th St Sw",
    "iso:country":"US",
    "sg:address":"22 7th St SW",
    "sg:city":"Minot",
    "sg:classifiers":[
        {
            "category":"Building & Trades",
            "subcategory":"Construction",
            "type":"Services"
        }
    ],
    "sg:phone":"+1 701 852 8235",
    "sg:postcode":"58701",
    "sg:province":"ND",
    "sg:tags":[
        "hanging",
        "business",
        "contractor"
    ],
    "wof:name":"A & D Painting",
    "wof:placetype":"venue"
},
  "geometry": {"coordinates":[-101.303788,48.235622],"type":"Point"}
}