{
  "type": "Feature",
  "properties": {
    "addr:full":"604 Broadway Fargo ND 58102",
    "addr:housenumber":"604",
    "addr:postcode":"58102",
    "addr:street":"Broadway",
    "iso:country":"US",
    "sg:address":"604 Broadway",
    "sg:city":"Fargo",
    "sg:classifiers":[
        {
            "category":"Organizations",
            "subcategory":"Religious Organization",
            "type":"Services"
        }
    ],
    "sg:phone":"+1 701 235 6354",
    "sg:postcode":"58102",
    "sg:province":"ND",
    "sg:tags":[
        "church"
    ],
    "wof:name":"St Mary's Cathedral",
    "wof:placetype":"venue"
},
  "geometry": {"coordinates":[-96.787807,46.883074],"type":"Point"}
}