{
  "type": "Feature",
  "properties": {
    "addr:full":"112 1st St NE Ashley ND 58413",
    "addr:housenumber":"112",
    "addr:postcode":"58413",
    "addr:street":"1St St Ne",
    "iso:country":"US",
    "sg:address":"112 1st St NE",
    "sg:city":"Ashley",
    "sg:classifiers":[
        {
            "category":"Government",
            "subcategory":"Office",
            "type":"Public Place"
        }
    ],
    "sg:phone":"+1 701 288 3343",
    "sg:postcode":"58413",
    "sg:province":"ND",
    "sg:tags":[
        "county",
        "resource"
    ],
    "wof:name":"Mc Intosh County Social Svc",
    "wof:placetype":"venue"
},
  "geometry": {"coordinates":[-99.37020699999999,46.035586],"type":"Point"}
}