{
  "type": "Feature",
  "properties": {
    "iso:country":"US",
    "sg:address":"810 S Main Ave",
    "sg:city":"Rugby",
    "sg:classifiers":[
        {
            "category":"Health Services",
            "subcategory":"Doctor",
            "type":"Services"
        }
    ],
    "sg:phone":"+1 701 776 5848",
    "sg:postcode":"58368",
    "sg:province":"ND",
    "sg:tags":[
        "medical"
    ],
    "wof:name":"Heart American Medical Center",
    "wof:placetype":"venue"
},
  "geometry": {"coordinates":[-99.996183,48.362765],"type":"Point"}
}