{
  "type": "Feature",
  "properties": {
    "addr:full":"2042 7th St NW Minot ND 58703",
    "addr:housenumber":"2042",
    "addr:postcode":"58703",
    "addr:street":"7Th St Nw",
    "iso:country":"US",
    "sg:address":"2042 7th St NW",
    "sg:city":"Minot",
    "sg:classifiers":[
        {
            "category":"Shopping",
            "subcategory":"Gifts & Souvenirs",
            "type":"Retail Goods"
        }
    ],
    "sg:phone":"+1 701 839 4180",
    "sg:postcode":"58703",
    "sg:province":"ND",
    "wof:name":"Pat & Bills Gift Boutique",
    "wof:placetype":"venue"
},
  "geometry": {"coordinates":[-101.304805,48.257589],"type":"Point"}
}