{
  "type": "Feature",
  "properties": {
    "addr:full":"301 6th St S Wahpeton ND 58075",
    "addr:housenumber":"301",
    "addr:postcode":"58075",
    "addr:street":"6Th St S",
    "iso:country":"US",
    "sg:address":"301 6th St S",
    "sg:city":"Wahpeton",
    "sg:classifiers":[
        {
            "category":"Food & Beverages",
            "subcategory":"Bakery",
            "type":"Retail Goods"
        }
    ],
    "sg:phone":"+1 701 642 5151",
    "sg:postcode":"58075",
    "sg:province":"ND",
    "wof:name":"Sara Lee Bakery Group Inc",
    "wof:placetype":"venue"
},
  "geometry": {"coordinates":[-96.60834699999999,46.261883],"type":"Point"}
}