{
  "type": "Feature",
  "properties": {
    "iso:country":"US",
    "sg:address":"3001 Memorial Hwy",
    "sg:city":"Mandan",
    "sg:classifiers":[
        {
            "category":"Food & Beverages",
            "subcategory":"Meat & Fish",
            "type":"Retail Goods"
        }
    ],
    "sg:phone":"+1 701 663 1888",
    "sg:postcode":"58554",
    "sg:province":"ND",
    "wof:name":"Choice Cut Meats",
    "wof:placetype":"venue"
},
  "geometry": {"coordinates":[-100.856544,46.821553],"type":"Point"}
}