{
  "type": "Feature",
  "properties": {
    "iso:country":"US",
    "sg:address":"1529 4th Ave N",
    "sg:city":"Fargo",
    "sg:classifiers":[
        {
            "category":"Building & Trades",
            "subcategory":"Plumbing",
            "type":"Services"
        }
    ],
    "sg:phone":"+1 701 237 3037",
    "sg:postcode":"58102",
    "sg:province":"ND",
    "sg:tags":[
        "balancing",
        "air"
    ],
    "wof:name":"Design Control",
    "wof:placetype":"venue"
},
  "geometry": {"coordinates":[-96.80551800000001,46.880604],"type":"Point"}
}