{
  "type": "Feature",
  "properties": {
    "iso:country":"US",
    "sg:address":"1618 11th St N",
    "sg:city":"Fargo",
    "sg:classifiers":[
        {
            "category":"Retail",
            "subcategory":"Laundry & Dry Cleaning",
            "type":"Services"
        }
    ],
    "sg:phone":"+1 701 235 1158",
    "sg:postcode":"58102",
    "sg:province":"ND",
    "sg:tags":[
        "personal"
    ],
    "wof:name":"Garys Handyman Services",
    "wof:placetype":"venue"
},
  "geometry": {"coordinates":[-96.79513,46.900812],"type":"Point"}
}