{
  "type": "Feature",
  "properties": {
    "iso:country":"US",
    "sg:address":"32400 27th St SE",
    "sg:city":"Max",
    "sg:classifiers":[
        {
            "category":"Building & Trades",
            "subcategory":"Construction",
            "type":"Services"
        }
    ],
    "sg:phone":"+1 701 679 2293",
    "sg:postcode":"58759",
    "sg:province":"ND",
    "sg:tags":[
        "excavation",
        "contractor",
        "general"
    ],
    "wof:name":"Delzer Construction & Excavati",
    "wof:placetype":"venue"
},
  "geometry": {"coordinates":[-101.25015999999999,47.906351],"type":"Point"}
}