{
  "type": "Feature",
  "properties": {
    "iso:country":"US",
    "sg:address":"1100 Industrial Dr",
    "sg:city":"Bismarck",
    "sg:classifiers":[
        {
            "category":"Building & Trades",
            "subcategory":"Construction",
            "type":"Services"
        }
    ],
    "sg:phone":"+1 701 224 1164",
    "sg:postcode":"58501",
    "sg:province":"ND",
    "sg:tags":[
        "design",
        "grain",
        "elevator"
    ],
    "sg:website":"www.jsonsinc.com",
    "wof:name":"J-Sons Inc",
    "wof:placetype":"venue"
},
  "geometry": {"coordinates":[-100.73126600000001,46.818337],"type":"Point"}
}