{
  "type": "Feature",
  "properties": {
    "addr:full":"600 5th Ave Langdon ND 58249",
    "addr:housenumber":"600",
    "addr:postcode":"58249",
    "addr:street":"5Th Ave",
    "iso:country":"US",
    "sg:address":"600 5th Ave",
    "sg:city":"Langdon",
    "sg:classifiers":[
        {
            "category":"Education",
            "subcategory":"Library",
            "type":"Public Place"
        }
    ],
    "sg:phone":"+1 701 256 5353",
    "sg:postcode":"58249",
    "sg:province":"ND",
    "wof:name":"Cavalier County Library",
    "wof:placetype":"venue"
},
  "geometry": {"coordinates":[-98.372753,48.759256],"type":"Point"}
}