{
  "type": "Feature",
  "properties": {
    "addr:full":"252 W Museum Dr Dickinson ND 58601",
    "addr:housenumber":"252",
    "addr:postcode":"58601",
    "addr:street":"W Museum Dr",
    "iso:country":"US",
    "sg:address":"252 W Museum Dr",
    "sg:city":"Dickinson",
    "sg:classifiers":[
        {
            "category":"Autos & Motor Vehicles",
            "subcategory":"Fuel & Gas Station",
            "type":"Retail Goods"
        }
    ],
    "sg:phone":"+1 701 483 7017",
    "sg:postcode":"58601",
    "sg:province":"ND",
    "sg:tags":[
        "oil"
    ],
    "wof:name":"Cenex",
    "wof:placetype":"venue"
},
  "geometry": {"coordinates":[-102.788787,46.894234],"type":"Point"}
}