{
  "type": "Feature",
  "properties": {
    "iso:country":"US",
    "sg:address":"212 S 4th St",
    "sg:city":"Grand Forks",
    "sg:classifiers":[
        {
            "category":"Recreation",
            "type":"Entertainment"
        }
    ],
    "sg:phone":"+1 701 775 4400",
    "sg:postcode":"58201",
    "sg:province":"ND",
    "sg:tags":[
        "amusement"
    ],
    "wof:name":"B Ball Exhibition",
    "wof:placetype":"venue"
},
  "geometry": {"coordinates":[-97.027517,47.922108],"type":"Point"}
}