{
  "type": "Feature",
  "properties": {
    "iso:country":"US",
    "sg:address":"1819 Michigan Ave",
    "sg:city":"Bismarck",
    "sg:classifiers":[
        {
            "category":"Personal",
            "subcategory":"Beauty Salon",
            "type":"Services"
        }
    ],
    "sg:phone":"+1 701 323 0333",
    "sg:postcode":"58504",
    "sg:province":"ND",
    "wof:name":"Studio 10 Hair Design",
    "wof:placetype":"venue"
},
  "geometry": {"coordinates":[-100.76336499999999,46.798335],"type":"Point"}
}