{
  "type": "Feature",
  "properties": {
    "iso:country":"US",
    "sg:address":"1417 Main Ave",
    "sg:city":"Oakes",
    "sg:classifiers":[
        {
            "category":"Travel",
            "subcategory":"Hotels & Motels",
            "type":"Entertainment"
        }
    ],
    "sg:phone":"+1 701 742 2151",
    "sg:postcode":"58474",
    "sg:province":"SD",
    "sg:tags":[
        "operation"
    ],
    "wof:name":"E & I Motel",
    "wof:placetype":"venue"
},
  "geometry": {"coordinates":[-98.079991,46.138897],"type":"Point"}
}