{
  "type": "Feature",
  "properties": {
    "iso:country":"US",
    "sg:address":"223 N 15th St",
    "sg:city":"Bismarck",
    "sg:classifiers":[
        {
            "category":"Food & Beverages",
            "subcategory":"Groceries & Convenience Stores",
            "type":"Retail Goods"
        }
    ],
    "sg:phone":"+1 701 224 1017",
    "sg:postcode":"58501",
    "sg:province":"ND",
    "wof:name":"Masters Plan Inc",
    "wof:placetype":"venue"
},
  "geometry": {"coordinates":[-100.769308,46.807079],"type":"Point"}
}