{
  "type": "Feature",
  "properties": {
    "addr:full":"35 Wiley Ave N Lidgerwood ND 58053",
    "addr:housenumber":"35",
    "addr:postcode":"58053",
    "addr:street":"Wiley Ave N",
    "iso:country":"US",
    "sg:address":"35 Wiley Ave N",
    "sg:city":"Lidgerwood",
    "sg:classifiers":[
        {
            "category":"Bars & Pubs",
            "type":"Food & Drink"
        }
    ],
    "sg:phone":"+1 701 538 9426",
    "sg:postcode":"58053",
    "sg:province":"ND",
    "wof:name":"Art's Tavern",
    "wof:placetype":"venue"
},
  "geometry": {"coordinates":[-97.15187899999999,46.076239],"type":"Point"}
}