{
  "type": "Feature",
  "properties": {
    "iso:country":"US",
    "sg:address":"1516 6th Ave N",
    "sg:city":"Grand Forks",
    "sg:classifiers":[
        {
            "category":"Social Services",
            "subcategory":"Child Care",
            "type":"Services"
        }
    ],
    "sg:phone":"+1 701 772 1503",
    "sg:postcode":"58203",
    "sg:province":"ND",
    "sg:tags":[
        "day"
    ],
    "wof:name":"Debbies Daycare",
    "wof:placetype":"venue"
},
  "geometry": {"coordinates":[-97.049209,47.925339],"type":"Point"}
}