{
  "type": "Feature",
  "properties": {
    "addr:full":"4118 34th Ave NW Mandan ND 58554",
    "addr:housenumber":"4118",
    "addr:postcode":"58554",
    "addr:street":"34Th Ave Nw",
    "iso:country":"US",
    "sg:address":"4118 34th Ave NW",
    "sg:city":"Mandan",
    "sg:classifiers":[
        {
            "category":"Building & Trades",
            "subcategory":"Construction",
            "type":"Services"
        }
    ],
    "sg:phone":"+1 701 663 2698",
    "sg:postcode":"58554",
    "sg:province":"ND",
    "sg:tags":[
        "porch",
        "enclosure",
        "patio",
        "deck"
    ],
    "wof:name":"A Plus Sunrooms Awnings Decks",
    "wof:placetype":"venue"
},
  "geometry": {"coordinates":[-100.936779,46.862365],"type":"Point"}
}