{
  "type": "Feature",
  "properties": {
    "addr:full":"519 3rd St Langdon ND 58249",
    "addr:housenumber":"519",
    "addr:postcode":"58249",
    "addr:street":"3Rd St",
    "iso:country":"US",
    "sg:address":"519 3rd St",
    "sg:city":"Langdon",
    "sg:classifiers":[
        {
            "category":"Food & Beverages",
            "subcategory":"Liquor & Beverages",
            "type":"Retail Goods"
        }
    ],
    "sg:phone":"+1 701 256 2305",
    "sg:postcode":"58249",
    "sg:province":"ND",
    "sg:tags":[
        "alcoholic"
    ],
    "wof:name":"Regal Liquors",
    "wof:placetype":"venue"
},
  "geometry": {"coordinates":[-98.368206,48.758045],"type":"Point"}
}