{
  "type": "Feature",
  "properties": {
    "iso:country":"US",
    "sg:address":"106 Railroad St",
    "sg:city":"Kulm",
    "sg:classifiers":[
        {
            "category":"Wholesale",
            "subcategory":"Farm Supplies",
            "type":"Manufacturing & Wholesale Goods"
        }
    ],
    "sg:phone":"+1 701 647 2307",
    "sg:postcode":"58456",
    "sg:province":"ND",
    "wof:name":"Farmers Union Oil Co Fert",
    "wof:placetype":"venue"
},
  "geometry": {"coordinates":[-98.950194,46.304409],"type":"Point"}
}