{
  "type": "Feature",
  "properties": {
    "iso:country":"US",
    "sg:address":"318 24th St N",
    "sg:city":"Fargo",
    "sg:classifiers":[
        {
            "category":"Retail",
            "subcategory":"Auto Repair",
            "type":"Services"
        }
    ],
    "sg:phone":"+1 701 232 3918",
    "sg:postcode":"58102",
    "sg:province":"ND",
    "sg:tags":[
        "exchanging",
        "automobile",
        "engine",
        "rebuilding"
    ],
    "wof:name":"Quality Engine & Machine Inc",
    "wof:placetype":"venue"
},
  "geometry": {"coordinates":[-96.81820999999999,46.881382],"type":"Point"}
}