{
  "type": "Feature",
  "properties": {
    "addr:full":"524 Central Ave New Rockford ND 58356",
    "addr:housenumber":"524",
    "addr:postcode":"58356",
    "addr:street":"Central Ave",
    "iso:country":"US",
    "sg:address":"524 Central Ave",
    "sg:city":"New Rockford",
    "sg:classifiers":[
        {
            "category":"Government",
            "subcategory":"Court House",
            "type":"Public Place"
        }
    ],
    "sg:phone":"+1 701 947 5777",
    "sg:postcode":"58356",
    "sg:province":"ND",
    "sg:tags":[
        "county"
    ],
    "wof:name":"Eddy County Judge",
    "wof:placetype":"venue"
},
  "geometry": {"coordinates":[-99.133522,47.68022],"type":"Point"}
}