{
  "type": "Feature",
  "properties": {
    "addr:full":"1805 Michigan Ave Bismarck ND 58504",
    "addr:housenumber":"1805",
    "addr:postcode":"58504",
    "addr:street":"Michigan Ave",
    "iso:country":"US",
    "sg:address":"1805 Michigan Ave",
    "sg:city":"Bismarck",
    "sg:classifiers":[
        {
            "category":"Wholesale",
            "subcategory":"Hardware",
            "type":"Manufacturing & Wholesale Goods"
        }
    ],
    "sg:phone":"+1 701 223 3557",
    "sg:postcode":"58504",
    "sg:province":"ND",
    "sg:tags":[
        "building",
        "brick",
        "fireplace",
        "stone",
        "accessory"
    ],
    "wof:name":"B & D Supply Inc",
    "wof:placetype":"venue"
},
  "geometry": {"coordinates":[-100.76318999999999,46.798332],"type":"Point"}
}