{
  "type": "Feature",
  "properties": {
    "iso:country":"US",
    "sg:address":"800 S 3rd St",
    "sg:city":"Bismarck",
    "sg:classifiers":[
        {
            "category":"Travel",
            "subcategory":"Hotels & Motels",
            "type":"Entertainment"
        }
    ],
    "sg:phone":"+1 701 258 7700",
    "sg:postcode":"58504",
    "sg:province":"ND",
    "sg:tags":[
        "operation",
        "eating",
        "drinking"
    ],
    "wof:name":"Best Western Ramkota Hotel",
    "wof:placetype":"venue"
},
  "geometry": {"coordinates":[-100.787952,46.795089],"type":"Point"}
}