{
  "type": "Feature",
  "properties": {
    "iso:country":"US",
    "sg:address":"1608 16th St NW",
    "sg:city":"Minot",
    "sg:classifiers":[
        {
            "category":"Wholesale",
            "subcategory":"Farm Supplies",
            "type":"Manufacturing & Wholesale Goods"
        }
    ],
    "sg:phone":"+1 701 839 5646",
    "sg:postcode":"58703",
    "sg:province":"ND",
    "sg:tags":[
        "livestock"
    ],
    "wof:name":"Wce",
    "wof:placetype":"venue"
},
  "geometry": {"coordinates":[-101.317567,48.250008],"type":"Point"}
}