{
  "type": "Feature",
  "properties": {
    "iso:country":"US",
    "sg:address":"62 27th St S",
    "sg:city":"Fargo",
    "sg:classifiers":[
        {
            "category":"Building & Trades",
            "subcategory":"Construction",
            "type":"Services"
        }
    ],
    "sg:phone":"+1 701 365 0516",
    "sg:postcode":"58103",
    "sg:province":"ND",
    "sg:tags":[
        "painter"
    ],
    "wof:name":"Ethnics Painting",
    "wof:placetype":"venue"
},
  "geometry": {"coordinates":[-96.821153,46.874576],"type":"Point"}
}