{
  "type": "Feature",
  "properties": {
    "iso:country":"US",
    "sg:address":"101 E Main St",
    "sg:city":"Grassy Butte",
    "sg:classifiers":[
        {
            "category":"Building & Trades",
            "subcategory":"Construction",
            "type":"Services"
        }
    ],
    "sg:phone":"+1 701 863 6771",
    "sg:postcode":"58626",
    "sg:province":"ND",
    "sg:tags":[
        "general",
        "contractor"
    ],
    "wof:name":"Trotter Construction",
    "wof:placetype":"venue"
},
  "geometry": {"coordinates":[-102.61904,47.352623],"type":"Point"}
}