{
  "type": "Feature",
  "properties": {
    "addr:full":"206 Main St Dahlen ND 58224",
    "addr:housenumber":"206",
    "addr:postcode":"58224",
    "addr:street":"Main St",
    "iso:country":"US",
    "sg:address":"206 Main St",
    "sg:city":"Dahlen",
    "sg:classifiers":[
        {
            "category":"Organizations",
            "subcategory":"Religious Organization",
            "type":"Services"
        }
    ],
    "sg:phone":"+1 701 384 6104",
    "sg:postcode":"58224",
    "sg:province":"ND",
    "sg:tags":[
        "church"
    ],
    "wof:name":"Dahlen Lutheran Church",
    "wof:placetype":"venue"
},
  "geometry": {"coordinates":[-97.929575,48.156742],"type":"Point"}
}