{
  "type": "Feature",
  "properties": {
    "addr:full":"1001 24th Ave S Grand Forks ND 58201",
    "addr:housenumber":"1001",
    "addr:postcode":"58201",
    "addr:street":"24Th Ave S",
    "iso:country":"US",
    "sg:address":"1001 24th Ave S",
    "sg:city":"Grand Forks",
    "sg:classifiers":[
        {
            "category":"Organizations",
            "subcategory":"Religious Organization",
            "type":"Services"
        }
    ],
    "sg:phone":"+1 701 772 1893",
    "sg:postcode":"58201",
    "sg:province":"ND",
    "sg:tags":[
        "church"
    ],
    "wof:name":"Zion United Methodist Church",
    "wof:placetype":"venue"
},
  "geometry": {"coordinates":[-97.04197000000001,47.896736],"type":"Point"}
}