{
  "type": "Feature",
  "properties": {
    "addr:full":"115 D St S Richardton ND 58652",
    "addr:housenumber":"115",
    "addr:postcode":"58652",
    "addr:street":"D St S Richardton",
    "iso:country":"US",
    "sg:address":"115 D St S",
    "sg:city":"Richardton",
    "sg:classifiers":[
        {
            "category":"Government",
            "subcategory":"Office",
            "type":"Public Place"
        }
    ],
    "sg:phone":"+1 701 974 3911",
    "sg:postcode":"58652",
    "sg:province":"ND",
    "sg:tags":[
        "department",
        "transportation"
    ],
    "wof:name":"Transportation Department",
    "wof:placetype":"venue"
},
  "geometry": {"coordinates":[-102.31231200000001,46.881697],"type":"Point"}
}