{
  "type": "Feature",
  "properties": {
    "iso:country":"US",
    "sg:address":"9106 State Hwy 32",
    "sg:city":"Forman",
    "sg:classifiers":[
        {
            "category":"Government",
            "subcategory":"Office",
            "type":"Public Place"
        }
    ],
    "sg:phone":"+1 701 724 3677",
    "sg:postcode":"58032",
    "sg:province":"ND",
    "sg:tags":[
        "state",
        "program"
    ],
    "wof:name":"Transportation Dept",
    "wof:placetype":"venue"
},
  "geometry": {"coordinates":[-97.63357499999999,46.094555],"type":"Point"}
}