{
  "type": "Feature",
  "properties": {
    "iso:country":"US",
    "sg:address":"233 W Broadway Ave",
    "sg:city":"Bismarck",
    "sg:classifiers":[
        {
            "category":"Banks & Credit Unions",
            "subcategory":"Bank",
            "type":"Services"
        }
    ],
    "sg:phone":"+1 701 355 0569",
    "sg:postcode":"58501",
    "sg:province":"ND",
    "sg:tags":[
        "loan"
    ],
    "wof:name":"Moneystation Inc",
    "wof:placetype":"venue"
},
  "geometry": {"coordinates":[-100.793871,46.806496],"type":"Point"}
}