{
  "type": "Feature",
  "properties": {
    "iso:country":"US",
    "sg:address":"1999 47th Ave S",
    "sg:city":"Grand Forks",
    "sg:classifiers":[
        {
            "category":"Education",
            "subcategory":"School",
            "type":"Public Place"
        }
    ],
    "sg:phone":"+1 701 746 2345",
    "sg:postcode":"58201",
    "sg:province":"ND",
    "wof:name":"South Middle School",
    "wof:placetype":"venue"
},
  "geometry": {"coordinates":[-97.054829,47.874837],"type":"Point"}
}