{
  "type": "Feature",
  "properties": {
    "iso:country":"US",
    "sg:address":"1343 University Dr S",
    "sg:city":"Fargo",
    "sg:classifiers":[
        {
            "category":"Autos & Motor Vehicles",
            "subcategory":"Automobile Sales",
            "type":"Retail Goods"
        },
        {
            "category":"Retail",
            "subcategory":"Auto Repair",
            "type":"Services"
        }
    ],
    "sg:phone":"+1 701 293 0022",
    "sg:postcode":"58103",
    "sg:province":"ND",
    "sg:tags":[
        "dealers-used",
        "car",
        "used",
        "cars-wholesale"
    ],
    "wof:name":"Pauls Auto Center",
    "wof:placetype":"venue"
},
  "geometry": {"coordinates":[-96.79841999999999,46.860742],"type":"Point"}
}