{
  "type": "Feature",
  "properties": {
    "addr:full":"2881 Warwick Loop Bismarck ND 58504",
    "addr:housenumber":"2881",
    "addr:postcode":"58504",
    "addr:street":"Warwick Loop",
    "iso:country":"US",
    "sg:address":"2881 Warwick Loop",
    "sg:city":"Bismarck",
    "sg:classifiers":[
        {
            "category":"Organizations",
            "subcategory":"Religious Organization",
            "type":"Services"
        }
    ],
    "sg:phone":"+1 701 222 1796",
    "sg:postcode":"58504",
    "sg:province":"ND",
    "sg:tags":[
        "clergy"
    ],
    "wof:name":"Arnold Spain",
    "wof:placetype":"venue"
},
  "geometry": {"coordinates":[-100.79586500000001,46.771202],"type":"Point"}
}