{
  "type": "Feature",
  "properties": {
    "iso:country":"US",
    "sg:address":"1270 12th Ave NE",
    "sg:city":"Grand Forks",
    "sg:classifiers":[
        {
            "category":"Building & Trades",
            "subcategory":"Landscaping Services",
            "type":"Services"
        }
    ],
    "sg:phone":"+1 701 775 9704",
    "sg:postcode":"58201",
    "sg:province":"ND",
    "sg:tags":[
        "landscape",
        "contractor"
    ],
    "wof:name":"Wilson Landscaping",
    "wof:placetype":"venue"
},
  "geometry": {"coordinates":[-97.10246100000001,47.845943],"type":"Point"}
}