{
  "type": "Feature",
  "properties": {
    "iso:country":"US",
    "sg:address":"118 1st Ave W",
    "sg:city":"Williston",
    "sg:classifiers":[
        {
            "category":"Manufacturing",
            "subcategory":"Wood Products",
            "type":"Manufacturing & Wholesale Goods"
        }
    ],
    "sg:phone":"+1 701 774 1276",
    "sg:postcode":"58801",
    "sg:province":"ND",
    "sg:tags":[
        "mfg"
    ],
    "wof:name":"GPG Inc",
    "wof:placetype":"venue"
},
  "geometry": {"coordinates":[-103.623065,48.14522],"type":"Point"}
}