{
  "type": "Feature",
  "properties": {
    "iso:country":"US",
    "sg:address":"2551 45th St S",
    "sg:city":"Fargo",
    "sg:classifiers":[
        {
            "category":"Professional",
            "subcategory":"Management & Consulting",
            "type":"Services"
        }
    ],
    "sg:phone":"+1 701 277 9675",
    "sg:postcode":"58104",
    "sg:province":"ND",
    "sg:tags":[
        "personnel",
        "consultant"
    ],
    "wof:name":"Command Staffing",
    "wof:placetype":"venue"
},
  "geometry": {"coordinates":[-96.862134,46.843409],"type":"Point"}
}