{
  "type": "Feature",
  "properties": {
    "addr:full":"2601 S University Dr Fargo ND 58103",
    "addr:housenumber":"2601",
    "addr:postcode":"58103",
    "addr:street":"S University Dr",
    "iso:country":"US",
    "sg:address":"2601 S University Dr",
    "sg:city":"Fargo",
    "sg:classifiers":[
        {
            "category":"Restaurant",
            "type":"Food & Drink"
        }
    ],
    "sg:phone":"+1 701 232 4640",
    "sg:postcode":"58103",
    "sg:province":"ND",
    "wof:name":"Fortune House",
    "wof:placetype":"venue"
},
  "geometry": {"coordinates":[-96.798892,46.839116],"type":"Point"}
}