{
  "type": "Feature",
  "properties": {
    "iso:country":"US",
    "sg:address":"2940 Fiechtner Dr",
    "sg:city":"Fargo",
    "sg:classifiers":[
        {
            "category":"Retail",
            "subcategory":"Repair Shop",
            "type":"Services"
        }
    ],
    "sg:phone":"+1 701 237 5344",
    "sg:postcode":"58103",
    "sg:province":"ND",
    "wof:name":"Twin City Sharpening Inc",
    "wof:placetype":"venue"
},
  "geometry": {"coordinates":[-96.82786299999999,46.867233],"type":"Point"}
}