{
  "type": "Feature",
  "properties": {
    "addr:full":"1830 E Century Ave Bismarck ND 58503",
    "addr:housenumber":"1830",
    "addr:postcode":"58503",
    "addr:street":"E Century Ave",
    "iso:country":"US",
    "sg:address":"1830 E Century Ave",
    "sg:city":"Bismarck",
    "sg:classifiers":[
        {
            "category":"Education",
            "subcategory":"Dance Studio",
            "type":"Public Place"
        }
    ],
    "sg:phone":"+1 701 222 1052",
    "sg:postcode":"58503",
    "sg:province":"ND",
    "wof:name":"Alexs Dance Studio",
    "wof:placetype":"venue"
},
  "geometry": {"coordinates":[-100.76376,46.838131],"type":"Point"}
}