{
  "type": "Feature",
  "properties": {
    "iso:country":"US",
    "sg:address":"2208 Laforest Ave",
    "sg:city":"Bismarck",
    "sg:classifiers":[
        {
            "category":"Building & Trades",
            "subcategory":"Construction",
            "type":"Services"
        }
    ],
    "sg:phone":"+1 701 223 6903",
    "sg:postcode":"58501",
    "sg:province":"ND",
    "sg:tags":[
        "contractor"
    ],
    "wof:name":"A & E Siding & Construstion",
    "wof:placetype":"venue"
},
  "geometry": {"coordinates":[-100.75803999999999,46.821472],"type":"Point"}
}