{
  "type": "Feature",
  "properties": {
    "iso:country":"US",
    "sg:address":"17350 69th St SE",
    "sg:city":"Wahpeton",
    "sg:classifiers":[
        {
            "category":"Organizations",
            "subcategory":"Religious Organization",
            "type":"Services"
        }
    ],
    "sg:phone":"+1 701 553 8578",
    "sg:postcode":"58018",
    "sg:province":"ND",
    "sg:tags":[
        "church"
    ],
    "wof:name":"Bethany Lutheran Church",
    "wof:placetype":"venue"
},
  "geometry": {"coordinates":[-96.788792,46.412919],"type":"Point"}
}