{
  "type": "Feature",
  "properties": {
    "iso:country":"US",
    "sg:address":"324 Chestnut St",
    "sg:city":"Grand Forks",
    "sg:classifiers":[
        {
            "category":"Social Services",
            "subcategory":"Child Care",
            "type":"Services"
        }
    ],
    "sg:phone":"+1 701 772 3773",
    "sg:postcode":"58201",
    "sg:province":"ND",
    "wof:name":"United Day Nursery",
    "wof:placetype":"venue"
},
  "geometry": {"coordinates":[-97.030241,47.918694],"type":"Point"}
}