{
  "type": "Feature",
  "properties": {
    "iso:country":"US",
    "sg:address":"1520 24th Ave SW",
    "sg:city":"Minot",
    "sg:classifiers":[
        {
            "category":"Autos & Motor Vehicles",
            "subcategory":"Fuel & Gas Station",
            "type":"Retail Goods"
        }
    ],
    "sg:phone":"+1 701 852 5781",
    "sg:postcode":"58701",
    "sg:province":"ND",
    "sg:tags":[
        "oil"
    ],
    "wof:name":"Dakota Square Amoco",
    "wof:placetype":"venue"
},
  "geometry": {"coordinates":[-101.316766,48.207825],"type":"Point"}
}