{
  "type": "Feature",
  "properties": {
    "addr:full":"104 1st Ave S Jamestown ND 58401",
    "addr:housenumber":"104",
    "addr:postcode":"58401",
    "addr:street":"1St Ave S",
    "iso:country":"US",
    "sg:address":"104 1st Ave S",
    "sg:city":"Jamestown",
    "sg:classifiers":[
        {
            "category":"Building & Trades",
            "subcategory":"Construction",
            "type":"Services"
        },
        {
            "category":"Social Services",
            "type":"Services"
        }
    ],
    "sg:phone":"+1 701 253 8095",
    "sg:postcode":"58401",
    "sg:province":"ND",
    "sg:tags":[
        "youth",
        "house",
        "membership",
        "center",
        "organization"
    ],
    "wof:name":"Jamestown Asset Builders Inc",
    "wof:placetype":"venue"
},
  "geometry": {"coordinates":[-98.70856999999999,46.908639],"type":"Point"}
}