{
  "type": "Feature",
  "properties": {
    "addr:full":"301 12th St S Oakes ND 58474",
    "addr:housenumber":"301",
    "addr:postcode":"58474",
    "addr:street":"12Th St S",
    "iso:country":"US",
    "sg:address":"301 12th St S",
    "sg:city":"Oakes",
    "sg:classifiers":[
        {
            "category":"Shopping",
            "type":"Retail Goods"
        }
    ],
    "sg:phone":"+1 701 742 2651",
    "sg:postcode":"58474",
    "sg:province":"ND",
    "sg:tags":[
        "cosmetic",
        "perfume"
    ],
    "wof:name":"Betty's Hair Design & Tanning",
    "wof:placetype":"venue"
},
  "geometry": {"coordinates":[-98.08305799999999,46.135715],"type":"Point"}
}