{
  "type": "Feature",
  "properties": {
    "iso:country":"US",
    "sg:address":"3885 State Hwy 13",
    "sg:city":"Wishek",
    "sg:classifiers":[
        {
            "category":"Autos & Motor Vehicles",
            "subcategory":"Auto Supplies",
            "type":"Retail Goods"
        }
    ],
    "sg:phone":"+1 701 452 4200",
    "sg:postcode":"58495",
    "sg:province":"ND",
    "sg:tags":[
        "automobile",
        "parts"
    ],
    "wof:name":"Carquest Auto Parts",
    "wof:placetype":"venue"
},
  "geometry": {"coordinates":[-99.569084,46.25918],"type":"Point"}
}