{
  "type": "Feature",
  "properties": {
    "iso:country":"US",
    "sg:address":"233 W Rosser Ave",
    "sg:city":"Bismarck",
    "sg:classifiers":[
        {
            "category":"Manufacturing",
            "subcategory":"Printing",
            "type":"Manufacturing & Wholesale Goods"
        }
    ],
    "sg:phone":"+1 701 222 0370",
    "sg:postcode":"58501",
    "sg:province":"ND",
    "sg:tags":[
        "publisher",
        "software"
    ],
    "wof:name":"Midkota Solutions",
    "wof:placetype":"venue"
},
  "geometry": {"coordinates":[-100.793843,46.808582],"type":"Point"}
}