{
  "type": "Feature",
  "properties": {
    "iso:country":"US",
    "sg:address":"10632 60th St SE",
    "sg:city":"Litchville",
    "sg:classifiers":[
        {
            "category":"Farming",
            "subcategory":"Farm",
            "type":"Manufacturing & Wholesale Goods"
        }
    ],
    "sg:phone":"+1 701 762 4894",
    "sg:postcode":"58461",
    "sg:province":"ND",
    "sg:tags":[
        "crop",
        "general"
    ],
    "wof:name":"Tim Bubach",
    "wof:placetype":"venue"
},
  "geometry": {"coordinates":[-98.18163,46.543872],"type":"Point"}
}