{
  "type": "Feature",
  "properties": {
    "iso:country":"US",
    "sg:address":"2419 N 7th St",
    "sg:city":"Bismarck",
    "sg:classifiers":[
        {
            "category":"Shopping",
            "subcategory":"Gifts & Souvenirs",
            "type":"Retail Goods"
        }
    ],
    "sg:phone":"+1 701 221 0862",
    "sg:postcode":"58503",
    "sg:province":"ND",
    "wof:name":"Desired Baskets",
    "wof:placetype":"venue"
},
  "geometry": {"coordinates":[-100.781435,46.834505],"type":"Point"}
}