{
  "type": "Feature",
  "properties": {
    "iso:country":"US",
    "sg:address":"6050 Co Rd 17 S",
    "sg:city":"Fargo",
    "sg:classifiers":[
        {
            "category":"Autos & Motor Vehicles",
            "subcategory":"Automobile Sales",
            "type":"Retail Goods"
        }
    ],
    "sg:phone":"+1 701 282 9368",
    "sg:postcode":"58104",
    "sg:province":"ND",
    "wof:name":"Golf Car North",
    "wof:placetype":"venue"
},
  "geometry": {"coordinates":[-96.902733,46.793371],"type":"Point"}
}