{
  "type": "Feature",
  "properties": {
    "addr:full":"2071 68th Ave NW Ryder ND 58779",
    "addr:housenumber":"2071",
    "addr:postcode":"58779",
    "addr:street":"68Th Ave Nw",
    "iso:country":"US",
    "sg:address":"2071 68th Ave NW",
    "sg:city":"Ryder",
    "sg:phone":"+1 701 743 4284",
    "sg:postcode":"58779",
    "sg:province":"ND",
    "sg:tags":[
        "farm",
        "wheat"
    ],
    "wof:name":"Todd Zahnow Farms Inc",
    "wof:placetype":"venue"
},
  "geometry": {"coordinates":[-102.04350599999999,47.717044],"type":"Point"}
}