{
  "type": "Feature",
  "properties": {
    "addr:full":"2500 Centennial Rd Bismarck ND 58503",
    "addr:housenumber":"2500",
    "addr:postcode":"58503",
    "addr:street":"Centennial Rd",
    "iso:country":"US",
    "sg:address":"2500 Centennial Rd",
    "sg:city":"Bismarck",
    "sg:classifiers":[
        {
            "category":"Farming",
            "subcategory":"Livestock Farm",
            "type":"Manufacturing & Wholesale Goods"
        }
    ],
    "sg:phone":"+1 701 223 7201",
    "sg:postcode":"58503",
    "sg:province":"ND",
    "sg:tags":[
        "beef",
        "feedlot",
        "cattle"
    ],
    "wof:name":"Lonnie Horner",
    "wof:placetype":"venue"
},
  "geometry": {"coordinates":[-100.73064599999999,46.832263],"type":"Point"}
}