{
  "type": "Feature",
  "properties": {
    "iso:country":"US",
    "sg:address":"228 3rd Ave",
    "sg:city":"Enderlin",
    "sg:classifiers":[
        {
            "category":"Insurance",
            "subcategory":"Insurance Agent",
            "type":"Services"
        }
    ],
    "sg:phone":"+1 701 437 3103",
    "sg:postcode":"58027",
    "sg:province":"ND",
    "sg:website":"www.tri-county.com",
    "wof:name":"Tri-County Insurance & Leasing",
    "wof:placetype":"venue"
},
  "geometry": {"coordinates":[-97.602521,46.624427],"type":"Point"}
}