{
  "type": "Feature",
  "properties": {
    "iso:country":"US",
    "sg:address":"5347 10th St NE",
    "sg:city":"Cathay",
    "sg:classifiers":[
        {
            "category":"Real Estate",
            "subcategory":"Developer",
            "type":"Services"
        }
    ],
    "sg:phone":"+1 701 984 2400",
    "sg:postcode":"58422",
    "sg:province":"ND",
    "sg:tags":[
        "cemetery"
    ],
    "wof:name":"Cathay Cemetery Association",
    "wof:placetype":"venue"
},
  "geometry": {"coordinates":[-99.405648,47.558592],"type":"Point"}
}