{
  "type": "Feature",
  "properties": {
    "addr:full":"1120 College Dr Bismarck ND 58501",
    "addr:housenumber":"1120",
    "addr:postcode":"58501",
    "addr:street":"College Dr",
    "iso:country":"US",
    "sg:address":"1120 College Dr",
    "sg:city":"Bismarck",
    "sg:classifiers":[
        {
            "category":"Banks & Credit Unions",
            "subcategory":"Investment Brokerage",
            "type":"Services"
        }
    ],
    "sg:phone":"+1 701 255 1551",
    "sg:postcode":"58501",
    "sg:province":"ND",
    "sg:tags":[
        "advisory",
        "financial"
    ],
    "sg:website":"www.lpl.com",
    "wof:name":"LPL Financial Svc",
    "wof:placetype":"venue"
},
  "geometry": {"coordinates":[-100.80758,46.82257],"type":"Point"}
}