{
  "type": "Feature",
  "properties": {
    "addr:full":"1833 S University Dr Fargo ND 58103",
    "addr:housenumber":"1833",
    "addr:postcode":"58103",
    "addr:street":"S University Dr",
    "iso:country":"US",
    "sg:address":"1833 S University Dr",
    "sg:city":"Fargo",
    "sg:classifiers":[
        {
            "category":"Banks & Credit Unions",
            "subcategory":"Bank",
            "type":"Services"
        }
    ],
    "sg:phone":"+1 701 293 7178",
    "sg:postcode":"58103",
    "sg:province":"ND",
    "sg:tags":[
        "cashing",
        "check"
    ],
    "wof:name":"Cash Connection",
    "wof:placetype":"venue"
},
  "geometry": {"coordinates":[-96.79871300000001,46.851095],"type":"Point"}
}