{
  "type": "Feature",
  "properties": {
    "iso:country":"US",
    "sg:address":"420 Main Ave",
    "sg:city":"Lemmon",
    "sg:classifiers":[
        {
            "category":"Insurance",
            "subcategory":"Insurance Agent",
            "type":"Services"
        }
    ],
    "sg:phone":"+1 605 374 3777",
    "sg:postcode":"57638",
    "sg:province":"ND",
    "wof:name":"State Farm Insurance",
    "wof:placetype":"venue"
},
  "geometry": {"coordinates":[-102.159271,45.940778],"type":"Point"}
}