{
  "type": "Feature",
  "properties": {
    "iso:country":"US",
    "sg:address":"1000 N 42nd St",
    "sg:city":"Grand Forks",
    "sg:classifiers":[
        {
            "category":"Travel",
            "subcategory":"Hotels & Motels",
            "type":"Entertainment"
        }
    ],
    "sg:phone":"+1 701 775 0555",
    "sg:postcode":"58203",
    "sg:province":"ND",
    "sg:website":"www.americasbestvalueinn.com",
    "wof:name":"Best Value Inn Of Grand Forks",
    "wof:placetype":"venue"
},
  "geometry": {"coordinates":[-97.088038,47.927484],"type":"Point"}
}