{
  "type": "Feature",
  "properties": {
    "iso:country":"US",
    "sg:address":"1975 92nd St NW",
    "sg:city":"Maxbass",
    "sg:phone":"+1 701 268 3156",
    "sg:postcode":"58760",
    "sg:province":"ND",
    "sg:tags":[
        "farm",
        "wheat"
    ],
    "wof:name":"Larry Romine",
    "wof:placetype":"venue"
},
  "geometry": {"coordinates":[-101.126941,48.748634],"type":"Point"}
}