{
  "type": "Feature",
  "properties": {
    "addr:full":"125 Main St Milnor ND 58060",
    "addr:housenumber":"125",
    "addr:postcode":"58060",
    "addr:street":"Main St",
    "iso:country":"US",
    "sg:address":"125 Main St",
    "sg:city":"Milnor",
    "sg:classifiers":[
        {
            "category":"Personal",
            "subcategory":"Beauty Salon",
            "type":"Services"
        }
    ],
    "sg:phone":"+1 701 427 9409",
    "sg:postcode":"58060",
    "sg:province":"ND",
    "wof:name":"Ione's Beauty Shop",
    "wof:placetype":"venue"
},
  "geometry": {"coordinates":[-97.45184399999999,46.25612],"type":"Point"}
}