{
  "type": "Feature",
  "properties": {
    "addr:full":"7999 17th Ave N Upham ND 58789",
    "addr:housenumber":"7999",
    "addr:postcode":"58789",
    "addr:street":"17Th Ave N Upham",
    "iso:country":"US",
    "sg:address":"7999 17th Ave N",
    "sg:city":"Upham",
    "sg:classifiers":[
        {
            "category":"Farming",
            "subcategory":"Nursery",
            "type":"Manufacturing & Wholesale Goods"
        }
    ],
    "sg:phone":"+1 701 272 6266",
    "sg:postcode":"58789",
    "sg:province":"ND",
    "sg:tags":[
        "greenhouse"
    ],
    "wof:name":"Bethke Gardens",
    "wof:placetype":"venue"
},
  "geometry": {"coordinates":[-100.95102300000001,48.560103],"type":"Point"}
}