{
  "type": "Feature",
  "properties": {
    "iso:country":"US",
    "sg:address":"11525 33rd St SE",
    "sg:city":"Valley City",
    "sg:classifiers":[
        {
            "category":"Building & Trades",
            "subcategory":"Construction",
            "type":"Services"
        }
    ],
    "sg:phone":"+1 701 845 2767",
    "sg:postcode":"58072",
    "sg:province":"ND",
    "sg:tags":[
        "house"
    ],
    "wof:name":"Stack Construction",
    "wof:placetype":"venue"
},
  "geometry": {"coordinates":[-98.036176,46.935028],"type":"Point"}
}