{
  "type": "Feature",
  "properties": {
    "addr:full":"107 S Main St Bowman ND 58623",
    "addr:housenumber":"107",
    "addr:postcode":"58623",
    "addr:street":"S Main St",
    "iso:country":"US",
    "sg:address":"107 S Main St",
    "sg:city":"Bowman",
    "sg:classifiers":[
        {
            "category":"Health Services",
            "subcategory":"Optometrist",
            "type":"Services"
        }
    ],
    "sg:phone":"+1 701 523 3700",
    "sg:postcode":"58623",
    "sg:province":"ND",
    "wof:name":"Advanced Vision Ctr",
    "wof:placetype":"venue"
},
  "geometry": {"coordinates":[-103.394902,46.181154],"type":"Point"}
}