{
  "type": "Feature",
  "properties": {
    "addr:full":"219 1st Ave S Jamestown ND 58401",
    "addr:housenumber":"219",
    "addr:postcode":"58401",
    "addr:street":"1St Ave S",
    "iso:country":"US",
    "sg:address":"219 1st Ave S",
    "sg:city":"Jamestown",
    "sg:classifiers":[
        {
            "category":"Real Estate",
            "subcategory":"Real Estate Agent",
            "type":"Services"
        }
    ],
    "sg:phone":"+1 701 952 5500",
    "sg:postcode":"58401",
    "sg:province":"ND",
    "wof:name":"Midstate Realty Inc",
    "wof:placetype":"venue"
},
  "geometry": {"coordinates":[-98.70837899999999,46.907401],"type":"Point"}
}