{
  "type": "Feature",
  "properties": {
    "iso:country":"US",
    "sg:address":"304 6th Ave",
    "sg:city":"Litchville",
    "sg:classifiers":[
        {
            "category":"Education",
            "subcategory":"School",
            "type":"Public Place"
        }
    ],
    "sg:phone":"+1 701 762 4245",
    "sg:postcode":"58461",
    "sg:province":"ND",
    "sg:website":"www.litchville-marion.k12.nd.us",
    "wof:name":"Litchville Marion School Dist",
    "wof:placetype":"venue"
},
  "geometry": {"coordinates":[-98.189547,46.655741],"type":"Point"}
}