{
  "type": "Feature",
  "properties": {
    "iso:country":"US",
    "sg:address":"5003 4th Ave N",
    "sg:city":"Grand Forks",
    "sg:classifiers":[
        {
            "category":"Freight",
            "type":"Transportation"
        }
    ],
    "sg:phone":"+1 701 772 8573",
    "sg:postcode":"58203",
    "sg:province":"ND",
    "sg:tags":[
        "operator",
        "local",
        "trucking"
    ],
    "wof:name":"E&G Trucking",
    "wof:placetype":"venue"
},
  "geometry": {"coordinates":[-97.101557,47.924167],"type":"Point"}
}