{
  "type": "Feature",
  "properties": {
    "iso:country":"US",
    "sg:address":"716 Madison Ave",
    "sg:city":"Portland",
    "sg:classifiers":[
        {
            "category":"Freight",
            "type":"Transportation"
        }
    ],
    "sg:phone":"+1 701 786 4263",
    "sg:postcode":"58274",
    "sg:province":"ND",
    "sg:tags":[
        "grain",
        "elevator"
    ],
    "sg:website":"www.mayportfarmers.com",
    "wof:name":"Mayport Farmers Co-Op",
    "wof:placetype":"venue"
},
  "geometry": {"coordinates":[-97.363964,47.498813],"type":"Point"}
}