{
  "type": "Feature",
  "properties": {
    "iso:country":"US",
    "sg:address":"1304 140th Ave SE",
    "sg:city":"Page",
    "sg:classifiers":[
        {
            "category":"Farming",
            "subcategory":"Farm",
            "type":"Manufacturing & Wholesale Goods"
        }
    ],
    "sg:phone":"+1 701 668 2795",
    "sg:postcode":"58064",
    "sg:province":"ND",
    "sg:tags":[
        "crop",
        "general"
    ],
    "wof:name":"Koenig Farms",
    "wof:placetype":"venue"
},
  "geometry": {"coordinates":[-97.536417,47.223866],"type":"Point"}
}