{
  "type": "Feature",
  "properties": {
    "addr:full":"334 E Central Ave Bismarck ND 58501",
    "addr:housenumber":"334",
    "addr:postcode":"58501",
    "addr:street":"E Central Ave",
    "iso:country":"US",
    "sg:address":"334 E Central Ave",
    "sg:city":"Bismarck",
    "sg:classifiers":[
        {
            "category":"Professional",
            "subcategory":"Business Services",
            "type":"Services"
        }
    ],
    "sg:phone":"+1 701 255 4476",
    "sg:postcode":"58501",
    "sg:province":"ND",
    "wof:name":"Wood Wright Enterprises Inc",
    "wof:placetype":"venue"
},
  "geometry": {"coordinates":[-100.786254,46.826468],"type":"Point"}
}