{
  "type": "Feature",
  "properties": {
    "iso:country":"US",
    "sg:address":"710 S Washington St",
    "sg:city":"Bismarck",
    "sg:classifiers":[
        {
            "category":"Restaurant",
            "type":"Food & Drink"
        }
    ],
    "sg:phone":"+1 701 258 0040",
    "sg:postcode":"58504",
    "sg:province":"ND",
    "sg:website":"www.greenmill.com",
    "wof:name":"Green Mill Restaurant",
    "wof:placetype":"venue"
},
  "geometry": {"coordinates":[-100.79452999999999,46.797352],"type":"Point"}
}