{
  "type": "Feature",
  "properties": {
    "addr:full":"1000 36th St S Fargo ND 58103",
    "addr:housenumber":"1000",
    "addr:postcode":"58103",
    "addr:street":"36Th St S",
    "iso:country":"US",
    "sg:address":"1000 36th St S",
    "sg:city":"Fargo",
    "sg:classifiers":[
        {
            "category":"Freight",
            "type":"Transportation"
        }
    ],
    "sg:phone":"+1 701 232 9452",
    "sg:postcode":"58103",
    "sg:province":"ND",
    "sg:tags":[
        "commercial",
        "storage",
        "general"
    ],
    "wof:name":"Fargo Space Center",
    "wof:placetype":"venue"
},
  "geometry": {"coordinates":[-96.84062900000001,46.865525],"type":"Point"}
}