{
  "type": "Feature",
  "properties": {
    "iso:country":"US",
    "sg:address":"720 Summit Ave",
    "sg:city":"Grafton",
    "sg:classifiers":[
        {
            "category":"Government",
            "subcategory":"Office",
            "type":"Public Place"
        }
    ],
    "sg:phone":"+1 701 352 2460",
    "sg:postcode":"58237",
    "sg:province":"ND",
    "wof:name":"Walsh County Garage",
    "wof:placetype":"venue"
},
  "geometry": {"coordinates":[-97.403959,48.417297],"type":"Point"}
}