{
  "type": "Feature",
  "properties": {
    "iso:country":"US",
    "sg:address":"3518 6th Ave N",
    "sg:city":"Grand Forks",
    "sg:classifiers":[
        {
            "category":"Building & Trades",
            "subcategory":"Construction",
            "type":"Services"
        }
    ],
    "sg:phone":"+1 701 746 7639",
    "sg:postcode":"58203",
    "sg:province":"ND",
    "sg:tags":[
        "hanging",
        "contractor"
    ],
    "wof:name":"Lewandowski Painting",
    "wof:placetype":"venue"
},
  "geometry": {"coordinates":[-97.080804,47.925845],"type":"Point"}
}