{
  "type": "Feature",
  "properties": {
    "addr:full":"8510 52nd St SW Richardton ND 58641",
    "addr:housenumber":"8510",
    "addr:postcode":"58641",
    "addr:street":"52Nd St Sw",
    "iso:country":"US",
    "sg:address":"8510 52nd St SW",
    "sg:city":"Richardton",
    "sg:classifiers":[
        {
            "category":"Farming",
            "subcategory":"Dairy Farm",
            "type":"Manufacturing & Wholesale Goods"
        }
    ],
    "sg:phone":"+1 701 974 3384",
    "sg:postcode":"58641",
    "sg:province":"ND",
    "sg:tags":[
        "b",
        "wheat",
        "ranch",
        "operates",
        "oat",
        "cattle"
    ],
    "wof:name":"Messer Beaver Creek Ranch",
    "wof:placetype":"venue"
},
  "geometry": {"coordinates":[-102.246725,46.660697],"type":"Point"}
}