{
  "type": "Feature",
  "properties": {
    "iso:country":"US",
    "sg:address":"111 Main St N",
    "sg:city":"Tioga",
    "sg:classifiers":[
        {
            "category":"Health Services",
            "subcategory":"Doctor",
            "type":"Services"
        }
    ],
    "sg:phone":"+1 701 664 2582",
    "sg:postcode":"58852",
    "sg:province":"ND",
    "sg:tags":[
        "dentist"
    ],
    "wof:name":"David C Carlson DDS",
    "wof:placetype":"venue"
},
  "geometry": {"coordinates":[-102.938221,48.397044],"type":"Point"}
}