{
  "type": "Feature",
  "properties": {
    "addr:full":"3306 Primrose Ct Grand Forks ND 58201",
    "addr:housenumber":"3306",
    "addr:postcode":"58201",
    "addr:street":"Primrose Ct",
    "iso:country":"US",
    "sg:address":"3306 Primrose Ct",
    "sg:city":"Grand Forks",
    "sg:classifiers":[
        {
            "category":"Social Services",
            "subcategory":"Child Care",
            "type":"Services"
        }
    ],
    "sg:phone":"+1 701 775 0444",
    "sg:postcode":"58201",
    "sg:province":"ND",
    "sg:tags":[
        "day"
    ],
    "wof:name":"Chromys Group Child Care Home",
    "wof:placetype":"venue"
},
  "geometry": {"coordinates":[-97.075513,47.901553],"type":"Point"}
}