{
  "type": "Feature",
  "properties": {
    "iso:country":"US",
    "sg:address":"1508 5th Ave N",
    "sg:city":"Fargo",
    "sg:classifiers":[
        {
            "category":"Wholesale",
            "subcategory":"Hardware",
            "type":"Manufacturing & Wholesale Goods"
        }
    ],
    "sg:phone":"+1 701 237 4096",
    "sg:postcode":"58102",
    "sg:province":"ND",
    "sg:tags":[
        "equipment",
        "heating",
        "system"
    ],
    "wof:name":"Northwest Iron Fireman Inc",
    "wof:placetype":"venue"
},
  "geometry": {"coordinates":[-96.804744,46.881494],"type":"Point"}
}