{
  "type": "Feature",
  "properties": {
    "iso:country":"US",
    "sg:address":"1201 7th Ave E",
    "sg:city":"West Fargo",
    "sg:classifiers":[
        {
            "category":"Organizations",
            "subcategory":"Professional Association",
            "type":"Services"
        }
    ],
    "sg:phone":"+1 701 277 9331",
    "sg:postcode":"58078",
    "sg:province":"ND",
    "wof:name":"West Fargo Hockey Assn",
    "wof:placetype":"venue"
},
  "geometry": {"coordinates":[-96.87230099999999,46.869223],"type":"Point"}
}