{
  "type": "Feature",
  "properties": {
    "iso:country":"US",
    "sg:address":"330 Main Ave",
    "sg:city":"Fargo",
    "sg:classifiers":[
        {
            "category":"Autos & Motor Vehicles",
            "subcategory":"Fuel & Gas Station",
            "type":"Retail Goods"
        }
    ],
    "sg:phone":"+1 701 293 6460",
    "sg:postcode":"58103",
    "sg:province":"ND",
    "sg:tags":[
        "oil"
    ],
    "wof:name":"Gateway Service Ctr Mobil",
    "wof:placetype":"venue"
},
  "geometry": {"coordinates":[-96.783168,46.873938],"type":"Point"}
}