{
  "type": "Feature",
  "properties": {
    "iso:country":"US",
    "sg:address":"738 Front St",
    "sg:city":"Casselton",
    "sg:classifiers":[
        {
            "category":"Social Services",
            "subcategory":"Child Care",
            "type":"Services"
        }
    ],
    "sg:phone":"+1 701 347 5201",
    "sg:postcode":"58012",
    "sg:province":"ND",
    "wof:name":"Play Corner",
    "wof:placetype":"venue"
},
  "geometry": {"coordinates":[-97.210937,46.900551],"type":"Point"}
}