{
  "type": "Feature",
  "properties": {
    "addr:full":"3001 Twin City Dr Mandan ND 58554",
    "addr:housenumber":"3001",
    "addr:postcode":"58554",
    "addr:street":"Twin City Dr",
    "iso:country":"US",
    "sg:address":"3001 Twin City Dr",
    "sg:city":"Mandan",
    "sg:classifiers":[
        {
            "category":"Professional",
            "subcategory":"Computer Services",
            "type":"Services"
        }
    ],
    "sg:phone":"+1 701 663 6785",
    "sg:postcode":"58554",
    "sg:province":"ND",
    "wof:name":"Dakota Geeks On Call",
    "wof:placetype":"venue"
},
  "geometry": {"coordinates":[-100.857477,46.8267],"type":"Point"}
}