{
  "type": "Feature",
  "properties": {
    "addr:full":"4 1st Ave SE Kulm ND 58456",
    "addr:housenumber":"4",
    "addr:postcode":"58456",
    "addr:street":"1St Ave Se",
    "iso:country":"US",
    "sg:address":"4 1st Ave SE",
    "sg:city":"Kulm",
    "sg:classifiers":[
        {
            "category":"Health Services",
            "subcategory":"Doctor",
            "type":"Services"
        }
    ],
    "sg:phone":"+1 701 647 2722",
    "sg:postcode":"58456",
    "sg:province":"ND",
    "sg:tags":[
        "clinic"
    ],
    "wof:name":"KULM Clinic",
    "wof:placetype":"venue"
},
  "geometry": {"coordinates":[-98.947306,46.302417],"type":"Point"}
}