{
  "type": "Feature",
  "properties": {
    "addr:full":"602 2nd St N Casselton ND 58012",
    "addr:housenumber":"602",
    "addr:postcode":"58012",
    "addr:street":"2Nd St N Casselton",
    "iso:country":"US",
    "sg:address":"602 2nd St N",
    "sg:city":"Casselton",
    "sg:classifiers":[
        {
            "category":"Organizations",
            "subcategory":"Religious Organization",
            "type":"Services"
        }
    ],
    "sg:phone":"+1 701 347 4289",
    "sg:postcode":"58012",
    "sg:province":"ND",
    "sg:tags":[
        "church"
    ],
    "wof:name":"Martin's Lutheran Church",
    "wof:placetype":"venue"
},
  "geometry": {"coordinates":[-97.212673,46.902758],"type":"Point"}
}