{
  "type": "Feature",
  "properties": {
    "iso:country":"US",
    "sg:address":"3645 29th Ave NE",
    "sg:city":"Gilby",
    "sg:classifiers":[
        {
            "category":"Farming",
            "subcategory":"Livestock Farm",
            "type":"Manufacturing & Wholesale Goods"
        }
    ],
    "sg:phone":"+1 701 865 4295",
    "sg:postcode":"58235",
    "sg:province":"ND",
    "sg:tags":[
        "beef",
        "feedlot",
        "cattle"
    ],
    "wof:name":"Hancock Farm",
    "wof:placetype":"venue"
},
  "geometry": {"coordinates":[-97.611553,48.093328],"type":"Point"}
}