{
  "type": "Feature",
  "properties": {
    "iso:country":"US",
    "sg:address":"1813 5th Ave S",
    "sg:city":"Fargo",
    "sg:classifiers":[
        {
            "category":"Personal",
            "subcategory":"Beauty Salon",
            "type":"Services"
        }
    ],
    "sg:phone":"+1 701 235 3740",
    "sg:postcode":"58103",
    "sg:province":"ND",
    "sg:tags":[
        "manicuring"
    ],
    "wof:name":"Fran's House Of Nails",
    "wof:placetype":"venue"
},
  "geometry": {"coordinates":[-96.81315499999999,46.869851],"type":"Point"}
}