{
  "type": "Feature",
  "properties": {
    "addr:full":"702 8th Ave NE Mandan ND 58554",
    "addr:housenumber":"702",
    "addr:postcode":"58554",
    "addr:street":"8Th Ave Ne",
    "iso:country":"US",
    "sg:address":"702 8th Ave NE",
    "sg:city":"Mandan",
    "sg:classifiers":[
        {
            "category":"Building & Trades",
            "subcategory":"Construction",
            "type":"Services"
        }
    ],
    "sg:phone":"+1 701 663 3554",
    "sg:postcode":"58554",
    "sg:province":"ND",
    "sg:tags":[
        "house"
    ],
    "wof:name":"Homes Plus",
    "wof:placetype":"venue"
},
  "geometry": {"coordinates":[-100.881626,46.833606],"type":"Point"}
}