{
  "type": "Feature",
  "properties": {
    "iso:country":"US",
    "sg:address":"121 1st Ave SE",
    "sg:city":"Mayville",
    "sg:classifiers":[
        {
            "category":"Retail",
            "subcategory":"Auto Repair",
            "type":"Services"
        }
    ],
    "sg:phone":"+1 701 786 3587",
    "sg:postcode":"58257",
    "sg:province":"ND",
    "sg:tags":[
        "body",
        "automobile",
        "painting"
    ],
    "wof:name":"Torgeson Body Shop Inc",
    "wof:placetype":"venue"
},
  "geometry": {"coordinates":[-97.32441,47.499228],"type":"Point"}
}