{
  "type": "Feature",
  "properties": {
    "addr:full":"1303 14th St S Fargo ND 58103",
    "addr:housenumber":"1303",
    "addr:postcode":"58103",
    "addr:street":"14Th St S",
    "iso:country":"US",
    "sg:address":"1303 14th St S",
    "sg:city":"Fargo",
    "sg:classifiers":[
        {
            "category":"Building & Trades",
            "subcategory":"Construction",
            "type":"Services"
        }
    ],
    "sg:phone":"+1 701 235 7106",
    "sg:postcode":"58103",
    "sg:province":"ND",
    "sg:tags":[
        "roofing",
        "contractor"
    ],
    "wof:name":"Quality Roofing Plus",
    "wof:placetype":"venue"
},
  "geometry": {"coordinates":[-96.801571,46.859642],"type":"Point"}
}