{
  "type": "Feature",
  "properties": {
    "iso:country":"US",
    "sg:address":"1840 Revere Dr",
    "sg:city":"Bismarck",
    "sg:classifiers":[
        {
            "category":"Wholesale",
            "subcategory":"Vending Machines",
            "type":"Manufacturing & Wholesale Goods"
        }
    ],
    "sg:phone":"+1 701 223 1102",
    "sg:postcode":"58501",
    "sg:province":"ND",
    "sg:website":"www.delmarvending.com",
    "wof:name":"Del-Mar Vending",
    "wof:placetype":"venue"
},
  "geometry": {"coordinates":[-100.725335,46.824889],"type":"Point"}
}