{
  "type": "Feature",
  "properties": {
    "addr:full":"8681 145th Ave NE St Thomas ND 58276",
    "addr:housenumber":"8681",
    "addr:postcode":"58276",
    "addr:street":"145Th Ave Ne",
    "iso:country":"US",
    "sg:address":"8681 145th Ave NE",
    "sg:city":"St Thomas",
    "sg:classifiers":[
        {
            "category":"Farming",
            "subcategory":"Farm",
            "type":"Manufacturing & Wholesale Goods"
        }
    ],
    "sg:phone":"+1 701 257 6564",
    "sg:postcode":"58276",
    "sg:province":"ND",
    "sg:tags":[
        "crop",
        "general"
    ],
    "wof:name":"Heuchert Brothers Farm Shop",
    "wof:placetype":"venue"
},
  "geometry": {"coordinates":[-97.51307300000001,48.661741],"type":"Point"}
}