{
  "type": "Feature",
  "properties": {
    "addr:full":"11851 5th St SE Cooperstown ND 58425",
    "addr:housenumber":"11851",
    "addr:postcode":"58425",
    "addr:street":"5Th St Se",
    "iso:country":"US",
    "sg:address":"11851 5th St SE",
    "sg:city":"Cooperstown",
    "sg:classifiers":[
        {
            "category":"Retail",
            "subcategory":"Animal Services",
            "type":"Services"
        }
    ],
    "sg:phone":"+1 701 797 3488",
    "sg:postcode":"58425",
    "sg:province":"ND",
    "sg:tags":[
        "breeder",
        "horse"
    ],
    "wof:name":"Schmidt Quarter Horses",
    "wof:placetype":"venue"
},
  "geometry": {"coordinates":[-98.018776,47.340863],"type":"Point"}
}