{
  "type": "Feature",
  "properties": {
    "addr:full":"112 2nd St SW Jamestown ND 58401",
    "addr:housenumber":"112",
    "addr:postcode":"58401",
    "addr:street":"2Nd St Sw",
    "iso:country":"US",
    "sg:address":"112 2nd St SW",
    "sg:city":"Jamestown",
    "sg:classifiers":[
        {
            "category":"Retail",
            "subcategory":"Photofinishing",
            "type":"Services"
        }
    ],
    "sg:phone":"+1 701 252 8883",
    "sg:postcode":"58401",
    "sg:province":"ND",
    "sg:tags":[
        "photo",
        "finishing"
    ],
    "wof:name":"King Photography",
    "wof:placetype":"venue"
},
  "geometry": {"coordinates":[-98.70909399999999,46.907701],"type":"Point"}
}