{
  "type": "Feature",
  "properties": {
    "addr:full":"802 1st Ave SE Belfield ND 58622",
    "addr:housenumber":"802",
    "addr:postcode":"58622",
    "addr:street":"1St Ave Se",
    "iso:country":"US",
    "sg:address":"802 1st Ave SE",
    "sg:city":"Belfield",
    "sg:phone":"+1 701 575 8452",
    "sg:postcode":"58622",
    "sg:province":"ND",
    "sg:tags":[
        "gas"
    ],
    "wof:name":"Cenex Propane",
    "wof:placetype":"venue"
},
  "geometry": {"coordinates":[-103.184478,46.880601],"type":"Point"}
}