{
  "type": "Feature",
  "properties": {
    "iso:country":"US",
    "sg:address":"1761 3rd Ave W",
    "sg:city":"Dickinson",
    "sg:classifiers":[
        {
            "category":"Shopping",
            "subcategory":"Department Store",
            "type":"Retail Goods"
        }
    ],
    "sg:phone":"+1 701 227 1861",
    "sg:postcode":"58601",
    "sg:province":"ND",
    "sg:website":"www.kmart.com",
    "wof:name":"Kmart",
    "wof:placetype":"venue"
},
  "geometry": {"coordinates":[-102.789806,46.901073],"type":"Point"}
}