{
  "type": "Feature",
  "properties": {
    "iso:country":"US",
    "sg:address":"1106 S 17th St",
    "sg:city":"Grand Forks",
    "sg:classifiers":[
        {
            "category":"Organizations",
            "subcategory":"Religious Organization",
            "type":"Services"
        }
    ],
    "sg:phone":"+1 701 335 2442",
    "sg:postcode":"58201",
    "sg:province":"ND",
    "sg:tags":[
        "church"
    ],
    "wof:name":"Faith Community Church",
    "wof:placetype":"venue"
},
  "geometry": {"coordinates":[-97.051191,47.910258],"type":"Point"}
}