{
  "type": "Feature",
  "properties": {
    "iso:country":"US",
    "sg:address":"1130 N 5th St",
    "sg:city":"Grand Forks",
    "sg:classifiers":[
        {
            "category":"Arts & Performance",
            "subcategory":"Theater",
            "type":"Entertainment"
        }
    ],
    "sg:phone":"+1 701 775 5121",
    "sg:postcode":"58203",
    "sg:province":"ND",
    "sg:tags":[
        "band",
        "orchestra"
    ],
    "wof:name":"Dick King Classic Swing Band",
    "wof:placetype":"venue"
},
  "geometry": {"coordinates":[-97.048568,47.932749],"type":"Point"}
}