{
  "type": "Feature",
  "properties": {
    "addr:full":"320 Main St SW Forman ND 58032",
    "addr:housenumber":"320",
    "addr:postcode":"58032",
    "addr:street":"Main St Sw",
    "iso:country":"US",
    "sg:address":"320 Main St SW",
    "sg:city":"Forman",
    "sg:classifiers":[
        {
            "category":"Bars & Pubs",
            "type":"Food & Drink"
        }
    ],
    "sg:phone":"+1 701 724 3231",
    "sg:postcode":"58032",
    "sg:province":"ND",
    "wof:name":"No Name Bar",
    "wof:placetype":"venue"
},
  "geometry": {"coordinates":[-97.636297,46.107352],"type":"Point"}
}