{
  "type": "Feature",
  "properties": {
    "iso:country":"US",
    "sg:address":"1481 22nd St NE",
    "sg:city":"Anamoose",
    "sg:classifiers":[
        {
            "category":"Real Estate",
            "subcategory":"Real Estate Operator",
            "type":"Services"
        }
    ],
    "sg:phone":"+1 701 465 3522",
    "sg:postcode":"58710",
    "sg:province":"ND",
    "sg:tags":[
        "property",
        "lessor"
    ],
    "wof:name":"Cicely Schuh Farm",
    "wof:placetype":"venue"
},
  "geometry": {"coordinates":[-100.266114,47.731865],"type":"Point"}
}