{
  "type": "Feature",
  "properties": {
    "iso:country":"US",
    "sg:address":"216 Main St",
    "sg:city":"Lakota",
    "sg:classifiers":[
        {
            "category":"Food & Beverages",
            "subcategory":"Groceries & Convenience Stores",
            "type":"Retail Goods"
        }
    ],
    "sg:phone":"+1 701 247 2822",
    "sg:postcode":"58344",
    "sg:province":"ND",
    "sg:tags":[
        "grocer"
    ],
    "wof:name":"Leon's Supermarket",
    "wof:placetype":"venue"
},
  "geometry": {"coordinates":[-98.343733,48.042253],"type":"Point"}
}