{
  "type": "Feature",
  "properties": {
    "iso:country":"US",
    "sg:address":"6435 172nd Ave SE",
    "sg:city":"Colfax",
    "sg:classifiers":[
        {
            "category":"Farming",
            "subcategory":"Livestock Farm",
            "type":"Manufacturing & Wholesale Goods"
        }
    ],
    "sg:phone":"+1 701 372 3773",
    "sg:postcode":"58018",
    "sg:province":"ND",
    "sg:tags":[
        "beef",
        "feedlot",
        "cattle"
    ],
    "wof:name":"Brad Hage",
    "wof:placetype":"venue"
},
  "geometry": {"coordinates":[-96.820297,46.480332],"type":"Point"}
}