{
  "type": "Feature",
  "properties": {
    "addr:full":"9920 170th Ave SE Hankinson ND 58041",
    "addr:housenumber":"9920",
    "addr:postcode":"58041",
    "addr:street":"170Th Ave Se",
    "iso:country":"US",
    "sg:address":"9920 170th Ave SE",
    "sg:city":"Hankinson",
    "sg:phone":"+1 701 242 7737",
    "sg:postcode":"58041",
    "sg:province":"ND",
    "sg:tags":[
        "farm",
        "wheat"
    ],
    "wof:name":"Rick Prochnow",
    "wof:placetype":"venue"
},
  "geometry": {"coordinates":[-96.846152,45.976367],"type":"Point"}
}