{
  "type": "Feature",
  "properties": {
    "iso:country":"US",
    "sg:address":"918 3rd St SW",
    "sg:city":"Valley City",
    "sg:classifiers":[
        {
            "category":"Autos & Motor Vehicles",
            "subcategory":"Automobile Sales",
            "type":"Retail Goods"
        }
    ],
    "sg:phone":"+1 701 845 0238",
    "sg:postcode":"58072",
    "sg:province":"ND",
    "sg:tags":[
        "used"
    ],
    "wof:name":"Prairie Auto Sales",
    "wof:placetype":"venue"
},
  "geometry": {"coordinates":[-98.015021,46.921096],"type":"Point"}
}