{
  "type": "Feature",
  "properties": {
    "iso:country":"US",
    "sg:address":"108 Main St W",
    "sg:city":"Beulah",
    "sg:classifiers":[
        {
            "category":"Personal",
            "subcategory":"Barber",
            "type":"Services"
        }
    ],
    "sg:phone":"+1 701 873 2323",
    "sg:postcode":"58523",
    "sg:province":"ND",
    "wof:name":"Town & Country Barbers",
    "wof:placetype":"venue"
},
  "geometry": {"coordinates":[-101.779596,47.26355],"type":"Point"}
}