{
  "type": "Feature",
  "properties": {
    "addr:full":"102 2nd St NE Rolla ND 58367",
    "addr:housenumber":"102",
    "addr:postcode":"58367",
    "addr:street":"2Nd St Ne",
    "iso:country":"US",
    "sg:address":"102 2nd St NE",
    "sg:city":"Rolla",
    "sg:classifiers":[
        {
            "category":"Government",
            "subcategory":"Court House",
            "type":"Public Place"
        }
    ],
    "sg:phone":"+1 701 477 3169",
    "sg:postcode":"58367",
    "sg:province":"ND",
    "sg:tags":[
        "state",
        "counsel"
    ],
    "wof:name":"Rolette States Attorney",
    "wof:placetype":"venue"
},
  "geometry": {"coordinates":[-99.61564799999999,48.861492],"type":"Point"}
}