{
  "type": "Feature",
  "properties": {
    "addr:full":"794 Main Ave E West Fargo ND 58078",
    "addr:housenumber":"794",
    "addr:postcode":"58078",
    "addr:street":"Main Ave E",
    "iso:country":"US",
    "sg:address":"794 Main Ave E",
    "sg:city":"West Fargo",
    "sg:classifiers":[
        {
            "category":"Organizations",
            "subcategory":"Professional Association",
            "type":"Services"
        }
    ],
    "sg:phone":"+1 701 282 4444",
    "sg:postcode":"58078",
    "sg:province":"ND",
    "sg:tags":[
        "chambers",
        "commerce"
    ],
    "sg:website":"www.westfargochamber.com",
    "wof:name":"West Fargo Chamber Of Commerce",
    "wof:placetype":"venue"
},
  "geometry": {"coordinates":[-96.888678,46.876754],"type":"Point"}
}