{
  "type": "Feature",
  "properties": {
    "iso:country":"US",
    "sg:address":"120 W Main St",
    "sg:city":"Valley City",
    "sg:classifiers":[
        {
            "category":"Retail",
            "subcategory":"Auto Repair",
            "type":"Services"
        }
    ],
    "sg:phone":"+1 701 845 1348",
    "sg:postcode":"58072",
    "sg:province":"ND",
    "sg:tags":[
        "repairing",
        "automobile"
    ],
    "wof:name":"Sheyenne Auto Ctr",
    "wof:placetype":"venue"
},
  "geometry": {"coordinates":[-98.00322300000001,46.92343],"type":"Point"}
}