{
  "type": "Feature",
  "properties": {
    "addr:full":"206 2nd St Underwood ND 58576",
    "addr:housenumber":"206",
    "addr:postcode":"58576",
    "addr:street":"2Nd St",
    "iso:country":"US",
    "sg:address":"206 2nd St",
    "sg:city":"Underwood",
    "sg:classifiers":[
        {
            "category":"Organizations",
            "subcategory":"Religious Organization",
            "type":"Services"
        }
    ],
    "sg:phone":"+1 701 442 5221",
    "sg:postcode":"58576",
    "sg:province":"ND",
    "sg:tags":[
        "church"
    ],
    "wof:name":"First Baptist Church",
    "wof:placetype":"venue"
},
  "geometry": {"coordinates":[-101.139799,47.457639],"type":"Point"}
}