{
  "type": "Feature",
  "properties": {
    "addr:full":"3401 1st St SE Minot ND 58701",
    "addr:housenumber":"3401",
    "addr:postcode":"58701",
    "addr:street":"1St St Se",
    "iso:country":"US",
    "sg:address":"3401 1st St SE",
    "sg:city":"Minot",
    "sg:classifiers":[
        {
            "category":"Building & Trades",
            "subcategory":"Landscaping Services",
            "type":"Services"
        }
    ],
    "sg:phone":"+1 701 833 9265",
    "sg:postcode":"58701",
    "sg:province":"ND",
    "sg:tags":[
        "lawn",
        "maintenance",
        "grounds"
    ],
    "wof:name":"B & B Ground Maintenance",
    "wof:placetype":"venue"
},
  "geometry": {"coordinates":[-101.29249799999999,48.199751],"type":"Point"}
}