{
  "type": "Feature",
  "properties": {
    "iso:country":"US",
    "sg:address":"520 Hackberry Dr",
    "sg:city":"Fargo",
    "sg:classifiers":[
        {
            "category":"Building & Trades",
            "subcategory":"Construction",
            "type":"Services"
        }
    ],
    "sg:phone":"+1 701 280 9736",
    "sg:postcode":"58104",
    "sg:province":"ND",
    "sg:tags":[
        "house",
        "builder",
        "home"
    ],
    "wof:name":"Molony Construction",
    "wof:placetype":"venue"
},
  "geometry": {"coordinates":[-96.79057400000001,46.829212],"type":"Point"}
}