{
  "type": "Feature",
  "properties": {
    "iso:country":"US",
    "sg:address":"4229 15th Ave N",
    "sg:city":"Fargo",
    "sg:classifiers":[
        {
            "category":"Freight",
            "type":"Transportation"
        }
    ],
    "sg:phone":"+1 701 282 0181",
    "sg:postcode":"58102",
    "sg:province":"ND",
    "sg:tags":[
        "trucking"
    ],
    "sg:website":"www.vitran-express.com",
    "wof:name":"Vitran Express",
    "wof:placetype":"venue"
},
  "geometry": {"coordinates":[-96.854755,46.897355],"type":"Point"}
}