{
  "type": "Feature",
  "properties": {
    "iso:country":"US",
    "sg:address":"114 N 6th St",
    "sg:city":"Bismarck",
    "sg:classifiers":[
        {
            "category":"Parking",
            "type":"Transportation"
        }
    ],
    "sg:phone":"+1 701 222 8954",
    "sg:postcode":"58501",
    "sg:province":"ND",
    "sg:tags":[
        "automobile"
    ],
    "wof:name":"Apcoa Parking",
    "wof:placetype":"venue"
},
  "geometry": {"coordinates":[-100.783169,46.806286],"type":"Point"}
}