{
  "type": "Feature",
  "properties": {
    "iso:country":"US",
    "sg:address":"522 Sinclair St",
    "sg:city":"Bottineau",
    "sg:classifiers":[
        {
            "category":"Museum",
            "type":"Entertainment"
        }
    ],
    "sg:phone":"+1 701 228 2943",
    "sg:postcode":"58318",
    "sg:province":"ND",
    "wof:name":"Bottineau County Hist Museum",
    "wof:placetype":"venue"
},
  "geometry": {"coordinates":[-100.447569,48.827095],"type":"Point"}
}