{
  "type": "Feature",
  "properties": {
    "iso:country":"US",
    "sg:address":"26 Roberts St N",
    "sg:city":"Fargo",
    "sg:classifiers":[
        {
            "category":"Retail",
            "subcategory":"Portrait Studio",
            "type":"Services"
        }
    ],
    "sg:phone":"+1 701 491 0489",
    "sg:postcode":"58102",
    "sg:province":"ND",
    "sg:tags":[
        "photographer"
    ],
    "wof:name":"Coulter Photography & Digital",
    "wof:placetype":"venue"
},
  "geometry": {"coordinates":[-96.790229,46.876056],"type":"Point"}
}