{
  "type": "Feature",
  "properties": {
    "iso:country":"US",
    "sg:address":"1304 E Century Ave",
    "sg:city":"Bismarck",
    "sg:classifiers":[
        {
            "category":"Restaurant",
            "type":"Food & Drink"
        }
    ],
    "sg:phone":"+1 701 223 6220",
    "sg:postcode":"58503",
    "sg:province":"ND",
    "sg:tags":[
        "drinking",
        "eating"
    ],
    "sg:website":"www.space-aliens.com",
    "wof:name":"Space Aliens Grill and Bar",
    "wof:placetype":"venue"
},
  "geometry": {"coordinates":[-100.772746,46.838155],"type":"Point"}
}