{
  "type": "Feature",
  "properties": {
    "iso:country":"US",
    "sg:address":"527 9th St W",
    "sg:city":"West Fargo",
    "sg:classifiers":[
        {
            "category":"Freight",
            "type":"Transportation"
        }
    ],
    "sg:phone":"+1 701 281 9349",
    "sg:postcode":"58078",
    "sg:province":"ND",
    "sg:tags":[
        "operator",
        "local",
        "trucking"
    ],
    "wof:name":"Mears Trucking",
    "wof:placetype":"venue"
},
  "geometry": {"coordinates":[-96.914269,46.870433],"type":"Point"}
}