{
  "type": "Feature",
  "properties": {
    "iso:country":"US",
    "sg:address":"1119 37th Ave S",
    "sg:city":"Fargo",
    "sg:classifiers":[
        {
            "category":"Building & Trades",
            "subcategory":"Construction",
            "type":"Services"
        }
    ],
    "sg:phone":"+1 701 293 3736",
    "sg:postcode":"58104",
    "sg:province":"ND",
    "sg:tags":[
        "house"
    ],
    "wof:name":"Richard Bakke Const",
    "wof:placetype":"venue"
},
  "geometry": {"coordinates":[-96.800817,46.82403],"type":"Point"}
}