{
  "type": "Feature",
  "properties": {
    "addr:full":"1601 W Century Ave Bismarck ND 58503",
    "addr:housenumber":"1601",
    "addr:postcode":"58503",
    "addr:street":"W Century Ave",
    "iso:country":"US",
    "sg:address":"1601 W Century Ave",
    "sg:city":"Bismarck",
    "sg:classifiers":[
        {
            "category":"Restaurant",
            "type":"Food & Drink"
        }
    ],
    "sg:menulink":"http://www.allmenus.com/nd/bismarck/105045-carinos-italian-grill/menu/",
    "sg:phone":"+1 701 258 5655",
    "sg:postcode":"58503",
    "sg:province":"ND",
    "sg:tags":[
        "american",
        "italian"
    ],
    "wof:name":"Carino's Italian Grill",
    "wof:placetype":"venue"
},
  "geometry": {"coordinates":[-100.81585200000001,46.832469],"type":"Point"}
}