{
  "type": "Feature",
  "properties": {
    "iso:country":"US",
    "sg:address":"102 2nd Ave NE",
    "sg:city":"Rolla",
    "sg:classifiers":[
        {
            "category":"Government",
            "subcategory":"Office",
            "type":"Public Place"
        }
    ],
    "sg:phone":"+1 701 477 3166",
    "sg:postcode":"58367",
    "sg:province":"ND",
    "wof:name":"Rolette Register Of Deeds",
    "wof:placetype":"venue"
},
  "geometry": {"coordinates":[-99.615695,48.861393],"type":"Point"}
}