{
  "type": "Feature",
  "properties": {
    "iso:country":"US",
    "sg:address":"1168 Center St",
    "sg:city":"West Fargo",
    "sg:classifiers":[
        {
            "category":"Building & Trades",
            "subcategory":"Construction",
            "type":"Services"
        }
    ],
    "sg:phone":"+1 701 277 1687",
    "sg:postcode":"58078",
    "sg:province":"ND",
    "sg:tags":[
        "concrete",
        "contractor"
    ],
    "wof:name":"A J Construction Inc",
    "wof:placetype":"venue"
},
  "geometry": {"coordinates":[-96.89983599999999,46.89054],"type":"Point"}
}