{
  "type": "Feature",
  "properties": {
    "addr:full":"821 3rd St Langdon ND 58249",
    "addr:housenumber":"821",
    "addr:postcode":"58249",
    "addr:street":"3Rd St",
    "iso:country":"US",
    "sg:address":"821 3rd St",
    "sg:city":"Langdon",
    "sg:classifiers":[
        {
            "category":"Shopping",
            "subcategory":"Hobbies, Toys, & Games",
            "type":"Retail Goods"
        }
    ],
    "sg:phone":"+1 701 256 3292",
    "sg:postcode":"58249",
    "sg:province":"ND",
    "sg:tags":[
        "craft",
        "supply"
    ],
    "wof:name":"Scrap Addicts Corner",
    "wof:placetype":"venue"
},
  "geometry": {"coordinates":[-98.368191,48.760975],"type":"Point"}
}