{
  "type": "Feature",
  "properties": {
    "iso:country":"US",
    "sg:address":"1208 S Washington St",
    "sg:city":"Grand Forks",
    "sg:classifiers":[
        {
            "category":"Government",
            "subcategory":"Office",
            "type":"Public Place"
        }
    ],
    "sg:phone":"+1 701 795 3847",
    "sg:postcode":"58201",
    "sg:province":"ND",
    "sg:tags":[
        "federal",
        "security"
    ],
    "wof:name":"Army National Guard",
    "wof:placetype":"venue"
},
  "geometry": {"coordinates":[-97.04510000000001,47.909231],"type":"Point"}
}