{
  "type": "Feature",
  "properties": {
    "addr:full":"112 10th St NE Beulah ND 58523",
    "addr:housenumber":"112",
    "addr:postcode":"58523",
    "addr:street":"10Th St Ne",
    "iso:country":"US",
    "sg:address":"112 10th St NE",
    "sg:city":"Beulah",
    "sg:classifiers":[
        {
            "category":"Building & Trades",
            "subcategory":"Construction",
            "type":"Services"
        }
    ],
    "sg:phone":"+1 701 873 4350",
    "sg:postcode":"58523",
    "sg:province":"ND",
    "sg:tags":[
        "house",
        "nonresidential"
    ],
    "wof:name":"R&S Contracting",
    "wof:placetype":"venue"
},
  "geometry": {"coordinates":[-101.777869,47.27309],"type":"Point"}
}