{
  "type": "Feature",
  "properties": {
    "iso:country":"US",
    "sg:address":"643 1st Ave E",
    "sg:city":"West Fargo",
    "sg:classifiers":[
        {
            "category":"Building & Trades",
            "subcategory":"Plumbing",
            "type":"Services"
        }
    ],
    "sg:phone":"+1 701 282 0264",
    "sg:postcode":"58078",
    "sg:province":"ND",
    "sg:tags":[
        "heating",
        "contractor"
    ],
    "wof:name":"Cass County Heating Inc",
    "wof:placetype":"venue"
},
  "geometry": {"coordinates":[-96.88646199999999,46.875402],"type":"Point"}
}