{
  "type": "Feature",
  "properties": {
    "iso:country":"US",
    "sg:address":"219 S Main Ave",
    "sg:city":"Rugby",
    "sg:classifiers":[
        {
            "category":"Manufacturing",
            "subcategory":"Printing",
            "type":"Manufacturing & Wholesale Goods"
        }
    ],
    "sg:phone":"+1 701 776 5252",
    "sg:postcode":"58368",
    "sg:province":"ND",
    "sg:tags":[
        "newspaper"
    ],
    "wof:name":"Pierce County Tribune",
    "wof:placetype":"venue"
},
  "geometry": {"coordinates":[-99.996031,48.368524],"type":"Point"}
}