{
  "type": "Feature",
  "properties": {
    "iso:country":"US",
    "sg:address":"7320 65th St SW",
    "sg:city":"New Leipzig",
    "sg:classifiers":[
        {
            "category":"Wholesale",
            "subcategory":"Farm Supplies",
            "type":"Manufacturing & Wholesale Goods"
        }
    ],
    "sg:phone":"+1 701 584 3333",
    "sg:postcode":"58562",
    "sg:province":"ND",
    "sg:tags":[
        "fertilizer",
        "agricultural"
    ],
    "wof:name":"Dakota Fertilizer Co Inc",
    "wof:placetype":"venue"
},
  "geometry": {"coordinates":[-101.96445799999999,46.471948],"type":"Point"}
}