{
  "type": "Feature",
  "properties": {
    "iso:country":"US",
    "sg:address":"204 Front St",
    "sg:city":"Forest River",
    "sg:classifiers":[
        {
            "category":"Social Services",
            "type":"Services"
        }
    ],
    "sg:phone":"+1 701 248 3710",
    "sg:postcode":"58233",
    "sg:province":"ND",
    "sg:tags":[
        "senior",
        "citizen"
    ],
    "wof:name":"Forest River Senior Citizen",
    "wof:placetype":"venue"
},
  "geometry": {"coordinates":[-97.46884300000001,48.215442],"type":"Point"}
}