{
  "type": "Feature",
  "properties": {
    "iso:country":"US",
    "sg:address":"1876 108th St NE",
    "sg:city":"Bottineau",
    "sg:classifiers":[
        {
            "category":"Organizations",
            "subcategory":"Religious Organization",
            "type":"Services"
        }
    ],
    "sg:phone":"+1 701 263 6706",
    "sg:postcode":"58318",
    "sg:province":"ND",
    "sg:tags":[
        "church"
    ],
    "wof:name":"First Baptist Church",
    "wof:placetype":"venue"
},
  "geometry": {"coordinates":[-100.303304,48.979144],"type":"Point"}
}