{
  "type": "Feature",
  "properties": {
    "iso:country":"US",
    "sg:address":"573 Cottonwood Loop",
    "sg:city":"Bismarck",
    "sg:classifiers":[
        {
            "category":"Food & Beverages",
            "subcategory":"Meat & Fish",
            "type":"Retail Goods"
        }
    ],
    "sg:phone":"+1 701 222 1747",
    "sg:postcode":"58504",
    "sg:province":"ND",
    "wof:name":"Gienger's Sausage & Meat",
    "wof:placetype":"venue"
},
  "geometry": {"coordinates":[-100.783198,46.778465],"type":"Point"}
}