{
  "type": "Feature",
  "properties": {
    "iso:country":"US",
    "sg:address":"12206 28th St SE",
    "sg:city":"Valley City",
    "sg:phone":"+1 701 845 2464",
    "sg:postcode":"58072",
    "sg:province":"ND",
    "sg:tags":[
        "farm",
        "corn"
    ],
    "wof:name":"Kurt Wittenberg",
    "wof:placetype":"venue"
},
  "geometry": {"coordinates":[-97.91604100000001,47.008165],"type":"Point"}
}