{
  "type": "Feature",
  "properties": {
    "iso:country":"US",
    "sg:address":"912 Page Dr",
    "sg:city":"Fargo",
    "sg:classifiers":[
        {
            "category":"Wholesale",
            "subcategory":"Machinery & Supplies",
            "type":"Manufacturing & Wholesale Goods"
        }
    ],
    "sg:phone":"+1 701 298 0040",
    "sg:postcode":"58103",
    "sg:province":"ND",
    "wof:name":"Track & Tractor Parts",
    "wof:placetype":"venue"
},
  "geometry": {"coordinates":[-96.82735599999999,46.865606],"type":"Point"}
}