{
  "type": "Feature",
  "properties": {
    "iso:country":"US",
    "sg:address":"25 S Main St",
    "sg:city":"Bowman",
    "sg:classifiers":[
        {
            "category":"Autos & Motor Vehicles",
            "subcategory":"Automobile Sales",
            "type":"Retail Goods"
        }
    ],
    "sg:phone":"+1 701 523 5222",
    "sg:postcode":"58623",
    "sg:province":"ND",
    "sg:tags":[
        "car",
        "dealer"
    ],
    "wof:name":"SAX Motor Co Sw",
    "wof:placetype":"venue"
},
  "geometry": {"coordinates":[-103.39490000000001,46.181971],"type":"Point"}
}