{
  "type": "Feature",
  "properties": {
    "addr:full":"1318 2nd Ave W Williston ND 58801",
    "addr:housenumber":"1318",
    "addr:postcode":"58801",
    "addr:street":"2Nd Ave W",
    "iso:country":"US",
    "sg:address":"1318 2nd Ave W",
    "sg:city":"Williston",
    "sg:classifiers":[
        {
            "category":"Retail",
            "subcategory":"Animal Services",
            "type":"Services"
        }
    ],
    "sg:phone":"+1 701 572 8567",
    "sg:postcode":"58801",
    "sg:province":"ND",
    "wof:name":"Pets N Stuff",
    "wof:placetype":"venue"
},
  "geometry": {"coordinates":[-103.62567900000001,48.157081],"type":"Point"}
}