{
  "type": "Feature",
  "properties": {
    "iso:country":"US",
    "sg:address":"1418 E Main Ave",
    "sg:city":"Bismarck",
    "sg:classifiers":[
        {
            "category":"Shopping",
            "subcategory":"Bicycles & Sporting Goods",
            "type":"Retail Goods"
        }
    ],
    "sg:phone":"+1 701 250 1713",
    "sg:postcode":"58501",
    "sg:province":"ND",
    "sg:tags":[
        "snowboard"
    ],
    "sg:website":"www.amos5oh.com",
    "wof:name":"Amo's 5-Oh Board Shop",
    "wof:placetype":"venue"
},
  "geometry": {"coordinates":[-100.769451,46.805328],"type":"Point"}
}