{
  "type": "Feature",
  "properties": {
    "iso:country":"US",
    "sg:address":"1206 12th Ave SE",
    "sg:city":"Jamestown",
    "sg:classifiers":[
        {
            "category":"Personal",
            "subcategory":"Tanning Parlor",
            "type":"Services"
        }
    ],
    "sg:phone":"+1 701 252 1433",
    "sg:postcode":"58401",
    "sg:province":"ND",
    "sg:tags":[
        "salon"
    ],
    "wof:name":"Total Tanning & Fitness",
    "wof:placetype":"venue"
},
  "geometry": {"coordinates":[-98.69149400000001,46.896604],"type":"Point"}
}