{
  "type": "Feature",
  "properties": {
    "iso:country":"US",
    "sg:address":"2045 49th Ave SE",
    "sg:city":"Woodworth",
    "sg:classifiers":[
        {
            "category":"Professional",
            "subcategory":"Business Services",
            "type":"Services"
        },
        {
            "category":"Wholesale",
            "subcategory":"Auto Parts",
            "type":"Manufacturing & Wholesale Goods"
        }
    ],
    "sg:phone":"+1 701 273 4125",
    "sg:postcode":"58496",
    "sg:province":"ND",
    "sg:tags":[
        "automobile",
        "rebuilt"
    ],
    "wof:name":"Ron's Salvage & Repair",
    "wof:placetype":"venue"
},
  "geometry": {"coordinates":[-99.462335,47.118494],"type":"Point"}
}