{
  "type": "Feature",
  "properties": {
    "iso:country":"US",
    "sg:address":"23900 State Hwy 1804",
    "sg:city":"Baldwin",
    "sg:classifiers":[
        {
            "category":"Farming",
            "subcategory":"Livestock Farm",
            "type":"Manufacturing & Wholesale Goods"
        }
    ],
    "sg:phone":"+1 701 734 6776",
    "sg:postcode":"58521",
    "sg:province":"ND",
    "sg:tags":[
        "wheat",
        "beef",
        "cash",
        "grain",
        "cattle",
        "feedlot"
    ],
    "wof:name":"Kenneth W Johnson",
    "wof:placetype":"venue"
},
  "geometry": {"coordinates":[-100.87811499999999,47.05936],"type":"Point"}
}