{
  "type": "Feature",
  "properties": {
    "addr:full":"483 S Main Ave Dickinson ND 58601",
    "addr:housenumber":"483",
    "addr:postcode":"58601",
    "addr:street":"S Main Ave",
    "iso:country":"US",
    "sg:address":"483 S Main Ave",
    "sg:city":"Dickinson",
    "sg:classifiers":[
        {
            "category":"Farming",
            "subcategory":"Nursery",
            "type":"Manufacturing & Wholesale Goods"
        }
    ],
    "sg:phone":"+1 701 483 3908",
    "sg:postcode":"58601",
    "sg:province":"ND",
    "sg:tags":[
        "ornamental"
    ],
    "wof:name":"John Gaffney Greenhouse",
    "wof:placetype":"venue"
},
  "geometry": {"coordinates":[-102.78984199999999,46.868922],"type":"Point"}
}