{
  "type": "Feature",
  "properties": {
    "iso:country":"US",
    "sg:address":"1506 Ave B",
    "sg:city":"Wahpeton",
    "sg:classifiers":[
        {
            "category":"Freight",
            "type":"Transportation"
        }
    ],
    "sg:phone":"+1 701 642 5757",
    "sg:postcode":"58075",
    "sg:province":"ND",
    "sg:tags":[
        "local",
        "without",
        "storage",
        "trucking"
    ],
    "wof:name":"Twin Town Taxi",
    "wof:placetype":"venue"
},
  "geometry": {"coordinates":[-96.62289800000001,46.275228],"type":"Point"}
}