{
  "type": "Feature",
  "properties": {
    "iso:country":"US",
    "sg:address":"596 H St",
    "sg:city":"Grand Forks Afb",
    "sg:classifiers":[
        {
            "category":"Professional",
            "type":"Services"
        }
    ],
    "sg:phone":"+1 701 594 3000",
    "sg:postcode":"58204",
    "sg:province":"ND",
    "wof:name":"Triwest Service Ctr",
    "wof:placetype":"venue"
},
  "geometry": {"coordinates":[-97.380195,47.950984],"type":"Point"}
}