{
  "type": "Feature",
  "properties": {
    "iso:country":"US",
    "sg:address":"217 Main St S",
    "sg:city":"Minot",
    "sg:classifiers":[
        {
            "category":"Real Estate",
            "subcategory":"Real Estate Operator",
            "type":"Services"
        }
    ],
    "sg:phone":"+1 701 839 7505",
    "sg:postcode":"58701",
    "sg:province":"ND",
    "sg:tags":[
        "apartment"
    ],
    "wof:name":"First Minot Management",
    "wof:placetype":"venue"
},
  "geometry": {"coordinates":[-101.292958,48.234838],"type":"Point"}
}