{
  "type": "Feature",
  "properties": {
    "iso:country":"US",
    "sg:address":"133 W Stutsman St",
    "sg:city":"Pembina",
    "sg:classifiers":[
        {
            "category":"Banks & Credit Unions",
            "subcategory":"Bank",
            "type":"Services"
        }
    ],
    "sg:phone":"+1 701 825 6289",
    "sg:postcode":"58271",
    "sg:province":"ND",
    "wof:name":"Citizens State Bank-Midwest",
    "wof:placetype":"venue"
},
  "geometry": {"coordinates":[-97.24517299999999,48.967092],"type":"Point"}
}