{
  "type": "Feature",
  "properties": {
    "addr:full":"515 Summit St Underwood ND 58576",
    "addr:housenumber":"515",
    "addr:postcode":"58576",
    "addr:street":"Summit St",
    "iso:country":"US",
    "sg:address":"515 Summit St",
    "sg:city":"Underwood",
    "sg:classifiers":[
        {
            "category":"Shopping",
            "type":"Retail Goods"
        }
    ],
    "sg:phone":"+1 701 442 5607",
    "sg:postcode":"58576",
    "sg:province":"ND",
    "sg:tags":[
        "cosmetic",
        "perfume"
    ],
    "wof:name":"Jafra Cosmetics",
    "wof:placetype":"venue"
},
  "geometry": {"coordinates":[-101.142489,47.453145],"type":"Point"}
}