{
  "type": "Feature",
  "properties": {
    "iso:country":"US",
    "sg:address":"517 1st St",
    "sg:city":"Devils Lake",
    "sg:classifiers":[
        {
            "category":"Insurance",
            "subcategory":"Insurance Agent",
            "type":"Services"
        }
    ],
    "sg:phone":"+1 701 662 5301",
    "sg:postcode":"58301",
    "sg:province":"ND",
    "sg:tags":[
        "adjuster"
    ],
    "wof:name":"Winston Noble Adjuster Co",
    "wof:placetype":"venue"
},
  "geometry": {"coordinates":[-98.858031,48.108799],"type":"Point"}
}