{
  "type": "Feature",
  "properties": {
    "iso:country":"US",
    "sg:address":"112 N Main St",
    "sg:city":"Bowman",
    "sg:classifiers":[
        {
            "category":"Health Services",
            "subcategory":"Doctor",
            "type":"Services"
        }
    ],
    "sg:phone":"+1 701 523 5651",
    "sg:postcode":"58623",
    "sg:province":"ND",
    "sg:tags":[
        "dentist"
    ],
    "wof:name":"Bonnie J Anderson DDS",
    "wof:placetype":"venue"
},
  "geometry": {"coordinates":[-103.39490600000001,46.183794],"type":"Point"}
}