{
  "type": "Feature",
  "properties": {
    "iso:country":"US",
    "sg:address":"703 8th Ave S",
    "sg:city":"Wahpeton",
    "sg:classifiers":[
        {
            "category":"Autos & Motor Vehicles",
            "subcategory":"Auto Supplies",
            "type":"Retail Goods"
        }
    ],
    "sg:phone":"+1 701 642 2270",
    "sg:postcode":"58075",
    "sg:province":"ND",
    "sg:tags":[
        "automobile",
        "part"
    ],
    "wof:name":"R & Z Repair",
    "wof:placetype":"venue"
},
  "geometry": {"coordinates":[-96.60978,46.256822],"type":"Point"}
}