{
  "type": "Feature",
  "properties": {
    "iso:country":"US",
    "sg:address":"8 5th St N",
    "sg:city":"Oakes",
    "sg:classifiers":[
        {
            "category":"Health Services",
            "subcategory":"Health Practitioner",
            "type":"Services"
        }
    ],
    "sg:phone":"+1 701 742 3474",
    "sg:postcode":"58474",
    "sg:province":"SD",
    "wof:name":"Helping Hands",
    "wof:placetype":"venue"
},
  "geometry": {"coordinates":[-98.093362,46.139849],"type":"Point"}
}