{
  "type": "Feature",
  "properties": {
    "iso:country":"US",
    "sg:address":"7400 72nd St SE",
    "sg:city":"Minot",
    "sg:classifiers":[
        {
            "category":"Building & Trades",
            "subcategory":"Construction",
            "type":"Services"
        }
    ],
    "sg:phone":"+1 701 624 5549",
    "sg:postcode":"58701",
    "sg:province":"ND",
    "sg:tags":[
        "house"
    ],
    "wof:name":"CC Construction",
    "wof:placetype":"venue"
},
  "geometry": {"coordinates":[-101.18618499999999,48.15913],"type":"Point"}
}