{
  "type": "Feature",
  "properties": {
    "iso:country":"US",
    "sg:address":"313 Broadway",
    "sg:city":"Fargo",
    "sg:classifiers":[
        {
            "category":"Personal",
            "subcategory":"Barber",
            "type":"Services"
        }
    ],
    "sg:phone":"+1 701 237 3900",
    "sg:postcode":"58102",
    "sg:province":"ND",
    "wof:name":"Grand Barber & Beauty World",
    "wof:placetype":"venue"
},
  "geometry": {"coordinates":[-96.787617,46.879934],"type":"Point"}
}