{
  "type": "Feature",
  "properties": {
    "iso:country":"US",
    "sg:address":"207 6th Ave E",
    "sg:city":"Lisbon",
    "sg:classifiers":[
        {
            "category":"Building & Trades",
            "subcategory":"Construction",
            "type":"Services"
        }
    ],
    "sg:phone":"+1 701 683 4112",
    "sg:postcode":"58054",
    "sg:province":"ND",
    "sg:tags":[
        "house"
    ],
    "wof:name":"H & K Services",
    "wof:placetype":"venue"
},
  "geometry": {"coordinates":[-97.676242,46.440613],"type":"Point"}
}