{
  "type": "Feature",
  "properties": {
    "iso:country":"US",
    "sg:address":"7219 30th St NE",
    "sg:city":"Sheyenne",
    "sg:classifiers":[
        {
            "category":"Farming",
            "subcategory":"Dairy Farm",
            "type":"Manufacturing & Wholesale Goods"
        }
    ],
    "sg:phone":"+1 701 996 3362",
    "sg:postcode":"58374",
    "sg:province":"ND",
    "wof:name":"Anderson Dairy",
    "wof:placetype":"venue"
},
  "geometry": {"coordinates":[-99.03918400000001,47.846694],"type":"Point"}
}