{
  "type": "Feature",
  "properties": {
    "iso:country":"US",
    "sg:address":"451 113th Ave SE",
    "sg:city":"Cooperstown",
    "sg:classifiers":[
        {
            "category":"Farming",
            "subcategory":"Farm",
            "type":"Manufacturing & Wholesale Goods"
        }
    ],
    "sg:phone":"+1 701 797 2155",
    "sg:postcode":"58425",
    "sg:province":"ND",
    "wof:name":"Barry Ronningen Farm",
    "wof:placetype":"venue"
},
  "geometry": {"coordinates":[-98.13461700000001,47.472045],"type":"Point"}
}