{
  "type": "Feature",
  "properties": {
    "iso:country":"US",
    "sg:address":"13758 State Hwy 5",
    "sg:city":"Cavalier",
    "sg:classifiers":[
        {
            "category":"Retail",
            "subcategory":"Auto Repair",
            "type":"Services"
        }
    ],
    "sg:phone":"+1 701 265 4256",
    "sg:postcode":"58220",
    "sg:province":"ND",
    "sg:tags":[
        "automotive"
    ],
    "wof:name":"Tonys Radiator Service",
    "wof:placetype":"venue"
},
  "geometry": {"coordinates":[-97.695245,48.775911],"type":"Point"}
}