{
  "type": "Feature",
  "properties": {
    "iso:country":"US",
    "sg:address":"632 W Turnpike Ave",
    "sg:city":"Bismarck",
    "sg:classifiers":[
        {
            "category":"Manufacturing",
            "subcategory":"Printing",
            "type":"Manufacturing & Wholesale Goods"
        }
    ],
    "sg:phone":"+1 701 222 0567",
    "sg:postcode":"58501",
    "sg:province":"ND",
    "sg:tags":[
        "commercial"
    ],
    "wof:name":"M A Sportswear",
    "wof:placetype":"venue"
},
  "geometry": {"coordinates":[-100.79903400000001,46.830485],"type":"Point"}
}