{
  "type": "Feature",
  "properties": {
    "addr:full":"2249 Main Ave W West Fargo ND 58078",
    "addr:housenumber":"2249",
    "addr:postcode":"58078",
    "addr:street":"Main Ave W",
    "iso:country":"US",
    "sg:address":"2249 Main Ave W",
    "sg:city":"West Fargo",
    "sg:classifiers":[
        {
            "category":"Retail",
            "subcategory":"Auto Repair",
            "type":"Services"
        }
    ],
    "sg:phone":"+1 701 282 2866",
    "sg:postcode":"58078",
    "sg:province":"ND",
    "sg:tags":[
        "automotive"
    ],
    "wof:name":"Dorso Trailer Sales Inc",
    "wof:placetype":"venue"
},
  "geometry": {"coordinates":[-96.939897,46.877059],"type":"Point"}
}