{
  "type": "Feature",
  "properties": {
    "addr:full":"4683 153rd Ave NW Williston ND 58801",
    "addr:housenumber":"4683",
    "addr:postcode":"58801",
    "addr:street":"153Rd Ave Nw",
    "iso:country":"US",
    "sg:address":"4683 153rd Ave NW",
    "sg:city":"Williston",
    "sg:classifiers":[
        {
            "category":"Organizations",
            "subcategory":"Non-profit Organization",
            "type":"Services"
        }
    ],
    "sg:phone":"+1 701 875 4376",
    "sg:postcode":"58801",
    "sg:province":"ND",
    "sg:tags":[
        "human"
    ],
    "wof:name":"Village Family Svc Ctr",
    "wof:placetype":"venue"
},
  "geometry": {"coordinates":[-103.99242099999999,48.089018],"type":"Point"}
}