{
  "type": "Feature",
  "properties": {
    "addr:full":"479 Burdick Ct Grand Forks ND 58203",
    "addr:housenumber":"479",
    "addr:postcode":"58203",
    "addr:street":"Burdick Ct",
    "iso:country":"US",
    "sg:address":"479 Burdick Ct",
    "sg:city":"Grand Forks",
    "sg:classifiers":[
        {
            "category":"Health Services",
            "subcategory":"Health Practitioner",
            "type":"Services"
        }
    ],
    "sg:phone":"+1 701 775 3559",
    "sg:postcode":"58203",
    "sg:province":"ND",
    "sg:tags":[
        "nurse"
    ],
    "wof:name":"Elaine M Gunville",
    "wof:placetype":"venue"
},
  "geometry": {"coordinates":[-97.096638,47.924232],"type":"Point"}
}