{
  "type": "Feature",
  "properties": {
    "addr:full":"2521 Railroad Ave Bismarck ND 58501",
    "addr:housenumber":"2521",
    "addr:postcode":"58501",
    "addr:street":"Railroad Ave",
    "iso:country":"US",
    "sg:address":"2521 Railroad Ave",
    "sg:city":"Bismarck",
    "sg:classifiers":[
        {
            "category":"Wholesale",
            "subcategory":"Office Equipment",
            "type":"Manufacturing & Wholesale Goods"
        },
        {
            "category":"Wholesale",
            "subcategory":"Durable Goods & Equipment",
            "type":"Manufacturing & Wholesale Goods"
        }
    ],
    "sg:phone":"+1 701 258 1191",
    "sg:postcode":"58501",
    "sg:province":"ND",
    "sg:tags":[
        "professional",
        "supply",
        "bank",
        "repair"
    ],
    "wof:name":"Bankers Equipment Service Inc",
    "wof:placetype":"venue"
},
  "geometry": {"coordinates":[-100.754687,46.803971],"type":"Point"}
}