{
  "type": "Feature",
  "properties": {
    "iso:country":"US",
    "sg:address":"3055 40th Ave S",
    "sg:city":"Fargo",
    "sg:classifiers":[
        {
            "category":"Manufacturing",
            "subcategory":"Tools & Machinery",
            "type":"Manufacturing & Wholesale Goods"
        }
    ],
    "sg:phone":"+1 701 356 5543",
    "sg:postcode":"58104",
    "sg:province":"ND",
    "sg:tags":[
        "computer",
        "networking"
    ],
    "wof:name":"MCA Inc",
    "wof:placetype":"venue"
},
  "geometry": {"coordinates":[-96.827467,46.8181],"type":"Point"}
}