{
  "type": "Feature",
  "properties": {
    "iso:country":"US",
    "sg:address":"13351 State Hwy 17",
    "sg:city":"Park River",
    "sg:classifiers":[
        {
            "category":"Home & Garden",
            "subcategory":"Garden Supply",
            "type":"Retail Goods"
        }
    ],
    "sg:phone":"+1 701 284 7363",
    "sg:postcode":"58270",
    "sg:province":"ND",
    "sg:tags":[
        "supp",
        "ornamental",
        "nursery",
        "landscape",
        "se"
    ],
    "wof:name":"Irvines Garden Center",
    "wof:placetype":"venue"
},
  "geometry": {"coordinates":[-97.718994,48.398195],"type":"Point"}
}