{
  "type": "Feature",
  "properties": {
    "addr:full":"321 Simrall Blvd Bottineau ND 58318",
    "addr:housenumber":"321",
    "addr:postcode":"58318",
    "addr:street":"Simrall Blvd",
    "iso:country":"US",
    "sg:address":"321 Simrall Blvd",
    "sg:city":"Bottineau",
    "sg:classifiers":[
        {
            "category":"Real Estate",
            "subcategory":"Real Estate Operator",
            "type":"Services"
        }
    ],
    "sg:phone":"+1 701 228 2788",
    "sg:postcode":"58318",
    "sg:province":"ND",
    "sg:tags":[
        "property",
        "lessor"
    ],
    "wof:name":"Walter Trengen",
    "wof:placetype":"venue"
},
  "geometry": {"coordinates":[-100.441115,48.829216],"type":"Point"}
}