{
  "type": "Feature",
  "properties": {
    "iso:country":"US",
    "sg:address":"4004 24th Ave S",
    "sg:city":"Grand Forks",
    "sg:classifiers":[
        {
            "category":"Health Services",
            "subcategory":"Nursing And Care Facility",
            "type":"Services"
        }
    ],
    "sg:phone":"+1 701 787 7500",
    "sg:postcode":"58201",
    "sg:province":"ND",
    "sg:tags":[
        "home",
        "convalescent"
    ],
    "wof:name":"Woodside Village-Valley Meml",
    "wof:placetype":"venue"
},
  "geometry": {"coordinates":[-97.088188,47.896704],"type":"Point"}
}