{
  "type": "Feature",
  "properties": {
    "addr:full":"316 W Main St Mandan ND 58554",
    "addr:housenumber":"316",
    "addr:postcode":"58554",
    "addr:street":"W Main St",
    "iso:country":"US",
    "sg:address":"316 W Main St",
    "sg:city":"Mandan",
    "sg:classifiers":[
        {
            "category":"Shopping",
            "subcategory":"Pharmacy",
            "type":"Retail Goods"
        }
    ],
    "sg:phone":"+1 701 663 5900",
    "sg:postcode":"58554",
    "sg:province":"ND",
    "sg:tags":[
        "drug",
        "store"
    ],
    "wof:name":"Lindy Sue Candy",
    "wof:placetype":"venue"
},
  "geometry": {"coordinates":[-100.89376300000001,46.825966],"type":"Point"}
}