{
  "type": "Feature",
  "properties": {
    "iso:country":"US",
    "sg:address":"602 Main St E",
    "sg:city":"Mohall",
    "sg:classifiers":[
        {
            "category":"Health Services",
            "subcategory":"Nursing And Care Facility",
            "type":"Services"
        }
    ],
    "sg:phone":"+1 701 756 6831",
    "sg:postcode":"58761",
    "sg:province":"ND",
    "sg:tags":[
        "home",
        "skilled",
        "convalescent"
    ],
    "sg:website":"www.good-sam.com",
    "wof:name":"North Centl Good Samaritan Ctr",
    "wof:placetype":"venue"
},
  "geometry": {"coordinates":[-101.50278400000001,48.763429],"type":"Point"}
}