{
  "type": "Feature",
  "properties": {
    "iso:country":"US",
    "sg:address":"7329 111th Ave SE",
    "sg:city":"Verona",
    "sg:classifiers":[
        {
            "category":"Professional",
            "type":"Services"
        }
    ],
    "sg:phone":"+1 701 432 5568",
    "sg:postcode":"58490",
    "sg:province":"ND",
    "wof:name":"Donald Geske",
    "wof:placetype":"venue"
},
  "geometry": {"coordinates":[-98.09746,46.350837],"type":"Point"}
}