{
  "type": "Feature",
  "properties": {
    "iso:country":"US",
    "sg:address":"4404 N Arlington Dr",
    "sg:city":"Bismarck",
    "sg:classifiers":[
        {
            "category":"Shopping",
            "subcategory":"Florist",
            "type":"Retail Goods"
        }
    ],
    "sg:phone":"+1 701 255 7782",
    "sg:postcode":"58503",
    "sg:province":"ND",
    "wof:name":"For All Occasions",
    "wof:placetype":"venue"
},
  "geometry": {"coordinates":[-100.722021,46.83762],"type":"Point"}
}