{
  "type": "Feature",
  "properties": {
    "addr:full":"67 Main Ave Edinburg ND 58227",
    "addr:housenumber":"67",
    "addr:postcode":"58227",
    "addr:street":"Main Ave",
    "iso:country":"US",
    "sg:address":"67 Main Ave",
    "sg:city":"Edinburg",
    "sg:classifiers":[
        {
            "category":"Home & Garden",
            "subcategory":"Hardware",
            "type":"Retail Goods"
        }
    ],
    "sg:phone":"+1 701 993 8122",
    "sg:postcode":"58227",
    "sg:province":"ND",
    "wof:name":"Edinburg General Store",
    "wof:placetype":"venue"
},
  "geometry": {"coordinates":[-97.865977,48.4963],"type":"Point"}
}