{
  "type": "Feature",
  "properties": {
    "addr:full":"721 11th Ave Langdon ND 58249",
    "addr:housenumber":"721",
    "addr:postcode":"58249",
    "addr:street":"11Th Ave",
    "iso:country":"US",
    "sg:address":"721 11th Ave",
    "sg:city":"Langdon",
    "sg:classifiers":[
        {
            "category":"Education",
            "subcategory":"School",
            "type":"Public Place"
        }
    ],
    "sg:phone":"+1 701 256 3270",
    "sg:postcode":"58249",
    "sg:province":"ND",
    "wof:name":"Langdon Elementary School",
    "wof:placetype":"venue"
},
  "geometry": {"coordinates":[-98.374639,48.76329],"type":"Point"}
}