{
  "type": "Feature",
  "properties": {
    "addr:full":"520 Logie St Jud ND 58454",
    "addr:housenumber":"520",
    "addr:postcode":"58454",
    "addr:street":"Logie St",
    "iso:country":"US",
    "sg:address":"520 Logie St",
    "sg:city":"Jud",
    "sg:classifiers":[
        {
            "category":"Professional",
            "type":"Services"
        }
    ],
    "sg:phone":"+1 701 685 2693",
    "sg:postcode":"58454",
    "sg:province":"ND",
    "sg:tags":[
        "establishment"
    ],
    "wof:name":"City",
    "wof:placetype":"venue"
},
  "geometry": {"coordinates":[-98.897657,46.525548],"type":"Point"}
}