{
  "type": "Feature",
  "properties": {
    "addr:full":"3225 55th Ave SE Medina ND 58467",
    "addr:housenumber":"3225",
    "addr:postcode":"58467",
    "addr:street":"55Th Ave Se",
    "iso:country":"US",
    "sg:address":"3225 55th Ave SE",
    "sg:city":"Medina",
    "sg:classifiers":[
        {
            "category":"Travel",
            "subcategory":"Hotels & Motels",
            "type":"Entertainment"
        }
    ],
    "sg:phone":"+1 701 486 3155",
    "sg:postcode":"58467",
    "sg:province":"ND",
    "sg:tags":[
        "operation"
    ],
    "wof:name":"North Country Lodge",
    "wof:placetype":"venue"
},
  "geometry": {"coordinates":[-99.29977100000001,46.93582],"type":"Point"}
}