{
  "type": "Feature",
  "properties": {
    "addr:full":"1200 Missouri Ave Bismarck ND 58504",
    "addr:housenumber":"1200",
    "addr:postcode":"58504",
    "addr:street":"Missouri Ave",
    "iso:country":"US",
    "sg:address":"1200 Missouri Ave",
    "sg:city":"Bismarck",
    "sg:classifiers":[
        {
            "category":"Government",
            "subcategory":"Office",
            "type":"Public Place"
        }
    ],
    "sg:phone":"+1 701 328 5210",
    "sg:postcode":"58504",
    "sg:province":"ND",
    "sg:tags":[
        "state",
        "program"
    ],
    "sg:website":"www.health.state.nd.us",
    "wof:name":"Water Quality Div",
    "wof:placetype":"venue"
},
  "geometry": {"coordinates":[-100.812453,46.809221],"type":"Point"}
}