{
  "type": "Feature",
  "properties": {
    "addr:full":"12003 71st Ave NE Bismarck ND 58503",
    "addr:housenumber":"12003",
    "addr:postcode":"58503",
    "addr:street":"71St Ave Ne",
    "iso:country":"US",
    "sg:address":"12003 71st Ave NE",
    "sg:city":"Bismarck",
    "sg:classifiers":[
        {
            "category":"Wholesale",
            "subcategory":"Auto Parts",
            "type":"Manufacturing & Wholesale Goods"
        }
    ],
    "sg:phone":"+1 701 258 3628",
    "sg:postcode":"58503",
    "sg:province":"ND",
    "sg:tags":[
        "automobile",
        "rebuilt"
    ],
    "wof:name":"Frontier Auto Wrecking & Rpr",
    "wof:placetype":"venue"
},
  "geometry": {"coordinates":[-100.60273599999999,46.881187],"type":"Point"}
}