{
  "type": "Feature",
  "properties": {
    "addr:full":"1634 Northview Ln Bismarck ND 58501",
    "addr:housenumber":"1634",
    "addr:postcode":"58501",
    "addr:street":"Northview Ln",
    "iso:country":"US",
    "sg:address":"1634 Northview Ln",
    "sg:city":"Bismarck",
    "sg:classifiers":[
        {
            "category":"Insurance",
            "subcategory":"Insurance Agent",
            "type":"Services"
        }
    ],
    "sg:phone":"+1 701 222 3400",
    "sg:postcode":"58501",
    "sg:province":"ND",
    "sg:tags":[
        "adjuster"
    ],
    "wof:name":"Schmidt Adjusters Of Bismark",
    "wof:placetype":"venue"
},
  "geometry": {"coordinates":[-100.75542900000001,46.821666],"type":"Point"}
}