{
  "type": "Feature",
  "properties": {
    "iso:country":"US",
    "sg:address":"3430 36th St",
    "sg:city":"Mandan",
    "sg:classifiers":[
        {
            "category":"Farming",
            "subcategory":"Farm",
            "type":"Manufacturing & Wholesale Goods"
        }
    ],
    "sg:phone":"+1 701 663 9150",
    "sg:postcode":"58554",
    "sg:province":"ND",
    "sg:tags":[
        "crop",
        "general"
    ],
    "wof:name":"Hatzenbu John",
    "wof:placetype":"venue"
},
  "geometry": {"coordinates":[-101.182188,46.890642],"type":"Point"}
}