{
  "type": "Feature",
  "properties": {
    "iso:country":"US",
    "sg:address":"101 1st St N",
    "sg:city":"New Rockford",
    "sg:classifiers":[
        {
            "category":"Restaurant",
            "type":"Food & Drink"
        }
    ],
    "sg:phone":"+1 701 947 5781",
    "sg:postcode":"58356",
    "sg:province":"ND",
    "wof:name":"Nathan's Burgers",
    "wof:placetype":"venue"
},
  "geometry": {"coordinates":[-99.12561599999999,47.681135],"type":"Point"}
}