{
  "type": "Feature",
  "properties": {
    "addr:full":"219 Dakota Ave Wahpeton ND 58075",
    "addr:housenumber":"219",
    "addr:postcode":"58075",
    "addr:street":"Dakota Ave",
    "iso:country":"US",
    "sg:address":"219 Dakota Ave",
    "sg:city":"Wahpeton",
    "sg:classifiers":[
        {
            "category":"Organizations",
            "subcategory":"Community Association",
            "type":"Services"
        }
    ],
    "sg:phone":"+1 701 642 2085",
    "sg:postcode":"58075",
    "sg:province":"ND",
    "sg:tags":[
        "military"
    ],
    "sg:website":"www.vfw.org",
    "wof:name":"Veterans Of Foreign Wars",
    "wof:placetype":"venue"
},
  "geometry": {"coordinates":[-96.603746,46.263834],"type":"Point"}
}