{
  "type": "Feature",
  "properties": {
    "addr:full":"620 3rd Ave Cando ND 58324",
    "addr:housenumber":"620",
    "addr:postcode":"58324",
    "addr:street":"3Rd Ave",
    "iso:country":"US",
    "sg:address":"620 3rd Ave",
    "sg:city":"Cando",
    "sg:classifiers":[
        {
            "category":"Organizations",
            "subcategory":"Religious Organization",
            "type":"Services"
        }
    ],
    "sg:phone":"+1 701 968 3248",
    "sg:postcode":"58324",
    "sg:province":"ND",
    "wof:name":"Church of Brethren",
    "wof:placetype":"venue"
},
  "geometry": {"coordinates":[-99.20672399999999,48.488662],"type":"Point"}
}