{
  "type": "Feature",
  "properties": {
    "iso:country":"US",
    "sg:address":"354 4th St NW",
    "sg:city":"Dickinson",
    "sg:classifiers":[
        {
            "category":"Personal",
            "subcategory":"Shoe Repair & Shine",
            "type":"Services"
        }
    ],
    "sg:phone":"+1 701 225 9464",
    "sg:postcode":"58601",
    "sg:province":"ND",
    "sg:tags":[
        "parlor"
    ],
    "wof:name":"Frenzel Shoe Repair & Saddlery",
    "wof:placetype":"venue"
},
  "geometry": {"coordinates":[-102.99157700000001,46.86344],"type":"Point"}
}