{
  "type": "Feature",
  "properties": {
    "iso:country":"US",
    "sg:address":"505 Main St",
    "sg:city":"Starkweather",
    "sg:classifiers":[
        {
            "category":"Education",
            "subcategory":"School",
            "type":"Public Place"
        }
    ],
    "sg:phone":"+1 701 292 4381",
    "sg:postcode":"58377",
    "sg:province":"ND",
    "wof:name":"Starkweather School Dist 44",
    "wof:placetype":"venue"
},
  "geometry": {"coordinates":[-98.875653,48.451865],"type":"Point"}
}