{
  "type": "Feature",
  "properties": {
    "addr:full":"707 20th Ave SE Minot ND 58701",
    "addr:housenumber":"707",
    "addr:postcode":"58701",
    "addr:street":"20Th Ave Se",
    "iso:country":"US",
    "sg:address":"707 20th Ave SE",
    "sg:city":"Minot",
    "sg:classifiers":[
        {
            "category":"Utilities",
            "subcategory":"Cable",
            "type":"Services"
        }
    ],
    "sg:phone":"+1 701 838 2808",
    "sg:postcode":"58701",
    "sg:province":"ND",
    "sg:tags":[
        "television"
    ],
    "wof:name":"Tcin Channel 16",
    "wof:placetype":"venue"
},
  "geometry": {"coordinates":[-101.28368500000001,48.211223],"type":"Point"}
}