{
  "type": "Feature",
  "properties": {
    "iso:country":"US",
    "sg:address":"517 Elm St",
    "sg:city":"Horace",
    "sg:classifiers":[
        {
            "category":"Building & Trades",
            "subcategory":"Construction",
            "type":"Services"
        }
    ],
    "sg:phone":"+1 701 367 4598",
    "sg:postcode":"58047",
    "sg:province":"ND",
    "sg:tags":[
        "house"
    ],
    "wof:name":"Plecity & Kowalski Cnstr",
    "wof:placetype":"venue"
},
  "geometry": {"coordinates":[-96.820464,46.673834],"type":"Point"}
}