{
  "type": "Feature",
  "properties": {
    "addr:full":"104 S Broadway St Linton ND 58552",
    "addr:housenumber":"104",
    "addr:postcode":"58552",
    "addr:street":"S Broadway St",
    "iso:country":"US",
    "sg:address":"104 S Broadway St",
    "sg:city":"Linton",
    "sg:classifiers":[
        {
            "category":"Real Estate",
            "subcategory":"Real Estate Agent",
            "type":"Services"
        }
    ],
    "sg:phone":"+1 701 254 4900",
    "sg:postcode":"58552",
    "sg:province":"ND",
    "sg:tags":[
        "appraiser"
    ],
    "wof:name":"Weisser Real Estate",
    "wof:placetype":"venue"
},
  "geometry": {"coordinates":[-100.23294300000001,46.265672],"type":"Point"}
}