{
  "type": "Feature",
  "properties": {
    "iso:country":"US",
    "sg:address":"1200 Hwy 49 N",
    "sg:city":"Beulah",
    "sg:classifiers":[
        {
            "category":"Restaurant",
            "type":"Food & Drink"
        }
    ],
    "sg:menulink":"http://www.allmenus.com/nd/west-mercer/244021-jimmys-pizza/menu/",
    "sg:phone":"+1 701 873 2500",
    "sg:postcode":"58523",
    "sg:province":"ND",
    "sg:tags":[
        "american",
        "pizza"
    ],
    "wof:name":"Jimmy's Pizza",
    "wof:placetype":"venue"
},
  "geometry": {"coordinates":[-101.78356599999999,47.274312],"type":"Point"}
}