{
  "type": "Feature",
  "properties": {
    "iso:country":"US",
    "sg:address":"921 Dakota Ave",
    "sg:city":"Wahpeton",
    "sg:classifiers":[
        {
            "category":"Home & Garden",
            "subcategory":"Building Materials",
            "type":"Retail Goods"
        }
    ],
    "sg:phone":"+1 701 672 4527",
    "sg:postcode":"58075",
    "sg:province":"ND",
    "sg:tags":[
        "glass",
        "window",
        "plate"
    ],
    "wof:name":"Jawaski Glass Repair & Rhino",
    "wof:placetype":"venue"
},
  "geometry": {"coordinates":[-96.61394199999999,46.263855],"type":"Point"}
}