{
  "type": "Feature",
  "properties": {
    "iso:country":"US",
    "sg:address":"220 4th St SW",
    "sg:city":"Steele",
    "sg:classifiers":[
        {
            "category":"Organizations",
            "subcategory":"Religious Organization",
            "type":"Services"
        }
    ],
    "sg:phone":"+1 701 475 2333",
    "sg:postcode":"58482",
    "sg:province":"ND",
    "sg:tags":[
        "church"
    ],
    "wof:name":"St Francis De Sales Catholic",
    "wof:placetype":"venue"
},
  "geometry": {"coordinates":[-99.918633,46.850441],"type":"Point"}
}