{
  "type": "Feature",
  "properties": {
    "iso:country":"US",
    "sg:address":"17 7th St S",
    "sg:city":"Fargo",
    "sg:classifiers":[
        {
            "category":"Real Estate",
            "subcategory":"Architect",
            "type":"Services"
        }
    ],
    "sg:phone":"+1 701 237 5427",
    "sg:postcode":"58103",
    "sg:province":"ND",
    "sg:tags":[
        "building",
        "designer"
    ],
    "wof:name":"By Design",
    "wof:placetype":"venue"
},
  "geometry": {"coordinates":[-96.789671,46.87414],"type":"Point"}
}