{
  "type": "Feature",
  "properties": {
    "iso:country":"US",
    "sg:address":"153 Museum Trl",
    "sg:city":"Dunn Center",
    "sg:classifiers":[
        {
            "category":"Museum",
            "type":"Entertainment"
        }
    ],
    "sg:phone":"+1 701 548 8111",
    "sg:postcode":"58626",
    "sg:province":"ND",
    "wof:name":"Dunn County Historical Museum",
    "wof:placetype":"venue"
},
  "geometry": {"coordinates":[-102.62316,47.354848],"type":"Point"}
}