{
  "type": "Feature",
  "properties": {
    "iso:country":"US",
    "sg:address":"411 Crescent Dr",
    "sg:city":"Thompson",
    "sg:classifiers":[
        {
            "category":"Recreation",
            "subcategory":"Picnic Area",
            "type":"Entertainment"
        },
        {
            "category":"Community Center",
            "type":"Public Place"
        }
    ],
    "sg:phone":"+1 701 741 5735",
    "sg:postcode":"58278",
    "sg:province":"ND",
    "sg:tags":[
        "amusement",
        "arcade"
    ],
    "wof:name":"Northern Tier Officials",
    "wof:placetype":"venue"
},
  "geometry": {"coordinates":[-97.10781299999999,47.772321],"type":"Point"}
}