{
  "type": "Feature",
  "properties": {
    "addr:full":"170 55th Ave NW Hazen ND 58545",
    "addr:housenumber":"170",
    "addr:postcode":"58545",
    "addr:street":"55Th Ave Nw",
    "iso:country":"US",
    "sg:address":"170 55th Ave NW",
    "sg:city":"Hazen",
    "sg:phone":"+1 701 748 2479",
    "sg:postcode":"58545",
    "sg:province":"ND",
    "sg:tags":[
        "farm",
        "grain",
        "cash"
    ],
    "wof:name":"Raymond Mattheis",
    "wof:placetype":"venue"
},
  "geometry": {"coordinates":[-101.71623,47.424319],"type":"Point"}
}