{
  "type": "Feature",
  "properties": {
    "iso:country":"US",
    "sg:address":"11516 78th St NE",
    "sg:city":"Milton",
    "sg:classifiers":[
        {
            "category":"Professional",
            "type":"Services"
        }
    ],
    "sg:phone":"+1 701 966 2505",
    "sg:postcode":"58260",
    "sg:province":"ND",
    "sg:tags":[
        "establishment"
    ],
    "wof:name":"Olson Homestead Trust",
    "wof:placetype":"venue"
},
  "geometry": {"coordinates":[-98.144412,48.543278],"type":"Point"}
}