{
  "type": "Feature",
  "properties": {
    "iso:country":"US",
    "sg:address":"8095 11th St NE",
    "sg:city":"Grace City",
    "sg:phone":"+1 701 674 3416",
    "sg:postcode":"58445",
    "sg:province":"ND",
    "sg:tags":[
        "farm",
        "wheat"
    ],
    "wof:name":"Gilbert Black",
    "wof:placetype":"venue"
},
  "geometry": {"coordinates":[-98.82075399999999,47.573063],"type":"Point"}
}