{
  "type": "Feature",
  "properties": {
    "iso:country":"US",
    "sg:address":"119 Broadway",
    "sg:city":"Fargo",
    "sg:classifiers":[
        {
            "category":"Restaurant",
            "type":"Food & Drink"
        }
    ],
    "sg:phone":"+1 701 235 7662",
    "sg:postcode":"58102",
    "sg:province":"ND",
    "sg:tags":[
        "eating"
    ],
    "wof:name":"Fargo Dog House",
    "wof:placetype":"venue"
},
  "geometry": {"coordinates":[-96.787611,46.877819],"type":"Point"}
}