{
  "type": "Feature",
  "properties": {
    "addr:full":"202 Main St Gackle ND 58442",
    "addr:housenumber":"202",
    "addr:postcode":"58442",
    "addr:street":"Main St",
    "iso:country":"US",
    "sg:address":"202 Main St",
    "sg:city":"Gackle",
    "sg:classifiers":[
        {
            "category":"Government",
            "subcategory":"Post Office",
            "type":"Public Place"
        }
    ],
    "sg:phone":"+1 701 485 3704",
    "sg:postcode":"58442",
    "sg:province":"ND",
    "wof:name":"US Post Office",
    "wof:placetype":"venue"
},
  "geometry": {"coordinates":[-99.14251899999999,46.628716],"type":"Point"}
}