{
  "type": "Feature",
  "properties": {
    "iso:country":"US",
    "sg:address":"2507 121st Ave S W",
    "sg:city":"Belfield",
    "sg:classifiers":[
        {
            "category":"Farming",
            "subcategory":"Livestock Farm",
            "type":"Manufacturing & Wholesale Goods"
        }
    ],
    "sg:phone":"+1 701 677 5817",
    "sg:postcode":"58622",
    "sg:province":"ND",
    "sg:tags":[
        "feedlot",
        "hog",
        "or",
        "beef",
        "cattle"
    ],
    "wof:name":"Myron Polensky",
    "wof:placetype":"venue"
},
  "geometry": {"coordinates":[-103.05413900000001,47.06769],"type":"Point"}
}