{
  "type": "Feature",
  "properties": {
    "iso:country":"US",
    "sg:address":"646 Lewis Ave",
    "sg:city":"Larimore",
    "sg:classifiers":[
        {
            "category":"Communications",
            "subcategory":"Radio Station",
            "type":"Services"
        }
    ],
    "sg:phone":"+1 701 343 7097",
    "sg:postcode":"58251",
    "sg:province":"ND",
    "sg:tags":[
        "education"
    ],
    "wof:name":"Jo-Anne Lavigne",
    "wof:placetype":"venue"
},
  "geometry": {"coordinates":[-97.62174400000001,47.910414],"type":"Point"}
}