{
  "type": "Feature",
  "properties": {
    "iso:country":"US",
    "sg:address":"16220 69th St SE",
    "sg:city":"Walcott",
    "sg:classifiers":[
        {
            "category":"Farming",
            "subcategory":"Farm",
            "type":"Manufacturing & Wholesale Goods"
        }
    ],
    "sg:phone":"+1 701 372 3785",
    "sg:postcode":"58077",
    "sg:province":"ND",
    "wof:name":"Dahlgren Farms",
    "wof:placetype":"venue"
},
  "geometry": {"coordinates":[-97.02851099999999,46.412594],"type":"Point"}
}