{
  "type": "Feature",
  "properties": {
    "addr:full":"9673 State Hwy 15 Tolna ND 58380",
    "addr:housenumber":"9673",
    "addr:postcode":"58380",
    "addr:street":"State Hwy 15 Tolna",
    "iso:country":"US",
    "sg:address":"9673 State Hwy 15",
    "sg:city":"Tolna",
    "sg:phone":"+1 701 262 4791",
    "sg:postcode":"58380",
    "sg:province":"ND",
    "sg:tags":[
        "farm",
        "wheat"
    ],
    "wof:name":"Myron Halvorso",
    "wof:placetype":"venue"
},
  "geometry": {"coordinates":[-98.50991,47.802843],"type":"Point"}
}