{
  "type": "Feature",
  "properties": {
    "iso:country":"US",
    "sg:address":"922 Lincoln Ave",
    "sg:city":"Harvey",
    "sg:classifiers":[
        {
            "category":"Health Services",
            "subcategory":"Doctor",
            "type":"Services"
        }
    ],
    "sg:phone":"+1 701 324 4856",
    "sg:postcode":"58341",
    "sg:province":"ND",
    "sg:tags":[
        "medical",
        "clinic"
    ],
    "wof:name":"Central Dakota Clinic",
    "wof:placetype":"venue"
},
  "geometry": {"coordinates":[-99.936272,47.768914],"type":"Point"}
}