{
  "type": "Feature",
  "properties": {
    "iso:country":"US",
    "sg:address":"421 Main St",
    "sg:city":"Williston",
    "sg:classifiers":[
        {
            "category":"Professional",
            "subcategory":"Business Services",
            "type":"Services"
        }
    ],
    "sg:phone":"+1 701 572 0392",
    "sg:postcode":"58801",
    "sg:province":"ND",
    "sg:tags":[
        "paging",
        "answering"
    ],
    "wof:name":"Missouri Valley Communications",
    "wof:placetype":"venue"
},
  "geometry": {"coordinates":[-103.622084,48.147749],"type":"Point"}
}