{
  "type": "Feature",
  "properties": {
    "iso:country":"US",
    "sg:address":"4311 122nd Ave SW",
    "sg:city":"South Heart",
    "sg:classifiers":[
        {
            "category":"Farming",
            "subcategory":"Farm",
            "type":"Manufacturing & Wholesale Goods"
        }
    ],
    "sg:phone":"+1 701 677 5696",
    "sg:postcode":"58655",
    "sg:province":"ND",
    "sg:tags":[
        "crop",
        "general"
    ],
    "wof:name":"Robert Privats",
    "wof:placetype":"venue"
},
  "geometry": {"coordinates":[-103.020515,46.788451],"type":"Point"}
}