{
  "type": "Feature",
  "properties": {
    "iso:country":"US",
    "sg:address":"8401 Cresthill Rd",
    "sg:city":"Bismarck",
    "sg:classifiers":[
        {
            "category":"Building & Trades",
            "subcategory":"Construction",
            "type":"Services"
        }
    ],
    "sg:phone":"+1 701 258 5041",
    "sg:postcode":"58504",
    "sg:province":"ND",
    "sg:tags":[
        "house"
    ],
    "wof:name":"Pifer Construction",
    "wof:placetype":"venue"
},
  "geometry": {"coordinates":[-100.660991,46.737608],"type":"Point"}
}