{
  "type": "Feature",
  "properties": {
    "iso:country":"US",
    "sg:address":"141 Lake Ave",
    "sg:city":"Sibley",
    "sg:classifiers":[
        {
            "category":"Utilities",
            "subcategory":"Refuse",
            "type":"Services"
        }
    ],
    "sg:phone":"+1 701 733 2327",
    "sg:postcode":"58429",
    "sg:province":"ND",
    "sg:tags":[
        "garbage",
        "collection"
    ],
    "wof:name":"Brager's Disposal Svc",
    "wof:placetype":"venue"
},
  "geometry": {"coordinates":[-97.965288,47.220155],"type":"Point"}
}