{
  "type": "Feature",
  "properties": {
    "addr:full":"1581 Atlanta Dr Bismarck ND 58504",
    "addr:housenumber":"1581",
    "addr:postcode":"58504",
    "addr:street":"Atlanta Dr",
    "iso:country":"US",
    "sg:address":"1581 Atlanta Dr",
    "sg:city":"Bismarck",
    "sg:classifiers":[
        {
            "category":"Social Services",
            "type":"Services"
        }
    ],
    "sg:phone":"+1 701 222 3222",
    "sg:postcode":"58504",
    "sg:province":"ND",
    "wof:name":"Western Counseling Consulting",
    "wof:placetype":"venue"
},
  "geometry": {"coordinates":[-100.78336,46.787681],"type":"Point"}
}