{
  "type": "Feature",
  "properties": {
    "addr:full":"1463 12th Street Ct West Fargo ND 58078",
    "addr:housenumber":"1463",
    "addr:postcode":"58078",
    "addr:street":"12Th Street Ct",
    "iso:country":"US",
    "sg:address":"1463 12th Street Ct",
    "sg:city":"West Fargo",
    "sg:classifiers":[
        {
            "category":"Building & Trades",
            "subcategory":"Construction",
            "type":"Services"
        }
    ],
    "sg:phone":"+1 701 282 6023",
    "sg:postcode":"58078",
    "sg:province":"ND",
    "sg:tags":[
        "house"
    ],
    "wof:name":"Klein Construction Inc",
    "wof:placetype":"venue"
},
  "geometry": {"coordinates":[-96.881282,46.859384],"type":"Point"}
}