{
  "type": "Feature",
  "properties": {
    "iso:country":"US",
    "sg:address":"117 23rd St N",
    "sg:city":"Fargo",
    "sg:classifiers":[
        {
            "category":"Building & Trades",
            "subcategory":"Construction",
            "type":"Services"
        }
    ],
    "sg:phone":"+1 701 293 5310",
    "sg:postcode":"58102",
    "sg:province":"ND",
    "sg:tags":[
        "siding",
        "contractor"
    ],
    "sg:website":"www.westernproducts.com",
    "wof:name":"Western Products Inc",
    "wof:placetype":"venue"
},
  "geometry": {"coordinates":[-96.816616,46.877979],"type":"Point"}
}