{
  "type": "Feature",
  "properties": {
    "iso:country":"US",
    "sg:address":"4615 127th Ave SE",
    "sg:city":"Fingal",
    "sg:phone":"+1 701 924 8820",
    "sg:postcode":"58031",
    "sg:province":"ND",
    "sg:tags":[
        "farm",
        "wheat"
    ],
    "wof:name":"Maasjo Marlyn",
    "wof:placetype":"venue"
},
  "geometry": {"coordinates":[-97.787328,46.743658],"type":"Point"}
}