{
  "type": "Feature",
  "properties": {
    "addr:full":"2919 17th St NW Coleharbor ND 58531",
    "addr:housenumber":"2919",
    "addr:postcode":"58531",
    "addr:street":"17Th St Nw Coleharbor",
    "iso:country":"US",
    "sg:address":"2919 17th St NW",
    "sg:city":"Coleharbor",
    "sg:classifiers":[
        {
            "category":"Building & Trades",
            "subcategory":"Construction",
            "type":"Services"
        }
    ],
    "sg:phone":"+1 701 337 5640",
    "sg:postcode":"58531",
    "sg:province":"ND",
    "sg:tags":[
        "water",
        "well",
        "drilling"
    ],
    "wof:name":"Stumvoll Drilling",
    "wof:placetype":"venue"
},
  "geometry": {"coordinates":[-101.176929,47.660475],"type":"Point"}
}