{
  "type": "Feature",
  "properties": {
    "iso:country":"US",
    "sg:address":"515 N 4th St",
    "sg:city":"Bismarck",
    "sg:classifiers":[
        {
            "category":"Professional",
            "subcategory":"Lawyer & Legal Services",
            "type":"Services"
        }
    ],
    "sg:phone":"+1 701 222 2035",
    "sg:postcode":"58501",
    "sg:province":"ND",
    "wof:name":"Bolinske Law Firm",
    "wof:placetype":"venue"
},
  "geometry": {"coordinates":[-100.785961,46.810501],"type":"Point"}
}