{
  "type": "Feature",
  "properties": {
    "addr:full":"1605 3rd Ave NW Mandan ND 58554",
    "addr:housenumber":"1605",
    "addr:postcode":"58554",
    "addr:street":"3Rd Ave Nw",
    "iso:country":"US",
    "sg:address":"1605 3rd Ave NW",
    "sg:city":"Mandan",
    "sg:classifiers":[
        {
            "category":"Building & Trades",
            "subcategory":"Construction",
            "type":"Services"
        }
    ],
    "sg:phone":"+1 701 663 4233",
    "sg:postcode":"58554",
    "sg:province":"ND",
    "sg:tags":[
        "concrete",
        "cutting",
        "breaking",
        "sawing"
    ],
    "wof:name":"J & J Equipment & Construction",
    "wof:placetype":"venue"
},
  "geometry": {"coordinates":[-100.897183,46.840811],"type":"Point"}
}