{
  "type": "Feature",
  "properties": {
    "addr:full":"501 Main St Gackle ND 58442",
    "addr:housenumber":"501",
    "addr:postcode":"58442",
    "addr:street":"Main St",
    "iso:country":"US",
    "sg:address":"501 Main St",
    "sg:city":"Gackle",
    "sg:classifiers":[
        {
            "category":"Professional",
            "subcategory":"Accounting & Tax Preparation",
            "type":"Services"
        }
    ],
    "sg:phone":"+1 701 485 3755",
    "sg:postcode":"58442",
    "sg:province":"ND",
    "sg:tags":[
        "bookkeeping",
        "general"
    ],
    "wof:name":"Integrity Business Svc",
    "wof:placetype":"venue"
},
  "geometry": {"coordinates":[-99.142504,46.625876],"type":"Point"}
}