{
  "type": "Feature",
  "properties": {
    "iso:country":"US",
    "sg:address":"1318 24th St W",
    "sg:city":"Williston",
    "sg:classifiers":[
        {
            "category":"Social Services",
            "subcategory":"Child Care",
            "type":"Services"
        }
    ],
    "sg:phone":"+1 701 572 8083",
    "sg:postcode":"58801",
    "sg:province":"ND",
    "wof:name":"Special Care",
    "wof:placetype":"venue"
},
  "geometry": {"coordinates":[-103.64222100000001,48.166706],"type":"Point"}
}