{
  "type": "Feature",
  "properties": {
    "iso:country":"US",
    "sg:address":"890 Main St",
    "sg:city":"Carrington",
    "sg:classifiers":[
        {
            "category":"Social Services",
            "type":"Services"
        }
    ],
    "sg:phone":"+1 701 652 2159",
    "sg:postcode":"58421",
    "sg:province":"ND",
    "sg:tags":[
        "youth",
        "organization",
        "center"
    ],
    "wof:name":"Carrington Youth Ctr",
    "wof:placetype":"venue"
},
  "geometry": {"coordinates":[-99.123925,47.449466],"type":"Point"}
}