{
  "type": "Feature",
  "properties": {
    "addr:full":"3251 162nd Ave SW Sentinel Butte ND 58654",
    "addr:housenumber":"3251",
    "addr:postcode":"58654",
    "addr:street":"162Nd Ave Sw",
    "iso:country":"US",
    "sg:address":"3251 162nd Ave SW",
    "sg:city":"Sentinel Butte",
    "sg:classifiers":[
        {
            "category":"Freight",
            "type":"Transportation"
        }
    ],
    "sg:phone":"+1 701 872 4965",
    "sg:postcode":"58654",
    "sg:province":"ND",
    "sg:tags":[
        "operator",
        "trucking"
    ],
    "wof:name":"M Anderson Loran",
    "wof:placetype":"venue"
},
  "geometry": {"coordinates":[-103.860472,46.936696],"type":"Point"}
}