{
  "type": "Feature",
  "properties": {
    "iso:country":"US",
    "sg:address":"406 Oak St",
    "sg:city":"Lisbon",
    "sg:classifiers":[
        {
            "category":"Building & Trades",
            "subcategory":"Construction",
            "type":"Services"
        }
    ],
    "sg:phone":"+1 701 683 3410",
    "sg:postcode":"58054",
    "sg:province":"ND",
    "sg:tags":[
        "excavating",
        "contractor"
    ],
    "wof:name":"Mlaskoch Excavating",
    "wof:placetype":"venue"
},
  "geometry": {"coordinates":[-97.683029,46.442431],"type":"Point"}
}