{
  "type": "Feature",
  "properties": {
    "addr:full":"616 Main St Bottineau ND 58318",
    "addr:housenumber":"616",
    "addr:postcode":"58318",
    "addr:street":"Main St",
    "iso:country":"US",
    "sg:address":"616 Main St",
    "sg:city":"Bottineau",
    "sg:classifiers":[
        {
            "category":"Professional",
            "subcategory":"Lawyer & Legal Services",
            "type":"Services"
        }
    ],
    "sg:phone":"+1 701 228 3655",
    "sg:postcode":"58318",
    "sg:province":"ND",
    "sg:tags":[
        "attorney"
    ],
    "wof:name":"Benson Law Office PC",
    "wof:placetype":"venue"
},
  "geometry": {"coordinates":[-100.446,48.826129],"type":"Point"}
}