{
  "type": "Feature",
  "properties": {
    "iso:country":"US",
    "sg:address":"80 Main St",
    "sg:city":"Buffalo",
    "sg:classifiers":[
        {
            "category":"Freight",
            "type":"Transportation"
        },
        {
            "category":"Wholesale",
            "subcategory":"Farm Supplies",
            "type":"Manufacturing & Wholesale Goods"
        }
    ],
    "sg:phone":"+1 701 633 5111",
    "sg:postcode":"58011",
    "sg:province":"ND",
    "sg:tags":[
        "grain",
        "elevator"
    ],
    "wof:name":"Buffalo Farm Supply Inc",
    "wof:placetype":"venue"
},
  "geometry": {"coordinates":[-97.55726900000001,46.919909],"type":"Point"}
}