{
  "type": "Feature",
  "properties": {
    "iso:country":"US",
    "sg:address":"3616 81st Ave SE",
    "sg:city":"Jamestown",
    "sg:classifiers":[
        {
            "category":"Farming",
            "subcategory":"Farm",
            "type":"Manufacturing & Wholesale Goods"
        }
    ],
    "sg:phone":"+1 701 252 5762",
    "sg:postcode":"58401",
    "sg:province":"ND",
    "sg:tags":[
        "crop",
        "general"
    ],
    "wof:name":"Corell John",
    "wof:placetype":"venue"
},
  "geometry": {"coordinates":[-98.755259,46.888247],"type":"Point"}
}