{
  "type": "Feature",
  "properties": {
    "addr:full":"2719 37th St NW Mandan ND 58554",
    "addr:housenumber":"2719",
    "addr:postcode":"58554",
    "addr:street":"37Th St Nw",
    "iso:country":"US",
    "sg:address":"2719 37th St NW",
    "sg:city":"Mandan",
    "sg:classifiers":[
        {
            "category":"Manufacturing",
            "subcategory":"Tools & Machinery",
            "type":"Manufacturing & Wholesale Goods"
        }
    ],
    "sg:phone":"+1 701 663 6736",
    "sg:postcode":"58554",
    "sg:province":"ND",
    "sg:tags":[
        "set",
        "mfg"
    ],
    "wof:name":"Power Generation Service",
    "wof:placetype":"venue"
},
  "geometry": {"coordinates":[-100.927662,46.858822],"type":"Point"}
}