{
  "type": "Feature",
  "properties": {
    "addr:full":"4101 13th Ave S Fargo ND 58103",
    "addr:housenumber":"4101",
    "addr:postcode":"58103",
    "addr:street":"13Th Ave S",
    "iso:country":"US",
    "sg:address":"4101 13th Ave S",
    "sg:city":"Fargo",
    "sg:classifiers":[
        {
            "category":"Banks & Credit Unions",
            "subcategory":"Bank",
            "type":"Services"
        }
    ],
    "sg:phone":"+1 701 281 4310",
    "sg:postcode":"58103",
    "sg:province":"ND",
    "wof:name":"Wells Fargo Bank",
    "wof:placetype":"venue"
},
  "geometry": {"coordinates":[-96.849276,46.861891],"type":"Point"}
}