{
  "type": "Feature",
  "properties": {
    "iso:country":"US",
    "sg:address":"1930 E Capitol Ave",
    "sg:city":"Bismarck",
    "sg:classifiers":[
        {
            "category":"Real Estate",
            "subcategory":"Real Estate Operator",
            "type":"Services"
        }
    ],
    "sg:phone":"+1 701 223 7399",
    "sg:postcode":"58501",
    "sg:province":"ND",
    "sg:tags":[
        "apartment"
    ],
    "wof:name":"North Pointe Apartments",
    "wof:placetype":"venue"
},
  "geometry": {"coordinates":[-100.76069099999999,46.829876],"type":"Point"}
}