{
  "type": "Feature",
  "properties": {
    "iso:country":"US",
    "sg:address":"714 Front St",
    "sg:city":"Casselton",
    "sg:classifiers":[
        {
            "category":"Home & Garden",
            "subcategory":"Hardware",
            "type":"Retail Goods"
        }
    ],
    "sg:phone":"+1 701 347 4265",
    "sg:postcode":"58012",
    "sg:province":"ND",
    "wof:name":"Hardware Hank",
    "wof:placetype":"venue"
},
  "geometry": {"coordinates":[-97.211206,46.900577],"type":"Point"}
}