{
  "type": "Feature",
  "properties": {
    "iso:country":"US",
    "sg:address":"1440 S Washington St",
    "sg:city":"Grand Forks",
    "sg:classifiers":[
        {
            "category":"Shopping",
            "subcategory":"Used Merchandise",
            "type":"Retail Goods"
        }
    ],
    "sg:phone":"+1 701 775 3443",
    "sg:postcode":"58201",
    "sg:province":"ND",
    "wof:name":"1st Rate Pawn",
    "wof:placetype":"venue"
},
  "geometry": {"coordinates":[-97.045109,47.90792],"type":"Point"}
}