{
  "type": "Feature",
  "properties": {
    "addr:full":"9685 65th Ave SE Ashley ND 58413",
    "addr:housenumber":"9685",
    "addr:postcode":"58413",
    "addr:street":"65Th Ave Se",
    "iso:country":"US",
    "sg:address":"9685 65th Ave SE",
    "sg:city":"Ashley",
    "sg:classifiers":[
        {
            "category":"Organizations",
            "subcategory":"Professional Association",
            "type":"Services"
        }
    ],
    "sg:phone":"+1 701 374 5611",
    "sg:postcode":"58413",
    "sg:province":"ND",
    "wof:name":"North Dakota Dairy Coalition",
    "wof:placetype":"venue"
},
  "geometry": {"coordinates":[-99.02569200000001,46.015027],"type":"Point"}
}