{
  "type": "Feature",
  "properties": {
    "iso:country":"US",
    "sg:address":"1613 Terrace Ct",
    "sg:city":"Minot",
    "sg:classifiers":[
        {
            "category":"Retail",
            "subcategory":"Animal Services",
            "type":"Services"
        }
    ],
    "sg:phone":"+1 701 838 5349",
    "sg:postcode":"58703",
    "sg:province":"ND",
    "wof:name":"Top Dog Grooming Salon",
    "wof:placetype":"venue"
},
  "geometry": {"coordinates":[-101.318444,48.254934],"type":"Point"}
}