{
  "type": "Feature",
  "properties": {
    "iso:country":"US",
    "sg:address":"927 3rd St NE",
    "sg:city":"Fessenden",
    "sg:classifiers":[
        {
            "category":"Social Services",
            "type":"Services"
        }
    ],
    "sg:phone":"+1 701 547 3698",
    "sg:postcode":"58438",
    "sg:province":"ND",
    "wof:name":"Fessenden Group Home",
    "wof:placetype":"venue"
},
  "geometry": {"coordinates":[-99.621095,47.649649],"type":"Point"}
}