{
  "type": "Feature",
  "properties": {
    "iso:country":"US",
    "sg:address":"1815 37th Ave S",
    "sg:city":"Fargo",
    "sg:classifiers":[
        {
            "category":"Professional",
            "subcategory":"Business Services",
            "type":"Services"
        }
    ],
    "sg:phone":"+1 701 237 5695",
    "sg:postcode":"58104",
    "sg:province":"ND",
    "wof:name":"Ace Group LLP",
    "wof:placetype":"venue"
},
  "geometry": {"coordinates":[-96.81127600000001,46.824078],"type":"Point"}
}