{
  "type": "Feature",
  "properties": {
    "iso:country":"US",
    "sg:address":"311 Main St",
    "sg:city":"New Town",
    "sg:classifiers":[
        {
            "category":"Autos & Motor Vehicles",
            "subcategory":"Auto Supplies",
            "type":"Retail Goods"
        }
    ],
    "sg:phone":"+1 701 627 4114",
    "sg:postcode":"58763",
    "sg:province":"ND",
    "sg:tags":[
        "automobile",
        "parts"
    ],
    "wof:name":"North Shore Auto Parts",
    "wof:placetype":"venue"
},
  "geometry": {"coordinates":[-102.487818,47.979594],"type":"Point"}
}