{
  "type": "Feature",
  "properties": {
    "iso:country":"US",
    "sg:address":"3552 81st Ave SE",
    "sg:city":"Jamestown",
    "sg:classifiers":[
        {
            "category":"Wholesale",
            "subcategory":"Farm Supplies",
            "type":"Manufacturing & Wholesale Goods"
        }
    ],
    "sg:phone":"+1 701 252 2777",
    "sg:postcode":"58401",
    "sg:province":"ND",
    "sg:tags":[
        "fertilizer"
    ],
    "wof:name":"Agramax",
    "wof:placetype":"venue"
},
  "geometry": {"coordinates":[-98.755251,46.90187],"type":"Point"}
}