{
  "type": "Feature",
  "properties": {
    "iso:country":"US",
    "sg:address":"3150 39th St SW",
    "sg:city":"Fargo",
    "sg:classifiers":[
        {
            "category":"Personal",
            "subcategory":"Beauty Salon",
            "type":"Services"
        }
    ],
    "sg:phone":"+1 701 356 9987",
    "sg:postcode":"58104",
    "sg:province":"ND",
    "wof:name":"B Sassy Salon",
    "wof:placetype":"venue"
},
  "geometry": {"coordinates":[-96.84575100000001,46.833302],"type":"Point"}
}