{
  "type": "Feature",
  "properties": {
    "iso:country":"US",
    "sg:address":"4141 38th St SW",
    "sg:city":"Fargo",
    "sg:classifiers":[
        {
            "category":"Banks & Credit Unions",
            "subcategory":"Bank",
            "type":"Services"
        }
    ],
    "sg:phone":"+1 701 356 6400",
    "sg:postcode":"58104",
    "sg:province":"ND",
    "sg:tags":[
        "loan"
    ],
    "wof:name":"Valesco Mortgage",
    "wof:placetype":"venue"
},
  "geometry": {"coordinates":[-96.84032999999999,46.815544],"type":"Point"}
}