{
  "type": "Feature",
  "properties": {
    "iso:country":"US",
    "sg:address":"2400 32nd Ave",
    "sg:city":"Fargo",
    "sg:classifiers":[
        {
            "category":"Health Services",
            "subcategory":"Doctor",
            "type":"Services"
        }
    ],
    "sg:phone":"+1 701 234 8850",
    "sg:postcode":"58103",
    "sg:province":"ND",
    "sg:tags":[
        "medical"
    ],
    "wof:name":"Meritcire",
    "wof:placetype":"venue"
},
  "geometry": {"coordinates":[-96.819706,46.832395],"type":"Point"}
}