{
  "type": "Feature",
  "properties": {
    "iso:country":"US",
    "sg:address":"275 5th Ave S",
    "sg:city":"Carrington",
    "sg:classifiers":[
        {
            "category":"Farming",
            "subcategory":"Livestock Farm",
            "type":"Manufacturing & Wholesale Goods"
        }
    ],
    "sg:phone":"+1 701 652 2747",
    "sg:postcode":"58421",
    "sg:province":"ND",
    "sg:tags":[
        "beef",
        "except",
        "feedlot",
        "cattle"
    ],
    "wof:name":"Reimers Farms",
    "wof:placetype":"venue"
},
  "geometry": {"coordinates":[-99.118996,47.446721],"type":"Point"}
}