{
  "type": "Feature",
  "properties": {
    "iso:country":"US",
    "sg:address":"6501 310th St NW",
    "sg:city":"Berthold",
    "sg:phone":"+1 701 453 3567",
    "sg:postcode":"58718",
    "sg:province":"ND",
    "sg:tags":[
        "farm",
        "grain",
        "cash"
    ],
    "wof:name":"Judith Deaver Farm",
    "wof:placetype":"venue"
},
  "geometry": {"coordinates":[-101.77168500000001,48.303186],"type":"Point"}
}