{
  "type": "Feature",
  "properties": {
    "iso:country":"US",
    "sg:address":"12 4th St NE",
    "sg:city":"Hillsboro",
    "sg:classifiers":[
        {
            "category":"Education",
            "subcategory":"School",
            "type":"Public Place"
        }
    ],
    "sg:phone":"+1 701 636 4360",
    "sg:postcode":"58045",
    "sg:province":"ND",
    "sg:website":"www.hillsboro.k12.nd.us",
    "wof:name":"Hillsboro High School",
    "wof:placetype":"venue"
},
  "geometry": {"coordinates":[-97.055235,47.404231],"type":"Point"}
}