{
  "type": "Feature",
  "properties": {
    "iso:country":"US",
    "sg:address":"812 Lilac Ave",
    "sg:city":"Oakes",
    "sg:classifiers":[
        {
            "category":"Real Estate",
            "subcategory":"Real Estate Operator",
            "type":"Services"
        }
    ],
    "sg:phone":"+1 701 742 3369",
    "sg:postcode":"58474",
    "sg:province":"ND",
    "sg:tags":[
        "property",
        "lessor"
    ],
    "wof:name":"Miles Thompson",
    "wof:placetype":"venue"
},
  "geometry": {"coordinates":[-98.088922,46.134607],"type":"Point"}
}