{
  "type": "Feature",
  "properties": {
    "iso:country":"US",
    "sg:address":"1521 24th Ave S",
    "sg:city":"Grand Forks",
    "sg:classifiers":[
        {
            "category":"Professional",
            "subcategory":"Detective & Security Services",
            "type":"Services"
        }
    ],
    "sg:phone":"+1 701 772 2611",
    "sg:postcode":"58201",
    "sg:province":"ND",
    "sg:tags":[
        "car",
        "armored"
    ],
    "wof:name":"Grand Forks Armored Express",
    "wof:placetype":"venue"
},
  "geometry": {"coordinates":[-97.047901,47.895885],"type":"Point"}
}