{
  "type": "Feature",
  "properties": {
    "iso:country":"US",
    "sg:address":"3401 25th St S",
    "sg:city":"Fargo",
    "sg:classifiers":[
        {
            "category":"Organizations",
            "subcategory":"Religious Organization",
            "type":"Services"
        }
    ],
    "sg:phone":"+1 701 232 0003",
    "sg:postcode":"58104",
    "sg:province":"ND",
    "wof:name":"First Assembly of God Church",
    "wof:placetype":"venue"
},
  "geometry": {"coordinates":[-96.81981399999999,46.82893],"type":"Point"}
}