{
  "type": "Feature",
  "properties": {
    "iso:country":"US",
    "sg:address":"702 8th St NE",
    "sg:city":"Belfield",
    "sg:classifiers":[
        {
            "category":"Wholesale",
            "subcategory":"Machinery & Supplies",
            "type":"Manufacturing & Wholesale Goods"
        }
    ],
    "sg:phone":"+1 701 575 4327",
    "sg:postcode":"58622",
    "sg:province":"ND",
    "sg:tags":[
        "field",
        "oil"
    ],
    "wof:name":"Wilson Supply Co",
    "wof:placetype":"venue"
},
  "geometry": {"coordinates":[-103.186322,46.894714],"type":"Point"}
}