{
  "type": "Feature",
  "properties": {
    "addr:full":"1009 W Villard St Dickinson ND 58601",
    "addr:housenumber":"1009",
    "addr:postcode":"58601",
    "addr:street":"W Villard St",
    "iso:country":"US",
    "sg:address":"1009 W Villard St",
    "sg:city":"Dickinson",
    "sg:classifiers":[
        {
            "category":"Retail",
            "subcategory":"Auto Repair",
            "type":"Services"
        }
    ],
    "sg:phone":"+1 701 225 8622",
    "sg:postcode":"58601",
    "sg:province":"ND",
    "sg:tags":[
        "automotive",
        "general"
    ],
    "wof:name":"Jeffs Towing",
    "wof:placetype":"venue"
},
  "geometry": {"coordinates":[-102.80152,46.879018],"type":"Point"}
}