{
  "type": "Feature",
  "properties": {
    "iso:country":"US",
    "sg:address":"1010 N 5th St",
    "sg:city":"Grand Forks",
    "sg:classifiers":[
        {
            "category":"Retail",
            "subcategory":"Laundry & Dry Cleaning",
            "type":"Services"
        }
    ],
    "sg:phone":"+1 701 775 5336",
    "sg:postcode":"58203",
    "sg:province":"ND",
    "sg:tags":[
        "drycleaning",
        "plant",
        "linen",
        "power",
        "supply"
    ],
    "wof:name":"C & R Cleaners & Laundry",
    "wof:placetype":"venue"
},
  "geometry": {"coordinates":[-97.046605,47.931732],"type":"Point"}
}