{
  "type": "Feature",
  "properties": {
    "addr:full":"351 E Main St Valley City ND 58072",
    "addr:housenumber":"351",
    "addr:postcode":"58072",
    "addr:street":"E Main St",
    "iso:country":"US",
    "sg:address":"351 E Main St",
    "sg:city":"Valley City",
    "sg:classifiers":[
        {
            "category":"Home & Garden",
            "subcategory":"Carpets & Floor Coverings",
            "type":"Retail Goods"
        }
    ],
    "sg:phone":"+1 701 845 2419",
    "sg:postcode":"58072",
    "sg:province":"ND",
    "sg:tags":[
        "installs",
        "wallpaper",
        "flooring",
        "cabinet"
    ],
    "sg:website":"www.valleyflooring.com",
    "wof:name":"Valley Flooring",
    "wof:placetype":"venue"
},
  "geometry": {"coordinates":[-97.99947400000001,46.923502],"type":"Point"}
}