{
  "type": "Feature",
  "properties": {
    "iso:country":"US",
    "sg:address":"1011 N 11th St",
    "sg:city":"Bismarck",
    "sg:classifiers":[
        {
            "category":"Health Services",
            "subcategory":"Clinic",
            "type":"Services"
        }
    ],
    "sg:phone":"+1 701 258 0669",
    "sg:postcode":"58501",
    "sg:province":"ND",
    "wof:name":"AIA-Farmers Health Alliance",
    "wof:placetype":"venue"
},
  "geometry": {"coordinates":[-100.775221,46.816337],"type":"Point"}
}