{
  "type": "Feature",
  "properties": {
    "iso:country":"US",
    "sg:address":"1706 43rd Ave SE",
    "sg:city":"Mandan",
    "sg:classifiers":[
        {
            "category":"Building & Trades",
            "subcategory":"Electrical",
            "type":"Services"
        }
    ],
    "sg:phone":"+1 701 222 0009",
    "sg:postcode":"58554",
    "sg:province":"ND",
    "sg:tags":[
        "electric",
        "contractor"
    ],
    "wof:name":"Northern Lights Electric",
    "wof:placetype":"venue"
},
  "geometry": {"coordinates":[-100.834772,46.80966],"type":"Point"}
}