{
  "type": "Feature",
  "properties": {
    "iso:country":"US",
    "sg:address":"12792 20th St S W",
    "sg:city":"Fairfield",
    "sg:classifiers":[
        {
            "category":"Freight",
            "type":"Transportation"
        }
    ],
    "sg:phone":"+1 701 575 8609",
    "sg:postcode":"58627",
    "sg:province":"ND",
    "sg:tags":[
        "operator",
        "local",
        "trucking"
    ],
    "wof:name":"G L Trucking & Rental Inc",
    "wof:placetype":"venue"
},
  "geometry": {"coordinates":[-103.16868599999999,47.125071],"type":"Point"}
}