{
  "type": "Feature",
  "properties": {
    "iso:country":"US",
    "sg:address":"413 E Ave D",
    "sg:city":"Bismarck",
    "sg:classifiers":[
        {
            "category":"Education",
            "subcategory":"School",
            "type":"Public Place"
        }
    ],
    "sg:phone":"+1 701 224 9070",
    "sg:postcode":"58501",
    "sg:province":"ND",
    "sg:website":"www.lutherschools.org",
    "wof:name":"Martin Luther Elementary Schl",
    "wof:placetype":"venue"
},
  "geometry": {"coordinates":[-100.78536800000001,46.812663],"type":"Point"}
}