{
  "type": "Feature",
  "properties": {
    "addr:full":"1923 11th Ave N Grand Forks ND 58203",
    "addr:housenumber":"1923",
    "addr:postcode":"58203",
    "addr:street":"11Th Ave N",
    "iso:country":"US",
    "sg:address":"1923 11th Ave N",
    "sg:city":"Grand Forks",
    "sg:classifiers":[
        {
            "category":"Freight",
            "type":"Transportation"
        }
    ],
    "sg:phone":"+1 701 775 6518",
    "sg:postcode":"58203",
    "sg:province":"ND",
    "sg:tags":[
        "operator",
        "delivery",
        "local",
        "trucking"
    ],
    "wof:name":"Discount Delivery Service",
    "wof:placetype":"venue"
},
  "geometry": {"coordinates":[-97.052722,47.930126],"type":"Point"}
}