{
  "type": "Feature",
  "properties": {
    "addr:full":"4000 E Divide Ave Bismarck ND 58501",
    "addr:housenumber":"4000",
    "addr:postcode":"58501",
    "addr:street":"E Divide Ave",
    "iso:country":"US",
    "sg:address":"4000 E Divide Ave",
    "sg:city":"Bismarck",
    "sg:classifiers":[
        {
            "category":"Restaurant",
            "type":"Food & Drink"
        }
    ],
    "sg:menulink":"http://www.allmenus.com/nd/bismarck/194614-mcdonalds/menu/",
    "sg:phone":"+1 701 355 4429",
    "sg:postcode":"58501",
    "sg:province":"ND",
    "sg:tags":[
        "burger",
        "american"
    ],
    "wof:name":"McDonald's",
    "wof:placetype":"venue"
},
  "geometry": {"coordinates":[-100.732851,46.828864],"type":"Point"}
}