{
  "type": "Feature",
  "properties": {
    "addr:full":"2219 Main Ave Fargo ND 58103",
    "addr:housenumber":"2219",
    "addr:postcode":"58103",
    "addr:street":"Main Ave",
    "iso:country":"US",
    "sg:address":"2219 Main Ave",
    "sg:city":"Fargo",
    "sg:classifiers":[
        {
            "category":"Autos & Motor Vehicles",
            "subcategory":"Auto Supplies",
            "type":"Retail Goods"
        }
    ],
    "sg:phone":"+1 701 298 0034",
    "sg:postcode":"58103",
    "sg:province":"ND",
    "sg:tags":[
        "automobile",
        "stereo",
        "radio"
    ],
    "wof:name":"Advantaged Autoworks",
    "wof:placetype":"venue"
},
  "geometry": {"coordinates":[-96.816121,46.875963],"type":"Point"}
}