{
  "type": "Feature",
  "properties": {
    "iso:country":"US",
    "sg:address":"234 New York St",
    "sg:city":"Bismarck",
    "sg:classifiers":[
        {
            "category":"Education",
            "subcategory":"Dance Studio",
            "type":"Public Place"
        }
    ],
    "sg:phone":"+1 701 223 2574",
    "sg:postcode":"58504",
    "sg:province":"ND",
    "wof:name":"Spotted Eagle Holy Otter Woman",
    "wof:placetype":"venue"
},
  "geometry": {"coordinates":[-100.76702,46.792727],"type":"Point"}
}