{
  "type": "Feature",
  "properties": {
    "addr:full":"8211 62nd St SE Edgeley ND 58433",
    "addr:housenumber":"8211",
    "addr:postcode":"58433",
    "addr:street":"62Nd St Se",
    "iso:country":"US",
    "sg:address":"8211 62nd St SE",
    "sg:city":"Edgeley",
    "sg:classifiers":[
        {
            "category":"Farming",
            "subcategory":"Farm",
            "type":"Manufacturing & Wholesale Goods"
        }
    ],
    "sg:phone":"+1 701 493 2881",
    "sg:postcode":"58433",
    "sg:province":"ND",
    "wof:name":"Darryl Edwards Shop & Mobile",
    "wof:placetype":"venue"
},
  "geometry": {"coordinates":[-98.70372500000001,46.514916],"type":"Point"}
}