{
  "type": "Feature",
  "properties": {
    "iso:country":"US",
    "sg:address":"1100 19th Ave N",
    "sg:city":"Fargo",
    "sg:classifiers":[
        {
            "category":"Professional",
            "subcategory":"Advertising",
            "type":"Services"
        }
    ],
    "sg:phone":"+1 701 235 9505",
    "sg:postcode":"58102",
    "sg:province":"ND",
    "sg:tags":[
        "mailing",
        "shipping"
    ],
    "wof:name":"UPS Store",
    "wof:placetype":"venue"
},
  "geometry": {"coordinates":[-96.795616,46.90471],"type":"Point"}
}