{
  "type": "Feature",
  "properties": {
    "addr:full":"4333 167th Ave SE Horace ND 58047",
    "addr:housenumber":"4333",
    "addr:postcode":"58047",
    "addr:street":"167Th Ave Se",
    "iso:country":"US",
    "sg:address":"4333 167th Ave SE",
    "sg:city":"Horace",
    "sg:classifiers":[
        {
            "category":"Recreation",
            "type":"Entertainment"
        }
    ],
    "sg:phone":"+1 701 282 3805",
    "sg:postcode":"58047",
    "sg:province":"ND",
    "sg:tags":[
        "range",
        "trap",
        "skeet"
    ],
    "wof:name":"Shooting Park",
    "wof:placetype":"venue"
},
  "geometry": {"coordinates":[-96.968559,46.78527],"type":"Point"}
}