{
  "type": "Feature",
  "properties": {
    "iso:country":"US",
    "sg:address":"1289 22nd St NE",
    "sg:city":"Emerado",
    "sg:classifiers":[
        {
            "category":"Farming",
            "subcategory":"Farm",
            "type":"Manufacturing & Wholesale Goods"
        }
    ],
    "sg:phone":"+1 701 594 6355",
    "sg:postcode":"58228",
    "sg:province":"ND",
    "sg:tags":[
        "crop",
        "general"
    ],
    "wof:name":"Sauer Farms LP",
    "wof:placetype":"venue"
},
  "geometry": {"coordinates":[-97.303766,47.860434],"type":"Point"}
}