{
  "type": "Feature",
  "properties": {
    "iso:country":"US",
    "sg:address":"7 8th St S",
    "sg:city":"Fargo",
    "sg:classifiers":[
        {
            "category":"Shopping",
            "subcategory":"Music",
            "type":"Retail Goods"
        }
    ],
    "sg:phone":"+1 701 478 4142",
    "sg:postcode":"58103",
    "sg:province":"ND",
    "sg:tags":[
        "compact",
        "record",
        "disc",
        "tape"
    ],
    "sg:website":"www.rcgmedia.com",
    "wof:name":"RCGMEDIA.COM",
    "wof:placetype":"venue"
},
  "geometry": {"coordinates":[-96.791178,46.874112],"type":"Point"}
}