{
  "type": "Feature",
  "properties": {
    "iso:country":"US",
    "sg:address":"2301 25th St SW",
    "sg:city":"Fargo",
    "sg:classifiers":[
        {
            "category":"Manufacturing",
            "subcategory":"Tools & Machinery",
            "type":"Manufacturing & Wholesale Goods"
        },
        {
            "category":"Health Services",
            "subcategory":"Doctor",
            "type":"Services"
        }
    ],
    "sg:phone":"+1 701 234 0112",
    "sg:postcode":"58103",
    "sg:province":"ND",
    "sg:tags":[
        "analytical",
        "instrument",
        "clinic",
        "mfg"
    ],
    "wof:name":"Institute Of Diagnostic Imgng",
    "wof:placetype":"venue"
},
  "geometry": {"coordinates":[-96.81977999999999,46.843415],"type":"Point"}
}