{
  "type": "Feature",
  "properties": {
    "addr:full":"12217 Co Rd 7 Edinburg ND 58227",
    "addr:housenumber":"12217;7",
    "addr:postcode":"58227",
    "addr:street":"Co Rd",
    "iso:country":"US",
    "sg:address":"12217 Co Rd 7",
    "sg:city":"Edinburg",
    "sg:classifiers":[
        {
            "category":"Farming",
            "subcategory":"Farm",
            "type":"Manufacturing & Wholesale Goods"
        }
    ],
    "sg:phone":"+1 701 993 8517",
    "sg:postcode":"58227",
    "sg:province":"ND",
    "sg:tags":[
        "crop",
        "general"
    ],
    "wof:name":"Thorson Farms",
    "wof:placetype":"venue"
},
  "geometry": {"coordinates":[-98.012699,48.512211],"type":"Point"}
}