{
  "type": "Feature",
  "properties": {
    "iso:country":"US",
    "sg:address":"810 Co Rd 21",
    "sg:city":"Beulah",
    "sg:classifiers":[
        {
            "category":"Professional",
            "subcategory":"Business Services",
            "type":"Services"
        }
    ],
    "sg:phone":"+1 701 873 2119",
    "sg:postcode":"58523",
    "sg:province":"ND",
    "sg:tags":[
        "water",
        "treatment"
    ],
    "wof:name":"Midwest Water Solutions",
    "wof:placetype":"venue"
},
  "geometry": {"coordinates":[-101.76997799999999,47.270211],"type":"Point"}
}