{
  "type": "Feature",
  "properties": {
    "iso:country":"US",
    "sg:address":"11291 39th St SW",
    "sg:city":"Dickinson",
    "sg:classifiers":[
        {
            "category":"Communications",
            "subcategory":"Radio Station",
            "type":"Services"
        }
    ],
    "sg:phone":"+1 701 483 1876",
    "sg:postcode":"58601",
    "sg:province":"ND",
    "sg:tags":[
        "company",
        "broadcasting"
    ],
    "sg:website":"www.z92fm.net",
    "wof:name":"Clear Channel Communications",
    "wof:placetype":"venue"
},
  "geometry": {"coordinates":[-102.82853900000001,46.846967],"type":"Point"}
}