{
  "type": "Feature",
  "properties": {
    "addr:full":"4860 State Hwy 15 Fessenden ND 58438",
    "addr:housenumber":"4860",
    "addr:postcode":"58438",
    "addr:street":"State Hwy 15 Fessenden",
    "iso:country":"US",
    "sg:address":"4860 State Hwy 15",
    "sg:city":"Fessenden",
    "sg:classifiers":[
        {
            "category":"Professional",
            "subcategory":"Computer Services",
            "type":"Services"
        }
    ],
    "sg:phone":"+1 701 547 2518",
    "sg:postcode":"58438",
    "sg:province":"ND",
    "sg:tags":[
        "datum"
    ],
    "wof:name":"Weston Rudel",
    "wof:placetype":"venue"
},
  "geometry": {"coordinates":[-99.501833,47.64545],"type":"Point"}
}