{
  "type": "Feature",
  "properties": {
    "iso:country":"US",
    "sg:address":"100 3rd St W",
    "sg:city":"Lemmon",
    "sg:classifiers":[
        {
            "category":"Professional",
            "type":"Services"
        }
    ],
    "sg:phone":"+1 605 374 5699",
    "sg:postcode":"57638",
    "sg:province":"ND",
    "sg:tags":[
        "establishment"
    ],
    "wof:name":"Lemmon Area Charitable & Ecnmc",
    "wof:placetype":"venue"
},
  "geometry": {"coordinates":[-102.16086,45.941931],"type":"Point"}
}