{
  "type": "Feature",
  "properties": {
    "addr:full":"11817 51st St NE Michigan ND 58259",
    "addr:housenumber":"11817",
    "addr:postcode":"nd 58259",
    "addr:street":"51St St Ne",
    "iso:country":"US",
    "sg:address":"11817 51st St NE",
    "sg:city":"Michigan",
    "sg:classifiers":[
        {
            "category":"Farming",
            "subcategory":"Livestock Farm",
            "type":"Manufacturing & Wholesale Goods"
        }
    ],
    "sg:phone":"+1 701 259 2428",
    "sg:postcode":"58259",
    "sg:province":"ND",
    "sg:tags":[
        "beef",
        "feedlot",
        "cattle"
    ],
    "wof:name":"Dwight Beck",
    "wof:placetype":"venue"
},
  "geometry": {"coordinates":[-98.067083,48.151427],"type":"Point"}
}