{
  "type": "Feature",
  "properties": {
    "iso:country":"US",
    "sg:address":"200 S Main St",
    "sg:city":"Hettinger",
    "sg:classifiers":[
        {
            "category":"Personal",
            "subcategory":"Beauty Salon",
            "type":"Services"
        }
    ],
    "sg:phone":"+1 701 567 2232",
    "sg:postcode":"58639",
    "sg:province":"ND",
    "wof:name":"Geri's Hair Shoppe",
    "wof:placetype":"venue"
},
  "geometry": {"coordinates":[-102.636887,45.999154],"type":"Point"}
}