{
  "type": "Feature",
  "properties": {
    "iso:country":"US",
    "sg:address":"2324 2nd Ave W",
    "sg:city":"Williston",
    "sg:classifiers":[
        {
            "category":"Travel",
            "subcategory":"Hotels & Motels",
            "type":"Entertainment"
        }
    ],
    "sg:phone":"+1 701 572 8371",
    "sg:postcode":"58801",
    "sg:province":"ND",
    "wof:name":"Super 8 Motel",
    "wof:placetype":"venue"
},
  "geometry": {"coordinates":[-103.62570100000001,48.16624],"type":"Point"}
}