{
  "type": "Feature",
  "properties": {
    "addr:full":"11168 60th St NE Lawton ND 58345",
    "addr:housenumber":"11168",
    "addr:postcode":"58345",
    "addr:street":"60Th St Ne",
    "iso:country":"US",
    "sg:address":"11168 60th St NE",
    "sg:city":"Lawton",
    "sg:classifiers":[
        {
            "category":"Farming",
            "subcategory":"Farm",
            "type":"Manufacturing & Wholesale Goods"
        }
    ],
    "sg:phone":"+1 701 655 3598",
    "sg:postcode":"58345",
    "sg:province":"ND",
    "sg:tags":[
        "crop",
        "general"
    ],
    "wof:name":"Lane Bina",
    "wof:placetype":"venue"
},
  "geometry": {"coordinates":[-98.212585,48.281931],"type":"Point"}
}