{
  "type": "Feature",
  "properties": {
    "iso:country":"US",
    "sg:address":"1121 7th Ave NE",
    "sg:city":"Mc Clusky",
    "sg:phone":"+1 701 363 2958",
    "sg:postcode":"58463",
    "sg:province":"ND",
    "sg:tags":[
        "farm",
        "grain",
        "cash"
    ],
    "wof:name":"Timothy Schindler",
    "wof:placetype":"venue"
},
  "geometry": {"coordinates":[-100.39480500000001,47.586967],"type":"Point"}
}