{
  "type": "Feature",
  "properties": {
    "iso:country":"US",
    "sg:address":"1738 35th St S",
    "sg:city":"Fargo",
    "sg:classifiers":[
        {
            "category":"Professional",
            "subcategory":"Business Services",
            "type":"Services"
        }
    ],
    "sg:phone":"+1 701 232 3950",
    "sg:postcode":"58103",
    "sg:province":"ND",
    "sg:tags":[
        "interior",
        "consultant",
        "designer",
        "design",
        "decorator"
    ],
    "wof:name":"Design Unlimited",
    "wof:placetype":"venue"
},
  "geometry": {"coordinates":[-96.838363,46.853584],"type":"Point"}
}