{
  "type": "Feature",
  "properties": {
    "iso:country":"US",
    "sg:address":"9875 136th Ave NW",
    "sg:city":"Fortuna",
    "sg:classifiers":[
        {
            "category":"Building & Trades",
            "subcategory":"Cleaning & Sanitation",
            "type":"Services"
        }
    ],
    "sg:phone":"+1 701 834 2441",
    "sg:postcode":"58844",
    "sg:province":"ND",
    "sg:tags":[
        "janitorial"
    ],
    "wof:name":"Deb L Selle",
    "wof:placetype":"venue"
},
  "geometry": {"coordinates":[-103.61867700000001,48.839523],"type":"Point"}
}