{
  "type": "Feature",
  "properties": {
    "iso:country":"US",
    "sg:address":"1001 S 22nd St",
    "sg:city":"Bismarck",
    "sg:classifiers":[
        {
            "category":"Education",
            "subcategory":"Special Training",
            "type":"Public Place"
        }
    ],
    "sg:phone":"+1 701 223 5609",
    "sg:postcode":"58504",
    "sg:province":"ND",
    "wof:name":"Abate Of Nd",
    "wof:placetype":"venue"
},
  "geometry": {"coordinates":[-100.757604,46.793323],"type":"Point"}
}