{
  "type": "Feature",
  "properties": {
    "iso:country":"US",
    "sg:address":"4656 Amber Valley Pkwy S",
    "sg:city":"Fargo",
    "sg:classifiers":[
        {
            "category":"Insurance",
            "subcategory":"Hazard Insurance",
            "type":"Services"
        }
    ],
    "sg:phone":"+1 701 232 4039",
    "sg:postcode":"58104",
    "sg:province":"ND",
    "sg:tags":[
        "profit",
        "sharing",
        "pension",
        "plan"
    ],
    "wof:name":"Dakota Capital Retention Corp",
    "wof:placetype":"venue"
},
  "geometry": {"coordinates":[-96.87111899999999,46.840987],"type":"Point"}
}