{
  "type": "Feature",
  "properties": {
    "addr:full":"302 1st St S Carrington ND 58421",
    "addr:housenumber":"302",
    "addr:postcode":"58421",
    "addr:street":"1St St S",
    "iso:country":"US",
    "sg:address":"302 1st St S",
    "sg:city":"Carrington",
    "sg:classifiers":[
        {
            "category":"Building & Trades",
            "subcategory":"Construction",
            "type":"Services"
        }
    ],
    "sg:phone":"+1 701 652 3909",
    "sg:postcode":"58421",
    "sg:province":"ND",
    "sg:tags":[
        "house"
    ],
    "wof:name":"Bronaugh Construction",
    "wof:placetype":"venue"
},
  "geometry": {"coordinates":[-99.115903,47.448483],"type":"Point"}
}