{
  "type": "Feature",
  "properties": {
    "iso:country":"US",
    "sg:address":"3142 71st St SE",
    "sg:city":"Napoleon",
    "sg:classifiers":[
        {
            "category":"Farming",
            "subcategory":"Livestock Farm",
            "type":"Manufacturing & Wholesale Goods"
        }
    ],
    "sg:phone":"+1 701 754 2464",
    "sg:postcode":"58561",
    "sg:province":"ND",
    "sg:tags":[
        "beef",
        "feedlot",
        "cattle"
    ],
    "wof:name":"Darrell Bitz",
    "wof:placetype":"venue"
},
  "geometry": {"coordinates":[-99.760491,46.385329],"type":"Point"}
}