{
  "type": "Feature",
  "properties": {
    "iso:country":"US",
    "sg:address":"314 Cambridge St",
    "sg:city":"Grand Forks",
    "sg:classifiers":[
        {
            "category":"Professional",
            "subcategory":"Business Services",
            "type":"Services"
        }
    ],
    "sg:phone":"+1 701 777 3664",
    "sg:postcode":"58203",
    "sg:province":"ND",
    "sg:tags":[
        "arbitration"
    ],
    "wof:name":"Conflict Resolution CTR-Und",
    "wof:placetype":"venue"
},
  "geometry": {"coordinates":[-97.070571,47.924153],"type":"Point"}
}