{
  "type": "Feature",
  "properties": {
    "addr:full":"3301 Co Rd 19 S Minot ND 58701",
    "addr:housenumber":"3301;19",
    "addr:postcode":"58701",
    "addr:street":"Co Rd;S Minot",
    "iso:country":"US",
    "sg:address":"3301 Co Rd 19 S",
    "sg:city":"Minot",
    "sg:classifiers":[
        {
            "category":"Wholesale",
            "subcategory":"Groceries",
            "type":"Manufacturing & Wholesale Goods"
        }
    ],
    "sg:phone":"+1 701 852 1369",
    "sg:postcode":"58701",
    "sg:province":"ND",
    "sg:tags":[
        "confectionery"
    ],
    "wof:name":"R J Trucking",
    "wof:placetype":"venue"
},
  "geometry": {"coordinates":[-101.247354,48.207484],"type":"Point"}
}