{
  "type": "Feature",
  "properties": {
    "addr:full":"41600 41st St NE Wilton ND 58579",
    "addr:housenumber":"41600",
    "addr:postcode":"58579",
    "addr:street":"41St St Ne",
    "iso:country":"US",
    "sg:address":"41600 41st St NE",
    "sg:city":"Wilton",
    "sg:classifiers":[
        {
            "category":"Farming",
            "subcategory":"Livestock Farm",
            "type":"Manufacturing & Wholesale Goods"
        }
    ],
    "sg:phone":"+1 701 734 6732",
    "sg:postcode":"58579",
    "sg:province":"ND",
    "sg:tags":[
        "wheat",
        "beef",
        "feedlot",
        "cattle"
    ],
    "wof:name":"Melvin Backman Farm",
    "wof:placetype":"venue"
},
  "geometry": {"coordinates":[-100.728353,47.264367],"type":"Point"}
}