{
  "type": "Feature",
  "properties": {
    "addr:full":"166 Bryan St Mc Henry ND 58466",
    "addr:housenumber":"166",
    "addr:postcode":"58466",
    "addr:street":"Bryan St Mc Henry",
    "iso:country":"US",
    "sg:address":"166 Bryan St",
    "sg:city":"Mc Henry",
    "sg:classifiers":[
        {
            "category":"Wholesale",
            "subcategory":"Petroleum",
            "type":"Manufacturing & Wholesale Goods"
        }
    ],
    "sg:phone":"+1 701 785 2600",
    "sg:postcode":"58466",
    "sg:province":"ND",
    "sg:tags":[
        "bulk",
        "station",
        "gasoline"
    ],
    "wof:name":"Briss Oil Company",
    "wof:placetype":"venue"
},
  "geometry": {"coordinates":[-98.334557,46.604405],"type":"Point"}
}