{
  "type": "Feature",
  "properties": {
    "addr:full":"501 2nd St W Lemmon ND 57638",
    "addr:housenumber":"501",
    "addr:postcode":"57638",
    "addr:street":"2Nd St W Lemmon",
    "iso:country":"US",
    "sg:address":"501 2nd St W",
    "sg:city":"Lemmon",
    "sg:classifiers":[
        {
            "category":"Building & Trades",
            "subcategory":"Electrical",
            "type":"Services"
        }
    ],
    "sg:phone":"+1 605 374 3771",
    "sg:postcode":"57638",
    "sg:province":"ND",
    "sg:tags":[
        "electrical",
        "household",
        "appliance",
        "electric",
        "contractor"
    ],
    "wof:name":"Dons Electric Inc",
    "wof:placetype":"venue"
},
  "geometry": {"coordinates":[-102.166856,45.943099],"type":"Point"}
}