{
  "type": "Feature",
  "properties": {
    "addr:full":"4501 15th Ave S Ste 102 Fargo ND 58103",
    "addr:housenumber":"4501",
    "addr:postcode":"58103",
    "addr:street":"15Th Ave S Ste 102",
    "iso:country":"US",
    "sg:address":"4501 15th Ave S Ste 102",
    "sg:city":"Fargo",
    "sg:classifiers":[
        {
            "category":"Professional",
            "subcategory":"Employment Agencies",
            "type":"Services"
        }
    ],
    "sg:phone":"+1 701 281 4850",
    "sg:postcode":"58103",
    "sg:province":"ND",
    "sg:tags":[
        "opportunity",
        "contractor"
    ],
    "sg:website":"http://www.kellyservices.com",
    "wof:name":"Kelly Services",
    "wof:placetype":"venue"
},
  "geometry": {"coordinates":[-96.86200700000001,46.858311],"type":"Point"}
}