{
  "type": "Feature",
  "properties": {
    "addr:full":"1478 14th St N Wahpeton ND 58075",
    "addr:housenumber":"1478",
    "addr:postcode":"58075",
    "addr:street":"14Th St N",
    "iso:country":"US",
    "sg:address":"1478 14th St N",
    "sg:city":"Wahpeton",
    "sg:classifiers":[
        {
            "category":"Home & Garden",
            "subcategory":"Furniture",
            "type":"Retail Goods"
        }
    ],
    "sg:phone":"+1 701 642 2100",
    "sg:postcode":"58075",
    "sg:province":"ND",
    "sg:tags":[
        "store"
    ],
    "wof:name":"Dakota Cabinetry Inc",
    "wof:placetype":"venue"
},
  "geometry": {"coordinates":[-96.620893,46.281087],"type":"Point"}
}