{
  "type": "Feature",
  "properties": {
    "iso:country":"US",
    "sg:address":"205 11th St E",
    "sg:city":"Williston",
    "sg:classifiers":[
        {
            "category":"Social Services",
            "type":"Services"
        }
    ],
    "sg:phone":"+1 701 572 7109",
    "sg:postcode":"58801",
    "sg:province":"ND",
    "sg:tags":[
        "organization"
    ],
    "wof:name":"Vickers Foundation",
    "wof:placetype":"venue"
},
  "geometry": {"coordinates":[-103.62006,48.154305],"type":"Point"}
}