{
  "type": "Feature",
  "properties": {
    "iso:country":"US",
    "sg:address":"3 4th St E",
    "sg:city":"Williston",
    "sg:classifiers":[
        {
            "category":"Professional",
            "subcategory":"Computer Services",
            "type":"Services"
        }
    ],
    "sg:phone":"+1 701 770 3556",
    "sg:postcode":"58801",
    "sg:province":"ND",
    "sg:tags":[
        "repair"
    ],
    "wof:name":"Kent's Computer Loft",
    "wof:placetype":"venue"
},
  "geometry": {"coordinates":[-103.621973,48.147632],"type":"Point"}
}