{
  "type": "Feature",
  "properties": {
    "addr:full":"101 Front St Forest River ND 58233",
    "addr:housenumber":"101",
    "addr:postcode":"58233",
    "addr:street":"Front St",
    "iso:country":"US",
    "sg:address":"101 Front St",
    "sg:city":"Forest River",
    "sg:classifiers":[
        {
            "category":"Manufacturing",
            "subcategory":"Printing",
            "type":"Manufacturing & Wholesale Goods"
        }
    ],
    "sg:phone":"+1 701 248 2410",
    "sg:postcode":"58233",
    "sg:province":"ND",
    "sg:tags":[
        "newspaper"
    ],
    "wof:name":"Dakota Shopper Inc",
    "wof:placetype":"venue"
},
  "geometry": {"coordinates":[-97.468915,48.21583],"type":"Point"}
}