{
  "type": "Feature",
  "properties": {
    "iso:country":"US",
    "sg:address":"418 3rd Ave W",
    "sg:city":"Richardton",
    "sg:classifiers":[
        {
            "category":"Education",
            "subcategory":"Library",
            "type":"Public Place"
        }
    ],
    "sg:phone":"+1 701 974 3315",
    "sg:postcode":"58652",
    "sg:province":"ND",
    "sg:tags":[
        "special",
        "interest"
    ],
    "sg:website":"www.assumptionabbey.com",
    "wof:name":"Assumption Abbey Library",
    "wof:placetype":"venue"
},
  "geometry": {"coordinates":[-102.319896,46.888353],"type":"Point"}
}