{
  "type": "Feature",
  "properties": {
    "addr:full":"305 1st Ave NE Mandan ND 58554",
    "addr:housenumber":"305",
    "addr:postcode":"58554",
    "addr:street":"1St Ave Ne",
    "iso:country":"US",
    "sg:address":"305 1st Ave NE",
    "sg:city":"Mandan",
    "sg:classifiers":[
        {
            "category":"Building & Trades",
            "subcategory":"Construction",
            "type":"Services"
        }
    ],
    "sg:phone":"+1 701 667 2943",
    "sg:postcode":"58554",
    "sg:province":"ND",
    "sg:tags":[
        "hanging",
        "contractor"
    ],
    "wof:name":"Dan and Dave Dual",
    "wof:placetype":"venue"
},
  "geometry": {"coordinates":[-100.8892,46.829696],"type":"Point"}
}