{
  "type": "Feature",
  "properties": {
    "iso:country":"US",
    "sg:address":"2400 E Front Ave",
    "sg:city":"Bismarck",
    "sg:classifiers":[
        {
            "category":"Wholesale",
            "subcategory":"Electrical",
            "type":"Manufacturing & Wholesale Goods"
        }
    ],
    "sg:phone":"+1 701 258 8899",
    "sg:postcode":"58504",
    "sg:province":"ND",
    "sg:tags":[
        "control"
    ],
    "sg:website":"www.fusionit.us",
    "wof:name":"Fusion Integrated Tech LLC",
    "wof:placetype":"venue"
},
  "geometry": {"coordinates":[-100.75551400000001,46.802487],"type":"Point"}
}