{
  "type": "Feature",
  "properties": {
    "addr:full":"7 1st St S New Rockford ND 58356",
    "addr:housenumber":"7",
    "addr:postcode":"58356",
    "addr:street":"1St St S",
    "iso:country":"US",
    "sg:address":"7 1st St S",
    "sg:city":"New Rockford",
    "sg:classifiers":[
        {
            "category":"Government",
            "subcategory":"Office",
            "type":"Public Place"
        }
    ],
    "sg:phone":"+1 701 947 2435",
    "sg:postcode":"58356",
    "sg:province":"ND",
    "wof:name":"Us Farm Svc Agency",
    "wof:placetype":"venue"
},
  "geometry": {"coordinates":[-99.12554,47.679165],"type":"Point"}
}