{
  "type": "Feature",
  "properties": {
    "iso:country":"US",
    "sg:address":"118 Broadway",
    "sg:city":"Fargo",
    "sg:classifiers":[
        {
            "category":"Personal",
            "subcategory":"Beauty Salon",
            "type":"Services"
        }
    ],
    "sg:phone":"+1 701 356 9955",
    "sg:postcode":"58102",
    "sg:province":"ND",
    "wof:name":"Salon Why",
    "wof:placetype":"venue"
},
  "geometry": {"coordinates":[-96.787761,46.877819],"type":"Point"}
}