{
  "type": "Feature",
  "properties": {
    "addr:full":"1024 10th St Langdon ND 58249",
    "addr:housenumber":"1024",
    "addr:postcode":"58249",
    "addr:street":"10Th St",
    "iso:country":"US",
    "sg:address":"1024 10th St",
    "sg:city":"Langdon",
    "sg:classifiers":[
        {
            "category":"Freight",
            "type":"Transportation"
        }
    ],
    "sg:phone":"+1 701 256 2288",
    "sg:postcode":"58249",
    "sg:province":"ND",
    "sg:tags":[
        "operator",
        "local",
        "trucking"
    ],
    "wof:name":"Klm Trucking",
    "wof:placetype":"venue"
},
  "geometry": {"coordinates":[-98.37918000000001,48.763121],"type":"Point"}
}