{
  "type": "Feature",
  "properties": {
    "iso:country":"US",
    "sg:address":"501 Lohstreter Rd",
    "sg:city":"Mandan",
    "sg:classifiers":[
        {
            "category":"Wholesale",
            "subcategory":"Stationery",
            "type":"Manufacturing & Wholesale Goods"
        }
    ],
    "sg:phone":"+1 701 663 1795",
    "sg:postcode":"58554",
    "sg:province":"ND",
    "sg:tags":[
        "supply"
    ],
    "wof:name":"Native Specialties and Forms",
    "wof:placetype":"venue"
},
  "geometry": {"coordinates":[-100.912654,46.829971],"type":"Point"}
}