{
  "type": "Feature",
  "properties": {
    "iso:country":"US",
    "sg:address":"323 Central Ave N",
    "sg:city":"Valley City",
    "sg:classifiers":[
        {
            "category":"Health Services",
            "subcategory":"Optometrist",
            "type":"Services"
        }
    ],
    "sg:phone":"+1 701 845 2572",
    "sg:postcode":"58072",
    "sg:province":"ND",
    "wof:name":"Vista Optical",
    "wof:placetype":"venue"
},
  "geometry": {"coordinates":[-98.00321099999999,46.926061],"type":"Point"}
}