{
  "type": "Feature",
  "properties": {
    "iso:country":"US",
    "sg:address":"604 2nd Ave NW",
    "sg:city":"Ashley",
    "sg:classifiers":[
        {
            "category":"Organizations",
            "subcategory":"Religious Organization",
            "type":"Services"
        }
    ],
    "sg:phone":"+1 701 288 3822",
    "sg:postcode":"58413",
    "sg:province":"ND",
    "sg:website":"www.gideons.org",
    "wof:name":"Gideons International",
    "wof:placetype":"venue"
},
  "geometry": {"coordinates":[-99.374701,46.038907],"type":"Point"}
}