{
  "type": "Feature",
  "properties": {
    "addr:full":"1406 2nd St NW Mandan ND 58554",
    "addr:housenumber":"1406",
    "addr:postcode":"58554",
    "addr:street":"2Nd St Nw",
    "iso:country":"US",
    "sg:address":"1406 2nd St NW",
    "sg:city":"Mandan",
    "sg:classifiers":[
        {
            "category":"Social Services",
            "type":"Services"
        }
    ],
    "sg:phone":"+1 701 663 2322",
    "sg:postcode":"58554",
    "sg:province":"ND",
    "sg:tags":[
        "organization",
        "welfare"
    ],
    "wof:name":"Southwest Key Program",
    "wof:placetype":"venue"
},
  "geometry": {"coordinates":[-100.911664,46.82695],"type":"Point"}
}