{
  "type": "Feature",
  "properties": {
    "addr:full":"619 Dakota Ave Wahpeton ND 58075",
    "addr:housenumber":"619",
    "addr:postcode":"58075",
    "addr:street":"Dakota Ave",
    "iso:country":"US",
    "sg:address":"619 Dakota Ave",
    "sg:city":"Wahpeton",
    "sg:classifiers":[
        {
            "category":"Cinema",
            "subcategory":"Movie Rental",
            "type":"Entertainment"
        }
    ],
    "sg:phone":"+1 701 642 6836",
    "sg:postcode":"58075",
    "sg:province":"ND",
    "sg:tags":[
        "video",
        "tape"
    ],
    "wof:name":"Video Action",
    "wof:placetype":"venue"
},
  "geometry": {"coordinates":[-96.609589,46.263863],"type":"Point"}
}