{
  "type": "Feature",
  "properties": {
    "addr:full":"1331 32nd Ave Fargo ND 58103",
    "addr:housenumber":"1331",
    "addr:postcode":"58103",
    "addr:street":"32Nd Ave",
    "iso:country":"US",
    "sg:address":"1331 32nd Ave",
    "sg:city":"Fargo",
    "sg:classifiers":[
        {
            "category":"Social Services",
            "type":"Services"
        }
    ],
    "sg:phone":"+1 701 298 6788",
    "sg:postcode":"58103",
    "sg:province":"ND",
    "sg:tags":[
        "counselor",
        "marriage",
        "family"
    ],
    "wof:name":"Dawn Groslie Counseling",
    "wof:placetype":"venue"
},
  "geometry": {"coordinates":[-96.80162300000001,46.832817],"type":"Point"}
}