{
  "type": "Feature",
  "properties": {
    "addr:full":"207 12th St W Bottineau ND 58318",
    "addr:housenumber":"207",
    "addr:postcode":"58318",
    "addr:street":"12Th St W Bottineau",
    "iso:country":"US",
    "sg:address":"207 12th St W",
    "sg:city":"Bottineau",
    "sg:classifiers":[
        {
            "category":"Retail",
            "subcategory":"Auto Repair",
            "type":"Services"
        }
    ],
    "sg:phone":"+1 701 228 2993",
    "sg:postcode":"58318",
    "sg:province":"ND",
    "sg:tags":[
        "general"
    ],
    "wof:name":"Macs Service",
    "wof:placetype":"venue"
},
  "geometry": {"coordinates":[-100.450557,48.819799],"type":"Point"}
}