{
  "type": "Feature",
  "properties": {
    "iso:country":"US",
    "sg:address":"204 W Main St",
    "sg:city":"Ashley",
    "sg:classifiers":[
        {
            "category":"Banks & Credit Unions",
            "subcategory":"Financial Services",
            "type":"Services"
        }
    ],
    "sg:phone":"+1 701 288 3491",
    "sg:postcode":"58413",
    "sg:province":"ND",
    "sg:tags":[
        "company",
        "holding"
    ],
    "sg:website":"www.makeitmcb.com",
    "wof:name":"Mc Intosh County Bank Holding",
    "wof:placetype":"venue"
},
  "geometry": {"coordinates":[-99.37574600000001,46.034553],"type":"Point"}
}