{
  "type": "Feature",
  "properties": {
    "iso:country":"US",
    "sg:address":"1119 N 42nd St",
    "sg:city":"Grand Forks",
    "sg:classifiers":[
        {
            "category":"Shopping",
            "subcategory":"Used Merchandise",
            "type":"Retail Goods"
        }
    ],
    "sg:phone":"+1 701 787 0979",
    "sg:postcode":"58203",
    "sg:province":"ND",
    "wof:name":"Cash Man",
    "wof:placetype":"venue"
},
  "geometry": {"coordinates":[-97.088189,47.926465],"type":"Point"}
}