{
  "type": "Feature",
  "properties": {
    "iso:country":"US",
    "sg:address":"8054 149th Ave NW",
    "sg:city":"Grenora",
    "sg:classifiers":[
        {
            "category":"Farming",
            "subcategory":"Livestock Farm",
            "type":"Manufacturing & Wholesale Goods"
        }
    ],
    "sg:phone":"+1 701 694 6805",
    "sg:postcode":"58845",
    "sg:province":"ND",
    "sg:tags":[
        "beef",
        "feedlot",
        "cattle"
    ],
    "wof:name":"Lewis Larson",
    "wof:placetype":"venue"
},
  "geometry": {"coordinates":[-103.906868,48.610318],"type":"Point"}
}