{
  "type": "Feature",
  "properties": {
    "iso:country":"US",
    "sg:address":"825 Oak St W",
    "sg:city":"West Fargo",
    "sg:classifiers":[
        {
            "category":"Manufacturing",
            "subcategory":"Rubber & Plastics",
            "type":"Manufacturing & Wholesale Goods"
        }
    ],
    "sg:phone":"+1 701 277 3090",
    "sg:postcode":"58078",
    "sg:province":"ND",
    "sg:tags":[
        "hair",
        "mfg",
        "accessory"
    ],
    "wof:name":"Briannes Beauties",
    "wof:placetype":"venue"
},
  "geometry": {"coordinates":[-96.906537,46.866972],"type":"Point"}
}