{
  "type": "Feature",
  "properties": {
    "iso:country":"US",
    "sg:address":"408 N Main St",
    "sg:city":"Carson",
    "sg:classifiers":[
        {
            "category":"Autos & Motor Vehicles",
            "subcategory":"Auto Supplies",
            "type":"Retail Goods"
        }
    ],
    "sg:phone":"+1 701 622 3662",
    "sg:postcode":"58529",
    "sg:province":"ND",
    "sg:tags":[
        "automobile",
        "parts"
    ],
    "wof:name":"D & G Auto Parts",
    "wof:placetype":"venue"
},
  "geometry": {"coordinates":[-101.566148,46.422603],"type":"Point"}
}