{
  "type": "Feature",
  "properties": {
    "iso:country":"US",
    "sg:address":"605 12th Ave N",
    "sg:city":"Fargo",
    "sg:classifiers":[
        {
            "category":"Retail",
            "subcategory":"Portrait Studio",
            "type":"Services"
        }
    ],
    "sg:phone":"+1 701 235 6144",
    "sg:postcode":"58102",
    "sg:province":"ND",
    "sg:tags":[
        "photographer"
    ],
    "wof:name":"Assignment Photography & Video",
    "wof:placetype":"venue"
},
  "geometry": {"coordinates":[-96.789315,46.890432],"type":"Point"}
}