{
  "type": "Feature",
  "properties": {
    "iso:country":"US",
    "sg:address":"208 1st St S",
    "sg:city":"Ellendale",
    "sg:classifiers":[
        {
            "category":"Organizations",
            "subcategory":"Religious Organization",
            "type":"Services"
        }
    ],
    "sg:phone":"+1 701 349 3594",
    "sg:postcode":"58436",
    "sg:province":"ND",
    "sg:tags":[
        "church"
    ],
    "wof:name":"First Baptist Church",
    "wof:placetype":"venue"
},
  "geometry": {"coordinates":[-98.52584299999999,46.000435],"type":"Point"}
}