{
  "type": "Feature",
  "properties": {
    "iso:country":"US",
    "sg:address":"1016 S 12th St",
    "sg:city":"Bismarck",
    "sg:classifiers":[
        {
            "category":"Shopping",
            "subcategory":"Used Merchandise",
            "type":"Retail Goods"
        }
    ],
    "sg:phone":"+1 701 223 4988",
    "sg:postcode":"58504",
    "sg:province":"ND",
    "sg:tags":[
        "pawnbroker"
    ],
    "wof:name":"Bob's Pawn",
    "wof:placetype":"venue"
},
  "geometry": {"coordinates":[-100.77349100000001,46.794418],"type":"Point"}
}