{
  "type": "Feature",
  "properties": {
    "iso:country":"US",
    "sg:address":"1100 19th Ave N",
    "sg:city":"Fargo",
    "sg:classifiers":[
        {
            "category":"Building & Trades",
            "subcategory":"Electrical",
            "type":"Services"
        }
    ],
    "sg:phone":"+1 701 451 9056",
    "sg:postcode":"58102",
    "sg:province":"ND",
    "sg:tags":[
        "electrician"
    ],
    "wof:name":"Cobra Electric",
    "wof:placetype":"venue"
},
  "geometry": {"coordinates":[-96.795016,46.904808],"type":"Point"}
}