{
  "type": "Feature",
  "properties": {
    "iso:country":"US",
    "sg:address":"6162 Comet Ln",
    "sg:city":"Bismarck",
    "sg:classifiers":[
        {
            "category":"Retail",
            "subcategory":"Repair Shop",
            "type":"Services"
        }
    ],
    "sg:phone":"+1 701 222 2871",
    "sg:postcode":"58503",
    "sg:province":"ND",
    "sg:tags":[
        "repairing",
        "piano",
        "refinishing"
    ],
    "wof:name":"Blaine Lutz Piano Svc",
    "wof:placetype":"venue"
},
  "geometry": {"coordinates":[-100.69334600000001,46.88586],"type":"Point"}
}