{
  "type": "Feature",
  "properties": {
    "addr:full":"507 University Ave Williston ND 58801",
    "addr:housenumber":"507",
    "addr:postcode":"58801",
    "addr:street":"University Ave",
    "iso:country":"US",
    "sg:address":"507 University Ave",
    "sg:city":"Williston",
    "sg:classifiers":[
        {
            "category":"Social Services",
            "type":"Services"
        }
    ],
    "sg:phone":"+1 701 572 5863",
    "sg:postcode":"58801",
    "sg:province":"ND",
    "sg:tags":[
        "counseling"
    ],
    "wof:name":"Region I Parenting Coalition",
    "wof:placetype":"venue"
},
  "geometry": {"coordinates":[-103.614983,48.149156],"type":"Point"}
}