{
  "type": "Feature",
  "properties": {
    "iso:country":"US",
    "sg:address":"5099 38th St SE",
    "sg:city":"Medina",
    "sg:classifiers":[
        {
            "category":"Recreation",
            "type":"Entertainment"
        }
    ],
    "sg:phone":"+1 701 251 1954",
    "sg:postcode":"58467",
    "sg:province":"ND",
    "sg:tags":[
        "instruction",
        "gymnastic"
    ],
    "wof:name":"New Horizons Gymnastics",
    "wof:placetype":"venue"
},
  "geometry": {"coordinates":[-99.384074,46.863589],"type":"Point"}
}