{
  "type": "Feature",
  "properties": {
    "addr:full":"403 Dakota Ave Wahpeton ND 58075",
    "addr:housenumber":"403",
    "addr:postcode":"58075",
    "addr:street":"Dakota Ave",
    "iso:country":"US",
    "sg:address":"403 Dakota Ave",
    "sg:city":"Wahpeton",
    "sg:classifiers":[
        {
            "category":"Home & Garden",
            "subcategory":"Hardware",
            "type":"Retail Goods"
        }
    ],
    "sg:phone":"+1 701 642 5544",
    "sg:postcode":"58075",
    "sg:province":"ND",
    "wof:name":"Wahpeton True Value",
    "wof:placetype":"venue"
},
  "geometry": {"coordinates":[-96.606891,46.26385],"type":"Point"}
}