{
  "type": "Feature",
  "properties": {
    "addr:full":"514 3rd St NE Minot ND 58703",
    "addr:housenumber":"514",
    "addr:postcode":"58703",
    "addr:street":"3Rd St Ne",
    "iso:country":"US",
    "sg:address":"514 3rd St NE",
    "sg:city":"Minot",
    "sg:classifiers":[
        {
            "category":"Retail",
            "subcategory":"Self-service Laundry",
            "type":"Services"
        }
    ],
    "sg:phone":"+1 701 857 4021",
    "sg:postcode":"58703",
    "sg:province":"ND",
    "sg:tags":[
        "coin"
    ],
    "wof:name":"King Koin Launderette",
    "wof:placetype":"venue"
},
  "geometry": {"coordinates":[-101.28765199999999,48.241931],"type":"Point"}
}