{
  "type": "Feature",
  "properties": {
    "iso:country":"US",
    "sg:address":"424 S 3rd St",
    "sg:city":"Bismarck",
    "sg:classifiers":[
        {
            "category":"Shopping",
            "type":"Retail Goods"
        }
    ],
    "sg:phone":"+1 701 258 9570",
    "sg:postcode":"58504",
    "sg:province":"ND",
    "sg:tags":[
        "art",
        "gallery",
        "dealer"
    ],
    "wof:name":"Wild Things Gallery & Frame",
    "wof:placetype":"venue"
},
  "geometry": {"coordinates":[-100.787856,46.800363],"type":"Point"}
}