{
  "type": "Feature",
  "properties": {
    "addr:full":"320 Main St Milnor ND 58060",
    "addr:housenumber":"320",
    "addr:postcode":"58060",
    "addr:street":"Main St",
    "iso:country":"US",
    "sg:address":"320 Main St",
    "sg:city":"Milnor",
    "sg:classifiers":[
        {
            "category":"Manufacturing",
            "subcategory":"Printing",
            "type":"Manufacturing & Wholesale Goods"
        }
    ],
    "sg:phone":"+1 701 427 5221",
    "sg:postcode":"58060",
    "sg:province":"ND",
    "sg:tags":[
        "printer"
    ],
    "wof:name":"J & M Printing",
    "wof:placetype":"venue"
},
  "geometry": {"coordinates":[-97.45433,46.258048],"type":"Point"}
}