{
  "type": "Feature",
  "properties": {
    "iso:country":"US",
    "sg:address":"123 N 4th St",
    "sg:city":"Bismarck",
    "sg:classifiers":[
        {
            "category":"Shopping",
            "subcategory":"Clothing, Apparel, & Fashions",
            "type":"Retail Goods"
        }
    ],
    "sg:phone":"+1 701 223 9742",
    "sg:postcode":"58501",
    "sg:province":"ND",
    "sg:tags":[
        "shop",
        "bridal"
    ],
    "wof:name":"Bridal-N-More",
    "wof:placetype":"venue"
},
  "geometry": {"coordinates":[-100.78604799999999,46.80623],"type":"Point"}
}