{
  "type": "Feature",
  "properties": {
    "addr:full":"11080 67th St NW Bismarck ND 58503",
    "addr:housenumber":"11080",
    "addr:postcode":"58503",
    "addr:street":"67Th St Nw",
    "iso:country":"US",
    "sg:address":"11080 67th St NW",
    "sg:city":"Bismarck",
    "sg:classifiers":[
        {
            "category":"Real Estate",
            "subcategory":"Real Estate Agent",
            "type":"Services"
        },
        {
            "category":"Building & Trades",
            "subcategory":"Construction",
            "type":"Services"
        }
    ],
    "sg:phone":"+1 701 222 1818",
    "sg:postcode":"58503",
    "sg:province":"ND",
    "sg:tags":[
        "home",
        "builder",
        "inspection",
        "custom"
    ],
    "sg:website":"www.superhome.com",
    "wof:name":"Kjonaas Super Homes Inc",
    "wof:placetype":"venue"
},
  "geometry": {"coordinates":[-100.894904,46.92631],"type":"Point"}
}