{
  "type": "Feature",
  "properties": {
    "iso:country":"US",
    "sg:address":"201 1st St SE",
    "sg:city":"Beulah",
    "sg:classifiers":[
        {
            "category":"Shopping",
            "subcategory":"Used Merchandise",
            "type":"Retail Goods"
        }
    ],
    "sg:phone":"+1 701 873 2970",
    "sg:postcode":"58523",
    "sg:province":"ND",
    "wof:name":"Junkyard Antiques",
    "wof:placetype":"venue"
},
  "geometry": {"coordinates":[-101.776948,47.259786],"type":"Point"}
}