{
  "type": "Feature",
  "properties": {
    "addr:full":"19300 153rd St SE Sawyer ND 58781",
    "addr:housenumber":"19300",
    "addr:postcode":"58781",
    "addr:street":"153Rd St Se",
    "iso:country":"US",
    "sg:address":"19300 153rd St SE",
    "sg:city":"Sawyer",
    "sg:phone":"+1 701 624 5127",
    "sg:postcode":"58781",
    "sg:province":"ND",
    "sg:tags":[
        "farm",
        "grain",
        "cash"
    ],
    "wof:name":"Liebelt Farm",
    "wof:placetype":"venue"
},
  "geometry": {"coordinates":[-101.05835500000001,48.034743],"type":"Point"}
}