{
  "type": "Feature",
  "properties": {
    "iso:country":"US",
    "sg:address":"212 10th Ave",
    "sg:city":"Enderlin",
    "sg:classifiers":[
        {
            "category":"Building & Trades",
            "subcategory":"Plumbing",
            "type":"Services"
        }
    ],
    "sg:phone":"+1 701 437 2864",
    "sg:postcode":"58027",
    "sg:province":"ND",
    "sg:tags":[
        "plumbing",
        "conditioning",
        "contractor",
        "system",
        "air"
    ],
    "wof:name":"Cal's Plumbing Heating Air Cnd",
    "wof:placetype":"venue"
},
  "geometry": {"coordinates":[-97.592979,46.618109],"type":"Point"}
}