{
  "type": "Feature",
  "properties": {
    "iso:country":"US",
    "sg:address":"5760 175th Ave SE",
    "sg:city":"Christine",
    "sg:phone":"+1 701 998 2142",
    "sg:postcode":"58015",
    "sg:province":"ND",
    "sg:tags":[
        "farm",
        "wheat",
        "soybean"
    ],
    "wof:name":"Craig Granholt",
    "wof:placetype":"venue"
},
  "geometry": {"coordinates":[-96.759463,46.579884],"type":"Point"}
}