{
  "type": "Feature",
  "properties": {
    "iso:country":"US",
    "sg:address":"105 7th Ave W",
    "sg:city":"Dickinson",
    "sg:classifiers":[
        {
            "category":"Organizations",
            "subcategory":"Religious Organization",
            "type":"Services"
        }
    ],
    "sg:phone":"+1 701 264 7862",
    "sg:postcode":"58601",
    "sg:province":"ND",
    "sg:tags":[
        "church"
    ],
    "wof:name":"New Life Pentecostal Church",
    "wof:placetype":"venue"
},
  "geometry": {"coordinates":[-102.795748,46.881094],"type":"Point"}
}