{
  "type": "Feature",
  "properties": {
    "addr:full":"5890 13th Ave Mandan ND 58554",
    "addr:housenumber":"5890",
    "addr:postcode":"58554",
    "addr:street":"13Th Ave",
    "iso:country":"US",
    "sg:address":"5890 13th Ave",
    "sg:city":"Mandan",
    "sg:classifiers":[
        {
            "category":"Wholesale",
            "subcategory":"Farm Supplies",
            "type":"Manufacturing & Wholesale Goods"
        }
    ],
    "sg:phone":"+1 701 663 1143",
    "sg:postcode":"58554",
    "sg:province":"ND",
    "wof:name":"Berger Ranch Supply",
    "wof:placetype":"venue"
},
  "geometry": {"coordinates":[-100.69756599999999,46.566234],"type":"Point"}
}