{
  "type": "Feature",
  "properties": {
    "addr:full":"1230 Airport Rd Bismarck ND 58504",
    "addr:housenumber":"1230",
    "addr:postcode":"58504",
    "addr:street":"Airport Rd",
    "iso:country":"US",
    "sg:address":"1230 Airport Rd",
    "sg:city":"Bismarck",
    "sg:classifiers":[
        {
            "category":"Professional",
            "subcategory":"Engineering",
            "type":"Services"
        }
    ],
    "sg:phone":"+1 701 255 7180",
    "sg:postcode":"58504",
    "sg:province":"ND",
    "sg:tags":[
        "engineer"
    ],
    "wof:name":"Braun Intertec Corp",
    "wof:placetype":"venue"
},
  "geometry": {"coordinates":[-100.76297700000001,46.791102],"type":"Point"}
}