{
  "type": "Feature",
  "properties": {
    "addr:full":"1109 55th Ave NE Cathay ND 58422",
    "addr:housenumber":"1109",
    "addr:postcode":"58422",
    "addr:street":"55Th Ave Ne",
    "iso:country":"US",
    "sg:address":"1109 55th Ave NE",
    "sg:city":"Cathay",
    "sg:classifiers":[
        {
            "category":"Real Estate",
            "subcategory":"Real Estate Operator",
            "type":"Services"
        }
    ],
    "sg:phone":"+1 701 984 2355",
    "sg:postcode":"58422",
    "sg:province":"ND",
    "sg:tags":[
        "building",
        "apartment"
    ],
    "wof:name":"Rocky Run Apts LLP",
    "wof:placetype":"venue"
},
  "geometry": {"coordinates":[-99.37290299999999,47.577956],"type":"Point"}
}