{
  "type": "Feature",
  "properties": {
    "addr:full":"809 Church Ave Hebron ND 58638",
    "addr:housenumber":"809",
    "addr:postcode":"58638",
    "addr:street":"Church Ave",
    "iso:country":"US",
    "sg:address":"809 Church Ave",
    "sg:city":"Hebron",
    "sg:classifiers":[
        {
            "category":"Retail",
            "subcategory":"Repair Shop",
            "type":"Services"
        }
    ],
    "sg:phone":"+1 701 878 4289",
    "sg:postcode":"58638",
    "sg:province":"ND",
    "sg:tags":[
        "upholsterer"
    ],
    "wof:name":"Spring & Custom Upholstery",
    "wof:placetype":"venue"
},
  "geometry": {"coordinates":[-102.043508,46.903505],"type":"Point"}
}