{
  "type": "Feature",
  "properties": {
    "addr:full":"5131 141st Ave NW Williston ND 58801",
    "addr:housenumber":"5131",
    "addr:postcode":"58801",
    "addr:street":"141St Ave Nw",
    "iso:country":"US",
    "sg:address":"5131 141st Ave NW",
    "sg:city":"Williston",
    "sg:classifiers":[
        {
            "category":"Mining & Drilling",
            "type":"Manufacturing & Wholesale Goods"
        }
    ],
    "sg:phone":"+1 701 572 6704",
    "sg:postcode":"58801",
    "sg:province":"ND",
    "sg:tags":[
        "oil",
        "well"
    ],
    "wof:name":"Nabors Drilling USA",
    "wof:placetype":"venue"
},
  "geometry": {"coordinates":[-103.733503,48.166497],"type":"Point"}
}