{
  "type": "Feature",
  "properties": {
    "iso:country":"US",
    "sg:address":"4405 47th St N",
    "sg:city":"Fargo",
    "sg:classifiers":[
        {
            "category":"Retail",
            "subcategory":"Auto Repair",
            "type":"Services"
        }
    ],
    "sg:phone":"+1 701 282 2958",
    "sg:postcode":"58102",
    "sg:province":"ND",
    "sg:tags":[
        "general"
    ],
    "wof:name":"K & K Repair and Machine",
    "wof:placetype":"venue"
},
  "geometry": {"coordinates":[-96.866195,46.940953],"type":"Point"}
}