{
  "type": "Feature",
  "properties": {
    "addr:full":"402 E St S Glen Ullin ND 58631",
    "addr:housenumber":"402",
    "addr:postcode":"58631",
    "addr:street":"E St S Glen",
    "iso:country":"US",
    "sg:address":"402 E St S",
    "sg:city":"Glen Ullin",
    "sg:classifiers":[
        {
            "category":"Food & Beverages",
            "subcategory":"Meat & Fish",
            "type":"Retail Goods"
        }
    ],
    "sg:phone":"+1 701 348 3635",
    "sg:postcode":"58631",
    "sg:province":"ND",
    "wof:name":"Kuntz's Butcher Shop",
    "wof:placetype":"venue"
},
  "geometry": {"coordinates":[-101.82431099999999,46.815392],"type":"Point"}
}