{
  "type": "Feature",
  "properties": {
    "iso:country":"US",
    "sg:address":"402 14th Ave NE",
    "sg:city":"Jamestown",
    "sg:classifiers":[
        {
            "category":"Organizations",
            "subcategory":"Religious Organization",
            "type":"Services"
        }
    ],
    "sg:phone":"+1 701 251 1478",
    "sg:postcode":"58401",
    "sg:province":"ND",
    "sg:tags":[
        "church"
    ],
    "wof:name":"Faith Baptist Church KJV",
    "wof:placetype":"venue"
},
  "geometry": {"coordinates":[-98.688912,46.91359],"type":"Point"}
}