{
  "type": "Feature",
  "properties": {
    "iso:country":"US",
    "sg:address":"7245 35th St",
    "sg:city":"Hebron",
    "sg:phone":"+1 701 878 4933",
    "sg:postcode":"58638",
    "sg:province":"ND",
    "sg:tags":[
        "farm",
        "grain",
        "cash"
    ],
    "wof:name":"James Wanner",
    "wof:placetype":"venue"
},
  "geometry": {"coordinates":[-101.955472,46.905933],"type":"Point"}
}