{
  "type": "Feature",
  "properties": {
    "iso:country":"US",
    "sg:address":"701 W 6th St",
    "sg:city":"Grafton",
    "sg:classifiers":[
        {
            "category":"Education",
            "subcategory":"Vocational School",
            "type":"Public Place"
        }
    ],
    "sg:phone":"+1 701 352 4200",
    "sg:postcode":"58237",
    "sg:province":"ND",
    "sg:tags":[
        "disabled",
        "for",
        "mentally"
    ],
    "wof:name":"Developmental Center",
    "wof:placetype":"venue"
},
  "geometry": {"coordinates":[-97.421342,48.418135],"type":"Point"}
}