{
  "type": "Feature",
  "properties": {
    "addr:full":"2106 8th Ave NW Minot ND 58703",
    "addr:housenumber":"2106",
    "addr:postcode":"58703",
    "addr:street":"8Th Ave Nw",
    "iso:country":"US",
    "sg:address":"2106 8th Ave NW",
    "sg:city":"Minot",
    "sg:classifiers":[
        {
            "category":"Professional",
            "subcategory":"Computer Services",
            "type":"Services"
        }
    ],
    "sg:phone":"+1 701 837 6563",
    "sg:postcode":"58703",
    "sg:province":"ND",
    "sg:tags":[
        "related"
    ],
    "wof:name":"Digital Doctors North Dakota",
    "wof:placetype":"venue"
},
  "geometry": {"coordinates":[-101.32691800000001,48.24465],"type":"Point"}
}