{
  "type": "Feature",
  "properties": {
    "addr:full":"314 3rd Ave W Dickinson ND 58601",
    "addr:housenumber":"314",
    "addr:postcode":"58601",
    "addr:street":"3Rd Ave W",
    "iso:country":"US",
    "sg:address":"314 3rd Ave W",
    "sg:city":"Dickinson",
    "sg:classifiers":[
        {
            "category":"Organizations",
            "subcategory":"Professional Association",
            "type":"Services"
        }
    ],
    "sg:phone":"+1 701 225 5115",
    "sg:postcode":"58601",
    "sg:province":"ND",
    "sg:tags":[
        "chambers",
        "commerce"
    ],
    "wof:name":"Chamber Of Commerce",
    "wof:placetype":"venue"
},
  "geometry": {"coordinates":[-102.78975199999999,46.882992],"type":"Point"}
}