{
  "type": "Feature",
  "properties": {
    "addr:full":"701 Woodland Trl Mandan ND 58554",
    "addr:housenumber":"701",
    "addr:postcode":"58554",
    "addr:street":"Woodland Trl",
    "iso:country":"US",
    "sg:address":"701 Woodland Trl",
    "sg:city":"Mandan",
    "sg:classifiers":[
        {
            "category":"Education",
            "subcategory":"Special Training",
            "type":"Public Place"
        }
    ],
    "sg:phone":"+1 701 663 6157",
    "sg:postcode":"58554",
    "sg:province":"ND",
    "wof:name":"Charlotte A Gartner",
    "wof:placetype":"venue"
},
  "geometry": {"coordinates":[-100.876992,46.819247],"type":"Point"}
}