{
  "type": "Feature",
  "properties": {
    "iso:country":"US",
    "sg:address":"409 5th St NE",
    "sg:city":"Watford City",
    "sg:classifiers":[
        {
            "category":"Government",
            "subcategory":"Office",
            "type":"Public Place"
        }
    ],
    "sg:phone":"+1 701 842 4048",
    "sg:postcode":"58854",
    "sg:province":"ND",
    "sg:tags":[
        "state"
    ],
    "wof:name":"Game & Fish Dept",
    "wof:placetype":"venue"
},
  "geometry": {"coordinates":[-103.27682799999999,47.806018],"type":"Point"}
}