{
  "type": "Feature",
  "properties": {
    "iso:country":"US",
    "sg:address":"300 45th St SW",
    "sg:city":"Fargo",
    "sg:classifiers":[
        {
            "category":"Wholesale",
            "subcategory":"Electrical",
            "type":"Manufacturing & Wholesale Goods"
        }
    ],
    "sg:phone":"+1 701 356 3300",
    "sg:postcode":"58103",
    "sg:province":"ND",
    "sg:tags":[
        "control",
        "security",
        "system"
    ],
    "sg:website":"www.echelon.com",
    "wof:name":"Echelon Corp",
    "wof:placetype":"venue"
},
  "geometry": {"coordinates":[-96.86158,46.872537],"type":"Point"}
}