{
  "type": "Feature",
  "properties": {
    "addr:full":"1826 S Washington St Grand Forks ND 58201",
    "addr:housenumber":"1826",
    "addr:postcode":"58201",
    "addr:street":"S Washington St",
    "iso:country":"US",
    "sg:address":"1826 S Washington St",
    "sg:city":"Grand Forks",
    "sg:classifiers":[
        {
            "category":"Shopping",
            "type":"Retail Goods"
        }
    ],
    "sg:phone":"+1 701 772 9692",
    "sg:postcode":"58201",
    "sg:province":"ND",
    "sg:tags":[
        "cosmetic",
        "perfume"
    ],
    "wof:name":"Cheri Paul",
    "wof:placetype":"venue"
},
  "geometry": {"coordinates":[-97.04558400000001,47.902651],"type":"Point"}
}