{
  "type": "Feature",
  "properties": {
    "addr:full":"1951 N Washington St Grand Forks ND 58203",
    "addr:housenumber":"1951",
    "addr:postcode":"58203",
    "addr:street":"N Washington St",
    "iso:country":"US",
    "sg:address":"1951 N Washington St",
    "sg:city":"Grand Forks",
    "sg:classifiers":[
        {
            "category":"Government",
            "subcategory":"Office",
            "type":"Public Place"
        }
    ],
    "sg:phone":"+1 701 787 6540",
    "sg:postcode":"58203",
    "sg:province":"ND",
    "wof:name":"Grand Forks Vehicle Svc",
    "wof:placetype":"venue"
},
  "geometry": {"coordinates":[-97.06340899999999,47.941863],"type":"Point"}
}