{
  "type": "Feature",
  "properties": {
    "iso:country":"US",
    "sg:address":"555 Memorial Hwy",
    "sg:city":"Bismarck",
    "sg:classifiers":[
        {
            "category":"Wholesale",
            "subcategory":"Groceries",
            "type":"Manufacturing & Wholesale Goods"
        }
    ],
    "sg:phone":"+1 701 222 1465",
    "sg:postcode":"58504",
    "sg:province":"ND",
    "sg:tags":[
        "bakery",
        "product"
    ],
    "wof:name":"Master Bread",
    "wof:placetype":"venue"
},
  "geometry": {"coordinates":[-100.79892100000001,46.80551],"type":"Point"}
}