{
  "type": "Feature",
  "properties": {
    "addr:full":"303 7th Ave N Fessenden ND 58438",
    "addr:housenumber":"303",
    "addr:postcode":"58438",
    "addr:street":"7Th Ave N Fessenden",
    "iso:country":"US",
    "sg:address":"303 7th Ave N",
    "sg:city":"Fessenden",
    "sg:classifiers":[
        {
            "category":"Organizations",
            "subcategory":"Religious Organization",
            "type":"Services"
        }
    ],
    "sg:phone":"+1 701 547 3550",
    "sg:postcode":"58438",
    "sg:province":"ND",
    "sg:tags":[
        "church"
    ],
    "wof:name":"Church Of The Nazarene",
    "wof:placetype":"venue"
},
  "geometry": {"coordinates":[-99.62398,47.651396],"type":"Point"}
}