{
  "type": "Feature",
  "properties": {
    "iso:country":"US",
    "sg:address":"118 Main St N",
    "sg:city":"Tioga",
    "sg:classifiers":[
        {
            "category":"Health Services",
            "subcategory":"Chiropractor",
            "type":"Services"
        }
    ],
    "sg:phone":"+1 701 664 2311",
    "sg:postcode":"58852",
    "sg:province":"ND",
    "wof:name":"Stewart Chiropractic Ctr",
    "wof:placetype":"venue"
},
  "geometry": {"coordinates":[-102.938388,48.397006],"type":"Point"}
}