{
  "type": "Feature",
  "properties": {
    "iso:country":"US",
    "sg:address":"3919 73rd Ave SE",
    "sg:city":"Jamestown",
    "sg:classifiers":[
        {
            "category":"Wholesale",
            "subcategory":"Electrical",
            "type":"Manufacturing & Wholesale Goods"
        }
    ],
    "sg:phone":"+1 701 763 6183",
    "sg:postcode":"58401",
    "sg:province":"ND",
    "sg:tags":[
        "telecommunication",
        "sales"
    ],
    "wof:name":"Heer Electronics",
    "wof:placetype":"venue"
},
  "geometry": {"coordinates":[-98.92474900000001,46.846124],"type":"Point"}
}