{
  "type": "Feature",
  "properties": {
    "iso:country":"US",
    "sg:address":"3439 110th Ave SW",
    "sg:city":"Dickinson",
    "sg:classifiers":[
        {
            "category":"Building & Trades",
            "subcategory":"Construction",
            "type":"Services"
        }
    ],
    "sg:phone":"+1 701 227 1685",
    "sg:postcode":"58601",
    "sg:province":"ND",
    "sg:tags":[
        "residential",
        "nonresidential"
    ],
    "wof:name":"Welk Home Improvement",
    "wof:placetype":"venue"
},
  "geometry": {"coordinates":[-102.768732,46.924562],"type":"Point"}
}