{
  "type": "Feature",
  "properties": {
    "iso:country":"US",
    "sg:address":"141 5th Ave W",
    "sg:city":"Dickinson",
    "sg:classifiers":[
        {
            "category":"Farming",
            "subcategory":"Farm",
            "type":"Manufacturing & Wholesale Goods"
        }
    ],
    "sg:phone":"+1 701 225 2040",
    "sg:postcode":"58601",
    "sg:province":"ND",
    "sg:tags":[
        "crop",
        "general"
    ],
    "wof:name":"Steffan Laudie",
    "wof:placetype":"venue"
},
  "geometry": {"coordinates":[-102.792872,46.880701],"type":"Point"}
}