{
  "type": "Feature",
  "properties": {
    "addr:full":"307 Stanford Rd Grand Forks ND 58203",
    "addr:housenumber":"307",
    "addr:postcode":"58203",
    "addr:street":"Stanford Rd",
    "iso:country":"US",
    "sg:address":"307 Stanford Rd",
    "sg:city":"Grand Forks",
    "sg:classifiers":[
        {
            "category":"Food & Beverages",
            "subcategory":"Specialty",
            "type":"Retail Goods"
        }
    ],
    "sg:phone":"+1 701 777 9884",
    "sg:postcode":"58203",
    "sg:province":"ND",
    "wof:name":"Next Generation Nutrition",
    "wof:placetype":"venue"
},
  "geometry": {"coordinates":[-97.081146,47.925701],"type":"Point"}
}