{
  "type": "Feature",
  "properties": {
    "iso:country":"US",
    "sg:address":"215 4th Ave NW",
    "sg:city":"Rugby",
    "sg:classifiers":[
        {
            "category":"Building & Trades",
            "subcategory":"Construction",
            "type":"Services"
        }
    ],
    "sg:phone":"+1 701 776 2879",
    "sg:postcode":"58368",
    "sg:province":"ND",
    "sg:tags":[
        "marking",
        "maintenance",
        "parking"
    ],
    "wof:name":"Rugby Street Dept",
    "wof:placetype":"venue"
},
  "geometry": {"coordinates":[-100.00075699999999,48.373049],"type":"Point"}
}