{
  "type": "Feature",
  "properties": {
    "addr:full":"332 2nd St W Devils Lake ND 58301",
    "addr:housenumber":"332",
    "addr:postcode":"58301",
    "addr:street":"2Nd St W",
    "iso:country":"US",
    "sg:address":"332 2nd St W",
    "sg:city":"Devils Lake",
    "sg:classifiers":[
        {
            "category":"Autos & Motor Vehicles",
            "subcategory":"Automobile Sales",
            "type":"Retail Goods"
        }
    ],
    "sg:phone":"+1 701 662 7571",
    "sg:postcode":"58301",
    "sg:province":"ND",
    "sg:tags":[
        "car",
        "dealer"
    ],
    "sg:website":"www.marketplaceford.com",
    "wof:name":"Marketplace Motors",
    "wof:placetype":"venue"
},
  "geometry": {"coordinates":[-98.86856400000001,48.109736],"type":"Point"}
}