{
  "type": "Feature",
  "properties": {
    "addr:full":"1226 38th St N Fargo ND 58102",
    "addr:housenumber":"1226",
    "addr:postcode":"58102",
    "addr:street":"38Th St N",
    "iso:country":"US",
    "sg:address":"1226 38th St N",
    "sg:city":"Fargo",
    "sg:classifiers":[
        {
            "category":"Wholesale",
            "subcategory":"Hardware",
            "type":"Manufacturing & Wholesale Goods"
        }
    ],
    "sg:phone":"+1 701 282 2088",
    "sg:postcode":"58102",
    "sg:province":"ND",
    "sg:tags":[
        "nut",
        "bolt"
    ],
    "wof:name":"Northern States Supply Inc",
    "wof:placetype":"venue"
},
  "geometry": {"coordinates":[-96.841469,46.891546],"type":"Point"}
}