{
  "type": "Feature",
  "properties": {
    "addr:full":"111 1st St NE Tioga ND 58852",
    "addr:housenumber":"111",
    "addr:postcode":"58852",
    "addr:street":"1St St Ne",
    "iso:country":"US",
    "sg:address":"111 1st St NE",
    "sg:city":"Tioga",
    "sg:classifiers":[
        {
            "category":"Sports & Exercise",
            "subcategory":"Gym",
            "type":"Entertainment"
        }
    ],
    "sg:phone":"+1 701 965 6354",
    "sg:postcode":"58852",
    "sg:province":"ND",
    "sg:tags":[
        "club",
        "health",
        "studio",
        "gymnasium"
    ],
    "wof:name":"Prairie Tumbleweeds Gym",
    "wof:placetype":"venue"
},
  "geometry": {"coordinates":[-102.93714199999999,48.395769],"type":"Point"}
}