{
  "type": "Feature",
  "properties": {
    "addr:full":"317 Beaver Ave Wishek ND 58495",
    "addr:housenumber":"317",
    "addr:postcode":"58495",
    "addr:street":"Beaver Ave",
    "iso:country":"US",
    "sg:address":"317 Beaver Ave",
    "sg:city":"Wishek",
    "sg:classifiers":[
        {
            "category":"Retail",
            "subcategory":"Car Wash",
            "type":"Services"
        }
    ],
    "sg:phone":"+1 701 452 2546",
    "sg:postcode":"58495",
    "sg:province":"ND",
    "sg:tags":[
        "automobile",
        "detail",
        "clean"
    ],
    "wof:name":"Craig's Car Care",
    "wof:placetype":"venue"
},
  "geometry": {"coordinates":[-99.56195200000001,46.259144],"type":"Point"}
}