{
  "type": "Feature",
  "properties": {
    "iso:country":"US",
    "sg:address":"1616 12th Ave N",
    "sg:city":"Fargo",
    "sg:classifiers":[
        {
            "category":"Organizations",
            "subcategory":"Non-profit Organization",
            "type":"Services"
        }
    ],
    "sg:phone":"+1 218 299 7840",
    "sg:postcode":"58102",
    "sg:province":"ND",
    "wof:name":"Moorhead Transitional Housing",
    "wof:placetype":"venue"
},
  "geometry": {"coordinates":[-96.806428,46.890295],"type":"Point"}
}