{
  "type": "Feature",
  "properties": {
    "iso:country":"US",
    "sg:address":"59 Wiley Ave N",
    "sg:city":"Lidgerwood",
    "sg:classifiers":[
        {
            "category":"Retail",
            "subcategory":"Auto Repair",
            "type":"Services"
        }
    ],
    "sg:phone":"+1 701 538 4649",
    "sg:postcode":"58053",
    "sg:province":"ND",
    "sg:tags":[
        "transmission"
    ],
    "wof:name":"Kraemer Repair",
    "wof:placetype":"venue"
},
  "geometry": {"coordinates":[-97.151881,46.075929],"type":"Point"}
}