{
  "type": "Feature",
  "properties": {
    "iso:country":"US",
    "sg:address":"1019 3rd Ave S",
    "sg:city":"Fargo",
    "sg:classifiers":[
        {
            "category":"Government",
            "subcategory":"Office",
            "type":"Public Place"
        }
    ],
    "sg:phone":"+1 701 241 5845",
    "sg:postcode":"58103",
    "sg:province":"ND",
    "wof:name":"Cass County Juvenile Detention",
    "wof:placetype":"venue"
},
  "geometry": {"coordinates":[-96.795873,46.871776],"type":"Point"}
}