{
  "type": "Feature",
  "properties": {
    "iso:country":"US",
    "sg:address":"600 Cooper Ave",
    "sg:city":"Grafton",
    "sg:classifiers":[
        {
            "category":"Government",
            "subcategory":"Office",
            "type":"Public Place"
        }
    ],
    "sg:phone":"+1 701 352 1077",
    "sg:postcode":"58237",
    "sg:province":"ND",
    "sg:tags":[
        "county",
        "taxation"
    ],
    "wof:name":"Walsh County Tax Equalization",
    "wof:placetype":"venue"
},
  "geometry": {"coordinates":[-97.405513,48.418523],"type":"Point"}
}