{
  "type": "Feature",
  "properties": {
    "iso:country":"US",
    "sg:address":"1837 Thomas Dr",
    "sg:city":"Larimore",
    "sg:phone":"+1 701 397 5299",
    "sg:postcode":"58251",
    "sg:province":"ND",
    "sg:tags":[
        "corn"
    ],
    "wof:name":"Clean A Rama",
    "wof:placetype":"venue"
},
  "geometry": {"coordinates":[-97.58529,47.935288],"type":"Point"}
}