{
  "type": "Feature",
  "properties": {
    "iso:country":"US",
    "sg:address":"220 Burdick Expy W",
    "sg:city":"Minot",
    "sg:classifiers":[
        {
            "category":"Coffee & Tea",
            "type":"Food & Drink"
        }
    ],
    "sg:menulink":"http://www.allmenus.com/nd/minot/124910-starbucks-coffee/menu/",
    "sg:phone":"+1 701 838 9609",
    "sg:postcode":"58701",
    "sg:province":"ND",
    "sg:tags":[
        "american"
    ],
    "wof:name":"Starbucks Coffee",
    "wof:placetype":"venue"
},
  "geometry": {"coordinates":[-101.296301,48.232521],"type":"Point"}
}