{
  "type": "Feature",
  "properties": {
    "iso:country":"US",
    "sg:address":"1128 W Main St",
    "sg:city":"Valley City",
    "sg:classifiers":[
        {
            "category":"Restaurant",
            "type":"Food & Drink"
        }
    ],
    "sg:menulink":"http://www.allmenus.com/nd/valley-city/129644-subway/menu/",
    "sg:phone":"+1 701 845 5489",
    "sg:postcode":"58072",
    "sg:province":"ND",
    "sg:tags":[
        "american",
        "sandwich"
    ],
    "wof:name":"Subway",
    "wof:placetype":"venue"
},
  "geometry": {"coordinates":[-98.01812200000001,46.920859],"type":"Point"}
}