{
  "type": "Feature",
  "properties": {
    "iso:country":"US",
    "sg:address":"2705 Twin City Dr",
    "sg:city":"Mandan",
    "sg:classifiers":[
        {
            "category":"Professional",
            "subcategory":"Business Services",
            "type":"Services"
        }
    ],
    "sg:phone":"+1 701 663 8930",
    "sg:postcode":"58554",
    "sg:province":"ND",
    "sg:tags":[
        "equipment",
        "microfilm",
        "bureau",
        "microfilming",
        "banking"
    ],
    "sg:website":"www.datrue.com",
    "wof:name":"Datrue Processing Automation",
    "wof:placetype":"venue"
},
  "geometry": {"coordinates":[-100.856134,46.825862],"type":"Point"}
}