{
  "type": "Feature",
  "properties": {
    "iso:country":"US",
    "sg:address":"2615 Dublin Dr",
    "sg:city":"Bismarck",
    "sg:classifiers":[
        {
            "category":"Building & Trades",
            "subcategory":"Construction",
            "type":"Services"
        }
    ],
    "sg:phone":"+1 701 400 0434",
    "sg:postcode":"58503",
    "sg:province":"ND",
    "sg:tags":[
        "excavating",
        "contractor"
    ],
    "wof:name":"Frontier Excavating",
    "wof:placetype":"venue"
},
  "geometry": {"coordinates":[-100.747209,46.909136],"type":"Point"}
}