{
  "type": "Feature",
  "properties": {
    "iso:country":"US",
    "sg:address":"3656 E Princeton Dr",
    "sg:city":"Bismarck",
    "sg:classifiers":[
        {
            "category":"Social Services",
            "type":"Services"
        }
    ],
    "sg:phone":"+1 701 255 1972",
    "sg:postcode":"58504",
    "sg:province":"ND",
    "wof:name":"East Princeton",
    "wof:placetype":"venue"
},
  "geometry": {"coordinates":[-100.772301,46.763906],"type":"Point"}
}