{
  "type": "Feature",
  "properties": {
    "iso:country":"US",
    "sg:address":"422 N 2nd St",
    "sg:city":"Bismarck",
    "sg:classifiers":[
        {
            "category":"Organizations",
            "subcategory":"Professional Association",
            "type":"Services"
        }
    ],
    "sg:phone":"+1 701 255 7250",
    "sg:postcode":"58501",
    "sg:province":"ND",
    "wof:name":"North Dakota Ready Mix Assn",
    "wof:placetype":"venue"
},
  "geometry": {"coordinates":[-100.789187,46.809406],"type":"Point"}
}