{
  "type": "Feature",
  "properties": {
    "iso:country":"US",
    "sg:address":"2760 US Hwy 2",
    "sg:city":"Rugby",
    "sg:classifiers":[
        {
            "category":"Autos & Motor Vehicles",
            "subcategory":"Automobile Sales",
            "type":"Retail Goods"
        }
    ],
    "sg:phone":"+1 701 776 5922",
    "sg:postcode":"58368",
    "sg:province":"ND",
    "sg:tags":[
        "used"
    ],
    "wof:name":"Kleins Truck Sales",
    "wof:placetype":"venue"
},
  "geometry": {"coordinates":[-100.02515699999999,48.354946],"type":"Point"}
}