{
  "type": "Feature",
  "properties": {
    "addr:full":"317 Antelope Ave SW Forman ND 58032",
    "addr:housenumber":"317",
    "addr:postcode":"58032",
    "addr:street":"Antelope Ave Sw",
    "iso:country":"US",
    "sg:address":"317 Antelope Ave SW",
    "sg:city":"Forman",
    "sg:classifiers":[
        {
            "category":"Health Services",
            "subcategory":"Doctor",
            "type":"Services"
        }
    ],
    "sg:phone":"+1 701 724 3671",
    "sg:postcode":"58032",
    "sg:province":"ND",
    "sg:tags":[
        "dentist"
    ],
    "wof:name":"Mark Williamson DDS",
    "wof:placetype":"venue"
},
  "geometry": {"coordinates":[-97.637761,46.107729],"type":"Point"}
}