{
  "type": "Feature",
  "properties": {
    "iso:country":"US",
    "sg:address":"322 Broadway",
    "sg:city":"Fargo",
    "sg:classifiers":[
        {
            "category":"Professional",
            "subcategory":"Employment Agencies",
            "type":"Services"
        }
    ],
    "sg:phone":"+1 701 297 6102",
    "sg:postcode":"58102",
    "sg:province":"ND",
    "wof:name":"Prairie Staffing",
    "wof:placetype":"venue"
},
  "geometry": {"coordinates":[-96.787766,46.879484],"type":"Point"}
}