{
  "type": "Feature",
  "properties": {
    "iso:country":"US",
    "sg:address":"535 2nd St S",
    "sg:city":"Carrington",
    "sg:classifiers":[
        {
            "category":"Building & Trades",
            "subcategory":"Construction",
            "type":"Services"
        }
    ],
    "sg:phone":"+1 701 652 2606",
    "sg:postcode":"58421",
    "sg:province":"ND",
    "sg:tags":[
        "well",
        "drilling"
    ],
    "wof:name":"Schimelfenig Well Drilling",
    "wof:placetype":"venue"
},
  "geometry": {"coordinates":[-99.11926800000001,47.447597],"type":"Point"}
}