{
  "type": "Feature",
  "properties": {
    "addr:full":"1517 S River Rd Fargo ND 58103",
    "addr:housenumber":"1517",
    "addr:postcode":"58103",
    "addr:street":"S River Rd",
    "iso:country":"US",
    "sg:address":"1517 S River Rd",
    "sg:city":"Fargo",
    "sg:classifiers":[
        {
            "category":"Professional",
            "subcategory":"Business Services",
            "type":"Services"
        }
    ],
    "sg:phone":"+1 701 235 6849",
    "sg:postcode":"58103",
    "sg:province":"ND",
    "wof:name":"Holtgard Enterprises LLC",
    "wof:placetype":"venue"
},
  "geometry": {"coordinates":[-96.78140999999999,46.857446],"type":"Point"}
}