{
  "type": "Feature",
  "properties": {
    "iso:country":"US",
    "sg:address":"4733 Ottawa St",
    "sg:city":"Bismarck",
    "sg:classifiers":[
        {
            "category":"Building & Trades",
            "subcategory":"Construction",
            "type":"Services"
        }
    ],
    "sg:phone":"+1 701 223 7877",
    "sg:postcode":"58503",
    "sg:province":"ND",
    "sg:tags":[
        "layer",
        "carpet"
    ],
    "wof:name":"Rugrat",
    "wof:placetype":"venue"
},
  "geometry": {"coordinates":[-100.77431900000001,46.858042],"type":"Point"}
}