{
  "type": "Feature",
  "properties": {
    "iso:country":"US",
    "sg:address":"212 27th St S",
    "sg:city":"Fargo",
    "sg:classifiers":[
        {
            "category":"Building & Trades",
            "subcategory":"Construction",
            "type":"Services"
        }
    ],
    "sg:phone":"+1 701 237 3845",
    "sg:postcode":"58103",
    "sg:province":"ND",
    "sg:tags":[
        "contractor"
    ],
    "wof:name":"Valley Sandblast & Paint",
    "wof:placetype":"venue"
},
  "geometry": {"coordinates":[-96.821146,46.873395],"type":"Point"}
}