{
  "type": "Feature",
  "properties": {
    "iso:country":"US",
    "sg:address":"6895 141st Ave NE",
    "sg:city":"Grafton",
    "sg:classifiers":[
        {
            "category":"Organizations",
            "subcategory":"Religious Organization",
            "type":"Services"
        }
    ],
    "sg:phone":"+1 701 284 7514",
    "sg:postcode":"58237",
    "sg:province":"ND",
    "wof:name":"Pleasant Valley Christian",
    "wof:placetype":"venue"
},
  "geometry": {"coordinates":[-97.60098499999999,48.40197],"type":"Point"}
}