{
  "type": "Feature",
  "properties": {
    "addr:full":"149 Prairiewood Dr S Fargo ND 58103",
    "addr:housenumber":"149",
    "addr:postcode":"58103",
    "addr:street":"Prairiewood Dr S",
    "iso:country":"US",
    "sg:address":"149 Prairiewood Dr S",
    "sg:city":"Fargo",
    "sg:classifiers":[
        {
            "category":"Government",
            "subcategory":"Office",
            "type":"Public Place"
        }
    ],
    "sg:phone":"+1 701 235 2172",
    "sg:postcode":"58103",
    "sg:province":"ND",
    "wof:name":"Kenneth Lee Barnes",
    "wof:placetype":"venue"
},
  "geometry": {"coordinates":[-96.833969,46.84848],"type":"Point"}
}