{
  "type": "Feature",
  "properties": {
    "iso:country":"US",
    "sg:address":"92 1st St SE",
    "sg:city":"Beach",
    "sg:classifiers":[
        {
            "category":"Insurance",
            "subcategory":"Insurance Agent",
            "type":"Services"
        }
    ],
    "sg:phone":"+1 701 872 4461",
    "sg:postcode":"58621",
    "sg:province":"ND",
    "sg:website":"www.agriinsurances.com",
    "wof:name":"Agri Risk Management",
    "wof:placetype":"venue"
},
  "geometry": {"coordinates":[-104.005308,46.913985],"type":"Point"}
}