{
  "type": "Feature",
  "properties": {
    "addr:full":"220 N 4th St Grand Forks ND 58203",
    "addr:housenumber":"220",
    "addr:postcode":"58203",
    "addr:street":"N 4Th St",
    "iso:country":"US",
    "sg:address":"220 N 4th St",
    "sg:city":"Grand Forks",
    "sg:classifiers":[
        {
            "category":"Personal",
            "subcategory":"Beauty Salon",
            "type":"Services"
        }
    ],
    "sg:phone":"+1 701 795 6040",
    "sg:postcode":"58203",
    "sg:province":"ND",
    "wof:name":"J B's Salon",
    "wof:placetype":"venue"
},
  "geometry": {"coordinates":[-97.034853,47.926395],"type":"Point"}
}