{
  "type": "Feature",
  "properties": {
    "addr:full":"2744 45th Ave NW Douglas ND 58735",
    "addr:housenumber":"2744",
    "addr:postcode":"58735",
    "addr:street":"45Th Ave Nw",
    "iso:country":"US",
    "sg:address":"2744 45th Ave NW",
    "sg:city":"Douglas",
    "sg:phone":"+1 701 529 4874",
    "sg:postcode":"58735",
    "sg:province":"ND",
    "sg:tags":[
        "farm",
        "wheat"
    ],
    "wof:name":"Zack Roberts",
    "wof:placetype":"venue"
},
  "geometry": {"coordinates":[-101.550663,47.804454],"type":"Point"}
}