{
  "type": "Feature",
  "properties": {
    "iso:country":"US",
    "sg:address":"3209 Fiechtner Dr",
    "sg:city":"Fargo",
    "sg:classifiers":[
        {
            "category":"Utilities",
            "subcategory":"Mobile Phone",
            "type":"Services"
        }
    ],
    "sg:phone":"+1 701 235 5148",
    "sg:postcode":"58103",
    "sg:province":"ND",
    "sg:tags":[
        "sales",
        "cellular"
    ],
    "wof:name":"Verizon",
    "wof:placetype":"venue"
},
  "geometry": {"coordinates":[-96.830528,46.86564],"type":"Point"}
}