{
  "type": "Feature",
  "properties": {
    "iso:country":"US",
    "sg:address":"14830 State Hwy 17",
    "sg:city":"Grafton",
    "sg:classifiers":[
        {
            "category":"Professional",
            "type":"Services"
        }
    ],
    "sg:phone":"+1 701 352 9611",
    "sg:postcode":"58237",
    "sg:province":"ND",
    "sg:tags":[
        "establishment"
    ],
    "wof:name":"Spudnik Equipment",
    "wof:placetype":"venue"
},
  "geometry": {"coordinates":[-97.441643,48.412554],"type":"Point"}
}