{
  "type": "Feature",
  "properties": {
    "iso:country":"US",
    "sg:address":"3100 13th Ave SW",
    "sg:city":"Fargo",
    "sg:classifiers":[
        {
            "category":"Banks & Credit Unions",
            "subcategory":"Investment Brokerage",
            "type":"Services"
        }
    ],
    "sg:phone":"+1 701 256 2757",
    "sg:postcode":"58103",
    "sg:province":"ND",
    "sg:tags":[
        "advice"
    ],
    "wof:name":"American Express",
    "wof:placetype":"venue"
},
  "geometry": {"coordinates":[-96.829229,46.861412],"type":"Point"}
}