{
  "type": "Feature",
  "properties": {
    "iso:country":"US",
    "sg:address":"400 N Broadway",
    "sg:city":"Minot",
    "sg:classifiers":[
        {
            "category":"Restaurant",
            "type":"Food & Drink"
        }
    ],
    "sg:phone":"+1 701 852 4486",
    "sg:postcode":"58703",
    "sg:province":"ND",
    "sg:tags":[
        "eating"
    ],
    "wof:name":"Sammys Pizza",
    "wof:placetype":"venue"
},
  "geometry": {"coordinates":[-101.296035,48.23766],"type":"Point"}
}