{
  "type": "Feature",
  "properties": {
    "addr:full":"244 14th Ave NE Jamestown ND 58401",
    "addr:housenumber":"244",
    "addr:postcode":"58401",
    "addr:street":"14Th Ave Ne",
    "iso:country":"US",
    "sg:address":"244 14th Ave NE",
    "sg:city":"Jamestown",
    "sg:classifiers":[
        {
            "category":"Building & Trades",
            "subcategory":"Cleaning & Sanitation",
            "type":"Services"
        }
    ],
    "sg:phone":"+1 701 252 0252",
    "sg:postcode":"58401",
    "sg:province":"ND",
    "sg:tags":[
        "ventilating",
        "system"
    ],
    "wof:name":"American Airduct Svc",
    "wof:placetype":"venue"
},
  "geometry": {"coordinates":[-98.68888800000001,46.910087],"type":"Point"}
}