{
  "type": "Feature",
  "properties": {
    "iso:country":"US",
    "sg:address":"204 E Ash Ave",
    "sg:city":"Glen Ullin",
    "sg:classifiers":[
        {
            "category":"Organizations",
            "subcategory":"Religious Organization",
            "type":"Services"
        }
    ],
    "sg:phone":"+1 701 348 3527",
    "sg:postcode":"58631",
    "sg:province":"ND",
    "sg:tags":[
        "church"
    ],
    "wof:name":"Sacred Heart Church",
    "wof:placetype":"venue"
},
  "geometry": {"coordinates":[-101.827758,46.813949],"type":"Point"}
}