{
  "type": "Feature",
  "properties": {
    "iso:country":"US",
    "sg:address":"7081 91st Ave SE",
    "sg:city":"Berlin",
    "sg:phone":"+1 701 883 4376",
    "sg:postcode":"58415",
    "sg:province":"ND",
    "sg:tags":[
        "farm",
        "wheat"
    ],
    "wof:name":"Allen Swiontek",
    "wof:placetype":"venue"
},
  "geometry": {"coordinates":[-98.51559,46.387018],"type":"Point"}
}