{
  "type": "Feature",
  "properties": {
    "iso:country":"US",
    "sg:address":"13989 98th St SE",
    "sg:city":"Havana",
    "sg:classifiers":[
        {
            "category":"Farming",
            "subcategory":"Farm",
            "type":"Manufacturing & Wholesale Goods"
        }
    ],
    "sg:phone":"+1 701 724 6343",
    "sg:postcode":"58043",
    "sg:province":"ND",
    "wof:name":"Joe Breker Farm",
    "wof:placetype":"venue"
},
  "geometry": {"coordinates":[-97.46230300000001,45.994157],"type":"Point"}
}