{
  "type": "Feature",
  "properties": {
    "iso:country":"US",
    "sg:address":"180 10th Ave NE",
    "sg:city":"Mc Clusky",
    "sg:classifiers":[
        {
            "category":"Real Estate",
            "subcategory":"Real Estate Operator",
            "type":"Services"
        }
    ],
    "sg:phone":"+1 701 363 2538",
    "sg:postcode":"58463",
    "sg:province":"ND",
    "sg:tags":[
        "property",
        "lessor"
    ],
    "wof:name":"Clarence Heitzmann Farm",
    "wof:placetype":"venue"
},
  "geometry": {"coordinates":[-100.331256,47.443232],"type":"Point"}
}