{
  "type": "Feature",
  "properties": {
    "iso:country":"US",
    "sg:address":"808 Rollin Ave SW",
    "sg:city":"Cooperstown",
    "sg:classifiers":[
        {
            "category":"Government",
            "subcategory":"Police Station",
            "type":"Public Place"
        }
    ],
    "sg:phone":"+1 701 797 3311",
    "sg:postcode":"58425",
    "sg:province":"ND",
    "sg:tags":[
        "protection"
    ],
    "wof:name":"County of Griggs",
    "wof:placetype":"venue"
},
  "geometry": {"coordinates":[-98.125287,47.442424],"type":"Point"}
}