{
  "type": "Feature",
  "properties": {
    "iso:country":"US",
    "sg:address":"1510 12th St N",
    "sg:city":"Fargo",
    "sg:classifiers":[
        {
            "category":"Government",
            "subcategory":"Office",
            "type":"Public Place"
        }
    ],
    "sg:phone":"+1 701 231 6000",
    "sg:postcode":"58102",
    "sg:province":"ND",
    "sg:tags":[
        "state",
        "inspection"
    ],
    "sg:website":"www.ndisonline.org",
    "wof:name":"Independent Study",
    "wof:placetype":"venue"
},
  "geometry": {"coordinates":[-96.796668,46.899247],"type":"Point"}
}