{
  "type": "Feature",
  "properties": {
    "addr:full":"1801 6th Ave S Fargo ND 58103",
    "addr:housenumber":"1801",
    "addr:postcode":"58103",
    "addr:street":"6Th Ave S",
    "iso:country":"US",
    "sg:address":"1801 6th Ave S",
    "sg:city":"Fargo",
    "sg:classifiers":[
        {
            "category":"Banks & Credit Unions",
            "subcategory":"Investment Brokerage",
            "type":"Services"
        }
    ],
    "sg:phone":"+1 701 237 3230",
    "sg:postcode":"58103",
    "sg:province":"ND",
    "sg:tags":[
        "mortgage"
    ],
    "wof:name":"General Maint & Mtge Servicing",
    "wof:placetype":"venue"
},
  "geometry": {"coordinates":[-96.81092700000001,46.86883],"type":"Point"}
}