{
  "type": "Feature",
  "properties": {
    "addr:full":"4141 38th St S Ste B2 Fargo ND 58104",
    "addr:housenumber":"4141",
    "addr:postcode":"58104",
    "addr:street":"38Th St S Ste B2",
    "iso:country":"US",
    "sg:address":"4141 38th St S Ste B2",
    "sg:city":"Fargo",
    "sg:classifiers":[
        {
            "category":"Professional",
            "subcategory":"Advertising",
            "type":"Services"
        },
        {
            "category":"Professional",
            "subcategory":"Business Services",
            "type":"Services"
        }
    ],
    "sg:phone":"+1 701 451 0663",
    "sg:postcode":"58104",
    "sg:province":"ND",
    "sg:tags":[
        "mail",
        "direct",
        "shipping"
    ],
    "sg:website":"http://www.dakotamailing.com",
    "wof:name":"Dakota Mailing & Shipping Eqpt",
    "wof:placetype":"venue"
},
  "geometry": {"coordinates":[-96.84034800000001,46.817391],"type":"Point"}
}