{
  "type": "Feature",
  "properties": {
    "iso:country":"US",
    "sg:address":"21 1st Ave SE",
    "sg:city":"Minot",
    "sg:classifiers":[
        {
            "category":"Social Services",
            "subcategory":"Adult Care",
            "type":"Services"
        },
        {
            "category":"Social Services",
            "type":"Services"
        }
    ],
    "sg:phone":"+1 701 852 3323",
    "sg:postcode":"58701",
    "sg:province":"ND",
    "sg:tags":[
        "organization",
        "senior",
        "citizen"
    ],
    "wof:name":"Senior Citizens League",
    "wof:placetype":"venue"
},
  "geometry": {"coordinates":[-101.292823,48.235494],"type":"Point"}
}