{
  "type": "Feature",
  "properties": {
    "addr:full":"401 W Main St Mandan ND 58554",
    "addr:housenumber":"401",
    "addr:postcode":"58554",
    "addr:street":"W Main St",
    "iso:country":"US",
    "sg:address":"401 W Main St",
    "sg:city":"Mandan",
    "sg:classifiers":[
        {
            "category":"Recreation",
            "type":"Entertainment"
        }
    ],
    "sg:phone":"+1 701 663 9344",
    "sg:postcode":"58554",
    "sg:province":"ND",
    "wof:name":"Gaming Division",
    "wof:placetype":"venue"
},
  "geometry": {"coordinates":[-100.894457,46.825787],"type":"Point"}
}