{
  "type": "Feature",
  "properties": {
    "iso:country":"US",
    "sg:address":"1025 N 3rd St",
    "sg:city":"Bismarck",
    "sg:classifiers":[
        {
            "category":"Education",
            "subcategory":"Special Training",
            "type":"Public Place"
        }
    ],
    "sg:phone":"+1 701 222 0977",
    "sg:postcode":"58501",
    "sg:province":"ND",
    "sg:tags":[
        "management"
    ],
    "wof:name":"Corporate Human Svc",
    "wof:placetype":"venue"
},
  "geometry": {"coordinates":[-100.787357,46.816307],"type":"Point"}
}