{
  "type": "Feature",
  "properties": {
    "iso:country":"US",
    "sg:address":"3936 138th Ave SE",
    "sg:city":"Buffalo",
    "sg:phone":"+1 701 633 5435",
    "sg:postcode":"58011",
    "sg:province":"ND",
    "sg:tags":[
        "farm",
        "corn",
        "wheat",
        "soybean"
    ],
    "wof:name":"Zaun Farm Inc",
    "wof:placetype":"venue"
},
  "geometry": {"coordinates":[-97.57695,46.841733],"type":"Point"}
}