{
  "type": "Feature",
  "properties": {
    "addr:full":"162 9th Ave E Dickinson ND 58601",
    "addr:housenumber":"162",
    "addr:postcode":"58601",
    "addr:street":"9Th Ave E",
    "iso:country":"US",
    "sg:address":"162 9th Ave E",
    "sg:city":"Dickinson",
    "sg:classifiers":[
        {
            "category":"Building & Trades",
            "subcategory":"Construction",
            "type":"Services"
        }
    ],
    "sg:phone":"+1 701 483 3700",
    "sg:postcode":"58601",
    "sg:province":"ND",
    "sg:tags":[
        "general",
        "contractor"
    ],
    "wof:name":"X-Cel Construction",
    "wof:placetype":"venue"
},
  "geometry": {"coordinates":[-102.77089599999999,46.880337],"type":"Point"}
}