{
  "type": "Feature",
  "properties": {
    "iso:country":"US",
    "sg:address":"401 Center St",
    "sg:city":"Wimbledon",
    "sg:classifiers":[
        {
            "category":"Food & Beverages",
            "subcategory":"Groceries & Convenience Stores",
            "type":"Retail Goods"
        }
    ],
    "sg:phone":"+1 701 435 2464",
    "sg:postcode":"58492",
    "sg:province":"ND",
    "sg:tags":[
        "grocer"
    ],
    "wof:name":"M & J's Grocery",
    "wof:placetype":"venue"
},
  "geometry": {"coordinates":[-98.45826599999999,47.169114],"type":"Point"}
}