{
  "type": "Feature",
  "properties": {
    "addr:full":"15 13th St N Oakes SD 58474",
    "addr:housenumber":"15",
    "addr:postcode":"58474",
    "addr:street":"13Th St N",
    "iso:country":"US",
    "sg:address":"15 13th St N",
    "sg:city":"Oakes",
    "sg:classifiers":[
        {
            "category":"Personal",
            "subcategory":"Beauty Salon",
            "type":"Services"
        }
    ],
    "sg:phone":"+1 701 742 2320",
    "sg:postcode":"58474",
    "sg:province":"SD",
    "sg:tags":[
        "shop"
    ],
    "wof:name":"Cutting Loose By Tracie",
    "wof:placetype":"venue"
},
  "geometry": {"coordinates":[-98.081614,46.139188],"type":"Point"}
}