{
  "type": "Feature",
  "properties": {
    "addr:full":"417 Main Ave Fargo ND 58103",
    "addr:housenumber":"417",
    "addr:postcode":"58103",
    "addr:street":"Main Ave",
    "iso:country":"US",
    "sg:address":"417 Main Ave",
    "sg:city":"Fargo",
    "sg:classifiers":[
        {
            "category":"Shopping",
            "subcategory":"Computers & Home Electronics",
            "type":"Retail Goods"
        }
    ],
    "sg:phone":"+1 701 232 6631",
    "sg:postcode":"58103",
    "sg:province":"ND",
    "sg:tags":[
        "software"
    ],
    "wof:name":"Diamond Municipal Solutions",
    "wof:placetype":"venue"
},
  "geometry": {"coordinates":[-96.787978,46.874452],"type":"Point"}
}