{
  "type": "Feature",
  "properties": {
    "iso:country":"US",
    "sg:address":"1210 N 18th St",
    "sg:city":"Bismarck",
    "sg:classifiers":[
        {
            "category":"Shopping",
            "subcategory":"Computers & Home Electronics",
            "type":"Retail Goods"
        }
    ],
    "sg:phone":"+1 701 223 8047",
    "sg:postcode":"58501",
    "sg:province":"ND",
    "sg:tags":[
        "parts",
        "supply"
    ],
    "wof:name":"Ken's Laser Recharge",
    "wof:placetype":"venue"
},
  "geometry": {"coordinates":[-100.76484000000001,46.81871],"type":"Point"}
}