{
  "type": "Feature",
  "properties": {
    "addr:full":"333 1st St NE Garrison ND 58540",
    "addr:housenumber":"333",
    "addr:postcode":"58540",
    "addr:street":"1St St Ne",
    "iso:country":"US",
    "sg:address":"333 1st St NE",
    "sg:city":"Garrison",
    "sg:classifiers":[
        {
            "category":"Social Services",
            "subcategory":"Adult Care",
            "type":"Services"
        }
    ],
    "sg:phone":"+1 701 463 7381",
    "sg:postcode":"58540",
    "sg:province":"ND",
    "sg:tags":[
        "residential"
    ],
    "wof:name":"Behles Adult Foster Care",
    "wof:placetype":"venue"
},
  "geometry": {"coordinates":[-101.415898,47.65465],"type":"Point"}
}