{
  "type": "Feature",
  "properties": {
    "iso:country":"US",
    "sg:address":"315 1st St SE",
    "sg:city":"Lamoure",
    "sg:classifiers":[
        {
            "category":"Health Services",
            "subcategory":"Nursing And Care Facility",
            "type":"Services"
        }
    ],
    "sg:phone":"+1 701 883 5363",
    "sg:postcode":"58458",
    "sg:province":"ND",
    "sg:tags":[
        "home",
        "retirement",
        "community"
    ],
    "sg:website":"www.bhshealth.org",
    "wof:name":"St Rose Care Ctr",
    "wof:placetype":"venue"
},
  "geometry": {"coordinates":[-98.293014,46.355131],"type":"Point"}
}