{
  "type": "Feature",
  "properties": {
    "iso:country":"US",
    "sg:address":"153 N Main St",
    "sg:city":"Garrison",
    "sg:classifiers":[
        {
            "category":"Cinema",
            "subcategory":"Movie Theater",
            "type":"Entertainment"
        }
    ],
    "sg:phone":"+1 701 463 7356",
    "sg:postcode":"58540",
    "sg:province":"ND",
    "wof:name":"Saca KOTA Theater",
    "wof:placetype":"venue"
},
  "geometry": {"coordinates":[-101.417455,47.652918],"type":"Point"}
}