{
  "type": "Feature",
  "properties": {
    "iso:country":"US",
    "sg:address":"185 Summer Ave",
    "sg:city":"Carrington",
    "sg:classifiers":[
        {
            "category":"Farming",
            "subcategory":"Farm",
            "type":"Manufacturing & Wholesale Goods"
        }
    ],
    "sg:phone":"+1 701 984 2483",
    "sg:postcode":"58421",
    "sg:province":"ND",
    "wof:name":"Wendell Linderman Farm",
    "wof:placetype":"venue"
},
  "geometry": {"coordinates":[-99.13975000000001,47.570716],"type":"Point"}
}