{
  "type": "Feature",
  "properties": {
    "addr:full":"21 7th St N Oakes SD 58474",
    "addr:housenumber":"21",
    "addr:postcode":"58474",
    "addr:street":"7Th St N",
    "iso:country":"US",
    "sg:address":"21 7th St N",
    "sg:city":"Oakes",
    "sg:classifiers":[
        {
            "category":"Health Services",
            "subcategory":"Hospital",
            "type":"Services"
        }
    ],
    "sg:phone":"+1 701 742 2859",
    "sg:postcode":"58474",
    "sg:province":"SD",
    "wof:name":"Oakes Community Hospital Dev",
    "wof:placetype":"venue"
},
  "geometry": {"coordinates":[-98.090571,46.139156],"type":"Point"}
}