{
  "type": "Feature",
  "properties": {
    "iso:country":"US",
    "sg:address":"509 5th St N",
    "sg:city":"New Town",
    "sg:classifiers":[
        {
            "category":"Education",
            "subcategory":"School",
            "type":"Public Place"
        }
    ],
    "sg:phone":"+1 701 627 3642",
    "sg:postcode":"58763",
    "sg:province":"ND",
    "wof:name":"Little Lodge Head Start",
    "wof:placetype":"venue"
},
  "geometry": {"coordinates":[-102.482687,47.984506],"type":"Point"}
}