{
  "type": "Feature",
  "properties": {
    "addr:full":"2105 N Broadway Minot ND 58703",
    "addr:housenumber":"2105",
    "addr:postcode":"58703",
    "addr:street":"N Broadway",
    "iso:country":"US",
    "sg:address":"2105 N Broadway",
    "sg:city":"Minot",
    "sg:classifiers":[
        {
            "category":"Shopping",
            "type":"Retail Goods"
        }
    ],
    "sg:phone":"+1 701 839 3474",
    "sg:postcode":"58703",
    "sg:province":"ND",
    "sg:tags":[
        "pet",
        "shop"
    ],
    "wof:name":"Purr Fect Pets Inc",
    "wof:placetype":"venue"
},
  "geometry": {"coordinates":[-101.29606699999999,48.258478],"type":"Point"}
}