{
  "type": "Feature",
  "properties": {
    "iso:country":"US",
    "sg:address":"13777 62nd St SE",
    "sg:city":"Sheldon",
    "sg:phone":"+1 701 437 3176",
    "sg:postcode":"58068",
    "sg:province":"ND",
    "sg:tags":[
        "farm",
        "corn"
    ],
    "wof:name":"Dwight Krueger",
    "wof:placetype":"venue"
},
  "geometry": {"coordinates":[-97.53245200000001,46.51487],"type":"Point"}
}