{
  "type": "Feature",
  "properties": {
    "addr:full":"35 Sims St Dickinson ND 58601",
    "addr:housenumber":"35",
    "addr:postcode":"58601",
    "addr:street":"Sims St",
    "iso:country":"US",
    "sg:address":"35 Sims St",
    "sg:city":"Dickinson",
    "sg:classifiers":[
        {
            "category":"Retail",
            "subcategory":"Portrait Studio",
            "type":"Services"
        }
    ],
    "sg:phone":"+1 701 483 3566",
    "sg:postcode":"58601",
    "sg:province":"ND",
    "sg:tags":[
        "photographer"
    ],
    "wof:name":"Photos By Jonathan",
    "wof:placetype":"venue"
},
  "geometry": {"coordinates":[-102.785634,46.879076],"type":"Point"}
}