{
  "type": "Feature",
  "properties": {
    "iso:country":"US",
    "sg:address":"203 10th St N",
    "sg:city":"Fargo",
    "sg:classifiers":[
        {
            "category":"Insurance",
            "subcategory":"Insurance Agent",
            "type":"Services"
        }
    ],
    "sg:phone":"+1 701 235 2085",
    "sg:postcode":"58102",
    "sg:province":"ND",
    "wof:name":"Noridian Mutual Insurance",
    "wof:placetype":"venue"
},
  "geometry": {"coordinates":[-96.793942,46.879426],"type":"Point"}
}