{
  "type": "Feature",
  "properties": {
    "addr:full":"501 Main Ave Napoleon ND 58561",
    "addr:housenumber":"501",
    "addr:postcode":"58561",
    "addr:street":"Main Ave",
    "iso:country":"US",
    "sg:address":"501 Main Ave",
    "sg:city":"Napoleon",
    "sg:classifiers":[
        {
            "category":"Recreation",
            "type":"Entertainment"
        }
    ],
    "sg:phone":"+1 701 754 9556",
    "sg:postcode":"58561",
    "sg:province":"ND",
    "sg:tags":[
        "pool",
        "swimming"
    ],
    "wof:name":"Napoleon Swimming Pool",
    "wof:placetype":"venue"
},
  "geometry": {"coordinates":[-99.775745,46.502542],"type":"Point"}
}