{
  "type": "Feature",
  "properties": {
    "iso:country":"US",
    "sg:address":"1310 E Main St",
    "sg:city":"Mandan",
    "sg:classifiers":[
        {
            "category":"Insurance",
            "subcategory":"Insurance Agent",
            "type":"Services"
        }
    ],
    "sg:phone":"+1 701 663 1146",
    "sg:postcode":"58554",
    "sg:province":"ND",
    "wof:name":"Rod Skytland Insurance Inc",
    "wof:placetype":"venue"
},
  "geometry": {"coordinates":[-100.87255500000001,46.828817],"type":"Point"}
}