{
  "type": "Feature",
  "properties": {
    "addr:full":"5060 97th St SE Ashley ND 58413",
    "addr:housenumber":"5060",
    "addr:postcode":"58413",
    "addr:street":"97Th St Se",
    "iso:country":"US",
    "sg:address":"5060 97th St SE",
    "sg:city":"Ashley",
    "sg:classifiers":[
        {
            "category":"Farming",
            "subcategory":"Livestock Farm",
            "type":"Manufacturing & Wholesale Goods"
        }
    ],
    "sg:phone":"+1 701 288 3011",
    "sg:postcode":"58413",
    "sg:province":"ND",
    "sg:tags":[
        "beef",
        "feedlot",
        "cattle"
    ],
    "wof:name":"Randy Ulmer",
    "wof:placetype":"venue"
},
  "geometry": {"coordinates":[-99.32390700000001,46.012536],"type":"Point"}
}