{
  "type": "Feature",
  "properties": {
    "iso:country":"US",
    "sg:address":"6122 25th Ave",
    "sg:city":"Solen",
    "sg:classifiers":[
        {
            "category":"Farming",
            "subcategory":"Livestock Farm",
            "type":"Manufacturing & Wholesale Goods"
        }
    ],
    "sg:phone":"+1 701 445 7448",
    "sg:postcode":"58570",
    "sg:province":"ND",
    "sg:tags":[
        "beef",
        "feedlot",
        "cattle"
    ],
    "wof:name":"Judy Gangl",
    "wof:placetype":"venue"
},
  "geometry": {"coordinates":[-100.944264,46.566995],"type":"Point"}
}