{
  "type": "Feature",
  "properties": {
    "addr:city":"Grand Forks",
    "addr:full":"261 Centennial Dr Grand Forks, Nd 58202",
    "addr:house_number":"261",
    "addr:housenumber":"261",
    "addr:phone":"+1 701-777-4195",
    "addr:postcode":"58202",
    "addr:road":"Centennial Dr",
    "addr:state":"ND",
    "addr:street":"Centennial Dr",
    "iso:country":"US",
    "sg:address":"261 Centennial Dr",
    "sg:city":"Grand Forks",
    "sg:classifiers":[
        {
            "category":"Museum",
            "type":"Entertainment"
        }
    ],
    "sg:phone":"+1 701 777 4195",
    "sg:postcode":"58203",
    "sg:province":"ND",
    "sg:website":"www.ndmoa.com",
    "wof:airports":[
        102528343
    ],
    "wof:name":"North Dakota Museum Of Art",
    "wof:placetype":"venue"
},
  "geometry": {"coordinates":[-97.07101,47.92176],"type":"Point"}
}