{
  "type": "Feature",
  "properties": {
    "addr:full":"261 Centennial Dr Grand Forks ND 58203",
    "addr:housenumber":"261",
    "addr:postcode":"58203",
    "addr:street":"Centennial Dr",
    "iso:country":"US",
    "sg:address":"261 Centennial Dr",
    "sg:city":"Grand Forks",
    "sg:classifiers":[
        {
            "category":"Museum",
            "type":"Entertainment"
        }
    ],
    "sg:phone":"+1 701 777 4195",
    "sg:postcode":"58203",
    "sg:province":"ND",
    "sg:website":"www.ndmoa.com",
    "wof:name":"North Dakota Museum Of Art",
    "wof:placetype":"venue"
},
  "geometry": {"coordinates":[-97.070999,47.921612],"type":"Point"}
}