{
  "type": "Feature",
  "properties": {
    "iso:country":"US",
    "sg:address":"926 2nd St S",
    "sg:city":"Wahpeton",
    "sg:classifiers":[
        {
            "category":"Social Services",
            "subcategory":"Child Care",
            "type":"Services"
        }
    ],
    "sg:phone":"+1 701 642 5835",
    "sg:postcode":"58075",
    "sg:province":"ND",
    "sg:tags":[
        "day"
    ],
    "wof:name":"Hagens Family Day Care",
    "wof:placetype":"venue"
},
  "geometry": {"coordinates":[-96.602934,46.256033],"type":"Point"}
}