{
  "type": "Feature",
  "properties": {
    "iso:country":"US",
    "sg:address":"1725 Broadway",
    "sg:city":"Fargo",
    "sg:classifiers":[
        {
            "category":"Education",
            "subcategory":"School",
            "type":"Public Place"
        }
    ],
    "sg:phone":"+1 701 446 5441",
    "sg:postcode":"58102",
    "sg:province":"ND",
    "wof:name":"Fargo Public Sch Dist No 1",
    "wof:placetype":"venue"
},
  "geometry": {"coordinates":[-96.787397,46.902557],"type":"Point"}
}