{
  "type": "Feature",
  "properties": {
    "iso:country":"US",
    "sg:address":"2800 S Columbia Rd",
    "sg:city":"Grand Forks",
    "sg:classifiers":[
        {
            "category":"Shopping",
            "type":"Retail Goods"
        }
    ],
    "sg:phone":"+1 701 780 2292",
    "sg:postcode":"58201",
    "sg:province":"ND",
    "sg:tags":[
        "sunglasses",
        "accessory"
    ],
    "wof:name":"Sunglass Hut 2507",
    "wof:placetype":"venue"
},
  "geometry": {"coordinates":[-97.06670699999999,47.889454],"type":"Point"}
}