{
  "type": "Feature",
  "properties": {
    "addr:full":"1310 41st St NW Jamestown ND 58401",
    "addr:housenumber":"1310",
    "addr:postcode":"58401",
    "addr:street":"41St St Nw",
    "iso:country":"US",
    "sg:address":"1310 41st St NW",
    "sg:city":"Jamestown",
    "sg:classifiers":[
        {
            "category":"Professional",
            "subcategory":"Art Services",
            "type":"Services"
        }
    ],
    "sg:phone":"+1 701 253 8265",
    "sg:postcode":"58401",
    "sg:province":"ND",
    "sg:tags":[
        "design"
    ],
    "wof:name":"Bohl Ironworks LLC",
    "wof:placetype":"venue"
},
  "geometry": {"coordinates":[-98.733042,46.950076],"type":"Point"}
}