{
  "type": "Feature",
  "properties": {
    "addr:full":"403 Walnut St W Devils Lake ND 58301",
    "addr:housenumber":"403",
    "addr:postcode":"58301",
    "addr:street":"Walnut St W",
    "iso:country":"US",
    "sg:address":"403 Walnut St W",
    "sg:city":"Devils Lake",
    "sg:classifiers":[
        {
            "category":"Restaurant",
            "type":"Food & Drink"
        }
    ],
    "sg:menulink":"http://www.allmenus.com/nd/devils-lake/183479-kfc---kentucky-fried-chicken/menu/",
    "sg:phone":"+1 701 662 2675",
    "sg:postcode":"58301",
    "sg:province":"ND",
    "sg:tags":[
        "american",
        "chicken"
    ],
    "wof:name":"KFC - Kentucky Fried Chicken",
    "wof:placetype":"venue"
},
  "geometry": {"coordinates":[-98.86882199999999,48.107756],"type":"Point"}
}