{
  "type": "Feature",
  "properties": {
    "iso:country":"US",
    "sg:address":"522 Southview Ct",
    "sg:city":"Thompson",
    "sg:classifiers":[
        {
            "category":"Organizations",
            "subcategory":"Community Association",
            "type":"Services"
        }
    ],
    "sg:phone":"+1 701 780 8229",
    "sg:postcode":"58278",
    "sg:province":"ND",
    "wof:name":"North Dakota Agri Women",
    "wof:placetype":"venue"
},
  "geometry": {"coordinates":[-97.103891,47.772319],"type":"Point"}
}