{
  "type": "Feature",
  "properties": {
    "addr:full":"3400 Broadway N Fargo ND 58102",
    "addr:housenumber":"3400",
    "addr:postcode":"58102",
    "addr:street":"Broadway N",
    "iso:country":"US",
    "sg:address":"3400 Broadway N",
    "sg:city":"Fargo",
    "sg:classifiers":[
        {
            "category":"Government",
            "subcategory":"Office",
            "type":"Public Place"
        }
    ],
    "sg:phone":"+1 701 241 1454",
    "sg:postcode":"58102",
    "sg:province":"ND",
    "sg:tags":[
        "township",
        "government-city",
        "village"
    ],
    "sg:website":"http://www.cityoffargo.com",
    "wof:name":"Waste Water Department",
    "wof:placetype":"venue"
},
  "geometry": {"coordinates":[-96.786779,46.921515],"type":"Point"}
}