{
  "type": "Feature",
  "properties": {
    "iso:country":"US",
    "sg:address":"3774 67th Ave SE",
    "sg:city":"Cleveland",
    "sg:classifiers":[
        {
            "category":"Farming",
            "subcategory":"Dairy Farm",
            "type":"Manufacturing & Wholesale Goods"
        }
    ],
    "sg:phone":"+1 701 763 6265",
    "sg:postcode":"58424",
    "sg:province":"ND",
    "wof:name":"Wanzek Dairy",
    "wof:placetype":"venue"
},
  "geometry": {"coordinates":[-99.051433,46.866361],"type":"Point"}
}