{
  "type": "Feature",
  "properties": {
    "iso:country":"US",
    "sg:address":"28 N Main St",
    "sg:city":"Bowman",
    "sg:classifiers":[
        {
            "category":"Personal",
            "subcategory":"Beauty Salon",
            "type":"Services"
        }
    ],
    "sg:phone":"+1 701 523 3247",
    "sg:postcode":"58623",
    "sg:province":"ND",
    "wof:name":"Classic Beauty Salon",
    "wof:placetype":"venue"
},
  "geometry": {"coordinates":[-103.39490600000001,46.182953],"type":"Point"}
}