{
  "type": "Feature",
  "properties": {
    "iso:country":"US",
    "sg:address":"1702 E Main St",
    "sg:city":"Mandan",
    "sg:classifiers":[
        {
            "category":"Building & Trades",
            "subcategory":"Construction",
            "type":"Services"
        }
    ],
    "sg:phone":"+1 701 663 2295",
    "sg:postcode":"58554",
    "sg:province":"ND",
    "sg:tags":[
        "siding",
        "contractor"
    ],
    "wof:name":"Dakota Siding",
    "wof:placetype":"venue"
},
  "geometry": {"coordinates":[-100.88077699999999,46.82773],"type":"Point"}
}