{
  "type": "Feature",
  "properties": {
    "iso:country":"US",
    "sg:address":"124 N 3rd St",
    "sg:city":"Grand Forks",
    "sg:classifiers":[
        {
            "category":"Professional",
            "subcategory":"Engineering",
            "type":"Services"
        }
    ],
    "sg:phone":"+1 701 775 2594",
    "sg:postcode":"58203",
    "sg:province":"ND",
    "sg:tags":[
        "engineer"
    ],
    "wof:name":"Haack Engineering",
    "wof:placetype":"venue"
},
  "geometry": {"coordinates":[-97.032642,47.92649],"type":"Point"}
}