{
  "type": "Feature",
  "properties": {
    "iso:country":"US",
    "sg:address":"1839 E Capitol Ave",
    "sg:city":"Bismarck",
    "sg:classifiers":[
        {
            "category":"Health Services",
            "subcategory":"Doctor",
            "type":"Services"
        }
    ],
    "sg:phone":"+1 701 255 4850",
    "sg:postcode":"58501",
    "sg:province":"ND",
    "sg:tags":[
        "dentist"
    ],
    "wof:name":"Bismarck Ctr-Laser & Cosmetic",
    "wof:placetype":"venue"
},
  "geometry": {"coordinates":[-100.76394999999999,46.830691],"type":"Point"}
}