{
  "type": "Feature",
  "properties": {
    "iso:country":"US",
    "sg:address":"3312 42nd St S Suite 100",
    "sg:city":"Fargo",
    "sg:classifiers":[
        {
            "category":"Utilities",
            "subcategory":"Mobile Phone",
            "type":"Services"
        },
        {
            "category":"Utilities",
            "subcategory":"Telephone",
            "type":"Services"
        },
        {
            "category":"Professional",
            "subcategory":"Computer Services",
            "type":"Services"
        }
    ],
    "sg:phone":"+1 701 356 6000",
    "sg:postcode":"58104",
    "sg:province":"ND",
    "sg:tags":[
        "communication",
        "isp",
        "provider",
        "cellular",
        "internet"
    ],
    "sg:website":"http://www.ideaone.com",
    "wof:name":"IdeaOne Telecom",
    "wof:placetype":"venue"
},
  "geometry": {"coordinates":[-96.85144099999999,46.829696],"type":"Point"}
}