{
  "type": "Feature",
  "properties": {
    "addr:full":"6710 44th Ave NE Wolford ND 58385",
    "addr:housenumber":"6710",
    "addr:postcode":"58385",
    "addr:street":"44Th Ave Ne",
    "iso:country":"US",
    "sg:address":"6710 44th Ave NE",
    "sg:city":"Wolford",
    "sg:phone":"+1 701 583 2834",
    "sg:postcode":"58385",
    "sg:province":"ND",
    "sg:tags":[
        "farm",
        "wheat"
    ],
    "wof:name":"William S Mahle",
    "wof:placetype":"venue"
},
  "geometry": {"coordinates":[-99.711005,48.38558],"type":"Point"}
}