{
  "type": "Feature",
  "properties": {
    "addr:full":"6700 2nd Ave W Williston ND 58801",
    "addr:housenumber":"6700",
    "addr:postcode":"58801",
    "addr:street":"2Nd Ave W",
    "iso:country":"US",
    "sg:address":"6700 2nd Ave W",
    "sg:city":"Williston",
    "sg:classifiers":[
        {
            "category":"Travel",
            "subcategory":"Campground",
            "type":"Entertainment"
        }
    ],
    "sg:phone":"+1 701 572 3206",
    "sg:postcode":"58801",
    "sg:province":"ND",
    "wof:name":"Buffalo Trails Campground",
    "wof:placetype":"venue"
},
  "geometry": {"coordinates":[-103.623368,48.207743],"type":"Point"}
}