{
  "type": "Feature",
  "properties": {
    "iso:country":"US",
    "sg:address":"8875 24th Ave NW",
    "sg:city":"Maxbass",
    "sg:phone":"+1 701 268 3336",
    "sg:postcode":"58760",
    "sg:province":"ND",
    "sg:tags":[
        "wheat",
        "farm",
        "cash",
        "crop",
        "field",
        "grain"
    ],
    "wof:name":"Streich Farms",
    "wof:placetype":"venue"
},
  "geometry": {"coordinates":[-101.23379300000001,48.700855],"type":"Point"}
}