{
  "type": "Feature",
  "properties": {
    "iso:country":"US",
    "sg:address":"1431 35th St S",
    "sg:city":"Fargo",
    "sg:classifiers":[
        {
            "category":"Education",
            "subcategory":"Vocational School",
            "type":"Public Place"
        }
    ],
    "sg:phone":"+1 701 293 7647",
    "sg:postcode":"58103",
    "sg:province":"ND",
    "sg:tags":[
        "training",
        "computer"
    ],
    "wof:name":"Lee Business Consultants",
    "wof:placetype":"venue"
},
  "geometry": {"coordinates":[-96.83808399999999,46.858923],"type":"Point"}
}