{
  "type": "Feature",
  "properties": {
    "addr:full":"1015 N 39th St Grand Forks ND 58203",
    "addr:housenumber":"1015",
    "addr:postcode":"58203",
    "addr:street":"N 39Th St",
    "iso:country":"US",
    "sg:address":"1015 N 39th St",
    "sg:city":"Grand Forks",
    "sg:classifiers":[
        {
            "category":"Professional",
            "subcategory":"Lawyer & Legal Services",
            "type":"Services"
        }
    ],
    "sg:phone":"+1 701 746 6707",
    "sg:postcode":"58203",
    "sg:province":"ND",
    "sg:tags":[
        "attorney"
    ],
    "wof:name":"Shawn Ackre",
    "wof:placetype":"venue"
},
  "geometry": {"coordinates":[-97.086967,47.931139],"type":"Point"}
}