{
  "type": "Feature",
  "properties": {
    "addr:full":"917 Alder Ave Harvey ND 58341",
    "addr:housenumber":"917",
    "addr:postcode":"58341",
    "addr:street":"Alder Ave",
    "iso:country":"US",
    "sg:address":"917 Alder Ave",
    "sg:city":"Harvey",
    "sg:classifiers":[
        {
            "category":"Real Estate",
            "subcategory":"Real Estate Agent",
            "type":"Services"
        }
    ],
    "sg:phone":"+1 701 324 4799",
    "sg:postcode":"58341",
    "sg:province":"ND",
    "sg:tags":[
        "appraiser"
    ],
    "wof:name":"Northern Appraisal & Realty",
    "wof:placetype":"venue"
},
  "geometry": {"coordinates":[-99.937505,47.769291],"type":"Point"}
}