{
  "type": "Feature",
  "properties": {
    "iso:country":"US",
    "sg:address":"4435 Memorial Hwy",
    "sg:city":"Mandan",
    "sg:classifiers":[
        {
            "category":"Personal",
            "subcategory":"Beauty Salon",
            "type":"Services"
        }
    ],
    "sg:phone":"+1 701 667 0145",
    "sg:postcode":"58554",
    "sg:province":"ND",
    "sg:tags":[
        "shop"
    ],
    "wof:name":"Hair For You Salon & Wig Btq",
    "wof:placetype":"venue"
},
  "geometry": {"coordinates":[-100.83320399999999,46.809632],"type":"Point"}
}