{
  "type": "Feature",
  "properties": {
    "addr:full":"901 3rd St Langdon ND 58249",
    "addr:housenumber":"901",
    "addr:postcode":"58249",
    "addr:street":"3Rd St",
    "iso:country":"US",
    "sg:address":"901 3rd St",
    "sg:city":"Langdon",
    "sg:classifiers":[
        {
            "category":"Government",
            "subcategory":"Office",
            "type":"Public Place"
        }
    ],
    "sg:phone":"+1 701 256 2229",
    "sg:postcode":"58249",
    "sg:province":"ND",
    "sg:tags":[
        "executive"
    ],
    "wof:name":"Cavalier County Road Maint",
    "wof:placetype":"venue"
},
  "geometry": {"coordinates":[-98.368264,48.762175],"type":"Point"}
}