{
  "type": "Feature",
  "properties": {
    "iso:country":"US",
    "sg:address":"15621 67th St NE",
    "sg:city":"Grafton",
    "sg:classifiers":[
        {
            "category":"Building & Trades",
            "subcategory":"Landscaping Services",
            "type":"Services"
        }
    ],
    "sg:phone":"+1 701 352 0999",
    "sg:postcode":"58237",
    "sg:province":"ND",
    "wof:name":"SOS Yard & Tree Care",
    "wof:placetype":"venue"
},
  "geometry": {"coordinates":[-97.27245600000001,48.38319],"type":"Point"}
}