{
  "type": "Feature",
  "properties": {
    "addr:full":"12872 25th St S W Belfield ND 58622",
    "addr:housenumber":"12872",
    "addr:postcode":"58622",
    "addr:street":"25Th St",
    "iso:country":"US",
    "sg:address":"12872 25th St S W",
    "sg:city":"Belfield",
    "sg:classifiers":[
        {
            "category":"Building & Trades",
            "subcategory":"Construction",
            "type":"Services"
        }
    ],
    "sg:phone":"+1 701 575 4656",
    "sg:postcode":"58622",
    "sg:province":"ND",
    "wof:name":"Arthurs Unlimited",
    "wof:placetype":"venue"
},
  "geometry": {"coordinates":[-103.220553,47.052603],"type":"Point"}
}