{
  "type": "Feature",
  "properties": {
    "addr:full":"101 Main St W Beulah ND 58523",
    "addr:housenumber":"101",
    "addr:postcode":"58523",
    "addr:street":"Main St W",
    "iso:country":"US",
    "sg:address":"101 Main St W",
    "sg:city":"Beulah",
    "sg:classifiers":[
        {
            "category":"Sports & Exercise",
            "subcategory":"Gym",
            "type":"Entertainment"
        }
    ],
    "sg:phone":"+1 701 873 7734",
    "sg:postcode":"58523",
    "sg:province":"ND",
    "sg:tags":[
        "club",
        "health",
        "studio",
        "gymnasium"
    ],
    "wof:name":"In Joy",
    "wof:placetype":"venue"
},
  "geometry": {"coordinates":[-101.77969400000001,47.263476],"type":"Point"}
}