{
  "type": "Feature",
  "properties": {
    "iso:country":"US",
    "sg:address":"1851 23rd Ave NE",
    "sg:city":"Harvey",
    "sg:classifiers":[
        {
            "category":"Travel",
            "subcategory":"Campground",
            "type":"Entertainment"
        }
    ],
    "sg:phone":"+1 701 324 2211",
    "sg:postcode":"58341",
    "sg:province":"ND",
    "wof:name":"Lonetree Wildlife Campground",
    "wof:placetype":"venue"
},
  "geometry": {"coordinates":[-100.09108000000001,47.68223],"type":"Point"}
}