{
  "type": "Feature",
  "properties": {
    "iso:country":"US",
    "sg:address":"220 Main St",
    "sg:city":"Turtle Lake",
    "sg:classifiers":[
        {
            "category":"Government",
            "subcategory":"Office",
            "type":"Public Place"
        },
        {
            "category":"Manufacturing",
            "subcategory":"Printing",
            "type":"Manufacturing & Wholesale Goods"
        }
    ],
    "sg:phone":"+1 701 448 2649",
    "sg:postcode":"58575",
    "sg:province":"ND",
    "sg:tags":[
        "county",
        "newspaper"
    ],
    "wof:name":"Me Lean County Journal",
    "wof:placetype":"venue"
},
  "geometry": {"coordinates":[-100.890109,47.520701],"type":"Point"}
}