{
  "type": "Feature",
  "properties": {
    "iso:country":"US",
    "sg:address":"8620 47th St SW",
    "sg:city":"Richardton",
    "sg:classifiers":[
        {
            "category":"Travel",
            "subcategory":"Campground",
            "type":"Entertainment"
        }
    ],
    "sg:phone":"+1 701 974 7000",
    "sg:postcode":"58652",
    "sg:province":"ND",
    "sg:tags":[
        "camp"
    ],
    "wof:name":"Cattle River Ranch LLP",
    "wof:placetype":"venue"
},
  "geometry": {"coordinates":[-102.265743,46.73199],"type":"Point"}
}