{
  "type": "Feature",
  "properties": {
    "iso:country":"US",
    "sg:address":"321 W Edmonton Dr",
    "sg:city":"Bismarck",
    "sg:classifiers":[
        {
            "category":"Professional",
            "subcategory":"Management & Consulting",
            "type":"Services"
        }
    ],
    "sg:phone":"+1 701 255 2715",
    "sg:postcode":"58503",
    "sg:province":"ND",
    "wof:name":"Kadrmas Properties LLP",
    "wof:placetype":"venue"
},
  "geometry": {"coordinates":[-100.79815600000001,46.844832],"type":"Point"}
}