{
  "type": "Feature",
  "properties": {
    "addr:full":"5110 US Hwy 2 Bus Minot ND 58701",
    "addr:housenumber":"5110",
    "addr:postcode":"58701",
    "addr:street":"Us Hwy 2 Bus",
    "iso:country":"US",
    "sg:address":"5110 US Hwy 2 Bus",
    "sg:city":"Minot",
    "sg:classifiers":[
        {
            "category":"Professional",
            "type":"Services"
        }
    ],
    "sg:phone":"+1 701 839 2017",
    "sg:postcode":"58701",
    "sg:province":"ND",
    "sg:tags":[
        "establishment"
    ],
    "wof:name":"Abrahamson & Abrahamson",
    "wof:placetype":"venue"
},
  "geometry": {"coordinates":[-101.221619,48.229135],"type":"Point"}
}