{
  "type": "Feature",
  "properties": {
    "iso:country":"US",
    "sg:address":"2800 S Columbia Rd",
    "sg:city":"Grand Forks",
    "sg:classifiers":[
        {
            "category":"Real Estate",
            "subcategory":"Real Estate Operator",
            "type":"Services"
        }
    ],
    "sg:phone":"+1 701 746 7383",
    "sg:postcode":"58201",
    "sg:province":"ND",
    "sg:tags":[
        "mall",
        "shopping",
        "center"
    ],
    "wof:name":"Columbia Mall Shopping Ctr",
    "wof:placetype":"venue"
},
  "geometry": {"coordinates":[-97.06670699999999,47.889454],"type":"Point"}
}