{
  "type": "Feature",
  "properties": {
    "iso:country":"US",
    "sg:address":"3402 Interstate Blvd S",
    "sg:city":"Fargo",
    "sg:classifiers":[
        {
            "category":"Sports & Exercise",
            "subcategory":"Bowling",
            "type":"Entertainment"
        }
    ],
    "sg:phone":"+1 701 235 4437",
    "sg:postcode":"58103",
    "sg:province":"ND",
    "sg:tags":[
        "center"
    ],
    "sg:website":"http://www.westacresbowl.com",
    "wof:name":"West Acres Bowl",
    "wof:placetype":"venue"
},
  "geometry": {"coordinates":[-96.836522,46.864482],"type":"Point"}
}