{
  "type": "Feature",
  "properties": {
    "iso:country":"US",
    "sg:address":"800 State Hwy 1",
    "sg:city":"Binford",
    "sg:classifiers":[
        {
            "category":"Farming",
            "subcategory":"Farm",
            "type":"Manufacturing & Wholesale Goods"
        }
    ],
    "sg:phone":"+1 701 676 2636",
    "sg:postcode":"58416",
    "sg:province":"ND",
    "wof:name":"Kermit Helland Farm",
    "wof:placetype":"venue"
},
  "geometry": {"coordinates":[-98.32952,47.536634],"type":"Point"}
}