{
  "type": "Feature",
  "properties": {
    "iso:country":"US",
    "sg:address":"533 4th St",
    "sg:city":"Thompson",
    "sg:phone":"+1 701 599 2680",
    "sg:postcode":"58278",
    "sg:province":"ND",
    "sg:tags":[
        "farm",
        "wheat"
    ],
    "wof:name":"Bernard West",
    "wof:placetype":"venue"
},
  "geometry": {"coordinates":[-97.10186,47.7767],"type":"Point"}
}