{
  "type": "Feature",
  "properties": {
    "iso:country":"US",
    "sg:address":"205 Main St N",
    "sg:city":"Berthold",
    "sg:classifiers":[
        {
            "category":"Bars & Pubs",
            "type":"Food & Drink"
        }
    ],
    "sg:phone":"+1 701 453 3445",
    "sg:postcode":"58718",
    "sg:province":"ND",
    "wof:name":"Windbreak",
    "wof:placetype":"venue"
},
  "geometry": {"coordinates":[-101.736698,48.315371],"type":"Point"}
}