{
  "type": "Feature",
  "properties": {
    "iso:country":"US",
    "sg:address":"201 3rd St SW",
    "sg:city":"Rugby",
    "sg:classifiers":[
        {
            "category":"Education",
            "subcategory":"Library",
            "type":"Public Place"
        }
    ],
    "sg:phone":"+1 701 776 6223",
    "sg:postcode":"58368",
    "sg:province":"ND",
    "wof:name":"Heart Of America Library",
    "wof:placetype":"venue"
},
  "geometry": {"coordinates":[-99.99879199999999,48.367697],"type":"Point"}
}