{
  "type": "Feature",
  "properties": {
    "iso:country":"US",
    "sg:address":"113 S Main St",
    "sg:city":"Hettinger",
    "sg:classifiers":[
        {
            "category":"Wholesale",
            "subcategory":"Hardware",
            "type":"Manufacturing & Wholesale Goods"
        }
    ],
    "sg:phone":"+1 701 567 0099",
    "sg:postcode":"58639",
    "sg:province":"ND",
    "sg:tags":[
        "refrigerating"
    ],
    "wof:name":"Hettinger Heating & Air Refrig",
    "wof:placetype":"venue"
},
  "geometry": {"coordinates":[-102.636949,46.000305],"type":"Point"}
}