{
  "type": "Feature",
  "properties": {
    "addr:full":"6227 120th Ave NE Lankin ND 58250",
    "addr:housenumber":"6227",
    "addr:postcode":"58250",
    "addr:street":"120Th Ave Ne",
    "iso:country":"US",
    "sg:address":"6227 120th Ave NE",
    "sg:city":"Lankin",
    "sg:classifiers":[
        {
            "category":"Farming",
            "subcategory":"Dairy Farm",
            "type":"Manufacturing & Wholesale Goods"
        }
    ],
    "sg:phone":"+1 701 593 6274",
    "sg:postcode":"58250",
    "sg:province":"ND",
    "wof:name":"Jack Karas",
    "wof:placetype":"venue"
},
  "geometry": {"coordinates":[-98.03294699999999,48.310493],"type":"Point"}
}