{
  "type": "Feature",
  "properties": {
    "iso:country":"US",
    "sg:address":"5525 99th Ave NE",
    "sg:city":"Brocket",
    "sg:classifiers":[
        {
            "category":"Personal",
            "subcategory":"Beauty Salon",
            "type":"Services"
        }
    ],
    "sg:phone":"+1 701 655 3873",
    "sg:postcode":"58321",
    "sg:province":"ND",
    "sg:tags":[
        "shop"
    ],
    "wof:name":"Shear Country",
    "wof:placetype":"venue"
},
  "geometry": {"coordinates":[-98.487004,48.214706],"type":"Point"}
}