{
  "type": "Feature",
  "properties": {
    "iso:country":"US",
    "sg:address":"318 5th Ave NW",
    "sg:city":"Minot",
    "sg:classifiers":[
        {
            "category":"Social Services",
            "type":"Services"
        }
    ],
    "sg:phone":"+1 701 839 4660",
    "sg:postcode":"58703",
    "sg:province":"ND",
    "sg:tags":[
        "youth",
        "organization",
        "center"
    ],
    "wof:name":"Youth For Christ",
    "wof:placetype":"venue"
},
  "geometry": {"coordinates":[-101.29864000000001,48.241802],"type":"Point"}
}