{
  "type": "Feature",
  "properties": {
    "addr:full":"205 2nd Ave NW Mandan ND 58554",
    "addr:housenumber":"205",
    "addr:postcode":"58554",
    "addr:street":"2Nd Ave Nw",
    "iso:country":"US",
    "sg:address":"205 2nd Ave NW",
    "sg:city":"Mandan",
    "sg:classifiers":[
        {
            "category":"Government",
            "subcategory":"Office",
            "type":"Public Place"
        }
    ],
    "sg:phone":"+1 701 667 3225",
    "sg:postcode":"58554",
    "sg:province":"ND",
    "sg:tags":[
        "village"
    ],
    "wof:name":"Mandan City Engineer",
    "wof:placetype":"venue"
},
  "geometry": {"coordinates":[-100.89333499999999,46.828046],"type":"Point"}
}