{
  "type": "Feature",
  "properties": {
    "addr:full":"19 N Main St Bowman ND 58623",
    "addr:housenumber":"19",
    "addr:postcode":"58623",
    "addr:street":"N Main St",
    "iso:country":"US",
    "sg:address":"19 N Main St",
    "sg:city":"Bowman",
    "sg:classifiers":[
        {
            "category":"Shopping",
            "subcategory":"Hobbies, Toys, & Games",
            "type":"Retail Goods"
        }
    ],
    "sg:phone":"+1 701 523 3178",
    "sg:postcode":"58623",
    "sg:province":"ND",
    "sg:tags":[
        "craft",
        "supply"
    ],
    "wof:name":"Jim's Arts & Crafts",
    "wof:placetype":"venue"
},
  "geometry": {"coordinates":[-103.39505699999999,46.18304],"type":"Point"}
}