{
  "type": "Feature",
  "properties": {
    "iso:country":"US",
    "sg:address":"201 Volga St S",
    "sg:city":"Balta",
    "sg:classifiers":[
        {
            "category":"Farming",
            "subcategory":"Farm",
            "type":"Manufacturing & Wholesale Goods"
        }
    ],
    "sg:phone":"+1 701 542 3345",
    "sg:postcode":"58313",
    "sg:province":"ND",
    "wof:name":"Daryl Klein Farm",
    "wof:placetype":"venue"
},
  "geometry": {"coordinates":[-100.03895900000001,48.165286],"type":"Point"}
}