{
  "type": "Feature",
  "properties": {
    "addr:full":"3739 38th St SW Fargo ND 58104",
    "addr:housenumber":"3739",
    "addr:postcode":"58104",
    "addr:street":"38Th St Sw",
    "iso:country":"US",
    "sg:address":"3739 38th St SW",
    "sg:city":"Fargo",
    "sg:classifiers":[
        {
            "category":"Wholesale",
            "subcategory":"Electrical",
            "type":"Manufacturing & Wholesale Goods"
        }
    ],
    "sg:phone":"+1 701 492 6267",
    "sg:postcode":"58104",
    "sg:province":"ND",
    "sg:tags":[
        "control",
        "security",
        "system"
    ],
    "sg:website":"www.ecisystems.com",
    "wof:name":"Electronic Communications",
    "wof:placetype":"venue"
},
  "geometry": {"coordinates":[-96.840576,46.820582],"type":"Point"}
}