{
  "type": "Feature",
  "properties": {
    "addr:full":"320 24th St N Fargo ND 58102",
    "addr:housenumber":"320",
    "addr:postcode":"58102",
    "addr:street":"24Th St N",
    "iso:country":"US",
    "sg:address":"320 24th St N",
    "sg:city":"Fargo",
    "sg:classifiers":[
        {
            "category":"Building & Trades",
            "subcategory":"Cleaning & Sanitation",
            "type":"Services"
        }
    ],
    "sg:phone":"+1 701 232 2054",
    "sg:postcode":"58102",
    "sg:province":"ND",
    "sg:tags":[
        "janitor"
    ],
    "wof:name":"G H Janitorial Svc",
    "wof:placetype":"venue"
},
  "geometry": {"coordinates":[-96.81820999999999,46.881361],"type":"Point"}
}