{
  "type": "Feature",
  "properties": {
    "addr:full":"600 Main St Sherwood ND 58782",
    "addr:housenumber":"600",
    "addr:postcode":"58782",
    "addr:street":"Main St",
    "iso:country":"US",
    "sg:address":"600 Main St",
    "sg:city":"Sherwood",
    "sg:classifiers":[
        {
            "category":"Education",
            "subcategory":"School",
            "type":"Public Place"
        }
    ],
    "sg:phone":"+1 701 459 2214",
    "sg:postcode":"58782",
    "sg:province":"ND",
    "wof:name":"Sherwood School District 2",
    "wof:placetype":"venue"
},
  "geometry": {"coordinates":[-101.63275299999999,48.963205],"type":"Point"}
}