{
  "type": "Feature",
  "properties": {
    "iso:country":"US",
    "sg:address":"43 Wiley Ave S",
    "sg:city":"Lidgerwood",
    "sg:classifiers":[
        {
            "category":"Personal",
            "subcategory":"Beauty Salon",
            "type":"Services"
        }
    ],
    "sg:phone":"+1 701 538 4484",
    "sg:postcode":"58053",
    "sg:province":"ND",
    "wof:name":"Lidgerwood Beauty Salon",
    "wof:placetype":"venue"
},
  "geometry": {"coordinates":[-97.151888,46.07491],"type":"Point"}
}