{
  "type": "Feature",
  "properties": {
    "iso:country":"US",
    "sg:address":"508 Rosie Ln NE",
    "sg:city":"Mandan",
    "sg:classifiers":[
        {
            "category":"Building & Trades",
            "subcategory":"Construction",
            "type":"Services"
        }
    ],
    "sg:phone":"+1 701 667 0191",
    "sg:postcode":"58554",
    "sg:province":"ND",
    "sg:tags":[
        "contractor"
    ],
    "wof:name":"S T Lipp Drywall Inc",
    "wof:placetype":"venue"
},
  "geometry": {"coordinates":[-100.91400899999999,46.903817],"type":"Point"}
}