{
  "type": "Feature",
  "properties": {
    "addr:full":"554 W 12th St Grafton ND 58237",
    "addr:housenumber":"554",
    "addr:postcode":"58237",
    "addr:street":"W 12Th St",
    "iso:country":"US",
    "sg:address":"554 W 12th St",
    "sg:city":"Grafton",
    "sg:classifiers":[
        {
            "category":"Social Services",
            "type":"Services"
        }
    ],
    "sg:phone":"+1 701 352 0060",
    "sg:postcode":"58237",
    "sg:province":"ND",
    "sg:tags":[
        "organization",
        "welfare"
    ],
    "sg:website":"www.friendship.com",
    "wof:name":"Friendship Inc Grafton/Park",
    "wof:placetype":"venue"
},
  "geometry": {"coordinates":[-97.420085,48.412429],"type":"Point"}
}