{
  "type": "Feature",
  "properties": {
    "addr:full":"611 Harvey Ave Minto ND 58261",
    "addr:housenumber":"611",
    "addr:postcode":"58261",
    "addr:street":"Harvey Ave",
    "iso:country":"US",
    "sg:address":"611 Harvey Ave",
    "sg:city":"Minto",
    "sg:classifiers":[
        {
            "category":"Farming",
            "subcategory":"Farm & Veterinary Services",
            "type":"Manufacturing & Wholesale Goods"
        }
    ],
    "sg:phone":"+1 701 248 3836",
    "sg:postcode":"58261",
    "sg:province":"ND",
    "sg:tags":[
        "crop",
        "harvesting"
    ],
    "wof:name":"Lyle Harvesting",
    "wof:placetype":"venue"
},
  "geometry": {"coordinates":[-97.38297300000001,48.291573],"type":"Point"}
}