{
  "type": "Feature",
  "properties": {
    "addr:full":"209 W Main St Mandan ND 58554",
    "addr:housenumber":"209",
    "addr:postcode":"58554",
    "addr:street":"W Main St",
    "iso:country":"US",
    "sg:address":"209 W Main St",
    "sg:city":"Mandan",
    "sg:classifiers":[
        {
            "category":"Restaurant",
            "type":"Food & Drink"
        }
    ],
    "sg:menulink":"http://www.allmenus.com/nd/mandan/77500-papa-murphys/menu/",
    "sg:phone":"+1 701 667 7272",
    "sg:postcode":"58554",
    "sg:province":"ND",
    "sg:tags":[
        "american",
        "pizza"
    ],
    "wof:name":"Papa Murphy's",
    "wof:placetype":"venue"
},
  "geometry": {"coordinates":[-100.89134799999999,46.826245],"type":"Point"}
}