{
  "type": "Feature",
  "properties": {
    "iso:country":"US",
    "sg:address":"9707 Co Rd 6",
    "sg:city":"Columbus",
    "sg:phone":"+1 701 939 4571",
    "sg:postcode":"58727",
    "sg:province":"ND",
    "sg:tags":[
        "farm",
        "wheat"
    ],
    "wof:name":"Lynn Watterud",
    "wof:placetype":"venue"
},
  "geometry": {"coordinates":[-102.83028400000001,48.807494],"type":"Point"}
}