{
  "type": "Feature",
  "properties": {
    "addr:full":"210 Collins Ave Mandan ND 58554",
    "addr:housenumber":"210",
    "addr:postcode":"58554",
    "addr:street":"Collins Ave",
    "iso:country":"US",
    "sg:address":"210 Collins Ave",
    "sg:city":"Mandan",
    "sg:classifiers":[
        {
            "category":"Professional",
            "subcategory":"Lawyer & Legal Services",
            "type":"Services"
        }
    ],
    "sg:phone":"+1 701 667 1888",
    "sg:postcode":"58554",
    "sg:province":"ND",
    "sg:tags":[
        "attorney"
    ],
    "wof:name":"Tom Tuntland",
    "wof:placetype":"venue"
},
  "geometry": {"coordinates":[-100.890247,46.828441],"type":"Point"}
}