{
  "type": "Feature",
  "properties": {
    "addr:full":"502 Dakota Ave Wahpeton ND 58075",
    "addr:housenumber":"502",
    "addr:postcode":"58075",
    "addr:street":"Dakota Ave",
    "iso:country":"US",
    "sg:address":"502 Dakota Ave",
    "sg:city":"Wahpeton",
    "sg:classifiers":[
        {
            "category":"Shopping",
            "subcategory":"Clothing, Apparel, & Fashions",
            "type":"Retail Goods"
        }
    ],
    "sg:phone":"+1 701 642 8372",
    "sg:postcode":"58075",
    "sg:province":"ND",
    "sg:tags":[
        "wear"
    ],
    "wof:name":"Jos Bon Inc",
    "wof:placetype":"venue"
},
  "geometry": {"coordinates":[-96.608304,46.264007],"type":"Point"}
}