{
  "type": "Feature",
  "properties": {
    "iso:country":"US",
    "sg:address":"2610 Old Red Trl NW",
    "sg:city":"Mandan",
    "sg:classifiers":[
        {
            "category":"Home & Garden",
            "subcategory":"Garden Supply",
            "type":"Retail Goods"
        },
        {
            "category":"Government",
            "subcategory":"Office",
            "type":"Public Place"
        }
    ],
    "sg:phone":"+1 701 667 1163",
    "sg:postcode":"58554",
    "sg:province":"ND",
    "sg:tags":[
        "soil",
        "state",
        "conservation",
        "government-united"
    ],
    "wof:name":"Natural Resources Conservation Service",
    "wof:placetype":"venue"
},
  "geometry": {"coordinates":[-100.92324000000001,46.85719],"type":"Point"}
}