{
  "type": "Feature",
  "properties": {
    "iso:country":"US",
    "sg:address":"45 65th St SE",
    "sg:city":"Hazelton",
    "sg:classifiers":[
        {
            "category":"Farming",
            "subcategory":"Livestock Farm",
            "type":"Manufacturing & Wholesale Goods"
        }
    ],
    "sg:phone":"+1 701 782 6868",
    "sg:postcode":"58544",
    "sg:province":"ND",
    "sg:tags":[
        "beef",
        "feedlot",
        "cattle"
    ],
    "wof:name":"Don L Schiermeister",
    "wof:placetype":"venue"
},
  "geometry": {"coordinates":[-100.416912,46.472995],"type":"Point"}
}