{
  "type": "Feature",
  "properties": {
    "addr:full":"109 4th Ave SW Beulah ND 58523",
    "addr:housenumber":"109",
    "addr:postcode":"58523",
    "addr:street":"4Th Ave Sw",
    "iso:country":"US",
    "sg:address":"109 4th Ave SW",
    "sg:city":"Beulah",
    "sg:classifiers":[
        {
            "category":"Shopping",
            "subcategory":"Gifts & Souvenirs",
            "type":"Retail Goods"
        }
    ],
    "sg:phone":"+1 701 873 4586",
    "sg:postcode":"58523",
    "sg:province":"ND",
    "wof:name":"Straight From Heart",
    "wof:placetype":"venue"
},
  "geometry": {"coordinates":[-101.78423600000001,47.263388],"type":"Point"}
}