{
  "type": "Feature",
  "properties": {
    "iso:country":"US",
    "sg:address":"555 40th St S Apt 226",
    "sg:city":"Fargo",
    "sg:classifiers":[
        {
            "category":"Real Estate",
            "subcategory":"Real Estate Operator",
            "type":"Services"
        }
    ],
    "sg:phone":"+1 701 281 2804",
    "sg:postcode":"58103",
    "sg:province":"ND",
    "sg:tags":[
        "apartment"
    ],
    "wof:name":"Park Avenue Apartment Homes Llp",
    "wof:placetype":"venue"
},
  "geometry": {"coordinates":[-96.846441,46.870004],"type":"Point"}
}