{
  "type": "Feature",
  "properties": {
    "iso:country":"US",
    "sg:address":"9755 19th Ave NE",
    "sg:city":"Bottineau",
    "sg:classifiers":[
        {
            "category":"Farming",
            "subcategory":"Livestock Farm",
            "type":"Manufacturing & Wholesale Goods"
        }
    ],
    "sg:phone":"+1 701 228 6092",
    "sg:postcode":"58318",
    "sg:province":"ND",
    "sg:tags":[
        "beef",
        "feedlot",
        "cattle"
    ],
    "wof:name":"Northern M Cattle Ranch",
    "wof:placetype":"venue"
},
  "geometry": {"coordinates":[-100.292658,48.826966],"type":"Point"}
}