{
  "type": "Feature",
  "properties": {
    "addr:full":"239 5th Ave NE Valley City ND 58072",
    "addr:housenumber":"239",
    "addr:postcode":"58072",
    "addr:street":"5Th Ave Ne",
    "iso:country":"US",
    "sg:address":"239 5th Ave NE",
    "sg:city":"Valley City",
    "sg:classifiers":[
        {
            "category":"Building & Trades",
            "subcategory":"Construction",
            "type":"Services"
        }
    ],
    "sg:phone":"+1 701 845 1636",
    "sg:postcode":"58072",
    "sg:province":"ND",
    "sg:tags":[
        "house"
    ],
    "wof:name":"John Stearns Construction Serv",
    "wof:placetype":"venue"
},
  "geometry": {"coordinates":[-97.997015,46.925087],"type":"Point"}
}