{
  "type": "Feature",
  "properties": {
    "addr:full":"825 S 8th St Bismarck ND 58504",
    "addr:housenumber":"825",
    "addr:postcode":"58504",
    "addr:street":"S 8Th St",
    "iso:country":"US",
    "sg:address":"825 S 8th St",
    "sg:city":"Bismarck",
    "sg:classifiers":[
        {
            "category":"Arts & Performance",
            "subcategory":"Theater",
            "type":"Entertainment"
        }
    ],
    "sg:phone":"+1 701 223 2952",
    "sg:postcode":"58504",
    "sg:province":"ND",
    "sg:tags":[
        "bureau"
    ],
    "wof:name":"Dakota Skies Bingo",
    "wof:placetype":"venue"
},
  "geometry": {"coordinates":[-100.780119,46.801255],"type":"Point"}
}