{
  "type": "Feature",
  "properties": {
    "iso:country":"US",
    "sg:address":"2010 10th Ave E",
    "sg:city":"Williston",
    "sg:classifiers":[
        {
            "category":"Real Estate",
            "subcategory":"Real Estate Operator",
            "type":"Services"
        }
    ],
    "sg:phone":"+1 701 774 8559",
    "sg:postcode":"58801",
    "sg:province":"ND",
    "sg:tags":[
        "building",
        "personal",
        "apartment"
    ],
    "wof:name":"Ridgeview Apts",
    "wof:placetype":"venue"
},
  "geometry": {"coordinates":[-103.608779,48.162257],"type":"Point"}
}