{
  "type": "Feature",
  "properties": {
    "iso:country":"US",
    "sg:address":"616 59th St N",
    "sg:city":"Granville",
    "sg:phone":"+1 701 728 6655",
    "sg:postcode":"58741",
    "sg:province":"ND",
    "sg:tags":[
        "farm",
        "grain",
        "cash"
    ],
    "wof:name":"Michael Zewick",
    "wof:placetype":"venue"
},
  "geometry": {"coordinates":[-100.734505,48.268778],"type":"Point"}
}