{
  "type": "Feature",
  "properties": {
    "iso:country":"US",
    "sg:address":"101 Railway Ave",
    "sg:city":"Tolley",
    "sg:classifiers":[
        {
            "category":"Freight",
            "type":"Transportation"
        }
    ],
    "sg:phone":"+1 701 386 2457",
    "sg:postcode":"58772",
    "sg:province":"ND",
    "sg:tags":[
        "grain",
        "elevator"
    ],
    "wof:name":"Renville Elevator Co",
    "wof:placetype":"venue"
},
  "geometry": {"coordinates":[-102.546494,48.995295],"type":"Point"}
}