{
  "type": "Feature",
  "properties": {
    "addr:full":"2345 25th St S Fargo ND 58103",
    "addr:housenumber":"2345",
    "addr:postcode":"58103",
    "addr:street":"25Th St S",
    "iso:country":"US",
    "sg:address":"2345 25th St S",
    "sg:city":"Fargo",
    "sg:classifiers":[
        {
            "category":"Health Services",
            "subcategory":"Health Practitioner",
            "type":"Services"
        }
    ],
    "sg:phone":"+1 701 297 7588",
    "sg:postcode":"58103",
    "sg:province":"ND",
    "wof:name":"Rodney A Swenson PHD Abpn",
    "wof:placetype":"venue"
},
  "geometry": {"coordinates":[-96.81970699999999,46.843777],"type":"Point"}
}