{
  "type": "Feature",
  "properties": {
    "iso:country":"US",
    "sg:address":"2830 S University Dr",
    "sg:city":"Fargo",
    "sg:classifiers":[
        {
            "category":"Real Estate",
            "subcategory":"Real Estate Agent",
            "type":"Services"
        }
    ],
    "sg:phone":"+1 701 237 4142",
    "sg:postcode":"58103",
    "sg:province":"ND",
    "sg:tags":[
        "investment"
    ],
    "wof:name":"Reed Investment Inc",
    "wof:placetype":"venue"
},
  "geometry": {"coordinates":[-96.79866,46.839953],"type":"Point"}
}