{
  "type": "Feature",
  "properties": {
    "addr:full":"210 W South Ave Glen Ullin ND 58631",
    "addr:housenumber":"210",
    "addr:postcode":"58631",
    "addr:street":"W South Ave Glen",
    "iso:country":"US",
    "sg:address":"210 W South Ave",
    "sg:city":"Glen Ullin",
    "sg:classifiers":[
        {
            "category":"Insurance",
            "subcategory":"Insurance Agent",
            "type":"Services"
        }
    ],
    "sg:phone":"+1 701 348 3917",
    "sg:postcode":"58631",
    "sg:province":"ND",
    "wof:name":"Farmers Union Insurance",
    "wof:placetype":"venue"
},
  "geometry": {"coordinates":[-101.831845,46.816155],"type":"Point"}
}