{
  "type": "Feature",
  "properties": {
    "iso:country":"US",
    "sg:address":"736 Broadway N",
    "sg:city":"Fargo",
    "sg:classifiers":[
        {
            "category":"Health Services",
            "subcategory":"Doctor",
            "type":"Services"
        }
    ],
    "sg:phone":"+1 701 234 2203",
    "sg:postcode":"58102",
    "sg:province":"ND",
    "sg:tags":[
        "medicine",
        "physician",
        "surgeon",
        "sport",
        "surgeons"
    ],
    "wof:name":"Americare Hospital",
    "wof:placetype":"venue"
},
  "geometry": {"coordinates":[-96.78769800000001,46.883671],"type":"Point"}
}