{
  "type": "Feature",
  "properties": {
    "iso:country":"US",
    "sg:address":"1300 54th Ave SW",
    "sg:city":"Minot",
    "sg:classifiers":[
        {
            "category":"Farming",
            "subcategory":"Livestock Farm",
            "type":"Manufacturing & Wholesale Goods"
        }
    ],
    "sg:phone":"+1 701 839 3715",
    "sg:postcode":"58701",
    "sg:province":"ND",
    "sg:tags":[
        "animal",
        "general"
    ],
    "wof:name":"Leavitt Elk Ranch",
    "wof:placetype":"venue"
},
  "geometry": {"coordinates":[-101.31325699999999,48.182405],"type":"Point"}
}