{
  "type": "Feature",
  "properties": {
    "iso:country":"US",
    "sg:address":"785 26th St W",
    "sg:city":"Dickinson",
    "sg:classifiers":[
        {
            "category":"Social Services",
            "subcategory":"Child Care",
            "type":"Services"
        }
    ],
    "sg:phone":"+1 701 227 8827",
    "sg:postcode":"58601",
    "sg:province":"ND",
    "wof:name":"Discovery Learning Ctr",
    "wof:placetype":"venue"
},
  "geometry": {"coordinates":[-102.797419,46.909228],"type":"Point"}
}