{
  "type": "Feature",
  "properties": {
    "iso:country":"US",
    "sg:address":"7205 105th Ave SE",
    "sg:city":"La Moure",
    "sg:phone":"+1 701 883 5745",
    "sg:postcode":"58458",
    "sg:province":"ND",
    "sg:tags":[
        "farm",
        "wheat"
    ],
    "wof:name":"Allen Lutgen",
    "wof:placetype":"venue"
},
  "geometry": {"coordinates":[-98.222662,46.368924],"type":"Point"}
}