{
  "type": "Feature",
  "properties": {
    "addr:full":"616 Kirkwood Mall Bismarck ND 58504",
    "addr:housenumber":"616",
    "addr:postcode":"58504",
    "addr:street":"Kirkwood Mall",
    "iso:country":"US",
    "sg:address":"616 Kirkwood Mall",
    "sg:city":"Bismarck",
    "sg:classifiers":[
        {
            "category":"Organizations",
            "subcategory":"Membership Organization",
            "type":"Services"
        }
    ],
    "sg:phone":"+1 701 223 6660",
    "sg:postcode":"58504",
    "sg:province":"ND",
    "sg:tags":[
        "automobile"
    ],
    "wof:name":"Triple A",
    "wof:placetype":"venue"
},
  "geometry": {"coordinates":[-100.784869,46.799641],"type":"Point"}
}