{
  "type": "Feature",
  "properties": {
    "addr:full":"930 3rd St NW Valley City ND 58072",
    "addr:housenumber":"930",
    "addr:postcode":"58072",
    "addr:street":"3Rd St Nw",
    "iso:country":"US",
    "sg:address":"930 3rd St NW",
    "sg:city":"Valley City",
    "sg:classifiers":[
        {
            "category":"Real Estate",
            "subcategory":"Real Estate Operator",
            "type":"Services"
        }
    ],
    "sg:phone":"+1 701 845 5319",
    "sg:postcode":"58072",
    "sg:province":"ND",
    "sg:tags":[
        "property",
        "lessor"
    ],
    "wof:name":"Clayton Olson",
    "wof:placetype":"venue"
},
  "geometry": {"coordinates":[-98.015722,46.925086],"type":"Point"}
}