{
  "type": "Feature",
  "properties": {
    "addr:full":"210 Main St Bisbee ND 58317",
    "addr:housenumber":"210",
    "addr:postcode":"58317",
    "addr:street":"Main St",
    "iso:country":"US",
    "sg:address":"210 Main St",
    "sg:city":"Bisbee",
    "sg:classifiers":[
        {
            "category":"Banks & Credit Unions",
            "subcategory":"Bank",
            "type":"Services"
        }
    ],
    "sg:phone":"+1 701 656 3241",
    "sg:postcode":"58317",
    "sg:province":"ND",
    "wof:name":"First State Bank",
    "wof:placetype":"venue"
},
  "geometry": {"coordinates":[-99.379859,48.627381],"type":"Point"}
}