{
  "type": "Feature",
  "properties": {
    "iso:country":"US",
    "sg:address":"1705 3rd Ave W",
    "sg:city":"Williston",
    "sg:classifiers":[
        {
            "category":"Social Services",
            "type":"Services"
        }
    ],
    "sg:phone":"+1 701 572 9414",
    "sg:postcode":"58801",
    "sg:province":"ND",
    "sg:tags":[
        "organization",
        "welfare"
    ],
    "wof:name":"Foster Grandparent Program",
    "wof:placetype":"venue"
},
  "geometry": {"coordinates":[-103.627551,48.160756],"type":"Point"}
}