{
  "type": "Feature",
  "properties": {
    "addr:full":"506 3rd Ave Litchville ND 58461",
    "addr:housenumber":"506",
    "addr:postcode":"58461",
    "addr:street":"3Rd Ave",
    "iso:country":"US",
    "sg:address":"506 3rd Ave",
    "sg:city":"Litchville",
    "sg:classifiers":[
        {
            "category":"Banks & Credit Unions",
            "subcategory":"Bank",
            "type":"Services"
        }
    ],
    "sg:phone":"+1 701 762 4256",
    "sg:postcode":"58461",
    "sg:province":"ND",
    "wof:name":"Wells Fargo Bank",
    "wof:placetype":"venue"
},
  "geometry": {"coordinates":[-98.19406499999999,46.653765],"type":"Point"}
}