{
  "type": "Feature",
  "properties": {
    "iso:country":"US",
    "sg:address":"110 N 5th St",
    "sg:city":"Bismarck",
    "sg:classifiers":[
        {
            "category":"Shopping",
            "subcategory":"Gifts & Souvenirs",
            "type":"Retail Goods"
        }
    ],
    "sg:phone":"+1 701 222 1433",
    "sg:postcode":"58501",
    "sg:province":"ND",
    "sg:tags":[
        "shop",
        "furniture",
        "wood",
        "store",
        "custom"
    ],
    "wof:name":"Country Barn Classic Design",
    "wof:placetype":"venue"
},
  "geometry": {"coordinates":[-100.784695,46.806334],"type":"Point"}
}