{
  "type": "Feature",
  "properties": {
    "addr:full":"1416 E Front Ave Bismarck ND 58504",
    "addr:housenumber":"1416",
    "addr:postcode":"58504",
    "addr:street":"E Front Ave",
    "iso:country":"US",
    "sg:address":"1416 E Front Ave",
    "sg:city":"Bismarck",
    "sg:classifiers":[
        {
            "category":"Home & Garden",
            "subcategory":"Building Materials",
            "type":"Retail Goods"
        }
    ],
    "sg:phone":"+1 701 255 1636",
    "sg:postcode":"58504",
    "sg:province":"ND",
    "sg:tags":[
        "lumber"
    ],
    "sg:website":"www.frontstreetmillwork.com",
    "wof:name":"Front Street Millwork & Lumber",
    "wof:placetype":"venue"
},
  "geometry": {"coordinates":[-100.769642,46.804073],"type":"Point"}
}