{
  "type": "Feature",
  "properties": {
    "iso:country":"US",
    "sg:address":"338 34th Ave SE",
    "sg:city":"Chaseley",
    "sg:classifiers":[
        {
            "category":"Farming",
            "subcategory":"Farm",
            "type":"Manufacturing & Wholesale Goods"
        }
    ],
    "sg:phone":"+1 701 962 3435",
    "sg:postcode":"58423",
    "sg:province":"ND",
    "sg:tags":[
        "grain",
        "cash"
    ],
    "wof:name":"Marvin Rodacker Farm",
    "wof:placetype":"venue"
},
  "geometry": {"coordinates":[-99.81998299999999,47.364614],"type":"Point"}
}