{
  "type": "Feature",
  "properties": {
    "iso:country":"US",
    "sg:address":"419 Tweeten Pl",
    "sg:city":"Dickinson",
    "sg:classifiers":[
        {
            "category":"Building & Trades",
            "subcategory":"Equipment Rental",
            "type":"Services"
        }
    ],
    "sg:phone":"+1 701 225 9487",
    "sg:postcode":"58601",
    "sg:province":"ND",
    "wof:name":"Vern C Jacobson Rentals",
    "wof:placetype":"venue"
},
  "geometry": {"coordinates":[-102.778358,46.889766],"type":"Point"}
}