{
  "type": "Feature",
  "properties": {
    "addr:full":"314 Center St Enderlin ND 58027",
    "addr:housenumber":"314",
    "addr:postcode":"58027",
    "addr:street":"Center St",
    "iso:country":"US",
    "sg:address":"314 Center St",
    "sg:city":"Enderlin",
    "sg:classifiers":[
        {
            "category":"Shopping",
            "subcategory":"Florist",
            "type":"Retail Goods"
        }
    ],
    "sg:phone":"+1 701 437 3381",
    "sg:postcode":"58027",
    "sg:province":"ND",
    "wof:name":"Flowers Etc",
    "wof:placetype":"venue"
},
  "geometry": {"coordinates":[-97.603393,46.623615],"type":"Point"}
}