{
  "type": "Feature",
  "properties": {
    "iso:country":"US",
    "sg:address":"3021 13th Ave SW",
    "sg:city":"Fargo",
    "sg:classifiers":[
        {
            "category":"Shopping",
            "type":"Retail Goods"
        }
    ],
    "sg:phone":"+1 701 239 0063",
    "sg:postcode":"58103",
    "sg:province":"ND",
    "sg:tags":[
        "art",
        "framing"
    ],
    "wof:name":"Affordable Framing & Prints",
    "wof:placetype":"venue"
},
  "geometry": {"coordinates":[-96.830028,46.861718],"type":"Point"}
}