{
  "type": "Feature",
  "properties": {
    "addr:full":"340 Wakeman Ave Grafton ND 58237",
    "addr:housenumber":"340",
    "addr:postcode":"58237",
    "addr:street":"Wakeman Ave",
    "iso:country":"US",
    "sg:address":"340 Wakeman Ave",
    "sg:city":"Grafton",
    "sg:classifiers":[
        {
            "category":"Organizations",
            "subcategory":"Community Association",
            "type":"Services"
        }
    ],
    "sg:phone":"+1 701 352 0946",
    "sg:postcode":"58237",
    "sg:province":"ND",
    "sg:tags":[
        "military"
    ],
    "wof:name":"Veterans Of Foreign Wars",
    "wof:placetype":"venue"
},
  "geometry": {"coordinates":[-97.408502,48.421147],"type":"Point"}
}