{
  "type": "Feature",
  "properties": {
    "addr:full":"1221 10th St SE Jamestown ND 58401",
    "addr:housenumber":"1221",
    "addr:postcode":"58401",
    "addr:street":"10Th St Se",
    "iso:country":"US",
    "sg:address":"1221 10th St SE",
    "sg:city":"Jamestown",
    "sg:classifiers":[
        {
            "category":"Shopping",
            "type":"Retail Goods"
        }
    ],
    "sg:phone":"+1 701 252 3866",
    "sg:postcode":"58401",
    "sg:province":"ND",
    "sg:tags":[
        "cut",
        "merchandise",
        "mfg"
    ],
    "wof:name":"Jamestown Monument",
    "wof:placetype":"venue"
},
  "geometry": {"coordinates":[-98.691542,46.899149],"type":"Point"}
}