{
  "type": "Feature",
  "properties": {
    "addr:full":"120 N Washington St Grand Forks ND 58203",
    "addr:housenumber":"120",
    "addr:postcode":"58203",
    "addr:street":"N Washington St",
    "iso:country":"US",
    "sg:address":"120 N Washington St",
    "sg:city":"Grand Forks",
    "sg:classifiers":[
        {
            "category":"Shopping",
            "type":"Retail Goods"
        }
    ],
    "sg:phone":"+1 701 772 0927",
    "sg:postcode":"58203",
    "sg:province":"ND",
    "sg:tags":[
        "aids",
        "education",
        "art",
        "devices",
        "supply"
    ],
    "wof:name":"Art & Learn",
    "wof:placetype":"venue"
},
  "geometry": {"coordinates":[-97.044918,47.920964],"type":"Point"}
}