{
  "type": "Feature",
  "properties": {
    "iso:country":"US",
    "sg:address":"217 4th St",
    "sg:city":"Finley",
    "sg:classifiers":[
        {
            "category":"Professional",
            "subcategory":"Accounting & Tax Preparation",
            "type":"Services"
        }
    ],
    "sg:phone":"+1 701 524 1611",
    "sg:postcode":"58230",
    "sg:province":"ND",
    "sg:tags":[
        "return",
        "filing"
    ],
    "wof:name":"Norgaard Farm Svc",
    "wof:placetype":"venue"
},
  "geometry": {"coordinates":[-97.836844,47.512026],"type":"Point"}
}