{
  "type": "Feature",
  "properties": {
    "addr:full":"8104 Gemini Cir Fargo ND 58104",
    "addr:housenumber":"8104",
    "addr:postcode":"58104",
    "addr:street":"Gemini Cir",
    "iso:country":"US",
    "sg:address":"8104 Gemini Cir",
    "sg:city":"Fargo",
    "sg:classifiers":[
        {
            "category":"Building & Trades",
            "subcategory":"Landscaping Services",
            "type":"Services"
        }
    ],
    "sg:phone":"+1 701 729 7208",
    "sg:postcode":"58104",
    "sg:province":"ND",
    "wof:name":"Cougar Tree Care",
    "wof:placetype":"venue"
},
  "geometry": {"coordinates":[-96.80039499999999,46.768447],"type":"Point"}
}