{
  "type": "Feature",
  "properties": {
    "iso:country":"US",
    "sg:address":"1217 N 22nd St",
    "sg:city":"Bismarck",
    "sg:phone":"+1 701 258 4123",
    "sg:postcode":"58501",
    "sg:province":"ND",
    "sg:tags":[
        "farm",
        "wheat"
    ],
    "wof:name":"Will Brothers",
    "wof:placetype":"venue"
},
  "geometry": {"coordinates":[-100.759559,46.818627],"type":"Point"}
}