{
  "type": "Feature",
  "properties": {
    "iso:country":"US",
    "sg:address":"708 4th St",
    "sg:city":"Maddock",
    "sg:classifiers":[
        {
            "category":"Insurance",
            "subcategory":"Insurance Agent",
            "type":"Services"
        }
    ],
    "sg:phone":"+1 701 438 2691",
    "sg:postcode":"58348",
    "sg:province":"ND",
    "wof:name":"Norheim Insurance Agency",
    "wof:placetype":"venue"
},
  "geometry": {"coordinates":[-99.52383500000001,47.95953],"type":"Point"}
}