{
  "type": "Feature",
  "properties": {
    "iso:country":"US",
    "sg:address":"72 Main St",
    "sg:city":"Rocklake",
    "sg:classifiers":[
        {
            "category":"Freight",
            "type":"Transportation"
        }
    ],
    "sg:phone":"+1 701 266 5668",
    "sg:postcode":"58365",
    "sg:province":"ND",
    "sg:tags":[
        "operator",
        "local",
        "trucking"
    ],
    "wof:name":"Swanson Construction",
    "wof:placetype":"venue"
},
  "geometry": {"coordinates":[-99.242385,48.791179],"type":"Point"}
}