{
  "type": "Feature",
  "properties": {
    "iso:country":"US",
    "sg:address":"5780 Co Rd 84",
    "sg:city":"Flasher",
    "sg:classifiers":[
        {
            "category":"Professional",
            "subcategory":"Accounting & Tax Preparation",
            "type":"Services"
        }
    ],
    "sg:phone":"+1 701 597 3076",
    "sg:postcode":"58535",
    "sg:province":"ND",
    "sg:tags":[
        "consulting",
        "management",
        "s"
    ],
    "wof:name":"Lawson Tax & Financial Service",
    "wof:placetype":"venue"
},
  "geometry": {"coordinates":[-101.268604,46.575907],"type":"Point"}
}