{
  "type": "Feature",
  "properties": {
    "iso:country":"US",
    "sg:address":"703 7th St",
    "sg:city":"Wyndmere",
    "sg:classifiers":[
        {
            "category":"Wholesale",
            "subcategory":"Machinery & Supplies",
            "type":"Manufacturing & Wholesale Goods"
        }
    ],
    "sg:phone":"+1 701 439 2217",
    "sg:postcode":"58081",
    "sg:province":"ND",
    "sg:tags":[
        "pressure",
        "washing",
        "equipment"
    ],
    "wof:name":"Midwest Sales & Svc",
    "wof:placetype":"venue"
},
  "geometry": {"coordinates":[-97.13506599999999,46.260425],"type":"Point"}
}