{
  "type": "Feature",
  "properties": {
    "addr:full":"313 7th St Thompson ND 58278",
    "addr:housenumber":"313",
    "addr:postcode":"58278",
    "addr:street":"7Th St",
    "iso:country":"US",
    "sg:address":"313 7th St",
    "sg:city":"Thompson",
    "sg:classifiers":[
        {
            "category":"Health Services",
            "subcategory":"Nursing And Care Facility",
            "type":"Services"
        }
    ],
    "sg:phone":"+1 701 845 1601",
    "sg:postcode":"58278",
    "sg:province":"ND",
    "sg:tags":[
        "home",
        "retirement",
        "community"
    ],
    "wof:name":"Thompson Manor Apartments",
    "wof:placetype":"venue"
},
  "geometry": {"coordinates":[-97.10978,47.779823],"type":"Point"}
}