{
  "type": "Feature",
  "properties": {
    "iso:country":"US",
    "sg:address":"509 1st Ave S",
    "sg:city":"Jamestown",
    "sg:classifiers":[
        {
            "category":"Shopping",
            "subcategory":"Tobacco",
            "type":"Retail Goods"
        }
    ],
    "sg:phone":"+1 701 252 1683",
    "sg:postcode":"58401",
    "sg:province":"ND",
    "sg:tags":[
        "cigarette",
        "cigar",
        "dealer"
    ],
    "wof:name":"Smokee's Tobacco Shop",
    "wof:placetype":"venue"
},
  "geometry": {"coordinates":[-98.70823300000001,46.904062],"type":"Point"}
}