{
  "type": "Feature",
  "properties": {
    "addr:full":"713 Parke Ave Portland ND 58274",
    "addr:housenumber":"713",
    "addr:postcode":"58274",
    "addr:street":"Parke Ave",
    "iso:country":"US",
    "sg:address":"713 Parke Ave",
    "sg:city":"Portland",
    "sg:classifiers":[
        {
            "category":"Insurance",
            "subcategory":"Insurance Agent",
            "type":"Services"
        }
    ],
    "sg:phone":"+1 701 786 2858",
    "sg:postcode":"58274",
    "sg:province":"ND",
    "sg:website":"www.mayportinsurance.com",
    "wof:name":"Mayport Insurance & Realty Inc",
    "wof:placetype":"venue"
},
  "geometry": {"coordinates":[-97.37246500000001,47.498389],"type":"Point"}
}