{
  "type": "Feature",
  "properties": {
    "iso:country":"US",
    "sg:address":"1217 97th Ave SE",
    "sg:city":"Wimbledon",
    "sg:phone":"+1 701 435 2624",
    "sg:postcode":"58492",
    "sg:province":"ND",
    "sg:tags":[
        "farm",
        "wheat",
        "grain",
        "cash"
    ],
    "wof:name":"Brian Fehr",
    "wof:placetype":"venue"
},
  "geometry": {"coordinates":[-98.446969,47.237938],"type":"Point"}
}