{
  "type": "Feature",
  "properties": {
    "iso:country":"US",
    "sg:address":"3395 State Hwy 13",
    "sg:city":"Wishek",
    "sg:classifiers":[
        {
            "category":"Manufacturing",
            "subcategory":"Tools & Machinery",
            "type":"Manufacturing & Wholesale Goods"
        }
    ],
    "sg:phone":"+1 701 452 2615",
    "sg:postcode":"58495",
    "sg:province":"ND",
    "sg:tags":[
        "mfg",
        "automotive",
        "industrial",
        "repair"
    ],
    "wof:name":"Lyle Bettenha",
    "wof:placetype":"venue"
},
  "geometry": {"coordinates":[-99.671663,46.259566],"type":"Point"}
}