{
  "type": "Feature",
  "properties": {
    "iso:country":"US",
    "sg:address":"4313 12th Ave N",
    "sg:city":"Voltaire",
    "sg:classifiers":[
        {
            "category":"Wholesale",
            "subcategory":"Farm Supplies",
            "type":"Manufacturing & Wholesale Goods"
        }
    ],
    "sg:phone":"+1 701 338 2212",
    "sg:postcode":"58792",
    "sg:province":"ND",
    "sg:tags":[
        "livestock"
    ],
    "wof:name":"Terry Krumwied",
    "wof:placetype":"venue"
},
  "geometry": {"coordinates":[-100.84221599999999,48.037029],"type":"Point"}
}