{
  "type": "Feature",
  "properties": {
    "addr:full":"3920 River Dr Fargo ND 58104",
    "addr:housenumber":"3920",
    "addr:postcode":"58104",
    "addr:street":"River Dr",
    "iso:country":"US",
    "sg:address":"3920 River Dr",
    "sg:city":"Fargo",
    "sg:classifiers":[
        {
            "category":"Banks & Credit Unions",
            "subcategory":"Financial Services",
            "type":"Services"
        }
    ],
    "sg:phone":"+1 701 232 7071",
    "sg:postcode":"58104",
    "sg:province":"ND",
    "sg:tags":[
        "company",
        "holding"
    ],
    "wof:name":"Stoke Holdings LLC",
    "wof:placetype":"venue"
},
  "geometry": {"coordinates":[-96.802249,46.818439],"type":"Point"}
}