{
  "type": "Feature",
  "properties": {
    "addr:full":"605 Thompson St Bottineau ND 58318",
    "addr:housenumber":"605",
    "addr:postcode":"58318",
    "addr:street":"Thompson St",
    "iso:country":"US",
    "sg:address":"605 Thompson St",
    "sg:city":"Bottineau",
    "sg:classifiers":[
        {
            "category":"Utilities",
            "subcategory":"Mobile Phone",
            "type":"Services"
        }
    ],
    "sg:phone":"+1 701 228 2520",
    "sg:postcode":"58318",
    "sg:province":"ND",
    "sg:tags":[
        "telephone",
        "cellular"
    ],
    "wof:name":"Mc Guire's Cellular Svc",
    "wof:placetype":"venue"
},
  "geometry": {"coordinates":[-100.44425200000001,48.826266],"type":"Point"}
}