{
  "type": "Feature",
  "properties": {
    "iso:country":"US",
    "sg:address":"9054 38th St SE",
    "sg:city":"Jamestown",
    "sg:phone":"+1 701 252 8291",
    "sg:postcode":"58401",
    "sg:province":"ND",
    "sg:tags":[
        "farm",
        "wheat"
    ],
    "wof:name":"Terry Exner",
    "wof:placetype":"venue"
},
  "geometry": {"coordinates":[-98.55931,46.863062],"type":"Point"}
}