{
  "type": "Feature",
  "properties": {
    "iso:country":"US",
    "sg:address":"1100 5th Ave SE",
    "sg:city":"Jamestown",
    "sg:classifiers":[
        {
            "category":"Wholesale",
            "subcategory":"Farm Supplies",
            "type":"Manufacturing & Wholesale Goods"
        }
    ],
    "sg:phone":"+1 701 252 1600",
    "sg:postcode":"58401",
    "sg:province":"ND",
    "wof:name":"Tractor Supply Co",
    "wof:placetype":"venue"
},
  "geometry": {"coordinates":[-98.70206399999999,46.89801],"type":"Point"}
}