{
  "type": "Feature",
  "properties": {
    "iso:country":"US",
    "sg:address":"3406 Dominion St",
    "sg:city":"Bismarck",
    "sg:classifiers":[
        {
            "category":"Social Services",
            "subcategory":"Adult Care",
            "type":"Services"
        }
    ],
    "sg:phone":"+1 701 258 7489",
    "sg:postcode":"58503",
    "sg:province":"ND",
    "sg:tags":[
        "residential"
    ],
    "sg:website":"www.edgewoodvista.com",
    "wof:name":"Edgewood Vista",
    "wof:placetype":"venue"
},
  "geometry": {"coordinates":[-100.78215299999999,46.84205],"type":"Point"}
}