{
  "type": "Feature",
  "properties": {
    "addr:full":"1225 Cherry St Grand Forks ND 58201",
    "addr:housenumber":"1225",
    "addr:postcode":"58201",
    "addr:street":"Cherry St",
    "iso:country":"US",
    "sg:address":"1225 Cherry St",
    "sg:city":"Grand Forks",
    "sg:classifiers":[
        {
            "category":"Wholesale",
            "subcategory":"Vending Machines",
            "type":"Manufacturing & Wholesale Goods"
        }
    ],
    "sg:phone":"+1 701 772 3272",
    "sg:postcode":"58201",
    "sg:province":"ND",
    "wof:name":"Behm's Vending & Games",
    "wof:placetype":"venue"
},
  "geometry": {"coordinates":[-97.03565399999999,47.91117],"type":"Point"}
}