{
  "type": "Feature",
  "properties": {
    "addr:full":"605 Memorial Hwy Bismarck ND 58504",
    "addr:housenumber":"605",
    "addr:postcode":"58504",
    "addr:street":"Memorial Hwy",
    "iso:country":"US",
    "sg:address":"605 Memorial Hwy",
    "sg:city":"Bismarck",
    "sg:classifiers":[
        {
            "category":"Retail",
            "subcategory":"Auto Repair",
            "type":"Services"
        }
    ],
    "sg:phone":"+1 701 223 6950",
    "sg:postcode":"58504",
    "sg:province":"ND",
    "sg:tags":[
        "repairing",
        "automobile"
    ],
    "wof:name":"Capital City Automotive",
    "wof:placetype":"venue"
},
  "geometry": {"coordinates":[-100.80200000000001,46.805559],"type":"Point"}
}