{
  "type": "Feature",
  "properties": {
    "addr:full":"530 Commerce St Grafton ND 58237",
    "addr:housenumber":"530",
    "addr:postcode":"58237",
    "addr:street":"Commerce St",
    "iso:country":"US",
    "sg:address":"530 Commerce St",
    "sg:city":"Grafton",
    "sg:classifiers":[
        {
            "category":"Building & Trades",
            "subcategory":"Construction",
            "type":"Services"
        }
    ],
    "sg:phone":"+1 701 352 1866",
    "sg:postcode":"58237",
    "sg:province":"ND",
    "sg:tags":[
        "concrete",
        "masonry",
        "contractor"
    ],
    "wof:name":"Dupree Masonry & Concrete",
    "wof:placetype":"venue"
},
  "geometry": {"coordinates":[-97.401646,48.43253],"type":"Point"}
}