{
  "type": "Feature",
  "properties": {
    "iso:country":"US",
    "sg:address":"839 Cherry Ave",
    "sg:city":"Dickinson",
    "sg:classifiers":[
        {
            "category":"Retail",
            "subcategory":"Auto Repair",
            "type":"Services"
        }
    ],
    "sg:phone":"+1 701 873 4210",
    "sg:postcode":"58601",
    "sg:province":"ND",
    "sg:tags":[
        "transmission"
    ],
    "wof:name":"Dakota Transmission",
    "wof:placetype":"venue"
},
  "geometry": {"coordinates":[-102.774941,46.887813],"type":"Point"}
}