{
  "type": "Feature",
  "properties": {
    "iso:country":"US",
    "sg:address":"805 E Broadway",
    "sg:city":"Williston",
    "sg:classifiers":[
        {
            "category":"Building & Trades",
            "subcategory":"Construction",
            "type":"Services"
        }
    ],
    "sg:phone":"+1 701 572 3460",
    "sg:postcode":"58801",
    "sg:province":"ND",
    "sg:tags":[
        "water",
        "well",
        "drilling"
    ],
    "sg:website":"www.vetcogray.com",
    "wof:name":"Vetco Gray Inc",
    "wof:placetype":"venue"
},
  "geometry": {"coordinates":[-103.608198,48.147095],"type":"Point"}
}