{
  "type": "Feature",
  "properties": {
    "addr:full":"12100 268th St NW Berthold ND 58718",
    "addr:housenumber":"12100",
    "addr:postcode":"58718",
    "addr:street":"268Th St Nw",
    "iso:country":"US",
    "sg:address":"12100 268th St NW",
    "sg:city":"Berthold",
    "sg:classifiers":[
        {
            "category":"Local Transit",
            "type":"Transportation"
        }
    ],
    "sg:phone":"+1 701 453 3537",
    "sg:postcode":"58718",
    "sg:province":"ND",
    "sg:tags":[
        "ambulance"
    ],
    "wof:name":"Berthold City Ambulance",
    "wof:placetype":"venue"
},
  "geometry": {"coordinates":[-101.706406,48.36424],"type":"Point"}
}