{
  "type": "Feature",
  "properties": {
    "iso:country":"US",
    "sg:address":"819 8th St E",
    "sg:city":"West Fargo",
    "sg:classifiers":[
        {
            "category":"Retail",
            "subcategory":"Car Wash",
            "type":"Services"
        }
    ],
    "sg:phone":"+1 701 492 7401",
    "sg:postcode":"58078",
    "sg:province":"ND",
    "sg:tags":[
        "automobile",
        "detail",
        "clean"
    ],
    "wof:name":"Trendsetters Automotive",
    "wof:placetype":"venue"
},
  "geometry": {"coordinates":[-96.88595100000001,46.866579],"type":"Point"}
}