{
  "type": "Feature",
  "properties": {
    "addr:full":"107 Main St Wheatland ND 58079",
    "addr:housenumber":"107",
    "addr:postcode":"58079",
    "addr:street":"Main St",
    "iso:country":"US",
    "sg:address":"107 Main St",
    "sg:city":"Wheatland",
    "sg:classifiers":[
        {
            "category":"Shopping",
            "subcategory":"Computers & Home Electronics",
            "type":"Retail Goods"
        }
    ],
    "sg:phone":"+1 701 347 4143",
    "sg:postcode":"58079",
    "sg:province":"ND",
    "sg:tags":[
        "bar"
    ],
    "wof:name":"R & L Enterprises",
    "wof:placetype":"venue"
},
  "geometry": {"coordinates":[-97.35519600000001,46.774391],"type":"Point"}
}