{
  "type": "Feature",
  "properties": {
    "iso:country":"US",
    "sg:address":"3745 State Hwy 25",
    "sg:city":"Mandan",
    "sg:classifiers":[
        {
            "category":"Manufacturing",
            "subcategory":"Tools & Machinery",
            "type":"Manufacturing & Wholesale Goods"
        }
    ],
    "sg:phone":"+1 701 663 6016",
    "sg:postcode":"58554",
    "sg:province":"ND",
    "sg:tags":[
        "farm",
        "equipment"
    ],
    "wof:name":"Vermer Baler Sales",
    "wof:placetype":"venue"
},
  "geometry": {"coordinates":[-101.00820899999999,46.902983],"type":"Point"}
}