{
  "type": "Feature",
  "properties": {
    "addr:full":"2400 Main Ave Fargo ND 58103",
    "addr:housenumber":"2400",
    "addr:postcode":"58103",
    "addr:street":"Main Ave",
    "iso:country":"US",
    "sg:address":"2400 Main Ave",
    "sg:city":"Fargo",
    "sg:classifiers":[
        {
            "category":"Home & Garden",
            "subcategory":"Building Materials",
            "type":"Retail Goods"
        }
    ],
    "sg:phone":"+1 701 232 3281",
    "sg:postcode":"58103",
    "sg:province":"ND",
    "wof:name":"Simonson Lumber Co",
    "wof:placetype":"venue"
},
  "geometry": {"coordinates":[-96.817848,46.875856],"type":"Point"}
}