{
  "type": "Feature",
  "properties": {
    "addr:full":"602 Lansing Ln Bismarck ND 58504",
    "addr:housenumber":"602",
    "addr:postcode":"58504",
    "addr:street":"Lansing Ln",
    "iso:country":"US",
    "sg:address":"602 Lansing Ln",
    "sg:city":"Bismarck",
    "sg:classifiers":[
        {
            "category":"Government",
            "subcategory":"Office",
            "type":"Public Place"
        }
    ],
    "sg:phone":"+1 701 258 6426",
    "sg:postcode":"58504",
    "sg:province":"ND",
    "sg:tags":[
        "federal",
        "program"
    ],
    "wof:name":"O N Fossland Rus",
    "wof:placetype":"venue"
},
  "geometry": {"coordinates":[-100.78330099999999,46.793031],"type":"Point"}
}