{
  "type": "Feature",
  "properties": {
    "iso:country":"US",
    "sg:address":"3222 28th St SW",
    "sg:city":"Fargo",
    "sg:classifiers":[
        {
            "category":"Social Services",
            "type":"Services"
        }
    ],
    "sg:phone":"+1 701 356 2273",
    "sg:postcode":"58104",
    "sg:province":"ND",
    "sg:tags":[
        "counselor",
        "marriage",
        "family"
    ],
    "wof:name":"Accent On Care Counseling",
    "wof:placetype":"venue"
},
  "geometry": {"coordinates":[-96.825625,46.832361],"type":"Point"}
}