{
  "type": "Feature",
  "properties": {
    "iso:country":"US",
    "sg:address":"9708 Robin Rd",
    "sg:city":"Horace",
    "sg:classifiers":[
        {
            "category":"Building & Trades",
            "subcategory":"Plumbing",
            "type":"Services"
        }
    ],
    "sg:phone":"+1 701 433 0401",
    "sg:postcode":"58047",
    "sg:province":"ND",
    "sg:tags":[
        "contractor"
    ],
    "wof:name":"All American Plumbing & Heatin",
    "wof:placetype":"venue"
},
  "geometry": {"coordinates":[-96.91944599999999,46.749526],"type":"Point"}
}