{
  "type": "Feature",
  "properties": {
    "iso:country":"US",
    "sg:address":"515 N 5th St",
    "sg:city":"Bismarck",
    "sg:classifiers":[
        {
            "category":"Professional",
            "subcategory":"Business Services",
            "type":"Services"
        }
    ],
    "sg:phone":"+1 701 222 6746",
    "sg:postcode":"58501",
    "sg:province":"ND",
    "sg:tags":[
        "project",
        "for",
        "library"
    ],
    "wof:name":"Library Foundation Inc",
    "wof:placetype":"venue"
},
  "geometry": {"coordinates":[-100.784432,46.810489],"type":"Point"}
}