{
  "type": "Feature",
  "properties": {
    "addr:full":"2921 N 11th St Bismarck ND 58503",
    "addr:housenumber":"2921",
    "addr:postcode":"58503",
    "addr:street":"N 11Th St",
    "iso:country":"US",
    "sg:address":"2921 N 11th St",
    "sg:city":"Bismarck",
    "sg:classifiers":[
        {
            "category":"Professional",
            "subcategory":"Advertising",
            "type":"Services"
        }
    ],
    "sg:phone":"+1 701 250 6680",
    "sg:postcode":"58503",
    "sg:province":"ND",
    "wof:name":"Capitol City Advertising",
    "wof:placetype":"venue"
},
  "geometry": {"coordinates":[-100.775402,46.839032],"type":"Point"}
}