{
  "type": "Feature",
  "properties": {
    "addr:full":"635 6th Ave SE Valley City ND 58072",
    "addr:housenumber":"635",
    "addr:postcode":"58072",
    "addr:street":"6Th Ave Se",
    "iso:country":"US",
    "sg:address":"635 6th Ave SE",
    "sg:city":"Valley City",
    "sg:classifiers":[
        {
            "category":"Travel",
            "subcategory":"Travel Agent",
            "type":"Entertainment"
        }
    ],
    "sg:phone":"+1 701 845 1683",
    "sg:postcode":"58072",
    "sg:province":"ND",
    "sg:tags":[
        "agency"
    ],
    "wof:name":"First Rate Travel Inc",
    "wof:placetype":"venue"
},
  "geometry": {"coordinates":[-97.99437,46.917793],"type":"Point"}
}