{
  "type": "Feature",
  "properties": {
    "iso:country":"US",
    "sg:address":"3994 35th Ave",
    "sg:city":"Mandan",
    "sg:classifiers":[
        {
            "category":"Retail",
            "subcategory":"Portrait Studio",
            "type":"Services"
        }
    ],
    "sg:phone":"+1 701 667 1037",
    "sg:postcode":"58554",
    "sg:province":"ND",
    "sg:tags":[
        "photo"
    ],
    "wof:name":"Photography By Fay",
    "wof:placetype":"venue"
},
  "geometry": {"coordinates":[-101.197862,46.847646],"type":"Point"}
}