{
  "type": "Feature",
  "properties": {
    "addr:full":"802 N 4th St Grand Forks ND 58203",
    "addr:housenumber":"802",
    "addr:postcode":"58203",
    "addr:street":"N 4Th St",
    "iso:country":"US",
    "sg:address":"802 N 4th St",
    "sg:city":"Grand Forks",
    "sg:classifiers":[
        {
            "category":"Building & Trades",
            "subcategory":"Construction",
            "type":"Services"
        }
    ],
    "sg:phone":"+1 701 335 4013",
    "sg:postcode":"58203",
    "sg:province":"ND",
    "sg:tags":[
        "home",
        "builder"
    ],
    "wof:name":"Development Homes Inc",
    "wof:placetype":"venue"
},
  "geometry": {"coordinates":[-97.042813,47.930969],"type":"Point"}
}