{
  "type": "Feature",
  "properties": {
    "iso:country":"US",
    "sg:address":"101 Main St",
    "sg:city":"Williston",
    "sg:classifiers":[
        {
            "category":"Personal",
            "subcategory":"Tattoo Parlor",
            "type":"Services"
        }
    ],
    "sg:phone":"+1 701 774 8282",
    "sg:postcode":"58801",
    "sg:province":"ND",
    "sg:tags":[
        "tattooing"
    ],
    "wof:name":"Skinful Pleasures",
    "wof:placetype":"venue"
},
  "geometry": {"coordinates":[-103.621472,48.144529],"type":"Point"}
}