{
  "type": "Feature",
  "properties": {
    "iso:country":"US",
    "sg:address":"406 4th Ave",
    "sg:city":"Devils Lake",
    "sg:classifiers":[
        {
            "category":"Education",
            "subcategory":"School",
            "type":"Public Place"
        }
    ],
    "sg:phone":"+1 701 662 7694",
    "sg:postcode":"58301",
    "sg:province":"ND",
    "wof:name":"Devils Lake Media Ctr",
    "wof:placetype":"venue"
},
  "geometry": {"coordinates":[-98.8603,48.112215],"type":"Point"}
}