{
  "type": "Feature",
  "properties": {
    "addr:full":"13 1st St NE Hillsboro ND 58045",
    "addr:housenumber":"13",
    "addr:postcode":"58045",
    "addr:street":"1St St Ne",
    "iso:country":"US",
    "sg:address":"13 1st St NE",
    "sg:city":"Hillsboro",
    "sg:classifiers":[
        {
            "category":"Manufacturing",
            "subcategory":"Pet Food",
            "type":"Manufacturing & Wholesale Goods"
        },
        {
            "category":"Farming",
            "subcategory":"Farm & Veterinary Services",
            "type":"Manufacturing & Wholesale Goods"
        }
    ],
    "sg:phone":"+1 701 636 5300",
    "sg:postcode":"58045",
    "sg:province":"ND",
    "sg:tags":[
        "seed",
        "grain",
        "cleaning",
        "mfg"
    ],
    "wof:name":"Red River Valley Seed Company",
    "wof:placetype":"venue"
},
  "geometry": {"coordinates":[-97.059911,47.404009],"type":"Point"}
}