{
  "type": "Feature",
  "properties": {
    "iso:country":"US",
    "sg:address":"300 18th Ave SW",
    "sg:city":"Minot",
    "sg:classifiers":[
        {
            "category":"Autos & Motor Vehicles",
            "subcategory":"Auto Supplies",
            "type":"Retail Goods"
        }
    ],
    "sg:phone":"+1 701 852 5160",
    "sg:postcode":"58701",
    "sg:province":"ND",
    "sg:tags":[
        "trailer",
        "hitch"
    ],
    "wof:name":"Ken's Southdale Rentals",
    "wof:placetype":"venue"
},
  "geometry": {"coordinates":[-101.296717,48.214631],"type":"Point"}
}