{
  "type": "Feature",
  "properties": {
    "iso:country":"US",
    "sg:address":"1710 Burnt Boat Dr",
    "sg:city":"Bismarck",
    "sg:classifiers":[
        {
            "category":"Organizations",
            "subcategory":"Professional Association",
            "type":"Services"
        }
    ],
    "sg:phone":"+1 701 222 0128",
    "sg:postcode":"58503",
    "sg:province":"ND",
    "sg:website":"www.ndpealentil.org",
    "wof:name":"N D Dry Pea & Lentil Office",
    "wof:placetype":"venue"
},
  "geometry": {"coordinates":[-100.820013,46.830305],"type":"Point"}
}