{
  "type": "Feature",
  "properties": {
    "iso:country":"US",
    "sg:address":"750 119th St NE",
    "sg:city":"Menoken",
    "sg:classifiers":[
        {
            "category":"Professional",
            "subcategory":"Business Services",
            "type":"Services"
        }
    ],
    "sg:phone":"+1 701 258 3933",
    "sg:postcode":"58558",
    "sg:province":"ND",
    "wof:name":"Mariner Construction Inc",
    "wof:placetype":"venue"
},
  "geometry": {"coordinates":[-100.60457599999999,46.815035],"type":"Point"}
}