{
  "type": "Feature",
  "properties": {
    "addr:full":"503 2nd St W Williston ND 58801",
    "addr:housenumber":"503",
    "addr:postcode":"58801",
    "addr:street":"2Nd St W",
    "iso:country":"US",
    "sg:address":"503 2nd St W",
    "sg:city":"Williston",
    "sg:classifiers":[
        {
            "category":"Autos & Motor Vehicles",
            "subcategory":"Motorcycle Sales",
            "type":"Retail Goods"
        }
    ],
    "sg:phone":"+1 701 572 3382",
    "sg:postcode":"58801",
    "sg:province":"ND",
    "sg:tags":[
        "scooter",
        "boat"
    ],
    "wof:name":"Arnie's Motorcycle Sales",
    "wof:placetype":"venue"
},
  "geometry": {"coordinates":[-103.631739,48.145127],"type":"Point"}
}