{
  "type": "Feature",
  "properties": {
    "iso:country":"US",
    "sg:address":"816 11th St E",
    "sg:city":"Dickinson",
    "sg:classifiers":[
        {
            "category":"Organizations",
            "subcategory":"Religious Organization",
            "type":"Services"
        }
    ],
    "sg:phone":"+1 701 225 5337",
    "sg:postcode":"58601",
    "sg:province":"ND",
    "wof:name":"Heights Of Glory Church Of God",
    "wof:placetype":"venue"
},
  "geometry": {"coordinates":[-102.771142,46.891652],"type":"Point"}
}