{
  "type": "Feature",
  "properties": {
    "iso:country":"US",
    "sg:address":"818 Kennedy Ct",
    "sg:city":"Fargo",
    "sg:classifiers":[
        {
            "category":"Building & Trades",
            "subcategory":"Landscaping Services",
            "type":"Services"
        }
    ],
    "sg:phone":"+1 701 239 0397",
    "sg:postcode":"58102",
    "sg:province":"ND",
    "sg:tags":[
        "designer",
        "landscape"
    ],
    "wof:name":"Landscape Design",
    "wof:placetype":"venue"
},
  "geometry": {"coordinates":[-96.792423,46.887854],"type":"Point"}
}