{
  "type": "Feature",
  "properties": {
    "addr:full":"3095 19th St NE Manvel ND 58256",
    "addr:housenumber":"3095",
    "addr:postcode":"58256",
    "addr:street":"19Th St Ne",
    "iso:country":"US",
    "sg:address":"3095 19th St NE",
    "sg:city":"Manvel",
    "sg:classifiers":[
        {
            "category":"Farming",
            "subcategory":"Livestock Farm",
            "type":"Manufacturing & Wholesale Goods"
        }
    ],
    "sg:phone":"+1 701 696 2572",
    "sg:postcode":"58256",
    "sg:province":"ND",
    "sg:tags":[
        "specialty",
        "animal"
    ],
    "wof:name":"North Country Sports",
    "wof:placetype":"venue"
},
  "geometry": {"coordinates":[-97.234657,48.119152],"type":"Point"}
}