{
  "type": "Feature",
  "properties": {
    "iso:country":"US",
    "sg:address":"3201 32nd St S",
    "sg:city":"Fargo",
    "sg:classifiers":[
        {
            "category":"Building & Trades",
            "subcategory":"Equipment Rental",
            "type":"Services"
        }
    ],
    "sg:phone":"+1 701 232 4469",
    "sg:postcode":"58104",
    "sg:province":"ND",
    "sg:tags":[
        "yard"
    ],
    "sg:website":"www.ur.com",
    "wof:name":"United Rentals",
    "wof:placetype":"venue"
},
  "geometry": {"coordinates":[-96.83045799999999,46.831596],"type":"Point"}
}