{
  "type": "Feature",
  "properties": {
    "addr:full":"1735 14th St NW Turtle Lake ND 58575",
    "addr:housenumber":"1735",
    "addr:postcode":"58575",
    "addr:street":"14Th St Nw Turtle",
    "iso:country":"US",
    "sg:address":"1735 14th St NW",
    "sg:city":"Turtle Lake",
    "sg:classifiers":[
        {
            "category":"Farming",
            "subcategory":"Livestock Farm",
            "type":"Manufacturing & Wholesale Goods"
        }
    ],
    "sg:phone":"+1 701 448 2498",
    "sg:postcode":"58575",
    "sg:province":"ND",
    "sg:tags":[
        "beef",
        "feedlot",
        "cattle"
    ],
    "wof:name":"Waldo Westrum",
    "wof:placetype":"venue"
},
  "geometry": {"coordinates":[-100.953726,47.617918],"type":"Point"}
}