{
  "type": "Feature",
  "properties": {
    "iso:country":"US",
    "sg:address":"1452 14th St SW",
    "sg:city":"Dickinson",
    "sg:classifiers":[
        {
            "category":"Wholesale",
            "subcategory":"Hardware",
            "type":"Manufacturing & Wholesale Goods"
        },
        {
            "category":"Building & Trades",
            "subcategory":"Plumbing",
            "type":"Services"
        }
    ],
    "sg:phone":"+1 701 483 5294",
    "sg:postcode":"58601",
    "sg:province":"ND",
    "sg:tags":[
        "plumbing",
        "c",
        "contractor"
    ],
    "wof:name":"Mann's Plumbing & Heating",
    "wof:placetype":"venue"
},
  "geometry": {"coordinates":[-102.80701500000001,46.851397],"type":"Point"}
}