{
  "type": "Feature",
  "properties": {
    "iso:country":"US",
    "sg:address":"31541 5th Ave NE",
    "sg:city":"Sterling",
    "sg:classifiers":[
        {
            "category":"Freight",
            "type":"Transportation"
        }
    ],
    "sg:phone":"+1 701 387 4554",
    "sg:postcode":"58501",
    "sg:province":"ND",
    "sg:tags":[
        "cartage",
        "trucking"
    ],
    "wof:name":"B & K Trucking",
    "wof:placetype":"venue"
},
  "geometry": {"coordinates":[-100.287173,46.80779],"type":"Point"}
}