{
  "type": "Feature",
  "properties": {
    "addr:full":"12925 Co Rd 1 Walhalla ND 58282",
    "addr:housenumber":"12925",
    "addr:postcode":"58282",
    "addr:street":"Co Rd 1",
    "iso:country":"US",
    "sg:address":"12925 Co Rd 1",
    "sg:city":"Walhalla",
    "sg:classifiers":[
        {
            "category":"Farming",
            "subcategory":"Farm",
            "type":"Manufacturing & Wholesale Goods"
        }
    ],
    "sg:phone":"+1 701 549 2687",
    "sg:postcode":"58282",
    "sg:province":"ND",
    "wof:name":"Berg Brothers",
    "wof:placetype":"venue"
},
  "geometry": {"coordinates":[-97.879713,48.876735],"type":"Point"}
}