{
  "type": "Feature",
  "properties": {
    "iso:country":"US",
    "sg:address":"201 Missile Ave",
    "sg:city":"Minot",
    "sg:classifiers":[
        {
            "category":"Health Services",
            "subcategory":"Doctor",
            "type":"Services"
        }
    ],
    "sg:phone":"+1 701 723 2992",
    "sg:postcode":"58704",
    "sg:province":"ND",
    "sg:tags":[
        "medical"
    ],
    "wof:name":"Wozani Wellness Ctr",
    "wof:placetype":"venue"
},
  "geometry": {"coordinates":[-101.32180700000001,48.418712],"type":"Point"}
}