{
  "type": "Feature",
  "properties": {
    "addr:full":"208 13th St SW Minot ND 58701",
    "addr:housenumber":"208",
    "addr:postcode":"58701",
    "addr:street":"13Th St Sw",
    "iso:country":"US",
    "sg:address":"208 13th St SW",
    "sg:city":"Minot",
    "sg:classifiers":[
        {
            "category":"Building & Trades",
            "subcategory":"Construction",
            "type":"Services"
        }
    ],
    "sg:phone":"+1 701 839 0704",
    "sg:postcode":"58701",
    "sg:province":"ND",
    "sg:tags":[
        "contractor"
    ],
    "wof:name":"Panasuk Drywall",
    "wof:placetype":"venue"
},
  "geometry": {"coordinates":[-101.312853,48.234146],"type":"Point"}
}