{
  "type": "Feature",
  "properties": {
    "iso:country":"US",
    "sg:address":"34 W Villard St",
    "sg:city":"Dickinson",
    "sg:classifiers":[
        {
            "category":"Shopping",
            "type":"Retail Goods"
        }
    ],
    "sg:phone":"+1 701 225 3178",
    "sg:postcode":"58601",
    "sg:province":"ND",
    "sg:tags":[
        "merchandise"
    ],
    "wof:name":"Paw & Claw Pet Palace",
    "wof:placetype":"venue"
},
  "geometry": {"coordinates":[-102.78592,46.878811],"type":"Point"}
}