{
  "type": "Feature",
  "properties": {
    "iso:country":"US",
    "sg:address":"1338 Gateway Dr",
    "sg:city":"Fargo",
    "sg:classifiers":[
        {
            "category":"Personal",
            "subcategory":"Beauty Salon",
            "type":"Services"
        }
    ],
    "sg:phone":"+1 701 241 7700",
    "sg:postcode":"58103",
    "sg:province":"ND",
    "wof:name":"Kristen's Kreations",
    "wof:placetype":"venue"
},
  "geometry": {"coordinates":[-96.82454199999999,46.859564],"type":"Point"}
}