{
  "type": "Feature",
  "properties": {
    "iso:country":"US",
    "sg:address":"417 Main Ave",
    "sg:city":"Fargo",
    "sg:classifiers":[
        {
            "category":"Building & Trades",
            "subcategory":"Electrical",
            "type":"Services"
        },
        {
            "category":"Wholesale",
            "subcategory":"Electrical",
            "type":"Manufacturing & Wholesale Goods"
        }
    ],
    "sg:phone":"+1 701 239 4623",
    "sg:postcode":"58103",
    "sg:province":"ND",
    "sg:tags":[
        "sound",
        "equipment",
        "installation",
        "system",
        "communication"
    ],
    "sg:website":"www.tricorneaudio.com",
    "wof:name":"Tricorne Audio Inc",
    "wof:placetype":"venue"
},
  "geometry": {"coordinates":[-96.787978,46.874452],"type":"Point"}
}