{
  "type": "Feature",
  "properties": {
    "iso:country":"US",
    "sg:address":"2210 11th Ave S",
    "sg:city":"Grand Forks",
    "sg:classifiers":[
        {
            "category":"Banks & Credit Unions",
            "subcategory":"Financial Services",
            "type":"Services"
        }
    ],
    "sg:phone":"+1 701 775 5193",
    "sg:postcode":"58201",
    "sg:province":"ND",
    "sg:tags":[
        "investment",
        "closed"
    ],
    "wof:name":"Alvis B Amble",
    "wof:placetype":"venue"
},
  "geometry": {"coordinates":[-97.062321,47.911307],"type":"Point"}
}