{
  "type": "Feature",
  "properties": {
    "iso:country":"US",
    "sg:address":"316 Pacific Ave",
    "sg:city":"Thompson",
    "sg:classifiers":[
        {
            "category":"Manufacturing",
            "subcategory":"Pottery",
            "type":"Manufacturing & Wholesale Goods"
        }
    ],
    "sg:phone":"+1 701 599 2582",
    "sg:postcode":"58278",
    "sg:province":"ND",
    "wof:name":"Drees Ceramics",
    "wof:placetype":"venue"
},
  "geometry": {"coordinates":[-97.109566,47.775757],"type":"Point"}
}