{
  "type": "Feature",
  "properties": {
    "addr:full":"914 Page Dr S Fargo ND 58103",
    "addr:housenumber":"914",
    "addr:postcode":"58103",
    "addr:street":"Page Dr S",
    "iso:country":"US",
    "sg:address":"914 Page Dr S",
    "sg:city":"Fargo",
    "sg:classifiers":[
        {
            "category":"Building & Trades",
            "subcategory":"Construction",
            "type":"Services"
        }
    ],
    "sg:phone":"+1 701 365 0365",
    "sg:postcode":"58103",
    "sg:province":"ND",
    "sg:tags":[
        "system",
        "specialty",
        "heating",
        "contractor",
        "air conditioning"
    ],
    "sg:website":"http://www.fargo-hvac-ca.com",
    "wof:name":"Custom Aire's One Hour Heating & Air Conditioning",
    "wof:placetype":"venue"
},
  "geometry": {"coordinates":[-96.827504,46.866282],"type":"Point"}
}