{
  "type": "Feature",
  "properties": {
    "iso:country":"US",
    "sg:address":"205 14th St W",
    "sg:city":"Dickinson",
    "sg:classifiers":[
        {
            "category":"Food & Beverages",
            "subcategory":"Bakery",
            "type":"Retail Goods"
        }
    ],
    "sg:phone":"+1 701 483 4726",
    "sg:postcode":"58601",
    "sg:province":"ND",
    "sg:tags":[
        "baker"
    ],
    "wof:name":"Twisted Bakery Inc",
    "wof:placetype":"venue"
},
  "geometry": {"coordinates":[-102.803167,46.897228],"type":"Point"}
}