{
  "type": "Feature",
  "properties": {
    "iso:country":"US",
    "sg:address":"3531 Memorial Hwy",
    "sg:city":"Mandan",
    "sg:classifiers":[
        {
            "category":"Freight",
            "type":"Transportation"
        }
    ],
    "sg:phone":"+1 701 663 5884",
    "sg:postcode":"58554",
    "sg:province":"ND",
    "sg:tags":[
        "trucking"
    ],
    "wof:name":"Royce Byron Trucking",
    "wof:placetype":"venue"
},
  "geometry": {"coordinates":[-100.849733,46.81795],"type":"Point"}
}