{
  "type": "Feature",
  "properties": {
    "addr:full":"304 Roberts St N Fargo ND 58102",
    "addr:housenumber":"304",
    "addr:postcode":"58102",
    "addr:street":"Roberts St N",
    "iso:country":"US",
    "sg:address":"304 Roberts St N",
    "sg:city":"Fargo",
    "sg:classifiers":[
        {
            "category":"Social Services",
            "type":"Services"
        }
    ],
    "sg:phone":"+1 701 232 5565",
    "sg:postcode":"58102",
    "sg:province":"ND",
    "sg:tags":[
        "organization",
        "welfare"
    ],
    "wof:name":"Salvation Army",
    "wof:placetype":"venue"
},
  "geometry": {"coordinates":[-96.789024,46.879938],"type":"Point"}
}