{
  "type": "Feature",
  "properties": {
    "addr:full":"410 Anthony St Rutland ND 58067",
    "addr:housenumber":"410",
    "addr:postcode":"58067",
    "addr:street":"Anthony St",
    "iso:country":"US",
    "sg:address":"410 Anthony St",
    "sg:city":"Rutland",
    "sg:classifiers":[
        {
            "category":"Building & Trades",
            "subcategory":"Construction",
            "type":"Services"
        }
    ],
    "sg:phone":"+1 701 724 4043",
    "sg:postcode":"58067",
    "sg:province":"ND",
    "sg:tags":[
        "fabricator",
        "metal"
    ],
    "wof:name":"Dakota Precision Fabricating",
    "wof:placetype":"venue"
},
  "geometry": {"coordinates":[-97.503028,46.052111],"type":"Point"}
}