{
  "type": "Feature",
  "properties": {
    "addr:full":"3518 Hidden Ct West Fargo ND 58078",
    "addr:housenumber":"3518",
    "addr:postcode":"58078",
    "addr:street":"Hidden Ct",
    "iso:country":"US",
    "sg:address":"3518 Hidden Ct",
    "sg:city":"West Fargo",
    "sg:classifiers":[
        {
            "category":"Manufacturing",
            "subcategory":"Soap",
            "type":"Manufacturing & Wholesale Goods"
        }
    ],
    "sg:phone":"+1 701 281 5687",
    "sg:postcode":"58078",
    "sg:province":"ND",
    "sg:tags":[
        "detergent",
        "industrial",
        "organic",
        "mfg"
    ],
    "wof:name":"Ecolab Inc",
    "wof:placetype":"venue"
},
  "geometry": {"coordinates":[-96.900629,46.827474],"type":"Point"}
}