{
  "type": "Feature",
  "properties": {
    "iso:country":"US",
    "sg:address":"1655 State Hwy 49",
    "sg:city":"Beulah",
    "sg:classifiers":[
        {
            "category":"Farming",
            "subcategory":"Farm",
            "type":"Manufacturing & Wholesale Goods"
        }
    ],
    "sg:phone":"+1 701 873 5310",
    "sg:postcode":"58523",
    "sg:province":"ND",
    "wof:name":"Erickson Farms",
    "wof:placetype":"venue"
},
  "geometry": {"coordinates":[-101.78521000000001,47.17731],"type":"Point"}
}