{
  "type": "Feature",
  "properties": {
    "iso:country":"US",
    "sg:address":"230 4th St NW",
    "sg:city":"Valley City",
    "sg:classifiers":[
        {
            "category":"Government",
            "subcategory":"Office",
            "type":"Public Place"
        }
    ],
    "sg:phone":"+1 701 733 2241",
    "sg:postcode":"58072",
    "sg:province":"ND",
    "sg:tags":[
        "executive"
    ],
    "wof:name":"Barnes County Shop",
    "wof:placetype":"venue"
},
  "geometry": {"coordinates":[-98.005095,46.926353],"type":"Point"}
}