{
  "type": "Feature",
  "properties": {
    "iso:country":"US",
    "sg:address":"39 Main St W",
    "sg:city":"Mayville",
    "sg:classifiers":[
        {
            "category":"Home & Garden",
            "subcategory":"Hardware",
            "type":"Retail Goods"
        }
    ],
    "sg:phone":"+1 701 788 2836",
    "sg:postcode":"58257",
    "sg:province":"ND",
    "sg:tags":[
        "store"
    ],
    "wof:name":"May-Port Hardware Hank",
    "wof:placetype":"venue"
},
  "geometry": {"coordinates":[-97.32686099999999,47.499961],"type":"Point"}
}