{
  "type": "Feature",
  "properties": {
    "iso:country":"US",
    "sg:address":"3066 118th Ave SE",
    "sg:city":"Valley City",
    "sg:classifiers":[
        {
            "category":"Shopping",
            "subcategory":"Shoes",
            "type":"Retail Goods"
        }
    ],
    "sg:phone":"+1 701 845 1054",
    "sg:postcode":"58072",
    "sg:province":"ND",
    "wof:name":"KS Crafts",
    "wof:placetype":"venue"
},
  "geometry": {"coordinates":[-97.975504,46.968874],"type":"Point"}
}