{
  "type": "Feature",
  "properties": {
    "addr:full":"625 13th Ave W West Fargo ND 58078",
    "addr:housenumber":"625",
    "addr:postcode":"58078",
    "addr:street":"13Th Ave W",
    "iso:country":"US",
    "sg:address":"625 13th Ave W",
    "sg:city":"West Fargo",
    "sg:classifiers":[
        {
            "category":"Social Services",
            "type":"Services"
        }
    ],
    "sg:phone":"+1 701 232 3900",
    "sg:postcode":"58078",
    "sg:province":"ND",
    "sg:tags":[
        "organization",
        "welfare"
    ],
    "sg:website":"www.clotheshelpingkids.org",
    "wof:name":"Clothes Helping Kids Inc",
    "wof:placetype":"venue"
},
  "geometry": {"coordinates":[-96.909645,46.862508],"type":"Point"}
}