{
  "type": "Feature",
  "properties": {
    "addr:full":"8550 State Hwy 200 Glenfield ND 58443",
    "addr:housenumber":"8550",
    "addr:postcode":"200;58443",
    "addr:street":"State Hwy",
    "iso:country":"US",
    "sg:address":"8550 State Hwy 200",
    "sg:city":"Glenfield",
    "sg:classifiers":[
        {
            "category":"Farming",
            "subcategory":"Livestock Farm",
            "type":"Manufacturing & Wholesale Goods"
        }
    ],
    "sg:phone":"+1 701 674 3346",
    "sg:postcode":"58443",
    "sg:province":"ND",
    "sg:tags":[
        "corn",
        "wheat",
        "feedlot",
        "beef",
        "cattle"
    ],
    "wof:name":"Frankie Vlach",
    "wof:placetype":"venue"
},
  "geometry": {"coordinates":[-98.72393599999999,47.457097],"type":"Point"}
}