{
  "type": "Feature",
  "properties": {
    "iso:country":"US",
    "sg:address":"421 52nd Ave NE",
    "sg:city":"Sykeston",
    "sg:phone":"+1 701 984 2797",
    "sg:postcode":"58486",
    "sg:province":"ND",
    "sg:tags":[
        "farm",
        "grain",
        "cash"
    ],
    "wof:name":"Richter Jamie & C C Wells",
    "wof:placetype":"venue"
},
  "geometry": {"coordinates":[-99.436899,47.474487],"type":"Point"}
}