{
  "type": "Feature",
  "properties": {
    "addr:full":"421 52nd Ave NE Sykeston ND 58486",
    "addr:housenumber":"421",
    "addr:postcode":"58486",
    "addr:street":"52Nd Ave Ne",
    "iso:country":"US",
    "sg:address":"421 52nd Ave NE",
    "sg:city":"Sykeston",
    "sg:phone":"+1 701 984 2797",
    "sg:postcode":"58486",
    "sg:province":"ND",
    "sg:tags":[
        "farm",
        "grain",
        "cash"
    ],
    "wof:name":"Richter Jamie & C C Wells",
    "wof:placetype":"venue"
},
  "geometry": {"coordinates":[-99.436899,47.474487],"type":"Point"}
}