{
  "type": "Feature",
  "properties": {
    "iso:country":"US",
    "sg:address":"708 2nd Ave NE",
    "sg:city":"Hillsboro",
    "sg:phone":"+1 701 636 4899",
    "sg:postcode":"58045",
    "sg:province":"ND",
    "sg:tags":[
        "farm",
        "wheat"
    ],
    "wof:name":"Joel Thorsrud",
    "wof:placetype":"venue"
},
  "geometry": {"coordinates":[-97.049555,47.406458],"type":"Point"}
}