{
  "type": "Feature",
  "properties": {
    "iso:country":"US",
    "sg:address":"404 Sheyenne St",
    "sg:city":"West Fargo",
    "sg:classifiers":[
        {
            "category":"Retail",
            "subcategory":"Animal Services",
            "type":"Services"
        }
    ],
    "sg:phone":"+1 701 282 7387",
    "sg:postcode":"58078",
    "sg:province":"ND",
    "sg:tags":[
        "pet",
        "grooming",
        "washing"
    ],
    "wof:name":"Fancy Paws Pet Salon",
    "wof:placetype":"venue"
},
  "geometry": {"coordinates":[-96.904116,46.871954],"type":"Point"}
}