{
  "type": "Feature",
  "properties": {
    "addr:full":"1815 10th St Langdon ND 58249",
    "addr:housenumber":"1815",
    "addr:postcode":"58249",
    "addr:street":"10Th St",
    "iso:country":"US",
    "sg:address":"1815 10th St",
    "sg:city":"Langdon",
    "sg:phone":"+1 701 283 5364",
    "sg:postcode":"58249",
    "sg:province":"ND",
    "sg:tags":[
        "farm",
        "wheat"
    ],
    "wof:name":"Gary Badding",
    "wof:placetype":"venue"
},
  "geometry": {"coordinates":[-98.38069400000001,48.773925],"type":"Point"}
}