{
  "type": "Feature",
  "properties": {
    "iso:country":"US",
    "sg:address":"1336 25th Ave S",
    "sg:city":"Fargo",
    "sg:classifiers":[
        {
            "category":"Food & Beverages",
            "subcategory":"Groceries & Convenience Stores",
            "type":"Retail Goods"
        }
    ],
    "sg:phone":"+1 701 297 0558",
    "sg:postcode":"58103",
    "sg:province":"ND",
    "sg:website":"www.holidaystationstores.com",
    "wof:name":"Holiday Stationstores",
    "wof:placetype":"venue"
},
  "geometry": {"coordinates":[-96.79970299999999,46.843407],"type":"Point"}
}