{
  "type": "Feature",
  "properties": {
    "iso:country":"US",
    "sg:address":"301 Main St",
    "sg:city":"Horace",
    "sg:classifiers":[
        {
            "category":"Wholesale",
            "subcategory":"Farm Supplies",
            "type":"Manufacturing & Wholesale Goods"
        },
        {
            "category":"Shopping",
            "subcategory":"Pets & Pet Supplies",
            "type":"Retail Goods"
        }
    ],
    "sg:phone":"+1 701 282 0208",
    "sg:postcode":"58047",
    "sg:province":"ND",
    "sg:tags":[
        "feed",
        "grain",
        "concentrate",
        "supplement"
    ],
    "sg:website":"http://www.dakotaprairieag.com",
    "wof:name":"Dakota Ag",
    "wof:placetype":"venue"
},
  "geometry": {"coordinates":[-96.90385000000001,46.759393],"type":"Point"}
}