{
  "type": "Feature",
  "properties": {
    "iso:country":"US",
    "sg:address":"2711 Valley Cir",
    "sg:city":"Grand Forks",
    "sg:classifiers":[
        {
            "category":"Wholesale",
            "subcategory":"Petroleum",
            "type":"Manufacturing & Wholesale Goods"
        }
    ],
    "sg:phone":"+1 701 746 9772",
    "sg:postcode":"58203",
    "sg:province":"ND",
    "sg:tags":[
        "pipe",
        "line",
        "company"
    ],
    "wof:name":"Enbridge Pipelines Nd",
    "wof:placetype":"venue"
},
  "geometry": {"coordinates":[-97.06796900000001,47.935121],"type":"Point"}
}