{
  "type": "Feature",
  "properties": {
    "iso:country":"US",
    "sg:address":"304 9th Ave",
    "sg:city":"Langdon",
    "sg:classifiers":[
        {
            "category":"Restaurant",
            "type":"Food & Drink"
        }
    ],
    "sg:phone":"+1 701 256 3377",
    "sg:postcode":"58249",
    "sg:province":"ND",
    "wof:name":"Stables Supper Club",
    "wof:placetype":"venue"
},
  "geometry": {"coordinates":[-98.369,48.761107],"type":"Point"}
}