{
  "type": "Feature",
  "properties": {
    "addr:full":"1111 22nd St NW Ruso ND 58778",
    "addr:housenumber":"1111",
    "addr:postcode":"58778",
    "addr:street":"22Nd St Nw",
    "iso:country":"US",
    "sg:address":"1111 22nd St NW",
    "sg:city":"Ruso",
    "sg:classifiers":[
        {
            "category":"Farming",
            "subcategory":"Farm & Veterinary Services",
            "type":"Manufacturing & Wholesale Goods"
        }
    ],
    "sg:phone":"+1 701 448 9102",
    "sg:postcode":"58778",
    "sg:province":"ND",
    "wof:name":"Lindteigen Wesley",
    "wof:placetype":"venue"
},
  "geometry": {"coordinates":[-100.82525099999999,47.733271],"type":"Point"}
}