{
  "type": "Feature",
  "properties": {
    "iso:country":"US",
    "sg:address":"661 Kirkwood Mall",
    "sg:city":"Bismarck",
    "sg:classifiers":[
        {
            "category":"Restaurant",
            "type":"Food & Drink"
        }
    ],
    "sg:phone":"+1 701 258 5840",
    "sg:postcode":"58504",
    "sg:province":"ND",
    "wof:name":"Grizzly's Grill & Saloon",
    "wof:placetype":"venue"
},
  "geometry": {"coordinates":[-100.78471500000001,46.799756],"type":"Point"}
}