{
  "type": "Feature",
  "properties": {
    "iso:country":"US",
    "sg:address":"712 E Bowen Ave",
    "sg:city":"Bismarck",
    "sg:classifiers":[
        {
            "category":"Social Services",
            "subcategory":"Job Training",
            "type":"Services"
        }
    ],
    "sg:phone":"+1 701 221 5857",
    "sg:postcode":"58504",
    "sg:province":"ND",
    "sg:tags":[
        "employment"
    ],
    "wof:name":"Burdick Job Corps",
    "wof:placetype":"venue"
},
  "geometry": {"coordinates":[-100.78027400000001,46.802101],"type":"Point"}
}