{
  "type": "Feature",
  "properties": {
    "iso:country":"US",
    "sg:address":"402 26th St W",
    "sg:city":"Williston",
    "sg:classifiers":[
        {
            "category":"Manufacturing",
            "subcategory":"Signs",
            "type":"Manufacturing & Wholesale Goods"
        }
    ],
    "sg:phone":"+1 701 572 4245",
    "sg:postcode":"58801",
    "sg:province":"ND",
    "wof:name":"Angie's Images",
    "wof:placetype":"venue"
},
  "geometry": {"coordinates":[-103.62984,48.168827],"type":"Point"}
}