{
  "type": "Feature",
  "properties": {
    "iso:country":"US",
    "sg:address":"2838 S University Dr",
    "sg:city":"Fargo",
    "sg:classifiers":[
        {
            "category":"Health Services",
            "subcategory":"Doctor",
            "type":"Services"
        }
    ],
    "sg:phone":"+1 701 293 0577",
    "sg:postcode":"58103",
    "sg:province":"ND",
    "wof:name":"James H Lancaster",
    "wof:placetype":"venue"
},
  "geometry": {"coordinates":[-96.79866,46.839953],"type":"Point"}
}