{
  "type": "Feature",
  "properties": {
    "iso:country":"US",
    "sg:address":"3586 18th Ave NE",
    "sg:city":"Larimore",
    "sg:classifiers":[
        {
            "category":"Government",
            "subcategory":"Office",
            "type":"Public Place"
        }
    ],
    "sg:phone":"+1 701 343 2078",
    "sg:postcode":"58251",
    "sg:province":"ND",
    "wof:name":"Grand Forks Cnty Larimore Dam",
    "wof:placetype":"venue"
},
  "geometry": {"coordinates":[-97.599772,47.932613],"type":"Point"}
}