{
  "type": "Feature",
  "properties": {
    "iso:country":"US",
    "sg:address":"1404 5th St",
    "sg:city":"Langdon",
    "sg:classifiers":[
        {
            "category":"Wholesale",
            "subcategory":"Farm Supplies",
            "type":"Manufacturing & Wholesale Goods"
        }
    ],
    "sg:phone":"+1 701 256 3736",
    "sg:postcode":"58249",
    "sg:province":"ND",
    "sg:tags":[
        "bulb",
        "seed"
    ],
    "wof:name":"Dahlgren & Co Inc",
    "wof:placetype":"venue"
},
  "geometry": {"coordinates":[-98.37230700000001,48.768255],"type":"Point"}
}