{
  "type": "Feature",
  "properties": {
    "addr:full":"202 6th Ave SW Bowman ND 58623",
    "addr:housenumber":"202",
    "addr:postcode":"58623",
    "addr:street":"6Th Ave Sw",
    "iso:country":"US",
    "sg:address":"202 6th Ave SW",
    "sg:city":"Bowman",
    "sg:classifiers":[
        {
            "category":"Health Services",
            "subcategory":"Hospital",
            "type":"Services"
        }
    ],
    "sg:phone":"+1 701 523 3632",
    "sg:postcode":"58623",
    "sg:province":"ND",
    "sg:tags":[
        "mental"
    ],
    "wof:name":"Badlands Human Svc Ctr",
    "wof:placetype":"venue"
},
  "geometry": {"coordinates":[-103.403774,46.180171],"type":"Point"}
}