{
  "type": "Feature",
  "properties": {
    "iso:country":"US",
    "sg:address":"1796 17th St NE",
    "sg:city":"Grand Forks",
    "sg:classifiers":[
        {
            "category":"Wholesale",
            "subcategory":"Machinery & Supplies",
            "type":"Manufacturing & Wholesale Goods"
        },
        {
            "category":"Manufacturing",
            "subcategory":"Motor Vehicles & Parts",
            "type":"Manufacturing & Wholesale Goods"
        }
    ],
    "sg:phone":"+1 701 772 5212",
    "sg:postcode":"58203",
    "sg:province":"ND",
    "sg:tags":[
        "agriculture",
        "trailer",
        "contractor"
    ],
    "wof:name":"Northern Manufacturing & Sales",
    "wof:placetype":"venue"
},
  "geometry": {"coordinates":[-97.196247,47.932392],"type":"Point"}
}