{
  "type": "Feature",
  "properties": {
    "iso:country":"US",
    "sg:address":"306 Main St",
    "sg:city":"Gackle",
    "sg:classifiers":[
        {
            "category":"Manufacturing",
            "subcategory":"Signs",
            "type":"Manufacturing & Wholesale Goods"
        }
    ],
    "sg:phone":"+1 701 485 3426",
    "sg:postcode":"58442",
    "sg:province":"ND",
    "wof:name":"Acme Signs",
    "wof:placetype":"venue"
},
  "geometry": {"coordinates":[-99.142477,46.627863],"type":"Point"}
}