{
  "type": "Feature",
  "properties": {
    "addr:full":"130 Cottage St Hazelton ND 58544",
    "addr:housenumber":"130",
    "addr:postcode":"58544",
    "addr:street":"Cottage St",
    "iso:country":"US",
    "sg:address":"130 Cottage St",
    "sg:city":"Hazelton",
    "sg:classifiers":[
        {
            "category":"Restaurant",
            "type":"Food & Drink"
        }
    ],
    "sg:phone":"+1 701 782 6221",
    "sg:postcode":"58544",
    "sg:province":"ND",
    "sg:tags":[
        "eating"
    ],
    "wof:name":"Big Joe's",
    "wof:placetype":"venue"
},
  "geometry": {"coordinates":[-100.280674,46.482671],"type":"Point"}
}