{
  "type": "Feature",
  "properties": {
    "iso:country":"US",
    "sg:address":"1000 S Columbia Rd",
    "sg:city":"Grand Forks",
    "sg:classifiers":[
        {
            "category":"Health Services",
            "subcategory":"Health Practitioner",
            "type":"Services"
        }
    ],
    "sg:phone":"+1 701 480 6447",
    "sg:postcode":"58201",
    "sg:province":"ND",
    "wof:name":"Ronald J Brockman",
    "wof:placetype":"venue"
},
  "geometry": {"coordinates":[-97.06644900000001,47.911235],"type":"Point"}
}