{
  "type": "Feature",
  "properties": {
    "iso:country":"US",
    "sg:address":"7016 US Hwy 281",
    "sg:city":"Cando",
    "sg:phone":"+1 701 968 3466",
    "sg:postcode":"58324",
    "sg:province":"ND",
    "sg:tags":[
        "farm",
        "wheat"
    ],
    "wof:name":"Rick Reed",
    "wof:placetype":"venue"
},
  "geometry": {"coordinates":[-99.209925,48.435886],"type":"Point"}
}