{
  "type": "Feature",
  "properties": {
    "addr:full":"241 State St N Streeter ND 58483",
    "addr:housenumber":"241",
    "addr:postcode":"58483",
    "addr:street":"State St N Streeter",
    "iso:country":"US",
    "sg:address":"241 State St N",
    "sg:city":"Streeter",
    "sg:classifiers":[
        {
            "category":"Freight",
            "type":"Transportation"
        }
    ],
    "sg:phone":"+1 701 424 3349",
    "sg:postcode":"58483",
    "sg:province":"ND",
    "sg:tags":[
        "hauling",
        "trucking"
    ],
    "wof:name":"William Graf Truck Line",
    "wof:placetype":"venue"
},
  "geometry": {"coordinates":[-99.351795,46.659056],"type":"Point"}
}