{
  "type": "Feature",
  "properties": {
    "iso:country":"US",
    "sg:address":"1525 24th Ave SW",
    "sg:city":"Minot",
    "sg:classifiers":[
        {
            "category":"Banks & Credit Unions",
            "subcategory":"Bank",
            "type":"Services"
        }
    ],
    "sg:phone":"+1 701 839 7696",
    "sg:postcode":"58701",
    "sg:province":"ND",
    "wof:name":"Wells Fargo Bank",
    "wof:placetype":"venue"
},
  "geometry": {"coordinates":[-101.316794,48.20775],"type":"Point"}
}