{
  "type": "Feature",
  "properties": {
    "addr:full":"1004 S 7th St Bismarck ND 58504",
    "addr:housenumber":"1004",
    "addr:postcode":"58504",
    "addr:street":"S 7Th St",
    "iso:country":"US",
    "sg:address":"1004 S 7th St",
    "sg:city":"Bismarck",
    "sg:classifiers":[
        {
            "category":"Health Services",
            "subcategory":"Doctor",
            "type":"Services"
        }
    ],
    "sg:phone":"+1 701 258 5220",
    "sg:postcode":"58504",
    "sg:province":"ND",
    "sg:tags":[
        "dentist"
    ],
    "wof:name":"Honkola & Honkola",
    "wof:placetype":"venue"
},
  "geometry": {"coordinates":[-100.78198500000001,46.794573],"type":"Point"}
}