{
  "type": "Feature",
  "properties": {
    "iso:country":"US",
    "sg:address":"2100 S 29th St",
    "sg:city":"Grand Forks",
    "sg:classifiers":[
        {
            "category":"Organizations",
            "subcategory":"Membership Organization",
            "type":"Services"
        }
    ],
    "sg:phone":"+1 701 746 8897",
    "sg:postcode":"58201",
    "sg:province":"ND",
    "wof:name":"National Assoc Retire Fed",
    "wof:placetype":"venue"
},
  "geometry": {"coordinates":[-97.069577,47.902974],"type":"Point"}
}