{
  "type": "Feature",
  "properties": {
    "addr:full":"232 Langer Ave N Casselton ND 58012",
    "addr:postcode":"58012",
    "addr:street":"Langer Ave N Casselton",
    "iso:country":"US",
    "sg:address":"232 Langer Ave N",
    "sg:city":"Casselton",
    "sg:classifiers":[
        {
            "category":"Professional",
            "subcategory":"Business Services",
            "type":"Services"
        }
    ],
    "sg:phone":"+1 701 373 1246",
    "sg:postcode":"58012",
    "sg:province":"ND",
    "wof:name":"Ultimate Interiors Inc",
    "wof:placetype":"venue"
},
  "geometry": {"coordinates":[-97.21109199999999,46.903305],"type":"Point"}
}