{
  "type": "Feature",
  "properties": {
    "addr:full":"726 US Hwy 2 Granville ND 58741",
    "addr:housenumber":"726",
    "addr:postcode":"58741",
    "addr:street":"Us Hwy 2",
    "iso:country":"US",
    "sg:address":"726 US Hwy 2",
    "sg:city":"Granville",
    "sg:classifiers":[
        {
            "category":"Building & Trades",
            "subcategory":"Construction",
            "type":"Services"
        }
    ],
    "sg:phone":"+1 701 728 6408",
    "sg:postcode":"58741",
    "sg:province":"ND",
    "sg:tags":[
        "general",
        "contractor"
    ],
    "wof:name":"Bachmeier's Construction",
    "wof:placetype":"venue"
},
  "geometry": {"coordinates":[-100.740247,48.286229],"type":"Point"}
}