{
  "type": "Feature",
  "properties": {
    "iso:country":"US",
    "sg:address":"4350 106th St NW",
    "sg:city":"Sherwood",
    "sg:classifiers":[
        {
            "category":"Freight",
            "type":"Transportation"
        }
    ],
    "sg:phone":"+1 701 459 2858",
    "sg:postcode":"58782",
    "sg:province":"ND",
    "sg:tags":[
        "trucking"
    ],
    "wof:name":"Des Lauriers Trucking",
    "wof:placetype":"venue"
},
  "geometry": {"coordinates":[-101.660951,48.95157],"type":"Point"}
}