{
  "type": "Feature",
  "properties": {
    "iso:country":"US",
    "sg:address":"3551 4th Ave S",
    "sg:city":"Fargo",
    "sg:classifiers":[
        {
            "category":"Retail",
            "subcategory":"Laundry & Dry Cleaning",
            "type":"Services"
        }
    ],
    "sg:phone":"+1 701 293 6000",
    "sg:postcode":"58103",
    "sg:province":"ND",
    "sg:tags":[
        "cleaners",
        "rug",
        "carpet"
    ],
    "sg:website":"www.accentcontracting.com",
    "wof:name":"Accent Carpet Cleaning",
    "wof:placetype":"venue"
},
  "geometry": {"coordinates":[-96.83702099999999,46.871338],"type":"Point"}
}