{
  "type": "Feature",
  "properties": {
    "addr:full":"3237 26th St NE Harvey ND 58341",
    "addr:housenumber":"3237",
    "addr:postcode":"58341",
    "addr:street":"26Th St Ne",
    "iso:country":"US",
    "sg:address":"3237 26th St NE",
    "sg:city":"Harvey",
    "sg:classifiers":[
        {
            "category":"Sports & Exercise",
            "subcategory":"Golf",
            "type":"Entertainment"
        }
    ],
    "sg:phone":"+1 701 324 2069",
    "sg:postcode":"58341",
    "sg:province":"ND",
    "sg:tags":[
        "course"
    ],
    "wof:name":"Harvey Country Club",
    "wof:placetype":"venue"
},
  "geometry": {"coordinates":[-99.876867,47.789339],"type":"Point"}
}