{
  "type": "Feature",
  "properties": {
    "addr:full":"2162 Missouri Dr N Mandan ND 58554",
    "addr:housenumber":"2162",
    "addr:postcode":"58554",
    "addr:street":"Missouri Dr N",
    "iso:country":"US",
    "sg:address":"2162 Missouri Dr N",
    "sg:city":"Mandan",
    "sg:classifiers":[
        {
            "category":"Farming",
            "subcategory":"Farm",
            "type":"Manufacturing & Wholesale Goods"
        }
    ],
    "sg:phone":"+1 701 663 6964",
    "sg:postcode":"58554",
    "sg:province":"ND",
    "sg:tags":[
        "crop",
        "general"
    ],
    "wof:name":"Jerry Meisch",
    "wof:placetype":"venue"
},
  "geometry": {"coordinates":[-100.914343,46.884194],"type":"Point"}
}