{
  "type": "Feature",
  "properties": {
    "iso:country":"US",
    "sg:address":"615 3rd Ave SE",
    "sg:city":"Mandan",
    "sg:classifiers":[
        {
            "category":"Retail",
            "subcategory":"Repair Shop",
            "type":"Services"
        }
    ],
    "sg:phone":"+1 701 663 7600",
    "sg:postcode":"58554",
    "sg:province":"ND",
    "sg:tags":[
        "appliance",
        "electrical"
    ],
    "wof:name":"Ron's Appliance Repair",
    "wof:placetype":"venue"
},
  "geometry": {"coordinates":[-100.883177,46.819584],"type":"Point"}
}