{
  "type": "Feature",
  "properties": {
    "iso:country":"US",
    "sg:address":"900 N Broadway",
    "sg:city":"Minot",
    "sg:classifiers":[
        {
            "category":"Health Services",
            "subcategory":"Hospital",
            "type":"Services"
        }
    ],
    "sg:phone":"+1 701 857 7686",
    "sg:postcode":"58703",
    "sg:province":"ND",
    "sg:tags":[
        "mental"
    ],
    "wof:name":"Protection & Advocacy Project",
    "wof:placetype":"venue"
},
  "geometry": {"coordinates":[-101.296041,48.242069],"type":"Point"}
}