{
  "type": "Feature",
  "properties": {
    "addr:full":"311 9th St N Wahpeton ND 58075",
    "addr:housenumber":"311",
    "addr:postcode":"58075",
    "addr:street":"9Th St N",
    "iso:country":"US",
    "sg:address":"311 9th St N",
    "sg:city":"Wahpeton",
    "sg:classifiers":[
        {
            "category":"Professional",
            "subcategory":"Secretarial Services",
            "type":"Services"
        }
    ],
    "sg:phone":"+1 701 642 8321",
    "sg:postcode":"58075",
    "sg:province":"ND",
    "sg:tags":[
        "reporting"
    ],
    "wof:name":"Secretarial Solutions",
    "wof:placetype":"venue"
},
  "geometry": {"coordinates":[-96.612773,46.266988],"type":"Point"}
}