{
  "type": "Feature",
  "properties": {
    "iso:country":"US",
    "sg:address":"1149 36th Ave S",
    "sg:city":"Grand Forks",
    "sg:classifiers":[
        {
            "category":"Food & Beverages",
            "subcategory":"Groceries & Convenience Stores",
            "type":"Retail Goods"
        }
    ],
    "sg:phone":"+1 701 780 9908",
    "sg:postcode":"58201",
    "sg:province":"ND",
    "wof:name":"Valdak Corporation",
    "wof:placetype":"venue"
},
  "geometry": {"coordinates":[-97.04298799999999,47.885853],"type":"Point"}
}