{
  "type": "Feature",
  "properties": {
    "addr:full":"528 5th St Milnor ND 58060",
    "addr:housenumber":"528",
    "addr:postcode":"58060",
    "addr:street":"5Th St",
    "iso:country":"US",
    "sg:address":"528 5th St",
    "sg:city":"Milnor",
    "sg:classifiers":[
        {
            "category":"Education",
            "subcategory":"Library",
            "type":"Public Place"
        }
    ],
    "sg:phone":"+1 701 427 5295",
    "sg:postcode":"58060",
    "sg:province":"ND",
    "wof:name":"Satre Memorial Library",
    "wof:placetype":"venue"
},
  "geometry": {"coordinates":[-97.455538,46.260361],"type":"Point"}
}