{
  "type": "Feature",
  "properties": {
    "iso:country":"US",
    "sg:address":"1422 Main Ave W",
    "sg:city":"West Fargo",
    "sg:classifiers":[
        {
            "category":"Retail",
            "subcategory":"Auto Repair",
            "type":"Services"
        }
    ],
    "sg:phone":"+1 701 280 0277",
    "sg:postcode":"58078",
    "sg:province":"ND",
    "sg:tags":[
        "wrecker"
    ],
    "wof:name":"Jim's Towing",
    "wof:placetype":"venue"
},
  "geometry": {"coordinates":[-96.935816,46.877179],"type":"Point"}
}