{
  "type": "Feature",
  "properties": {
    "iso:country":"US",
    "sg:address":"12601 182nd St NW",
    "sg:city":"Berthold",
    "sg:classifiers":[
        {
            "category":"Building & Trades",
            "subcategory":"Construction",
            "type":"Services"
        }
    ],
    "sg:phone":"+1 701 468 5945",
    "sg:postcode":"58718",
    "sg:province":"ND",
    "sg:tags":[
        "house"
    ],
    "wof:name":"Stans Remodeling",
    "wof:placetype":"venue"
},
  "geometry": {"coordinates":[-101.570589,48.368313],"type":"Point"}
}