{
  "type": "Feature",
  "properties": {
    "iso:country":"US",
    "sg:address":"3301 13th Ave S",
    "sg:city":"Fargo",
    "sg:classifiers":[
        {
            "category":"Personal",
            "subcategory":"Beauty Salon",
            "type":"Services"
        }
    ],
    "sg:phone":"+1 701 237 9655",
    "sg:postcode":"58103",
    "sg:province":"ND",
    "sg:tags":[
        "shop"
    ],
    "wof:name":"Jill Rogers",
    "wof:placetype":"venue"
},
  "geometry": {"coordinates":[-96.836125,46.861677],"type":"Point"}
}