{
  "type": "Feature",
  "properties": {
    "iso:country":"US",
    "sg:address":"500 Columbia Dr",
    "sg:city":"Bismarck",
    "sg:classifiers":[
        {
            "category":"Wholesale",
            "subcategory":"Machinery & Supplies",
            "type":"Manufacturing & Wholesale Goods"
        }
    ],
    "sg:phone":"+1 701 223 8199",
    "sg:postcode":"58504",
    "sg:province":"ND",
    "sg:tags":[
        "equipment",
        "establishment"
    ],
    "wof:name":"Summit Fire Protection",
    "wof:placetype":"venue"
},
  "geometry": {"coordinates":[-100.78246900000001,46.793797],"type":"Point"}
}