{
  "type": "Feature",
  "properties": {
    "iso:country":"US",
    "sg:address":"7100 135th Ave SW",
    "sg:city":"Minot",
    "sg:phone":"+1 701 722 3512",
    "sg:postcode":"58701",
    "sg:province":"ND",
    "sg:tags":[
        "farm",
        "wheat"
    ],
    "wof:name":"Jim Novak",
    "wof:placetype":"venue"
},
  "geometry": {"coordinates":[-101.401695,48.095459],"type":"Point"}
}