{
  "type": "Feature",
  "properties": {
    "iso:country":"US",
    "sg:address":"913 5th St",
    "sg:city":"Langdon",
    "sg:classifiers":[
        {
            "category":"Real Estate",
            "subcategory":"Real Estate Operator",
            "type":"Services"
        }
    ],
    "sg:phone":"+1 701 256 3227",
    "sg:postcode":"58249",
    "sg:province":"ND",
    "sg:tags":[
        "property",
        "lessor"
    ],
    "wof:name":"Fran Waltz",
    "wof:placetype":"venue"
},
  "geometry": {"coordinates":[-98.37127099999999,48.761569],"type":"Point"}
}