{
  "type": "Feature",
  "properties": {
    "addr:full":"113 Lincoln Ave Underwood ND 58576",
    "addr:housenumber":"113",
    "addr:postcode":"58576",
    "addr:street":"Lincoln Ave",
    "iso:country":"US",
    "sg:address":"113 Lincoln Ave",
    "sg:city":"Underwood",
    "sg:classifiers":[
        {
            "category":"Personal",
            "subcategory":"Beauty Salon",
            "type":"Services"
        }
    ],
    "sg:phone":"+1 701 442 5300",
    "sg:postcode":"58576",
    "sg:province":"ND",
    "wof:name":"Connie's Cut-N-Curl",
    "wof:placetype":"venue"
},
  "geometry": {"coordinates":[-101.13738499999999,47.456124],"type":"Point"}
}