{
  "type": "Feature",
  "properties": {
    "addr:full":"315 Tucson Ave Bismarck ND 58504",
    "addr:housenumber":"315",
    "addr:postcode":"58504",
    "addr:street":"Tucson Ave",
    "iso:country":"US",
    "sg:address":"315 Tucson Ave",
    "sg:city":"Bismarck",
    "sg:classifiers":[
        {
            "category":"Organizations",
            "subcategory":"Community Association",
            "type":"Services"
        }
    ],
    "sg:phone":"+1 701 250 9921",
    "sg:postcode":"58504",
    "sg:province":"ND",
    "sg:tags":[
        "environmental",
        "org"
    ],
    "wof:name":"Pheasants Forever Regional Off",
    "wof:placetype":"venue"
},
  "geometry": {"coordinates":[-100.786722,46.787029],"type":"Point"}
}