{
  "type": "Feature",
  "properties": {
    "iso:country":"US",
    "sg:address":"321 W Main St",
    "sg:city":"Larimore",
    "sg:classifiers":[
        {
            "category":"Organizations",
            "subcategory":"Religious Organization",
            "type":"Services"
        }
    ],
    "sg:phone":"+1 701 343 2658",
    "sg:postcode":"58251",
    "sg:province":"ND",
    "sg:tags":[
        "church"
    ],
    "wof:name":"Our Savior's Luth Chr",
    "wof:placetype":"venue"
},
  "geometry": {"coordinates":[-97.62740599999999,47.905774],"type":"Point"}
}