{
  "type": "Feature",
  "properties": {
    "addr:full":"215 11th Ave SW Minot ND 58701",
    "addr:housenumber":"215",
    "addr:postcode":"58701",
    "addr:street":"11Th Ave Sw",
    "iso:country":"US",
    "sg:address":"215 11th Ave SW",
    "sg:city":"Minot",
    "sg:classifiers":[
        {
            "category":"Government",
            "subcategory":"Office",
            "type":"Public Place"
        }
    ],
    "sg:phone":"+1 701 852 5403",
    "sg:postcode":"58701",
    "sg:province":"ND",
    "sg:tags":[
        "federal"
    ],
    "wof:name":"US Consolidated Farm Svc Agcy",
    "wof:placetype":"venue"
},
  "geometry": {"coordinates":[-101.296606,48.225445],"type":"Point"}
}