{
  "type": "Feature",
  "properties": {
    "iso:country":"US",
    "sg:address":"1430 Main Ave",
    "sg:city":"Washburn",
    "sg:phone":"+1 701 462 3357",
    "sg:postcode":"58577",
    "sg:province":"ND",
    "sg:tags":[
        "farm",
        "wheat"
    ],
    "wof:name":"Jay Barnick",
    "wof:placetype":"venue"
},
  "geometry": {"coordinates":[-101.0184,47.283449],"type":"Point"}
}