{
  "type": "Feature",
  "properties": {
    "addr:full":"407 4th St Devils Lake ND 58301",
    "addr:housenumber":"407",
    "addr:postcode":"58301",
    "addr:street":"4Th St",
    "iso:country":"US",
    "sg:address":"407 4th St",
    "sg:city":"Devils Lake",
    "sg:classifiers":[
        {
            "category":"Shopping",
            "subcategory":"Stationery & Office Supplies",
            "type":"Retail Goods"
        }
    ],
    "sg:phone":"+1 701 662 5041",
    "sg:postcode":"58301",
    "sg:province":"ND",
    "wof:name":"Hoiberg's Office Supply",
    "wof:placetype":"venue"
},
  "geometry": {"coordinates":[-98.860319,48.111837],"type":"Point"}
}