{
  "type": "Feature",
  "properties": {
    "iso:country":"US",
    "sg:address":"7553 88th St SE",
    "sg:city":"Ellendale",
    "sg:classifiers":[
        {
            "category":"Real Estate",
            "subcategory":"Real Estate Operator",
            "type":"Services"
        }
    ],
    "sg:phone":"+1 701 396 7591",
    "sg:postcode":"58436",
    "sg:province":"ND",
    "sg:tags":[
        "property",
        "lessor"
    ],
    "wof:name":"Darwin Nill",
    "wof:placetype":"venue"
},
  "geometry": {"coordinates":[-98.82293199999999,46.141868],"type":"Point"}
}