{
  "type": "Feature",
  "properties": {
    "addr:full":"730 13th Ave E West Fargo ND 58078",
    "addr:housenumber":"730",
    "addr:postcode":"58078",
    "addr:street":"13Th Ave E",
    "iso:country":"US",
    "sg:address":"730 13th Ave E",
    "sg:city":"West Fargo",
    "sg:classifiers":[
        {
            "category":"Retail",
            "subcategory":"Veterinary Services",
            "type":"Services"
        }
    ],
    "sg:phone":"+1 701 282 2898",
    "sg:postcode":"58078",
    "sg:province":"ND",
    "sg:tags":[
        "veterinarian"
    ],
    "wof:name":"West Fargo Animal Hospital",
    "wof:placetype":"venue"
},
  "geometry": {"coordinates":[-96.887905,46.862347],"type":"Point"}
}