{
  "type": "Feature",
  "properties": {
    "iso:country":"US",
    "sg:address":"4945 145th Ave NW",
    "sg:city":"Williston",
    "sg:classifiers":[
        {
            "category":"Building & Trades",
            "subcategory":"Construction",
            "type":"Services"
        }
    ],
    "sg:phone":"+1 701 774 3607",
    "sg:postcode":"58801",
    "sg:province":"ND",
    "sg:tags":[
        "house"
    ],
    "wof:name":"Basin Improvements",
    "wof:placetype":"venue"
},
  "geometry": {"coordinates":[-103.819821,48.131717],"type":"Point"}
}