{
  "type": "Feature",
  "properties": {
    "addr:full":"1040 40th St S Fargo ND 58103",
    "addr:housenumber":"1040",
    "addr:postcode":"58103",
    "addr:street":"40Th St S",
    "iso:country":"US",
    "sg:address":"1040 40th St S",
    "sg:city":"Fargo",
    "sg:classifiers":[
        {
            "category":"Travel",
            "subcategory":"Hotels & Motels",
            "type":"Entertainment"
        },
        {
            "category":"Retail",
            "subcategory":"Event Space",
            "type":"Services"
        }
    ],
    "sg:phone":"+1 800 345 8082",
    "sg:postcode":"58103",
    "sg:province":"ND",
    "sg:tags":[
        "facility",
        "banquet",
        "reception",
        "lodging",
        "corporate",
        "hall"
    ],
    "sg:website":"http://ad.doubleclick.net/clk;222816988;46581822;v?http://www.hiexpress.com/redirect?path=hd&brandCode=ex&hotelCode=farex&_PMID=99601036&cm_mmc=mdpr-_-yellowpages-_-ex-_-farex",
    "wof:name":"Holiday Inn Express Fargo-West Acres",
    "wof:placetype":"venue"
},
  "geometry": {"coordinates":[-96.848045,46.865061],"type":"Point"}
}