{
  "type": "Feature",
  "properties": {
    "iso:country":"US",
    "sg:address":"351 Central Ave N",
    "sg:city":"Valley City",
    "sg:classifiers":[
        {
            "category":"Manufacturing",
            "subcategory":"Printing",
            "type":"Manufacturing & Wholesale Goods"
        }
    ],
    "sg:phone":"+1 701 845 0275",
    "sg:postcode":"58072",
    "sg:province":"ND",
    "sg:tags":[
        "commercial",
        "offset"
    ],
    "wof:name":"Sheyenne Publishing & Off Sup",
    "wof:placetype":"venue"
},
  "geometry": {"coordinates":[-98.003202,46.925768],"type":"Point"}
}