{
  "type": "Feature",
  "properties": {
    "addr:full":"6853 102nd Ave NW Tioga ND 58852",
    "addr:housenumber":"6853",
    "addr:postcode":"58852",
    "addr:street":"102Nd Ave Nw",
    "iso:country":"US",
    "sg:address":"6853 102nd Ave NW",
    "sg:city":"Tioga",
    "sg:classifiers":[
        {
            "category":"Professional",
            "subcategory":"Management & Consulting",
            "type":"Services"
        }
    ],
    "sg:phone":"+1 701 664 1492",
    "sg:postcode":"58852",
    "sg:province":"ND",
    "sg:tags":[
        "consultant"
    ],
    "wof:name":"Neset Consulting Svc",
    "wof:placetype":"venue"
},
  "geometry": {"coordinates":[-102.885738,48.408739],"type":"Point"}
}