{
  "type": "Feature",
  "properties": {
    "iso:country":"US",
    "sg:address":"405 Central Ave E",
    "sg:city":"Minot",
    "sg:classifiers":[
        {
            "category":"Banks & Credit Unions",
            "subcategory":"Bank",
            "type":"Services"
        }
    ],
    "sg:phone":"+1 701 852 3866",
    "sg:postcode":"58701",
    "sg:province":"ND",
    "wof:name":"GEM Federal Credit Union",
    "wof:placetype":"venue"
},
  "geometry": {"coordinates":[-101.28609299999999,48.23649],"type":"Point"}
}