{
  "type": "Feature",
  "properties": {
    "addr:full":"120 11th St N New Rockford ND 58356",
    "addr:housenumber":"120",
    "addr:postcode":"58356",
    "addr:street":"11Th St N",
    "iso:country":"US",
    "sg:address":"120 11th St N",
    "sg:city":"New Rockford",
    "sg:classifiers":[
        {
            "category":"Organizations",
            "subcategory":"Non-profit Organization",
            "type":"Services"
        }
    ],
    "sg:phone":"+1 701 947 2147",
    "sg:postcode":"58356",
    "sg:province":"ND",
    "sg:tags":[
        "human"
    ],
    "wof:name":"Fourth Corp",
    "wof:placetype":"venue"
},
  "geometry": {"coordinates":[-99.143772,47.68136],"type":"Point"}
}