{
  "type": "Feature",
  "properties": {
    "addr:full":"303 2nd St SE Woodworth ND 58496",
    "addr:housenumber":"303",
    "addr:postcode":"58496",
    "addr:street":"2Nd St Se",
    "iso:country":"US",
    "sg:address":"303 2nd St SE",
    "sg:city":"Woodworth",
    "sg:classifiers":[
        {
            "category":"Freight",
            "type":"Transportation"
        }
    ],
    "sg:phone":"+1 701 752 4143",
    "sg:postcode":"58496",
    "sg:province":"ND",
    "sg:tags":[
        "grain",
        "elevator"
    ],
    "wof:name":"Woodworth Farmers Grain Co",
    "wof:placetype":"venue"
},
  "geometry": {"coordinates":[-99.303364,47.139858],"type":"Point"}
}