{
  "type": "Feature",
  "properties": {
    "iso:country":"US",
    "sg:address":"316 11th St W",
    "sg:city":"West Fargo",
    "sg:classifiers":[
        {
            "category":"Food & Beverages",
            "subcategory":"Groceries & Convenience Stores",
            "type":"Retail Goods"
        }
    ],
    "sg:phone":"+1 701 282 9152",
    "sg:postcode":"58078",
    "sg:province":"ND",
    "sg:tags":[
        "product"
    ],
    "wof:name":"Old Dutch Foods",
    "wof:placetype":"venue"
},
  "geometry": {"coordinates":[-96.91753,46.873345],"type":"Point"}
}