{
  "type": "Feature",
  "properties": {
    "iso:country":"US",
    "sg:address":"303 1st Ave SE",
    "sg:city":"Belfield",
    "sg:classifiers":[
        {
            "category":"Mining & Drilling",
            "type":"Manufacturing & Wholesale Goods"
        }
    ],
    "sg:phone":"+1 701 575 8057",
    "sg:postcode":"58622",
    "sg:province":"ND",
    "sg:tags":[
        "rigger"
    ],
    "wof:name":"Olie's Rigging Inc",
    "wof:placetype":"venue"
},
  "geometry": {"coordinates":[-103.195559,46.883088],"type":"Point"}
}