{
  "type": "Feature",
  "properties": {
    "iso:country":"US",
    "sg:address":"600 14th Ave SW",
    "sg:city":"Bismarck",
    "sg:classifiers":[
        {
            "category":"Government",
            "subcategory":"Office",
            "type":"Public Place"
        }
    ],
    "sg:phone":"+1 701 328 3722",
    "sg:postcode":"58577",
    "sg:province":"ND",
    "sg:tags":[
        "state",
        "resource"
    ],
    "wof:name":"Industrial Commission",
    "wof:placetype":"venue"
},
  "geometry": {"coordinates":[-100.79167099999999,47.327175],"type":"Point"}
}