{
  "type": "Feature",
  "properties": {
    "addr:full":"1930 S Columbia Rd Grand Forks ND 58201",
    "addr:housenumber":"1930",
    "addr:postcode":"58201",
    "addr:street":"S Columbia Rd",
    "iso:country":"US",
    "sg:address":"1930 S Columbia Rd",
    "sg:city":"Grand Forks",
    "sg:classifiers":[
        {
            "category":"Restaurant",
            "type":"Food & Drink"
        }
    ],
    "sg:menulink":"http://www.allmenus.com/nd/grand-forks/23657-green-mill/menu/",
    "sg:phone":"+1 701 780 9000",
    "sg:postcode":"58201",
    "sg:province":"ND",
    "sg:tags":[
        "american",
        "pizza"
    ],
    "wof:name":"Green Mill",
    "wof:placetype":"venue"
},
  "geometry": {"coordinates":[-97.066508,47.901569],"type":"Point"}
}