{
  "type": "Feature",
  "properties": {
    "iso:country":"US",
    "sg:address":"8975 173rd Ave SE",
    "sg:city":"Wahpeton",
    "sg:phone":"+1 701 545 7456",
    "sg:postcode":"58075",
    "sg:province":"ND",
    "sg:tags":[
        "farm",
        "wheat"
    ],
    "wof:name":"Charles Rossow",
    "wof:placetype":"venue"
},
  "geometry": {"coordinates":[-96.784232,45.963414],"type":"Point"}
}