{
  "type": "Feature",
  "properties": {
    "addr:full":"107 S Main St Velva ND 58790",
    "addr:housenumber":"107",
    "addr:postcode":"58790",
    "addr:street":"S Main St",
    "iso:country":"US",
    "sg:address":"107 S Main St",
    "sg:city":"Velva",
    "sg:classifiers":[
        {
            "category":"Food & Beverages",
            "subcategory":"Groceries & Convenience Stores",
            "type":"Retail Goods"
        }
    ],
    "sg:phone":"+1 701 338 2971",
    "sg:postcode":"58790",
    "sg:province":"ND",
    "sg:tags":[
        "grocer"
    ],
    "wof:name":"Velva Fresh Foods Inc",
    "wof:placetype":"venue"
},
  "geometry": {"coordinates":[-100.93046,48.054365],"type":"Point"}
}