{
  "type": "Feature",
  "properties": {
    "iso:country":"US",
    "sg:address":"15160 Sundown Dr",
    "sg:city":"Bismarck",
    "sg:classifiers":[
        {
            "category":"Organizations",
            "subcategory":"Religious Organization",
            "type":"Services"
        }
    ],
    "sg:phone":"+1 701 258 1899",
    "sg:postcode":"58503",
    "sg:province":"ND",
    "wof:name":"Religious Society Of Friends",
    "wof:placetype":"venue"
},
  "geometry": {"coordinates":[-100.92945,46.971072],"type":"Point"}
}