{
  "type": "Feature",
  "properties": {
    "iso:country":"US",
    "sg:address":"210 Main Ave",
    "sg:city":"Napoleon",
    "sg:classifiers":[
        {
            "category":"Real Estate",
            "subcategory":"Real Estate Services",
            "type":"Services"
        }
    ],
    "sg:phone":"+1 701 754 2200",
    "sg:postcode":"58561",
    "sg:province":"ND",
    "wof:name":"Logan County Abstract Co",
    "wof:placetype":"venue"
},
  "geometry": {"coordinates":[-99.771182,46.502582],"type":"Point"}
}