{
  "type": "Feature",
  "properties": {
    "iso:country":"US",
    "sg:address":"711 Collins Ave",
    "sg:city":"Mandan",
    "sg:classifiers":[
        {
            "category":"Shopping",
            "subcategory":"Computers & Home Electronics",
            "type":"Retail Goods"
        }
    ],
    "sg:phone":"+1 701 663 7004",
    "sg:postcode":"58554",
    "sg:province":"ND",
    "sg:tags":[
        "equipment",
        "electronic",
        "supply"
    ],
    "wof:name":"Austins Electronics",
    "wof:placetype":"venue"
},
  "geometry": {"coordinates":[-100.89182700000001,46.833498],"type":"Point"}
}