{
  "type": "Feature",
  "properties": {
    "iso:country":"US",
    "sg:address":"6306 133rd Ave SE",
    "sg:city":"Lisbon",
    "sg:classifiers":[
        {
            "category":"Farming",
            "subcategory":"Livestock Farm",
            "type":"Manufacturing & Wholesale Goods"
        }
    ],
    "sg:phone":"+1 701 683 4485",
    "sg:postcode":"58054",
    "sg:province":"ND",
    "sg:tags":[
        "corn",
        "beef",
        "feedlot",
        "cattle"
    ],
    "wof:name":"Kevin Schultz",
    "wof:placetype":"venue"
},
  "geometry": {"coordinates":[-97.63679500000001,46.49881],"type":"Point"}
}