{
  "type": "Feature",
  "properties": {
    "iso:country":"US",
    "sg:address":"1705 Sunset Dr",
    "sg:city":"Mandan",
    "sg:classifiers":[
        {
            "category":"Organizations",
            "subcategory":"Religious Organization",
            "type":"Services"
        }
    ],
    "sg:phone":"+1 701 663 8466",
    "sg:postcode":"58554",
    "sg:province":"ND",
    "sg:tags":[
        "church"
    ],
    "wof:name":"American Lutheran Church",
    "wof:placetype":"venue"
},
  "geometry": {"coordinates":[-100.90534,46.839445],"type":"Point"}
}