{
  "type": "Feature",
  "properties": {
    "addr:full":"1000 W Villard St Dickinson ND 58601",
    "addr:housenumber":"1000",
    "addr:postcode":"58601",
    "addr:street":"W Villard St",
    "iso:country":"US",
    "sg:address":"1000 W Villard St",
    "sg:city":"Dickinson",
    "sg:classifiers":[
        {
            "category":"Travel",
            "subcategory":"Hotels & Motels",
            "type":"Entertainment"
        }
    ],
    "sg:phone":"+1 701 225 6703",
    "sg:postcode":"58601",
    "sg:province":"ND",
    "sg:tags":[
        "operation"
    ],
    "wof:name":"Oasis Motel",
    "wof:placetype":"venue"
},
  "geometry": {"coordinates":[-102.801605,46.879094],"type":"Point"}
}