{
  "type": "Feature",
  "properties": {
    "addr:full":"850 57th Ave NW Bismarck ND 58503",
    "addr:housenumber":"850",
    "addr:postcode":"58503",
    "addr:street":"57Th Ave Nw",
    "iso:country":"US",
    "sg:address":"850 57th Ave NW",
    "sg:city":"Bismarck",
    "sg:classifiers":[
        {
            "category":"Wholesale",
            "subcategory":"Petroleum",
            "type":"Manufacturing & Wholesale Goods"
        }
    ],
    "sg:phone":"+1 701 530 1688",
    "sg:postcode":"58503",
    "sg:province":"ND",
    "sg:tags":[
        "pipe",
        "line",
        "company"
    ],
    "wof:name":"Williston Basin Interstate",
    "wof:placetype":"venue"
},
  "geometry": {"coordinates":[-100.80429100000001,46.867047],"type":"Point"}
}