{
  "type": "Feature",
  "properties": {
    "iso:country":"US",
    "sg:address":"124 E Main St",
    "sg:city":"Ashley",
    "sg:classifiers":[
        {
            "category":"Retail",
            "subcategory":"Auto Repair",
            "type":"Services"
        }
    ],
    "sg:phone":"+1 701 288 3662",
    "sg:postcode":"58413",
    "sg:province":"ND",
    "sg:tags":[
        "repairing",
        "automobile"
    ],
    "wof:name":"Willie's Service",
    "wof:placetype":"venue"
},
  "geometry": {"coordinates":[-99.370121,46.034536],"type":"Point"}
}