{
  "type": "Feature",
  "properties": {
    "addr:full":"1803 S 19th St Grand Forks ND 58201",
    "addr:housenumber":"1803",
    "addr:postcode":"58201",
    "addr:street":"S 19Th St",
    "iso:country":"US",
    "sg:address":"1803 S 19th St",
    "sg:city":"Grand Forks",
    "sg:classifiers":[
        {
            "category":"Shopping",
            "subcategory":"Computers & Home Electronics",
            "type":"Retail Goods"
        }
    ],
    "sg:phone":"+1 701 772 8182",
    "sg:postcode":"58201",
    "sg:province":"ND",
    "sg:tags":[
        "television",
        "radio"
    ],
    "wof:name":"Goodman TV Svc",
    "wof:placetype":"venue"
},
  "geometry": {"coordinates":[-97.053355,47.902018],"type":"Point"}
}