{
  "type": "Feature",
  "properties": {
    "iso:country":"US",
    "sg:address":"703 6th Ave SE",
    "sg:city":"Mandan",
    "sg:classifiers":[
        {
            "category":"Professional",
            "subcategory":"Management & Consulting",
            "type":"Services"
        }
    ],
    "sg:phone":"+1 701 527 0395",
    "sg:postcode":"58554",
    "sg:province":"ND",
    "wof:name":"Unmuddled Existence",
    "wof:placetype":"venue"
},
  "geometry": {"coordinates":[-100.880606,46.818466],"type":"Point"}
}