{
  "type": "Feature",
  "properties": {
    "iso:country":"US",
    "sg:address":"118 3rd Ave NE",
    "sg:city":"Lidgerwood",
    "sg:classifiers":[
        {
            "category":"Retail",
            "subcategory":"Laundry & Dry Cleaning",
            "type":"Services"
        }
    ],
    "sg:phone":"+1 701 538 4106",
    "sg:postcode":"58053",
    "sg:province":"ND",
    "wof:name":"Gettels Marcela Weaving",
    "wof:placetype":"venue"
},
  "geometry": {"coordinates":[-97.147572,46.07772],"type":"Point"}
}