{
  "type": "Feature",
  "properties": {
    "addr:full":"203 13th St S Hettinger ND 58639",
    "addr:housenumber":"203",
    "addr:postcode":"58639",
    "addr:street":"13Th St S Hettinger",
    "iso:country":"US",
    "sg:address":"203 13th St S",
    "sg:city":"Hettinger",
    "sg:classifiers":[
        {
            "category":"Professional",
            "type":"Services"
        }
    ],
    "sg:phone":"+1 701 567 4420",
    "sg:postcode":"58639",
    "sg:province":"ND",
    "sg:tags":[
        "establishment"
    ],
    "wof:name":"Drolc Curt",
    "wof:placetype":"venue"
},
  "geometry": {"coordinates":[-102.625868,45.99918],"type":"Point"}
}