{
  "type": "Feature",
  "properties": {
    "iso:country":"US",
    "sg:address":"1110 25th Ave N",
    "sg:city":"Fargo",
    "sg:classifiers":[
        {
            "category":"Professional",
            "subcategory":"Advertising",
            "type":"Services"
        },
        {
            "category":"Manufacturing",
            "subcategory":"Signs",
            "type":"Manufacturing & Wholesale Goods"
        }
    ],
    "sg:phone":"+1 701 293 8599",
    "sg:postcode":"58102",
    "sg:province":"ND",
    "sg:tags":[
        "specialty"
    ],
    "sg:website":"http://www.dakotafence.com",
    "wof:name":"3 D Specialties, Inc",
    "wof:placetype":"venue"
},
  "geometry": {"coordinates":[-96.79492999999999,46.909833],"type":"Point"}
}