{
  "type": "Feature",
  "properties": {
    "iso:country":"US",
    "sg:address":"4595 79th Ave NE",
    "sg:city":"Devils Lake",
    "sg:classifiers":[
        {
            "category":"Building & Trades",
            "subcategory":"Construction",
            "type":"Services"
        }
    ],
    "sg:phone":"+1 701 230 2280",
    "sg:postcode":"58301",
    "sg:province":"ND",
    "sg:tags":[
        "concrete"
    ],
    "wof:name":"Lake Country Handyman",
    "wof:placetype":"venue"
},
  "geometry": {"coordinates":[-98.91909099999999,48.07761],"type":"Point"}
}