{
  "type": "Feature",
  "properties": {
    "iso:country":"US",
    "sg:address":"215 2nd Ave SE",
    "sg:city":"Rugby",
    "sg:classifiers":[
        {
            "category":"Food & Beverages",
            "subcategory":"Groceries & Convenience Stores",
            "type":"Retail Goods"
        }
    ],
    "sg:phone":"+1 701 776 5889",
    "sg:postcode":"58368",
    "sg:province":"ND",
    "wof:name":"Leevers Store",
    "wof:placetype":"venue"
},
  "geometry": {"coordinates":[-99.994501,48.368547],"type":"Point"}
}