{
  "type": "Feature",
  "properties": {
    "iso:country":"US",
    "sg:address":"2011 2nd Ave E",
    "sg:city":"Williston",
    "sg:classifiers":[
        {
            "category":"Building & Trades",
            "subcategory":"Construction",
            "type":"Services"
        }
    ],
    "sg:phone":"+1 701 572 9208",
    "sg:postcode":"58801",
    "sg:province":"ND",
    "sg:tags":[
        "hanging",
        "wallpaper",
        "contractor"
    ],
    "wof:name":"Leipke Painting & Decorating",
    "wof:placetype":"venue"
},
  "geometry": {"coordinates":[-103.61975,48.163369],"type":"Point"}
}