{
  "type": "Feature",
  "properties": {
    "addr:full":"2710 63rd St NW Minot ND 58703",
    "addr:housenumber":"2710",
    "addr:postcode":"58703",
    "addr:street":"63Rd St Nw",
    "iso:country":"US",
    "sg:address":"2710 63rd St NW",
    "sg:city":"Minot",
    "sg:classifiers":[
        {
            "category":"Manufacturing",
            "subcategory":"Apparel",
            "type":"Manufacturing & Wholesale Goods"
        }
    ],
    "sg:phone":"+1 701 837 1750",
    "sg:postcode":"58703",
    "sg:province":"ND",
    "sg:tags":[
        "flag",
        "banner"
    ],
    "wof:name":"Sign D'Zyn Of Minot",
    "wof:placetype":"venue"
},
  "geometry": {"coordinates":[-101.387469,48.267231],"type":"Point"}
}