{
  "type": "Feature",
  "properties": {
    "iso:country":"US",
    "sg:address":"3860 109th Ave SW",
    "sg:city":"Dickinson",
    "sg:classifiers":[
        {
            "category":"Freight",
            "type":"Transportation"
        }
    ],
    "sg:phone":"+1 701 483 7114",
    "sg:postcode":"58601",
    "sg:province":"ND",
    "sg:tags":[
        "operator",
        "trucking"
    ],
    "wof:name":"Troy Anderson Trucking",
    "wof:placetype":"venue"
},
  "geometry": {"coordinates":[-102.747435,46.852633],"type":"Point"}
}