{
  "type": "Feature",
  "properties": {
    "iso:country":"US",
    "sg:address":"319 Broadway",
    "sg:city":"Fargo",
    "sg:classifiers":[
        {
            "category":"Home & Garden",
            "subcategory":"Furniture",
            "type":"Retail Goods"
        }
    ],
    "sg:phone":"+1 701 235 1078",
    "sg:postcode":"58102",
    "sg:province":"ND",
    "wof:name":"Broadway Furniture Inc",
    "wof:placetype":"venue"
},
  "geometry": {"coordinates":[-96.787617,46.879871],"type":"Point"}
}