{
  "type": "Feature",
  "properties": {
    "addr:full":"1681 3rd Ave W Dickinson ND 58601",
    "addr:housenumber":"1681",
    "addr:postcode":"58601",
    "addr:street":"3Rd Ave W",
    "iso:country":"US",
    "sg:address":"1681 3rd Ave W",
    "sg:city":"Dickinson",
    "sg:classifiers":[
        {
            "category":"Shopping",
            "subcategory":"Clothing, Apparel, & Fashions",
            "type":"Retail Goods"
        }
    ],
    "sg:phone":"+1 701 225 6822",
    "sg:postcode":"58601",
    "sg:province":"ND",
    "sg:website":"www.vanityshops.com",
    "wof:name":"Vanity",
    "wof:placetype":"venue"
},
  "geometry": {"coordinates":[-102.789796,46.901915],"type":"Point"}
}