{
  "type": "Feature",
  "properties": {
    "iso:country":"US",
    "sg:address":"958 38th Ave E",
    "sg:city":"Dickinson",
    "sg:classifiers":[
        {
            "category":"Mining & Drilling",
            "type":"Manufacturing & Wholesale Goods"
        }
    ],
    "sg:phone":"+1 701 483 0679",
    "sg:postcode":"58601",
    "sg:province":"ND",
    "sg:tags":[
        "field",
        "oil"
    ],
    "wof:name":"High Plains Inc",
    "wof:placetype":"venue"
},
  "geometry": {"coordinates":[-102.717114,46.888984],"type":"Point"}
}