{
  "type": "Feature",
  "properties": {
    "iso:country":"US",
    "sg:address":"200 36th Ave NE",
    "sg:city":"Minot",
    "sg:classifiers":[
        {
            "category":"Wholesale",
            "subcategory":"Machinery & Supplies",
            "type":"Manufacturing & Wholesale Goods"
        }
    ],
    "sg:phone":"+1 701 838 6557",
    "sg:postcode":"58703",
    "sg:province":"ND",
    "sg:tags":[
        "farm",
        "equipment"
    ],
    "wof:name":"Maki-Minot Enterprises Inc",
    "wof:placetype":"venue"
},
  "geometry": {"coordinates":[-101.284436,48.276171],"type":"Point"}
}