{
  "type": "Feature",
  "properties": {
    "iso:country":"US",
    "sg:address":"121 Sheyenne St",
    "sg:city":"West Fargo",
    "sg:classifiers":[
        {
            "category":"Social Services",
            "subcategory":"Child Care",
            "type":"Services"
        }
    ],
    "sg:phone":"+1 701 356 5262",
    "sg:postcode":"58078",
    "sg:province":"ND",
    "sg:tags":[
        "kindergarten",
        "academic",
        "school"
    ],
    "wof:name":"Little Lambs Christian Prschl",
    "wof:placetype":"venue"
},
  "geometry": {"coordinates":[-96.903953,46.875665],"type":"Point"}
}