{
  "type": "Feature",
  "properties": {
    "iso:country":"US",
    "sg:address":"3515 N Broadway",
    "sg:city":"Minot",
    "sg:classifiers":[
        {
            "category":"Autos & Motor Vehicles",
            "subcategory":"Automobile Sales",
            "type":"Retail Goods"
        }
    ],
    "sg:phone":"+1 701 839 3534",
    "sg:postcode":"58703",
    "sg:province":"ND",
    "sg:tags":[
        "car",
        "dealer"
    ],
    "wof:name":"Car Mart",
    "wof:placetype":"venue"
},
  "geometry": {"coordinates":[-101.296029,48.275928],"type":"Point"}
}