{
  "type": "Feature",
  "properties": {
    "addr:full":"3400 7th Ave N Fargo ND 58102",
    "addr:housenumber":"3400",
    "addr:postcode":"58102",
    "addr:street":"7Th Ave N",
    "iso:country":"US",
    "sg:address":"3400 7th Ave N",
    "sg:city":"Fargo",
    "sg:classifiers":[
        {
            "category":"Wholesale",
            "subcategory":"Hardware",
            "type":"Manufacturing & Wholesale Goods"
        }
    ],
    "sg:phone":"+1 701 241 4400",
    "sg:postcode":"58102",
    "sg:province":"ND",
    "sg:tags":[
        "refrigerating"
    ],
    "sg:website":"www.galarson.com",
    "wof:name":"Gustave A Larson Co",
    "wof:placetype":"venue"
},
  "geometry": {"coordinates":[-96.83362200000001,46.883272],"type":"Point"}
}