{
  "type": "Feature",
  "properties": {
    "iso:country":"US",
    "sg:address":"405 6th Ave W",
    "sg:city":"Lemmon",
    "sg:classifiers":[
        {
            "category":"Health Services",
            "subcategory":"Nursing And Care Facility",
            "type":"Services"
        }
    ],
    "sg:phone":"+1 605 374 3871",
    "sg:postcode":"57638",
    "sg:province":"ND",
    "sg:tags":[
        "home",
        "convalescent"
    ],
    "wof:name":"Five Counties Hospital & Nrsng",
    "wof:placetype":"venue"
},
  "geometry": {"coordinates":[-102.16807,45.940947],"type":"Point"}
}