{
  "type": "Feature",
  "properties": {
    "iso:country":"US",
    "sg:address":"5839 Lariat Loop",
    "sg:city":"Bismarck",
    "sg:classifiers":[
        {
            "category":"Professional",
            "subcategory":"Engineering",
            "type":"Services"
        },
        {
            "category":"Wholesale",
            "subcategory":"Durable Goods & Equipment",
            "type":"Manufacturing & Wholesale Goods"
        }
    ],
    "sg:phone":"+1 701 224 0346",
    "sg:postcode":"58503",
    "sg:province":"ND",
    "sg:tags":[
        "representative",
        "manufacturer"
    ],
    "wof:name":"K & B Engineering",
    "wof:placetype":"venue"
},
  "geometry": {"coordinates":[-100.883875,46.888073],"type":"Point"}
}