{
  "type": "Feature",
  "properties": {
    "iso:country":"US",
    "sg:address":"414 4th St",
    "sg:city":"Devils Lake",
    "sg:classifiers":[
        {
            "category":"Shopping",
            "type":"Retail Goods"
        }
    ],
    "sg:phone":"+1 701 662 6950",
    "sg:postcode":"58301",
    "sg:province":"ND",
    "sg:tags":[
        "merchandise"
    ],
    "wof:name":"Dakota Gold & Silver",
    "wof:placetype":"venue"
},
  "geometry": {"coordinates":[-98.860237,48.111687],"type":"Point"}
}