{
  "type": "Feature",
  "properties": {
    "iso:country":"US",
    "sg:address":"1407 24th Ave S",
    "sg:city":"Grand Forks",
    "sg:classifiers":[
        {
            "category":"Health Services",
            "subcategory":"Health Practitioner",
            "type":"Services"
        }
    ],
    "sg:phone":"+1 701 746 6336",
    "sg:postcode":"58201",
    "sg:province":"ND",
    "sg:tags":[
        "psychologist"
    ],
    "wof:name":"Agassiz Associates Pllc",
    "wof:placetype":"venue"
},
  "geometry": {"coordinates":[-97.05003000000001,47.895724],"type":"Point"}
}