{
  "type": "Feature",
  "properties": {
    "iso:country":"US",
    "sg:address":"3327 E Broadway Ave",
    "sg:city":"Bismarck",
    "sg:classifiers":[
        {
            "category":"Building & Trades",
            "subcategory":"Electrical",
            "type":"Services"
        }
    ],
    "sg:phone":"+1 701 223 3962",
    "sg:postcode":"58501",
    "sg:province":"ND",
    "sg:tags":[
        "electric",
        "contractor"
    ],
    "wof:name":"Ben's Electric",
    "wof:placetype":"venue"
},
  "geometry": {"coordinates":[-100.740229,46.807926],"type":"Point"}
}