{
  "type": "Feature",
  "properties": {
    "addr:full":"1021 Main Ave W West Fargo ND 58078",
    "addr:housenumber":"1021",
    "addr:postcode":"58078",
    "addr:street":"Main Ave W",
    "iso:country":"US",
    "sg:address":"1021 Main Ave W",
    "sg:city":"West Fargo",
    "sg:classifiers":[
        {
            "category":"Autos & Motor Vehicles",
            "subcategory":"Fuel & Gas Station",
            "type":"Retail Goods"
        }
    ],
    "sg:phone":"+1 701 281 9180",
    "sg:postcode":"58078",
    "sg:province":"ND",
    "sg:tags":[
        "plaza",
        "truck",
        "stops"
    ],
    "wof:name":"West Fargo Truck Stop",
    "wof:placetype":"venue"
},
  "geometry": {"coordinates":[-96.917452,46.876957],"type":"Point"}
}