{
  "type": "Feature",
  "properties": {
    "iso:country":"US",
    "sg:address":"419 9th St S",
    "sg:city":"Oakes",
    "sg:phone":"+1 701 742 3324",
    "sg:postcode":"58474",
    "sg:province":"ND",
    "sg:tags":[
        "farm",
        "grain",
        "cash"
    ],
    "wof:name":"Harvey Karas",
    "wof:placetype":"venue"
},
  "geometry": {"coordinates":[-98.087621,46.134512],"type":"Point"}
}