{
  "type": "Feature",
  "properties": {
    "iso:country":"US",
    "sg:address":"8744 39th St NW",
    "sg:city":"New Town",
    "sg:classifiers":[
        {
            "category":"Retail",
            "subcategory":"Auto Repair",
            "type":"Services"
        }
    ],
    "sg:phone":"+1 701 627 5244",
    "sg:postcode":"58763",
    "sg:province":"ND",
    "wof:name":"Sam's Auto Repair",
    "wof:placetype":"venue"
},
  "geometry": {"coordinates":[-73.833456,40.759308],"type":"Point"}
}