{
  "type": "Feature",
  "properties": {
    "iso:country":"US",
    "sg:address":"310 2nd Ave SW",
    "sg:city":"Rugby",
    "sg:classifiers":[
        {
            "category":"Organizations",
            "subcategory":"Political Organization",
            "type":"Services"
        }
    ],
    "sg:phone":"+1 701 776 6686",
    "sg:postcode":"58368",
    "sg:province":"ND",
    "wof:name":"Rob Bollinger For Congres",
    "wof:placetype":"venue"
},
  "geometry": {"coordinates":[-99.99772299999999,48.367581],"type":"Point"}
}