{
  "type": "Feature",
  "properties": {
    "addr:full":"500 E Rosser Ave Bismarck ND 58501",
    "addr:housenumber":"500",
    "addr:postcode":"58501",
    "addr:street":"E Rosser Ave",
    "iso:country":"US",
    "sg:address":"500 E Rosser Ave",
    "sg:city":"Bismarck",
    "sg:classifiers":[
        {
            "category":"Banks & Credit Unions",
            "subcategory":"Bank",
            "type":"Services"
        }
    ],
    "sg:phone":"+1 701 222 5100",
    "sg:postcode":"58501",
    "sg:province":"ND",
    "wof:name":"Wells Fargo Bank",
    "wof:placetype":"venue"
},
  "geometry": {"coordinates":[-100.78304300000001,46.808552],"type":"Point"}
}