{
  "type": "Feature",
  "properties": {
    "addr:full":"2220 24th Ave SE Minot ND 58701",
    "addr:housenumber":"2220",
    "addr:postcode":"58701",
    "addr:street":"24Th Ave Se",
    "iso:country":"US",
    "sg:address":"2220 24th Ave SE",
    "sg:city":"Minot",
    "sg:classifiers":[
        {
            "category":"Organizations",
            "subcategory":"Religious Organization",
            "type":"Services"
        }
    ],
    "sg:phone":"+1 701 852 0684",
    "sg:postcode":"58701",
    "sg:province":"ND",
    "sg:tags":[
        "church"
    ],
    "wof:name":"South Side Church of Nazarene",
    "wof:placetype":"venue"
},
  "geometry": {"coordinates":[-101.25826499999999,48.208427],"type":"Point"}
}