{
  "type": "Feature",
  "properties": {
    "addr:full":"511 S Anderson St Bismarck ND 58504",
    "addr:housenumber":"511",
    "addr:postcode":"58504",
    "addr:street":"S Anderson St",
    "iso:country":"US",
    "sg:address":"511 S Anderson St",
    "sg:city":"Bismarck",
    "sg:classifiers":[
        {
            "category":"Organizations",
            "subcategory":"Religious Organization",
            "type":"Services"
        }
    ],
    "sg:phone":"+1 701 258 6786",
    "sg:postcode":"58504",
    "sg:province":"ND",
    "wof:name":"Power Club",
    "wof:placetype":"venue"
},
  "geometry": {"coordinates":[-100.799451,46.80076],"type":"Point"}
}