{
  "type": "Feature",
  "properties": {
    "addr:full":"4400 Hwy 6 Mandan ND 58554",
    "addr:housenumber":"4400",
    "addr:postcode":"58554",
    "addr:street":"Hwy 6",
    "iso:country":"US",
    "sg:address":"4400 Hwy 6",
    "sg:city":"Mandan",
    "sg:classifiers":[
        {
            "category":"Farming",
            "subcategory":"Farm",
            "type":"Manufacturing & Wholesale Goods"
        }
    ],
    "sg:phone":"+1 701 663 6606",
    "sg:postcode":"58554",
    "sg:province":"ND",
    "wof:name":"Renner Farm",
    "wof:placetype":"venue"
},
  "geometry": {"coordinates":[-100.901494,46.767475],"type":"Point"}
}