{
  "type": "Feature",
  "properties": {
    "addr:full":"2215 E Main Ave Bismarck ND 58501",
    "addr:housenumber":"2215",
    "addr:postcode":"58501",
    "addr:street":"E Main Ave",
    "iso:country":"US",
    "sg:address":"2215 E Main Ave",
    "sg:city":"Bismarck",
    "sg:classifiers":[
        {
            "category":"Health Services",
            "subcategory":"Chiropractor",
            "type":"Services"
        }
    ],
    "sg:phone":"+1 701 222 3013",
    "sg:postcode":"58501",
    "sg:province":"ND",
    "wof:name":"Kraft Chiropractic Clinic",
    "wof:placetype":"venue"
},
  "geometry": {"coordinates":[-100.758662,46.805063],"type":"Point"}
}