{
  "type": "Feature",
  "properties": {
    "addr:full":"7390 51 St NW Palermo ND 58769",
    "addr:housenumber":"7390",
    "addr:postcode":"58769",
    "addr:street":"51 St Nw",
    "iso:country":"US",
    "sg:address":"7390 51 St NW",
    "sg:city":"Palermo",
    "sg:classifiers":[
        {
            "category":"Farming",
            "subcategory":"Farm",
            "type":"Manufacturing & Wholesale Goods"
        }
    ],
    "sg:phone":"+1 701 628 2095",
    "sg:postcode":"58769",
    "sg:province":"ND",
    "sg:tags":[
        "crop",
        "general"
    ],
    "wof:name":"M N Farm Inc",
    "wof:placetype":"venue"
},
  "geometry": {"coordinates":[-101.221295,48.511928],"type":"Point"}
}