{
  "type": "Feature",
  "properties": {
    "addr:full":"1014 17th St SW Jamestown ND 58401",
    "addr:housenumber":"1014",
    "addr:postcode":"58401",
    "addr:street":"17Th St Sw",
    "iso:country":"US",
    "sg:address":"1014 17th St SW",
    "sg:city":"Jamestown",
    "sg:classifiers":[
        {
            "category":"Food & Beverages",
            "subcategory":"Groceries & Convenience Stores",
            "type":"Retail Goods"
        }
    ],
    "sg:phone":"+1 701 251 2220",
    "sg:postcode":"58401",
    "sg:province":"ND",
    "wof:name":"Neighborhood Grocery",
    "wof:placetype":"venue"
},
  "geometry": {"coordinates":[-98.71979,46.892225],"type":"Point"}
}