{
  "type": "Feature",
  "properties": {
    "addr:full":"115 10th Ave NW Valley City ND 58072",
    "addr:housenumber":"115",
    "addr:postcode":"58072",
    "addr:street":"10Th Ave Nw",
    "iso:country":"US",
    "sg:address":"115 10th Ave NW",
    "sg:city":"Valley City",
    "sg:classifiers":[
        {
            "category":"Building & Trades",
            "subcategory":"Construction",
            "type":"Services"
        }
    ],
    "sg:phone":"+1 701 845 8508",
    "sg:postcode":"58072",
    "sg:province":"ND",
    "sg:tags":[
        "grading",
        "contractor"
    ],
    "sg:website":"www.co.barnes.nd.us",
    "wof:name":"Barnes County Highway Dept",
    "wof:placetype":"venue"
},
  "geometry": {"coordinates":[-98.01648299999999,46.923786],"type":"Point"}
}