{
  "type": "Feature",
  "properties": {
    "addr:full":"647 Kirkwood Mall Bismarck ND 58504",
    "addr:housenumber":"647",
    "addr:postcode":"58504",
    "addr:street":"Kirkwood Mall",
    "iso:country":"US",
    "sg:address":"647 Kirkwood Mall",
    "sg:city":"Bismarck",
    "sg:classifiers":[
        {
            "category":"Banks & Credit Unions",
            "subcategory":"Bank",
            "type":"Services"
        }
    ],
    "sg:phone":"+1 701 258 3184",
    "sg:postcode":"58504",
    "sg:province":"ND",
    "sg:tags":[
        "national"
    ],
    "wof:name":"US Bank",
    "wof:placetype":"venue"
},
  "geometry": {"coordinates":[-100.784716,46.799717],"type":"Point"}
}