{
  "type": "Feature",
  "properties": {
    "addr:full":"209 Main St Solen ND 58570",
    "addr:housenumber":"209",
    "addr:postcode":"58570",
    "addr:street":"Main St",
    "iso:country":"US",
    "sg:address":"209 Main St",
    "sg:city":"Solen",
    "sg:classifiers":[
        {
            "category":"Bars & Pubs",
            "type":"Food & Drink"
        }
    ],
    "sg:phone":"+1 701 445 3415",
    "sg:postcode":"58570",
    "sg:province":"ND",
    "wof:name":"Last Chance Bar",
    "wof:placetype":"venue"
},
  "geometry": {"coordinates":[-100.796482,46.385917],"type":"Point"}
}