{
  "type": "Feature",
  "properties": {
    "iso:country":"US",
    "sg:address":"1930 Burnt Boat Dr",
    "sg:city":"Bismarck",
    "sg:classifiers":[
        {
            "category":"Government",
            "subcategory":"Office",
            "type":"Public Place"
        }
    ],
    "sg:phone":"+1 701 328 9885",
    "sg:postcode":"58503",
    "sg:province":"ND",
    "sg:website":"www.discovernd.com",
    "wof:name":"Retirement & Investment Office",
    "wof:placetype":"venue"
},
  "geometry": {"coordinates":[-100.830324,46.832184],"type":"Point"}
}