{
  "type": "Feature",
  "properties": {
    "iso:country":"US",
    "sg:address":"617 Main Ave",
    "sg:city":"Hebron",
    "sg:classifiers":[
        {
            "category":"Professional",
            "type":"Services"
        }
    ],
    "sg:phone":"+1 701 878 9700",
    "sg:postcode":"58638",
    "sg:province":"ND",
    "sg:tags":[
        "establishment"
    ],
    "wof:name":"Grizella Corp",
    "wof:placetype":"venue"
},
  "geometry": {"coordinates":[-102.045372,46.900795],"type":"Point"}
}