{
  "type": "Feature",
  "properties": {
    "addr:full":"3331 S University Dr Fargo ND 58104",
    "addr:housenumber":"3331",
    "addr:postcode":"58104",
    "addr:street":"S University Dr",
    "iso:country":"US",
    "sg:address":"3331 S University Dr",
    "sg:city":"Fargo",
    "sg:classifiers":[
        {
            "category":"Arts & Performance",
            "subcategory":"Theater",
            "type":"Entertainment"
        }
    ],
    "sg:phone":"+1 701 235 3695",
    "sg:postcode":"58104",
    "sg:province":"ND",
    "sg:tags":[
        "a",
        "sales",
        "also",
        "visual",
        "provides",
        "audio",
        "rental"
    ],
    "wof:name":"HB Sound & Light",
    "wof:placetype":"venue"
},
  "geometry": {"coordinates":[-96.8013,46.829051],"type":"Point"}
}