{
  "type": "Feature",
  "properties": {
    "iso:country":"US",
    "sg:address":"8631 104th Ave SE",
    "sg:city":"Oakes",
    "sg:classifiers":[
        {
            "category":"Farming",
            "subcategory":"Fish & Marine Products",
            "type":"Manufacturing & Wholesale Goods"
        }
    ],
    "sg:phone":"+1 701 742 2613",
    "sg:postcode":"58474",
    "sg:province":"SD",
    "sg:tags":[
        "catching",
        "feedlot",
        "beef",
        "cattle"
    ],
    "wof:name":"Doug Ptacek",
    "wof:placetype":"venue"
},
  "geometry": {"coordinates":[-98.215051,46.155094],"type":"Point"}
}