{
  "type": "Feature",
  "properties": {
    "iso:country":"US",
    "sg:address":"631 8th Ave S",
    "sg:city":"Casselton",
    "sg:phone":"+1 701 347 5338",
    "sg:postcode":"58012",
    "sg:province":"ND",
    "sg:tags":[
        "c",
        "wheat",
        "farm",
        "cash",
        "beet",
        "grain"
    ],
    "wof:name":"Douglas Moderow",
    "wof:placetype":"venue"
},
  "geometry": {"coordinates":[-97.210734,46.893376],"type":"Point"}
}