{
  "type": "Feature",
  "properties": {
    "iso:country":"US",
    "sg:address":"659 Wyndemere Dr",
    "sg:city":"West Fargo",
    "sg:classifiers":[
        {
            "category":"Building & Trades",
            "subcategory":"Electrical",
            "type":"Services"
        }
    ],
    "sg:phone":"+1 701 282 7519",
    "sg:postcode":"58078",
    "sg:province":"ND",
    "sg:tags":[
        "electrical",
        "contractor"
    ],
    "wof:name":"West Fargo Electric",
    "wof:placetype":"venue"
},
  "geometry": {"coordinates":[-96.892596,46.856095],"type":"Point"}
}