{
  "type": "Feature",
  "properties": {
    "iso:country":"US",
    "sg:address":"8844 108th Ave SE",
    "sg:city":"Oakes",
    "sg:classifiers":[
        {
            "category":"Building & Trades",
            "subcategory":"Plumbing",
            "type":"Services"
        }
    ],
    "sg:phone":"+1 701 742 3085",
    "sg:postcode":"58474",
    "sg:province":"SD",
    "sg:tags":[
        "plumbing",
        "contractor"
    ],
    "wof:name":"B & K Murphy Plumbing & Heatin",
    "wof:placetype":"venue"
},
  "geometry": {"coordinates":[-98.13164500000001,46.131867],"type":"Point"}
}