{
  "type": "Feature",
  "properties": {
    "iso:country":"US",
    "sg:address":"2125 2nd St SW",
    "sg:city":"Minot",
    "sg:classifiers":[
        {
            "category":"Autos & Motor Vehicles",
            "subcategory":"Boat Sales",
            "type":"Retail Goods"
        }
    ],
    "sg:phone":"+1 701 852 1625",
    "sg:postcode":"58701",
    "sg:province":"ND",
    "sg:tags":[
        "dealer",
        "sales"
    ],
    "sg:website":"www.vallelymarine.com",
    "wof:name":"Vallely Sport & Marine",
    "wof:placetype":"venue"
},
  "geometry": {"coordinates":[-101.29583,48.20997],"type":"Point"}
}