{
  "type": "Feature",
  "properties": {
    "iso:country":"US",
    "sg:address":"800 31st Ave SW",
    "sg:city":"Minot",
    "sg:classifiers":[
        {
            "category":"Building & Trades",
            "subcategory":"Construction",
            "type":"Services"
        }
    ],
    "sg:phone":"+1 701 852 6942",
    "sg:postcode":"58701",
    "sg:province":"ND",
    "sg:tags":[
        "hanging",
        "contractor"
    ],
    "wof:name":"Partners In Painting",
    "wof:placetype":"venue"
},
  "geometry": {"coordinates":[-101.304149,48.202983],"type":"Point"}
}