{
  "type": "Feature",
  "properties": {
    "iso:country":"US",
    "sg:address":"8210 33rd St SE",
    "sg:city":"Jamestown",
    "sg:classifiers":[
        {
            "category":"Professional",
            "type":"Services"
        }
    ],
    "sg:phone":"+1 701 252 0032",
    "sg:postcode":"58401",
    "sg:province":"ND",
    "sg:tags":[
        "establishment"
    ],
    "wof:name":"Anchor Bar",
    "wof:placetype":"venue"
},
  "geometry": {"coordinates":[-98.73134400000001,46.935421],"type":"Point"}
}