{
  "type": "Feature",
  "properties": {
    "iso:country":"US",
    "sg:address":"216 41st Ave NE",
    "sg:city":"Bowdon",
    "sg:phone":"+1 701 962 3327",
    "sg:postcode":"58418",
    "sg:province":"ND",
    "sg:tags":[
        "farm",
        "wheat"
    ],
    "wof:name":"Terry Jesse",
    "wof:placetype":"venue"
},
  "geometry": {"coordinates":[-99.671358,47.443264],"type":"Point"}
}