{
  "type": "Feature",
  "properties": {
    "iso:country":"US",
    "sg:address":"896 64th Ave SE",
    "sg:city":"Pingree",
    "sg:classifiers":[
        {
            "category":"Farming",
            "subcategory":"Livestock Farm",
            "type":"Manufacturing & Wholesale Goods"
        }
    ],
    "sg:phone":"+1 701 285 3338",
    "sg:postcode":"58476",
    "sg:province":"ND",
    "sg:tags":[
        "beef",
        "feedlot",
        "cattle"
    ],
    "wof:name":"Gary Edinger",
    "wof:placetype":"venue"
},
  "geometry": {"coordinates":[-99.14342600000001,47.284412],"type":"Point"}
}