{
  "type": "Feature",
  "properties": {
    "iso:country":"US",
    "sg:address":"1443 S 3rd St",
    "sg:city":"Bismarck",
    "sg:classifiers":[
        {
            "category":"Building & Trades",
            "subcategory":"Construction",
            "type":"Services"
        }
    ],
    "sg:phone":"+1 701 400 6734",
    "sg:postcode":"58504",
    "sg:province":"ND",
    "sg:tags":[
        "house"
    ],
    "wof:name":"Olheiser Repair & Construction",
    "wof:placetype":"venue"
},
  "geometry": {"coordinates":[-100.7842,46.788571],"type":"Point"}
}