{
  "type": "Feature",
  "properties": {
    "addr:full":"1118 6th St Langdon ND 58249",
    "addr:housenumber":"1118",
    "addr:postcode":"58249",
    "addr:street":"6Th St",
    "iso:country":"US",
    "sg:address":"1118 6th St",
    "sg:city":"Langdon",
    "sg:phone":"+1 701 256 2479",
    "sg:postcode":"58249",
    "sg:province":"ND",
    "sg:tags":[
        "farm",
        "grain",
        "cash"
    ],
    "wof:name":"Darin R Ullyott",
    "wof:placetype":"venue"
},
  "geometry": {"coordinates":[-98.37295399999999,48.764011],"type":"Point"}
}