{
  "type": "Feature",
  "properties": {
    "iso:country":"US",
    "sg:address":"123 1st Ave S",
    "sg:city":"Jamestown",
    "sg:classifiers":[
        {
            "category":"Banks & Credit Unions",
            "subcategory":"Investment Brokerage",
            "type":"Services"
        }
    ],
    "sg:phone":"+1 701 253 2713",
    "sg:postcode":"58401",
    "sg:province":"ND",
    "sg:tags":[
        "security"
    ],
    "wof:name":"US Bancorp Investments Inc",
    "wof:placetype":"venue"
},
  "geometry": {"coordinates":[-98.70841799999999,46.908442],"type":"Point"}
}