{
  "type": "Feature",
  "properties": {
    "iso:country":"US",
    "sg:address":"2802 12th St S",
    "sg:city":"Fargo",
    "sg:classifiers":[
        {
            "category":"Organizations",
            "subcategory":"Religious Organization",
            "type":"Services"
        }
    ],
    "sg:phone":"+1 701 237 9140",
    "sg:postcode":"58103",
    "sg:province":"ND",
    "sg:tags":[
        "church"
    ],
    "wof:name":"Calvary United Mthdst Kitchen",
    "wof:placetype":"venue"
},
  "geometry": {"coordinates":[-96.796947,46.834842],"type":"Point"}
}