{
  "type": "Feature",
  "properties": {
    "iso:country":"US",
    "sg:address":"228 Eagle Dr",
    "sg:city":"New Town",
    "sg:classifiers":[
        {
            "category":"Organizations",
            "subcategory":"Religious Organization",
            "type":"Services"
        }
    ],
    "sg:phone":"+1 701 627 4434",
    "sg:postcode":"58763",
    "sg:province":"ND",
    "sg:tags":[
        "church"
    ],
    "wof:name":"Bethel Lutheran Church Inc",
    "wof:placetype":"venue"
},
  "geometry": {"coordinates":[-102.488882,47.980734],"type":"Point"}
}