{
  "type": "Feature",
  "properties": {
    "iso:country":"US",
    "sg:address":"716 1st Ave N",
    "sg:city":"Fargo",
    "sg:classifiers":[
        {
            "category":"Professional",
            "subcategory":"Advertising",
            "type":"Services"
        }
    ],
    "sg:phone":"+1 701 293 1190",
    "sg:postcode":"58102",
    "sg:province":"ND",
    "sg:tags":[
        "mail",
        "direct"
    ],
    "wof:name":"Advanced Marketing Inc",
    "wof:placetype":"venue"
},
  "geometry": {"coordinates":[-96.791422,46.877142],"type":"Point"}
}