{
  "type": "Feature",
  "properties": {
    "iso:country":"US",
    "sg:address":"5970 Lariat Loop",
    "sg:city":"Bismarck",
    "sg:classifiers":[
        {
            "category":"Building & Trades",
            "subcategory":"Pest Control",
            "type":"Services"
        }
    ],
    "sg:phone":"+1 701 258 7016",
    "sg:postcode":"58503",
    "sg:province":"ND",
    "wof:name":"Spiderman",
    "wof:placetype":"venue"
},
  "geometry": {"coordinates":[-100.886078,46.887135],"type":"Point"}
}