{
  "type": "Feature",
  "properties": {
    "iso:country":"US",
    "sg:address":"389 15th St W",
    "sg:city":"Dickinson",
    "sg:classifiers":[
        {
            "category":"Health Services",
            "subcategory":"Doctor",
            "type":"Services"
        }
    ],
    "sg:phone":"+1 701 483 1385",
    "sg:postcode":"58601",
    "sg:province":"ND",
    "sg:tags":[
        "dentist"
    ],
    "wof:name":"Sharon Carver-King DDS",
    "wof:placetype":"venue"
},
  "geometry": {"coordinates":[-102.79059700000001,46.898817],"type":"Point"}
}