{
  "type": "Feature",
  "properties": {
    "iso:country":"US",
    "sg:address":"208 College Dr S",
    "sg:city":"Devils Lake",
    "sg:classifiers":[
        {
            "category":"Building & Trades",
            "subcategory":"Construction",
            "type":"Services"
        }
    ],
    "sg:phone":"+1 701 662 4394",
    "sg:postcode":"58301",
    "sg:province":"ND",
    "sg:tags":[
        "excavating",
        "contractor"
    ],
    "wof:name":"Durbin Excavating",
    "wof:placetype":"venue"
},
  "geometry": {"coordinates":[-98.865093,48.107275],"type":"Point"}
}