{
  "type": "Feature",
  "properties": {
    "iso:country":"US",
    "sg:address":"1353 State Hwy 22",
    "sg:city":"Manning",
    "sg:phone":"+1 701 573 4439",
    "sg:postcode":"58642",
    "sg:province":"ND",
    "sg:tags":[
        "farm",
        "wheat",
        "dairy"
    ],
    "wof:name":"Shawn Brew",
    "wof:placetype":"venue"
},
  "geometry": {"coordinates":[-102.770644,47.231718],"type":"Point"}
}