{
  "type": "Feature",
  "properties": {
    "addr:full":"411 W Main St Mandan ND 58554",
    "addr:housenumber":"411",
    "addr:postcode":"58554",
    "addr:street":"W Main St",
    "iso:country":"US",
    "sg:address":"411 W Main St",
    "sg:city":"Mandan",
    "sg:classifiers":[
        {
            "category":"Professional",
            "subcategory":"Management & Consulting",
            "type":"Services"
        }
    ],
    "sg:phone":"+1 701 663 6978",
    "sg:postcode":"58554",
    "sg:province":"ND",
    "sg:tags":[
        "business"
    ],
    "wof:name":"Kipp & Associates Inc",
    "wof:placetype":"venue"
},
  "geometry": {"coordinates":[-100.89433200000001,46.825735],"type":"Point"}
}