{
  "type": "Feature",
  "properties": {
    "iso:country":"US",
    "sg:address":"4101 13th Ave SW",
    "sg:city":"Fargo",
    "sg:classifiers":[
        {
            "category":"Shopping",
            "subcategory":"Bicycles & Sporting Goods",
            "type":"Retail Goods"
        }
    ],
    "sg:phone":"+1 701 282 0131",
    "sg:postcode":"58103",
    "sg:province":"ND",
    "wof:name":"Outdoorsman Inc",
    "wof:placetype":"venue"
},
  "geometry": {"coordinates":[-96.849276,46.861891],"type":"Point"}
}