{
  "type": "Feature",
  "properties": {
    "iso:country":"US",
    "sg:address":"4110 State Hwy 5",
    "sg:city":"Mohall",
    "sg:phone":"+1 701 756 6485",
    "sg:postcode":"58761",
    "sg:province":"ND",
    "sg:tags":[
        "farm",
        "wheat"
    ],
    "wof:name":"Moberg Farms",
    "wof:placetype":"venue"
},
  "geometry": {"coordinates":[-101.522043,48.76349],"type":"Point"}
}