{
  "type": "Feature",
  "properties": {
    "addr:full":"5350 12th St SE Bismarck ND 58504",
    "addr:housenumber":"5350",
    "addr:postcode":"58504",
    "addr:street":"12Th St Se",
    "iso:country":"US",
    "sg:address":"5350 12th St SE",
    "sg:city":"Bismarck",
    "sg:classifiers":[
        {
            "category":"Professional",
            "subcategory":"Management & Consulting",
            "type":"Services"
        }
    ],
    "sg:phone":"+1 701 258 6185",
    "sg:postcode":"58504",
    "sg:province":"ND",
    "wof:name":"Cz Consulting",
    "wof:placetype":"venue"
},
  "geometry": {"coordinates":[-100.774079,46.744888],"type":"Point"}
}