{
  "type": "Feature",
  "properties": {
    "iso:country":"US",
    "sg:address":"108 1st St NW",
    "sg:city":"Gwinner",
    "sg:classifiers":[
        {
            "category":"Freight",
            "type":"Transportation"
        }
    ],
    "sg:phone":"+1 701 678 2468",
    "sg:postcode":"58040",
    "sg:province":"ND",
    "sg:tags":[
        "grain",
        "elevator"
    ],
    "wof:name":"Gwinner Farmers Elevator Co",
    "wof:placetype":"venue"
},
  "geometry": {"coordinates":[-97.663994,46.22743],"type":"Point"}
}