{
  "type": "Feature",
  "properties": {
    "iso:country":"US",
    "sg:address":"360 26th St NW",
    "sg:city":"Butte",
    "sg:classifiers":[
        {
            "category":"Freight",
            "type":"Transportation"
        }
    ],
    "sg:phone":"+1 701 626 7392",
    "sg:postcode":"58723",
    "sg:province":"ND",
    "sg:tags":[
        "operator",
        "local",
        "trucking"
    ],
    "wof:name":"Dt Trucking",
    "wof:placetype":"venue"
},
  "geometry": {"coordinates":[-100.660714,47.789989],"type":"Point"}
}