{
  "type": "Feature",
  "properties": {
    "iso:country":"US",
    "sg:address":"8 2nd St SE",
    "sg:city":"Rolla",
    "sg:classifiers":[
        {
            "category":"Arts & Performance",
            "subcategory":"Theater",
            "type":"Entertainment"
        }
    ],
    "sg:phone":"+1 701 477 6188",
    "sg:postcode":"58367",
    "sg:province":"ND",
    "sg:tags":[
        "theatrical"
    ],
    "wof:name":"Dakota Prrie Cmnty Action Agcy",
    "wof:placetype":"venue"
},
  "geometry": {"coordinates":[-99.613938,48.859674],"type":"Point"}
}