{
  "type": "Feature",
  "properties": {
    "iso:country":"US",
    "sg:address":"5245 38th St NE",
    "sg:city":"Maddock",
    "sg:classifiers":[
        {
            "category":"Building & Trades",
            "subcategory":"Construction",
            "type":"Services"
        }
    ],
    "sg:phone":"+1 701 438 2337",
    "sg:postcode":"58348",
    "sg:province":"ND",
    "wof:name":"Maddox Construction Co",
    "wof:placetype":"venue"
},
  "geometry": {"coordinates":[-99.45338,47.962686],"type":"Point"}
}