{
  "type": "Feature",
  "properties": {
    "addr:full":"104 Central Ave Maddock ND 58348",
    "addr:housenumber":"104",
    "addr:postcode":"58348",
    "addr:street":"Central Ave",
    "iso:country":"US",
    "sg:address":"104 Central Ave",
    "sg:city":"Maddock",
    "sg:classifiers":[
        {
            "category":"Banks & Credit Unions",
            "subcategory":"Bank",
            "type":"Services"
        }
    ],
    "sg:phone":"+1 701 438 2828",
    "sg:postcode":"58348",
    "sg:province":"ND",
    "sg:tags":[
        "loan"
    ],
    "wof:name":"Ramsey National Bank & Trust",
    "wof:placetype":"venue"
},
  "geometry": {"coordinates":[-99.530188,47.962175],"type":"Point"}
}