{
  "type": "Feature",
  "properties": {
    "addr:full":"1258 12th St N Fargo ND 58102",
    "addr:housenumber":"1258",
    "addr:postcode":"58102",
    "addr:street":"12Th St N",
    "iso:country":"US",
    "sg:address":"1258 12th St N",
    "sg:city":"Fargo",
    "sg:classifiers":[
        {
            "category":"Organizations",
            "subcategory":"Community Association",
            "type":"Services"
        }
    ],
    "sg:phone":"+1 701 478 1834",
    "sg:postcode":"58102",
    "sg:province":"ND",
    "wof:name":"Delta Upsilon Frat",
    "wof:placetype":"venue"
},
  "geometry": {"coordinates":[-96.796773,46.891618],"type":"Point"}
}