{
  "type": "Feature",
  "properties": {
    "iso:country":"US",
    "sg:address":"750 7th St N",
    "sg:city":"Carrington",
    "sg:classifiers":[
        {
            "category":"Wholesale",
            "subcategory":"Farm Supplies",
            "type":"Manufacturing & Wholesale Goods"
        }
    ],
    "sg:phone":"+1 701 652 3301",
    "sg:postcode":"58421",
    "sg:province":"ND",
    "sg:tags":[
        "fertilizer"
    ],
    "wof:name":"Agresource",
    "wof:placetype":"venue"
},
  "geometry": {"coordinates":[-99.11966,47.456325],"type":"Point"}
}