{
  "type": "Feature",
  "properties": {
    "addr:full":"422 2nd Ave NW Jamestown ND 58401",
    "addr:housenumber":"422",
    "addr:postcode":"58401",
    "addr:street":"2Nd Ave Nw",
    "iso:country":"US",
    "sg:address":"422 2nd Ave NW",
    "sg:city":"Jamestown",
    "sg:classifiers":[
        {
            "category":"Personal",
            "subcategory":"Beauty Salon",
            "type":"Services"
        }
    ],
    "sg:phone":"+1 701 252 4580",
    "sg:postcode":"58401",
    "sg:province":"ND",
    "sg:tags":[
        "shop"
    ],
    "wof:name":"Judy's Hair Fashions",
    "wof:placetype":"venue"
},
  "geometry": {"coordinates":[-98.71009599999999,46.912423],"type":"Point"}
}