{
  "type": "Feature",
  "properties": {
    "iso:country":"US",
    "sg:address":"82 23rd Ave N",
    "sg:city":"Fargo",
    "sg:classifiers":[
        {
            "category":"Professional",
            "subcategory":"Management & Consulting",
            "type":"Services"
        },
        {
            "category":"Professional",
            "subcategory":"Advertising",
            "type":"Services"
        },
        {
            "category":"Professional",
            "type":"Services"
        }
    ],
    "sg:phone":"+1 701 232 8132",
    "sg:postcode":"58102",
    "sg:province":"ND",
    "sg:tags":[
        "sample",
        "product",
        "service-circular",
        "fair",
        "marketing",
        "trade",
        "distributing",
        "program",
        "exposition",
        "consultant",
        "advertising-promotional",
        "shows"
    ],
    "wof:name":"Swor Marketing",
    "wof:placetype":"venue"
},
  "geometry": {"coordinates":[-96.778362,46.908215],"type":"Point"}
}