{
  "type": "Feature",
  "properties": {
    "iso:country":"US",
    "sg:address":"387 S Central Ave",
    "sg:city":"Beach",
    "sg:classifiers":[
        {
            "category":"Organizations",
            "subcategory":"Religious Organization",
            "type":"Services"
        }
    ],
    "sg:phone":"+1 701 872 4700",
    "sg:postcode":"58621",
    "sg:province":"ND",
    "sg:tags":[
        "church"
    ],
    "wof:name":"St Paul's Lutheran Church",
    "wof:placetype":"venue"
},
  "geometry": {"coordinates":[-104.00649900000001,46.911093],"type":"Point"}
}