{
  "type": "Feature",
  "properties": {
    "addr:full":"211 4th Ave Enderlin ND 58027",
    "addr:housenumber":"211",
    "addr:postcode":"58027",
    "addr:street":"4Th Ave",
    "iso:country":"US",
    "sg:address":"211 4th Ave",
    "sg:city":"Enderlin",
    "sg:classifiers":[
        {
            "category":"Organizations",
            "subcategory":"Religious Organization",
            "type":"Services"
        }
    ],
    "sg:phone":"+1 701 683 4408",
    "sg:postcode":"58027",
    "sg:province":"ND",
    "sg:tags":[
        "church"
    ],
    "wof:name":"Hope Evangelical Free Church",
    "wof:placetype":"venue"
},
  "geometry": {"coordinates":[-97.60123400000001,46.623773],"type":"Point"}
}