{
  "type": "Feature",
  "properties": {
    "iso:country":"US",
    "sg:address":"118 Broadway",
    "sg:city":"Fargo",
    "sg:classifiers":[
        {
            "category":"Professional",
            "subcategory":"Management & Consulting",
            "type":"Services"
        }
    ],
    "sg:phone":"+1 701 239 8445",
    "sg:postcode":"58102",
    "sg:province":"ND",
    "sg:tags":[
        "consultant",
        "business"
    ],
    "wof:name":"One Degree Consulting",
    "wof:placetype":"venue"
},
  "geometry": {"coordinates":[-96.787761,46.877819],"type":"Point"}
}