{
  "type": "Feature",
  "properties": {
    "iso:country":"US",
    "sg:address":"408 20th Ave SE",
    "sg:city":"Minot",
    "sg:classifiers":[
        {
            "category":"Retail",
            "subcategory":"Repair Shop",
            "type":"Services"
        },
        {
            "category":"Shopping",
            "subcategory":"Clothing, Apparel, & Fashions",
            "type":"Retail Goods"
        }
    ],
    "sg:phone":"+1 701 852 0722",
    "sg:postcode":"58701",
    "sg:province":"ND",
    "sg:tags":[
        "leather"
    ],
    "wof:name":"Hensen's Fur & Leather",
    "wof:placetype":"venue"
},
  "geometry": {"coordinates":[-101.289193,48.210996],"type":"Point"}
}