{
  "type": "Feature",
  "properties": {
    "iso:country":"US",
    "sg:address":"1657 96th Ave NE",
    "sg:city":"Mc Henry",
    "sg:classifiers":[
        {
            "category":"Farming",
            "subcategory":"Farm",
            "type":"Manufacturing & Wholesale Goods"
        }
    ],
    "sg:phone":"+1 701 785 2430",
    "sg:postcode":"58464",
    "sg:province":"ND",
    "sg:tags":[
        "crop",
        "general"
    ],
    "wof:name":"Hoffman Farms",
    "wof:placetype":"venue"
},
  "geometry": {"coordinates":[-98.500221,47.645499],"type":"Point"}
}