{
  "type": "Feature",
  "properties": {
    "iso:country":"US",
    "sg:address":"1681 3rd Ave W",
    "sg:city":"Dickinson",
    "sg:classifiers":[
        {
            "category":"Banks & Credit Unions",
            "subcategory":"Bank",
            "type":"Services"
        }
    ],
    "sg:phone":"+1 701 483 0874",
    "sg:postcode":"58601",
    "sg:province":"ND",
    "sg:website":"www.wellsfargo.com",
    "wof:name":"Wells Fargo Bank",
    "wof:placetype":"venue"
},
  "geometry": {"coordinates":[-102.789796,46.901915],"type":"Point"}
}