{
  "type": "Feature",
  "properties": {
    "iso:country":"US",
    "sg:address":"2725 109th Ave SE",
    "sg:city":"Sanborn",
    "sg:classifiers":[
        {
            "category":"Manufacturing",
            "subcategory":"Toys & Sporting Goods",
            "type":"Manufacturing & Wholesale Goods"
        }
    ],
    "sg:phone":"+1 701 646 6259",
    "sg:postcode":"58480",
    "sg:province":"ND",
    "sg:tags":[
        "mfg",
        "musical",
        "jester",
        "doll"
    ],
    "wof:name":"Hunters Imagination Unlimited",
    "wof:placetype":"venue"
},
  "geometry": {"coordinates":[-98.192055,47.023281],"type":"Point"}
}