{
  "type": "Feature",
  "properties": {
    "iso:country":"US",
    "sg:address":"1014 2nd St W",
    "sg:city":"Williston",
    "sg:classifiers":[
        {
            "category":"Building & Trades",
            "subcategory":"Equipment Rental",
            "type":"Services"
        }
    ],
    "sg:phone":"+1 701 572 0158",
    "sg:postcode":"58801",
    "sg:province":"ND",
    "sg:tags":[
        "yard"
    ],
    "wof:name":"Rent & Save",
    "wof:placetype":"venue"
},
  "geometry": {"coordinates":[-103.639045,48.145285],"type":"Point"}
}