{
  "type": "Feature",
  "properties": {
    "iso:country":"US",
    "sg:address":"920 Lincoln Ave",
    "sg:city":"Harvey",
    "sg:classifiers":[
        {
            "category":"Banks & Credit Unions",
            "subcategory":"Investment Brokerage",
            "type":"Services"
        }
    ],
    "sg:phone":"+1 701 324 2279",
    "sg:postcode":"58341",
    "sg:province":"ND",
    "sg:tags":[
        "security",
        "management",
        "consulting"
    ],
    "wof:name":"Investment Centers Of America",
    "wof:placetype":"venue"
},
  "geometry": {"coordinates":[-99.93628200000001,47.768896],"type":"Point"}
}