{
  "type": "Feature",
  "properties": {
    "iso:country":"US",
    "sg:address":"416 3rd St W",
    "sg:city":"Lakota",
    "sg:classifiers":[
        {
            "category":"Organizations",
            "subcategory":"Religious Organization",
            "type":"Services"
        }
    ],
    "sg:phone":"+1 701 247 2777",
    "sg:postcode":"58344",
    "sg:province":"ND",
    "sg:tags":[
        "church"
    ],
    "wof:name":"Lakota Lutheran Church",
    "wof:placetype":"venue"
},
  "geometry": {"coordinates":[-98.346481,48.044578],"type":"Point"}
}