{
  "type": "Feature",
  "properties": {
    "iso:country":"US",
    "sg:address":"5700 Gateway Dr",
    "sg:city":"Grand Forks",
    "sg:classifiers":[
        {
            "category":"Local Transit",
            "type":"Transportation"
        }
    ],
    "sg:phone":"+1 701 772 4187",
    "sg:postcode":"58203",
    "sg:province":"ND",
    "sg:tags":[
        "limousine"
    ],
    "wof:name":"Magic Limousine Svc",
    "wof:placetype":"venue"
},
  "geometry": {"coordinates":[-97.112531,47.932958],"type":"Point"}
}