{
  "type": "Feature",
  "properties": {
    "addr:full":"5301 Heatherwood Ln Bismarck ND 58501",
    "addr:housenumber":"5301",
    "addr:postcode":"58501",
    "addr:street":"Heatherwood Ln",
    "iso:country":"US",
    "sg:address":"5301 Heatherwood Ln",
    "sg:city":"Bismarck",
    "sg:classifiers":[
        {
            "category":"Social Services",
            "type":"Services"
        }
    ],
    "sg:phone":"+1 701 221 9800",
    "sg:postcode":"58501",
    "sg:province":"ND",
    "sg:tags":[
        "counseling"
    ],
    "wof:name":"Spirit Care Christian Cnslng",
    "wof:placetype":"venue"
},
  "geometry": {"coordinates":[-100.708292,46.807519],"type":"Point"}
}