{
  "type": "Feature",
  "properties": {
    "iso:country":"US",
    "sg:address":"13247 76th St NE",
    "sg:city":"Hoople",
    "sg:classifiers":[
        {
            "category":"Farming",
            "subcategory":"Farm",
            "type":"Manufacturing & Wholesale Goods"
        }
    ],
    "sg:phone":"+1 701 993 8489",
    "sg:postcode":"58243",
    "sg:province":"ND",
    "wof:name":"M G Erickson Farm",
    "wof:placetype":"venue"
},
  "geometry": {"coordinates":[-97.784194,48.513998],"type":"Point"}
}