{
  "type": "Feature",
  "properties": {
    "iso:country":"US",
    "sg:address":"11 1st Ave NE",
    "sg:city":"Rolla",
    "sg:classifiers":[
        {
            "category":"Manufacturing",
            "subcategory":"Printing",
            "type":"Manufacturing & Wholesale Goods"
        }
    ],
    "sg:phone":"+1 701 477 6495",
    "sg:postcode":"58367",
    "sg:province":"ND",
    "sg:tags":[
        "newspaper"
    ],
    "wof:name":"Turtle Mountain Star",
    "wof:placetype":"venue"
},
  "geometry": {"coordinates":[-99.616241,48.860026],"type":"Point"}
}