{
  "type": "Feature",
  "properties": {
    "iso:country":"US",
    "sg:address":"808 Clarke Dr",
    "sg:city":"Minot",
    "sg:classifiers":[
        {
            "category":"Organizations",
            "subcategory":"Membership Organization",
            "type":"Services"
        }
    ],
    "sg:phone":"+1 701 839 5832",
    "sg:postcode":"58701",
    "sg:province":"ND",
    "wof:name":"I Help Inc",
    "wof:placetype":"venue"
},
  "geometry": {"coordinates":[-101.305252,48.217302],"type":"Point"}
}