{
  "type": "Feature",
  "properties": {
    "iso:country":"US",
    "sg:address":"220 Towner Ave",
    "sg:city":"Larimore",
    "sg:classifiers":[
        {
            "category":"Bars & Pubs",
            "type":"Food & Drink"
        }
    ],
    "sg:phone":"+1 701 343 2044",
    "sg:postcode":"58251",
    "sg:province":"ND",
    "wof:name":"Good Friends Bar & Casino",
    "wof:placetype":"venue"
},
  "geometry": {"coordinates":[-97.623797,47.905041],"type":"Point"}
}