{
  "type": "Feature",
  "properties": {
    "iso:country":"US",
    "sg:address":"740 Hill Ave",
    "sg:city":"Grafton",
    "sg:classifiers":[
        {
            "category":"Retail",
            "subcategory":"Auto Repair",
            "type":"Services"
        }
    ],
    "sg:phone":"+1 701 352 2235",
    "sg:postcode":"58237",
    "sg:province":"ND",
    "sg:tags":[
        "general"
    ],
    "wof:name":"Jims Service Center",
    "wof:placetype":"venue"
},
  "geometry": {"coordinates":[-97.411074,48.41714],"type":"Point"}
}