{
  "type": "Feature",
  "properties": {
    "iso:country":"US",
    "sg:address":"2505 State St",
    "sg:city":"Bismarck",
    "sg:classifiers":[
        {
            "category":"Restaurant",
            "type":"Food & Drink"
        }
    ],
    "sg:phone":"+1 701 223 1907",
    "sg:postcode":"58503",
    "sg:province":"ND",
    "sg:tags":[
        "eating"
    ],
    "wof:name":"Kroll's Kitchen North",
    "wof:placetype":"venue"
},
  "geometry": {"coordinates":[-100.77269099999999,46.836102],"type":"Point"}
}