{
  "type": "Feature",
  "properties": {
    "iso:country":"US",
    "sg:address":"1731 34th St S",
    "sg:city":"Fargo",
    "sg:classifiers":[
        {
            "category":"Building & Trades",
            "subcategory":"Construction",
            "type":"Services"
        }
    ],
    "sg:phone":"+1 701 293 8921",
    "sg:postcode":"58103",
    "sg:province":"ND",
    "sg:tags":[
        "roofing",
        "siding",
        "work"
    ],
    "wof:name":"Rohrich Siding",
    "wof:placetype":"venue"
},
  "geometry": {"coordinates":[-96.83625499999999,46.853584],"type":"Point"}
}