{
  "type": "Feature",
  "properties": {
    "iso:country":"US",
    "sg:address":"2695 16th Ave NW",
    "sg:city":"Ruso",
    "sg:classifiers":[
        {
            "category":"Manufacturing",
            "subcategory":"Metals",
            "type":"Manufacturing & Wholesale Goods"
        }
    ],
    "sg:phone":"+1 701 626 7375",
    "sg:postcode":"58778",
    "sg:province":"ND",
    "sg:tags":[
        "product",
        "fabricated",
        "mfg"
    ],
    "wof:name":"Royal Distributors Inc",
    "wof:placetype":"venue"
},
  "geometry": {"coordinates":[-100.928967,47.804214],"type":"Point"}
}