{
  "type": "Feature",
  "properties": {
    "iso:country":"US",
    "sg:address":"616 1st Ave S",
    "sg:city":"Fargo",
    "sg:classifiers":[
        {
            "category":"Recreation",
            "type":"Entertainment"
        }
    ],
    "sg:phone":"+1 701 235 7685",
    "sg:postcode":"58103",
    "sg:province":"ND",
    "sg:tags":[
        "pool",
        "swimming"
    ],
    "wof:name":"Fargo Park Swimming Pools",
    "wof:placetype":"venue"
},
  "geometry": {"coordinates":[-96.78872800000001,46.873289],"type":"Point"}
}