{
  "type": "Feature",
  "properties": {
    "iso:country":"US",
    "sg:address":"20770 139th St SE",
    "sg:city":"Sawyer",
    "sg:phone":"+1 701 624 5569",
    "sg:postcode":"58781",
    "sg:province":"ND",
    "sg:tags":[
        "farm",
        "wheat",
        "grain",
        "cash"
    ],
    "wof:name":"Paul E Knorr",
    "wof:placetype":"venue"
},
  "geometry": {"coordinates":[-101.078883,48.020009],"type":"Point"}
}