{
  "type": "Feature",
  "properties": {
    "addr:full":"1730 N Washington St Grand Forks ND 58203",
    "addr:housenumber":"1730",
    "addr:postcode":"58203",
    "addr:street":"N Washington St",
    "iso:country":"US",
    "sg:address":"1730 N Washington St",
    "sg:city":"Grand Forks",
    "sg:classifiers":[
        {
            "category":"Shopping",
            "subcategory":"Discount & Variety Stores",
            "type":"Retail Goods"
        }
    ],
    "sg:phone":"+1 701 772 6471",
    "sg:postcode":"58203",
    "sg:province":"ND",
    "sg:tags":[
        "merchandise",
        "general"
    ],
    "wof:name":"Surplus Center Inc",
    "wof:placetype":"venue"
},
  "geometry": {"coordinates":[-97.05558499999999,47.935365],"type":"Point"}
}