{
  "type": "Feature",
  "properties": {
    "iso:country":"US",
    "sg:address":"2607 S Gate Dr",
    "sg:city":"Fargo",
    "sg:classifiers":[
        {
            "category":"Building & Trades",
            "subcategory":"Construction",
            "type":"Services"
        }
    ],
    "sg:phone":"+1 701 793 0273",
    "sg:postcode":"58103",
    "sg:province":"ND",
    "sg:tags":[
        "roofing",
        "contractor"
    ],
    "wof:name":"Peterson Residential Roofing",
    "wof:placetype":"venue"
},
  "geometry": {"coordinates":[-96.822695,46.856765],"type":"Point"}
}