{
  "type": "Feature",
  "properties": {
    "iso:country":"US",
    "sg:address":"10774 82nd St SE",
    "sg:city":"Oakes",
    "sg:classifiers":[
        {
            "category":"Real Estate",
            "subcategory":"Real Estate Operator",
            "type":"Services"
        }
    ],
    "sg:phone":"+1 701 742 2983",
    "sg:postcode":"58474",
    "sg:province":"SD",
    "sg:tags":[
        "property",
        "lessor"
    ],
    "wof:name":"Harry Whitfield",
    "wof:placetype":"venue"
},
  "geometry": {"coordinates":[-98.13649,46.225982],"type":"Point"}
}