{
  "type": "Feature",
  "properties": {
    "addr:full":"49600 422nd Ave NW Kenmare ND 58746",
    "addr:housenumber":"49600",
    "addr:postcode":"58746",
    "addr:street":"422Nd Ave Nw",
    "iso:country":"US",
    "sg:address":"49600 422nd Ave NW",
    "sg:city":"Kenmare",
    "sg:classifiers":[
        {
            "category":"Utilities",
            "subcategory":"Electric",
            "type":"Services"
        }
    ],
    "sg:phone":"+1 701 385 4804",
    "sg:postcode":"58746",
    "sg:province":"ND",
    "sg:tags":[
        "company"
    ],
    "wof:name":"Burke-Divide Electric Coop",
    "wof:placetype":"venue"
},
  "geometry": {"coordinates":[-102.064323,48.676714],"type":"Point"}
}