{
  "type": "Feature",
  "properties": {
    "iso:country":"US",
    "sg:address":"3902 13th Ave S",
    "sg:city":"Fargo",
    "sg:classifiers":[
        {
            "category":"Personal",
            "subcategory":"Massage",
            "type":"Services"
        }
    ],
    "sg:phone":"+1 701 277 8311",
    "sg:postcode":"58103",
    "sg:province":"ND",
    "wof:name":"Ron's Aqua Massage",
    "wof:placetype":"venue"
},
  "geometry": {"coordinates":[-96.84670300000001,46.861535],"type":"Point"}
}