{
  "type": "Feature",
  "properties": {
    "iso:country":"US",
    "sg:address":"6315 15th St N",
    "sg:city":"Fargo",
    "sg:classifiers":[
        {
            "category":"Building & Trades",
            "subcategory":"Electrical",
            "type":"Services"
        }
    ],
    "sg:phone":"+1 701 234 9105",
    "sg:postcode":"58102",
    "sg:province":"ND",
    "sg:tags":[
        "electrical",
        "contractor"
    ],
    "wof:name":"Houska Electric Inc",
    "wof:placetype":"venue"
},
  "geometry": {"coordinates":[-96.804829,46.961724],"type":"Point"}
}