{
  "type": "Feature",
  "properties": {
    "addr:full":"4498 Hwy 6 Mandan ND 58554",
    "addr:housenumber":"4498",
    "addr:postcode":"58554",
    "addr:street":"Hwy 6",
    "iso:country":"US",
    "sg:address":"4498 Hwy 6",
    "sg:city":"Mandan",
    "sg:classifiers":[
        {
            "category":"Farming",
            "subcategory":"Farm & Veterinary Services",
            "type":"Manufacturing & Wholesale Goods"
        }
    ],
    "sg:phone":"+1 701 667 0156",
    "sg:postcode":"58554",
    "sg:province":"ND",
    "sg:tags":[
        "aerial",
        "applicator"
    ],
    "wof:name":"Sprayers Inc",
    "wof:placetype":"venue"
},
  "geometry": {"coordinates":[-100.901494,46.767475],"type":"Point"}
}