{
  "type": "Feature",
  "properties": {
    "iso:country":"US",
    "sg:address":"2222 7th Ave N",
    "sg:city":"Fargo",
    "sg:classifiers":[
        {
            "category":"Wholesale",
            "subcategory":"Construction Materials",
            "type":"Manufacturing & Wholesale Goods"
        }
    ],
    "sg:phone":"+1 701 277 1544",
    "sg:postcode":"58102",
    "sg:province":"ND",
    "sg:tags":[
        "product",
        "ceiling",
        "system"
    ],
    "wof:name":"Reinke Wholesale North Dakota",
    "wof:placetype":"venue"
},
  "geometry": {"coordinates":[-96.81577,46.883105],"type":"Point"}
}