{
  "type": "Feature",
  "properties": {
    "iso:country":"US",
    "sg:address":"2300 E Main Ave",
    "sg:city":"Bismarck",
    "sg:classifiers":[
        {
            "category":"Utilities",
            "subcategory":"Fuel Oil & Lpg",
            "type":"Services"
        }
    ],
    "sg:phone":"+1 701 223 1262",
    "sg:postcode":"58501",
    "sg:province":"ND",
    "sg:tags":[
        "liquefied",
        "gas",
        "petroleum"
    ],
    "wof:name":"Ferrellgas",
    "wof:placetype":"venue"
},
  "geometry": {"coordinates":[-100.76095100000001,46.805227],"type":"Point"}
}