{
  "type": "Feature",
  "properties": {
    "iso:country":"US",
    "sg:address":"21202 111th St SE",
    "sg:city":"Sawyer",
    "sg:phone":"+1 701 624 5791",
    "sg:postcode":"58781",
    "sg:province":"ND",
    "sg:tags":[
        "farm",
        "grain",
        "cash"
    ],
    "wof:name":"Phyllis Bailey",
    "wof:placetype":"venue"
},
  "geometry": {"coordinates":[-101.12148000000001,48.010776],"type":"Point"}
}