{
  "type": "Feature",
  "properties": {
    "iso:country":"US",
    "sg:address":"2741 Leahy Ave",
    "sg:city":"Fargo",
    "sg:classifiers":[
        {
            "category":"Building & Trades",
            "subcategory":"Construction",
            "type":"Services"
        }
    ],
    "sg:phone":"+1 701 232 6821",
    "sg:postcode":"58103",
    "sg:province":"ND",
    "sg:tags":[
        "dry wall",
        "contractor"
    ],
    "wof:name":"G & M Lathing Contractors Inc",
    "wof:placetype":"venue"
},
  "geometry": {"coordinates":[-96.82225699999999,46.871482],"type":"Point"}
}