{
  "type": "Feature",
  "properties": {
    "iso:country":"US",
    "sg:address":"4320 Main St",
    "sg:city":"Williston",
    "sg:classifiers":[
        {
            "category":"Building & Trades",
            "subcategory":"Construction",
            "type":"Services"
        }
    ],
    "sg:phone":"+1 701 572 2086",
    "sg:postcode":"58801",
    "sg:province":"ND",
    "sg:tags":[
        "general",
        "contractor"
    ],
    "wof:name":"Goebel Construction",
    "wof:placetype":"venue"
},
  "geometry": {"coordinates":[-103.62267300000001,48.184885],"type":"Point"}
}