{
  "type": "Feature",
  "properties": {
    "iso:country":"US",
    "sg:address":"521 5th Ave",
    "sg:city":"Cando",
    "sg:classifiers":[
        {
            "category":"Sports & Exercise",
            "subcategory":"Bowling",
            "type":"Entertainment"
        }
    ],
    "sg:phone":"+1 701 968 4542",
    "sg:postcode":"58324",
    "sg:province":"ND",
    "sg:tags":[
        "tape",
        "video",
        "rental",
        "center"
    ],
    "wof:name":"Wilderness Lanes",
    "wof:placetype":"venue"
},
  "geometry": {"coordinates":[-99.20358299999999,48.489673],"type":"Point"}
}