{
  "type": "Feature",
  "properties": {
    "iso:country":"US",
    "sg:address":"12400 72nd St SW",
    "sg:city":"Minot",
    "sg:phone":"+1 701 722 3349",
    "sg:postcode":"58701",
    "sg:province":"ND",
    "sg:tags":[
        "farm",
        "wheat",
        "grain",
        "cash"
    ],
    "wof:name":"Laverne Mikkelson",
    "wof:placetype":"venue"
},
  "geometry": {"coordinates":[-101.403914,48.106818],"type":"Point"}
}