{
  "type": "Feature",
  "properties": {
    "iso:country":"US",
    "sg:address":"605 Stanford Rd",
    "sg:city":"Grand Forks",
    "sg:classifiers":[
        {
            "category":"Education",
            "subcategory":"School",
            "type":"Public Place"
        }
    ],
    "sg:phone":"+1 701 746 2275",
    "sg:postcode":"58203",
    "sg:province":"ND",
    "wof:name":"Lake Agassiz Elementary School",
    "wof:placetype":"venue"
},
  "geometry": {"coordinates":[-97.08114,47.926742],"type":"Point"}
}