{
  "type": "Feature",
  "properties": {
    "addr:full":"4141 38th St S Fargo ND 58104",
    "addr:housenumber":"4141",
    "addr:postcode":"58104",
    "addr:street":"38Th St S",
    "iso:country":"US",
    "sg:address":"4141 38th St S",
    "sg:city":"Fargo",
    "sg:classifiers":[
        {
            "category":"Wholesale",
            "subcategory":"Electrical",
            "type":"Manufacturing & Wholesale Goods"
        }
    ],
    "sg:phone":"+1 701 281 2595",
    "sg:postcode":"58104",
    "sg:province":"ND",
    "sg:tags":[
        "operated",
        "telephone",
        "card"
    ],
    "wof:name":"Gerlach Enterprises",
    "wof:placetype":"venue"
},
  "geometry": {"coordinates":[-96.84032999999999,46.815544],"type":"Point"}
}