{
  "type": "Feature",
  "properties": {
    "iso:country":"US",
    "sg:address":"507 S 8th St",
    "sg:city":"Bismarck",
    "sg:classifiers":[
        {
            "category":"Real Estate",
            "subcategory":"Real Estate Operator",
            "type":"Services"
        }
    ],
    "sg:phone":"+1 701 258 6205",
    "sg:postcode":"58504",
    "sg:province":"ND",
    "sg:tags":[
        "mobile",
        "home",
        "community"
    ],
    "wof:name":"Civic Mobile Home Park",
    "wof:placetype":"venue"
},
  "geometry": {"coordinates":[-100.780202,46.797956],"type":"Point"}
}