{
  "type": "Feature",
  "properties": {
    "iso:country":"US",
    "sg:address":"630 May Ave",
    "sg:city":"Page",
    "sg:classifiers":[
        {
            "category":"Education",
            "subcategory":"School",
            "type":"Public Place"
        }
    ],
    "sg:phone":"+1 701 668 2520",
    "sg:postcode":"58064",
    "sg:province":"ND",
    "wof:name":"Page Public School",
    "wof:placetype":"venue"
},
  "geometry": {"coordinates":[-97.569858,47.160632],"type":"Point"}
}