{
  "type": "Feature",
  "properties": {
    "iso:country":"US",
    "sg:address":"2524 Hillview Ave",
    "sg:city":"Bismarck",
    "sg:classifiers":[
        {
            "category":"Building & Trades",
            "subcategory":"Construction",
            "type":"Services"
        }
    ],
    "sg:phone":"+1 701 223 1801",
    "sg:postcode":"58501",
    "sg:province":"ND",
    "sg:tags":[
        "hanging",
        "contractor"
    ],
    "wof:name":"Mische Painting LLP",
    "wof:placetype":"venue"
},
  "geometry": {"coordinates":[-100.756694,46.817802],"type":"Point"}
}