{
  "type": "Feature",
  "properties": {
    "iso:country":"US",
    "sg:address":"1421 2nd Ave SW",
    "sg:city":"Minot",
    "sg:classifiers":[
        {
            "category":"Social Services",
            "subcategory":"Adult Care",
            "type":"Services"
        }
    ],
    "sg:phone":"+1 701 859 9800",
    "sg:postcode":"58701",
    "sg:province":"ND",
    "sg:tags":[
        "home",
        "residential"
    ],
    "wof:name":"Wellington Assisted Living",
    "wof:placetype":"venue"
},
  "geometry": {"coordinates":[-101.314514,48.234285],"type":"Point"}
}