{
  "type": "Feature",
  "properties": {
    "iso:country":"US",
    "sg:address":"14 2nd St W",
    "sg:city":"Williston",
    "sg:classifiers":[
        {
            "category":"Food & Beverages",
            "subcategory":"Liquor & Beverages",
            "type":"Retail Goods"
        }
    ],
    "sg:phone":"+1 701 572 2591",
    "sg:postcode":"58801",
    "sg:province":"ND",
    "wof:name":"J R's Grape N Grain",
    "wof:placetype":"venue"
},
  "geometry": {"coordinates":[-103.622299,48.145541],"type":"Point"}
}