{
  "type": "Feature",
  "properties": {
    "addr:full":"322 Main St Williston ND 58801",
    "addr:housenumber":"322",
    "addr:postcode":"58801",
    "addr:street":"Main St",
    "iso:country":"US",
    "sg:address":"322 Main St",
    "sg:city":"Williston",
    "sg:classifiers":[
        {
            "category":"Banks & Credit Unions",
            "subcategory":"Investment Brokerage",
            "type":"Services"
        }
    ],
    "sg:phone":"+1 701 572 4527",
    "sg:postcode":"58801",
    "sg:province":"ND",
    "sg:tags":[
        "stock",
        "bond"
    ],
    "wof:name":"Miller Johnson Steichen",
    "wof:placetype":"venue"
},
  "geometry": {"coordinates":[-103.62176700000001,48.146779],"type":"Point"}
}