{
  "type": "Feature",
  "properties": {
    "iso:country":"US",
    "sg:address":"130 7th Ave W",
    "sg:city":"Dickinson",
    "sg:classifiers":[
        {
            "category":"Professional",
            "subcategory":"Management & Consulting",
            "type":"Services"
        }
    ],
    "sg:phone":"+1 701 225 4703",
    "sg:postcode":"58601",
    "sg:province":"ND",
    "sg:tags":[
        "business"
    ],
    "wof:name":"Dln Consulting Inc",
    "wof:placetype":"venue"
},
  "geometry": {"coordinates":[-102.795599,46.88082],"type":"Point"}
}