{
  "type": "Feature",
  "properties": {
    "iso:country":"US",
    "sg:address":"676 Santa Cruz Dr",
    "sg:city":"Fargo",
    "sg:classifiers":[
        {
            "category":"Home & Garden",
            "subcategory":"Carpets & Floor Coverings",
            "type":"Retail Goods"
        }
    ],
    "sg:phone":"+1 701 282 9691",
    "sg:postcode":"58103",
    "sg:province":"ND",
    "wof:name":"Dyenamic Carpet Clg & Dye Co",
    "wof:placetype":"venue"
},
  "geometry": {"coordinates":[-96.85433399999999,46.86962],"type":"Point"}
}