{
  "type": "Feature",
  "properties": {
    "iso:country":"US",
    "sg:address":"635 1st Ave N",
    "sg:city":"Fargo",
    "sg:classifiers":[
        {
            "category":"Professional",
            "type":"Services"
        }
    ],
    "sg:phone":"+1 701 235 4902",
    "sg:postcode":"58102",
    "sg:province":"ND",
    "sg:tags":[
        "establishment"
    ],
    "wof:name":"C Lizzy's",
    "wof:placetype":"venue"
},
  "geometry": {"coordinates":[-96.789584,46.877007],"type":"Point"}
}