{
  "type": "Feature",
  "properties": {
    "iso:country":"US",
    "sg:address":"3140 33rd St SW",
    "sg:city":"Fargo",
    "sg:classifiers":[
        {
            "category":"Building & Trades",
            "subcategory":"Construction",
            "type":"Services"
        }
    ],
    "sg:phone":"+1 701 232 8883",
    "sg:postcode":"58103",
    "sg:province":"ND",
    "sg:tags":[
        "downspouts",
        "gutter"
    ],
    "wof:name":"Dakota Raingutter Inc",
    "wof:placetype":"venue"
},
  "geometry": {"coordinates":[-96.83290700000001,46.835422],"type":"Point"}
}