{
  "type": "Feature",
  "properties": {
    "addr:full":"2025 6th St NW Minot ND 58703",
    "addr:housenumber":"2025",
    "addr:postcode":"58703",
    "addr:street":"6Th St Nw",
    "iso:country":"US",
    "sg:address":"2025 6th St NW",
    "sg:city":"Minot",
    "sg:classifiers":[
        {
            "category":"Building & Trades",
            "subcategory":"Landscaping Services",
            "type":"Services"
        }
    ],
    "sg:phone":"+1 701 838 7753",
    "sg:postcode":"58703",
    "sg:province":"ND",
    "sg:tags":[
        "lawn",
        "maintenance",
        "grounds"
    ],
    "wof:name":"Whorley's Maintenance Svc",
    "wof:placetype":"venue"
},
  "geometry": {"coordinates":[-101.30373899999999,48.25794],"type":"Point"}
}