{
  "type": "Feature",
  "properties": {
    "iso:country":"US",
    "sg:address":"6714 98th St NE",
    "sg:city":"Rocklake",
    "sg:phone":"+1 701 266 5443",
    "sg:postcode":"58365",
    "sg:province":"ND",
    "sg:tags":[
        "farm",
        "wheat"
    ],
    "wof:name":"Pat Broderic",
    "wof:placetype":"venue"
},
  "geometry": {"coordinates":[-99.242407,48.834004],"type":"Point"}
}