{
  "type": "Feature",
  "properties": {
    "addr:full":"2811 Knight Dr Grand Forks ND 58201",
    "addr:housenumber":"2811",
    "addr:postcode":"58201",
    "addr:street":"Knight Dr",
    "iso:country":"US",
    "sg:address":"2811 Knight Dr",
    "sg:city":"Grand Forks",
    "sg:classifiers":[
        {
            "category":"Building & Trades",
            "subcategory":"Construction",
            "type":"Services"
        }
    ],
    "sg:phone":"+1 701 741 0729",
    "sg:postcode":"58201",
    "sg:province":"ND",
    "sg:tags":[
        "painter"
    ],
    "wof:name":"Dave's Palette Pro Painting",
    "wof:placetype":"venue"
},
  "geometry": {"coordinates":[-97.06997800000001,47.906128],"type":"Point"}
}