{
  "type": "Feature",
  "properties": {
    "iso:country":"US",
    "sg:address":"513 1st Ave E",
    "sg:city":"West Fargo",
    "sg:classifiers":[
        {
            "category":"Professional",
            "subcategory":"Advertising",
            "type":"Services"
        }
    ],
    "sg:phone":"+1 701 492 7317",
    "sg:postcode":"58078",
    "sg:province":"ND",
    "sg:tags":[
        "counselor"
    ],
    "wof:name":"Koppelmann & Assoc",
    "wof:placetype":"venue"
},
  "geometry": {"coordinates":[-96.889899,46.875437],"type":"Point"}
}