{
  "type": "Feature",
  "properties": {
    "iso:country":"US",
    "sg:address":"4000 13th Ave S",
    "sg:city":"Fargo",
    "sg:classifiers":[
        {
            "category":"Restaurant",
            "type":"Food & Drink"
        }
    ],
    "sg:menulink":"http://www.allmenus.com/nd/fargo/110364-chilis/menu/",
    "sg:phone":"+1 701 282 2669",
    "sg:postcode":"58103",
    "sg:province":"ND",
    "sg:tags":[
        "burger",
        "american",
        "sandwich",
        "tex-mex",
        "soup"
    ],
    "wof:name":"Chili's",
    "wof:placetype":"venue"
},
  "geometry": {"coordinates":[-96.84886899999999,46.861236],"type":"Point"}
}