{
  "type": "Feature",
  "properties": {
    "iso:country":"US",
    "sg:address":"201 Veitch St",
    "sg:city":"Emerado",
    "sg:classifiers":[
        {
            "category":"Ice Cream",
            "type":"Food & Drink"
        }
    ],
    "sg:menulink":"http://www.allmenus.com/nd/chester/167700-dairy-queen/menu/",
    "sg:phone":"+1 701 594 4021",
    "sg:postcode":"58228",
    "sg:province":"ND",
    "sg:tags":[
        "burger",
        "american"
    ],
    "wof:name":"Dairy Queen",
    "wof:placetype":"venue"
},
  "geometry": {"coordinates":[-97.364473,47.924738],"type":"Point"}
}