{
  "type": "Feature",
  "properties": {
    "iso:country":"US",
    "sg:address":"7510 Red River Rd",
    "sg:city":"Wahpeton",
    "sg:classifiers":[
        {
            "category":"Manufacturing",
            "subcategory":"Tools & Machinery",
            "type":"Manufacturing & Wholesale Goods"
        }
    ],
    "sg:phone":"+1 701 642 2949",
    "sg:postcode":"58075",
    "sg:province":"ND",
    "sg:tags":[
        "machine",
        "shop"
    ],
    "wof:name":"DMC Precision Machining LLC",
    "wof:placetype":"venue"
},
  "geometry": {"coordinates":[-96.611289,46.324251],"type":"Point"}
}