{
  "type": "Feature",
  "properties": {
    "iso:country":"US",
    "sg:address":"11710 40th St SW",
    "sg:city":"Dickinson",
    "sg:classifiers":[
        {
            "category":"Professional",
            "subcategory":"Business Services",
            "type":"Services"
        }
    ],
    "sg:phone":"+1 701 225 5417",
    "sg:postcode":"58601",
    "sg:province":"ND",
    "wof:name":"J&P Praus Auction Service LLC",
    "wof:placetype":"venue"
},
  "geometry": {"coordinates":[-102.91978899999999,46.830746],"type":"Point"}
}