{
  "type": "Feature",
  "properties": {
    "addr:full":"667 Demers Ave Grand Forks ND 58201",
    "addr:housenumber":"667",
    "addr:postcode":"58201",
    "addr:street":"Demers Ave",
    "iso:country":"US",
    "sg:address":"667 Demers Ave",
    "sg:city":"Grand Forks",
    "sg:classifiers":[
        {
            "category":"Real Estate",
            "subcategory":"Real Estate Operator",
            "type":"Services"
        }
    ],
    "sg:phone":"+1 701 746 1439",
    "sg:postcode":"58201",
    "sg:province":"ND",
    "sg:tags":[
        "building",
        "nonresidential"
    ],
    "wof:name":"Depot Investors",
    "wof:placetype":"venue"
},
  "geometry": {"coordinates":[-97.034369,47.922522],"type":"Point"}
}