{
  "type": "Feature",
  "properties": {
    "iso:country":"US",
    "sg:address":"1219 10th St",
    "sg:city":"Langdon",
    "sg:classifiers":[
        {
            "category":"Freight",
            "type":"Transportation"
        }
    ],
    "sg:phone":"+1 701 256 3420",
    "sg:postcode":"58249",
    "sg:province":"ND",
    "sg:tags":[
        "operator",
        "local",
        "trucking"
    ],
    "wof:name":"Ronald Downs",
    "wof:placetype":"venue"
},
  "geometry": {"coordinates":[-98.37903300000001,48.765746],"type":"Point"}
}