{
  "type": "Feature",
  "properties": {
    "addr:full":"5577 143rd Ave SE Sheldon ND 58068",
    "addr:housenumber":"5577",
    "addr:postcode":"58068",
    "addr:street":"143Rd Ave Se",
    "iso:country":"US",
    "sg:address":"5577 143rd Ave SE",
    "sg:city":"Sheldon",
    "sg:classifiers":[
        {
            "category":"Farming",
            "subcategory":"Farm",
            "type":"Manufacturing & Wholesale Goods"
        }
    ],
    "sg:phone":"+1 701 882 3265",
    "sg:postcode":"58068",
    "sg:province":"ND",
    "wof:name":"Halvorson Farms",
    "wof:placetype":"venue"
},
  "geometry": {"coordinates":[-97.427514,46.604583],"type":"Point"}
}