{
  "type": "Feature",
  "properties": {
    "addr:full":"1205 E Bismarck Expy Bismarck ND 58504",
    "addr:housenumber":"1205",
    "addr:postcode":"58504",
    "addr:street":"E Bismarck Expy",
    "iso:country":"US",
    "sg:address":"1205 E Bismarck Expy",
    "sg:city":"Bismarck",
    "sg:classifiers":[
        {
            "category":"Professional",
            "subcategory":"Accounting & Tax Preparation",
            "type":"Services"
        }
    ],
    "sg:phone":"+1 701 223 9666",
    "sg:postcode":"58504",
    "sg:province":"ND",
    "sg:tags":[
        "return",
        "filing"
    ],
    "wof:name":"H & R Block Tax Svc",
    "wof:placetype":"venue"
},
  "geometry": {"coordinates":[-100.768625,46.794566],"type":"Point"}
}