{
  "type": "Feature",
  "properties": {
    "iso:country":"US",
    "sg:address":"9077 53rd St NE",
    "sg:city":"Devils Lake",
    "sg:classifiers":[
        {
            "category":"Freight",
            "type":"Transportation"
        }
    ],
    "sg:phone":"+1 701 398 3863",
    "sg:postcode":"58301",
    "sg:province":"ND",
    "sg:tags":[
        "operator",
        "local",
        "trucking"
    ],
    "wof:name":"Deplazes Trucking",
    "wof:placetype":"venue"
},
  "geometry": {"coordinates":[-98.662014,48.180403],"type":"Point"}
}