{
  "type": "Feature",
  "properties": {
    "iso:country":"US",
    "sg:address":"6310 State Hwy 35",
    "sg:city":"Adams",
    "sg:classifiers":[
        {
            "category":"Professional",
            "subcategory":"Business Services",
            "type":"Services"
        }
    ],
    "sg:phone":"+1 701 944 2536",
    "sg:postcode":"58210",
    "sg:province":"ND",
    "wof:name":"Highway 35 Cstm Design Grading",
    "wof:placetype":"venue"
},
  "geometry": {"coordinates":[-98.11979599999999,48.325112],"type":"Point"}
}