{
  "type": "Feature",
  "properties": {
    "addr:full":"302 E Villard St Dickinson ND 58601",
    "addr:housenumber":"302",
    "addr:postcode":"58601",
    "addr:street":"E Villard St",
    "iso:country":"US",
    "sg:address":"302 E Villard St",
    "sg:city":"Dickinson",
    "sg:classifiers":[
        {
            "category":"Retail",
            "subcategory":"Auto Repair",
            "type":"Services"
        }
    ],
    "sg:phone":"+1 701 483 2886",
    "sg:postcode":"58601",
    "sg:province":"ND",
    "sg:tags":[
        "general"
    ],
    "wof:name":"Chads Automotive Clinic",
    "wof:placetype":"venue"
},
  "geometry": {"coordinates":[-102.780511,46.878262],"type":"Point"}
}