{
  "type": "Feature",
  "properties": {
    "iso:country":"US",
    "sg:address":"10728 15th St NE",
    "sg:city":"Binford",
    "sg:classifiers":[
        {
            "category":"Farming",
            "subcategory":"Farm",
            "type":"Manufacturing & Wholesale Goods"
        }
    ],
    "sg:phone":"+1 701 676 2857",
    "sg:postcode":"58416",
    "sg:province":"ND",
    "wof:name":"Donald Ronningen Farm",
    "wof:placetype":"venue"
},
  "geometry": {"coordinates":[-98.261087,47.630609],"type":"Point"}
}