{
  "type": "Feature",
  "properties": {
    "iso:country":"US",
    "sg:address":"304 Central Ave N",
    "sg:city":"Valley City",
    "sg:classifiers":[
        {
            "category":"Shopping",
            "subcategory":"Florist",
            "type":"Retail Goods"
        }
    ],
    "sg:phone":"+1 701 845 3881",
    "sg:postcode":"58072",
    "sg:province":"ND",
    "wof:name":"Bettin's Flower Shop",
    "wof:placetype":"venue"
},
  "geometry": {"coordinates":[-98.003067,46.926254],"type":"Point"}
}