{
  "type": "Feature",
  "properties": {
    "addr:full":"2401 13th Ave S Fargo ND 58103",
    "addr:housenumber":"2401",
    "addr:postcode":"58103",
    "addr:street":"13Th Ave S",
    "iso:country":"US",
    "sg:address":"2401 13th Ave S",
    "sg:city":"Fargo",
    "sg:classifiers":[
        {
            "category":"Shopping",
            "subcategory":"Pharmacy",
            "type":"Retail Goods"
        }
    ],
    "sg:phone":"+1 701 232 4872",
    "sg:postcode":"58103",
    "sg:province":"ND",
    "sg:website":"www.albertsons.com",
    "wof:name":"Osco Drug",
    "wof:placetype":"venue"
},
  "geometry": {"coordinates":[-96.81815400000001,46.86164],"type":"Point"}
}