{
  "type": "Feature",
  "properties": {
    "iso:country":"US",
    "sg:address":"62 Main Ave S",
    "sg:city":"Fessenden",
    "sg:classifiers":[
        {
            "category":"Professional",
            "subcategory":"Accounting & Tax Preparation",
            "type":"Services"
        }
    ],
    "sg:phone":"+1 701 547 3369",
    "sg:postcode":"58438",
    "sg:province":"ND",
    "sg:tags":[
        "return",
        "filing"
    ],
    "wof:name":"Houchin Tax Svc & Bookkeeping",
    "wof:placetype":"venue"
},
  "geometry": {"coordinates":[-99.62974800000001,47.648618],"type":"Point"}
}