{
  "type": "Feature",
  "properties": {
    "iso:country":"US",
    "sg:address":"418 E Rosser Ave",
    "sg:city":"Bismarck",
    "sg:classifiers":[
        {
            "category":"Professional",
            "subcategory":"Lawyer & Legal Services",
            "type":"Services"
        }
    ],
    "sg:phone":"+1 701 222 0903",
    "sg:postcode":"58501",
    "sg:province":"ND",
    "sg:tags":[
        "attorney"
    ],
    "wof:name":"Thomas J Glass Attorney",
    "wof:placetype":"venue"
},
  "geometry": {"coordinates":[-100.784752,46.808637],"type":"Point"}
}