{
  "type": "Feature",
  "properties": {
    "addr:full":"3100 S Columbia Rd Grand Forks ND 58201",
    "addr:housenumber":"3100",
    "addr:postcode":"58201",
    "addr:street":"S Columbia Rd",
    "iso:country":"US",
    "sg:address":"3100 S Columbia Rd",
    "sg:city":"Grand Forks",
    "sg:classifiers":[
        {
            "category":"Banks & Credit Unions",
            "subcategory":"Bank",
            "type":"Services"
        }
    ],
    "sg:phone":"+1 701 795 4500",
    "sg:postcode":"58201",
    "sg:province":"ND",
    "sg:website":"www.bremer.com",
    "wof:name":"Bremer Bank",
    "wof:placetype":"venue"
},
  "geometry": {"coordinates":[-97.06675799999999,47.891501],"type":"Point"}
}