{
  "type": "Feature",
  "properties": {
    "iso:country":"US",
    "sg:address":"150 W 14th St",
    "sg:city":"Grafton",
    "sg:classifiers":[
        {
            "category":"Professional",
            "subcategory":"Accounting & Tax Preparation",
            "type":"Services"
        }
    ],
    "sg:phone":"+1 701 352 2004",
    "sg:postcode":"58237",
    "sg:province":"ND",
    "sg:tags":[
        "accountant"
    ],
    "wof:name":"James L Bowen CPA",
    "wof:placetype":"venue"
},
  "geometry": {"coordinates":[-97.413511,48.410458],"type":"Point"}
}