{
  "type": "Feature",
  "properties": {
    "iso:country":"US",
    "sg:address":"554 4th St SE",
    "sg:city":"Mayville",
    "sg:phone":"+1 701 786 9076",
    "sg:postcode":"58257",
    "sg:province":"ND",
    "sg:tags":[
        "farm",
        "grain",
        "cash"
    ],
    "wof:name":"Bradley Vaagene",
    "wof:placetype":"venue"
},
  "geometry": {"coordinates":[-97.31791200000001,47.497135],"type":"Point"}
}