{
  "type": "Feature",
  "properties": {
    "iso:country":"US",
    "sg:address":"311 1st Ave S",
    "sg:city":"Jamestown",
    "sg:classifiers":[
        {
            "category":"Professional",
            "subcategory":"Lawyer & Legal Services",
            "type":"Services"
        }
    ],
    "sg:phone":"+1 701 251 1486",
    "sg:postcode":"58401",
    "sg:province":"ND",
    "sg:tags":[
        "attorney"
    ],
    "wof:name":"Glen R Nagel",
    "wof:placetype":"venue"
},
  "geometry": {"coordinates":[-98.70832799999999,46.906224],"type":"Point"}
}