{
  "type": "Feature",
  "properties": {
    "iso:country":"US",
    "sg:address":"2415 3rd St NW",
    "sg:city":"Underwood",
    "sg:classifiers":[
        {
            "category":"Real Estate",
            "subcategory":"Real Estate Operator",
            "type":"Services"
        }
    ],
    "sg:phone":"+1 701 442 3560",
    "sg:postcode":"58576",
    "sg:province":"ND",
    "sg:tags":[
        "property",
        "lessor"
    ],
    "wof:name":"Mautz Gary Farm of",
    "wof:placetype":"venue"
},
  "geometry": {"coordinates":[-101.08495000000001,47.458539],"type":"Point"}
}