{
  "type": "Feature",
  "properties": {
    "iso:country":"US",
    "sg:address":"810 E Rosser Ave",
    "sg:city":"Bismarck",
    "sg:classifiers":[
        {
            "category":"Health Services",
            "subcategory":"Doctor",
            "type":"Services"
        }
    ],
    "sg:phone":"+1 701 530 7246",
    "sg:postcode":"58501",
    "sg:province":"ND",
    "sg:tags":[
        "physician",
        "surgeon"
    ],
    "wof:name":"Primecare Pain Clinic",
    "wof:placetype":"venue"
},
  "geometry": {"coordinates":[-100.778593,46.808559],"type":"Point"}
}