{
  "type": "Feature",
  "properties": {
    "addr:full":"4637 Trenton Dr Bismarck ND 58503",
    "addr:housenumber":"4637",
    "addr:postcode":"58503",
    "addr:street":"Trenton Dr",
    "iso:country":"US",
    "sg:address":"4637 Trenton Dr",
    "sg:city":"Bismarck",
    "sg:classifiers":[
        {
            "category":"Freight",
            "type":"Transportation"
        }
    ],
    "sg:phone":"+1 701 223 2638",
    "sg:postcode":"58503",
    "sg:province":"ND",
    "sg:tags":[
        "trucking"
    ],
    "wof:name":"Rakar Transport",
    "wof:placetype":"venue"
},
  "geometry": {"coordinates":[-100.719674,46.833326],"type":"Point"}
}