{
  "type": "Feature",
  "properties": {
    "iso:country":"US",
    "sg:address":"123 2nd Ave SE",
    "sg:city":"Minot",
    "sg:classifiers":[
        {
            "category":"Social Services",
            "subcategory":"Child Care",
            "type":"Services"
        }
    ],
    "sg:phone":"+1 701 852 5591",
    "sg:postcode":"58701",
    "sg:province":"ND",
    "wof:name":"St Leo's Child Care Ctr",
    "wof:placetype":"venue"
},
  "geometry": {"coordinates":[-101.290221,48.234527],"type":"Point"}
}