{
  "type": "Feature",
  "properties": {
    "addr:full":"201 37th Ave SW Minot ND 58701",
    "addr:housenumber":"201",
    "addr:postcode":"58701",
    "addr:street":"37Th Ave Sw",
    "iso:country":"US",
    "sg:address":"201 37th Ave SW",
    "sg:city":"Minot",
    "sg:classifiers":[
        {
            "category":"Bars & Pubs",
            "type":"Food & Drink"
        }
    ],
    "sg:phone":"+1 701 838 4033",
    "sg:postcode":"58701",
    "sg:province":"ND",
    "wof:name":"Pour Farm",
    "wof:placetype":"venue"
},
  "geometry": {"coordinates":[-101.296784,48.196557],"type":"Point"}
}