{
  "type": "Feature",
  "properties": {
    "addr:full":"5832 40th Ave SE Napoleon ND 58561",
    "addr:housenumber":"5832",
    "addr:postcode":"58561",
    "addr:street":"40Th Ave Se",
    "iso:country":"US",
    "sg:address":"5832 40th Ave SE",
    "sg:city":"Napoleon",
    "sg:classifiers":[
        {
            "category":"Real Estate",
            "subcategory":"Real Estate Operator",
            "type":"Services"
        }
    ],
    "sg:phone":"+1 701 754 2568",
    "sg:postcode":"58561",
    "sg:province":"ND",
    "sg:tags":[
        "property",
        "lessor"
    ],
    "wof:name":"Emil Dewald Farm",
    "wof:placetype":"venue"
},
  "geometry": {"coordinates":[-99.58031,46.569793],"type":"Point"}
}