{
  "type": "Feature",
  "properties": {
    "iso:country":"US",
    "sg:address":"310 E Thayer Ave",
    "sg:city":"Bismarck",
    "sg:classifiers":[
        {
            "category":"Shopping",
            "type":"Retail Goods"
        }
    ],
    "sg:phone":"+1 701 223 0938",
    "sg:postcode":"58501",
    "sg:province":"ND",
    "sg:tags":[
        "lock",
        "safe",
        "sales",
        "key"
    ],
    "wof:name":"Warrens Locks & Keys Inc",
    "wof:placetype":"venue"
},
  "geometry": {"coordinates":[-100.78621,46.807629],"type":"Point"}
}