{
  "type": "Feature",
  "properties": {
    "iso:country":"US",
    "sg:address":"1001 2nd St NE",
    "sg:city":"Fessenden",
    "sg:classifiers":[
        {
            "category":"Travel",
            "subcategory":"Hotels & Motels",
            "type":"Entertainment"
        }
    ],
    "sg:phone":"+1 701 547 3411",
    "sg:postcode":"58438",
    "sg:province":"ND",
    "sg:tags":[
        "breakfast",
        "accommodation",
        "bed"
    ],
    "wof:name":"Bed & Breakfast",
    "wof:placetype":"venue"
},
  "geometry": {"coordinates":[-99.621751,47.648814],"type":"Point"}
}