{
  "type": "Feature",
  "properties": {
    "iso:country":"US",
    "sg:address":"3967 20th St NW",
    "sg:city":"Garrison",
    "sg:phone":"+1 701 337 5413",
    "sg:postcode":"58540",
    "sg:province":"ND",
    "sg:tags":[
        "farm",
        "corn"
    ],
    "wof:name":"Nottom Brothers",
    "wof:placetype":"venue"
},
  "geometry": {"coordinates":[-101.437,47.703182],"type":"Point"}
}