{
  "type": "Feature",
  "properties": {
    "addr:full":"1301 E Main Ave Bismarck ND 58501",
    "addr:housenumber":"1301",
    "addr:postcode":"58501",
    "addr:street":"E Main Ave",
    "iso:country":"US",
    "sg:address":"1301 E Main Ave",
    "sg:city":"Bismarck",
    "sg:classifiers":[
        {
            "category":"Farming",
            "subcategory":"Dairy Farm",
            "type":"Manufacturing & Wholesale Goods"
        }
    ],
    "sg:phone":"+1 701 223 3180",
    "sg:postcode":"58501",
    "sg:province":"ND",
    "sg:website":"www.deanfoods.com",
    "wof:name":"Dean Foods-Land O'Lakes",
    "wof:placetype":"venue"
},
  "geometry": {"coordinates":[-100.767473,46.805156],"type":"Point"}
}