{
  "type": "Feature",
  "properties": {
    "iso:country":"US",
    "sg:address":"216 Main St",
    "sg:city":"Harwood",
    "sg:classifiers":[
        {
            "category":"Building & Trades",
            "subcategory":"Landscaping Services",
            "type":"Services"
        }
    ],
    "sg:phone":"+1 701 281 1208",
    "sg:postcode":"58042",
    "sg:province":"ND",
    "sg:tags":[
        "landscape"
    ],
    "wof:name":"Signature Landscapes",
    "wof:placetype":"venue"
},
  "geometry": {"coordinates":[-96.88072699999999,46.979147],"type":"Point"}
}