{
  "type": "Feature",
  "properties": {
    "iso:country":"US",
    "sg:address":"189 4th St SW",
    "sg:city":"Garrison",
    "sg:classifiers":[
        {
            "category":"Wholesale",
            "subcategory":"Machinery & Supplies",
            "type":"Manufacturing & Wholesale Goods"
        }
    ],
    "sg:phone":"+1 701 463 2271",
    "sg:postcode":"58540",
    "sg:province":"ND",
    "sg:tags":[
        "farm",
        "equipment"
    ],
    "wof:name":"Lakeside Implement",
    "wof:placetype":"venue"
},
  "geometry": {"coordinates":[-101.42349299999999,47.649531],"type":"Point"}
}