{
  "type": "Feature",
  "properties": {
    "addr:full":"208 Business Loop W Jamestown ND 58401",
    "addr:housenumber":"208",
    "addr:postcode":"58401",
    "addr:street":"Business Loop W",
    "iso:country":"US",
    "sg:address":"208 Business Loop W",
    "sg:city":"Jamestown",
    "sg:classifiers":[
        {
            "category":"Building & Trades",
            "subcategory":"Equipment Rental",
            "type":"Services"
        }
    ],
    "sg:phone":"+1 701 252 2895",
    "sg:postcode":"58401",
    "sg:province":"ND",
    "sg:tags":[
        "appliance",
        "yard",
        "rent",
        "furniture"
    ],
    "wof:name":"Appliance & Furniture Rent All",
    "wof:placetype":"venue"
},
  "geometry": {"coordinates":[-98.70986600000001,46.898349],"type":"Point"}
}