{
  "type": "Feature",
  "properties": {
    "addr:full":"2205 State Hwy 20 Devils Lake ND 58301",
    "addr:housenumber":"2205",
    "addr:postcode":"58301",
    "addr:street":"State Hwy 20",
    "iso:country":"US",
    "sg:address":"2205 State Hwy 20",
    "sg:city":"Devils Lake",
    "sg:classifiers":[
        {
            "category":"Farming",
            "subcategory":"Farm",
            "type":"Manufacturing & Wholesale Goods"
        }
    ],
    "sg:phone":"+1 701 662 6512",
    "sg:postcode":"58301",
    "sg:province":"ND",
    "sg:tags":[
        "crop",
        "general"
    ],
    "wof:name":"Garden Dwellers Farm",
    "wof:placetype":"venue"
},
  "geometry": {"coordinates":[-98.874786,48.092206],"type":"Point"}
}