{
  "type": "Feature",
  "properties": {
    "addr:full":"423 4th Ave S Devils Lake ND 58301",
    "addr:housenumber":"423",
    "addr:postcode":"58301",
    "addr:street":"4Th Ave S Devils Lake",
    "iso:country":"US",
    "sg:address":"423 4th Ave S",
    "sg:city":"Devils Lake",
    "sg:classifiers":[
        {
            "category":"Manufacturing",
            "subcategory":"Printing",
            "type":"Manufacturing & Wholesale Goods"
        }
    ],
    "sg:phone":"+1 701 662 6570",
    "sg:postcode":"58301",
    "sg:province":"ND",
    "sg:tags":[
        "screen"
    ],
    "wof:name":"Creative Impressions",
    "wof:placetype":"venue"
},
  "geometry": {"coordinates":[-98.86058800000001,48.105481],"type":"Point"}
}