{
  "type": "Feature",
  "properties": {
    "iso:country":"US",
    "sg:address":"1523 Dyke Ave",
    "sg:city":"Grand Forks",
    "sg:classifiers":[
        {
            "category":"Food & Beverages",
            "subcategory":"Specialty",
            "type":"Retail Goods"
        }
    ],
    "sg:phone":"+1 701 792 3444",
    "sg:postcode":"58203",
    "sg:province":"ND",
    "sg:tags":[
        "water",
        "bulk",
        "company"
    ],
    "wof:name":"Premium Waters Inc",
    "wof:placetype":"venue"
},
  "geometry": {"coordinates":[-97.049166,47.919019],"type":"Point"}
}