{
  "type": "Feature",
  "properties": {
    "iso:country":"US",
    "sg:address":"491 2nd Ave NE",
    "sg:city":"Valley City",
    "sg:classifiers":[
        {
            "category":"Social Services",
            "subcategory":"Adult Care",
            "type":"Services"
        }
    ],
    "sg:phone":"+1 701 845 3363",
    "sg:postcode":"58072",
    "sg:province":"ND",
    "sg:tags":[
        "home",
        "group"
    ],
    "wof:name":"Open Door Group Home Four",
    "wof:placetype":"venue"
},
  "geometry": {"coordinates":[-98.00170900000001,46.926437],"type":"Point"}
}