{
  "type": "Feature",
  "properties": {
    "iso:country":"US",
    "sg:address":"2525 University Dr S",
    "sg:city":"Fargo",
    "sg:classifiers":[
        {
            "category":"Manufacturing",
            "subcategory":"Tools & Machinery",
            "type":"Manufacturing & Wholesale Goods"
        },
        {
            "category":"Wholesale",
            "subcategory":"Electrical",
            "type":"Manufacturing & Wholesale Goods"
        }
    ],
    "sg:phone":"+1 701 232 7670",
    "sg:postcode":"58103",
    "sg:province":"ND",
    "sg:tags":[
        "equipment",
        "manufacturer",
        "supplies-wholesale",
        "electric",
        "supply"
    ],
    "wof:name":"Design Solutions and Integration",
    "wof:placetype":"venue"
},
  "geometry": {"coordinates":[-96.799058,46.841924],"type":"Point"}
}