{
  "type": "Feature",
  "properties": {
    "iso:country":"US",
    "sg:address":"510 E Main Ave",
    "sg:city":"Bismarck",
    "sg:classifiers":[
        {
            "category":"Arts & Performance",
            "subcategory":"Theater",
            "type":"Entertainment"
        }
    ],
    "sg:phone":"+1 701 250 8699",
    "sg:postcode":"58501",
    "sg:province":"ND",
    "sg:tags":[
        "bureau"
    ],
    "wof:name":"Stringbean Entertainment",
    "wof:placetype":"venue"
},
  "geometry": {"coordinates":[-100.78322799999999,46.805486],"type":"Point"}
}