{
  "type": "Feature",
  "properties": {
    "iso:country":"US",
    "sg:address":"2587 29th Ave NW",
    "sg:city":"Max",
    "sg:phone":"+1 701 679 2659",
    "sg:postcode":"58759",
    "sg:province":"ND",
    "sg:tags":[
        "farm",
        "wheat"
    ],
    "wof:name":"Otto Kohler",
    "wof:placetype":"venue"
},
  "geometry": {"coordinates":[-101.207491,47.790236],"type":"Point"}
}