{
  "type": "Feature",
  "properties": {
    "iso:country":"US",
    "sg:address":"3 Main St",
    "sg:city":"Alamo",
    "sg:classifiers":[
        {
            "category":"Government",
            "subcategory":"Fire Station",
            "type":"Public Place"
        }
    ],
    "sg:phone":"+1 701 528 4822",
    "sg:postcode":"58856",
    "sg:province":"ND",
    "sg:tags":[
        "department"
    ],
    "wof:name":"Alamo Fire Dept",
    "wof:placetype":"venue"
},
  "geometry": {"coordinates":[-103.93748600000001,48.616672],"type":"Point"}
}