{
  "type": "Feature",
  "properties": {
    "iso:country":"US",
    "sg:address":"119 Main St S",
    "sg:city":"Elgin",
    "sg:classifiers":[
        {
            "category":"Manufacturing",
            "subcategory":"Printing",
            "type":"Manufacturing & Wholesale Goods"
        }
    ],
    "sg:phone":"+1 701 584 2900",
    "sg:postcode":"58533",
    "sg:province":"ND",
    "sg:tags":[
        "newspaper"
    ],
    "wof:name":"Grant County News/Carson Press",
    "wof:placetype":"venue"
},
  "geometry": {"coordinates":[-101.701115,46.389822],"type":"Point"}
}