{
  "type": "Feature",
  "properties": {
    "iso:country":"US",
    "sg:address":"29100 54th St NW",
    "sg:city":"Wilton",
    "sg:classifiers":[
        {
            "category":"Building & Trades",
            "subcategory":"Plumbing",
            "type":"Services"
        }
    ],
    "sg:phone":"+1 701 734 6748",
    "sg:postcode":"58579",
    "sg:province":"ND",
    "sg:tags":[
        "plumbing",
        "contractor"
    ],
    "wof:name":"Town & Country Plumbing & Htg",
    "wof:placetype":"venue"
},
  "geometry": {"coordinates":[-100.875936,47.12224],"type":"Point"}
}