{
  "type": "Feature",
  "properties": {
    "addr:full":"1001 State Hwy 20 Devils Lake ND 58301",
    "addr:housenumber":"1001",
    "addr:postcode":"58301",
    "addr:street":"State Hwy 20",
    "iso:country":"US",
    "sg:address":"1001 State Hwy 20",
    "sg:city":"Devils Lake",
    "sg:classifiers":[
        {
            "category":"Recreation",
            "type":"Entertainment"
        }
    ],
    "sg:phone":"+1 701 662 5161",
    "sg:postcode":"58301",
    "sg:province":"ND",
    "sg:tags":[
        "amusement"
    ],
    "wof:name":"Dales Motorsports",
    "wof:placetype":"venue"
},
  "geometry": {"coordinates":[-98.866215,48.101051],"type":"Point"}
}