{
  "type": "Feature",
  "properties": {
    "iso:country":"US",
    "sg:address":"1720 Sykes Dr",
    "sg:city":"Bismarck",
    "sg:classifiers":[
        {
            "category":"Insurance",
            "subcategory":"Insurance Agent",
            "type":"Services"
        }
    ],
    "sg:phone":"+1 701 250 5380",
    "sg:postcode":"58504",
    "sg:province":"ND",
    "wof:name":"Coventry Management Svc Inc",
    "wof:placetype":"venue"
},
  "geometry": {"coordinates":[-100.75783,46.787033],"type":"Point"}
}