{
  "type": "Feature",
  "properties": {
    "addr:full":"5300 48th Ave SE Streeter ND 58483",
    "addr:housenumber":"5300",
    "addr:postcode":"58483",
    "addr:street":"48Th Ave Se",
    "iso:country":"US",
    "sg:address":"5300 48th Ave SE",
    "sg:city":"Streeter",
    "sg:classifiers":[
        {
            "category":"Farming",
            "subcategory":"Livestock Farm",
            "type":"Manufacturing & Wholesale Goods"
        }
    ],
    "sg:phone":"+1 701 424 3627",
    "sg:postcode":"58483",
    "sg:province":"ND",
    "sg:tags":[
        "beef",
        "feedlot",
        "cattle"
    ],
    "wof:name":"Donald Gienger",
    "wof:placetype":"venue"
},
  "geometry": {"coordinates":[-99.449488,46.646167],"type":"Point"}
}