{
  "type": "Feature",
  "properties": {
    "addr:full":"1021 12th St Langdon ND 58249",
    "addr:housenumber":"1021",
    "addr:postcode":"58249",
    "addr:street":"12Th St",
    "iso:country":"US",
    "sg:address":"1021 12th St",
    "sg:city":"Langdon",
    "sg:classifiers":[
        {
            "category":"Restaurant",
            "type":"Food & Drink"
        }
    ],
    "sg:phone":"+1 701 256 2750",
    "sg:postcode":"58249",
    "sg:province":"ND",
    "wof:name":"Crossroads",
    "wof:placetype":"venue"
},
  "geometry": {"coordinates":[-98.382048,48.761788],"type":"Point"}
}