{
  "type": "Feature",
  "properties": {
    "addr:full":"718 23rd St S Fargo ND 58103",
    "addr:housenumber":"718",
    "addr:postcode":"58103",
    "addr:street":"23Rd St S",
    "iso:country":"US",
    "sg:address":"718 23rd St S",
    "sg:city":"Fargo",
    "sg:classifiers":[
        {
            "category":"Building & Trades",
            "subcategory":"Construction",
            "type":"Services"
        }
    ],
    "sg:phone":"+1 701 461 8950",
    "sg:postcode":"58103",
    "sg:province":"ND",
    "sg:tags":[
        "contractor"
    ],
    "wof:name":"Dave Morley Construction",
    "wof:placetype":"venue"
},
  "geometry": {"coordinates":[-96.817058,46.866895],"type":"Point"}
}