{
  "type": "Feature",
  "properties": {
    "iso:country":"US",
    "sg:address":"607 Crescent Ln",
    "sg:city":"Bismarck",
    "sg:classifiers":[
        {
            "category":"Building & Trades",
            "subcategory":"Landscaping Services",
            "type":"Services"
        }
    ],
    "sg:phone":"+1 701 471 1430",
    "sg:postcode":"58501",
    "sg:province":"ND",
    "sg:tags":[
        "lawn",
        "maintenance",
        "grounds"
    ],
    "wof:name":"D K's Lawn Care",
    "wof:placetype":"venue"
},
  "geometry": {"coordinates":[-100.806648,46.812383],"type":"Point"}
}