{
  "type": "Feature",
  "properties": {
    "iso:country":"US",
    "sg:address":"9230 156th Ave SE",
    "sg:city":"Lidgerwood",
    "sg:phone":"+1 701 538 7753",
    "sg:postcode":"58053",
    "sg:province":"ND",
    "sg:tags":[
        "farm",
        "corn",
        "soybean"
    ],
    "wof:name":"Dale Witt",
    "wof:placetype":"venue"
},
  "geometry": {"coordinates":[-97.135442,46.074808],"type":"Point"}
}