{
  "type": "Feature",
  "properties": {
    "addr:full":"516 6th St SE Rugby ND 58368",
    "addr:housenumber":"516",
    "addr:postcode":"58368",
    "addr:street":"6Th St Se",
    "iso:country":"US",
    "sg:address":"516 6th St SE",
    "sg:city":"Rugby",
    "sg:classifiers":[
        {
            "category":"Farming",
            "subcategory":"Farm & Veterinary Services",
            "type":"Manufacturing & Wholesale Goods"
        }
    ],
    "sg:phone":"+1 701 776 5171",
    "sg:postcode":"58368",
    "sg:province":"ND",
    "sg:tags":[
        "aerial",
        "applicator"
    ],
    "wof:name":"Schneider Aerial Spraying Svc",
    "wof:placetype":"venue"
},
  "geometry": {"coordinates":[-99.987853,48.364584],"type":"Point"}
}