{
  "type": "Feature",
  "properties": {
    "addr:full":"4228 15th Ave S Fargo ND 58103",
    "addr:housenumber":"4228",
    "addr:postcode":"58103",
    "addr:street":"15Th Ave S",
    "iso:country":"US",
    "sg:address":"4228 15th Ave S",
    "sg:city":"Fargo",
    "sg:classifiers":[
        {
            "category":"Restaurant",
            "type":"Food & Drink"
        }
    ],
    "sg:phone":"+1 701 282 8888",
    "sg:postcode":"58103",
    "sg:province":"ND",
    "wof:name":"Mandarin Restaurant",
    "wof:placetype":"venue"
},
  "geometry": {"coordinates":[-96.851608,46.858145],"type":"Point"}
}