{
  "type": "Feature",
  "properties": {
    "iso:country":"US",
    "sg:address":"106 S Main St",
    "sg:city":"Bowman",
    "sg:classifiers":[
        {
            "category":"Professional",
            "type":"Services"
        }
    ],
    "sg:phone":"+1 701 523 5000",
    "sg:postcode":"58623",
    "sg:province":"ND",
    "sg:tags":[
        "establishment"
    ],
    "wof:name":"Has Beens",
    "wof:placetype":"venue"
},
  "geometry": {"coordinates":[-103.39505200000001,46.181151],"type":"Point"}
}