{
  "type": "Feature",
  "properties": {
    "iso:country":"US",
    "sg:address":"1500 State Hwy 32 N",
    "sg:city":"Walhalla",
    "sg:classifiers":[
        {
            "category":"Freight",
            "type":"Transportation"
        }
    ],
    "sg:phone":"+1 701 549 3210",
    "sg:postcode":"58282",
    "sg:province":"ND",
    "sg:tags":[
        "grain",
        "elevator"
    ],
    "wof:name":"Walhalla Farmers Grain",
    "wof:placetype":"venue"
},
  "geometry": {"coordinates":[-97.90906,48.927637],"type":"Point"}
}