{
  "type": "Feature",
  "properties": {
    "iso:country":"US",
    "sg:address":"1112 Nodak Dr",
    "sg:city":"Fargo",
    "sg:classifiers":[
        {
            "category":"Social Services",
            "subcategory":"Job Training",
            "type":"Services"
        }
    ],
    "sg:phone":"+1 701 234 1714",
    "sg:postcode":"58103",
    "sg:province":"ND",
    "sg:tags":[
        "employment"
    ],
    "wof:name":"Burdick Job Corps",
    "wof:placetype":"venue"
},
  "geometry": {"coordinates":[-96.83291199999999,46.863285],"type":"Point"}
}