{
  "type": "Feature",
  "properties": {
    "addr:full":"1301 15th Ave W Williston ND 58801",
    "addr:housenumber":"1301",
    "addr:postcode":"58801",
    "addr:street":"15Th Ave W",
    "iso:country":"US",
    "sg:address":"1301 15th Ave W",
    "sg:city":"Williston",
    "sg:classifiers":[
        {
            "category":"Health Services",
            "subcategory":"Health Practitioner",
            "type":"Services"
        }
    ],
    "sg:phone":"+1 701 774 7436",
    "sg:postcode":"58801",
    "sg:province":"ND",
    "wof:name":"Mercy Rhbiliation Therapy Svcs",
    "wof:placetype":"venue"
},
  "geometry": {"coordinates":[-103.645489,48.155072],"type":"Point"}
}