{
  "type": "Feature",
  "properties": {
    "iso:country":"US",
    "sg:address":"7353 Co Rd 60",
    "sg:city":"Lamoure",
    "sg:classifiers":[
        {
            "category":"Farming",
            "subcategory":"Farm & Veterinary Services",
            "type":"Manufacturing & Wholesale Goods"
        }
    ],
    "sg:phone":"+1 701 883 5127",
    "sg:postcode":"58458",
    "sg:province":"ND",
    "sg:tags":[
        "aerial",
        "applicator"
    ],
    "wof:name":"Roberts Aerial Svc",
    "wof:placetype":"venue"
},
  "geometry": {"coordinates":[-98.20205900000001,46.347621],"type":"Point"}
}