{
  "type": "Feature",
  "properties": {
    "addr:full":"511 E Elm Ave Linton ND 58552",
    "addr:housenumber":"511",
    "addr:postcode":"58552",
    "addr:street":"E Elm Ave",
    "iso:country":"US",
    "sg:address":"511 E Elm Ave",
    "sg:city":"Linton",
    "sg:classifiers":[
        {
            "category":"Health Services",
            "subcategory":"Doctor",
            "type":"Services"
        }
    ],
    "sg:phone":"+1 701 254 4531",
    "sg:postcode":"58552",
    "sg:province":"ND",
    "sg:tags":[
        "clinic"
    ],
    "wof:name":"Linton Medical Ctr",
    "wof:placetype":"venue"
},
  "geometry": {"coordinates":[-100.22644,46.271739],"type":"Point"}
}