{
  "type": "Feature",
  "properties": {
    "iso:country":"US",
    "sg:address":"105 Main St",
    "sg:city":"Rolette",
    "sg:phone":"+1 701 246 3493",
    "sg:postcode":"58366",
    "sg:province":"ND",
    "sg:tags":[
        "oil"
    ],
    "wof:name":"Farmer's Union Oil Co",
    "wof:placetype":"venue"
},
  "geometry": {"coordinates":[-99.84496900000001,48.660857],"type":"Point"}
}