{
  "type": "Feature",
  "properties": {
    "iso:country":"US",
    "sg:address":"10100 117th Ave NW",
    "sg:city":"Crosby",
    "sg:classifiers":[
        {
            "category":"Building & Trades",
            "subcategory":"Plumbing",
            "type":"Services"
        }
    ],
    "sg:phone":"+1 701 965 6448",
    "sg:postcode":"58730",
    "sg:province":"ND",
    "sg:tags":[
        "heating",
        "contractor"
    ],
    "wof:name":"D K's Plumbing & Heating",
    "wof:placetype":"venue"
},
  "geometry": {"coordinates":[-103.268292,48.879821],"type":"Point"}
}