{
  "type": "Feature",
  "properties": {
    "addr:full":"21 S University Dr Fargo ND 58103",
    "addr:housenumber":"21",
    "addr:postcode":"58103",
    "addr:street":"S University Dr",
    "iso:country":"US",
    "sg:address":"21 S University Dr",
    "sg:city":"Fargo",
    "sg:classifiers":[
        {
            "category":"Autos & Motor Vehicles",
            "subcategory":"Automobile Sales",
            "type":"Retail Goods"
        },
        {
            "category":"Wholesale",
            "subcategory":"Motor Vehicles",
            "type":"Manufacturing & Wholesale Goods"
        }
    ],
    "sg:phone":"+1 701 280 2572",
    "sg:postcode":"58103",
    "sg:province":"ND",
    "sg:tags":[
        "car",
        "used",
        "dealer"
    ],
    "wof:name":"Dean's Auto Sales",
    "wof:placetype":"venue"
},
  "geometry": {"coordinates":[-96.798346,46.874705],"type":"Point"}
}