{
  "type": "Feature",
  "properties": {
    "iso:country":"US",
    "sg:address":"1306 5th Ave S",
    "sg:city":"Fargo",
    "sg:classifiers":[
        {
            "category":"Real Estate",
            "subcategory":"Real Estate Operator",
            "type":"Services"
        }
    ],
    "sg:phone":"+1 701 280 1178",
    "sg:postcode":"58103",
    "sg:province":"ND",
    "sg:tags":[
        "apartment"
    ],
    "wof:name":"Kendall & Gloria Nygard",
    "wof:placetype":"venue"
},
  "geometry": {"coordinates":[-96.798631,46.869713],"type":"Point"}
}