{
  "type": "Feature",
  "properties": {
    "iso:country":"US",
    "sg:address":"9175 54th St NE",
    "sg:city":"Crary",
    "sg:classifiers":[
        {
            "category":"Farming",
            "subcategory":"Farm",
            "type":"Manufacturing & Wholesale Goods"
        }
    ],
    "sg:phone":"+1 701 398 3845",
    "sg:postcode":"58327",
    "sg:province":"ND",
    "sg:tags":[
        "crop",
        "general"
    ],
    "wof:name":"Jim Stromme",
    "wof:placetype":"venue"
},
  "geometry": {"coordinates":[-98.645871,48.194889],"type":"Point"}
}