{
  "type": "Feature",
  "properties": {
    "addr:full":"115 E Century Ave Bismarck ND 58503",
    "addr:housenumber":"115",
    "addr:postcode":"58503",
    "addr:street":"E Century Ave",
    "iso:country":"US",
    "sg:address":"115 E Century Ave",
    "sg:city":"Bismarck",
    "sg:classifiers":[
        {
            "category":"Personal",
            "subcategory":"Beauty Salon",
            "type":"Services"
        },
        {
            "category":"Personal",
            "subcategory":"Nail Salon",
            "type":"Services"
        }
    ],
    "sg:phone":"+1 701 222 4987",
    "sg:postcode":"58503",
    "sg:province":"ND",
    "sg:tags":[
        "hair",
        "stylist"
    ],
    "wof:name":"Hair Of The Century",
    "wof:placetype":"venue"
},
  "geometry": {"coordinates":[-100.793487,46.838106],"type":"Point"}
}