{
  "type": "Feature",
  "properties": {
    "iso:country":"US",
    "sg:address":"9021 Baine Dr",
    "sg:city":"Bismarck",
    "sg:classifiers":[
        {
            "category":"Building & Trades",
            "subcategory":"Construction",
            "type":"Services"
        }
    ],
    "sg:phone":"+1 701 226 6989",
    "sg:postcode":"58503",
    "sg:province":"ND",
    "wof:name":"Midwest Power Inc",
    "wof:placetype":"venue"
},
  "geometry": {"coordinates":[-100.763616,46.903763],"type":"Point"}
}