{
  "type": "Feature",
  "properties": {
    "iso:country":"US",
    "sg:address":"8040 Co Rd 15 W",
    "sg:city":"Minot",
    "sg:classifiers":[
        {
            "category":"Building & Trades",
            "subcategory":"Landscaping Services",
            "type":"Services"
        }
    ],
    "sg:phone":"+1 701 833 6367",
    "sg:postcode":"58703",
    "sg:province":"ND",
    "sg:tags":[
        "lawn",
        "maintenance",
        "grounds"
    ],
    "wof:name":"Sauer Brothers",
    "wof:placetype":"venue"
},
  "geometry": {"coordinates":[-101.414045,48.285747],"type":"Point"}
}