{
  "type": "Feature",
  "properties": {
    "addr:full":"710 Main Ave Washburn ND 58577",
    "addr:housenumber":"710",
    "addr:postcode":"58577",
    "addr:street":"Main Ave",
    "iso:country":"US",
    "sg:address":"710 Main Ave",
    "sg:city":"Washburn",
    "sg:classifiers":[
        {
            "category":"Insurance",
            "subcategory":"Insurance Agent",
            "type":"Services"
        }
    ],
    "sg:phone":"+1 701 462 8404",
    "sg:postcode":"58577",
    "sg:province":"ND",
    "wof:name":"Washburn Insurance Inc",
    "wof:placetype":"venue"
},
  "geometry": {"coordinates":[-101.028814,47.289007],"type":"Point"}
}