{
  "type": "Feature",
  "properties": {
    "addr:full":"2150 32nd Ave S Grand Forks ND 58201",
    "addr:housenumber":"2150",
    "addr:postcode":"58201",
    "addr:street":"32Nd Ave S",
    "iso:country":"US",
    "sg:address":"2150 32nd Ave S",
    "sg:city":"Grand Forks",
    "sg:classifiers":[
        {
            "category":"Wholesale",
            "subcategory":"Machinery & Supplies",
            "type":"Manufacturing & Wholesale Goods"
        }
    ],
    "sg:phone":"+1 701 775 2563",
    "sg:postcode":"58201",
    "sg:province":"ND",
    "sg:tags":[
        "salon",
        "beauty"
    ],
    "wof:name":"Aerial Beauty Supply",
    "wof:placetype":"venue"
},
  "geometry": {"coordinates":[-97.058238,47.889516],"type":"Point"}
}