{
  "type": "Feature",
  "properties": {
    "iso:country":"US",
    "sg:address":"418 E Rosser Ave",
    "sg:city":"Bismarck",
    "sg:classifiers":[
        {
            "category":"Organizations",
            "subcategory":"Non-profit Organization",
            "type":"Services"
        }
    ],
    "sg:phone":"+1 701 471 1170",
    "sg:postcode":"58501",
    "sg:province":"ND",
    "sg:tags":[
        "information",
        "alcoholism",
        "treatment"
    ],
    "wof:name":"Audrey Kazmierczak",
    "wof:placetype":"venue"
},
  "geometry": {"coordinates":[-100.784752,46.808637],"type":"Point"}
}