{
  "type": "Feature",
  "properties": {
    "iso:country":"US",
    "sg:address":"1235 15th Ave SW",
    "sg:city":"Minot",
    "sg:classifiers":[
        {
            "category":"Professional",
            "subcategory":"Business Services",
            "type":"Services"
        }
    ],
    "sg:phone":"+1 701 839 1061",
    "sg:postcode":"58701",
    "sg:province":"ND",
    "sg:tags":[
        "auctioneer"
    ],
    "wof:name":"Sundsbak Auction Svc",
    "wof:placetype":"venue"
},
  "geometry": {"coordinates":[-101.30211300000001,48.22017],"type":"Point"}
}