{
  "type": "Feature",
  "properties": {
    "iso:country":"US",
    "sg:address":"109 Water St W",
    "sg:city":"Medina",
    "sg:classifiers":[
        {
            "category":"Restaurant",
            "type":"Food & Drink"
        }
    ],
    "sg:phone":"+1 701 486 3114",
    "sg:postcode":"58467",
    "sg:province":"ND",
    "wof:name":"Medina Cafe",
    "wof:placetype":"venue"
},
  "geometry": {"coordinates":[-99.300014,46.893981],"type":"Point"}
}