{
  "type": "Feature",
  "properties": {
    "addr:full":"1605 11th St N Wahpeton ND 58075",
    "addr:housenumber":"1605",
    "addr:postcode":"58075",
    "addr:street":"11Th St N",
    "iso:country":"US",
    "sg:address":"1605 11th St N",
    "sg:city":"Wahpeton",
    "sg:classifiers":[
        {
            "category":"Restaurant",
            "type":"Food & Drink"
        }
    ],
    "sg:phone":"+1 701 642 1135",
    "sg:postcode":"58075",
    "sg:province":"ND",
    "wof:name":"Prante's Fine Dining",
    "wof:placetype":"venue"
},
  "geometry": {"coordinates":[-96.61551300000001,46.285399],"type":"Point"}
}