{
  "type": "Feature",
  "properties": {
    "iso:country":"US",
    "sg:address":"926 2nd Ave N",
    "sg:city":"Wahpeton",
    "sg:classifiers":[
        {
            "category":"Professional",
            "subcategory":"Business Services",
            "type":"Services"
        },
        {
            "category":"Government",
            "subcategory":"Post Office",
            "type":"Public Place"
        }
    ],
    "sg:phone":"+1 800 275 8777",
    "sg:postcode":"58075",
    "sg:province":"ND",
    "sg:tags":[
        "mail",
        "shipping"
    ],
    "sg:website":"http://www.usps.com",
    "wof:name":"USPS - United States Post Office - Wahpeton Main Office",
    "wof:placetype":"venue"
},
  "geometry": {"coordinates":[-96.613128,46.265011],"type":"Point"}
}