{
  "type": "Feature",
  "properties": {
    "iso:country":"US",
    "sg:address":"205 N 1st St",
    "sg:city":"Bismarck",
    "sg:classifiers":[
        {
            "category":"Wholesale",
            "subcategory":"Auto Parts",
            "type":"Manufacturing & Wholesale Goods"
        }
    ],
    "sg:phone":"+1 701 221 4217",
    "sg:postcode":"58501",
    "sg:province":"ND",
    "sg:tags":[
        "automobile"
    ],
    "wof:name":"Benco Equipment Co",
    "wof:placetype":"venue"
},
  "geometry": {"coordinates":[-100.790612,46.807546],"type":"Point"}
}