{
  "type": "Feature",
  "properties": {
    "iso:country":"US",
    "sg:address":"14260 62nd St NE",
    "sg:city":"Grafton",
    "sg:classifiers":[
        {
            "category":"Retail",
            "subcategory":"Repair Shop",
            "type":"Services"
        }
    ],
    "sg:phone":"+1 701 352 1153",
    "sg:postcode":"58237",
    "sg:province":"ND",
    "sg:tags":[
        "plumbing",
        "drain",
        "cleaning",
        "sewer"
    ],
    "wof:name":"Kringstad Drain Cleaning",
    "wof:placetype":"venue"
},
  "geometry": {"coordinates":[-97.54443999999999,48.310566],"type":"Point"}
}