{
  "type": "Feature",
  "properties": {
    "addr:full":"1526 7th Ave S Fargo ND 58103",
    "addr:housenumber":"1526",
    "addr:postcode":"58103",
    "addr:street":"7Th Ave S",
    "iso:country":"US",
    "sg:address":"1526 7th Ave S",
    "sg:city":"Fargo",
    "sg:classifiers":[
        {
            "category":"Social Services",
            "subcategory":"Child Care",
            "type":"Services"
        }
    ],
    "sg:phone":"+1 701 232 3704",
    "sg:postcode":"58103",
    "sg:province":"ND",
    "sg:tags":[
        "day"
    ],
    "wof:name":"Hollands Family Day Care Inc",
    "wof:placetype":"venue"
},
  "geometry": {"coordinates":[-96.805896,46.867704],"type":"Point"}
}