{
  "type": "Feature",
  "properties": {
    "addr:full":"500 River Rd Burlington ND 58722",
    "addr:housenumber":"500",
    "addr:postcode":"58722",
    "addr:street":"River Rd",
    "iso:country":"US",
    "sg:address":"500 River Rd",
    "sg:city":"Burlington",
    "sg:classifiers":[
        {
            "category":"Recreation",
            "type":"Entertainment"
        }
    ],
    "sg:phone":"+1 701 838 2939",
    "sg:postcode":"58722",
    "sg:province":"ND",
    "sg:tags":[
        "center"
    ],
    "wof:name":"Burlington Recreation Sports",
    "wof:placetype":"venue"
},
  "geometry": {"coordinates":[-101.420157,48.276406],"type":"Point"}
}