{
  "type": "Feature",
  "properties": {
    "addr:full":"103 Ballman Ave Martin ND 58758",
    "addr:housenumber":"103",
    "addr:postcode":"58758",
    "addr:street":"Ballman Ave",
    "iso:country":"US",
    "sg:address":"103 Ballman Ave",
    "sg:city":"Martin",
    "sg:classifiers":[
        {
            "category":"Retail",
            "subcategory":"Auto Repair",
            "type":"Services"
        }
    ],
    "sg:phone":"+1 701 693 2804",
    "sg:postcode":"58758",
    "sg:province":"ND",
    "sg:tags":[
        "body",
        "automobile",
        "painting"
    ],
    "wof:name":"Doug's Auto Body",
    "wof:placetype":"venue"
},
  "geometry": {"coordinates":[-100.1151,47.826357],"type":"Point"}
}