{
  "type": "Feature",
  "properties": {
    "iso:country":"US",
    "sg:address":"4 3rd Ave NE",
    "sg:city":"Rolla",
    "sg:classifiers":[
        {
            "category":"Health Services",
            "subcategory":"Doctor",
            "type":"Services"
        }
    ],
    "sg:phone":"+1 701 477 3821",
    "sg:postcode":"58367",
    "sg:province":"ND",
    "sg:tags":[
        "dentist"
    ],
    "wof:name":"Turners Dental Office",
    "wof:placetype":"venue"
},
  "geometry": {"coordinates":[-99.61788900000001,48.861625],"type":"Point"}
}