{
  "type": "Feature",
  "properties": {
    "iso:country":"US",
    "sg:address":"203 N Elm St",
    "sg:city":"Hebron",
    "sg:classifiers":[
        {
            "category":"Organizations",
            "subcategory":"Religious Organization",
            "type":"Services"
        }
    ],
    "sg:phone":"+1 701 878 4199",
    "sg:postcode":"58638",
    "sg:province":"ND",
    "sg:tags":[
        "church"
    ],
    "wof:name":"Grace Reformed Chr-Lord Jesus",
    "wof:placetype":"venue"
},
  "geometry": {"coordinates":[-102.042953,46.904943],"type":"Point"}
}