{
  "type": "Feature",
  "properties": {
    "iso:country":"US",
    "sg:address":"1124 7th St S",
    "sg:city":"Oakes",
    "sg:classifiers":[
        {
            "category":"Farming",
            "subcategory":"Nursery",
            "type":"Manufacturing & Wholesale Goods"
        }
    ],
    "sg:phone":"+1 701 742 3519",
    "sg:postcode":"58474",
    "sg:province":"SD",
    "sg:tags":[
        "ornamental",
        "greenhouse"
    ],
    "wof:name":"Geffre's Greenhouse",
    "wof:placetype":"venue"
},
  "geometry": {"coordinates":[-98.090543,46.127561],"type":"Point"}
}