{
  "type": "Feature",
  "properties": {
    "addr:full":"10441 28th St NE Pekin ND 58361",
    "addr:housenumber":"10441",
    "addr:postcode":"58361",
    "addr:street":"28Th St Ne",
    "iso:country":"US",
    "sg:address":"10441 28th St NE",
    "sg:city":"Pekin",
    "sg:classifiers":[
        {
            "category":"Farming",
            "subcategory":"Nursery",
            "type":"Manufacturing & Wholesale Goods"
        }
    ],
    "sg:phone":"+1 701 296 4551",
    "sg:postcode":"58361",
    "sg:province":"ND",
    "sg:tags":[
        "greenhouse"
    ],
    "wof:name":"Plant Ranch",
    "wof:placetype":"venue"
},
  "geometry": {"coordinates":[-98.34741,47.817303],"type":"Point"}
}