{
  "type": "Feature",
  "properties": {
    "addr:full":"518 Np Ave Fargo ND 58102",
    "addr:housenumber":"518",
    "addr:postcode":"58102",
    "addr:street":"Np Ave",
    "iso:country":"US",
    "sg:address":"518 Np Ave",
    "sg:city":"Fargo",
    "sg:classifiers":[
        {
            "category":"Professional",
            "type":"Services"
        }
    ],
    "sg:phone":"+1 701 461 7291",
    "sg:postcode":"58102",
    "sg:province":"ND",
    "sg:tags":[
        "establishment"
    ],
    "wof:name":"ALCU Of The Dakotas",
    "wof:placetype":"venue"
},
  "geometry": {"coordinates":[-96.786548,46.875855],"type":"Point"}
}