{
  "type": "Feature",
  "properties": {
    "iso:country":"US",
    "sg:address":"2620 State St",
    "sg:city":"Bismarck",
    "sg:classifiers":[
        {
            "category":"Restaurant",
            "type":"Food & Drink"
        }
    ],
    "sg:phone":"+1 701 224 1111",
    "sg:postcode":"58503",
    "sg:province":"ND",
    "sg:website":"www.paradiso.com",
    "wof:name":"Paradiso Mexican Restaurant",
    "wof:placetype":"venue"
},
  "geometry": {"coordinates":[-100.773134,46.835578],"type":"Point"}
}