{
  "type": "Feature",
  "properties": {
    "addr:full":"455 7th Ave NE Valley City ND 58072",
    "addr:housenumber":"455",
    "addr:postcode":"58072",
    "addr:street":"7Th Ave Ne",
    "iso:country":"US",
    "sg:address":"455 7th Ave NE",
    "sg:city":"Valley City",
    "sg:classifiers":[
        {
            "category":"Health Services",
            "subcategory":"Hospital",
            "type":"Services"
        }
    ],
    "sg:phone":"+1 701 845 3681",
    "sg:postcode":"58072",
    "sg:province":"ND",
    "wof:name":"Mercy Hospital",
    "wof:placetype":"venue"
},
  "geometry": {"coordinates":[-97.99382199999999,46.927034],"type":"Point"}
}