{
  "type": "Feature",
  "properties": {
    "iso:country":"US",
    "sg:address":"226 3rd Ave",
    "sg:city":"Enderlin",
    "sg:classifiers":[
        {
            "category":"Bars & Pubs",
            "type":"Food & Drink"
        }
    ],
    "sg:phone":"+1 701 437 2058",
    "sg:postcode":"58027",
    "sg:province":"ND",
    "wof:name":"Spare Time Lounge",
    "wof:placetype":"venue"
},
  "geometry": {"coordinates":[-97.602504,46.624444],"type":"Point"}
}