{
  "type": "Feature",
  "properties": {
    "addr:full":"5831 Vvv Rd Sentinel Butte ND 58654",
    "addr:housenumber":"5831",
    "addr:postcode":"58654",
    "addr:street":"Vvv Rd",
    "iso:country":"US",
    "sg:address":"5831 Vvv Rd",
    "sg:city":"Sentinel Butte",
    "sg:classifiers":[
        {
            "category":"Farming",
            "subcategory":"Livestock Farm",
            "type":"Manufacturing & Wholesale Goods"
        }
    ],
    "sg:phone":"+1 701 279 5779",
    "sg:postcode":"58654",
    "sg:province":"ND",
    "sg:tags":[
        "ranch"
    ],
    "wof:name":"VVV Ranch",
    "wof:placetype":"venue"
},
  "geometry": {"coordinates":[-103.842788,46.623022],"type":"Point"}
}