{
  "type": "Feature",
  "properties": {
    "addr:full":"540 W 12th St Grafton ND 58237",
    "addr:housenumber":"540",
    "addr:postcode":"58237",
    "addr:street":"W 12Th St",
    "iso:country":"US",
    "sg:address":"540 W 12th St",
    "sg:city":"Grafton",
    "sg:classifiers":[
        {
            "category":"Insurance",
            "subcategory":"Insurance Agent",
            "type":"Services"
        }
    ],
    "sg:phone":"+1 701 352 3320",
    "sg:postcode":"58237",
    "sg:province":"ND",
    "wof:name":"AFLAC",
    "wof:placetype":"venue"
},
  "geometry": {"coordinates":[-97.41907,48.412419],"type":"Point"}
}