{
  "type": "Feature",
  "properties": {
    "iso:country":"US",
    "sg:address":"1101 11th St S",
    "sg:city":"Fargo",
    "sg:classifiers":[
        {
            "category":"Building & Trades",
            "subcategory":"Construction",
            "type":"Services"
        }
    ],
    "sg:phone":"+1 701 235 8128",
    "sg:postcode":"58103",
    "sg:province":"ND",
    "sg:tags":[
        "siding",
        "contractor"
    ],
    "wof:name":"Fargo Siding And Windows",
    "wof:placetype":"venue"
},
  "geometry": {"coordinates":[-96.79650100000001,46.863659],"type":"Point"}
}