{
  "type": "Feature",
  "properties": {
    "iso:country":"US",
    "sg:address":"2530 48th St NE",
    "sg:city":"Rugby",
    "sg:classifiers":[
        {
            "category":"Farming",
            "subcategory":"Livestock Farm",
            "type":"Manufacturing & Wholesale Goods"
        }
    ],
    "sg:phone":"+1 701 542 3869",
    "sg:postcode":"58368",
    "sg:province":"ND",
    "sg:tags":[
        "beef",
        "feedlot",
        "cattle"
    ],
    "wof:name":"Mike Schneider",
    "wof:placetype":"venue"
},
  "geometry": {"coordinates":[-100.079899,48.108721],"type":"Point"}
}