{
  "type": "Feature",
  "properties": {
    "addr:full":"430 W Main St Valley City ND 58072",
    "addr:housenumber":"430",
    "addr:postcode":"58072",
    "addr:street":"W Main St",
    "iso:country":"US",
    "sg:address":"430 W Main St",
    "sg:city":"Valley City",
    "sg:classifiers":[
        {
            "category":"Insurance",
            "subcategory":"Insurance Agent",
            "type":"Services"
        }
    ],
    "sg:phone":"+1 701 845 1185",
    "sg:postcode":"58072",
    "sg:province":"ND",
    "wof:name":"Security Insurance",
    "wof:placetype":"venue"
},
  "geometry": {"coordinates":[-98.00794,46.923328],"type":"Point"}
}