{
  "type": "Feature",
  "properties": {
    "iso:country":"US",
    "sg:address":"923 E Interstate Ave",
    "sg:city":"Bismarck",
    "sg:classifiers":[
        {
            "category":"Shopping",
            "subcategory":"Department Store",
            "type":"Retail Goods"
        }
    ],
    "sg:phone":"+1 701 255 6200",
    "sg:postcode":"58503",
    "sg:province":"ND",
    "wof:name":"One Stop Dollar Shop",
    "wof:placetype":"venue"
},
  "geometry": {"coordinates":[-100.777158,46.832722],"type":"Point"}
}