{
  "type": "Feature",
  "properties": {
    "iso:country":"US",
    "sg:address":"15 Main Ave S",
    "sg:city":"Fessenden",
    "sg:classifiers":[
        {
            "category":"Freight",
            "type":"Transportation"
        }
    ],
    "sg:phone":"+1 701 547 3154",
    "sg:postcode":"58438",
    "sg:province":"ND",
    "sg:tags":[
        "grain",
        "elevator"
    ],
    "wof:name":"Fessenden Co-Op Assn-Heimdal",
    "wof:placetype":"venue"
},
  "geometry": {"coordinates":[-99.630105,47.648261],"type":"Point"}
}