{
  "type": "Feature",
  "properties": {
    "iso:country":"US",
    "sg:address":"105 Main St",
    "sg:city":"Williston",
    "sg:classifiers":[
        {
            "category":"Home & Garden",
            "subcategory":"Household Appliances",
            "type":"Retail Goods"
        }
    ],
    "sg:phone":"+1 701 774 3090",
    "sg:postcode":"58801",
    "sg:province":"ND",
    "sg:tags":[
        "repair",
        "electrical"
    ],
    "wof:name":"Discount Sew-Vac",
    "wof:placetype":"venue"
},
  "geometry": {"coordinates":[-103.621551,48.144561],"type":"Point"}
}