{
  "type": "Feature",
  "properties": {
    "iso:country":"US",
    "sg:address":"4701 15th Ave S",
    "sg:city":"Fargo",
    "sg:classifiers":[
        {
            "category":"Freight",
            "type":"Transportation"
        }
    ],
    "sg:phone":"+1 701 282 4321",
    "sg:postcode":"58103",
    "sg:province":"ND",
    "sg:tags":[
        "storage"
    ],
    "wof:name":"Union Storage & Transfer Co",
    "wof:placetype":"venue"
},
  "geometry": {"coordinates":[-96.864698,46.858949],"type":"Point"}
}