{
  "type": "Feature",
  "properties": {
    "addr:full":"131 2nd Ave N Casselton ND 58012",
    "addr:housenumber":"131",
    "addr:postcode":"58012",
    "addr:street":"2Nd Ave N Casselton",
    "iso:country":"US",
    "sg:address":"131 2nd Ave N",
    "sg:city":"Casselton",
    "sg:classifiers":[
        {
            "category":"Building & Trades",
            "subcategory":"Plumbing",
            "type":"Services"
        }
    ],
    "sg:phone":"+1 701 347 4761",
    "sg:postcode":"58012",
    "sg:province":"ND",
    "sg:tags":[
        "conditioning",
        "air",
        "system",
        "contractor"
    ],
    "wof:name":"Steve's Heating Air Cond",
    "wof:placetype":"venue"
},
  "geometry": {"coordinates":[-97.218857,46.902634],"type":"Point"}
}