{
  "type": "Feature",
  "properties": {
    "iso:country":"US",
    "sg:address":"601 16th Ave SE",
    "sg:city":"Minot",
    "sg:classifiers":[
        {
            "category":"Arena",
            "subcategory":"Sports Club",
            "type":"Entertainment"
        }
    ],
    "sg:phone":"+1 701 857 4789",
    "sg:postcode":"58701",
    "sg:province":"ND",
    "sg:tags":[
        "athletic",
        "fields",
        "stadium"
    ],
    "wof:name":"South Hill Complex East End",
    "wof:placetype":"venue"
},
  "geometry": {"coordinates":[-101.28293499999999,48.21825],"type":"Point"}
}