{
  "type": "Feature",
  "properties": {
    "iso:country":"US",
    "sg:address":"1310 23rd St S",
    "sg:city":"Fargo",
    "sg:classifiers":[
        {
            "category":"Manufacturing",
            "subcategory":"Signs",
            "type":"Manufacturing & Wholesale Goods"
        }
    ],
    "sg:phone":"+1 701 232 1671",
    "sg:postcode":"58103",
    "sg:province":"ND",
    "sg:tags":[
        "specialty",
        "mfg"
    ],
    "wof:name":"Tri City Signs",
    "wof:placetype":"venue"
},
  "geometry": {"coordinates":[-96.817097,46.861211],"type":"Point"}
}