{
  "type": "Feature",
  "properties": {
    "addr:full":"3117 US Hwy 52 Harvey ND 58341",
    "addr:housenumber":"3117",
    "addr:postcode":"58341",
    "addr:street":"Us Hwy 52",
    "iso:country":"US",
    "sg:address":"3117 US Hwy 52",
    "sg:city":"Harvey",
    "sg:classifiers":[
        {
            "category":"Wholesale",
            "subcategory":"Machinery & Supplies",
            "type":"Manufacturing & Wholesale Goods"
        }
    ],
    "sg:phone":"+1 701 324 4631",
    "sg:postcode":"58341",
    "sg:province":"ND",
    "sg:tags":[
        "farm",
        "repair",
        "equipment"
    ],
    "wof:name":"Greenvision",
    "wof:placetype":"venue"
},
  "geometry": {"coordinates":[-99.90880199999999,47.745943],"type":"Point"}
}