{
  "type": "Feature",
  "properties": {
    "iso:country":"US",
    "sg:address":"1461 30th Ave NE",
    "sg:city":"Harvey",
    "sg:classifiers":[
        {
            "category":"Farming",
            "subcategory":"Livestock Farm",
            "type":"Manufacturing & Wholesale Goods"
        },
        {
            "category":"Farming",
            "subcategory":"Farm",
            "type":"Manufacturing & Wholesale Goods"
        }
    ],
    "sg:phone":"+1 701 324 2033",
    "sg:postcode":"58341",
    "sg:province":"ND",
    "sg:tags":[
        "hog",
        "wheat",
        "cash",
        "grain",
        "or",
        "feedlot"
    ],
    "wof:name":"Douglas Heitmann Farms",
    "wof:placetype":"venue"
},
  "geometry": {"coordinates":[-99.940772,47.761756],"type":"Point"}
}