{
  "type": "Feature",
  "properties": {
    "iso:country":"US",
    "sg:address":"218 S 26th St",
    "sg:city":"Bismarck",
    "sg:classifiers":[
        {
            "category":"Wholesale",
            "subcategory":"Auto Parts",
            "type":"Manufacturing & Wholesale Goods"
        }
    ],
    "sg:phone":"+1 701 255 1194",
    "sg:postcode":"58501",
    "sg:province":"ND",
    "sg:tags":[
        "automobile",
        "rebuilt"
    ],
    "wof:name":"Dave's Auto Inc",
    "wof:placetype":"venue"
},
  "geometry": {"coordinates":[-100.752172,46.803368],"type":"Point"}
}