{
  "type": "Feature",
  "properties": {
    "addr:full":"717 4th Ave E Williston ND 58801",
    "addr:housenumber":"717",
    "addr:postcode":"58801",
    "addr:street":"4Th Ave E",
    "iso:country":"US",
    "sg:address":"717 4th Ave E",
    "sg:city":"Williston",
    "sg:classifiers":[
        {
            "category":"Building & Trades",
            "subcategory":"Construction",
            "type":"Services"
        }
    ],
    "sg:phone":"+1 701 572 6668",
    "sg:postcode":"58801",
    "sg:province":"ND",
    "sg:tags":[
        "painter"
    ],
    "wof:name":"Casey's Painting Svc",
    "wof:placetype":"venue"
},
  "geometry": {"coordinates":[-103.61659299999999,48.151146],"type":"Point"}
}