{
  "type": "Feature",
  "properties": {
    "iso:country":"US",
    "sg:address":"627 Hillside Dr",
    "sg:city":"Dickinson",
    "sg:classifiers":[
        {
            "category":"Banks & Credit Unions",
            "subcategory":"Investment Brokerage",
            "type":"Services"
        }
    ],
    "sg:phone":"+1 701 225 5507",
    "sg:postcode":"58601",
    "sg:province":"ND",
    "sg:tags":[
        "land",
        "oil",
        "lease"
    ],
    "wof:name":"Contex Energy Co",
    "wof:placetype":"venue"
},
  "geometry": {"coordinates":[-102.79633800000001,46.893909],"type":"Point"}
}