{
  "type": "Feature",
  "properties": {
    "addr:full":"7324 68th Ave NE Cando ND 58324",
    "addr:housenumber":"7324",
    "addr:postcode":"58324",
    "addr:street":"68Th Ave Ne",
    "iso:country":"US",
    "sg:address":"7324 68th Ave NE",
    "sg:city":"Cando",
    "sg:classifiers":[
        {
            "category":"Government",
            "subcategory":"Office",
            "type":"Public Place"
        }
    ],
    "sg:phone":"+1 701 968 3259",
    "sg:postcode":"58324",
    "sg:province":"ND",
    "sg:tags":[
        "state",
        "program"
    ],
    "wof:name":"Nd Transportation Maintenance",
    "wof:placetype":"venue"
},
  "geometry": {"coordinates":[-99.187843,48.474065],"type":"Point"}
}