{
  "type": "Feature",
  "properties": {
    "iso:country":"US",
    "sg:address":"120 1st St S",
    "sg:city":"Wahpeton",
    "sg:classifiers":[
        {
            "category":"Professional",
            "subcategory":"Lawyer & Legal Services",
            "type":"Services"
        }
    ],
    "sg:phone":"+1 701 642 4747",
    "sg:postcode":"58075",
    "sg:province":"ND",
    "sg:tags":[
        "attorney",
        "business",
        "practice",
        "plan",
        "law",
        "bankruptcy"
    ],
    "wof:name":"Krassin Law Office",
    "wof:placetype":"venue"
},
  "geometry": {"coordinates":[-96.60090599999999,46.26353],"type":"Point"}
}