{
  "type": "Feature",
  "properties": {
    "iso:country":"US",
    "sg:address":"9788 134th Ave SE",
    "sg:city":"Havana",
    "sg:classifiers":[
        {
            "category":"Farming",
            "subcategory":"Farm",
            "type":"Manufacturing & Wholesale Goods"
        }
    ],
    "sg:phone":"+1 701 724 3798",
    "sg:postcode":"58043",
    "sg:province":"ND",
    "wof:name":"Jackie Peterson Farm",
    "wof:placetype":"venue"
},
  "geometry": {"coordinates":[-97.59232299999999,45.994868],"type":"Point"}
}