{
  "type": "Feature",
  "properties": {
    "addr:full":"103 6th St N Hettinger ND 58639",
    "addr:housenumber":"103",
    "addr:postcode":"58639",
    "addr:street":"6Th St N Hettinger",
    "iso:country":"US",
    "sg:address":"103 6th St N",
    "sg:city":"Hettinger",
    "sg:classifiers":[
        {
            "category":"Education",
            "subcategory":"Library",
            "type":"Public Place"
        }
    ],
    "sg:phone":"+1 701 567 2741",
    "sg:postcode":"58639",
    "sg:province":"ND",
    "wof:name":"Adams County Library",
    "wof:placetype":"venue"
},
  "geometry": {"coordinates":[-102.635431,46.001203],"type":"Point"}
}