{
  "type": "Feature",
  "properties": {
    "iso:country":"US",
    "sg:address":"221 1st St NE",
    "sg:city":"Rugby",
    "sg:classifiers":[
        {
            "category":"Retail",
            "subcategory":"Portrait Studio",
            "type":"Services"
        }
    ],
    "sg:phone":"+1 701 776 5074",
    "sg:postcode":"58368",
    "sg:province":"ND",
    "sg:tags":[
        "photo"
    ],
    "wof:name":"H H Photography",
    "wof:placetype":"venue"
},
  "geometry": {"coordinates":[-99.993521,48.371278],"type":"Point"}
}