{
  "type": "Feature",
  "properties": {
    "iso:country":"US",
    "sg:address":"1067 3rd Ave W",
    "sg:city":"Dickinson",
    "sg:classifiers":[
        {
            "category":"Shopping",
            "subcategory":"Musical Instruments",
            "type":"Retail Goods"
        }
    ],
    "sg:phone":"+1 701 483 6873",
    "sg:postcode":"58601",
    "sg:province":"ND",
    "sg:website":"www.jacobsenmusic.com",
    "wof:name":"Jacobsen Music Inc",
    "wof:placetype":"venue"
},
  "geometry": {"coordinates":[-102.789855,46.891063],"type":"Point"}
}