{
  "type": "Feature",
  "properties": {
    "iso:country":"US",
    "sg:address":"1225 Chautauqua Blvd",
    "sg:city":"Valley City",
    "sg:classifiers":[
        {
            "category":"Real Estate",
            "subcategory":"Real Estate Operator",
            "type":"Services"
        }
    ],
    "sg:phone":"+1 701 845 4632",
    "sg:postcode":"58072",
    "sg:province":"ND",
    "sg:tags":[
        "building",
        "apartment"
    ],
    "wof:name":"Jama Ltd",
    "wof:placetype":"venue"
},
  "geometry": {"coordinates":[-97.99377800000001,46.93755],"type":"Point"}
}