{
  "type": "Feature",
  "properties": {
    "iso:country":"US",
    "sg:address":"8284 123rd Ave NW",
    "sg:city":"Alamo",
    "sg:classifiers":[
        {
            "category":"Wholesale",
            "subcategory":"Non-durable Goods",
            "type":"Manufacturing & Wholesale Goods"
        }
    ],
    "sg:phone":"+1 701 539 2167",
    "sg:postcode":"58830",
    "sg:province":"ND",
    "sg:tags":[
        "canvas"
    ],
    "wof:name":"Canvas Shop",
    "wof:placetype":"venue"
},
  "geometry": {"coordinates":[-103.342383,48.616468],"type":"Point"}
}