{
  "type": "Feature",
  "properties": {
    "iso:country":"US",
    "sg:address":"5750 35th St",
    "sg:city":"New Salem",
    "sg:classifiers":[
        {
            "category":"Building & Trades",
            "subcategory":"Construction",
            "type":"Services"
        }
    ],
    "sg:phone":"+1 701 843 8657",
    "sg:postcode":"58563",
    "sg:province":"ND",
    "sg:tags":[
        "house"
    ],
    "wof:name":"Dan Kroh Construction",
    "wof:placetype":"venue"
},
  "geometry": {"coordinates":[-101.679239,46.905693],"type":"Point"}
}