{
  "type": "Feature",
  "properties": {
    "iso:country":"US",
    "sg:address":"210 1st St E",
    "sg:city":"Ross",
    "sg:classifiers":[
        {
            "category":"Retail",
            "subcategory":"Repair Shop",
            "type":"Services"
        }
    ],
    "sg:phone":"+1 701 755 3255",
    "sg:postcode":"58776",
    "sg:province":"ND",
    "sg:tags":[
        "upholsterer"
    ],
    "wof:name":"Doris' Upholstery",
    "wof:placetype":"venue"
},
  "geometry": {"coordinates":[-102.542553,48.313373],"type":"Point"}
}