{
  "type": "Feature",
  "properties": {
    "iso:country":"US",
    "sg:address":"10221 63rd Ave NW",
    "sg:city":"Dickinson",
    "sg:classifiers":[
        {
            "category":"Shopping",
            "subcategory":"Hobbies, Toys, & Games",
            "type":"Retail Goods"
        }
    ],
    "sg:phone":"+1 701 225 9559",
    "sg:postcode":"58601",
    "sg:province":"ND",
    "wof:name":"Dolls Galore",
    "wof:placetype":"venue"
},
  "geometry": {"coordinates":[-102.79446900000001,46.952408],"type":"Point"}
}