{
  "type": "Feature",
  "properties": {
    "iso:country":"US",
    "sg:address":"521 1st St SW",
    "sg:city":"Beulah",
    "sg:classifiers":[
        {
            "category":"Social Services",
            "subcategory":"Child Care",
            "type":"Services"
        }
    ],
    "sg:phone":"+1 701 873 2326",
    "sg:postcode":"58523",
    "sg:province":"ND",
    "sg:tags":[
        "day"
    ],
    "wof:name":"Romper Room",
    "wof:placetype":"venue"
},
  "geometry": {"coordinates":[-101.78523300000001,47.258872],"type":"Point"}
}