{
  "type": "Feature",
  "properties": {
    "iso:country":"US",
    "sg:address":"18 2nd St SE",
    "sg:city":"Stanley",
    "sg:classifiers":[
        {
            "category":"Government",
            "subcategory":"Office",
            "type":"Public Place"
        }
    ],
    "sg:phone":"+1 701 628 2951",
    "sg:postcode":"58784",
    "sg:province":"ND",
    "wof:name":"Mountrail County Nurse",
    "wof:placetype":"venue"
},
  "geometry": {"coordinates":[-102.387514,48.319491],"type":"Point"}
}