{
  "type": "Feature",
  "properties": {
    "iso:country":"US",
    "sg:address":"225 Walnut St W",
    "sg:city":"Devils Lake",
    "sg:classifiers":[
        {
            "category":"Banks & Credit Unions",
            "subcategory":"Bank",
            "type":"Services"
        }
    ],
    "sg:phone":"+1 701 662 5356",
    "sg:postcode":"58301",
    "sg:province":"ND",
    "sg:tags":[
        "federal",
        "agency"
    ],
    "wof:name":"Farm Credit Svcs Grnd Forks",
    "wof:placetype":"venue"
},
  "geometry": {"coordinates":[-98.866961,48.107814],"type":"Point"}
}