{
  "type": "Feature",
  "properties": {
    "iso:country":"US",
    "sg:address":"912 E Owens Ave",
    "sg:city":"Bismarck",
    "sg:classifiers":[
        {
            "category":"Professional",
            "subcategory":"Lawyer & Legal Services",
            "type":"Services"
        }
    ],
    "sg:phone":"+1 701 222 1808",
    "sg:postcode":"58501",
    "sg:province":"ND",
    "sg:tags":[
        "attorney"
    ],
    "wof:name":"Gregory Ian Runge",
    "wof:placetype":"venue"
},
  "geometry": {"coordinates":[-100.776258,46.824613],"type":"Point"}
}