{
  "type": "Feature",
  "properties": {
    "addr:full":"216 Brown Ave Mott ND 58646",
    "addr:housenumber":"216",
    "addr:postcode":"58646",
    "addr:street":"Brown Ave",
    "iso:country":"US",
    "sg:address":"216 Brown Ave",
    "sg:city":"Mott",
    "sg:classifiers":[
        {
            "category":"Shopping",
            "subcategory":"Pharmacy",
            "type":"Retail Goods"
        }
    ],
    "sg:phone":"+1 701 824 2897",
    "sg:postcode":"58646",
    "sg:province":"ND",
    "wof:name":"Mott Drug Store",
    "wof:placetype":"venue"
},
  "geometry": {"coordinates":[-102.32706399999999,46.372467],"type":"Point"}
}