{
  "type": "Feature",
  "properties": {
    "iso:country":"US",
    "sg:address":"2309 Memorial Hwy",
    "sg:city":"Mandan",
    "sg:classifiers":[
        {
            "category":"Food & Beverages",
            "subcategory":"Fruits & Vegetables",
            "type":"Retail Goods"
        },
        {
            "category":"Home & Garden",
            "subcategory":"Garden Supply",
            "type":"Retail Goods"
        }
    ],
    "sg:phone":"+1 701 663 9223",
    "sg:postcode":"58554",
    "sg:province":"ND",
    "sg:tags":[
        "seed",
        "center"
    ],
    "wof:name":"Faulkner's Market",
    "wof:placetype":"venue"
},
  "geometry": {"coordinates":[-100.86306,46.824815],"type":"Point"}
}