{
  "type": "Feature",
  "properties": {
    "iso:country":"US",
    "sg:address":"332 2nd Ave N",
    "sg:city":"Wahpeton",
    "sg:classifiers":[
        {
            "category":"Social Services",
            "type":"Services"
        }
    ],
    "sg:phone":"+1 701 642 7070",
    "sg:postcode":"58075",
    "sg:province":"ND",
    "wof:name":"PHD Richard LP Geiselhart",
    "wof:placetype":"venue"
},
  "geometry": {"coordinates":[-96.60432299999999,46.265059],"type":"Point"}
}