{
  "type": "Feature",
  "properties": {
    "iso:country":"US",
    "sg:address":"605 E Broadway",
    "sg:city":"Williston",
    "sg:classifiers":[
        {
            "category":"Mining & Drilling",
            "type":"Manufacturing & Wholesale Goods"
        }
    ],
    "sg:phone":"+1 701 572 5333",
    "sg:postcode":"58801",
    "sg:province":"ND",
    "sg:tags":[
        "field",
        "oil"
    ],
    "wof:name":"Production Service Co",
    "wof:placetype":"venue"
},
  "geometry": {"coordinates":[-103.611801,48.147083],"type":"Point"}
}