{
  "type": "Feature",
  "properties": {
    "addr:full":"629 3rd St Minto ND 58261",
    "addr:housenumber":"629",
    "addr:postcode":"58261",
    "addr:street":"3Rd St",
    "iso:country":"US",
    "sg:address":"629 3rd St",
    "sg:city":"Minto",
    "sg:classifiers":[
        {
            "category":"Organizations",
            "subcategory":"Religious Organization",
            "type":"Services"
        }
    ],
    "sg:phone":"+1 701 248 3589",
    "sg:postcode":"58261",
    "sg:province":"ND",
    "sg:tags":[
        "church"
    ],
    "wof:name":"Sacred Heart Catholic Church",
    "wof:placetype":"venue"
},
  "geometry": {"coordinates":[-97.373046,48.289686],"type":"Point"}
}