{
  "type": "Feature",
  "properties": {
    "iso:country":"US",
    "sg:address":"3333 E Broadway Ave",
    "sg:city":"Bismarck",
    "sg:classifiers":[
        {
            "category":"Organizations",
            "subcategory":"Political Organization",
            "type":"Services"
        }
    ],
    "sg:phone":"+1 701 222 3265",
    "sg:postcode":"58501",
    "sg:province":"ND",
    "wof:name":"Bismarck Democrats",
    "wof:placetype":"venue"
},
  "geometry": {"coordinates":[-100.740284,46.80783],"type":"Point"}
}