{
  "type": "Feature",
  "properties": {
    "iso:country":"US",
    "sg:address":"3385 State Hwy 11",
    "sg:city":"Ashley",
    "sg:classifiers":[
        {
            "category":"Farming",
            "subcategory":"Farm",
            "type":"Manufacturing & Wholesale Goods"
        }
    ],
    "sg:phone":"+1 701 684 6381",
    "sg:postcode":"58413",
    "sg:province":"ND",
    "sg:tags":[
        "crop",
        "general"
    ],
    "wof:name":"Eugene Noltz",
    "wof:placetype":"venue"
},
  "geometry": {"coordinates":[-99.67171500000001,46.027946],"type":"Point"}
}