{
  "type": "Feature",
  "properties": {
    "iso:country":"US",
    "sg:address":"311 E Thayer Ave",
    "sg:city":"Bismarck",
    "sg:classifiers":[
        {
            "category":"Professional",
            "subcategory":"Lawyer & Legal Services",
            "type":"Services"
        }
    ],
    "sg:phone":"+1 701 258 2769",
    "sg:postcode":"58501",
    "sg:province":"ND",
    "wof:name":"Tom Disselhorst",
    "wof:placetype":"venue"
},
  "geometry": {"coordinates":[-100.78621099999999,46.807479],"type":"Point"}
}