{
  "type": "Feature",
  "properties": {
    "iso:country":"US",
    "sg:address":"551 39th Ave NE",
    "sg:city":"Bowdon",
    "sg:classifiers":[
        {
            "category":"Farming",
            "subcategory":"Farm",
            "type":"Manufacturing & Wholesale Goods"
        }
    ],
    "sg:phone":"+1 701 962 3888",
    "sg:postcode":"58418",
    "sg:province":"ND",
    "wof:name":"Wendell Hoff Farm",
    "wof:placetype":"venue"
},
  "geometry": {"coordinates":[-99.714251,47.493758],"type":"Point"}
}