{
  "type": "Feature",
  "properties": {
    "iso:country":"US",
    "sg:address":"411 Rothschiller St",
    "sg:city":"Gladstone",
    "sg:classifiers":[
        {
            "category":"Wholesale",
            "subcategory":"Farm Supplies",
            "type":"Manufacturing & Wholesale Goods"
        }
    ],
    "sg:phone":"+1 701 483 0021",
    "sg:postcode":"58630",
    "sg:province":"ND",
    "sg:tags":[
        "feed"
    ],
    "sg:website":"www.swgrain.com",
    "wof:name":"Southwest Grain",
    "wof:placetype":"venue"
},
  "geometry": {"coordinates":[-102.56869,46.861819],"type":"Point"}
}