{
  "type": "Feature",
  "properties": {
    "iso:country":"US",
    "sg:address":"206 US Hwy 83",
    "sg:city":"Linton",
    "sg:classifiers":[
        {
            "category":"Food & Beverages",
            "subcategory":"Groceries & Convenience Stores",
            "type":"Retail Goods"
        }
    ],
    "sg:phone":"+1 701 254 5344",
    "sg:postcode":"58552",
    "sg:province":"ND",
    "sg:tags":[
        "grocer"
    ],
    "wof:name":"Schmaltz's Food Pride",
    "wof:placetype":"venue"
},
  "geometry": {"coordinates":[-100.23432099999999,46.264796],"type":"Point"}
}