{
  "type": "Feature",
  "properties": {
    "iso:country":"US",
    "sg:address":"410 3rd Ave SW",
    "sg:city":"Rugby",
    "sg:classifiers":[
        {
            "category":"Wholesale",
            "subcategory":"Farm Supplies",
            "type":"Manufacturing & Wholesale Goods"
        }
    ],
    "sg:phone":"+1 701 776 5662",
    "sg:postcode":"58368",
    "sg:province":"ND",
    "wof:name":"Dakota Prairie Supply",
    "wof:placetype":"venue"
},
  "geometry": {"coordinates":[-99.99887699999999,48.366606],"type":"Point"}
}