{
  "type": "Feature",
  "properties": {
    "iso:country":"US",
    "sg:address":"1318 Oak St N",
    "sg:city":"Fargo",
    "sg:classifiers":[
        {
            "category":"Building & Trades",
            "subcategory":"Plumbing",
            "type":"Services"
        }
    ],
    "sg:phone":"+1 701 232 3366",
    "sg:postcode":"58102",
    "sg:province":"ND",
    "sg:tags":[
        "plumbing",
        "contractor"
    ],
    "wof:name":"Roto-Rooter Plumbing & Drain",
    "wof:placetype":"venue"
},
  "geometry": {"coordinates":[-96.77862,46.894487],"type":"Point"}
}