{
  "type": "Feature",
  "properties": {
    "addr:full":"1321 28th St SW Minot ND 58701",
    "addr:housenumber":"1321",
    "addr:postcode":"58701",
    "addr:street":"28Th St Sw",
    "iso:country":"US",
    "sg:address":"1321 28th St SW",
    "sg:city":"Minot",
    "sg:classifiers":[
        {
            "category":"Shopping",
            "subcategory":"Computers & Home Electronics",
            "type":"Retail Goods"
        }
    ],
    "sg:phone":"+1 701 838 4989",
    "sg:postcode":"58701",
    "sg:province":"ND",
    "sg:tags":[
        "farm",
        "mfg"
    ],
    "wof:name":"Martronics Information Systems",
    "wof:placetype":"venue"
},
  "geometry": {"coordinates":[-101.336697,48.222211],"type":"Point"}
}