{
  "type": "Feature",
  "properties": {
    "iso:country":"US",
    "sg:address":"10 15th St NW",
    "sg:city":"West Fargo",
    "sg:classifiers":[
        {
            "category":"Restaurant",
            "type":"Food & Drink"
        }
    ],
    "sg:phone":"+1 701 277 0080",
    "sg:postcode":"58078",
    "sg:province":"ND",
    "wof:name":"Burger Time Acquisition Corp",
    "wof:placetype":"venue"
},
  "geometry": {"coordinates":[-96.926171,46.877244],"type":"Point"}
}