{
  "type": "Feature",
  "properties": {
    "addr:full":"610 72nd Ave NE Carrington ND 58421",
    "addr:housenumber":"610",
    "addr:postcode":"58421",
    "addr:street":"72Nd Ave Ne",
    "iso:country":"US",
    "sg:address":"610 72nd Ave NE",
    "sg:city":"Carrington",
    "sg:classifiers":[
        {
            "category":"Wholesale",
            "subcategory":"Farm Supplies",
            "type":"Manufacturing & Wholesale Goods"
        }
    ],
    "sg:phone":"+1 701 652 2946",
    "sg:postcode":"58421",
    "sg:province":"ND",
    "sg:tags":[
        "bulb",
        "seed"
    ],
    "wof:name":"United Seed & Supply Co",
    "wof:placetype":"venue"
},
  "geometry": {"coordinates":[-99.010498,47.501964],"type":"Point"}
}