{
  "type": "Feature",
  "properties": {
    "iso:country":"US",
    "sg:address":"102 2nd Ave NE",
    "sg:city":"Jamestown",
    "sg:classifiers":[
        {
            "category":"Retail",
            "subcategory":"Repair Shop",
            "type":"Services"
        }
    ],
    "sg:phone":"+1 701 252 1382",
    "sg:postcode":"58401",
    "sg:province":"ND",
    "sg:tags":[
        "appliance"
    ],
    "wof:name":"Paul's Appliance Svc",
    "wof:placetype":"venue"
},
  "geometry": {"coordinates":[-98.70690500000001,46.909128],"type":"Point"}
}