{
  "type": "Feature",
  "properties": {
    "iso:country":"US",
    "sg:address":"829 E Villard St",
    "sg:city":"Dickinson",
    "sg:classifiers":[
        {
            "category":"Manufacturing",
            "subcategory":"Tools & Machinery",
            "type":"Manufacturing & Wholesale Goods"
        }
    ],
    "sg:phone":"+1 701 483 5221",
    "sg:postcode":"58601",
    "sg:province":"ND",
    "sg:tags":[
        "machine",
        "shop"
    ],
    "wof:name":"Dakota Tool & Machine",
    "wof:placetype":"venue"
},
  "geometry": {"coordinates":[-102.771332,46.877809],"type":"Point"}
}