{
  "type": "Feature",
  "properties": {
    "iso:country":"US",
    "sg:address":"1701 10th Ave SE",
    "sg:city":"Mandan",
    "sg:classifiers":[
        {
            "category":"Professional",
            "subcategory":"Engineering",
            "type":"Services"
        }
    ],
    "sg:phone":"+1 701 663 1116",
    "sg:postcode":"58554",
    "sg:province":"ND",
    "sg:tags":[
        "engineer"
    ],
    "wof:name":"De Haan Grabs & Assoc",
    "wof:placetype":"venue"
},
  "geometry": {"coordinates":[-100.87715900000001,46.808333],"type":"Point"}
}