{
  "type": "Feature",
  "properties": {
    "iso:country":"US",
    "sg:address":"1410 University Ave",
    "sg:city":"Williston",
    "sg:classifiers":[
        {
            "category":"Education",
            "subcategory":"College",
            "type":"Public Place"
        }
    ],
    "sg:phone":"+1 701 774 4564",
    "sg:postcode":"58801",
    "sg:province":"ND",
    "sg:tags":[
        "academic",
        "school"
    ],
    "wof:name":"Dickinson State University",
    "wof:placetype":"venue"
},
  "geometry": {"coordinates":[-103.614919,48.157894],"type":"Point"}
}