{
  "type": "Feature",
  "properties": {
    "addr:full":"1002 Howard Ave SE Cooperstown ND 58425",
    "addr:housenumber":"1002",
    "addr:postcode":"58425",
    "addr:street":"Howard Ave Se",
    "iso:country":"US",
    "sg:address":"1002 Howard Ave SE",
    "sg:city":"Cooperstown",
    "sg:classifiers":[
        {
            "category":"Social Services",
            "subcategory":"Child Care",
            "type":"Services"
        }
    ],
    "sg:phone":"+1 701 797 2210",
    "sg:postcode":"58425",
    "sg:province":"ND",
    "sg:tags":[
        "day"
    ],
    "wof:name":"Ashlands Group Child Care",
    "wof:placetype":"venue"
},
  "geometry": {"coordinates":[-98.120812,47.440339],"type":"Point"}
}