{
  "type": "Feature",
  "properties": {
    "iso:country":"US",
    "sg:address":"318 13th Ave NE",
    "sg:city":"Jamestown",
    "sg:classifiers":[
        {
            "category":"Social Services",
            "subcategory":"Child Care",
            "type":"Services"
        }
    ],
    "sg:phone":"+1 701 252 7082",
    "sg:postcode":"58401",
    "sg:province":"ND",
    "sg:tags":[
        "day"
    ],
    "wof:name":"Cheryls Family Day Care",
    "wof:placetype":"venue"
},
  "geometry": {"coordinates":[-98.690353,46.912097],"type":"Point"}
}