{
  "type": "Feature",
  "properties": {
    "iso:country":"US",
    "sg:address":"1026 6th Ave NE",
    "sg:city":"Thompson",
    "sg:classifiers":[
        {
            "category":"Farming",
            "subcategory":"Livestock Farm",
            "type":"Manufacturing & Wholesale Goods"
        }
    ],
    "sg:phone":"+1 701 599 2986",
    "sg:postcode":"58278",
    "sg:province":"ND",
    "sg:tags":[
        "animal",
        "general"
    ],
    "wof:name":"Sannes Systems",
    "wof:placetype":"venue"
},
  "geometry": {"coordinates":[-97.051171,47.759155],"type":"Point"}
}