{
  "type": "Feature",
  "properties": {
    "iso:country":"US",
    "sg:address":"1434 11th St SE",
    "sg:city":"Jamestown",
    "sg:classifiers":[
        {
            "category":"Professional",
            "subcategory":"Testing Lab",
            "type":"Services"
        }
    ],
    "sg:phone":"+1 701 252 6567",
    "sg:postcode":"58401",
    "sg:province":"ND",
    "sg:tags":[
        "asbestos"
    ],
    "wof:name":"Asbestos Consulting",
    "wof:placetype":"venue"
},
  "geometry": {"coordinates":[-98.686874,46.89797],"type":"Point"}
}