{
  "type": "Feature",
  "properties": {
    "addr:full":"410 Franklin Ave Grand Forks ND 58201",
    "addr:housenumber":"410",
    "addr:postcode":"58201",
    "addr:street":"Franklin Ave",
    "iso:country":"US",
    "sg:address":"410 Franklin Ave",
    "sg:city":"Grand Forks",
    "sg:classifiers":[
        {
            "category":"Freight",
            "type":"Transportation"
        }
    ],
    "sg:phone":"+1 701 746 6050",
    "sg:postcode":"58201",
    "sg:province":"ND",
    "sg:tags":[
        "operator",
        "local",
        "trucking"
    ],
    "wof:name":"Grand Cities Meal Delivery",
    "wof:placetype":"venue"
},
  "geometry": {"coordinates":[-97.02598,47.92006],"type":"Point"}
}