{
  "type": "Feature",
  "properties": {
    "iso:country":"US",
    "sg:address":"256 7th St NW",
    "sg:city":"Valley City",
    "sg:phone":"+1 701 845 4032",
    "sg:postcode":"58072",
    "sg:province":"ND",
    "sg:tags":[
        "farm",
        "grain",
        "cash"
    ],
    "wof:name":"Curtis E Christianson",
    "wof:placetype":"venue"
},
  "geometry": {"coordinates":[-98.005616,46.929729],"type":"Point"}
}