{
  "type": "Feature",
  "properties": {
    "addr:full":"76 67th Ave NE Carrington ND 58421",
    "addr:housenumber":"76",
    "addr:postcode":"58421",
    "addr:street":"67Th Ave Ne",
    "iso:country":"US",
    "sg:address":"76 67th Ave NE",
    "sg:city":"Carrington",
    "sg:classifiers":[
        {
            "category":"Farming",
            "subcategory":"Farm",
            "type":"Manufacturing & Wholesale Goods"
        }
    ],
    "sg:phone":"+1 701 674 3135",
    "sg:postcode":"58421",
    "sg:province":"ND",
    "wof:name":"Randy Goheen Farm",
    "wof:placetype":"venue"
},
  "geometry": {"coordinates":[-99.1173,47.423514],"type":"Point"}
}