{
  "type": "Feature",
  "properties": {
    "addr:full":"118 1st Ave NW Ashley ND 58413",
    "addr:housenumber":"118",
    "addr:postcode":"58413",
    "addr:street":"1St Ave Nw",
    "iso:country":"US",
    "sg:address":"118 1st Ave NW",
    "sg:city":"Ashley",
    "sg:classifiers":[
        {
            "category":"Bars & Pubs",
            "type":"Food & Drink"
        }
    ],
    "sg:phone":"+1 701 288 3228",
    "sg:postcode":"58413",
    "sg:province":"ND",
    "wof:name":"Roost",
    "wof:placetype":"venue"
},
  "geometry": {"coordinates":[-99.373261,46.036396],"type":"Point"}
}