{
  "type": "Feature",
  "properties": {
    "addr:full":"400 Hillcrest Dr NE Minot ND 58703",
    "addr:housenumber":"400",
    "addr:postcode":"58703",
    "addr:street":"Hillcrest Dr Ne",
    "iso:country":"US",
    "sg:address":"400 Hillcrest Dr NE",
    "sg:city":"Minot",
    "sg:classifiers":[
        {
            "category":"Social Services",
            "subcategory":"Child Care",
            "type":"Services"
        }
    ],
    "sg:phone":"+1 701 838 4627",
    "sg:postcode":"58703",
    "sg:province":"ND",
    "sg:tags":[
        "day"
    ],
    "wof:name":"Marvels Day Care",
    "wof:placetype":"venue"
},
  "geometry": {"coordinates":[-101.28642000000001,48.24733],"type":"Point"}
}