{
  "type": "Feature",
  "properties": {
    "iso:country":"US",
    "sg:address":"121 E Arikara Ave",
    "sg:city":"Bismarck",
    "sg:classifiers":[
        {
            "category":"Insurance",
            "subcategory":"Insurance Agent",
            "type":"Services"
        }
    ],
    "sg:phone":"+1 701 221 5845",
    "sg:postcode":"58501",
    "sg:province":"ND",
    "wof:name":"AFLAC",
    "wof:placetype":"venue"
},
  "geometry": {"coordinates":[-100.788673,46.819158],"type":"Point"}
}