{
  "type": "Feature",
  "properties": {
    "addr:full":"1005 12th Ave SE Jamestown ND 58401",
    "addr:housenumber":"1005",
    "addr:postcode":"58401",
    "addr:street":"12Th Ave Se",
    "iso:country":"US",
    "sg:address":"1005 12th Ave SE",
    "sg:city":"Jamestown",
    "sg:classifiers":[
        {
            "category":"Organizations",
            "subcategory":"Professional Association",
            "type":"Services"
        }
    ],
    "sg:phone":"+1 701 252 5122",
    "sg:postcode":"58401",
    "sg:province":"ND",
    "wof:name":"American Heart Assn",
    "wof:placetype":"venue"
},
  "geometry": {"coordinates":[-98.691738,46.898472],"type":"Point"}
}