{
  "type": "Feature",
  "properties": {
    "addr:full":"4417 13th Ave SW Fargo ND 58103",
    "addr:housenumber":"4417",
    "addr:postcode":"58103",
    "addr:street":"13Th Ave Sw",
    "iso:country":"US",
    "sg:address":"4417 13th Ave SW",
    "sg:city":"Fargo",
    "sg:classifiers":[
        {
            "category":"Utilities",
            "subcategory":"Mobile Phone",
            "type":"Services"
        }
    ],
    "sg:phone":"+1 701 492 0777",
    "sg:postcode":"58103",
    "sg:province":"ND",
    "sg:tags":[
        "communication",
        "radiotelephone"
    ],
    "wof:name":"Cellular One",
    "wof:placetype":"venue"
},
  "geometry": {"coordinates":[-96.861785,46.861899],"type":"Point"}
}