{
  "type": "Feature",
  "properties": {
    "addr:full":"75 2nd Ln SW Hazen ND 58545",
    "addr:housenumber":"75",
    "addr:postcode":"58545",
    "addr:street":"2Nd Ln Sw",
    "iso:country":"US",
    "sg:address":"75 2nd Ln SW",
    "sg:city":"Hazen",
    "sg:classifiers":[
        {
            "category":"Recreation",
            "type":"Entertainment"
        }
    ],
    "sg:phone":"+1 701 487 3336",
    "sg:postcode":"58545",
    "sg:province":"ND",
    "sg:tags":[
        "guide"
    ],
    "wof:name":"Terry's Guide Svc",
    "wof:placetype":"venue"
},
  "geometry": {"coordinates":[-101.45925200000001,47.509231],"type":"Point"}
}