{
  "type": "Feature",
  "properties": {
    "iso:country":"US",
    "sg:address":"519 Main St",
    "sg:city":"Edgeley",
    "sg:classifiers":[
        {
            "category":"Health Services",
            "subcategory":"Doctor",
            "type":"Services"
        }
    ],
    "sg:phone":"+1 701 493 2388",
    "sg:postcode":"58433",
    "sg:province":"ND",
    "sg:tags":[
        "physician",
        "surgeon"
    ],
    "wof:name":"Southeast Medical Ctr",
    "wof:placetype":"venue"
},
  "geometry": {"coordinates":[-98.711406,46.360719],"type":"Point"}
}