{
  "type": "Feature",
  "properties": {
    "iso:country":"US",
    "sg:address":"1832 S Washington St",
    "sg:city":"Grand Forks",
    "sg:classifiers":[
        {
            "category":"Organizations",
            "subcategory":"Professional Association",
            "type":"Services"
        }
    ],
    "sg:phone":"+1 701 792 3333",
    "sg:postcode":"58201",
    "sg:province":"ND",
    "wof:name":"American Cancer Society",
    "wof:placetype":"venue"
},
  "geometry": {"coordinates":[-97.04558400000001,47.902683],"type":"Point"}
}