{
  "type": "Feature",
  "properties": {
    "addr:full":"1008 10th St SE Jamestown ND 58401",
    "addr:housenumber":"1008",
    "addr:postcode":"58401",
    "addr:street":"10Th St Se",
    "iso:country":"US",
    "sg:address":"1008 10th St SE",
    "sg:city":"Jamestown",
    "sg:classifiers":[
        {
            "category":"Building & Trades",
            "subcategory":"Construction",
            "type":"Services"
        }
    ],
    "sg:phone":"+1 701 252 6800",
    "sg:postcode":"58401",
    "sg:province":"ND",
    "sg:tags":[
        "general",
        "contractor"
    ],
    "wof:name":"Williams Construction",
    "wof:placetype":"venue"
},
  "geometry": {"coordinates":[-98.694467,46.898994],"type":"Point"}
}