{
  "type": "Feature",
  "properties": {
    "iso:country":"US",
    "sg:address":"19 Wiley Ave S",
    "sg:city":"Lidgerwood",
    "sg:classifiers":[
        {
            "category":"Health Services",
            "subcategory":"Doctor",
            "type":"Services"
        }
    ],
    "sg:phone":"+1 701 538 4583",
    "sg:postcode":"58053",
    "sg:province":"ND",
    "sg:tags":[
        "dentist"
    ],
    "wof:name":"Lidgerwood Dental Office",
    "wof:placetype":"venue"
},
  "geometry": {"coordinates":[-97.151887,46.075197],"type":"Point"}
}