{
  "type": "Feature",
  "properties": {
    "iso:country":"US",
    "sg:address":"601 Dakota Ave",
    "sg:city":"Wahpeton",
    "sg:classifiers":[
        {
            "category":"Manufacturing",
            "subcategory":"Printing",
            "type":"Manufacturing & Wholesale Goods"
        }
    ],
    "sg:phone":"+1 701 642 8585",
    "sg:postcode":"58075",
    "sg:province":"ND",
    "sg:tags":[
        "newspaper"
    ],
    "wof:name":"Daily News",
    "wof:placetype":"venue"
},
  "geometry": {"coordinates":[-96.60977200000001,46.263939],"type":"Point"}
}