{
  "type": "Feature",
  "properties": {
    "addr:full":"1800 16th St SW Minot ND 58701",
    "addr:housenumber":"1800",
    "addr:postcode":"58701",
    "addr:street":"16Th St Sw",
    "iso:country":"US",
    "sg:address":"1800 16th St SW",
    "sg:city":"Minot",
    "sg:classifiers":[
        {
            "category":"Professional",
            "type":"Services"
        }
    ],
    "sg:phone":"+1 701 852 5252",
    "sg:postcode":"58701",
    "sg:province":"ND",
    "sg:tags":[
        "weather",
        "establishment",
        "forecast"
    ],
    "wof:name":"Weather Forecast Minot",
    "wof:placetype":"venue"
},
  "geometry": {"coordinates":[-101.31762500000001,48.214679],"type":"Point"}
}