{
  "type": "Feature",
  "properties": {
    "iso:country":"US",
    "sg:address":"525 10th Ave S",
    "sg:city":"Carrington",
    "sg:classifiers":[
        {
            "category":"Home & Garden",
            "subcategory":"Building Materials",
            "type":"Retail Goods"
        }
    ],
    "sg:phone":"+1 701 652 3140",
    "sg:postcode":"58421",
    "sg:province":"ND",
    "sg:tags":[
        "mixed",
        "concrete"
    ],
    "wof:name":"Aggregate Industries",
    "wof:placetype":"venue"
},
  "geometry": {"coordinates":[-99.12421399999999,47.444124],"type":"Point"}
}