{
  "type": "Feature",
  "properties": {
    "iso:country":"US",
    "sg:address":"320 1st Ave SW",
    "sg:city":"Beulah",
    "sg:classifiers":[
        {
            "category":"Freight",
            "type":"Transportation"
        }
    ],
    "sg:phone":"+1 701 873 5777",
    "sg:postcode":"58523",
    "sg:province":"ND",
    "sg:tags":[
        "operator",
        "trucking"
    ],
    "wof:name":"Antelope Creek Trucking",
    "wof:placetype":"venue"
},
  "geometry": {"coordinates":[-101.779709,47.260371],"type":"Point"}
}