{
  "type": "Feature",
  "properties": {
    "iso:country":"US",
    "sg:address":"7120 97th Ave NW",
    "sg:city":"Dickinson",
    "sg:classifiers":[
        {
            "category":"Building & Trades",
            "subcategory":"Construction",
            "type":"Services"
        }
    ],
    "sg:phone":"+1 701 225 1796",
    "sg:postcode":"58601",
    "sg:province":"ND",
    "sg:tags":[
        "e",
        "well",
        "heating",
        "water",
        "source",
        "cooling",
        "drilling",
        "ground"
    ],
    "wof:name":"Gregory Water & Energy Inc",
    "wof:placetype":"venue"
},
  "geometry": {"coordinates":[-102.868595,46.90808],"type":"Point"}
}