{
  "type": "Feature",
  "properties": {
    "iso:country":"US",
    "sg:address":"4333 12th Ave N",
    "sg:city":"Fargo",
    "sg:classifiers":[
        {
            "category":"Manufacturing",
            "subcategory":"Tools & Machinery",
            "type":"Manufacturing & Wholesale Goods"
        },
        {
            "category":"Building & Trades",
            "subcategory":"Equipment Rental",
            "type":"Services"
        }
    ],
    "sg:phone":"+1 701 205 0599",
    "sg:postcode":"58102",
    "sg:province":"ND",
    "sg:tags":[
        "construction",
        "contractor",
        "yard",
        "store",
        "supply"
    ],
    "sg:website":"http://www.herculift.com",
    "wof:name":"Herc-U-Lift Inc",
    "wof:placetype":"venue"
},
  "geometry": {"coordinates":[-96.85715,46.890624],"type":"Point"}
}