{
  "type": "Feature",
  "properties": {
    "iso:country":"US",
    "sg:address":"410 3rd Ave NW",
    "sg:city":"Jamestown",
    "sg:classifiers":[
        {
            "category":"Retail",
            "subcategory":"Repair Shop",
            "type":"Services"
        }
    ],
    "sg:phone":"+1 701 252 8103",
    "sg:postcode":"58401",
    "sg:province":"ND",
    "sg:tags":[
        "upholsterer"
    ],
    "wof:name":"Brown's Upholstery",
    "wof:placetype":"venue"
},
  "geometry": {"coordinates":[-98.71162,46.912528],"type":"Point"}
}