{
  "type": "Feature",
  "properties": {
    "addr:full":"1185 S 9th St Grand Forks ND 58201",
    "addr:housenumber":"1185",
    "addr:postcode":"58201",
    "addr:street":"S 9Th St",
    "iso:country":"US",
    "sg:address":"1185 S 9th St",
    "sg:city":"Grand Forks",
    "sg:classifiers":[
        {
            "category":"Professional",
            "subcategory":"Research",
            "type":"Services"
        }
    ],
    "sg:phone":"+1 701 772 1986",
    "sg:postcode":"58201",
    "sg:province":"ND",
    "wof:name":"St Jude Research",
    "wof:placetype":"venue"
},
  "geometry": {"coordinates":[-97.038769,47.910746],"type":"Point"}
}