{
  "type": "Feature",
  "properties": {
    "addr:full":"3120 32nd St S Fargo ND 58103",
    "addr:housenumber":"3120",
    "addr:postcode":"58103",
    "addr:street":"32Nd St S",
    "iso:country":"US",
    "sg:address":"3120 32nd St S",
    "sg:city":"Fargo",
    "sg:classifiers":[
        {
            "category":"Utilities",
            "subcategory":"Telephone",
            "type":"Services"
        }
    ],
    "sg:phone":"+1 701 845 4663",
    "sg:postcode":"58103",
    "sg:province":"ND",
    "sg:tags":[
        "communications"
    ],
    "wof:name":"Jeremy Neuharth",
    "wof:placetype":"venue"
},
  "geometry": {"coordinates":[-96.830366,46.834296],"type":"Point"}
}