{
  "type": "Feature",
  "properties": {
    "addr:full":"8512 77th Ave SE Edgeley ND 58433",
    "addr:housenumber":"8512",
    "addr:postcode":"58433",
    "addr:street":"77Th Ave Se",
    "iso:country":"US",
    "sg:address":"8512 77th Ave SE",
    "sg:city":"Edgeley",
    "sg:classifiers":[
        {
            "category":"Farming",
            "subcategory":"Livestock Farm",
            "type":"Manufacturing & Wholesale Goods"
        }
    ],
    "sg:phone":"+1 701 396 7221",
    "sg:postcode":"58433",
    "sg:province":"ND",
    "sg:tags":[
        "wheat",
        "beef",
        "feedlot",
        "cattle"
    ],
    "wof:name":"Wayne Steinwand",
    "wof:placetype":"venue"
},
  "geometry": {"coordinates":[-98.775896,46.177577],"type":"Point"}
}