{
  "type": "Feature",
  "properties": {
    "iso:country":"US",
    "sg:address":"916 4th Ave",
    "sg:city":"Langdon",
    "sg:classifiers":[
        {
            "category":"Organizations",
            "subcategory":"Religious Organization",
            "type":"Services"
        }
    ],
    "sg:phone":"+1 701 256 2801",
    "sg:postcode":"58249",
    "sg:province":"ND",
    "wof:name":"Catholic Daughters of AME",
    "wof:placetype":"venue"
},
  "geometry": {"coordinates":[-98.37800799999999,48.760397],"type":"Point"}
}