{
  "type": "Feature",
  "properties": {
    "iso:country":"US",
    "sg:address":"12851 31st St SW",
    "sg:city":"Belfield",
    "sg:phone":"+1 701 575 4834",
    "sg:postcode":"58622",
    "sg:province":"ND",
    "sg:tags":[
        "wheat",
        "beef",
        "farm",
        "corn",
        "cattle",
        "feedlot"
    ],
    "wof:name":"Victor Cymbaluk",
    "wof:placetype":"venue"
},
  "geometry": {"coordinates":[-103.147451,46.963219],"type":"Point"}
}