{
  "type": "Feature",
  "properties": {
    "addr:full":"900 16th St SW Minot ND 58701",
    "addr:housenumber":"900",
    "addr:postcode":"58701",
    "addr:street":"16Th St Sw",
    "iso:country":"US",
    "sg:address":"900 16th St SW",
    "sg:city":"Minot",
    "sg:classifiers":[
        {
            "category":"Government",
            "subcategory":"Office",
            "type":"Public Place"
        }
    ],
    "sg:phone":"+1 701 857 4760",
    "sg:postcode":"58701",
    "sg:province":"ND",
    "sg:tags":[
        "govt",
        "city"
    ],
    "wof:name":"Water Treatment Plant",
    "wof:placetype":"venue"
},
  "geometry": {"coordinates":[-101.31470299999999,48.227968],"type":"Point"}
}