{
  "type": "Feature",
  "properties": {
    "iso:country":"US",
    "sg:address":"1116 12th Ave SW",
    "sg:city":"Minot",
    "sg:classifiers":[
        {
            "category":"Shopping",
            "type":"Retail Goods"
        }
    ],
    "sg:phone":"+1 701 852 5407",
    "sg:postcode":"58701",
    "sg:province":"ND",
    "sg:tags":[
        "contractor",
        "electrical",
        "merchandise",
        "consult"
    ],
    "wof:name":"Security Plus",
    "wof:placetype":"venue"
},
  "geometry": {"coordinates":[-101.30802300000001,48.22393],"type":"Point"}
}