{
  "type": "Feature",
  "properties": {
    "addr:full":"728 Hill Ave Grafton ND 58237",
    "addr:housenumber":"728",
    "addr:postcode":"58237",
    "addr:street":"Hill Ave",
    "iso:country":"US",
    "sg:address":"728 Hill Ave",
    "sg:city":"Grafton",
    "sg:classifiers":[
        {
            "category":"Social Services",
            "type":"Services"
        }
    ],
    "sg:phone":"+1 701 352 1667",
    "sg:postcode":"58237",
    "sg:province":"ND",
    "sg:tags":[
        "counselor",
        "marriage",
        "family"
    ],
    "wof:name":"Mab Addiction Counseling Svc",
    "wof:placetype":"venue"
},
  "geometry": {"coordinates":[-97.411074,48.417265],"type":"Point"}
}