{
  "type": "Feature",
  "properties": {
    "addr:full":"119 S Elm St Hebron ND 58638",
    "addr:housenumber":"119",
    "addr:postcode":"58638",
    "addr:street":"S Elm St",
    "iso:country":"US",
    "sg:address":"119 S Elm St",
    "sg:city":"Hebron",
    "sg:classifiers":[
        {
            "category":"Personal",
            "subcategory":"Beauty Salon",
            "type":"Services"
        }
    ],
    "sg:phone":"+1 701 878 4262",
    "sg:postcode":"58638",
    "sg:province":"ND",
    "sg:tags":[
        "shop"
    ],
    "wof:name":"Homestyling Hair & Tan Salon",
    "wof:placetype":"venue"
},
  "geometry": {"coordinates":[-102.042253,46.900884],"type":"Point"}
}