{
  "type": "Feature",
  "properties": {
    "iso:country":"US",
    "sg:address":"2125 Sims St",
    "sg:city":"Dickinson",
    "sg:classifiers":[
        {
            "category":"Wholesale",
            "subcategory":"Electrical",
            "type":"Manufacturing & Wholesale Goods"
        }
    ],
    "sg:phone":"+1 701 225 9608",
    "sg:postcode":"58601",
    "sg:province":"ND",
    "sg:tags":[
        "communication",
        "radio",
        "system"
    ],
    "wof:name":"R & J Communications Co",
    "wof:placetype":"venue"
},
  "geometry": {"coordinates":[-102.785034,46.905905],"type":"Point"}
}