{
  "type": "Feature",
  "properties": {
    "iso:country":"US",
    "sg:address":"8700 36th St SE",
    "sg:city":"Jamestown",
    "sg:classifiers":[
        {
            "category":"Organizations",
            "subcategory":"Membership Organization",
            "type":"Services"
        }
    ],
    "sg:phone":"+1 701 252 0747",
    "sg:postcode":"58401",
    "sg:province":"ND",
    "sg:tags":[
        "society",
        "humane"
    ],
    "wof:name":"James River Humane Society",
    "wof:placetype":"venue"
},
  "geometry": {"coordinates":[-98.629357,46.892196],"type":"Point"}
}