{
  "type": "Feature",
  "properties": {
    "iso:country":"US",
    "sg:address":"602 College Dr S",
    "sg:city":"Devils Lake",
    "sg:classifiers":[
        {
            "category":"Professional",
            "subcategory":"Accounting & Tax Preparation",
            "type":"Services"
        }
    ],
    "sg:phone":"+1 701 662 4704",
    "sg:postcode":"58301",
    "sg:province":"ND",
    "sg:tags":[
        "accountant"
    ],
    "wof:name":"Emil Schoenfish CPA",
    "wof:placetype":"venue"
},
  "geometry": {"coordinates":[-98.86408,48.103653],"type":"Point"}
}