{
  "type": "Feature",
  "properties": {
    "iso:country":"US",
    "sg:address":"200 3rd Ave W",
    "sg:city":"Richardton",
    "sg:classifiers":[
        {
            "category":"Health Services",
            "subcategory":"Doctor",
            "type":"Services"
        }
    ],
    "sg:phone":"+1 701 974 2118",
    "sg:postcode":"58652",
    "sg:province":"ND",
    "sg:tags":[
        "dentist"
    ],
    "wof:name":"Richardton Dental Clinic",
    "wof:placetype":"venue"
},
  "geometry": {"coordinates":[-102.317205,46.887909],"type":"Point"}
}