{
  "type": "Feature",
  "properties": {
    "iso:country":"US",
    "sg:address":"3003 32nd St S",
    "sg:city":"Fargo",
    "sg:classifiers":[
        {
            "category":"Health Services",
            "subcategory":"Doctor",
            "type":"Services"
        }
    ],
    "sg:phone":"+1 701 293 8101",
    "sg:postcode":"58103",
    "sg:province":"ND",
    "sg:tags":[
        "surgery",
        "eye",
        "center"
    ],
    "wof:name":"Valley Laser Eye Center",
    "wof:placetype":"venue"
},
  "geometry": {"coordinates":[-96.83045199999999,46.836878],"type":"Point"}
}