{
  "type": "Feature",
  "properties": {
    "addr:full":"3435 S 10th St Grand Forks ND 58201",
    "addr:housenumber":"3435",
    "addr:postcode":"58201",
    "addr:street":"S 10Th St",
    "iso:country":"US",
    "sg:address":"3435 S 10th St",
    "sg:city":"Grand Forks",
    "sg:classifiers":[
        {
            "category":"Building & Trades",
            "subcategory":"Construction",
            "type":"Services"
        }
    ],
    "sg:phone":"+1 701 772 8295",
    "sg:postcode":"58201",
    "sg:province":"ND",
    "sg:tags":[
        "excavation",
        "contractor"
    ],
    "wof:name":"Dennis J Duray",
    "wof:placetype":"venue"
},
  "geometry": {"coordinates":[-97.039755,47.885898],"type":"Point"}
}