{
  "type": "Feature",
  "properties": {
    "iso:country":"US",
    "sg:address":"920 24th Ave NW",
    "sg:city":"Coleharbor",
    "sg:phone":"+1 701 448 2595",
    "sg:postcode":"58531",
    "sg:province":"ND",
    "sg:tags":[
        "farm",
        "wheat"
    ],
    "wof:name":"Herbert Nathan Farm",
    "wof:placetype":"venue"
},
  "geometry": {"coordinates":[-101.036064,47.550526],"type":"Point"}
}