{
  "type": "Feature",
  "properties": {
    "iso:country":"US",
    "sg:address":"401 43rd St N",
    "sg:city":"Fargo",
    "sg:classifiers":[
        {
            "category":"Freight",
            "type":"Transportation"
        }
    ],
    "sg:phone":"+1 701 280 2285",
    "sg:postcode":"58102",
    "sg:province":"ND",
    "sg:tags":[
        "trucking"
    ],
    "wof:name":"ABF Freight System Inc",
    "wof:placetype":"venue"
},
  "geometry": {"coordinates":[-96.85737899999999,46.88128],"type":"Point"}
}