{
  "type": "Feature",
  "properties": {
    "addr:full":"3451 32nd Ave S Grand Forks ND 58201",
    "addr:housenumber":"3451",
    "addr:postcode":"58201",
    "addr:street":"32Nd Ave S",
    "iso:country":"US",
    "sg:address":"3451 32nd Ave S",
    "sg:city":"Grand Forks",
    "sg:classifiers":[
        {
            "category":"Ice Cream",
            "type":"Food & Drink"
        }
    ],
    "sg:menulink":"http://www.allmenus.com/nd/grand-forks/182891-culvers/menu/",
    "sg:phone":"+1 701 772 9199",
    "sg:postcode":"58201",
    "sg:province":"ND",
    "sg:tags":[
        "burger",
        "american"
    ],
    "wof:name":"Culver's",
    "wof:placetype":"venue"
},
  "geometry": {"coordinates":[-97.07803,47.889387],"type":"Point"}
}