{
  "type": "Feature",
  "properties": {
    "addr:full":"1700 River Rd Bismarck ND 58503",
    "addr:housenumber":"1700",
    "addr:postcode":"58503",
    "addr:street":"River Rd",
    "iso:country":"US",
    "sg:address":"1700 River Rd",
    "sg:city":"Bismarck",
    "sg:classifiers":[
        {
            "category":"Restaurant",
            "type":"Food & Drink"
        }
    ],
    "sg:phone":"+1 701 258 0666",
    "sg:postcode":"58503",
    "sg:province":"ND",
    "wof:name":"Meriwether's",
    "wof:placetype":"venue"
},
  "geometry": {"coordinates":[-100.832515,46.832419],"type":"Point"}
}