{
  "type": "Feature",
  "properties": {
    "iso:country":"US",
    "sg:address":"821 Dakota Ave",
    "sg:city":"Wahpeton",
    "sg:classifiers":[
        {
            "category":"Autos & Motor Vehicles",
            "subcategory":"Fuel & Gas Station",
            "type":"Retail Goods"
        }
    ],
    "sg:phone":"+1 701 642 8530",
    "sg:postcode":"58075",
    "sg:province":"ND",
    "sg:tags":[
        "oil"
    ],
    "wof:name":"Wahpeton Amoco",
    "wof:placetype":"venue"
},
  "geometry": {"coordinates":[-96.612511,46.263852],"type":"Point"}
}