{
  "type": "Feature",
  "properties": {
    "iso:country":"US",
    "sg:address":"13911 51st St NW",
    "sg:city":"Williston",
    "sg:classifiers":[
        {
            "category":"Building & Trades",
            "subcategory":"Plumbing",
            "type":"Services"
        }
    ],
    "sg:phone":"+1 701 572 8892",
    "sg:postcode":"58801",
    "sg:province":"ND",
    "sg:tags":[
        "contractor"
    ],
    "wof:name":"Roto-Rooter",
    "wof:placetype":"venue"
},
  "geometry": {"coordinates":[-103.69526500000001,48.154205],"type":"Point"}
}