{
  "type": "Feature",
  "properties": {
    "iso:country":"US",
    "sg:address":"803 3rd Ave NW",
    "sg:city":"Jamestown",
    "sg:classifiers":[
        {
            "category":"Bars & Pubs",
            "type":"Food & Drink"
        }
    ],
    "sg:phone":"+1 701 252 9192",
    "sg:postcode":"58401",
    "sg:province":"ND",
    "wof:name":"Hitching Post",
    "wof:placetype":"venue"
},
  "geometry": {"coordinates":[-98.711923,46.916918],"type":"Point"}
}