{
  "type": "Feature",
  "properties": {
    "iso:country":"US",
    "sg:address":"4395 145th Ave SE",
    "sg:city":"Wheatland",
    "sg:classifiers":[
        {
            "category":"Wholesale",
            "subcategory":"Construction Materials",
            "type":"Manufacturing & Wholesale Goods"
        }
    ],
    "sg:phone":"+1 701 633 5537",
    "sg:postcode":"58079",
    "sg:province":"ND",
    "wof:name":"Camas Sand & Gravel",
    "wof:placetype":"venue"
},
  "geometry": {"coordinates":[-97.430002,46.775335],"type":"Point"}
}