{
  "type": "Feature",
  "properties": {
    "addr:full":"633 1st Ave N Fargo ND 58102",
    "addr:housenumber":"633",
    "addr:postcode":"58102",
    "addr:street":"1St Ave N",
    "iso:country":"US",
    "sg:address":"633 1st Ave N",
    "sg:city":"Fargo",
    "sg:classifiers":[
        {
            "category":"Professional",
            "subcategory":"Research",
            "type":"Services"
        }
    ],
    "sg:phone":"+1 701 298 7979",
    "sg:postcode":"58102",
    "sg:province":"ND",
    "sg:tags":[
        "foundation",
        "philanthropic"
    ],
    "wof:name":"Dacotah Pioneer Supervisor",
    "wof:placetype":"venue"
},
  "geometry": {"coordinates":[-96.789653,46.877006],"type":"Point"}
}