{
  "type": "Feature",
  "properties": {
    "iso:country":"US",
    "sg:address":"12791 56th St NE",
    "sg:city":"Fordville",
    "sg:classifiers":[
        {
            "category":"Farming",
            "subcategory":"Livestock Farm",
            "type":"Manufacturing & Wholesale Goods"
        }
    ],
    "sg:phone":"+1 701 229 3204",
    "sg:postcode":"58231",
    "sg:province":"ND",
    "sg:tags":[
        "beef",
        "feedlot",
        "cattle"
    ],
    "wof:name":"Melvin Amundson",
    "wof:placetype":"venue"
},
  "geometry": {"coordinates":[-97.862927,48.223961],"type":"Point"}
}