{
  "type": "Feature",
  "properties": {
    "iso:country":"US",
    "sg:address":"902 Burrel Ave SE",
    "sg:city":"Cooperstown",
    "sg:classifiers":[
        {
            "category":"Education",
            "subcategory":"Library",
            "type":"Public Place"
        }
    ],
    "sg:phone":"+1 701 797 2214",
    "sg:postcode":"58425",
    "sg:province":"ND",
    "wof:name":"Griggs County Library",
    "wof:placetype":"venue"
},
  "geometry": {"coordinates":[-98.123836,47.444484],"type":"Point"}
}