{
  "type": "Feature",
  "properties": {
    "addr:full":"1408 20th Ave SW Minot ND 58701",
    "addr:housenumber":"1408",
    "addr:postcode":"58701",
    "addr:street":"20Th Ave Sw",
    "iso:country":"US",
    "sg:address":"1408 20th Ave SW",
    "sg:city":"Minot",
    "sg:classifiers":[
        {
            "category":"Freight",
            "type":"Transportation"
        }
    ],
    "sg:phone":"+1 701 837 4875",
    "sg:postcode":"58701",
    "sg:province":"ND",
    "sg:tags":[
        "grain",
        "elevator"
    ],
    "wof:name":"James Richardson Intl Inc",
    "wof:placetype":"venue"
},
  "geometry": {"coordinates":[-101.314864,48.211187],"type":"Point"}
}