{
  "type": "Feature",
  "properties": {
    "iso:country":"US",
    "sg:address":"4 Cedar Ave",
    "sg:city":"Fargo",
    "sg:classifiers":[
        {
            "category":"Shopping",
            "subcategory":"Gifts & Souvenirs",
            "type":"Retail Goods"
        }
    ],
    "sg:phone":"+1 701 235 7458",
    "sg:postcode":"58102",
    "sg:province":"ND",
    "wof:name":"Munch N More Candy Co",
    "wof:placetype":"venue"
},
  "geometry": {"coordinates":[-96.778762,46.915927],"type":"Point"}
}