{
  "type": "Feature",
  "properties": {
    "addr:full":"966 Industrial Dr Bismarck ND 58501",
    "addr:housenumber":"966",
    "addr:postcode":"58501",
    "addr:street":"Industrial Dr",
    "iso:country":"US",
    "sg:address":"966 Industrial Dr",
    "sg:city":"Bismarck",
    "sg:classifiers":[
        {
            "category":"Manufacturing",
            "subcategory":"Building Materials",
            "type":"Manufacturing & Wholesale Goods"
        }
    ],
    "sg:phone":"+1 701 224 8060",
    "sg:postcode":"58501",
    "sg:province":"ND",
    "sg:website":"www.jsspecialties.com",
    "wof:name":"Dakota Mill Work",
    "wof:placetype":"venue"
},
  "geometry": {"coordinates":[-100.73128800000001,46.816819],"type":"Point"}
}