{
  "type": "Feature",
  "properties": {
    "addr:full":"2700 State St Bismarck ND 58503",
    "addr:housenumber":"2700",
    "addr:postcode":"58503",
    "addr:street":"State St",
    "iso:country":"US",
    "sg:address":"2700 State St",
    "sg:city":"Bismarck",
    "sg:classifiers":[
        {
            "category":"Restaurant",
            "type":"Food & Drink"
        }
    ],
    "sg:phone":"+1 701 258 9955",
    "sg:postcode":"58503",
    "sg:province":"ND",
    "sg:tags":[
        "eating"
    ],
    "wof:name":"Asian Buffet",
    "wof:placetype":"venue"
},
  "geometry": {"coordinates":[-100.773132,46.83627],"type":"Point"}
}