{
  "type": "Feature",
  "properties": {
    "iso:country":"US",
    "sg:address":"6630 N Star Acres Rd",
    "sg:city":"Bismarck",
    "sg:classifiers":[
        {
            "category":"Building & Trades",
            "subcategory":"Construction",
            "type":"Services"
        }
    ],
    "sg:phone":"+1 701 223 1621",
    "sg:postcode":"58503",
    "sg:province":"ND",
    "sg:tags":[
        "house"
    ],
    "wof:name":"Erhardt Construction",
    "wof:placetype":"venue"
},
  "geometry": {"coordinates":[-100.756275,46.88146],"type":"Point"}
}