{
  "type": "Feature",
  "properties": {
    "iso:country":"US",
    "sg:address":"7535 61st St SW",
    "sg:city":"New Leipzig",
    "sg:phone":"+1 701 584 2864",
    "sg:postcode":"58562",
    "sg:province":"ND",
    "sg:tags":[
        "farm",
        "wheat",
        "beef",
        "feedlot",
        "cattle"
    ],
    "wof:name":"C Schatz",
    "wof:placetype":"venue"
},
  "geometry": {"coordinates":[-101.994849,46.529864],"type":"Point"}
}