{
  "type": "Feature",
  "properties": {
    "addr:full":"129 2nd St NE Rugby ND 58368",
    "addr:housenumber":"129",
    "addr:postcode":"58368",
    "addr:street":"2Nd St Ne",
    "iso:country":"US",
    "sg:address":"129 2nd St NE",
    "sg:city":"Rugby",
    "sg:classifiers":[
        {
            "category":"Organizations",
            "subcategory":"Religious Organization",
            "type":"Services"
        }
    ],
    "sg:phone":"+1 701 776 5740",
    "sg:postcode":"58368",
    "sg:province":"ND",
    "wof:name":"Kingdom Hall Jhovahs Witnesses",
    "wof:placetype":"venue"
},
  "geometry": {"coordinates":[-99.995676,48.372269],"type":"Point"}
}