{
  "type": "Feature",
  "properties": {
    "iso:country":"US",
    "sg:address":"1042 14th Ave E",
    "sg:city":"West Fargo",
    "sg:classifiers":[
        {
            "category":"Wholesale",
            "subcategory":"Metals & Minerals",
            "type":"Manufacturing & Wholesale Goods"
        }
    ],
    "sg:phone":"+1 701 282 8282",
    "sg:postcode":"58078",
    "sg:province":"ND",
    "sg:tags":[
        "coal",
        "by",
        "reseller"
    ],
    "wof:name":"Ceres",
    "wof:placetype":"venue"
},
  "geometry": {"coordinates":[-96.88178000000001,46.860701],"type":"Point"}
}