{
  "type": "Feature",
  "properties": {
    "addr:full":"3140 34th Ave NE Harvey ND 58341",
    "addr:housenumber":"3140",
    "addr:postcode":"58341",
    "addr:street":"34Th Ave Ne",
    "iso:country":"US",
    "sg:address":"3140 34th Ave NE",
    "sg:city":"Harvey",
    "sg:classifiers":[
        {
            "category":"Real Estate",
            "subcategory":"Real Estate Operator",
            "type":"Services"
        }
    ],
    "sg:phone":"+1 701 324 2720",
    "sg:postcode":"58341",
    "sg:province":"ND",
    "sg:tags":[
        "property",
        "lessor"
    ],
    "wof:name":"Andy Axtman",
    "wof:placetype":"venue"
},
  "geometry": {"coordinates":[-99.85524700000001,47.868139],"type":"Point"}
}