{
  "type": "Feature",
  "properties": {
    "iso:country":"US",
    "sg:address":"4997 13th Ave NE",
    "sg:city":"Rugby",
    "sg:classifiers":[
        {
            "category":"Farming",
            "subcategory":"Livestock Farm",
            "type":"Manufacturing & Wholesale Goods"
        }
    ],
    "sg:phone":"+1 701 537 5248",
    "sg:postcode":"58368",
    "sg:province":"ND",
    "sg:tags":[
        "beef",
        "feedlot",
        "cattle"
    ],
    "wof:name":"Daniel Kuntz",
    "wof:placetype":"venue"
},
  "geometry": {"coordinates":[-100.30200600000001,48.137415],"type":"Point"}
}