{
  "type": "Feature",
  "properties": {
    "iso:country":"US",
    "sg:address":"2823 US Hwy 2",
    "sg:city":"Rugby",
    "sg:classifiers":[
        {
            "category":"Freight",
            "type":"Transportation"
        }
    ],
    "sg:phone":"+1 701 776 5701",
    "sg:postcode":"58368",
    "sg:province":"ND",
    "sg:tags":[
        "carrier",
        "common",
        "contract"
    ],
    "sg:website":"www.centralcarriers.com",
    "wof:name":"Central Carriers Inc",
    "wof:placetype":"venue"
},
  "geometry": {"coordinates":[-100.012401,48.354925],"type":"Point"}
}