{
  "type": "Feature",
  "properties": {
    "iso:country":"US",
    "sg:address":"1614 Bison Dr",
    "sg:city":"Williston",
    "sg:classifiers":[
        {
            "category":"Professional",
            "subcategory":"Lawyer & Legal Services",
            "type":"Services"
        }
    ],
    "sg:phone":"+1 701 774 3212",
    "sg:postcode":"58801",
    "sg:province":"ND",
    "sg:tags":[
        "attorney"
    ],
    "wof:name":"Harley D Brakey",
    "wof:placetype":"venue"
},
  "geometry": {"coordinates":[-103.64772000000001,48.161538],"type":"Point"}
}