{
  "type": "Feature",
  "properties": {
    "iso:country":"US",
    "sg:address":"4258 3rd Ave NW",
    "sg:city":"Fargo",
    "sg:classifiers":[
        {
            "category":"Utilities",
            "subcategory":"Electric",
            "type":"Services"
        }
    ],
    "sg:phone":"+1 701 232 7670",
    "sg:postcode":"58102",
    "sg:province":"ND",
    "sg:tags":[
        "company"
    ],
    "wof:name":"Design Solutions & Integratio",
    "wof:placetype":"venue"
},
  "geometry": {"coordinates":[-96.85458800000001,46.880302],"type":"Point"}
}