{
  "type": "Feature",
  "properties": {
    "iso:country":"US",
    "sg:address":"11 15th St S",
    "sg:city":"Fargo",
    "sg:classifiers":[
        {
            "category":"Wholesale",
            "subcategory":"Durable Goods & Equipment",
            "type":"Manufacturing & Wholesale Goods"
        }
    ],
    "sg:phone":"+1 701 237 6006",
    "sg:postcode":"58103",
    "sg:province":"ND",
    "sg:tags":[
        "fire",
        "extinguisher"
    ],
    "wof:name":"Hintz Fire Equipment Inc",
    "wof:placetype":"venue"
},
  "geometry": {"coordinates":[-96.804059,46.87489],"type":"Point"}
}