{
  "type": "Feature",
  "properties": {
    "iso:country":"US",
    "sg:address":"3297 4th St SW",
    "sg:city":"Washburn",
    "sg:classifiers":[
        {
            "category":"Organizations",
            "subcategory":"Religious Organization",
            "type":"Services"
        }
    ],
    "sg:phone":"+1 701 462 8433",
    "sg:postcode":"58577",
    "sg:province":"ND",
    "sg:tags":[
        "church"
    ],
    "wof:name":"Birka Lutheran Church",
    "wof:placetype":"venue"
},
  "geometry": {"coordinates":[-101.289928,47.357065],"type":"Point"}
}