{
  "type": "Feature",
  "properties": {
    "iso:country":"US",
    "sg:address":"1860 73rd St SE",
    "sg:city":"Linton",
    "sg:classifiers":[
        {
            "category":"Farming",
            "subcategory":"Farm",
            "type":"Manufacturing & Wholesale Goods"
        }
    ],
    "sg:phone":"+1 701 782 4213",
    "sg:postcode":"58552",
    "sg:province":"ND",
    "sg:tags":[
        "crop",
        "general"
    ],
    "wof:name":"Kevin Bernhardt",
    "wof:placetype":"venue"
},
  "geometry": {"coordinates":[-100.011478,46.35597],"type":"Point"}
}