{
  "type": "Feature",
  "properties": {
    "addr:full":"4220 74th Ave Hebron ND 58638",
    "addr:housenumber":"4220",
    "addr:postcode":"58638",
    "addr:street":"74Th Ave",
    "iso:country":"US",
    "sg:address":"4220 74th Ave",
    "sg:city":"Hebron",
    "sg:phone":"+1 701 878 4529",
    "sg:postcode":"58638",
    "sg:province":"ND",
    "sg:tags":[
        "farm",
        "wheat"
    ],
    "wof:name":"Miles Schantz",
    "wof:placetype":"venue"
},
  "geometry": {"coordinates":[-102.01252100000001,46.799057],"type":"Point"}
}