{
  "type": "Feature",
  "properties": {
    "iso:country":"US",
    "sg:address":"8211 52nd St NE",
    "sg:city":"Devils Lake",
    "sg:classifiers":[
        {
            "category":"Retail",
            "subcategory":"Repair Shop",
            "type":"Services"
        }
    ],
    "sg:phone":"+1 701 662 8334",
    "sg:postcode":"58301",
    "sg:province":"ND",
    "sg:tags":[
        "repairing",
        "piano",
        "refinishing"
    ],
    "wof:name":"Petska Piano Svc",
    "wof:placetype":"venue"
},
  "geometry": {"coordinates":[-98.851873,48.165822],"type":"Point"}
}