{
  "type": "Feature",
  "properties": {
    "iso:country":"US",
    "sg:address":"1007 Main Ave W",
    "sg:city":"West Fargo",
    "sg:classifiers":[
        {
            "category":"Building & Trades",
            "subcategory":"Construction",
            "type":"Services"
        }
    ],
    "sg:phone":"+1 701 277 1002",
    "sg:postcode":"58078",
    "sg:province":"ND",
    "sg:tags":[
        "masonry",
        "contractor"
    ],
    "wof:name":"Gabel Masonry Construction Inc",
    "wof:placetype":"venue"
},
  "geometry": {"coordinates":[-96.917547,46.876959],"type":"Point"}
}