{
  "type": "Feature",
  "properties": {
    "iso:country":"US",
    "sg:address":"207 1st Ave NE",
    "sg:city":"Mandan",
    "sg:classifiers":[
        {
            "category":"Personal",
            "type":"Services"
        }
    ],
    "sg:phone":"+1 701 250 0119",
    "sg:postcode":"58554",
    "sg:province":"ND",
    "sg:tags":[
        "therapist",
        "massage"
    ],
    "wof:name":"Tri One Massage",
    "wof:placetype":"venue"
},
  "geometry": {"coordinates":[-100.888875,46.828658],"type":"Point"}
}