{
  "type": "Feature",
  "properties": {
    "addr:full":"4014 15th Ave N Fargo ND 58102",
    "addr:housenumber":"4014",
    "addr:postcode":"58102",
    "addr:street":"15Th Ave N",
    "iso:country":"US",
    "sg:address":"4014 15th Ave N",
    "sg:city":"Fargo",
    "sg:classifiers":[
        {
            "category":"Manufacturing",
            "subcategory":"Pet Food",
            "type":"Manufacturing & Wholesale Goods"
        }
    ],
    "sg:phone":"+1 701 282 9656",
    "sg:postcode":"58102",
    "sg:province":"ND",
    "sg:tags":[
        "milling"
    ],
    "sg:website":"www.romanmealmilling.com",
    "wof:name":"Roman Meal Milling Co",
    "wof:placetype":"venue"
},
  "geometry": {"coordinates":[-96.850483,46.897199],"type":"Point"}
}