{
  "type": "Feature",
  "properties": {
    "iso:country":"US",
    "sg:address":"501 Main St W",
    "sg:city":"Hazen",
    "sg:classifiers":[
        {
            "category":"Manufacturing",
            "subcategory":"Tools & Machinery",
            "type":"Manufacturing & Wholesale Goods"
        }
    ],
    "sg:phone":"+1 701 748 5614",
    "sg:postcode":"58545",
    "sg:province":"ND",
    "sg:tags":[
        "machine",
        "shop"
    ],
    "wof:name":"Hazen Welding & Machine",
    "wof:placetype":"venue"
},
  "geometry": {"coordinates":[-101.637745,47.294703],"type":"Point"}
}