{
  "type": "Feature",
  "properties": {
    "iso:country":"US",
    "sg:address":"7495 85th St NE",
    "sg:city":"Egeland",
    "sg:classifiers":[
        {
            "category":"Farming",
            "subcategory":"Livestock Farm",
            "type":"Manufacturing & Wholesale Goods"
        }
    ],
    "sg:phone":"+1 701 266 5403",
    "sg:postcode":"58331",
    "sg:province":"ND",
    "sg:tags":[
        "beef",
        "feedlot",
        "cattle"
    ],
    "wof:name":"Blake Karbell",
    "wof:placetype":"venue"
},
  "geometry": {"coordinates":[-99.045648,48.645668],"type":"Point"}
}