{
  "type": "Feature",
  "properties": {
    "addr:full":"17075 Co Rd 15 Hankinson ND 58075",
    "addr:housenumber":"17075;15",
    "addr:postcode":"58075",
    "addr:street":"Co Rd",
    "iso:country":"US",
    "sg:address":"17075 Co Rd 15",
    "sg:city":"Hankinson",
    "sg:classifiers":[
        {
            "category":"Travel",
            "subcategory":"Travel Agent",
            "type":"Entertainment"
        }
    ],
    "sg:phone":"+1 701 545 7526",
    "sg:postcode":"58075",
    "sg:province":"ND",
    "sg:tags":[
        "agency"
    ],
    "wof:name":"Dreamtime Travel",
    "wof:placetype":"venue"
},
  "geometry": {"coordinates":[-96.83144,46.080528],"type":"Point"}
}