{
  "type": "Feature",
  "properties": {
    "iso:country":"US",
    "sg:address":"11741 54th St NE",
    "sg:city":"Michigan",
    "sg:phone":"+1 701 259 2523",
    "sg:postcode":"58250",
    "sg:province":"ND",
    "sg:tags":[
        "farm",
        "wheat"
    ],
    "wof:name":"Jeff Moen",
    "wof:placetype":"venue"
},
  "geometry": {"coordinates":[-98.089235,48.194779],"type":"Point"}
}