{
  "type": "Feature",
  "properties": {
    "iso:country":"US",
    "sg:address":"2322 W Front St",
    "sg:city":"Williston",
    "sg:classifiers":[
        {
            "category":"Bars & Pubs",
            "type":"Food & Drink"
        }
    ],
    "sg:phone":"+1 701 572 4153",
    "sg:postcode":"58801",
    "sg:province":"ND",
    "wof:name":"Midway Junction",
    "wof:placetype":"venue"
},
  "geometry": {"coordinates":[-103.655995,48.144115],"type":"Point"}
}