{
  "type": "Feature",
  "properties": {
    "addr:full":"1650 17th Ave NW Turtle Lake ND 58575",
    "addr:housenumber":"1650",
    "addr:postcode":"58575",
    "addr:street":"17Th Ave Nw Turtle",
    "iso:country":"US",
    "sg:address":"1650 17th Ave NW",
    "sg:city":"Turtle Lake",
    "sg:classifiers":[
        {
            "category":"Organizations",
            "subcategory":"Non-profit Organization",
            "type":"Services"
        }
    ],
    "sg:phone":"+1 701 448 2848",
    "sg:postcode":"58575",
    "sg:province":"ND",
    "wof:name":"Midwest Assistance Program",
    "wof:placetype":"venue"
},
  "geometry": {"coordinates":[-100.907617,47.65745],"type":"Point"}
}