{
  "type": "Feature",
  "properties": {
    "iso:country":"US",
    "sg:address":"4902 16th Ave S",
    "sg:city":"Fargo",
    "sg:classifiers":[
        {
            "category":"Real Estate",
            "subcategory":"Real Estate Operator",
            "type":"Services"
        }
    ],
    "sg:phone":"+1 701 277 9481",
    "sg:postcode":"58103",
    "sg:province":"ND",
    "sg:tags":[
        "building",
        "apartment"
    ],
    "wof:name":"Skaff Apts",
    "wof:placetype":"venue"
},
  "geometry": {"coordinates":[-96.86918799999999,46.857099],"type":"Point"}
}