{
  "type": "Feature",
  "properties": {
    "iso:country":"US",
    "sg:address":"1300 E Main St",
    "sg:city":"Mandan",
    "sg:classifiers":[
        {
            "category":"Autos & Motor Vehicles",
            "subcategory":"Fuel & Gas Station",
            "type":"Retail Goods"
        }
    ],
    "sg:phone":"+1 701 663 6985",
    "sg:postcode":"58554",
    "sg:province":"ND",
    "sg:tags":[
        "filling",
        "station",
        "convenience",
        "store"
    ],
    "sg:website":"www.stamart.com",
    "wof:name":"Stamart",
    "wof:placetype":"venue"
},
  "geometry": {"coordinates":[-100.872433,46.828762],"type":"Point"}
}