{
  "type": "Feature",
  "properties": {
    "addr:full":"305 4th Ave NW Hettinger ND 58639",
    "addr:housenumber":"305",
    "addr:postcode":"hettinger;58639",
    "addr:street":"4Th Ave Nw",
    "iso:country":"US",
    "sg:address":"305 4th Ave NW",
    "sg:city":"Hettinger",
    "sg:classifiers":[
        {
            "category":"Farming",
            "subcategory":"Livestock Farm",
            "type":"Manufacturing & Wholesale Goods"
        }
    ],
    "sg:phone":"+1 701 567 2676",
    "sg:postcode":"58639",
    "sg:province":"ND",
    "sg:tags":[
        "beef",
        "feedlot",
        "cattle"
    ],
    "wof:name":"Thomas Arndorfe",
    "wof:placetype":"venue"
},
  "geometry": {"coordinates":[-102.68476,46.046358],"type":"Point"}
}