{
  "type": "Feature",
  "properties": {
    "iso:country":"US",
    "sg:address":"304 Dakota Ave",
    "sg:city":"Wahpeton",
    "sg:classifiers":[
        {
            "category":"Bars & Pubs",
            "type":"Food & Drink"
        }
    ],
    "sg:phone":"+1 701 642 2296",
    "sg:postcode":"58075",
    "sg:province":"ND",
    "wof:name":"Sportsman's Lounge",
    "wof:placetype":"venue"
},
  "geometry": {"coordinates":[-96.605447,46.263993],"type":"Point"}
}