{
  "type": "Feature",
  "properties": {
    "addr:full":"105 W Shipley Ave Binford ND 58416",
    "addr:housenumber":"105",
    "addr:postcode":"58416",
    "addr:street":"W Shipley Ave",
    "iso:country":"US",
    "sg:address":"105 W Shipley Ave",
    "sg:city":"Binford",
    "sg:classifiers":[
        {
            "category":"Retail",
            "subcategory":"Auto Repair",
            "type":"Services"
        }
    ],
    "sg:phone":"+1 701 676 2301",
    "sg:postcode":"58416",
    "sg:province":"ND",
    "sg:tags":[
        "repairing",
        "automobile"
    ],
    "wof:name":"Edlund Motor Co",
    "wof:placetype":"venue"
},
  "geometry": {"coordinates":[-98.346385,47.561484],"type":"Point"}
}