{
  "type": "Feature",
  "properties": {
    "addr:full":"232 3rd St NE Valley City ND 58072",
    "addr:housenumber":"232",
    "addr:postcode":"58072",
    "addr:street":"3Rd St Ne",
    "iso:country":"US",
    "sg:address":"232 3rd St NE",
    "sg:city":"Valley City",
    "sg:classifiers":[
        {
            "category":"Education",
            "subcategory":"School",
            "type":"Public Place"
        }
    ],
    "sg:phone":"+1 701 845 3402",
    "sg:postcode":"58072",
    "sg:province":"ND",
    "sg:tags":[
        "academic",
        "special"
    ],
    "wof:name":"Sheyenne Valley Multidistrict",
    "wof:placetype":"venue"
},
  "geometry": {"coordinates":[-98.001238,46.925229],"type":"Point"}
}