{
  "type": "Feature",
  "properties": {
    "iso:country":"US",
    "sg:address":"1500 University Ave W",
    "sg:city":"Minot",
    "sg:classifiers":[
        {
            "category":"Government",
            "subcategory":"Office",
            "type":"Public Place"
        },
        {
            "category":"Social Services",
            "subcategory":"Job Training",
            "type":"Services"
        }
    ],
    "sg:phone":"+1 701 857 9600",
    "sg:postcode":"58703",
    "sg:province":"ND",
    "sg:tags":[
        "rehab",
        "center",
        "corps"
    ],
    "wof:name":"Quentin-Burdick Job Corps Ctr",
    "wof:placetype":"venue"
},
  "geometry": {"coordinates":[-101.317702,48.24519],"type":"Point"}
}