{
  "type": "Feature",
  "properties": {
    "iso:country":"US",
    "sg:address":"302 S Main St",
    "sg:city":"Velva",
    "sg:classifiers":[
        {
            "category":"Real Estate",
            "subcategory":"Real Estate Operator",
            "type":"Services"
        }
    ],
    "sg:phone":"+1 701 338 2933",
    "sg:postcode":"58790",
    "sg:province":"ND",
    "sg:tags":[
        "property",
        "lessor"
    ],
    "wof:name":"Robert Senechal",
    "wof:placetype":"venue"
},
  "geometry": {"coordinates":[-100.93053500000001,48.054376],"type":"Point"}
}