{
  "type": "Feature",
  "properties": {
    "iso:country":"US",
    "sg:address":"317 Main Ave",
    "sg:city":"Regent",
    "sg:classifiers":[
        {
            "category":"Organizations",
            "subcategory":"Religious Organization",
            "type":"Services"
        }
    ],
    "sg:phone":"+1 701 563 4439",
    "sg:postcode":"58650",
    "sg:province":"ND",
    "sg:tags":[
        "church"
    ],
    "wof:name":"Regent Lutheran Church",
    "wof:placetype":"venue"
},
  "geometry": {"coordinates":[-102.55946,46.420118],"type":"Point"}
}