{
  "type": "Feature",
  "properties": {
    "iso:country":"US",
    "sg:address":"108 S Main St",
    "sg:city":"Stanley",
    "sg:classifiers":[
        {
            "category":"Health Services",
            "subcategory":"Chiropractor",
            "type":"Services"
        }
    ],
    "sg:phone":"+1 701 628 2136",
    "sg:postcode":"58784",
    "sg:province":"ND",
    "wof:name":"Johnson Chiropractic Clinic",
    "wof:placetype":"venue"
},
  "geometry": {"coordinates":[-102.390422,48.311257],"type":"Point"}
}