{
  "type": "Feature",
  "properties": {
    "addr:full":"2839 33rd St S Fargo ND 58103",
    "addr:housenumber":"2839",
    "addr:postcode":"58103",
    "addr:street":"33Rd St S",
    "iso:country":"US",
    "sg:address":"2839 33rd St S",
    "sg:city":"Fargo",
    "sg:classifiers":[
        {
            "category":"Health Services",
            "subcategory":"Clinic",
            "type":"Services"
        }
    ],
    "sg:phone":"+1 701 280 9900",
    "sg:postcode":"58103",
    "sg:province":"ND",
    "wof:name":"ABC Health Products",
    "wof:placetype":"venue"
},
  "geometry": {"coordinates":[-96.83133100000001,46.839446],"type":"Point"}
}