{
  "type": "Feature",
  "properties": {
    "addr:full":"1440 4th Ave NE Valley City ND 58072",
    "addr:housenumber":"1440",
    "addr:postcode":"58072",
    "addr:street":"4Th Ave Ne",
    "iso:country":"US",
    "sg:address":"1440 4th Ave NE",
    "sg:city":"Valley City",
    "sg:classifiers":[
        {
            "category":"Autos & Motor Vehicles",
            "subcategory":"Automobile Sales",
            "type":"Retail Goods"
        }
    ],
    "sg:phone":"+1 701 845 0850",
    "sg:postcode":"58072",
    "sg:province":"ND",
    "wof:name":"Reis Motors",
    "wof:placetype":"venue"
},
  "geometry": {"coordinates":[-97.998637,46.936658],"type":"Point"}
}