{
  "type": "Feature",
  "properties": {
    "iso:country":"US",
    "sg:address":"315 24th Ave S",
    "sg:city":"Grand Forks",
    "sg:classifiers":[
        {
            "category":"Professional",
            "subcategory":"Advertising",
            "type":"Services"
        }
    ],
    "sg:phone":"+1 701 885 5193",
    "sg:postcode":"58201",
    "sg:province":"ND",
    "wof:name":"Valley Buzz",
    "wof:placetype":"venue"
},
  "geometry": {"coordinates":[-97.030473,47.896664],"type":"Point"}
}