{
  "type": "Feature",
  "properties": {
    "iso:country":"US",
    "sg:address":"207 Washington Ave",
    "sg:city":"Cleveland",
    "sg:classifiers":[
        {
            "category":"Organizations",
            "subcategory":"Religious Organization",
            "type":"Services"
        }
    ],
    "sg:phone":"+1 701 763 6192",
    "sg:postcode":"58424",
    "sg:province":"ND",
    "wof:name":"St Annes Church",
    "wof:placetype":"venue"
},
  "geometry": {"coordinates":[-99.04405800000001,46.896103],"type":"Point"}
}