{
  "type": "Feature",
  "properties": {
    "addr:full":"102 Butte Ave N Center ND 58530",
    "addr:housenumber":"102",
    "addr:postcode":"58530",
    "addr:street":"Butte Ave N Center",
    "iso:country":"US",
    "sg:address":"102 Butte Ave N",
    "sg:city":"Center",
    "sg:classifiers":[
        {
            "category":"Organizations",
            "subcategory":"Religious Organization",
            "type":"Services"
        }
    ],
    "sg:phone":"+1 701 794 3166",
    "sg:postcode":"58530",
    "sg:province":"ND",
    "sg:tags":[
        "church"
    ],
    "wof:name":"St Paul's Lutheran Church",
    "wof:placetype":"venue"
},
  "geometry": {"coordinates":[-101.296547,47.117385],"type":"Point"}
}