{
  "type": "Feature",
  "properties": {
    "iso:country":"US",
    "sg:address":"116 Main St W",
    "sg:city":"Beulah",
    "sg:classifiers":[
        {
            "category":"Shopping",
            "subcategory":"Florist",
            "type":"Retail Goods"
        }
    ],
    "sg:phone":"+1 701 873 2291",
    "sg:postcode":"58523",
    "sg:province":"ND",
    "wof:name":"Bloom'n House",
    "wof:placetype":"venue"
},
  "geometry": {"coordinates":[-101.779499,47.263549],"type":"Point"}
}