{
  "type": "Feature",
  "properties": {
    "addr:full":"1511 Island Park Dr Jamestown ND 58401",
    "addr:housenumber":"1511",
    "addr:postcode":"58401",
    "addr:street":"Island Park Dr",
    "iso:country":"US",
    "sg:address":"1511 Island Park Dr",
    "sg:city":"Jamestown",
    "sg:classifiers":[
        {
            "category":"Retail",
            "subcategory":"Portrait Studio",
            "type":"Services"
        }
    ],
    "sg:phone":"+1 701 252 0076",
    "sg:postcode":"58401",
    "sg:province":"ND",
    "sg:tags":[
        "photographer"
    ],
    "wof:name":"Divine Photographics",
    "wof:placetype":"venue"
},
  "geometry": {"coordinates":[-98.70935,46.927308],"type":"Point"}
}