{
  "type": "Feature",
  "properties": {
    "iso:country":"US",
    "sg:address":"4110 86th Ave SE",
    "sg:city":"Jamestown",
    "sg:classifiers":[
        {
            "category":"Building & Trades",
            "subcategory":"Construction",
            "type":"Services"
        }
    ],
    "sg:phone":"+1 701 251 9080",
    "sg:postcode":"58401",
    "sg:province":"ND",
    "sg:tags":[
        "company"
    ],
    "wof:name":"G F Construction",
    "wof:placetype":"venue"
},
  "geometry": {"coordinates":[-98.64970099999999,46.817453],"type":"Point"}
}