{
  "type": "Feature",
  "properties": {
    "addr:full":"124 Main St S Watford City ND 58854",
    "addr:housenumber":"124",
    "addr:postcode":"58854",
    "addr:street":"Main St S Watford",
    "iso:country":"US",
    "sg:address":"124 Main St S",
    "sg:city":"Watford City",
    "sg:classifiers":[
        {
            "category":"Travel",
            "subcategory":"Hotels & Motels",
            "type":"Entertainment"
        }
    ],
    "sg:phone":"+1 701 444 4126",
    "sg:postcode":"58854",
    "sg:province":"ND",
    "wof:name":"Fin & Feather Inn",
    "wof:placetype":"venue"
},
  "geometry": {"coordinates":[-103.283101,47.801289],"type":"Point"}
}