{
  "type": "Feature",
  "properties": {
    "iso:country":"US",
    "sg:address":"1431 7th Ave N",
    "sg:city":"Fargo",
    "sg:classifiers":[
        {
            "category":"Building & Trades",
            "subcategory":"Plumbing",
            "type":"Services"
        }
    ],
    "sg:phone":"+1 701 241 7900",
    "sg:postcode":"58102",
    "sg:province":"ND",
    "sg:tags":[
        "plumbing",
        "contractor"
    ],
    "wof:name":"Skalicky Plumbing & Heating",
    "wof:placetype":"venue"
},
  "geometry": {"coordinates":[-96.803361,46.883247],"type":"Point"}
}