{
  "type": "Feature",
  "properties": {
    "addr:full":"3824 Dominion St Bismarck ND 58503",
    "addr:housenumber":"3824",
    "addr:postcode":"58503",
    "addr:street":"Dominion St",
    "iso:country":"US",
    "sg:address":"3824 Dominion St",
    "sg:city":"Bismarck",
    "sg:classifiers":[
        {
            "category":"Building & Trades",
            "subcategory":"Plumbing",
            "type":"Services"
        }
    ],
    "sg:phone":"+1 701 222 2437",
    "sg:postcode":"58503",
    "sg:province":"ND",
    "sg:tags":[
        "furnace",
        "cleaning"
    ],
    "wof:name":"Blair's Power Vac",
    "wof:placetype":"venue"
},
  "geometry": {"coordinates":[-100.77769600000001,46.847625],"type":"Point"}
}