{
  "type": "Feature",
  "properties": {
    "addr:full":"206 Main St Northwood ND 58267",
    "addr:housenumber":"206",
    "addr:postcode":"58267",
    "addr:street":"Main St",
    "iso:country":"US",
    "sg:address":"206 Main St",
    "sg:city":"Northwood",
    "sg:classifiers":[
        {
            "category":"Professional",
            "subcategory":"Research",
            "type":"Services"
        }
    ],
    "sg:phone":"+1 701 587 5343",
    "sg:postcode":"58267",
    "sg:province":"ND",
    "sg:tags":[
        "commercial",
        "physical"
    ],
    "wof:name":"A G V I S E Research Inc",
    "wof:placetype":"venue"
},
  "geometry": {"coordinates":[-97.566586,47.734146],"type":"Point"}
}