{
  "type": "Feature",
  "properties": {
    "iso:country":"US",
    "sg:address":"320 Main St",
    "sg:city":"Arthur",
    "sg:classifiers":[
        {
            "category":"Bars & Pubs",
            "type":"Food & Drink"
        }
    ],
    "sg:phone":"+1 701 967 8977",
    "sg:postcode":"58006",
    "sg:province":"ND",
    "sg:tags":[
        "drinking"
    ],
    "wof:name":"Coaches Corner LLC",
    "wof:placetype":"venue"
},
  "geometry": {"coordinates":[-97.218035,47.104034],"type":"Point"}
}