{
  "type": "Feature",
  "properties": {
    "iso:country":"US",
    "sg:address":"7550 State Hwy 1806",
    "sg:city":"Dodge",
    "sg:classifiers":[
        {
            "category":"Farming",
            "subcategory":"Livestock Farm",
            "type":"Manufacturing & Wholesale Goods"
        }
    ],
    "sg:phone":"+1 701 983 4424",
    "sg:postcode":"58625",
    "sg:province":"ND",
    "sg:tags":[
        "beef",
        "feedlot",
        "cattle"
    ],
    "wof:name":"Lindeman Farms",
    "wof:placetype":"venue"
},
  "geometry": {"coordinates":[-102.142364,47.458111],"type":"Point"}
}