{
  "type": "Feature",
  "properties": {
    "iso:country":"US",
    "sg:address":"204 11th St E",
    "sg:city":"Bottineau",
    "sg:classifiers":[
        {
            "category":"Food & Beverages",
            "subcategory":"Groceries & Convenience Stores",
            "type":"Retail Goods"
        }
    ],
    "sg:phone":"+1 701 228 2222",
    "sg:postcode":"58318",
    "sg:province":"ND",
    "sg:tags":[
        "grocer"
    ],
    "wof:name":"Dan's Super Valu",
    "wof:placetype":"venue"
},
  "geometry": {"coordinates":[-100.444323,48.820634],"type":"Point"}
}