{
  "type": "Feature",
  "properties": {
    "iso:country":"US",
    "sg:address":"423 N 5th St",
    "sg:city":"Grand Forks",
    "sg:classifiers":[
        {
            "category":"Food & Beverages",
            "subcategory":"Groceries & Convenience Stores",
            "type":"Retail Goods"
        }
    ],
    "sg:phone":"+1 701 772 2974",
    "sg:postcode":"58203",
    "sg:province":"ND",
    "wof:name":"M & H Gas Station",
    "wof:placetype":"venue"
},
  "geometry": {"coordinates":[-97.038312,47.926816],"type":"Point"}
}