{
  "type": "Feature",
  "properties": {
    "addr:full":"307 Main Ave Fargo ND 58103",
    "addr:housenumber":"307",
    "addr:postcode":"58103",
    "addr:street":"Main Ave",
    "iso:country":"US",
    "sg:address":"307 Main Ave",
    "sg:city":"Fargo",
    "sg:classifiers":[
        {
            "category":"Freight",
            "type":"Transportation"
        }
    ],
    "sg:phone":"+1 701 364 3696",
    "sg:postcode":"58103",
    "sg:province":"ND",
    "sg:tags":[
        "commercial",
        "storage"
    ],
    "wof:name":"F M Records Ctr",
    "wof:placetype":"venue"
},
  "geometry": {"coordinates":[-96.781847,46.87415],"type":"Point"}
}