{
  "type": "Feature",
  "properties": {
    "iso:country":"US",
    "sg:address":"202 5th St W",
    "sg:city":"Park River",
    "sg:classifiers":[
        {
            "category":"Home & Garden",
            "subcategory":"Building Materials",
            "type":"Retail Goods"
        }
    ],
    "sg:phone":"+1 701 284 6621",
    "sg:postcode":"58270",
    "sg:province":"ND",
    "sg:tags":[
        "glass",
        "leaded"
    ],
    "wof:name":"Sundog Glass Design",
    "wof:placetype":"venue"
},
  "geometry": {"coordinates":[-97.750027,48.393683],"type":"Point"}
}