{
  "type": "Feature",
  "properties": {
    "iso:country":"US",
    "sg:address":"205 Pleasant Ave S",
    "sg:city":"Surrey",
    "sg:classifiers":[
        {
            "category":"Home & Garden",
            "subcategory":"Furniture",
            "type":"Retail Goods"
        }
    ],
    "sg:phone":"+1 701 852 4957",
    "sg:postcode":"58785",
    "sg:province":"ND",
    "sg:tags":[
        "cabinet"
    ],
    "sg:website":"www.kauffmankitchens.com",
    "wof:name":"Kauffman Kitchen & Bath",
    "wof:placetype":"venue"
},
  "geometry": {"coordinates":[-101.133681,48.236498],"type":"Point"}
}