{
  "type": "Feature",
  "properties": {
    "iso:country":"US",
    "sg:address":"702 Main Ave S",
    "sg:city":"Hankinson",
    "sg:classifiers":[
        {
            "category":"Travel",
            "subcategory":"Hotels & Motels",
            "type":"Entertainment"
        }
    ],
    "sg:phone":"+1 701 242 7363",
    "sg:postcode":"58041",
    "sg:province":"ND",
    "wof:name":"Hankinson Motel Reservation Ln",
    "wof:placetype":"venue"
},
  "geometry": {"coordinates":[-96.90214400000001,46.065168],"type":"Point"}
}