{
  "type": "Feature",
  "properties": {
    "addr:full":"9846 153rd Ave NE Hamilton ND 58238",
    "addr:housenumber":"9846",
    "addr:postcode":"58238",
    "addr:street":"153Rd Ave Ne",
    "iso:country":"US",
    "sg:address":"9846 153rd Ave NE",
    "sg:city":"Hamilton",
    "sg:classifiers":[
        {
            "category":"Real Estate",
            "subcategory":"Real Estate Operator",
            "type":"Services"
        }
    ],
    "sg:phone":"+1 701 265 8275",
    "sg:postcode":"58238",
    "sg:province":"ND",
    "sg:tags":[
        "property",
        "lessor"
    ],
    "wof:name":"Arnold L Beyer",
    "wof:placetype":"venue"
},
  "geometry": {"coordinates":[-97.35898899999999,48.839908],"type":"Point"}
}