{
  "type": "Feature",
  "properties": {
    "iso:country":"US",
    "sg:address":"115 B St S",
    "sg:city":"Glen Ullin",
    "sg:classifiers":[
        {
            "category":"Personal",
            "subcategory":"Beauty Salon",
            "type":"Services"
        }
    ],
    "sg:phone":"+1 701 348 3370",
    "sg:postcode":"58631",
    "sg:province":"ND",
    "sg:tags":[
        "shop"
    ],
    "wof:name":"Hair Works",
    "wof:placetype":"venue"
},
  "geometry": {"coordinates":[-101.82881500000001,46.816308],"type":"Point"}
}