{
  "type": "Feature",
  "properties": {
    "addr:full":"115 B St S Glen Ullin ND 58631",
    "addr:housenumber":"115",
    "addr:postcode":"58631",
    "addr:street":"B St S Glen",
    "iso:country":"US",
    "sg:address":"115 B St S",
    "sg:city":"Glen Ullin",
    "sg:classifiers":[
        {
            "category":"Personal",
            "subcategory":"Beauty Salon",
            "type":"Services"
        }
    ],
    "sg:phone":"+1 701 348 3370",
    "sg:postcode":"58631",
    "sg:province":"ND",
    "sg:tags":[
        "shop"
    ],
    "wof:name":"Hair Works",
    "wof:placetype":"venue"
},
  "geometry": {"coordinates":[-101.82881500000001,46.816308],"type":"Point"}
}