{
  "type": "Feature",
  "properties": {
    "iso:country":"US",
    "sg:address":"303 Oakland Ave",
    "sg:city":"Milton",
    "sg:classifiers":[
        {
            "category":"Autos & Motor Vehicles",
            "subcategory":"Fuel & Gas Station",
            "type":"Retail Goods"
        }
    ],
    "sg:phone":"+1 701 496 3121",
    "sg:postcode":"58260",
    "sg:province":"ND",
    "sg:tags":[
        "oil"
    ],
    "wof:name":"Milton Service",
    "wof:placetype":"venue"
},
  "geometry": {"coordinates":[-98.044059,48.627037],"type":"Point"}
}