{
  "type": "Feature",
  "properties": {
    "iso:country":"US",
    "sg:address":"111 Main St",
    "sg:city":"Wildrose",
    "sg:phone":"+1 701 539 2272",
    "sg:postcode":"58748",
    "sg:province":"ND",
    "sg:tags":[
        "oil"
    ],
    "wof:name":"Farmer's Union Oil Co",
    "wof:placetype":"venue"
},
  "geometry": {"coordinates":[-100.49941,48.700646],"type":"Point"}
}