{
  "type": "Feature",
  "properties": {
    "iso:country":"US",
    "sg:address":"308 Sunny Hills Dr S",
    "sg:city":"Devils Lake",
    "sg:classifiers":[
        {
            "category":"Building & Trades",
            "subcategory":"Construction",
            "type":"Services"
        }
    ],
    "sg:phone":"+1 701 662 5620",
    "sg:postcode":"58301",
    "sg:province":"ND",
    "sg:tags":[
        "house"
    ],
    "wof:name":"Armstrong Builders",
    "wof:placetype":"venue"
},
  "geometry": {"coordinates":[-98.99181,48.128174],"type":"Point"}
}