{
  "type": "Feature",
  "properties": {
    "addr:full":"54 S Central Ave Beach ND 58621",
    "addr:housenumber":"54",
    "addr:postcode":"58621",
    "addr:street":"S Central Ave",
    "iso:country":"US",
    "sg:address":"54 S Central Ave",
    "sg:city":"Beach",
    "sg:classifiers":[
        {
            "category":"Retail",
            "subcategory":"Repair Shop",
            "type":"Services"
        }
    ],
    "sg:phone":"+1 701 872 4323",
    "sg:postcode":"58621",
    "sg:province":"ND",
    "sg:tags":[
        "television",
        "radio"
    ],
    "wof:name":"Brockmeyer TV & Radio Svc",
    "wof:placetype":"venue"
},
  "geometry": {"coordinates":[-104.00613,46.914434],"type":"Point"}
}