{
  "type": "Feature",
  "properties": {
    "iso:country":"US",
    "sg:address":"14651 249th St SE",
    "sg:city":"Moffit",
    "sg:classifiers":[
        {
            "category":"Farming",
            "subcategory":"Livestock Farm",
            "type":"Manufacturing & Wholesale Goods"
        }
    ],
    "sg:phone":"+1 701 387 4417",
    "sg:postcode":"58560",
    "sg:province":"ND",
    "sg:tags":[
        "animal",
        "general"
    ],
    "wof:name":"Brian Dralle",
    "wof:placetype":"venue"
},
  "geometry": {"coordinates":[-100.39624499999999,46.642482],"type":"Point"}
}