{
  "type": "Feature",
  "properties": {
    "iso:country":"US",
    "sg:address":"137 2nd St NW",
    "sg:city":"Valley City",
    "sg:classifiers":[
        {
            "category":"Manufacturing",
            "subcategory":"Textiles",
            "type":"Manufacturing & Wholesale Goods"
        }
    ],
    "sg:phone":"+1 701 845 3143",
    "sg:postcode":"58072",
    "sg:province":"ND",
    "sg:tags":[
        "finishing",
        "plant",
        "cotton"
    ],
    "wof:name":"Bridgetown Imprints",
    "wof:placetype":"venue"
},
  "geometry": {"coordinates":[-98.004074,46.924119],"type":"Point"}
}