{
  "type": "Feature",
  "properties": {
    "addr:full":"4586 67th Ave SE Cleveland ND 58424",
    "addr:housenumber":"4586",
    "addr:postcode":"58424",
    "addr:street":"67Th Ave Se",
    "iso:country":"US",
    "sg:address":"4586 67th Ave SE",
    "sg:city":"Cleveland",
    "sg:classifiers":[
        {
            "category":"Farming",
            "subcategory":"Farm",
            "type":"Manufacturing & Wholesale Goods"
        }
    ],
    "sg:phone":"+1 701 763 6372",
    "sg:postcode":"58424",
    "sg:province":"ND",
    "wof:name":"John Gomke Jr Farm",
    "wof:placetype":"venue"
},
  "geometry": {"coordinates":[-99.050348,46.748398],"type":"Point"}
}