{
  "type": "Feature",
  "properties": {
    "iso:country":"US",
    "sg:address":"8 7th St N",
    "sg:city":"Fargo",
    "sg:classifiers":[
        {
            "category":"Real Estate",
            "subcategory":"Architect",
            "type":"Services"
        }
    ],
    "sg:phone":"+1 701 239 4198",
    "sg:postcode":"58102",
    "sg:province":"ND",
    "sg:tags":[
        "architects'",
        "specification",
        "builders'",
        "construction",
        "architectural",
        "engineer"
    ],
    "sg:website":"http://www.tlstroh.com",
    "wof:name":"T. L. Stroh Architects, Ltd.",
    "wof:placetype":"venue"
},
  "geometry": {"coordinates":[-96.79172,46.875956],"type":"Point"}
}