{
  "type": "Feature",
  "properties": {
    "iso:country":"US",
    "sg:address":"1001 17th St SW",
    "sg:city":"Jamestown",
    "sg:classifiers":[
        {
            "category":"Organizations",
            "subcategory":"Religious Organization",
            "type":"Services"
        }
    ],
    "sg:phone":"+1 701 952 0777",
    "sg:postcode":"58401",
    "sg:province":"ND",
    "wof:name":"Agape Ministries Inc",
    "wof:placetype":"venue"
},
  "geometry": {"coordinates":[-98.719928,46.89223],"type":"Point"}
}