{
  "type": "Feature",
  "properties": {
    "addr:full":"3676 116th Ave SW Dickinson ND 58601",
    "addr:housenumber":"3676",
    "addr:postcode":"58601",
    "addr:street":"116Th Ave Sw",
    "iso:country":"US",
    "sg:address":"3676 116th Ave SW",
    "sg:city":"Dickinson",
    "sg:classifiers":[
        {
            "category":"Building & Trades",
            "subcategory":"Equipment Rental",
            "type":"Services"
        }
    ],
    "sg:phone":"+1 701 483 8363",
    "sg:postcode":"58601",
    "sg:province":"ND",
    "sg:tags":[
        "crane"
    ],
    "wof:name":"Taylor Crane Svc",
    "wof:placetype":"venue"
},
  "geometry": {"coordinates":[-102.894165,46.879689],"type":"Point"}
}