{
  "type": "Feature",
  "properties": {
    "addr:full":"620 8th Ave S Grand Forks ND 58201",
    "addr:housenumber":"620",
    "addr:postcode":"58201",
    "addr:street":"8Th Ave S",
    "iso:country":"US",
    "sg:address":"620 8th Ave S",
    "sg:city":"Grand Forks",
    "sg:classifiers":[
        {
            "category":"Shopping",
            "subcategory":"Used Merchandise",
            "type":"Retail Goods"
        }
    ],
    "sg:phone":"+1 701 795 8614",
    "sg:postcode":"58201",
    "sg:province":"ND",
    "sg:tags":[
        "shop",
        "thrift"
    ],
    "wof:name":"St Vincent De Paul",
    "wof:placetype":"venue"
},
  "geometry": {"coordinates":[-97.035376,47.91411],"type":"Point"}
}