{
  "type": "Feature",
  "properties": {
    "iso:country":"US",
    "sg:address":"511 2nd St",
    "sg:city":"Edgeley",
    "sg:classifiers":[
        {
            "category":"Government",
            "subcategory":"Post Office",
            "type":"Public Place"
        }
    ],
    "sg:phone":"+1 701 493 2831",
    "sg:postcode":"58433",
    "sg:province":"ND",
    "sg:tags":[
        "postal",
        "us"
    ],
    "wof:name":"US Post Office",
    "wof:placetype":"venue"
},
  "geometry": {"coordinates":[-98.71140800000001,46.360802],"type":"Point"}
}