{
  "type": "Feature",
  "properties": {
    "addr:full":"725 Airport Rd Bismarck ND 58504",
    "addr:housenumber":"725",
    "addr:postcode":"58504",
    "addr:street":"Airport Rd",
    "iso:country":"US",
    "sg:address":"725 Airport Rd",
    "sg:city":"Bismarck",
    "sg:classifiers":[
        {
            "category":"Building & Trades",
            "subcategory":"Plumbing",
            "type":"Services"
        }
    ],
    "sg:phone":"+1 701 223 8260",
    "sg:postcode":"58504",
    "sg:province":"ND",
    "sg:tags":[
        "conditioning",
        "air",
        "system",
        "contractor"
    ],
    "wof:name":"Cooling & Heating Unlimited",
    "wof:placetype":"venue"
},
  "geometry": {"coordinates":[-100.76275200000001,46.797009],"type":"Point"}
}