{
  "type": "Feature",
  "properties": {
    "iso:country":"US",
    "sg:address":"221 S Main St",
    "sg:city":"Stanley",
    "sg:classifiers":[
        {
            "category":"Government",
            "subcategory":"Office",
            "type":"Public Place"
        }
    ],
    "sg:phone":"+1 701 628 2225",
    "sg:postcode":"58784",
    "sg:province":"ND",
    "sg:tags":[
        "city"
    ],
    "wof:name":"Stanley City Hall",
    "wof:placetype":"venue"
},
  "geometry": {"coordinates":[-102.390422,48.311101],"type":"Point"}
}