{
  "type": "Feature",
  "properties": {
    "iso:country":"US",
    "sg:address":"6 5th Ave SE",
    "sg:city":"Stanley",
    "sg:classifiers":[
        {
            "category":"Building & Trades",
            "subcategory":"Construction",
            "type":"Services"
        }
    ],
    "sg:phone":"+1 701 628 1546",
    "sg:postcode":"58784",
    "sg:province":"ND",
    "sg:tags":[
        "general",
        "contractor"
    ],
    "wof:name":"A M Construction",
    "wof:placetype":"venue"
},
  "geometry": {"coordinates":[-102.39049300000001,48.314112],"type":"Point"}
}