{
  "type": "Feature",
  "properties": {
    "addr:full":"606 5th St Oriska ND 58063",
    "addr:housenumber":"606",
    "addr:postcode":"58063",
    "addr:street":"5Th St",
    "iso:country":"US",
    "sg:address":"606 5th St",
    "sg:city":"Oriska",
    "sg:classifiers":[
        {
            "category":"Organizations",
            "subcategory":"Religious Organization",
            "type":"Services"
        }
    ],
    "sg:phone":"+1 701 845 3713",
    "sg:postcode":"58063",
    "sg:province":"ND",
    "sg:tags":[
        "church"
    ],
    "wof:name":"St Bernard Catholic Church",
    "wof:placetype":"venue"
},
  "geometry": {"coordinates":[-97.790835,46.930384],"type":"Point"}
}