{
  "type": "Feature",
  "properties": {
    "addr:full":"600 S 2nd St Bismarck ND 58504",
    "addr:housenumber":"600",
    "addr:postcode":"58504",
    "addr:street":"S 2Nd St",
    "iso:country":"US",
    "sg:address":"600 S 2nd St",
    "sg:city":"Bismarck",
    "sg:classifiers":[
        {
            "category":"Social Services",
            "type":"Services"
        }
    ],
    "sg:phone":"+1 701 255 7566",
    "sg:postcode":"58504",
    "sg:province":"ND",
    "sg:tags":[
        "organization",
        "welfare"
    ],
    "wof:name":"Habitat For Humanity",
    "wof:placetype":"venue"
},
  "geometry": {"coordinates":[-100.789666,46.79942],"type":"Point"}
}