{
  "type": "Feature",
  "properties": {
    "addr:full":"712 11th St NW Minot ND 58703",
    "addr:housenumber":"712",
    "addr:postcode":"58703",
    "addr:street":"11Th St Nw",
    "iso:country":"US",
    "sg:address":"712 11th St NW",
    "sg:city":"Minot",
    "sg:classifiers":[
        {
            "category":"Utilities",
            "subcategory":"Refuse",
            "type":"Services"
        }
    ],
    "sg:phone":"+1 701 838 3278",
    "sg:postcode":"58703",
    "sg:province":"ND",
    "sg:tags":[
        "repair",
        "system"
    ],
    "wof:name":"S & S Taxidermy",
    "wof:placetype":"venue"
},
  "geometry": {"coordinates":[-101.31044900000001,48.245065],"type":"Point"}
}