{
  "type": "Feature",
  "properties": {
    "iso:country":"US",
    "sg:address":"117 Main St",
    "sg:city":"Turtle Lake",
    "sg:classifiers":[
        {
            "category":"Restaurant",
            "type":"Food & Drink"
        }
    ],
    "sg:phone":"+1 701 448 2472",
    "sg:postcode":"58575",
    "sg:province":"ND",
    "wof:name":"Bev's Cafe",
    "wof:placetype":"venue"
},
  "geometry": {"coordinates":[-100.889905,47.521728],"type":"Point"}
}