{
  "type": "Feature",
  "properties": {
    "addr:full":"915 Sunset Dr Grand Forks ND 58201",
    "addr:housenumber":"915",
    "addr:postcode":"58201",
    "addr:street":"Sunset Dr",
    "iso:country":"US",
    "sg:address":"915 Sunset Dr",
    "sg:city":"Grand Forks",
    "sg:classifiers":[
        {
            "category":"Freight",
            "type":"Transportation"
        }
    ],
    "sg:phone":"+1 701 795 7142",
    "sg:postcode":"58201",
    "sg:province":"ND",
    "sg:tags":[
        "local",
        "storage",
        "trucking"
    ],
    "wof:name":"Rugged Trails Liability Co",
    "wof:placetype":"venue"
},
  "geometry": {"coordinates":[-97.039975,47.904419],"type":"Point"}
}