{
  "type": "Feature",
  "properties": {
    "addr:full":"103 E Villard St Dickinson ND 58601",
    "addr:housenumber":"103",
    "addr:postcode":"58601",
    "addr:street":"E Villard St",
    "iso:country":"US",
    "sg:address":"103 E Villard St",
    "sg:city":"Dickinson",
    "sg:classifiers":[
        {
            "category":"Personal",
            "subcategory":"Beauty Salon",
            "type":"Services"
        }
    ],
    "sg:phone":"+1 701 483 9191",
    "sg:postcode":"58601",
    "sg:province":"ND",
    "sg:tags":[
        "shop"
    ],
    "wof:name":"Skin Radiance By April",
    "wof:placetype":"venue"
},
  "geometry": {"coordinates":[-102.782715,46.878587],"type":"Point"}
}