{
  "type": "Feature",
  "properties": {
    "iso:country":"US",
    "sg:address":"1809 S Broadway St",
    "sg:city":"Minot",
    "sg:classifiers":[
        {
            "category":"Personal",
            "type":"Services"
        }
    ],
    "sg:phone":"+1 701 852 2690",
    "sg:postcode":"58701",
    "sg:province":"ND",
    "sg:tags":[
        "electrolysis"
    ],
    "wof:name":"Electrolysis Studio",
    "wof:placetype":"venue"
},
  "geometry": {"coordinates":[-101.29598300000001,48.214497],"type":"Point"}
}