{
  "type": "Feature",
  "properties": {
    "iso:country":"US",
    "sg:address":"701 N 25th St",
    "sg:city":"Grand Forks",
    "sg:classifiers":[
        {
            "category":"Retail",
            "subcategory":"Repair Shop",
            "type":"Services"
        }
    ],
    "sg:phone":"+1 701 772 4774",
    "sg:postcode":"58203",
    "sg:province":"ND",
    "sg:tags":[
        "piano",
        "tuning"
    ],
    "wof:name":"L & C Piano Tuning and Repair",
    "wof:placetype":"venue"
},
  "geometry": {"coordinates":[-97.062656,47.925296],"type":"Point"}
}