{
  "type": "Feature",
  "properties": {
    "addr:full":"901 Burrel Ave NE Cooperstown ND 58425",
    "addr:housenumber":"901",
    "addr:postcode":"58425",
    "addr:street":"Burrel Ave Ne",
    "iso:country":"US",
    "sg:address":"901 Burrel Ave NE",
    "sg:city":"Cooperstown",
    "sg:classifiers":[
        {
            "category":"Banks & Credit Unions",
            "subcategory":"Bank",
            "type":"Services"
        }
    ],
    "sg:phone":"+1 701 797 2311",
    "sg:postcode":"58425",
    "sg:province":"ND",
    "sg:tags":[
        "state",
        "commercial"
    ],
    "wof:name":"Bank Of The West",
    "wof:placetype":"venue"
},
  "geometry": {"coordinates":[-98.123857,47.444559],"type":"Point"}
}