{
  "type": "Feature",
  "properties": {
    "iso:country":"US",
    "sg:address":"151 53rd Ave SE",
    "sg:city":"Sykeston",
    "sg:classifiers":[
        {
            "category":"Farming",
            "subcategory":"Livestock Farm",
            "type":"Manufacturing & Wholesale Goods"
        }
    ],
    "sg:phone":"+1 701 984 2249",
    "sg:postcode":"58486",
    "sg:province":"ND",
    "sg:tags":[
        "from",
        "soil",
        "crop",
        "custom",
        "cattle",
        "feedlot"
    ],
    "wof:name":"Polries-Marcotte Inc",
    "wof:placetype":"venue"
},
  "geometry": {"coordinates":[-99.41541100000001,47.391739],"type":"Point"}
}