{
  "type": "Feature",
  "properties": {
    "iso:country":"US",
    "sg:address":"2219 E Main Ave",
    "sg:city":"Bismarck",
    "sg:classifiers":[
        {
            "category":"Professional",
            "subcategory":"Computer Services",
            "type":"Services"
        }
    ],
    "sg:phone":"+1 701 222 2242",
    "sg:postcode":"58501",
    "sg:province":"ND",
    "sg:tags":[
        "tel",
        "design",
        "datum",
        "system"
    ],
    "wof:name":"Inet Technologies",
    "wof:placetype":"venue"
},
  "geometry": {"coordinates":[-100.75870399999999,46.805064],"type":"Point"}
}