{
  "type": "Feature",
  "properties": {
    "iso:country":"US",
    "sg:address":"4431 Memorial Hwy",
    "sg:city":"Mandan",
    "sg:classifiers":[
        {
            "category":"Professional",
            "subcategory":"Accounting & Tax Preparation",
            "type":"Services"
        }
    ],
    "sg:phone":"+1 701 255 7259",
    "sg:postcode":"58554",
    "sg:province":"ND",
    "sg:tags":[
        "accountant"
    ],
    "wof:name":"Power & Assoc",
    "wof:placetype":"venue"
},
  "geometry": {"coordinates":[-100.833039,46.809528],"type":"Point"}
}