{
  "type": "Feature",
  "properties": {
    "addr:full":"305 1st Ave N Ellendale ND 58436",
    "addr:housenumber":"305",
    "addr:postcode":"58436",
    "addr:street":"1St Ave N",
    "iso:country":"US",
    "sg:address":"305 1st Ave N",
    "sg:city":"Ellendale",
    "sg:classifiers":[
        {
            "category":"Personal",
            "subcategory":"Beauty Salon",
            "type":"Services"
        }
    ],
    "sg:phone":"+1 701 349 3601",
    "sg:postcode":"58436",
    "sg:province":"ND",
    "wof:name":"Lucille's Beauty Salon",
    "wof:placetype":"venue"
},
  "geometry": {"coordinates":[-98.52737,46.005038],"type":"Point"}
}