{
  "type": "Feature",
  "properties": {
    "addr:full":"1404 33rd St SW Fargo ND 58103",
    "addr:housenumber":"1404",
    "addr:postcode":"58103",
    "addr:street":"33Rd St Sw",
    "iso:country":"US",
    "sg:address":"1404 33rd St SW",
    "sg:city":"Fargo",
    "sg:classifiers":[
        {
            "category":"Personal",
            "type":"Services"
        }
    ],
    "sg:phone":"+1 701 729 8781",
    "sg:postcode":"58103",
    "sg:province":"ND",
    "wof:name":"Cloud 9 Massage Therapy",
    "wof:placetype":"venue"
},
  "geometry": {"coordinates":[-96.832407,46.860098],"type":"Point"}
}