{
  "type": "Feature",
  "properties": {
    "iso:country":"US",
    "sg:address":"2263 166th Ave SE",
    "sg:city":"Argusville",
    "sg:phone":"+1 701 484 5636",
    "sg:postcode":"58005",
    "sg:province":"ND",
    "sg:tags":[
        "farm",
        "beet"
    ],
    "wof:name":"Ben Bush",
    "wof:placetype":"venue"
},
  "geometry": {"coordinates":[-96.985145,47.084736],"type":"Point"}
}