{
  "type": "Feature",
  "properties": {
    "iso:country":"US",
    "sg:address":"3416 15th Ave NE",
    "sg:city":"Anamoose",
    "sg:classifiers":[
        {
            "category":"Banks & Credit Unions",
            "subcategory":"Financial Services",
            "type":"Services"
        }
    ],
    "sg:phone":"+1 701 465 3315",
    "sg:postcode":"58710",
    "sg:province":"ND",
    "sg:tags":[
        "trust",
        "management"
    ],
    "wof:name":"Frueh Family",
    "wof:placetype":"venue"
},
  "geometry": {"coordinates":[-100.26255399999999,47.902363],"type":"Point"}
}