{
  "type": "Feature",
  "properties": {
    "addr:full":"7940 55th St NW Stanley ND 58784",
    "addr:housenumber":"7940",
    "addr:postcode":"58784",
    "addr:street":"55Th St Nw",
    "iso:country":"US",
    "sg:address":"7940 55th St NW",
    "sg:city":"Stanley",
    "sg:classifiers":[
        {
            "category":"Building & Trades",
            "subcategory":"Electrical",
            "type":"Services"
        }
    ],
    "sg:phone":"+1 701 628 3343",
    "sg:postcode":"58784",
    "sg:province":"ND",
    "sg:tags":[
        "electrical",
        "contractor"
    ],
    "wof:name":"Craft Electric",
    "wof:placetype":"venue"
},
  "geometry": {"coordinates":[-102.349446,48.211424],"type":"Point"}
}