{
  "type": "Feature",
  "properties": {
    "iso:country":"US",
    "sg:address":"811 23rd Ave N",
    "sg:city":"Wahpeton",
    "sg:classifiers":[
        {
            "category":"Wholesale",
            "subcategory":"Chemicals & Plastics",
            "type":"Manufacturing & Wholesale Goods"
        }
    ],
    "sg:phone":"+1 701 642 5965",
    "sg:postcode":"58075",
    "sg:province":"ND",
    "wof:name":"Agsco Inc",
    "wof:placetype":"venue"
},
  "geometry": {"coordinates":[-96.611401,46.293906],"type":"Point"}
}