{
  "type": "Feature",
  "properties": {
    "iso:country":"US",
    "sg:address":"500 Burlington St SE",
    "sg:city":"Mandan",
    "sg:classifiers":[
        {
            "category":"Shopping",
            "subcategory":"Pharmacy",
            "type":"Retail Goods"
        }
    ],
    "sg:phone":"+1 701 667 1843",
    "sg:postcode":"58554",
    "sg:province":"ND",
    "wof:name":"Gateway Pharmacy Inc",
    "wof:placetype":"venue"
},
  "geometry": {"coordinates":[-100.883605,46.824251],"type":"Point"}
}