{
  "type": "Feature",
  "properties": {
    "addr:full":"7091 30th Ave NE Rugby ND 58368",
    "addr:housenumber":"7091",
    "addr:postcode":"58368",
    "addr:street":"30Th Ave Ne",
    "iso:country":"US",
    "sg:address":"7091 30th Ave NE",
    "sg:city":"Rugby",
    "sg:classifiers":[
        {
            "category":"Farming",
            "subcategory":"Farm",
            "type":"Manufacturing & Wholesale Goods"
        }
    ],
    "sg:phone":"+1 701 776 2259",
    "sg:postcode":"58368",
    "sg:province":"ND",
    "wof:name":"Allan Brossart Farm",
    "wof:placetype":"venue"
},
  "geometry": {"coordinates":[-100.015429,48.429246],"type":"Point"}
}