{
  "type": "Feature",
  "properties": {
    "iso:country":"US",
    "sg:address":"1354 8th St N",
    "sg:city":"Fargo",
    "sg:classifiers":[
        {
            "category":"Building & Trades",
            "subcategory":"Landscaping Services",
            "type":"Services"
        }
    ],
    "sg:phone":"+1 701 730 0475",
    "sg:postcode":"58102",
    "sg:province":"ND",
    "sg:tags":[
        "lawn",
        "maintenance",
        "grounds"
    ],
    "wof:name":"Shrub Services Etc",
    "wof:placetype":"venue"
},
  "geometry": {"coordinates":[-96.790778,46.893841],"type":"Point"}
}