{
  "type": "Feature",
  "properties": {
    "iso:country":"US",
    "sg:address":"4950 13th Ave S",
    "sg:city":"Fargo",
    "sg:classifiers":[
        {
            "category":"Utilities",
            "subcategory":"Mobile Phone",
            "type":"Services"
        },
        {
            "category":"Coffee & Tea",
            "type":"Food & Drink"
        }
    ],
    "sg:phone":"+1 701 282 4694",
    "sg:postcode":"58103",
    "sg:province":"ND",
    "sg:tags":[
        "shop",
        "wi-fi",
        "espresso",
        "hotspot",
        "restaurant"
    ],
    "sg:website":"http://www.starbuckscoffee.com",
    "wof:name":"Starbucks Coffee",
    "wof:placetype":"venue"
},
  "geometry": {"coordinates":[-96.869822,46.861867],"type":"Point"}
}