{
  "type": "Feature",
  "properties": {
    "iso:country":"US",
    "sg:address":"219 3rd Ave NW",
    "sg:city":"Jamestown",
    "sg:classifiers":[
        {
            "category":"Retail",
            "subcategory":"Auto Repair",
            "type":"Services"
        }
    ],
    "sg:phone":"+1 701 252 0319",
    "sg:postcode":"58401",
    "sg:province":"ND",
    "sg:tags":[
        "repairing",
        "automobile"
    ],
    "wof:name":"Dwaine's Auto Svc",
    "wof:placetype":"venue"
},
  "geometry": {"coordinates":[-98.711652,46.909795],"type":"Point"}
}