{
  "type": "Feature",
  "properties": {
    "iso:country":"US",
    "sg:address":"731 S Main Ave",
    "sg:city":"Dickinson",
    "sg:classifiers":[
        {
            "category":"Organizations",
            "subcategory":"Religious Organization",
            "type":"Services"
        }
    ],
    "sg:phone":"+1 701 225 1366",
    "sg:postcode":"58601",
    "sg:province":"ND",
    "wof:name":"Jehovahs Wtnesses Kingdom Hall",
    "wof:placetype":"venue"
},
  "geometry": {"coordinates":[-102.78977500000001,46.862296],"type":"Point"}
}