{
  "type": "Feature",
  "properties": {
    "addr:full":"100 E Broadway Ave Bismarck ND 58501",
    "addr:housenumber":"100",
    "addr:postcode":"58501",
    "addr:street":"E Broadway Ave",
    "iso:country":"US",
    "sg:address":"100 E Broadway Ave",
    "sg:city":"Bismarck",
    "sg:classifiers":[
        {
            "category":"Freight",
            "type":"Transportation"
        }
    ],
    "sg:phone":"+1 701 221 4205",
    "sg:postcode":"58501",
    "sg:province":"ND",
    "sg:tags":[
        "warehouse"
    ],
    "sg:website":"www.nemacwarehouse.com",
    "wof:name":"NEMAC Warehouse",
    "wof:placetype":"venue"
},
  "geometry": {"coordinates":[-100.789165,46.806512],"type":"Point"}
}