{
  "type": "Feature",
  "properties": {
    "addr:full":"107 W Main Ave Bismarck ND 58501",
    "addr:housenumber":"107",
    "addr:postcode":"58501",
    "addr:street":"W Main Ave",
    "iso:country":"US",
    "sg:address":"107 W Main Ave",
    "sg:city":"Bismarck",
    "sg:classifiers":[
        {
            "category":"Health Services",
            "subcategory":"Health Practitioner",
            "type":"Services"
        }
    ],
    "sg:phone":"+1 701 255 6032",
    "sg:postcode":"58501",
    "sg:province":"ND",
    "sg:tags":[
        "audiologists"
    ],
    "wof:name":"Audiological Services",
    "wof:placetype":"venue"
},
  "geometry": {"coordinates":[-100.792187,46.805442],"type":"Point"}
}