{
  "type": "Feature",
  "properties": {
    "addr:full":"8306 86th Ave SE Ellendale ND 58436",
    "addr:housenumber":"8306",
    "addr:postcode":"58436",
    "addr:street":"86Th Ave Se",
    "iso:country":"US",
    "sg:address":"8306 86th Ave SE",
    "sg:city":"Ellendale",
    "sg:phone":"+1 701 349 4815",
    "sg:postcode":"58436",
    "sg:province":"ND",
    "sg:tags":[
        "farm",
        "soybean"
    ],
    "wof:name":"Jason Hildenbrand",
    "wof:placetype":"venue"
},
  "geometry": {"coordinates":[-98.586911,46.214922],"type":"Point"}
}