{
  "type": "Feature",
  "properties": {
    "iso:country":"US",
    "sg:address":"3 4th St E",
    "sg:city":"Williston",
    "sg:classifiers":[
        {
            "category":"Communications",
            "type":"Services"
        }
    ],
    "sg:phone":"+1 701 774 3421",
    "sg:postcode":"58801",
    "sg:province":"ND",
    "wof:name":"Northwest Communication Co-Op",
    "wof:placetype":"venue"
},
  "geometry": {"coordinates":[-103.621973,48.147632],"type":"Point"}
}