{
  "type": "Feature",
  "properties": {
    "addr:full":"601 John St Rolette ND 58366",
    "addr:housenumber":"601",
    "addr:postcode":"58366",
    "addr:street":"John St",
    "iso:country":"US",
    "sg:address":"601 John St",
    "sg:city":"Rolette",
    "sg:classifiers":[
        {
            "category":"Professional",
            "subcategory":"Management & Consulting",
            "type":"Services"
        }
    ],
    "sg:phone":"+1 701 246 3321",
    "sg:postcode":"58366",
    "sg:province":"ND",
    "sg:tags":[
        "consultant",
        "business"
    ],
    "wof:name":"Davis & Assoc",
    "wof:placetype":"venue"
},
  "geometry": {"coordinates":[-99.84647699999999,48.665983],"type":"Point"}
}