{
  "type": "Feature",
  "properties": {
    "addr:full":"2549 94th Ave SE Wimbledon ND 58492",
    "addr:housenumber":"2549",
    "addr:postcode":"58492",
    "addr:street":"94Th Ave Se",
    "iso:country":"US",
    "sg:address":"2549 94th Ave SE",
    "sg:city":"Wimbledon",
    "sg:classifiers":[
        {
            "category":"Farming",
            "subcategory":"Livestock Farm",
            "type":"Manufacturing & Wholesale Goods"
        }
    ],
    "sg:phone":"+1 701 252 4140",
    "sg:postcode":"58492",
    "sg:province":"ND",
    "sg:tags":[
        "animal",
        "general"
    ],
    "wof:name":"Ames Farm",
    "wof:placetype":"venue"
},
  "geometry": {"coordinates":[-98.509727,47.044845],"type":"Point"}
}