{
  "type": "Feature",
  "properties": {
    "iso:country":"US",
    "sg:address":"101 4th Ave NE",
    "sg:city":"Lidgerwood",
    "sg:classifiers":[
        {
            "category":"Building & Trades",
            "subcategory":"Construction",
            "type":"Services"
        }
    ],
    "sg:phone":"+1 701 538 4089",
    "sg:postcode":"58053",
    "sg:province":"ND",
    "sg:tags":[
        "heavy"
    ],
    "wof:name":"Stroehl Construction",
    "wof:placetype":"venue"
},
  "geometry": {"coordinates":[-97.146036,46.077962],"type":"Point"}
}