{
  "type": "Feature",
  "properties": {
    "iso:country":"US",
    "sg:address":"3739 38th St S",
    "sg:city":"Fargo",
    "sg:classifiers":[
        {
            "category":"Wholesale",
            "subcategory":"Machinery & Supplies",
            "type":"Manufacturing & Wholesale Goods"
        }
    ],
    "sg:phone":"+1 701 277 8200",
    "sg:postcode":"58104",
    "sg:province":"ND",
    "sg:tags":[
        "equipment",
        "vehicle"
    ],
    "wof:name":"Midland Mfg Inc",
    "wof:placetype":"venue"
},
  "geometry": {"coordinates":[-96.840576,46.820582],"type":"Point"}
}