{
  "type": "Feature",
  "properties": {
    "addr:full":"2315 N Washington St Grand Forks ND 58203",
    "addr:housenumber":"2315",
    "addr:postcode":"58203",
    "addr:street":"N Washington St",
    "iso:country":"US",
    "sg:address":"2315 N Washington St",
    "sg:city":"Grand Forks",
    "sg:classifiers":[
        {
            "category":"Wholesale",
            "subcategory":"Construction Materials",
            "type":"Manufacturing & Wholesale Goods"
        }
    ],
    "sg:phone":"+1 701 746 6253",
    "sg:postcode":"58203",
    "sg:province":"ND",
    "sg:tags":[
        "sand",
        "gravel"
    ],
    "wof:name":"Storbakken Trucking",
    "wof:placetype":"venue"
},
  "geometry": {"coordinates":[-97.066259,47.94468],"type":"Point"}
}