{
  "type": "Feature",
  "properties": {
    "iso:country":"US",
    "sg:address":"4085 51st Ave SE",
    "sg:city":"Medina",
    "sg:classifiers":[
        {
            "category":"Farming",
            "subcategory":"Farm",
            "type":"Manufacturing & Wholesale Goods"
        }
    ],
    "sg:phone":"+1 701 486 3279",
    "sg:postcode":"58467",
    "sg:province":"ND",
    "wof:name":"Darin Dockter Farm",
    "wof:placetype":"venue"
},
  "geometry": {"coordinates":[-99.384525,46.822256],"type":"Point"}
}