{
  "type": "Feature",
  "properties": {
    "iso:country":"US",
    "sg:address":"900 Forest Rd",
    "sg:city":"Minot",
    "sg:classifiers":[
        {
            "category":"Sports & Exercise",
            "subcategory":"Golf",
            "type":"Entertainment"
        }
    ],
    "sg:phone":"+1 701 857 1570",
    "sg:postcode":"58701",
    "sg:province":"ND",
    "sg:tags":[
        "course"
    ],
    "wof:name":"Jack Hoeven Wee Links",
    "wof:placetype":"venue"
},
  "geometry": {"coordinates":[-101.316874,48.228367],"type":"Point"}
}