{
  "type": "Feature",
  "properties": {
    "addr:full":"9300 114th Ave NW Minot ND 58703",
    "addr:housenumber":"9300",
    "addr:postcode":"58703",
    "addr:street":"114Th Ave Nw",
    "iso:country":"US",
    "sg:address":"9300 114th Ave NW",
    "sg:city":"Minot",
    "sg:classifiers":[
        {
            "category":"Autos & Motor Vehicles",
            "subcategory":"Automobile Sales",
            "type":"Retail Goods"
        }
    ],
    "sg:phone":"+1 701 725 4818",
    "sg:postcode":"58703",
    "sg:province":"ND",
    "sg:tags":[
        "used"
    ],
    "wof:name":"Lenzke Auto Enterprises",
    "wof:placetype":"venue"
},
  "geometry": {"coordinates":[-101.44608100000001,48.356257],"type":"Point"}
}