{
  "type": "Feature",
  "properties": {
    "iso:country":"US",
    "sg:address":"12238 19th St NE",
    "sg:city":"Aneta",
    "sg:classifiers":[
        {
            "category":"Organizations",
            "subcategory":"Religious Organization",
            "type":"Services"
        }
    ],
    "sg:phone":"+1 701 326 4300",
    "sg:postcode":"58212",
    "sg:province":"ND",
    "wof:name":"Aneta Community Church",
    "wof:placetype":"venue"
},
  "geometry": {"coordinates":[-97.97539399999999,47.686688],"type":"Point"}
}