{
  "type": "Feature",
  "properties": {
    "iso:country":"US",
    "sg:address":"2525 Smokey Ln",
    "sg:city":"Bismarck",
    "sg:phone":"+1 701 258 6995",
    "sg:postcode":"58504",
    "sg:province":"ND",
    "sg:tags":[
        "farm",
        "wheat"
    ],
    "wof:name":"Guy Otteson",
    "wof:placetype":"venue"
},
  "geometry": {"coordinates":[-100.818022,46.774996],"type":"Point"}
}