{
  "type": "Feature",
  "properties": {
    "addr:full":"1345 Main Ave Fargo ND 58103",
    "addr:housenumber":"1345",
    "addr:postcode":"58103",
    "addr:street":"Main Ave",
    "iso:country":"US",
    "sg:address":"1345 Main Ave",
    "sg:city":"Fargo",
    "sg:classifiers":[
        {
            "category":"Manufacturing",
            "subcategory":"Tools & Machinery",
            "type":"Manufacturing & Wholesale Goods"
        }
    ],
    "sg:phone":"+1 701 280 1122",
    "sg:postcode":"58103",
    "sg:province":"ND",
    "sg:tags":[
        "equipment",
        "electric"
    ],
    "sg:website":"www.idaco.com",
    "wof:name":"IDA Corp",
    "wof:placetype":"venue"
},
  "geometry": {"coordinates":[-96.799504,46.875108],"type":"Point"}
}