{
  "type": "Feature",
  "properties": {
    "iso:country":"US",
    "sg:address":"617 17th Ave W",
    "sg:city":"Williston",
    "sg:classifiers":[
        {
            "category":"Building & Trades",
            "subcategory":"Construction",
            "type":"Services"
        }
    ],
    "sg:phone":"+1 701 572 8135",
    "sg:postcode":"58801",
    "sg:province":"ND",
    "sg:tags":[
        "contractor"
    ],
    "wof:name":"Oscar Noriega",
    "wof:placetype":"venue"
},
  "geometry": {"coordinates":[-103.647363,48.149559],"type":"Point"}
}