{
  "type": "Feature",
  "properties": {
    "iso:country":"US",
    "sg:address":"3209 Fiechtner Dr",
    "sg:city":"Fargo",
    "sg:classifiers":[
        {
            "category":"Insurance",
            "subcategory":"Insurance Agent",
            "type":"Services"
        }
    ],
    "sg:phone":"+1 701 235 0408",
    "sg:postcode":"58103",
    "sg:province":"ND",
    "wof:name":"Fargo Office",
    "wof:placetype":"venue"
},
  "geometry": {"coordinates":[-96.830528,46.86564],"type":"Point"}
}