{
  "type": "Feature",
  "properties": {
    "iso:country":"US",
    "sg:address":"5711 Co Rd 17 S",
    "sg:city":"Fargo",
    "sg:classifiers":[
        {
            "category":"Building & Trades",
            "subcategory":"Construction",
            "type":"Services"
        }
    ],
    "sg:phone":"+1 701 282 7668",
    "sg:postcode":"58104",
    "sg:province":"ND",
    "sg:tags":[
        "general",
        "contractor"
    ],
    "wof:name":"Bernath Construction Inc",
    "wof:placetype":"venue"
},
  "geometry": {"coordinates":[-96.902824,46.79624],"type":"Point"}
}