{
  "type": "Feature",
  "properties": {
    "iso:country":"US",
    "sg:address":"117 W Front Ave",
    "sg:city":"Bismarck",
    "sg:classifiers":[
        {
            "category":"Wholesale",
            "subcategory":"Office Equipment",
            "type":"Manufacturing & Wholesale Goods"
        },
        {
            "category":"Professional",
            "subcategory":"Business Services",
            "type":"Services"
        },
        {
            "category":"Professional",
            "subcategory":"Printing & Photocopies",
            "type":"Services"
        },
        {
            "category":"Shopping",
            "subcategory":"Computers & Home Electronics",
            "type":"Retail Goods"
        }
    ],
    "sg:phone":"+1 701 223 0505",
    "sg:postcode":"58504",
    "sg:province":"ND",
    "sg:tags":[
        "scanning",
        "printer",
        "supply",
        "services-commercial",
        "duplicating",
        "shipping",
        "copying",
        "mail",
        "plotting"
    ],
    "sg:website":"http://www.unitedprinting.com/WEDDINGS",
    "wof:name":"United Printing And Mailing",
    "wof:placetype":"venue"
},
  "geometry": {"coordinates":[-100.790994,46.804196],"type":"Point"}
}