{
  "type": "Feature",
  "properties": {
    "addr:full":"116 5th St W Bottineau ND 58318",
    "addr:housenumber":"116",
    "addr:postcode":"58318",
    "addr:street":"5Th St W Bottineau",
    "iso:country":"US",
    "sg:address":"116 5th St W",
    "sg:city":"Bottineau",
    "sg:classifiers":[
        {
            "category":"Professional",
            "subcategory":"Lawyer & Legal Services",
            "type":"Services"
        }
    ],
    "sg:phone":"+1 701 228 3624",
    "sg:postcode":"58318",
    "sg:province":"ND",
    "sg:tags":[
        "attorney"
    ],
    "wof:name":"Mc Intee Law Firm",
    "wof:placetype":"venue"
},
  "geometry": {"coordinates":[-100.446538,48.827402],"type":"Point"}
}