{
  "type": "Feature",
  "properties": {
    "iso:country":"US",
    "sg:address":"209 Maine St",
    "sg:city":"Christine",
    "sg:classifiers":[
        {
            "category":"Home & Garden",
            "subcategory":"Building Materials",
            "type":"Retail Goods"
        }
    ],
    "sg:phone":"+1 701 998 2003",
    "sg:postcode":"58015",
    "sg:province":"ND",
    "sg:tags":[
        "glass",
        "leaded"
    ],
    "wof:name":"Stained Glass Overlay",
    "wof:placetype":"venue"
},
  "geometry": {"coordinates":[-96.80604599999999,46.574752],"type":"Point"}
}