{
  "type": "Feature",
  "properties": {
    "addr:full":"1616 N 17th St Bismarck ND 58501",
    "addr:housenumber":"1616",
    "addr:postcode":"58501",
    "addr:street":"N 17Th St",
    "iso:country":"US",
    "sg:address":"1616 N 17th St",
    "sg:city":"Bismarck",
    "sg:classifiers":[
        {
            "category":"Professional",
            "subcategory":"Business Services",
            "type":"Services"
        }
    ],
    "sg:phone":"+1 701 223 4444",
    "sg:postcode":"58501",
    "sg:province":"ND",
    "wof:name":"Blind Shine",
    "wof:placetype":"venue"
},
  "geometry": {"coordinates":[-100.766347,46.823452],"type":"Point"}
}