{
  "type": "Feature",
  "properties": {
    "iso:country":"US",
    "sg:address":"313 3rd Ave",
    "sg:city":"Petersburg",
    "sg:classifiers":[
        {
            "category":"Shopping",
            "subcategory":"Bicycles & Sporting Goods",
            "type":"Retail Goods"
        }
    ],
    "sg:phone":"+1 701 345 8242",
    "sg:postcode":"58272",
    "sg:province":"ND",
    "sg:tags":[
        "saddlery",
        "harness"
    ],
    "wof:name":"Roland Harness Supply",
    "wof:placetype":"venue"
},
  "geometry": {"coordinates":[-97.99964300000001,48.010754],"type":"Point"}
}