{
  "type": "Feature",
  "properties": {
    "iso:country":"US",
    "sg:address":"3200 Majestic St",
    "sg:city":"Bismarck",
    "sg:classifiers":[
        {
            "category":"Shopping",
            "subcategory":"Florist",
            "type":"Retail Goods"
        }
    ],
    "sg:phone":"+1 701 255 7782",
    "sg:postcode":"58504",
    "sg:province":"ND",
    "wof:name":"For All Occasions",
    "wof:placetype":"venue"
},
  "geometry": {"coordinates":[-100.68171599999999,46.754814],"type":"Point"}
}