{
  "type": "Feature",
  "properties": {
    "iso:country":"US",
    "sg:address":"1827 Lovett Ave",
    "sg:city":"Bismarck",
    "sg:classifiers":[
        {
            "category":"Retail",
            "subcategory":"Auto Repair",
            "type":"Services"
        }
    ],
    "sg:phone":"+1 701 258 8800",
    "sg:postcode":"58504",
    "sg:province":"ND",
    "sg:website":"www.countryautoclinic.com",
    "wof:name":"Country Auto Clinic Inc",
    "wof:placetype":"venue"
},
  "geometry": {"coordinates":[-100.763299,46.793292],"type":"Point"}
}