{
  "type": "Feature",
  "properties": {
    "iso:country":"US",
    "sg:address":"26 Roberts St N",
    "sg:city":"Fargo",
    "sg:classifiers":[
        {
            "category":"Real Estate",
            "subcategory":"Real Estate Agent",
            "type":"Services"
        }
    ],
    "sg:phone":"+1 701 232 4505",
    "sg:postcode":"58102",
    "sg:province":"ND",
    "sg:tags":[
        "management"
    ],
    "wof:name":"Paramount Property Mgmt LLC",
    "wof:placetype":"venue"
},
  "geometry": {"coordinates":[-96.790229,46.876056],"type":"Point"}
}