{
  "type": "Feature",
  "properties": {
    "addr:full":"423 2nd St E Napoleon ND 58561",
    "addr:housenumber":"423",
    "addr:postcode":"58561",
    "addr:street":"2Nd St;Napoleon",
    "iso:country":"US",
    "sg:address":"423 2nd St E",
    "sg:city":"Napoleon",
    "sg:classifiers":[
        {
            "category":"Organizations",
            "subcategory":"Religious Organization",
            "type":"Services"
        }
    ],
    "sg:phone":"+1 701 754 2500",
    "sg:postcode":"58561",
    "sg:province":"ND",
    "wof:name":"Trinity Lutheran Church",
    "wof:placetype":"venue"
},
  "geometry": {"coordinates":[-99.767512,46.504386],"type":"Point"}
}