{
  "type": "Feature",
  "properties": {
    "iso:country":"US",
    "sg:address":"1820 75th Ave SE",
    "sg:city":"Pingree",
    "sg:phone":"+1 701 252 6844",
    "sg:postcode":"58476",
    "sg:province":"ND",
    "sg:tags":[
        "farm",
        "grain"
    ],
    "wof:name":"Kleinknecht Delno Farm",
    "wof:placetype":"venue"
},
  "geometry": {"coordinates":[-98.911507,47.150428],"type":"Point"}
}