{
  "type": "Feature",
  "properties": {
    "iso:country":"US",
    "sg:address":"305 3rd St",
    "sg:city":"Manvel",
    "sg:classifiers":[
        {
            "category":"Retail",
            "subcategory":"Auto Repair",
            "type":"Services"
        }
    ],
    "sg:phone":"+1 701 696 2020",
    "sg:postcode":"58256",
    "sg:province":"ND",
    "sg:tags":[
        "repairing",
        "automobile",
        "general"
    ],
    "wof:name":"Jim's Bumper To Bumper",
    "wof:placetype":"venue"
},
  "geometry": {"coordinates":[-97.177025,48.077608],"type":"Point"}
}