{
  "type": "Feature",
  "properties": {
    "iso:country":"US",
    "sg:address":"1206 1st Ave S",
    "sg:city":"Fargo",
    "sg:classifiers":[
        {
            "category":"Health Services",
            "subcategory":"Chiropractor",
            "type":"Services"
        }
    ],
    "sg:phone":"+1 701 451 9098",
    "sg:postcode":"58103",
    "sg:province":"ND",
    "wof:name":"Midwest Spine & Sports Clinic",
    "wof:placetype":"venue"
},
  "geometry": {"coordinates":[-96.79823399999999,46.873878],"type":"Point"}
}