{
  "type": "Feature",
  "properties": {
    "addr:full":"235 Broadway Medora ND 58645",
    "addr:housenumber":"235",
    "addr:postcode":"58645",
    "addr:street":"Broadway",
    "iso:country":"US",
    "sg:address":"235 Broadway",
    "sg:city":"Medora",
    "sg:classifiers":[
        {
            "category":"Shopping",
            "subcategory":"Used Merchandise",
            "type":"Retail Goods"
        }
    ],
    "sg:phone":"+1 701 623 3322",
    "sg:postcode":"58645",
    "sg:province":"ND",
    "sg:tags":[
        "antique"
    ],
    "wof:name":"O Quarter Circle Antiques",
    "wof:placetype":"venue"
},
  "geometry": {"coordinates":[-103.52468399999999,46.913812],"type":"Point"}
}