{
  "type": "Feature",
  "properties": {
    "iso:country":"US",
    "sg:address":"7935 173rd Ave SE",
    "sg:city":"Wahpeton",
    "sg:phone":"+1 701 642 6846",
    "sg:postcode":"58075",
    "sg:province":"ND",
    "sg:tags":[
        "farm",
        "corn"
    ],
    "wof:name":"Kevin Onchuck",
    "wof:placetype":"venue"
},
  "geometry": {"coordinates":[-96.781988,46.263553],"type":"Point"}
}