{
  "type": "Feature",
  "properties": {
    "iso:country":"US",
    "sg:address":"114 N 3rd St",
    "sg:city":"Bismarck",
    "sg:classifiers":[
        {
            "category":"Organizations",
            "subcategory":"Religious Organization",
            "type":"Services"
        }
    ],
    "sg:phone":"+1 701 663 4287",
    "sg:postcode":"58501",
    "sg:province":"ND",
    "sg:tags":[
        "church"
    ],
    "wof:name":"Covenant Orthodox Presbyterian",
    "wof:placetype":"venue"
},
  "geometry": {"coordinates":[-100.787729,46.806342],"type":"Point"}
}