{
  "type": "Feature",
  "properties": {
    "iso:country":"US",
    "sg:address":"725 12th St E",
    "sg:city":"Dickinson",
    "sg:classifiers":[
        {
            "category":"Organizations",
            "subcategory":"Religious Organization",
            "type":"Services"
        }
    ],
    "sg:phone":"+1 701 483 2134",
    "sg:postcode":"58601",
    "sg:province":"ND",
    "sg:website":"www.queenofpeacedickinson.org",
    "wof:name":"Queen Of Peace Parish",
    "wof:placetype":"venue"
},
  "geometry": {"coordinates":[-102.77273700000001,46.893416],"type":"Point"}
}