{
  "type": "Feature",
  "properties": {
    "iso:country":"US",
    "sg:address":"20 Burdick Expy W",
    "sg:city":"Minot",
    "sg:classifiers":[
        {
            "category":"Health Services",
            "subcategory":"Podiatrist",
            "type":"Services"
        },
        {
            "category":"Health Services",
            "subcategory":"Doctor",
            "type":"Services"
        }
    ],
    "sg:phone":"+1 701 857 5419",
    "sg:postcode":"58701",
    "sg:province":"ND",
    "sg:tags":[
        "medical"
    ],
    "wof:name":"R J Deckert DPM",
    "wof:placetype":"venue"
},
  "geometry": {"coordinates":[-101.29360200000001,48.23271],"type":"Point"}
}