{
  "type": "Feature",
  "properties": {
    "iso:country":"US",
    "sg:address":"213 Main St",
    "sg:city":"Wing",
    "sg:classifiers":[
        {
            "category":"Social Services",
            "subcategory":"Adult Care",
            "type":"Services"
        }
    ],
    "sg:phone":"+1 701 943 2490",
    "sg:postcode":"58494",
    "sg:province":"ND",
    "sg:tags":[
        "organization",
        "senior",
        "citizen"
    ],
    "wof:name":"Wing Senior Ctr",
    "wof:placetype":"venue"
},
  "geometry": {"coordinates":[-100.27968799999999,47.14131],"type":"Point"}
}