{
  "type": "Feature",
  "properties": {
    "addr:full":"163 S Main Ave Dickinson ND 58601",
    "addr:housenumber":"163",
    "addr:postcode":"58601",
    "addr:street":"S Main Ave",
    "iso:country":"US",
    "sg:address":"163 S Main Ave",
    "sg:city":"Dickinson",
    "sg:classifiers":[
        {
            "category":"Food & Beverages",
            "subcategory":"Liquor & Beverages",
            "type":"Retail Goods"
        }
    ],
    "sg:phone":"+1 701 483 4357",
    "sg:postcode":"58601",
    "sg:province":"ND",
    "wof:name":"Frontier Liquors",
    "wof:placetype":"venue"
},
  "geometry": {"coordinates":[-102.789929,46.875025],"type":"Point"}
}