{
  "type": "Feature",
  "properties": {
    "iso:country":"US",
    "sg:address":"517 Main St",
    "sg:city":"Ellendale",
    "sg:classifiers":[
        {
            "category":"Government",
            "subcategory":"Office",
            "type":"Public Place"
        }
    ],
    "sg:phone":"+1 701 742 3328",
    "sg:postcode":"58436",
    "sg:province":"ND",
    "sg:tags":[
        "county",
        "resource"
    ],
    "wof:name":"Dickey County Social Svc",
    "wof:placetype":"venue"
},
  "geometry": {"coordinates":[-98.521512,46.001578],"type":"Point"}
}