{
  "type": "Feature",
  "properties": {
    "iso:country":"US",
    "sg:address":"14874 State Hwy 17",
    "sg:city":"Grafton",
    "sg:classifiers":[
        {
            "category":"Wholesale",
            "subcategory":"Chemicals & Plastics",
            "type":"Manufacturing & Wholesale Goods"
        }
    ],
    "sg:phone":"+1 701 352 2510",
    "sg:postcode":"58237",
    "sg:province":"ND",
    "wof:name":"Agsco",
    "wof:placetype":"venue"
},
  "geometry": {"coordinates":[-97.431945,48.412557],"type":"Point"}
}