{
  "type": "Feature",
  "properties": {
    "addr:full":"11 4th Ave S Carrington ND 58421",
    "addr:housenumber":"11",
    "addr:postcode":"58421",
    "addr:street":"4Th Ave S Carrington",
    "iso:country":"US",
    "sg:address":"11 4th Ave S",
    "sg:city":"Carrington",
    "sg:classifiers":[
        {
            "category":"Food & Beverages",
            "subcategory":"Groceries & Convenience Stores",
            "type":"Retail Goods"
        }
    ],
    "sg:phone":"+1 701 652 2107",
    "sg:postcode":"58421",
    "sg:province":"ND",
    "wof:name":"Sooper C",
    "wof:placetype":"venue"
},
  "geometry": {"coordinates":[-99.117417,47.449456],"type":"Point"}
}