{
  "type": "Feature",
  "properties": {
    "iso:country":"US",
    "sg:address":"1820 State Hwy 32 N",
    "sg:city":"Walhalla",
    "sg:classifiers":[
        {
            "category":"Home & Garden",
            "subcategory":"Hardware",
            "type":"Retail Goods"
        }
    ],
    "sg:phone":"+1 701 549 2320",
    "sg:postcode":"58282",
    "sg:province":"ND",
    "wof:name":"Walhalla Home & Building Ctr",
    "wof:placetype":"venue"
},
  "geometry": {"coordinates":[-97.90706400000001,48.930836],"type":"Point"}
}