{
  "type": "Feature",
  "properties": {
    "iso:country":"US",
    "sg:address":"322 Main St",
    "sg:city":"Williston",
    "sg:classifiers":[
        {
            "category":"Professional",
            "subcategory":"Accounting & Tax Preparation",
            "type":"Services"
        }
    ],
    "sg:phone":"+1 701 577 1177",
    "sg:postcode":"58801",
    "sg:province":"ND",
    "sg:tags":[
        "bookkeeping",
        "general"
    ],
    "wof:name":"Consolidated Professional Svcs",
    "wof:placetype":"venue"
},
  "geometry": {"coordinates":[-103.62176700000001,48.146779],"type":"Point"}
}