{
  "type": "Feature",
  "properties": {
    "addr:full":"722 Front St Casselton ND 58012",
    "addr:housenumber":"722",
    "addr:postcode":"58012",
    "addr:street":"Front St",
    "iso:country":"US",
    "sg:address":"722 Front St",
    "sg:city":"Casselton",
    "sg:classifiers":[
        {
            "category":"Professional",
            "subcategory":"Accounting & Tax Preparation",
            "type":"Services"
        }
    ],
    "sg:phone":"+1 701 347 4363",
    "sg:postcode":"58012",
    "sg:province":"ND",
    "sg:tags":[
        "return",
        "filing"
    ],
    "wof:name":"Piper Tax Svc Inc",
    "wof:placetype":"venue"
},
  "geometry": {"coordinates":[-97.211116,46.900568],"type":"Point"}
}