{
  "type": "Feature",
  "properties": {
    "iso:country":"US",
    "sg:address":"2452 Buffalo Ml",
    "sg:city":"Jamestown",
    "sg:classifiers":[
        {
            "category":"Shopping",
            "subcategory":"Clothing, Apparel, & Fashions",
            "type":"Retail Goods"
        }
    ],
    "sg:phone":"+1 701 251 2501",
    "sg:postcode":"58401",
    "sg:province":"ND",
    "sg:website":"www.vanityshops.com",
    "wof:name":"Vanity",
    "wof:placetype":"venue"
},
  "geometry": {"coordinates":[-98.723187,46.882857],"type":"Point"}
}