{
  "type": "Feature",
  "properties": {
    "iso:country":"US",
    "sg:address":"165 Railroad St",
    "sg:city":"Killdeer",
    "sg:classifiers":[
        {
            "category":"Government",
            "subcategory":"Police Station",
            "type":"Public Place"
        }
    ],
    "sg:phone":"+1 701 764 5678",
    "sg:postcode":"58640",
    "sg:province":"ND",
    "sg:tags":[
        "protection"
    ],
    "wof:name":"Killdeer Police Department",
    "wof:placetype":"venue"
},
  "geometry": {"coordinates":[-102.751428,47.368833],"type":"Point"}
}