{
  "type": "Feature",
  "properties": {
    "addr:full":"120 N 3rd St Bismarck ND 58501",
    "addr:housenumber":"120",
    "addr:postcode":"58501",
    "addr:street":"N 3Rd St",
    "iso:country":"US",
    "sg:address":"120 N 3rd St",
    "sg:city":"Bismarck",
    "sg:classifiers":[
        {
            "category":"Insurance",
            "subcategory":"Life Insurance",
            "type":"Services"
        }
    ],
    "sg:phone":"+1 701 224 0664",
    "sg:postcode":"58501",
    "sg:province":"ND",
    "sg:tags":[
        "carrier",
        "carrie"
    ],
    "wof:name":"Prudential",
    "wof:placetype":"venue"
},
  "geometry": {"coordinates":[-100.787729,46.80628],"type":"Point"}
}