{
  "type": "Feature",
  "properties": {
    "iso:country":"US",
    "sg:address":"1834 Rose Creek Dr",
    "sg:city":"Fargo",
    "sg:classifiers":[
        {
            "category":"Professional",
            "subcategory":"Business Services",
            "type":"Services"
        }
    ],
    "sg:phone":"+1 701 235 8803",
    "sg:postcode":"58104",
    "sg:province":"ND",
    "sg:tags":[
        "interior",
        "consultant",
        "design",
        "decorator"
    ],
    "wof:name":"Denise Drake Interior Design",
    "wof:placetype":"venue"
},
  "geometry": {"coordinates":[-96.809541,46.818099],"type":"Point"}
}