{
  "type": "Feature",
  "properties": {
    "iso:country":"US",
    "sg:address":"302 4th Ave E",
    "sg:city":"West Fargo",
    "sg:classifiers":[
        {
            "category":"Social Services",
            "subcategory":"Child Care",
            "type":"Services"
        }
    ],
    "sg:phone":"+1 701 282 6675",
    "sg:postcode":"58078",
    "sg:province":"ND",
    "sg:tags":[
        "day"
    ],
    "wof:name":"Holmes Family Day Care",
    "wof:placetype":"venue"
},
  "geometry": {"coordinates":[-96.895365,46.872787],"type":"Point"}
}