{
  "type": "Feature",
  "properties": {
    "iso:country":"US",
    "sg:address":"1106 Main Ave W",
    "sg:city":"Rolla",
    "sg:classifiers":[
        {
            "category":"Government",
            "subcategory":"Office",
            "type":"Public Place"
        }
    ],
    "sg:phone":"+1 701 477 3167",
    "sg:postcode":"58367",
    "sg:province":"ND",
    "wof:name":"FARM Service Agency",
    "wof:placetype":"venue"
},
  "geometry": {"coordinates":[-99.632007,48.851331],"type":"Point"}
}