{
  "type": "Feature",
  "properties": {
    "iso:country":"US",
    "sg:address":"3198 State Hwy 16",
    "sg:city":"Beach",
    "sg:classifiers":[
        {
            "category":"Autos & Motor Vehicles",
            "subcategory":"Automobile Sales",
            "type":"Retail Goods"
        }
    ],
    "sg:phone":"+1 701 872 3632",
    "sg:postcode":"58621",
    "sg:province":"ND",
    "sg:tags":[
        "truck"
    ],
    "wof:name":"C P & The Farm Boys Truck-Auto",
    "wof:placetype":"venue"
},
  "geometry": {"coordinates":[-104.007859,46.948235],"type":"Point"}
}