{
  "type": "Feature",
  "properties": {
    "addr:full":"203 2nd St W Taylor ND 58656",
    "addr:housenumber":"203",
    "addr:postcode":"58656",
    "addr:street":"2Nd St W",
    "iso:country":"US",
    "sg:address":"203 2nd St W",
    "sg:city":"Taylor",
    "sg:classifiers":[
        {
            "category":"Organizations",
            "subcategory":"Religious Organization",
            "type":"Services"
        }
    ],
    "sg:phone":"+1 701 974 3773",
    "sg:postcode":"58656",
    "sg:province":"ND",
    "sg:tags":[
        "clergy"
    ],
    "wof:name":"Taylor Lutheran Parsonage",
    "wof:placetype":"venue"
},
  "geometry": {"coordinates":[-102.42577199999999,46.902759],"type":"Point"}
}