{
  "type": "Feature",
  "properties": {
    "addr:full":"3500 E Rosser Ave Bismarck ND 58501",
    "addr:housenumber":"3500",
    "addr:postcode":"58501",
    "addr:street":"E Rosser Ave",
    "iso:country":"US",
    "sg:address":"3500 E Rosser Ave",
    "sg:city":"Bismarck",
    "sg:classifiers":[
        {
            "category":"Professional",
            "type":"Services"
        }
    ],
    "sg:phone":"+1 701 223 9365",
    "sg:postcode":"58501",
    "sg:province":"ND",
    "sg:tags":[
        "establishment"
    ],
    "wof:name":"MCI/Btna",
    "wof:placetype":"venue"
},
  "geometry": {"coordinates":[-100.73693900000001,46.809087],"type":"Point"}
}