{
  "type": "Feature",
  "properties": {
    "addr:full":"7659 139th Ave NW Zahl ND 58856",
    "addr:housenumber":"7659",
    "addr:postcode":"58856",
    "addr:street":"139Th Ave Nw",
    "iso:country":"US",
    "sg:address":"7659 139th Ave NW",
    "sg:city":"Zahl",
    "sg:phone":"+1 701 694 4721",
    "sg:postcode":"58856",
    "sg:province":"ND",
    "sg:tags":[
        "beef",
        "farm",
        "cash",
        "grain",
        "cattle",
        "feedlot"
    ],
    "wof:name":"Ted Haugen",
    "wof:placetype":"venue"
},
  "geometry": {"coordinates":[-103.689555,48.526327],"type":"Point"}
}