{
  "type": "Feature",
  "properties": {
    "iso:country":"US",
    "sg:address":"15 E 5th St",
    "sg:city":"Grafton",
    "sg:classifiers":[
        {
            "category":"Bars & Pubs",
            "type":"Food & Drink"
        }
    ],
    "sg:phone":"+1 701 352 2229",
    "sg:postcode":"58237",
    "sg:province":"ND",
    "sg:tags":[
        "drinking"
    ],
    "wof:name":"Extra End The",
    "wof:placetype":"venue"
},
  "geometry": {"coordinates":[-97.410067,48.419624],"type":"Point"}
}