{
  "type": "Feature",
  "properties": {
    "iso:country":"US",
    "sg:address":"10925 State Hwy 28",
    "sg:city":"Sherwood",
    "sg:classifiers":[
        {
            "category":"Building & Trades",
            "subcategory":"Cleaning & Sanitation",
            "type":"Services"
        }
    ],
    "sg:phone":"+1 701 459 2498",
    "sg:postcode":"58782",
    "sg:province":"ND",
    "wof:name":"Verlae M Martel",
    "wof:placetype":"venue"
},
  "geometry": {"coordinates":[-101.627853,48.998031],"type":"Point"}
}