{
  "type": "Feature",
  "properties": {
    "iso:country":"US",
    "sg:address":"448 21st St E",
    "sg:city":"Dickinson",
    "sg:classifiers":[
        {
            "category":"Professional",
            "subcategory":"Accounting & Tax Preparation",
            "type":"Services"
        }
    ],
    "sg:phone":"+1 701 225 1613",
    "sg:postcode":"58601",
    "sg:province":"ND",
    "sg:tags":[
        "accountant"
    ],
    "sg:website":"www.lercpa.com",
    "wof:name":"Larry E Robinson CPA",
    "wof:placetype":"venue"
},
  "geometry": {"coordinates":[-102.77849000000001,46.904803],"type":"Point"}
}