{
  "type": "Feature",
  "properties": {
    "addr:full":"210 S Main St Hettinger ND 58639",
    "addr:housenumber":"210",
    "addr:postcode":"58639",
    "addr:street":"S Main St",
    "iso:country":"US",
    "sg:address":"210 S Main St",
    "sg:city":"Hettinger",
    "sg:classifiers":[
        {
            "category":"Insurance",
            "subcategory":"Insurance Agent",
            "type":"Services"
        }
    ],
    "sg:phone":"+1 701 579 4630",
    "sg:postcode":"58639",
    "sg:province":"ND",
    "wof:name":"Nodak Mutual Insurance Company",
    "wof:placetype":"venue"
},
  "geometry": {"coordinates":[-102.636808,45.999667],"type":"Point"}
}