{
  "type": "Feature",
  "properties": {
    "iso:country":"US",
    "sg:address":"101 5th St SW",
    "sg:city":"Hillsboro",
    "sg:classifiers":[
        {
            "category":"Travel",
            "subcategory":"Hotels & Motels",
            "type":"Entertainment"
        }
    ],
    "sg:phone":"+1 701 436 5501",
    "sg:postcode":"58045",
    "sg:province":"ND",
    "wof:name":"Hillsboro Inn",
    "wof:placetype":"venue"
},
  "geometry": {"coordinates":[-97.06871599999999,47.40168],"type":"Point"}
}