{
  "type": "Feature",
  "properties": {
    "addr:full":"205 State Hwy 49 Beulah ND 58523",
    "addr:housenumber":"205",
    "addr:postcode":"58523",
    "addr:street":"State Hwy 49",
    "iso:country":"US",
    "sg:address":"205 State Hwy 49",
    "sg:city":"Beulah",
    "sg:classifiers":[
        {
            "category":"Freight",
            "type":"Transportation"
        }
    ],
    "sg:phone":"+1 701 873 5635",
    "sg:postcode":"58523",
    "sg:province":"ND",
    "wof:name":"Department Of Transportation",
    "wof:placetype":"venue"
},
  "geometry": {"coordinates":[-101.78573299999999,47.265496],"type":"Point"}
}