{
  "type": "Feature",
  "properties": {
    "addr:full":"1412 2nd Ave W Williston ND 58801",
    "addr:housenumber":"1412",
    "addr:postcode":"58801",
    "addr:street":"2Nd Ave W",
    "iso:country":"US",
    "sg:address":"1412 2nd Ave W",
    "sg:city":"Williston",
    "sg:classifiers":[
        {
            "category":"Personal",
            "subcategory":"Barber",
            "type":"Services"
        }
    ],
    "sg:phone":"+1 701 572 2430",
    "sg:postcode":"58801",
    "sg:province":"ND",
    "sg:tags":[
        "shop"
    ],
    "wof:name":"Sunset Barber Shop",
    "wof:placetype":"venue"
},
  "geometry": {"coordinates":[-103.625681,48.157937],"type":"Point"}
}