{
  "type": "Feature",
  "properties": {
    "iso:country":"US",
    "sg:address":"1024 N 14th St",
    "sg:city":"Bismarck",
    "sg:classifiers":[
        {
            "category":"Retail",
            "subcategory":"Auto Repair",
            "type":"Services"
        }
    ],
    "sg:phone":"+1 701 400 5217",
    "sg:postcode":"58501",
    "sg:province":"ND",
    "sg:tags":[
        "automotive"
    ],
    "wof:name":"Larsons Creative Concepts",
    "wof:placetype":"venue"
},
  "geometry": {"coordinates":[-100.770937,46.816182],"type":"Point"}
}