{
  "type": "Feature",
  "properties": {
    "iso:country":"US",
    "sg:address":"303 Railway St",
    "sg:city":"Enderlin",
    "sg:classifiers":[
        {
            "category":"Organizations",
            "subcategory":"Non-profit Organization",
            "type":"Services"
        }
    ],
    "sg:phone":"+1 701 437 2877",
    "sg:postcode":"58027",
    "sg:province":"ND",
    "wof:name":"Heart LAHBNP",
    "wof:placetype":"venue"
},
  "geometry": {"coordinates":[-97.60216200000001,46.624654],"type":"Point"}
}