{
  "type": "Feature",
  "properties": {
    "addr:full":"120 26th St E Williston ND 58801",
    "addr:housenumber":"120",
    "addr:postcode":"58801",
    "addr:street":"26Th St E",
    "iso:country":"US",
    "sg:address":"120 26th St E",
    "sg:city":"Williston",
    "sg:classifiers":[
        {
            "category":"Retail",
            "subcategory":"Portrait Studio",
            "type":"Services"
        }
    ],
    "sg:phone":"+1 701 774 9440",
    "sg:postcode":"58801",
    "sg:province":"ND",
    "sg:tags":[
        "photographer"
    ],
    "wof:name":"Wal-Mart Portrait Studio",
    "wof:placetype":"venue"
},
  "geometry": {"coordinates":[-103.621488,48.168638],"type":"Point"}
}