{
  "type": "Feature",
  "properties": {
    "iso:country":"US",
    "sg:address":"230 Front St",
    "sg:city":"Sheldon",
    "sg:classifiers":[
        {
            "category":"Restaurant",
            "type":"Food & Drink"
        }
    ],
    "sg:phone":"+1 701 882 3376",
    "sg:postcode":"58068",
    "sg:province":"ND",
    "sg:tags":[
        "eating"
    ],
    "wof:name":"Sheldon Beef & Ale",
    "wof:placetype":"venue"
},
  "geometry": {"coordinates":[-97.491699,46.589121],"type":"Point"}
}