{
  "type": "Feature",
  "properties": {
    "iso:country":"US",
    "sg:address":"1612 13th St SW",
    "sg:city":"Minot",
    "sg:phone":"+1 701 838 8833",
    "sg:postcode":"58701",
    "sg:province":"ND",
    "sg:tags":[
        "product",
        "petroleum"
    ],
    "wof:name":"Northland Oil & Gas Corp",
    "wof:placetype":"venue"
},
  "geometry": {"coordinates":[-101.311086,48.217653],"type":"Point"}
}