{
  "type": "Feature",
  "properties": {
    "iso:country":"US",
    "sg:address":"1932 27th Ave NE",
    "sg:city":"Harvey",
    "sg:phone":"+1 701 324 2705",
    "sg:postcode":"58341",
    "sg:province":"ND",
    "sg:tags":[
        "farm",
        "wheat"
    ],
    "wof:name":"Gary Weinmann",
    "wof:placetype":"venue"
},
  "geometry": {"coordinates":[-100.005172,47.688409],"type":"Point"}
}