{
  "type": "Feature",
  "properties": {
    "addr:full":"315 S University Dr Fargo ND 58103",
    "addr:housenumber":"315",
    "addr:postcode":"58103",
    "addr:street":"S University Dr",
    "iso:country":"US",
    "sg:address":"315 S University Dr",
    "sg:city":"Fargo",
    "sg:classifiers":[
        {
            "category":"Professional",
            "subcategory":"Engineering",
            "type":"Services"
        }
    ],
    "sg:phone":"+1 701 232 0449",
    "sg:postcode":"58103",
    "sg:province":"ND",
    "sg:tags":[
        "design",
        "structural",
        "m",
        "engineer"
    ],
    "wof:name":"Hurst & Henrichs Ltd",
    "wof:placetype":"venue"
},
  "geometry": {"coordinates":[-96.79836899999999,46.87095],"type":"Point"}
}