{
  "type": "Feature",
  "properties": {
    "addr:full":"110 Cedar St E Gackle ND 58442",
    "addr:housenumber":"110",
    "addr:postcode":"58442",
    "addr:street":"Cedar St E Gackle",
    "iso:country":"US",
    "sg:address":"110 Cedar St E",
    "sg:city":"Gackle",
    "sg:classifiers":[
        {
            "category":"Shopping",
            "subcategory":"Hobbies, Toys, & Games",
            "type":"Retail Goods"
        }
    ],
    "sg:phone":"+1 701 485 3740",
    "sg:postcode":"58442",
    "sg:province":"ND",
    "sg:tags":[
        "product",
        "ceramic"
    ],
    "wof:name":"Side Street Ceramics",
    "wof:placetype":"venue"
},
  "geometry": {"coordinates":[-99.14206,46.628004],"type":"Point"}
}