{
  "type": "Feature",
  "properties": {
    "addr:full":"107 St Ann St St John ND 58369",
    "addr:housenumber":"107",
    "addr:postcode":"58369",
    "addr:street":"St Ann St",
    "iso:country":"US",
    "sg:address":"107 St Ann St",
    "sg:city":"St John",
    "sg:classifiers":[
        {
            "category":"Organizations",
            "subcategory":"Religious Organization",
            "type":"Services"
        }
    ],
    "sg:phone":"+1 701 477 3081",
    "sg:postcode":"58369",
    "sg:province":"ND",
    "sg:tags":[
        "church"
    ],
    "wof:name":"St John The Baptist Catholic",
    "wof:placetype":"venue"
},
  "geometry": {"coordinates":[-99.708264,48.945472],"type":"Point"}
}