{
  "type": "Feature",
  "properties": {
    "addr:full":"802 14th St NW Mandan ND 58554",
    "addr:housenumber":"802",
    "addr:postcode":"58554",
    "addr:street":"14Th St Nw",
    "iso:country":"US",
    "sg:address":"802 14th St NW",
    "sg:city":"Mandan",
    "sg:classifiers":[
        {
            "category":"Building & Trades",
            "subcategory":"Construction",
            "type":"Services"
        }
    ],
    "sg:phone":"+1 701 224 8214",
    "sg:postcode":"58554",
    "sg:province":"ND",
    "sg:tags":[
        "general",
        "contractor"
    ],
    "wof:name":"Midwest Maintenance & Constr",
    "wof:placetype":"venue"
},
  "geometry": {"coordinates":[-100.90463,46.838655],"type":"Point"}
}