{
  "type": "Feature",
  "properties": {
    "addr:full":"3805 4th Ave W Williston ND 58801",
    "addr:housenumber":"3805",
    "addr:postcode":"58801",
    "addr:street":"4Th Ave W",
    "iso:country":"US",
    "sg:address":"3805 4th Ave W",
    "sg:city":"Williston",
    "sg:classifiers":[
        {
            "category":"Retail",
            "subcategory":"Auto Repair",
            "type":"Services"
        }
    ],
    "sg:phone":"+1 701 572 2000",
    "sg:postcode":"58801",
    "sg:province":"ND",
    "sg:tags":[
        "transmission",
        "tractor"
    ],
    "wof:name":"Interstate Powersystems",
    "wof:placetype":"venue"
},
  "geometry": {"coordinates":[-103.62933099999999,48.180738],"type":"Point"}
}