{
  "type": "Feature",
  "properties": {
    "iso:country":"US",
    "sg:address":"10 1st Ave SW",
    "sg:city":"Minot",
    "sg:classifiers":[
        {
            "category":"Health Services",
            "subcategory":"Doctor",
            "type":"Services"
        }
    ],
    "sg:phone":"+1 701 852 3939",
    "sg:postcode":"58701",
    "sg:province":"ND",
    "sg:tags":[
        "dentist"
    ],
    "wof:name":"R L Wood DDS",
    "wof:placetype":"venue"
},
  "geometry": {"coordinates":[-101.293728,48.235489],"type":"Point"}
}