{
  "type": "Feature",
  "properties": {
    "iso:country":"US",
    "sg:address":"3902 13th Ave S",
    "sg:city":"Fargo",
    "sg:classifiers":[
        {
            "category":"Restaurant",
            "type":"Food & Drink"
        }
    ],
    "sg:phone":"+1 701 356 0366",
    "sg:postcode":"58103",
    "sg:province":"ND",
    "sg:tags":[
        "cafe"
    ],
    "wof:name":"Cajun Cafe",
    "wof:placetype":"venue"
},
  "geometry": {"coordinates":[-96.84670300000001,46.861535],"type":"Point"}
}