{
  "type": "Feature",
  "properties": {
    "addr:full":"3101 34th Ave SW Fargo ND 58104",
    "addr:housenumber":"3101",
    "addr:postcode":"58104",
    "addr:street":"34Th Ave Sw",
    "iso:country":"US",
    "sg:address":"3101 34th Ave SW",
    "sg:city":"Fargo",
    "sg:classifiers":[
        {
            "category":"Real Estate",
            "subcategory":"Real Estate Operator",
            "type":"Services"
        }
    ],
    "sg:phone":"+1 701 239 8140",
    "sg:postcode":"58104",
    "sg:province":"ND",
    "sg:tags":[
        "apartment"
    ],
    "wof:name":"Dakota Part Apartment Homes",
    "wof:placetype":"venue"
},
  "geometry": {"coordinates":[-96.830032,46.829681],"type":"Point"}
}