{
  "type": "Feature",
  "properties": {
    "iso:country":"US",
    "sg:address":"304 E Rosser Ave Ste 200",
    "sg:city":"Bismarck",
    "sg:classifiers":[
        {
            "category":"Restaurant",
            "type":"Food & Drink"
        }
    ],
    "sg:phone":"+1 701 223 8499",
    "sg:postcode":"58501",
    "sg:province":"ND",
    "sg:tags":[
        "style",
        "family",
        "lunch",
        "american",
        "brunch",
        "breakfast"
    ],
    "sg:website":"http://www.dennys.com",
    "wof:name":"Denny's",
    "wof:placetype":"venue"
},
  "geometry": {"coordinates":[-100.787519,46.808589],"type":"Point"}
}