{
  "type": "Feature",
  "properties": {
    "iso:country":"US",
    "sg:address":"15 4th Ave NE",
    "sg:city":"Minot",
    "sg:classifiers":[
        {
            "category":"Professional",
            "subcategory":"Detective & Security Services",
            "type":"Services"
        }
    ],
    "sg:phone":"+1 701 852 1562",
    "sg:postcode":"58703",
    "sg:province":"ND",
    "sg:tags":[
        "guard",
        "patrol"
    ],
    "wof:name":"J-N-T Security Svc",
    "wof:placetype":"venue"
},
  "geometry": {"coordinates":[-101.292192,48.240119],"type":"Point"}
}