{
  "type": "Feature",
  "properties": {
    "iso:country":"US",
    "sg:address":"206 1st Ave S",
    "sg:city":"Jamestown",
    "sg:classifiers":[
        {
            "category":"Utilities",
            "subcategory":"Mobile Phone",
            "type":"Services"
        }
    ],
    "sg:phone":"+1 701 252 4574",
    "sg:postcode":"58401",
    "sg:province":"ND",
    "sg:tags":[
        "telephone",
        "cellular"
    ],
    "wof:name":"Infinity Wireless Solutions",
    "wof:placetype":"venue"
},
  "geometry": {"coordinates":[-98.708534,46.907555],"type":"Point"}
}