{
  "type": "Feature",
  "properties": {
    "iso:country":"US",
    "sg:address":"603 3rd St",
    "sg:city":"Langdon",
    "sg:classifiers":[
        {
            "category":"Retail",
            "subcategory":"Car Wash",
            "type":"Services"
        }
    ],
    "sg:phone":"+1 701 256 3637",
    "sg:postcode":"58249",
    "sg:province":"ND",
    "sg:tags":[
        "carwash",
        "cleaning"
    ],
    "wof:name":"Hoffarth Steam Clean",
    "wof:placetype":"venue"
},
  "geometry": {"coordinates":[-98.368205,48.759126],"type":"Point"}
}