{
  "type": "Feature",
  "properties": {
    "iso:country":"US",
    "sg:address":"603 Main St",
    "sg:city":"Williston",
    "sg:classifiers":[
        {
            "category":"Travel",
            "subcategory":"Travel Agent",
            "type":"Entertainment"
        }
    ],
    "sg:phone":"+1 701 774 8366",
    "sg:postcode":"58801",
    "sg:province":"ND",
    "sg:tags":[
        "agency",
        "bureau"
    ],
    "sg:website":"www.gowithworldtravel.com",
    "wof:name":"Travel World",
    "wof:placetype":"venue"
},
  "geometry": {"coordinates":[-103.622411,48.149567],"type":"Point"}
}