{
  "type": "Feature",
  "properties": {
    "addr:full":"123 9th Ave E Langdon ND 58249",
    "addr:housenumber":"123",
    "addr:postcode":"58249",
    "addr:street":"9Th Ave E",
    "iso:country":"US",
    "sg:address":"123 9th Ave E",
    "sg:city":"Langdon",
    "sg:classifiers":[
        {
            "category":"Retail",
            "subcategory":"Repair Shop",
            "type":"Services"
        }
    ],
    "sg:phone":"+1 701 256 5400",
    "sg:postcode":"58249",
    "sg:province":"ND",
    "sg:tags":[
        "tractor"
    ],
    "wof:name":"Christianson Sales & Svc",
    "wof:placetype":"venue"
},
  "geometry": {"coordinates":[-98.364971,48.761251],"type":"Point"}
}