{
  "type": "Feature",
  "properties": {
    "iso:country":"US",
    "sg:address":"4489 State Hwy 41",
    "sg:city":"Velva",
    "sg:classifiers":[
        {
            "category":"Professional",
            "subcategory":"Management & Consulting",
            "type":"Services"
        },
        {
            "category":"Building & Trades",
            "subcategory":"Landscaping Services",
            "type":"Services"
        }
    ],
    "sg:phone":"+1 701 338 2589",
    "sg:postcode":"58790",
    "sg:province":"ND",
    "sg:tags":[
        "consultant",
        "business",
        "landscape"
    ],
    "wof:name":"Agro Tech Inc",
    "wof:placetype":"venue"
},
  "geometry": {"coordinates":[-100.92878899999999,48.064833],"type":"Point"}
}