{
  "type": "Feature",
  "properties": {
    "addr:full":"3429 Interstate Blvd S Fargo ND 58103",
    "addr:housenumber":"3429",
    "addr:postcode":"58103",
    "addr:street":"Interstate Blvd S",
    "iso:country":"US",
    "sg:address":"3429 Interstate Blvd S",
    "sg:city":"Fargo",
    "sg:classifiers":[
        {
            "category":"Wholesale",
            "subcategory":"Office Equipment",
            "type":"Manufacturing & Wholesale Goods"
        }
    ],
    "sg:phone":"+1 701 241 8504",
    "sg:postcode":"58103",
    "sg:province":"ND",
    "sg:tags":[
        "machine",
        "duplicating",
        "copying"
    ],
    "sg:website":"www.liberty.com",
    "wof:name":"Liberty Business Systems Inc",
    "wof:placetype":"venue"
},
  "geometry": {"coordinates":[-96.83687999999999,46.864472],"type":"Point"}
}