{
  "type": "Feature",
  "properties": {
    "iso:country":"US",
    "sg:address":"1309 1st Ave N",
    "sg:city":"Fargo",
    "sg:classifiers":[
        {
            "category":"Autos & Motor Vehicles",
            "subcategory":"Automobile Sales",
            "type":"Retail Goods"
        }
    ],
    "sg:phone":"+1 701 280 6979",
    "sg:postcode":"58102",
    "sg:province":"ND",
    "sg:tags":[
        "car",
        "dealer"
    ],
    "wof:name":"Northwest Imports",
    "wof:placetype":"venue"
},
  "geometry": {"coordinates":[-96.799373,46.877454],"type":"Point"}
}