{
  "type": "Feature",
  "properties": {
    "iso:country":"US",
    "sg:address":"230 1st St NW",
    "sg:city":"Lidgerwood",
    "sg:classifiers":[
        {
            "category":"Organizations",
            "subcategory":"Religious Organization",
            "type":"Services"
        }
    ],
    "sg:phone":"+1 701 538 4604",
    "sg:postcode":"58053",
    "sg:province":"ND",
    "sg:tags":[
        "church"
    ],
    "wof:name":"St Boniface Church/Hall",
    "wof:placetype":"venue"
},
  "geometry": {"coordinates":[-97.15521699999999,46.076713],"type":"Point"}
}