{
  "type": "Feature",
  "properties": {
    "addr:full":"620 17th St W Williston ND 58801",
    "addr:housenumber":"620",
    "addr:postcode":"58801",
    "addr:street":"17Th St W",
    "iso:country":"US",
    "sg:address":"620 17th St W",
    "sg:city":"Williston",
    "sg:classifiers":[
        {
            "category":"Shopping",
            "subcategory":"Computers & Home Electronics",
            "type":"Retail Goods"
        }
    ],
    "sg:phone":"+1 701 572 2828",
    "sg:postcode":"58801",
    "sg:province":"ND",
    "sg:tags":[
        "equipment",
        "electronic",
        "supply"
    ],
    "wof:name":"Trouba Telephone Svc",
    "wof:placetype":"venue"
},
  "geometry": {"coordinates":[-103.634218,48.160623],"type":"Point"}
}