{
  "type": "Feature",
  "properties": {
    "iso:country":"US",
    "sg:address":"397 15th St W",
    "sg:city":"Dickinson",
    "sg:classifiers":[
        {
            "category":"Cinema",
            "subcategory":"Movie Rental",
            "type":"Entertainment"
        }
    ],
    "sg:phone":"+1 701 225 4003",
    "sg:postcode":"58601",
    "sg:province":"ND",
    "sg:tags":[
        "equipment",
        "video",
        "disc",
        "leasing",
        "tape"
    ],
    "wof:name":"Total Entertainment Center",
    "wof:placetype":"venue"
},
  "geometry": {"coordinates":[-102.790481,46.898818],"type":"Point"}
}