{
  "type": "Feature",
  "properties": {
    "iso:country":"US",
    "sg:address":"3209 42nd Ave SW",
    "sg:city":"Fargo",
    "sg:classifiers":[
        {
            "category":"Organizations",
            "subcategory":"Professional Association",
            "type":"Services"
        }
    ],
    "sg:phone":"+1 701 239 8021",
    "sg:postcode":"58104",
    "sg:province":"ND",
    "sg:website":"www.americanheart.org",
    "wof:name":"American Heart Assn",
    "wof:placetype":"venue"
},
  "geometry": {"coordinates":[-96.83386900000001,46.815749],"type":"Point"}
}