{
  "type": "Feature",
  "properties": {
    "iso:country":"US",
    "sg:address":"4360 131st Ave SW",
    "sg:city":"Belfield",
    "sg:classifiers":[
        {
            "category":"Travel",
            "subcategory":"Hotels & Motels",
            "type":"Entertainment"
        }
    ],
    "sg:phone":"+1 701 724 6492",
    "sg:postcode":"58622",
    "sg:province":"ND",
    "sg:tags":[
        "cottage",
        "cabin"
    ],
    "wof:name":"Cottage Cabin Rental",
    "wof:placetype":"venue"
},
  "geometry": {"coordinates":[-103.210701,46.78764],"type":"Point"}
}