{
  "type": "Feature",
  "properties": {
    "iso:country":"US",
    "sg:address":"416 4th Ave N",
    "sg:city":"Cleveland",
    "sg:classifiers":[
        {
            "category":"Government",
            "subcategory":"Fire Station",
            "type":"Public Place"
        }
    ],
    "sg:phone":"+1 701 763 6230",
    "sg:postcode":"58424",
    "sg:province":"ND",
    "sg:tags":[
        "department"
    ],
    "wof:name":"Cleveland Rural Fire District",
    "wof:placetype":"venue"
},
  "geometry": {"coordinates":[-99.119545,46.890421],"type":"Point"}
}