{
  "type": "Feature",
  "properties": {
    "iso:country":"US",
    "sg:address":"905 5th St S",
    "sg:city":"Devils Lake",
    "sg:classifiers":[
        {
            "category":"Freight",
            "type":"Transportation"
        }
    ],
    "sg:phone":"+1 701 662 5935",
    "sg:postcode":"58301",
    "sg:province":"ND",
    "sg:tags":[
        "trucking"
    ],
    "wof:name":"Lewis Trucklines Inc",
    "wof:placetype":"venue"
},
  "geometry": {"coordinates":[-98.85141,48.104216],"type":"Point"}
}