{
  "type": "Feature",
  "properties": {
    "iso:country":"US",
    "sg:address":"902 Main Ave E",
    "sg:city":"West Fargo",
    "sg:classifiers":[
        {
            "category":"Wholesale",
            "subcategory":"Petroleum",
            "type":"Manufacturing & Wholesale Goods"
        }
    ],
    "sg:phone":"+1 701 282 3208",
    "sg:postcode":"58078",
    "sg:province":"ND",
    "sg:tags":[
        "pipe",
        "line",
        "company"
    ],
    "wof:name":"Williams Pipeline Co",
    "wof:placetype":"venue"
},
  "geometry": {"coordinates":[-96.881845,46.876671],"type":"Point"}
}