{
  "type": "Feature",
  "properties": {
    "addr:full":"921 US Hwy 281 Jamestown ND 58401",
    "addr:housenumber":"921",
    "addr:postcode":"58401",
    "addr:street":"Us Hwy 281",
    "iso:country":"US",
    "sg:address":"921 US Hwy 281",
    "sg:city":"Jamestown",
    "sg:classifiers":[
        {
            "category":"Building & Trades",
            "subcategory":"Construction",
            "type":"Services"
        }
    ],
    "sg:phone":"+1 701 252 2502",
    "sg:postcode":"58401",
    "sg:province":"ND",
    "sg:tags":[
        "project"
    ],
    "wof:name":"Jerry Iverson Construction",
    "wof:placetype":"venue"
},
  "geometry": {"coordinates":[-98.719551,46.917048],"type":"Point"}
}