{
  "type": "Feature",
  "properties": {
    "iso:country":"US",
    "sg:address":"8195 162nd Ave SE",
    "sg:city":"Barney",
    "sg:phone":"+1 701 439 2917",
    "sg:postcode":"58008",
    "sg:province":"ND",
    "sg:tags":[
        "beef",
        "farm",
        "corn",
        "crop",
        "field",
        "cattle",
        "feedlot"
    ],
    "wof:name":"Leslie G & Loreen M Mauch",
    "wof:placetype":"venue"
},
  "geometry": {"coordinates":[-97.010858,46.225975],"type":"Point"}
}