{
  "type": "Feature",
  "properties": {
    "iso:country":"US",
    "sg:address":"401 2nd Ave",
    "sg:city":"Rolette",
    "sg:classifiers":[
        {
            "category":"Personal",
            "type":"Services"
        }
    ],
    "sg:phone":"+1 701 246 3737",
    "sg:postcode":"58366",
    "sg:province":"ND",
    "sg:tags":[
        "therapist",
        "massage"
    ],
    "wof:name":"Rolette Therapeutic Massage",
    "wof:placetype":"venue"
},
  "geometry": {"coordinates":[-99.846486,48.661919],"type":"Point"}
}