{
  "type": "Feature",
  "properties": {
    "iso:country":"US",
    "sg:address":"1406 2nd St NW",
    "sg:city":"Mandan",
    "sg:classifiers":[
        {
            "category":"Professional",
            "type":"Services"
        }
    ],
    "sg:phone":"+1 701 667 2131",
    "sg:postcode":"58554",
    "sg:province":"ND",
    "sg:tags":[
        "establishment"
    ],
    "sg:website":"www.tc4hope.org",
    "wof:name":"Northern Plains Teen Challenge",
    "wof:placetype":"venue"
},
  "geometry": {"coordinates":[-100.911664,46.82695],"type":"Point"}
}