{
  "type": "Feature",
  "properties": {
    "addr:full":"1124 23rd St NW Minot ND 58703",
    "addr:housenumber":"1124",
    "addr:postcode":"58703",
    "addr:street":"23Rd St Nw",
    "iso:country":"US",
    "sg:address":"1124 23rd St NW",
    "sg:city":"Minot",
    "sg:classifiers":[
        {
            "category":"Building & Trades",
            "subcategory":"Equipment Rental",
            "type":"Services"
        }
    ],
    "sg:phone":"+1 701 240 7329",
    "sg:postcode":"58703",
    "sg:province":"ND",
    "wof:name":"Alanas Storks",
    "wof:placetype":"venue"
},
  "geometry": {"coordinates":[-101.328491,48.249162],"type":"Point"}
}