{
  "type": "Feature",
  "properties": {
    "iso:country":"US",
    "sg:address":"7085 108th St NW",
    "sg:city":"Northgate",
    "sg:classifiers":[
        {
            "category":"Freight",
            "type":"Transportation"
        }
    ],
    "sg:phone":"+1 701 596 3288",
    "sg:postcode":"58737",
    "sg:province":"ND",
    "sg:tags":[
        "grain",
        "elevator"
    ],
    "wof:name":"General Mills Operations",
    "wof:placetype":"venue"
},
  "geometry": {"coordinates":[-102.258402,48.981174],"type":"Point"}
}