{
  "type": "Feature",
  "properties": {
    "addr:full":"1929 N Washington St Bismarck ND 58501",
    "addr:housenumber":"1929",
    "addr:postcode":"58501",
    "addr:street":"N Washington St",
    "iso:country":"US",
    "sg:address":"1929 N Washington St",
    "sg:city":"Bismarck",
    "sg:classifiers":[
        {
            "category":"Health Services",
            "subcategory":"Doctor",
            "type":"Services"
        }
    ],
    "sg:phone":"+1 701 222 8394",
    "sg:postcode":"58501",
    "sg:province":"ND",
    "sg:tags":[
        "physician",
        "surgeon"
    ],
    "wof:name":"Gruver Clinic",
    "wof:placetype":"venue"
},
  "geometry": {"coordinates":[-100.794,46.827171],"type":"Point"}
}