{
  "type": "Feature",
  "properties": {
    "iso:country":"US",
    "sg:address":"1120 Tacoma Ave",
    "sg:city":"Bismarck",
    "sg:classifiers":[
        {
            "category":"Food & Beverages",
            "subcategory":"Groceries & Convenience Stores",
            "type":"Retail Goods"
        }
    ],
    "sg:phone":"+1 701 255 2251",
    "sg:postcode":"58504",
    "sg:province":"ND",
    "wof:name":"Home Run C-Store",
    "wof:placetype":"venue"
},
  "geometry": {"coordinates":[-100.77688000000001,46.782897],"type":"Point"}
}