{
  "type": "Feature",
  "properties": {
    "iso:country":"US",
    "sg:address":"110 4th Ave SE",
    "sg:city":"Gwinner",
    "sg:classifiers":[
        {
            "category":"Shopping",
            "subcategory":"Jewelry",
            "type":"Retail Goods"
        }
    ],
    "sg:phone":"+1 701 678 2285",
    "sg:postcode":"58040",
    "sg:province":"ND",
    "sg:tags":[
        "clocks"
    ],
    "wof:name":"Maro Memorabilia Inc",
    "wof:placetype":"venue"
},
  "geometry": {"coordinates":[-97.65962,46.221432],"type":"Point"}
}