{
  "type": "Feature",
  "properties": {
    "addr:full":"3301 15th St S Fargo ND 58104",
    "addr:housenumber":"3301",
    "addr:postcode":"58104",
    "addr:street":"15Th St S",
    "iso:country":"US",
    "sg:address":"3301 15th St S",
    "sg:city":"Fargo",
    "sg:classifiers":[
        {
            "category":"Manufacturing",
            "subcategory":"Retail Goods",
            "type":"Manufacturing & Wholesale Goods"
        }
    ],
    "sg:phone":"+1 701 280 9292",
    "sg:postcode":"58104",
    "sg:province":"ND",
    "sg:tags":[
        "machine",
        "product",
        "vending",
        "mfg"
    ],
    "wof:name":"Cei",
    "wof:placetype":"venue"
},
  "geometry": {"coordinates":[-96.80334499999999,46.829431],"type":"Point"}
}