{
  "type": "Feature",
  "properties": {
    "iso:country":"US",
    "sg:address":"500 17th St SW",
    "sg:city":"Jamestown",
    "sg:classifiers":[
        {
            "category":"Autos & Motor Vehicles",
            "subcategory":"Automobile Sales",
            "type":"Retail Goods"
        }
    ],
    "sg:phone":"+1 701 252 4690",
    "sg:postcode":"58401",
    "sg:province":"ND",
    "sg:tags":[
        "car",
        "dealer"
    ],
    "wof:name":"Lloyds Motors",
    "wof:placetype":"venue"
},
  "geometry": {"coordinates":[-98.71539900000001,46.891969],"type":"Point"}
}