{
  "type": "Feature",
  "properties": {
    "iso:country":"US",
    "sg:address":"1226 Park Ave",
    "sg:city":"Bismarck",
    "sg:classifiers":[
        {
            "category":"Retail",
            "subcategory":"Auto Repair",
            "type":"Services"
        }
    ],
    "sg:phone":"+1 701 224 1426",
    "sg:postcode":"58504",
    "sg:province":"ND",
    "sg:tags":[
        "repairing",
        "automobile",
        "general"
    ],
    "wof:name":"Northland Performance & 4 W D",
    "wof:placetype":"venue"
},
  "geometry": {"coordinates":[-100.772024,46.790475],"type":"Point"}
}