{
  "type": "Feature",
  "properties": {
    "addr:full":"1244 Basin Ave Bismarck ND 58504",
    "addr:housenumber":"1244",
    "addr:postcode":"58504",
    "addr:street":"Basin Ave",
    "iso:country":"US",
    "sg:address":"1244 Basin Ave",
    "sg:city":"Bismarck",
    "sg:classifiers":[
        {
            "category":"Wholesale",
            "subcategory":"Tobacco Products",
            "type":"Manufacturing & Wholesale Goods"
        },
        {
            "category":"Wholesale",
            "subcategory":"Non-durable Goods",
            "type":"Manufacturing & Wholesale Goods"
        }
    ],
    "sg:phone":"+1 701 258 1278",
    "sg:postcode":"58504",
    "sg:province":"ND",
    "sg:tags":[
        "confectionery"
    ],
    "wof:name":"Wholesale Supply Company Inc",
    "wof:placetype":"venue"
},
  "geometry": {"coordinates":[-100.76956800000001,46.784281],"type":"Point"}
}