{
  "type": "Feature",
  "properties": {
    "iso:country":"US",
    "sg:address":"3065 118th Ave SE",
    "sg:city":"Valley City",
    "sg:classifiers":[
        {
            "category":"Banks & Credit Unions",
            "subcategory":"Financial Services",
            "type":"Services"
        }
    ],
    "sg:phone":"+1 701 845 4082",
    "sg:postcode":"58072",
    "sg:province":"ND",
    "sg:tags":[
        "trust",
        "management"
    ],
    "wof:name":"J C S Trust",
    "wof:placetype":"venue"
},
  "geometry": {"coordinates":[-97.975652,46.969197],"type":"Point"}
}