{
  "type": "Feature",
  "properties": {
    "addr:full":"110 13th Ave NE Mandan ND 58554",
    "addr:housenumber":"110",
    "addr:postcode":"58554",
    "addr:street":"13Th Ave Ne",
    "iso:country":"US",
    "sg:address":"110 13th Ave NE",
    "sg:city":"Mandan",
    "sg:classifiers":[
        {
            "category":"Autos & Motor Vehicles",
            "subcategory":"Auto Supplies",
            "type":"Retail Goods"
        }
    ],
    "sg:phone":"+1 701 663 9848",
    "sg:postcode":"58554",
    "sg:province":"ND",
    "sg:tags":[
        "automobile",
        "parts"
    ],
    "wof:name":"Carquest Auto Parts",
    "wof:placetype":"venue"
},
  "geometry": {"coordinates":[-100.87200900000001,46.829802],"type":"Point"}
}