{
  "type": "Feature",
  "properties": {
    "iso:country":"US",
    "sg:address":"2527 E Ave B",
    "sg:city":"Bismarck",
    "sg:classifiers":[
        {
            "category":"Communications",
            "subcategory":"Film & Video Production",
            "type":"Services"
        }
    ],
    "sg:phone":"+1 701 258 2674",
    "sg:postcode":"58501",
    "sg:province":"ND",
    "sg:tags":[
        "motion",
        "electronic"
    ],
    "wof:name":"Big Red Button Audio Recording",
    "wof:placetype":"venue"
},
  "geometry": {"coordinates":[-100.752487,46.81007],"type":"Point"}
}