{
  "type": "Feature",
  "properties": {
    "iso:country":"US",
    "sg:address":"111 1st St NW",
    "sg:city":"Tioga",
    "sg:classifiers":[
        {
            "category":"Retail",
            "subcategory":"Repair Shop",
            "type":"Services"
        }
    ],
    "sg:phone":"+1 701 965 6038",
    "sg:postcode":"58852",
    "sg:province":"ND",
    "sg:tags":[
        "welding"
    ],
    "wof:name":"Wayne's Welding & Repair",
    "wof:placetype":"venue"
},
  "geometry": {"coordinates":[-102.940907,48.396552],"type":"Point"}
}