{
  "type": "Feature",
  "properties": {
    "iso:country":"US",
    "sg:address":"2219 E Main Ave",
    "sg:city":"Bismarck",
    "sg:classifiers":[
        {
            "category":"Manufacturing",
            "subcategory":"Printing",
            "type":"Manufacturing & Wholesale Goods"
        }
    ],
    "sg:phone":"+1 701 255 1197",
    "sg:postcode":"58501",
    "sg:province":"ND",
    "sg:tags":[
        "publisher"
    ],
    "sg:website":"www.vintageguitar.com",
    "wof:name":"Vintage Guitar Magazine",
    "wof:placetype":"venue"
},
  "geometry": {"coordinates":[-100.75870399999999,46.805064],"type":"Point"}
}