{
  "type": "Feature",
  "properties": {
    "iso:country":"US",
    "sg:address":"200 Shady Ln",
    "sg:city":"Mandan",
    "sg:classifiers":[
        {
            "category":"Organizations",
            "subcategory":"Religious Organization",
            "type":"Services"
        }
    ],
    "sg:phone":"+1 701 663 0303",
    "sg:postcode":"58554",
    "sg:province":"ND",
    "wof:name":"Assembly of God",
    "wof:placetype":"venue"
},
  "geometry": {"coordinates":[-100.864,46.832038],"type":"Point"}
}