{
  "type": "Feature",
  "properties": {
    "iso:country":"US",
    "sg:address":"1012 3rd St",
    "sg:city":"Langdon",
    "sg:phone":"+1 701 256 5317",
    "sg:postcode":"58249",
    "sg:province":"ND",
    "sg:tags":[
        "farm",
        "wheat",
        "grain",
        "cash"
    ],
    "wof:name":"Thomas Kram",
    "wof:placetype":"venue"
},
  "geometry": {"coordinates":[-98.368335,48.763053],"type":"Point"}
}