{
  "type": "Feature",
  "properties": {
    "iso:country":"US",
    "sg:address":"857 Main Ave E",
    "sg:city":"West Fargo",
    "sg:classifiers":[
        {
            "category":"Building & Trades",
            "subcategory":"Construction",
            "type":"Services"
        }
    ],
    "sg:phone":"+1 701 282 2754",
    "sg:postcode":"58078",
    "sg:province":"ND",
    "sg:tags":[
        "sandblasting"
    ],
    "wof:name":"Porta-Blast",
    "wof:placetype":"venue"
},
  "geometry": {"coordinates":[-96.88383899999999,46.87655],"type":"Point"}
}