{
  "type": "Feature",
  "properties": {
    "addr:full":"657 2nd Ave N Fargo ND 58102",
    "addr:housenumber":"657",
    "addr:postcode":"58102",
    "addr:street":"2Nd Ave N",
    "iso:country":"US",
    "sg:address":"657 2nd Ave N",
    "sg:city":"Fargo",
    "sg:classifiers":[
        {
            "category":"Banks & Credit Unions",
            "subcategory":"Bank",
            "type":"Services"
        }
    ],
    "sg:phone":"+1 701 235 1359",
    "sg:postcode":"58102",
    "sg:province":"ND",
    "wof:name":"FFE Federal Credit Union",
    "wof:placetype":"venue"
},
  "geometry": {"coordinates":[-96.790896,46.878283],"type":"Point"}
}