{
  "type": "Feature",
  "properties": {
    "iso:country":"US",
    "sg:address":"17 2nd Ave SE",
    "sg:city":"Minot",
    "sg:classifiers":[
        {
            "category":"Shopping",
            "subcategory":"Used Merchandise",
            "type":"Retail Goods"
        }
    ],
    "sg:phone":"+1 701 858 1926",
    "sg:postcode":"58701",
    "sg:province":"ND",
    "sg:tags":[
        "antique"
    ],
    "wof:name":"That's It",
    "wof:placetype":"venue"
},
  "geometry": {"coordinates":[-101.292862,48.2345],"type":"Point"}
}