{
  "type": "Feature",
  "properties": {
    "iso:country":"US",
    "sg:address":"14023 79th St SE",
    "sg:city":"Milnor",
    "sg:classifiers":[
        {
            "category":"Real Estate",
            "subcategory":"Real Estate Operator",
            "type":"Services"
        }
    ],
    "sg:phone":"+1 701 427 9279",
    "sg:postcode":"58060",
    "sg:province":"ND",
    "sg:tags":[
        "property",
        "lessor"
    ],
    "wof:name":"Gary Wallin",
    "wof:placetype":"venue"
},
  "geometry": {"coordinates":[-97.463326,46.268282],"type":"Point"}
}